Workbook

Sheet Cover
B3: ASM International NV
B4: Equity Valuation Report
B6: AC444 Valuation and Security Analysis
B7: London School of Economics
B9: Ticker: | C9: ENXTAM:ASM
B10: Currency: | C10: EUR (Thousands)
B11: Data Period: | C11: FY 2019 - FY 2024
B12: Forecast Period: | C12: FY 2025E - FY 2030E
B13: Peers: | C13: AIXTRON SE, Applied Materials, Lam Research
B15: Table of Contents
B16: 1. Cover | C16: Title page and overview
B17: 2. Input ASM | C17: Raw financial data - ASM International
B18: 3. Input ASM (Reported) | C18: As-reported financial data - ASM International
B19: 4. Input AIXTRON | C19: Raw financial data - AIXTRON SE
B20: 5. Input AMAT | C20: Raw financial data - Applied Materials
B21: 6. Input LRCX | C21: Raw financial data - Lam Research
B22: 7. Standardized ASM | C22: Standardized financial statements - ASM
B23: 8. Standardized AIXTRON | C23: Standardized financial statements - AIXTRON
B24: 9. Standardized AMAT | C24: Standardized financial statements - Applied Materials
B25: 10. Standardized LRCX | C25: Standardized financial statements - Lam Research
B26: 11. Adjustments | C26: Adjustments and adjusted financial statements
B27: 12. Ratio Analysis | C27: Key financial ratios and analysis
... B32: 17. Football Field | C32: Valuation range summary
B34: Generated: 26 March 2026

Sheet Input ASM
A2: ASM International NV | Income Statement
A3: ENXTAM:ASM (MI KEY: 4231951; SPCIQ KEY: 322899)
A5: Source: Recommended
A6: Period Category: Fiscal
A7: Period Type: Years
A8: Reporting Basis: Current/Restated
A9: Sort Order: Latest on Right
A10: Currency: Euro (EUR)
A11: Magnitude: Thousands (K)
A13: Recommended: S&P Capital IQ - Standard | B13: 2019 FY | C13: 2020 FY | D13: 2021 FY | E13: 2022 FY | F13: 2023 FY | G13: 2024 FY
B14: Current/Restated | C14: Current/Restated | D14: Current/Restated | E14: Current/Restated | F14: Current/Restated | G14: Current/Restated
A15: Period Ended | B15: 43830 | C15: 44196 | D15: 44561 | E15: 44926 | F15: 45291 | G15: 45657
A16: Financial Filing Date | B16: 44260 | C16: 44623 | D16: 44987 | E16: 45352 | F16: 45722 | G16: 45722
A17: Spot Exchange Rate | B17: 1 | C17: 1 | D17: 1 | E17: 1 | F17: 1 | G17: 1
A18: Average Exchange Rate | B18: 1 | C18: 1 | D18: 1 | E18: 1 | F18: 1 | G18: 1
A20: (€000)
A21: Revenue | B21: 1283860 | C21: 1328122 | D21: 1729911 | E21: 2410927 | F21: 2634331 | G21: 2932724
A22: Total Revenue | B22: 1283860 | C22: 1328122 | D22: 1729911 | E22: 2410927 | F22: 2634331 | G22: 2932724
A23: Cost Of Goods Sold | B23: 645396 | C23: 704553 | D23: 901780 | E23: 1268046 | F23: 1362635 | G23: 1451351
A24: Gross Profit | B24: 638464 | C24: 623569 | D24: 828131 | E24: 1142881 | F24: 1271696 | G24: 1481373
A26: Selling General & Admin Exp. | B26: 148929 | C26: 157424 | D26: 189547 | E26: 276620 | F26: 308727 | G26: 316811
A27: R & D Exp. | B27: 106091 | C27: 128876 | D27: 149230 | E27: 233860 | F27: 306822 | G27: 369370
A28: Amort. of Goodwill and Intangibles | B28: 13788 | C28: 12863 | D28: 12213 | E28: 13642 | F28: 3666 | G28: 378
A29: Other Operating Expense | B29: NA | C29: NA | D29: NA | E29: NA | F29: -254 | G29: -355
A30: Other Operating Exp., Total | B30: 268808 | C30: 299163 | D30: 350990 | E30: 524122 | F30: 618961 | G30: 686204
A31: Operating Income | B31: 369656 | C31: 324406 | D31: 477141 | E31: 618759 | F31: 652735 | G31: 795169
A33: Interest Expense | B33: -1766 | C33: -2008 | D33: -2012 | E33: -1523 | F33: -3945 | G33: -1884
A34: Interest and Invest. Income | B34: 1639 | C34: 141 | D34: 23 | E34: 2246 | F34: 14826 | G34: 21658
A35: Net Interest Exp. | B35: -127 | C35: -1867 | D35: -1989 | E35: 723 | F35: 10881 | G35: 19774
A36: Income from Affiliates | B36: 18035 | C36: 44813 | D36: 86595 | E36: 78413 | F36: 21206 | G36: 10021
A37: Currency Exchange Gains | B37: -146 | C37: -23157 | D37: 33473 | E37: 25011 | F37: -21375 | G37: 45048
A38: EBT Excl Unusual Items | B38: 387418 | C38: 344195 | D38: 595220 | E38: 722906 | F38: 663447 | G38: 870012
A39: Gain (Loss) On Sale Of Invest. | B39: NA | C39: NA | D39: NA | E39: -215389 | F39: 215389 | G39: NA
A40: Gain (Loss) On Sale Of Assets | B40: NA | C40: NA | D40: 4071 | E40: 40 | F40: -185 | G40: 7036
A41: Asset Writedown | B41: -4755 | C41: -10126 | D41: -1967 | E41: -6 | F41: -2475 | G41: -448
A42: Other Unusual Items | B42: NA | C42: NA | D42: NA | E42: -2575 | F42: -9655 | G42: -8698
A43: EBT Incl. Unusual Items | B43: 382663 | C43: 334069 | D43: 597324 | E43: 504976 | F43: 866521 | G43: 867902
A45: Income Tax Expense | B45: 53650 | C45: 48673 | D45: 102615 | E45: 115863 | F45: 114448 | G45: 182168
A46: Earnings from Cont. Ops. | B46: 329013 | C46: 285396 | D46: 494709 | E46: 389113 | F46: 752073 | G46: 685734
A47: Net Income to Company | B47: 329013 | C47: 285396 | D47: 494709 | E47: 389113 | F47: 752073 | G47: 685734
A48: Net Income | B48: 329013 | C48: 285396 | D48: 494709 | E48: 389113 | F48: 752073 | G48: 685734
A49: NI to Common Incl Extra Items | B49: 329013 | C49: 285396 | D49: 494709 | E49: 389113 | F49: 752073 | G49: 685734
A50: NI to Common Excl. Extra Items | B50: 329013 | C50: 285396 | D50: 494709 | E50: 389113 | F50: 752073 | G50: 685734
A51: Per Share Items (€)
A52: Basic EPS | B52: 6.658 | C52: 5.835 | D52: 10.17 | E52: 7.97 | F52: 15.259 | G52: 13.948
A53: Basic EPS Excl. Extra Items | B53: 6.658 | C53: 5.835 | D53: 10.17 | E53: 7.97 | F53: 15.259 | G53: 13.948
A54: Weighted Avg. Basic Shares Out. (actual) | B54: 49418000 | C54: 48907000 | D54: 48645000 | E54: 48820000 | F54: 49286000 | G54: 49165000
A55: Diluted EPS Incl. Extra Items | B55: 6.58 | C55: 5.78 | D55: 10.11 | E55: 7.93 | F55: 15.18 | G55: 13.89
A56: Diluted EPS Excl. Extra Items | B56: 6.58 | C56: 5.78 | D56: 10.11 | E56: 7.93 | F56: 15.18 | G56: 13.89
A57: Weighted Avg. Diluted Shares Out. (actual) | B57: 49999000 | C57: 49359000 | D57: 48909000 | E57: 49097000 | F57: 49555000 | G57: 49386000
A58: Normalized Basic EPS | B58: 4.9 | C58: 4.399 | D58: 7.647 | E58: 9.255 | F58: 8.413 | G58: 11.06
A59: Normalized Diluted EPS | B59: 4.843 | C59: 4.358 | D59: 7.606 | E59: 9.203 | F59: 8.368 | G59: 11.01
A60: Dividends per Share | B60: 1.5 | C60: 2 | D60: 2.5 | E60: 2.5 | F60: 2.75 | G60: 3
A61: Payout Ratio (%) | B61: 30.181 | C61: 34.579 | D61: 19.586 | E61: 31.263 | F61: 16.406 | G61: 19.758
A62: Shares per Depositary Receipt (actual) | B62: 1 | C62: 1 | D62: 1 | E62: 1 | F62: 1 | G62: 1
A63: Supplemental Items (€000)
A64: EBITDA | B64: 429559 | C64: 383511 | D64: 535957 | E64: 694618 | F64: 769512 | G64: 907256
A65: EBITA | B65: 384114 | C65: 337554 | D65: 477151 | E65: 624810 | F65: 689323 | G65: 814102
A66: EBIT | B66: 369656 | C66: 324406 | D66: 477141 | E66: 618759 | F66: 652735 | G66: 795169
A67: EBITDAR | B67: 429904 | C67: 383781 | D67: 536021 | E67: 694869 | F67: 770012 | G67: 907890
A68: Effective Tax Rate (%) | B68: 14.02 | C68: 14.57 | D68: 17.179 | E68: 22.944 | F68: 13.208 | G68: 20.989
A69: Current Domestic Taxes | B69: 28409 | C69: 25462 | D69: 72032 | E69: 78738 | F69: NA | G69: NA
A70: Current Foreign Taxes | B70: 9011 | C70: 17754 | D70: 7718 | E70: 36430 | F70: NA | G70: NA
A71: Total Current Taxes | B71: 37420 | C71: 43216 | D71: 79750 | E71: 115168 | F71: 85548 | G71: 172198
A72: Deferred Domestic Taxes | B72: 6860 | C72: 3348 | D72: 5948 | E72: 1875 | F72: NA | G72: NA
A73: Deferred Foreign Taxes | B73: 9370 | C73: 2109 | D73: 16917 | E73: -1180 | F73: NA | G73: NA
A74: Total Deferred Taxes | B74: 16230 | C74: 5457 | D74: 22865 | E74: 695 | F74: 28900 | G74: 9970
A75: Normalized Net Income | B75: 242136.25 | C75: 215121.88 | D75: 372012.5 | E75: 451816.25 | F75: 414654.38 | G75: 543757.5
A76: Interest on Long-term Debt | B76: 586 | C76: 561 | D76: 523 | E76: 603 | F76: 705 | G76: 800
A77: Non-Cash Pension Expense | B77: -4 | C77: -3 | D77: -10 | E77: NA | F77: NA | G77: NA
A78: Supplemental Operating Expense Items (€000)
A79: R&D Expense | B79: 110895 | C79: 139029 | D79: 151197 | E79: 233866 | F79: 309297 | G79: 369818
A80: Net Rental Expense, Total | B80: 345 | C80: 270 | D80: 64 | E80: 251 | F80: 500 | G80: 634
A81: Imputed Oper. Lease Interest Exp. | B81: NA | C81: 206.33 | D81: 48.221 | E81: 118.57 | F81: 511.656 | G81: 277.702
A82: Imputed Oper. Lease Depreciation | B82: NA | C82: 63.67 | D82: 15.779 | E82: 132.43 | F82: -11.656 | G82: 356.298
A83: Stock-Based Comp., Unallocated | B83: 10538 | C83: 12792 | D83: 17242 | E83: 29877 | F83: 37308 | G83: 41576
A84: Stock-Based Comp., Total | B84: 10538 | C84: 12792 | D84: 17242 | E84: 29877 | F84: 37308 | G84: 41576
A85: CIQ Restatement Type Code | B85: NC | C85: NC | D85: NC | E85: RC | F85: NC | G85: O
A86: CIQ Calculation Type Code | B86: REP | C86: REP | D86: REP | E86: REP | F86: REP | G86: REP
A87: Options Outstanding
A88: Options Out. at the Begin of Period, Common Stock | B88: 451170 | C88: NA | D88: NA | E88: 18249 | F88: NA | G88: NA
A89: Options Exercised During the Period, Common Stock | B89: 313531 | C89: NA | D89: 123521 | E89: NA | F89: NA | G89: NA
A90: Options Cancelled During the Period, Common Stock | B90: 10387 | C90: NA | D90: NA | E90: NA | F90: NA | G90: NA
A91: Options Out. at the End of Period, Common Stock | B91: 127252 | C91: NA | D91: NA | E91: 18249 | F91: NA | G91: NA
A92: Options Wtd Avg Strike Price of Outstd, Comm Stock (€) | B92: 21.79 | C92: NA | D92: NA | E92: NA | F92: NA | G92: NA
A93: Options Outstanding - All Classes
A94: Options Out. at the Beginning of the Period, Total | B94: 451170 | C94: NA | D94: NA | E94: 18249 | F94: NA | G94: NA
A95: Options Exercised During the Period, Total | B95: 313531 | C95: NA | D95: 123521 | E95: NA | F95: NA | G95: NA
A96: Options Cancelled During the Period, Total | B96: 10387 | C96: NA | D96: NA | E96: NA | F96: NA | G96: NA
A97: Options Out. at the End of the Period, Total | B97: 127252 | C97: NA | D97: NA | E97: 18249 | F97: NA | G97: NA
A98: Stock Based Compensation (€000)
A99: Stock Based Comp. Exp., Before Tax | B99: 10538 | C99: 12792 | D99: 17242 | E99: 29877 | F99: 37308 | G99: 41576
A102: Recommended: S&P Capital IQ - Standard | B102: 2019 FY | C102: 2020 FY | D102: 2021 FY | E102: 2022 FY | F102: 2023 FY | G102: 2024 FY
B103: Current/Restated | C103: Current/Restated | D103: Current/Restated | E103: Current/Restated | F103: Current/Restated | G103: Current/Restated
A104: Period Ended | B104: 43830 | C104: 44196 | D104: 44561 | E104: 44926 | F104: 45291 | G104: 45657
A105: Financial Filing Date | B105: 44260 | C105: 44623 | D105: 44987 | E105: 45352 | F105: 45722 | G105: 45722
A106: Spot Exchange Rate | B106: 1 | C106: 1 | D106: 1 | E106: 1 | F106: 1 | G106: 1
A107: Average Exchange Rate | B107: 1 | C107: 1 | D107: 1 | E107: 1 | F107: 1 | G107: 1
A109: Operating Activities (€000)
A110: Net Income - CF | B110: 329013 | C110: 285396 | D110: 494709 | E110: 389113 | F110: 752073 | G110: 685734
...

Sheet Input ASM (Reported)
A2: ASM International NV | Income Statement (As Reported)
A3: ENXTAM: ASM (MI KEY: 4231951; SPCIQ KEY: 322899)
A5: Source: Recommended
A6: Period Category: Fiscal
A7: Period Type: Years
A8: Sort Order: Latest on Right
A9: Currency: Euro
A12: Recommended: S&P Capital IQ - Standard | B12: 2019 FY | C12: 2020 FY | D12: 2021 FY | E12: 2022 FY | F12: 2023 FY | G12: 2024 FY
A13: Period Ended | B13: 43830 | C13: 44196 | D13: 44561 | E13: 44926 | F13: 45291 | G13: 45657
A14: Currency | B14: EUR | C14: EUR | D14: EUR | E14: EUR | F14: EUR | G14: EUR
A15: Units | B15: Thousands | C15: Thousands | D15: Thousands | E15: Thousands | F15: Thousands | G15: Thousands
A16: Revenues
A17: Revenues | B17: 1283860 | C17: 1328122 | D17: 1729911 | E17: 2410927 | F17: 2634331 | G17: 2932724
A18: Expenses
A19: Cost of Sales | B19: -645396 | C19: -704553 | D19: -901780 | E19: -1268046 | F19: -1362635 | G19: -1451351
A20: Selling, General and Administrative | B20: -148929 | C20: -157424 | D20: -189547 | E20: -276620 | F20: -308727 | G20: -316811
A21: Research and Development | B21: -110846 | C21: -139002 | D21: -151197 | E21: -233866 | F21: -309297 | G21: -369818
A22: Other Income | B22: NA | C22: NA | D22: 4071 | E22: 40 | F22: 69 | G22: 7391
A23: Gain/loss from Sale of Investments | B23: NA | C23: NA | D23: NA | E23: -215389 | F23: 215389 | G23: NA
A24: Currency Translation Gain(Loss) | B24: -146 | C24: -23157 | D24: 33473 | E24: 25011 | F24: -21375 | G24: 45048
A25: Finance Income | B25: 1639 | C25: 141 | D25: 23 | E25: 2246 | F25: 14826 | G25: 21658
A26: Finance Expenses | B26: -1766 | C26: -2008 | D26: -2012 | E26: -4098 | F26: -13600 | G26: -10582
A27: Share in Income of Investments and Associates | B27: 4247 | C27: 31950 | D27: 74382 | E27: 64771 | F27: 17540 | G27: 9643
A28: Earnings before Taxes | B28: 382663 | C28: 334069 | D28: 597324 | E28: 504976 | F28: 866521 | G28: 867902
A29: Taxes and Other Expenses
A30: Provision for Income Tax | B30: -53650 | C30: -48673 | D30: -102615 | E30: -115863 | F30: -114448 | G30: -182168
A31: Net Income (Loss) | B31: 329013 | C31: 285396 | D31: 494709 | E31: 389113 | F31: 752073 | G31: 685734
A32: Supplementary Info
A33: Gross Profit/loss | B33: 638464 | C33: 623569 | D33: 828131 | E33: 1142881 | F33: 1271696 | G33: 1481373
A34: Operating Income (Loss) | B34: 378689 | C34: 327143 | D34: 491458 | E34: 632435 | F34: 653741 | G34: 802135
A35: Basic EPS - Continuing Operations | B35: 6.66 | C35: 5.84 | D35: 10.17 | E35: 7.97 | F35: 15.26 | G35: 13.95
A36: Diluted EPS - Continuing Operations | B36: 6.58 | C36: 5.78 | D36: 10.11 | E36: 7.93 | F36: 15.18 | G36: 13.89
A39: Recommended: S&P Capital IQ - Standard | B39: 2019 FY | C39: 2020 FY | D39: 2021 FY | E39: 2022 FY | F39: 2023 FY | G39: 2024 FY
A40: Period Ended | B40: 43830 | C40: 44196 | D40: 44561 | E40: 44926 | F40: 45291 | G40: 45657
A41: Currency | B41: EUR | C41: EUR | D41: EUR | E41: EUR | F41: EUR | G41: EUR
A42: Units | B42: Thousands | C42: Thousands | D42: Thousands | E42: Thousands | F42: Thousands | G42: Thousands
A43: Operating Activities
A44: Net Income | B44: 329013 | C44: 285396 | D44: 494709 | E44: 389113 | F44: 752073 | G44: 685734
A45: Depreciation, amortization and Impairment | B45: 78321 | C45: 89029 | D45: 95580 | E45: 122434 | F45: 180896 | G45: 195800
A46: Net Gain/loss on Sale of Property, Plant & Equipment | B46: NA | C46: NA | D46: -4071 | E46: -40 | F46: 185 | G46: -7036
A47: Gain/loss from Sale of Investments | B47: NA | C47: NA | D47: NA | E47: 215389 | F47: NA | G47: NA
A48: Impairment (reversal of impairment) of investments in associates, net | B48: NA | C48: NA | D48: NA | E48: NA | F48: -215389 | G48: NA
A49: Changes in Evaluation Tools At Customers | B49: NA | C49: -39710 | D49: -7980 | E49: -20516 | F49: -32218 | G49: -47080
A50: Share Based Compensation | B50: 10538 | C50: 12792 | D50: 17242 | E50: 29877 | F50: 37308 | G50: 41576
A51: Income Tax | B51: 53650 | C51: 48673 | D51: 102615 | E51: 115863 | F51: 114448 | G51: 182168
A52: Income tax paid | B52: -6186 | C52: -8055 | D52: -151623 | E52: -90481 | F52: -118766 | G52: -97563
A53: Other Assets | B53: -24280 | C53: NA | D53: NA | E53: NA | F53: NA | G53: NA
A54: Non Cash Interest | B54: 593 | C54: NA | D54: NA | E54: NA | F54: NA | G54: NA
A55: Net Finance Income/(costs) | B55: NA | C55: 11975 | D55: -23510 | E55: 3886 | F55: -9466 | G55: -24759
A56: Non Cash Costs | B56: 4884 | C56: NA | D56: NA | E56: NA | F56: NA | G56: NA
A57: Share in Income of Investments in Associates | B57: -4247 | C57: -31950 | D57: -74382 | E57: -64771 | F57: -17539 | G57: -9643
A58: Evaluation Tools | B58: -13670 | C58: NA | D58: NA | E58: NA | F58: NA | G58: NA
A59: Changes in Employee Benefits Pension Plans | B59: NA | C59: -407 | D59: -339 | E59: 198 | F59: 98 | G59: -11
A60: Accounts Receivable | B60: -23937 | C60: -93000 | D60: -154030 | E60: -125068 | F60: 67660 | G60: -294635
A61: Contract Assets and Liabilities | B61: NA | C61: NA | D61: NA | E61: 131178 | F61: 21485 | G61: 184598
A62: Inventories | B62: 3058 | C62: 498 | D62: -39148 | E62: -276914 | F62: -3537 | G62: -31961
A63: Accounts Payable, Accrued Expenses and Other Payables | B63: 81134 | C63: -12696 | D63: 103087 | E63: 120324 | F63: -9314 | G63: 112055
A64: Other Current Assets | B64: NA | C64: -2006 | D64: 15350 | E64: -14081 | F64: -21817 | G64: -1522
A65: Provision for Warranty | B65: NA | C65: 3814 | D65: 7140 | E65: 5097 | F65: -10220 | G65: 9933
A66: Cash Flow from Operating Activities | B66: 488871 | C66: 264353 | D66: 380640 | E66: 541488 | F66: 735887 | G66: 897654
A67: Investing Activities
A68: Capital Expenditures-property, Plant & Equipment | B68: -48707 | C68: -95441 | D68: -72199 | E68: -101184 | F68: -154103 | G68: -167895
A69: Proceeds From Sale of Property, Plant & Equipment | B69: 28 | C69: 2348 | D69: 6159 | E69: 940 | F69: 3558 | G69: 8817
A70: Investment in Subsidiary | B70: NA | C70: NA | D70: NA | E70: -314295 | F70: NA | G70: NA
A71: Net Purchase of Intangible Assets | B71: -2320 | C71: -3230 | D71: -2680 | E71: -4662 | F71: -16389 | G71: -30492
A72: Capitalized Development Expenditure | B72: -60202 | C72: -64126 | D72: -81973 | E72: -102627 | F72: -147220 | G72: -166343
A73: Dividends Received from Associate | B73: 31960 | C73: 16142 | D73: 36297 | E73: 48919 | F73: 30753 | G73: 13668
A74: Other Investments | B74: NA | C74: NA | D74: NA | E74: -1971 | F74: -5641 | G74: -7721
A75: Cash Flow from Investing Activities | B75: -79241 | C75: -144307 | D75: -114396 | E75: -474880 | F75: -289042 | G75: -349966
A76: Financing Activities
A77: Payment of Lease Liabilities | B77: -12048 | C77: -7819 | D77: -7854 | E77: -10289 | F77: -12602 | G77: -14177
A78: Proceeds from Issuance of Treasury Shares | B78: 6767 | C78: 2774 | D78: 4630 | E78: NA | F78: 863 | G78: NA
A79: Purchase of Treasury Shares | B79: -99929 | C79: -66715 | D79: -140142 | E79: NA | F79: -100928 | G79: -151366
A80: Capital Repayment | B80: -1144 | C80: NA | D80: NA | E80: NA | F80: NA | G80: NA
A81: Dividends to Common Shareholders | B81: -99298 | C81: -98688 | D81: -96893 | E81: -121650 | F81: -123383 | G81: -135487
A82: Credit Facility Renewal Fee Paid | B82: NA | C82: NA | D82: NA | E82: -660 | F82: NA | G82: NA
A83: Cash Flow from Financing Activities | B83: -205652 | C83: -170448 | D83: -240259 | E83: -132599 | F83: -236050 | G83: -301030
A84: Other Adjustments
A85: Foreign Exchange Rate Effect on Cash and Cash Equivalents | B85: 7989 | C85: -12244 | D85: 30294 | E85: -6201 | F85: 7154 | G85: 42579
A86: Cash Flow Net Changes in Cash | B86: 211967 | C86: -62646 | D86: 56279 | E86: -72192 | F86: 217949 | G86: 289237
A89: Recommended: S&P Capital IQ - Standard | B89: 2019 FY | C89: 2020 FY | D89: 2021 FY | E89: 2022 FY | F89: 2023 FY | G89: 2024 FY
A90: Period Ended | B90: 43830 | C90: 44196 | D90: 44561 | E90: 44926 | F90: 45291 | G90: 45657
A91: Currency | B91: EUR | C91: EUR | D91: EUR | E91: EUR | F91: EUR | G91: EUR
A92: Units | B92: Thousands | C92: Thousands | D92: Thousands | E92: Thousands | F92: Thousands | G92: Thousands
A93: Current Assets
A94: Cash and Cash Equivalents | B94: 497874 | C94: 435228 | D94: 491507 | E94: 419315 | F94: 637264 | G94: 926501
A95: Accounts Receivables | B95: 199535 | C95: 280061 | D95: 446724 | E95: 580823 | F95: 487727 | G95: 788958
A96: Contract Asset | B96: NA | C96: NA | D96: NA | E96: 63982 | F96: 59392 | G96: 57745
A97: Incomes Taxes Receivable | B97: 1220 | C97: 553 | D97: 18614 | E97: 18778 | F97: 29957 | G97: 4836
A98: Inventories | B98: 173189 | C98: 162199 | D98: 211841 | E98: 538425 | F98: 525690 | G98: 567007
A99: Other Current Assets | B99: 73479 | C99: 72945 | D99: 50972 | E99: 48189 | F99: 68845 | G99: 70277
A100: Total Current Assets | B100: 945297 | C100: 950986 | D100: 1219658 | E100: 1669512 | F100: 1808875 | G100: 2415324
A101: Noncurrent Assets
A102: Right of Use Assets | B102: 27547 | C102: 23387 | D102: 26938 | E102: 31663 | F102: 35395 | G102: 36525
A103: Property, Plant and Equipment | B103: 164863 | C103: 213967 | D103: 257017 | E103: 312053 | F103: 384949 | G103: 482901
A104: Investment in Associates | B104: 778268 | C104: 742714 | D104: 848812 | E104: 686341 | F104: 861937 | G104: 903625
A105: Other Investments | B105: NA | C105: NA | D105: NA | E105: 5814 | F105: 11307 | G105: 19821
A106: Deferred Tax Assets | B106: 3064 | C106: 196 | D106: 69 | E106: 181 | F106: 179 | G106: 34651
A107: Goodwill | B107: 11270 | C107: 11270 | D107: 11270 | E107: 320818 | F107: 320167 | G107: 321318
A108: Other Intangible Assets | B108: 189224 | C108: 209924 | D108: 274833 | E108: 646104 | F108: 705624 | G108: 815590
...

Sheet Input AIXTRON
A2: AIXTRON SE | Income Statement
A3: XTRA:AIXA (MI KEY: 4434404; SPCIQ KEY: 138633)
A5: Source: Recommended
A6: Period Category: Fiscal
A7: Period Type: Years
A8: Reporting Basis: Current/Restated
A9: Sort Order: Latest on Right
A10: Currency: Euro (EUR)
A11: Magnitude: Thousands (K)
A13: Recommended: S&P Capital IQ - Standard | B13: 2019 FY | C13: 2020 FY | D13: 2021 FY | E13: 2022 FY | F13: 2023 FY | G13: 2024 FY
B14: Current/Restated | C14: Current/Restated | D14: Current/Restated | E14: Current/Restated | F14: Current/Restated | G14: Current/Restated
A15: Period Ended | B15: 43830 | C15: 44196 | D15: 44561 | E15: 44926 | F15: 45291 | G15: 45657
A16: Financial Filing Date | B16: 44252 | C16: 44616 | D16: 44985 | E16: 45351 | F16: 45715 | G16: 45715
A17: Spot Exchange Rate | B17: 1 | C17: 1 | D17: 1 | E17: 1 | F17: 1 | G17: 1
A18: Average Exchange Rate | B18: 1 | C18: 1 | D18: 1 | E18: 1 | F18: 1 | G18: 1
A20: (€000)
A21: Revenue | B21: 259627 | C21: 269247 | D21: 428954 | E21: 463167 | F21: 629879 | G21: 633159
A22: Total Revenue | B22: 259627 | C22: 269247 | D22: 428954 | E22: 463167 | F22: 629879 | G22: 633159
A23: Cost Of Goods Sold | B23: 150882 | C23: 160960 | D23: 247433 | E23: 267896 | F23: 350847 | G23: 370688
A24: Gross Profit | B24: 108745 | C24: 108287 | D24: 181521 | E24: 195271 | F24: 279032 | G24: 262471
A26: Selling General & Admin Exp. | B26: 26400 | C26: 27673 | D26: 34683 | E26: 40439 | F26: 46654 | G26: 46052
A27: R & D Exp. | B27: 54955 | C27: 58379 | D27: 53211 | E27: 57726 | F27: 87681 | G27: 91365
A28: Other Operating Expense | B28: -8951 | C28: -10013 | D28: -9316 | E28: -5857 | F28: -6686 | G28: -6616
A29: Other Operating Exp., Total | B29: 72404 | C29: 76039 | D29: 78578 | E29: 92308 | F29: 127649 | G29: 130801
A30: Operating Income | B30: 36341 | C30: 32248 | D30: 102943 | E30: 102963 | F30: 151383 | G30: 131670
A32: Interest Expense | B32: -143 | C32: -104 | D32: -279 | E32: -356 | F32: -205 | G32: -429
A33: Interest and Invest. Income | B33: 865 | C33: 348 | D33: 232 | E33: 803 | F33: 1119 | G33: 1389
A34: Net Interest Exp. | B34: 722 | C34: 244 | D34: -47 | E34: 447 | F34: 914 | G34: 960
... A36: EBT Excl Unusual Items | B36: 38327 | C36: 31697 | D36: 104056 | E36: 106204 | F36: 153056 | G36: 131290
A37: Restructuring Charges | B37: NA | C37: NA | D37: -3888 | E37: NA | F37: NA | G37: NA
A38: Gain (Loss) On Sale Of Invest. | B38: NA | C38: -16 | D38: -708 | E38: -1047 | F38: 4846 | G38: 1042
A39: Gain (Loss) On Sale Of Assets | B39: -35 | C39: -51 | D39: -83 | E39: -14 | F39: -221 | G39: -139
A40: Asset Writedown | B40: NA | C40: 2909 | D40: -456 | E40: NA | F40: NA | G40: NA
A41: Insurance Settlements | B41: 1427 | C41: 535 | D41: 10 | E41: NA | F41: NA | G41: NA
A42: EBT Incl. Unusual Items | B42: 39719 | C42: 35074 | D42: 98931 | E42: 105143 | F42: 157681 | G42: 132193
A44: Income Tax Expense | B44: 7241 | C44: 604 | D44: 4092 | E44: 4671 | F44: 12492 | G44: 25945
A45: Earnings from Cont. Ops. | B45: 32478 | C45: 34470 | D45: 94839 | E45: 100472 | F45: 145189 | G45: 106248
A46: Net Income to Company | B46: 32478 | C46: 34470 | D46: 94839 | E46: 100472 | F46: 145189 | G46: 106248
A47: Minority Int. in Earnings | B47: 355 | C47: 409 | D47: 821 | E47: -35 | F47: -4 | G47: 35
A48: Net Income | B48: 32833 | C48: 34879 | D48: 95660 | E48: 100437 | F48: 145185 | G48: 106283
A49: NI to Common Incl Extra Items | B49: 32833 | C49: 34879 | D49: 95660 | E49: 100437 | F49: 145185 | G49: 106283
A50: NI to Common Excl. Extra Items | B50: 32833 | C50: 34879 | D50: 95660 | E50: 100437 | F50: 145185 | G50: 106283
A51: Per Share Items (€)
A52: Basic EPS | B52: 0.294 | C52: 0.312 | D52: 0.854 | E52: 0.894 | F52: 1.291 | G52: 0.944
A53: Basic EPS Excl. Extra Items | B53: 0.294 | C53: 0.312 | D53: 0.854 | E53: 0.894 | F53: 1.291 | G53: 0.944
A54: Weighted Avg. Basic Shares Out. (actual) | B54: 111840015 | C54: 111840146 | D54: 112056282 | E54: 112297083 | F54: 112465961 | G54: 112621622
A55: Diluted EPS Incl. Extra Items | B55: 0.29 | C55: 0.31 | D55: 0.85 | E55: 0.89 | F55: 1.29 | G55: 0.94
A56: Diluted EPS Excl. Extra Items | B56: 0.29 | C56: 0.31 | D56: 0.85 | E56: 0.89 | F56: 1.29 | G56: 0.94
A57: Weighted Avg. Diluted Shares Out. (actual) | B57: 111840015 | C57: 111887161 | D57: 112104323 | E57: 112354397 | F57: 112497842 | G57: 112621622
A58: Normalized Basic EPS | B58: 0.217 | C58: 0.181 | D58: 0.588 | E58: 0.591 | F58: 0.851 | G58: 0.729
A59: Normalized Diluted EPS | B59: 0.217 | C59: 0.181 | D59: 0.587 | E59: 0.59 | F59: 0.85 | G59: 0.729
A60: Dividends per Share | B60: NA | C60: 0.11 | D60: 0.3 | E60: 0.31 | F60: 0.4 | G60: 0.15
A61: Payout Ratio (%) | B61: NA | C61: NA | D61: 12.861 | E61: 33.516 | F61: 23.996 | G61: 42.371
A62: Shares per Depositary Receipt (actual) | B62: 2 | C62: 2 | D62: 2 | E62: 2 | F62: 2 | G62: 2
A63: Supplemental Items (€000)
A64: EBITDA | B64: 45297 | C64: 41024 | D64: 110862 | E64: 110363 | F64: 161057 | G64: 143830
A65: EBITA | B65: 37363 | C65: 33179 | D65: 104118 | E65: 104156 | F65: 152691 | G65: 133282
A66: EBIT | B66: 36341 | C66: 32248 | D66: 102943 | E66: 102963 | F66: 151383 | G66: 131670
A67: EBITDAR | B67: 45947 | C67: 41273 | D67: 111130 | E67: 110802 | F67: 161394 | G67: 144122
A68: Effective Tax Rate (%) | B68: 18.231 | C68: 1.722 | D68: 4.136 | E68: 4.443 | F68: 7.922 | G68: 19.627
A69: Total Current Taxes | B69: 5584 | C69: 3914 | D69: 13635 | E69: 13878 | F69: 19710 | G69: 18496
A70: Total Deferred Taxes | B70: 1657 | C70: -3310 | D70: -9543 | E70: -9207 | F70: -7218 | G70: 7449
A71: Normalized Net Income | B71: 24309.375 | C71: 20219.625 | D71: 65856 | E71: 66342.5 | F71: 95656 | G71: 82091.25
A72: Interest on Long-term Debt | B72: 87 | C72: 69 | D72: 107 | E72: 139 | F72: 187 | G72: 165
A73: Supplemental Operating Expense Items (€000)
A74: Selling and Marketing Expense | B74: 9945 | C74: 9723 | D74: 10005 | E74: 11223 | F74: 14082 | G74: 14182
A75: General and Administrative Expense | B75: 16455 | C75: 17950 | D75: 24678 | E75: 29216 | F75: 32572 | G75: 31870
A76: R&D Expense | B76: 54955 | C76: 58379 | D76: 56809 | E76: 57726 | F76: 87681 | G76: 91365
A77: Net Rental Expense, Total | B77: 650 | C77: 249 | D77: 268 | E77: 439 | F77: 337 | G77: 292
A78: Imputed Oper. Lease Interest Exp. | B78: NA | C78: 61.264 | D78: 156.876 | E78: 202.667 | F78: 80.805 | G78: 181.432
A79: Imputed Oper. Lease Depreciation | B79: NA | C79: 187.736 | D79: 111.124 | E79: 236.333 | F79: 256.195 | G79: 110.568
A80: Stock-Based Comp., Unallocated | B80: 889 | C80: 1129 | D80: 3860 | E80: 4441 | F80: 4762 | G80: 4528
A81: Stock-Based Comp., Total | B81: 889 | C81: 1129 | D81: 3860 | E81: 4441 | F81: 4762 | G81: 4528
A82: CIQ Restatement Type Code | B82: NC | C82: NC | D82: NC | E82: RC | F82: NC | G82: O
A83: CIQ Calculation Type Code | B83: REP | C83: REP | D83: REP | E83: REP | F83: REP | G83: REP
A84: Options Outstanding
A85: Options Out. at the Begin of Period, Common Stock | B85: 1338000 | C85: 995450 | D85: 601600 | E85: 182500 | F85: 112100 | G85: 48300
A86: Options Exercised During the Period, Common Stock | B86: NA | C86: NA | D86: 364700 | E86: 56400 | F86: 62600 | G86: 45100
A87: Options Cancelled During the Period, Common Stock | B87: 342550 | C87: 393850 | D87: 54400 | E87: 14000 | F87: 1200 | G87: 3200
A88: Options Out. at the End of Period, Common Stock | B88: 995450 | C88: 601600 | D88: 182500 | E88: 112100 | F88: 48300 | G88: NA
A89: Options Wtd Avg Strike Price of Outstd, Comm Stock (€) | B89: 17.84 | C89: 13.15 | D89: 13.16 | E89: 13.14 | F89: 13.14 | G89: 13.14
A90: Options Outstanding - All Classes
A91: Options Out. at the Beginning of the Period, Total | B91: 1338000 | C91: 995450 | D91: 601600 | E91: 182500 | F91: 112100 | G91: 48300
A92: Options Exercised During the Period, Total | B92: NA | C92: NA | D92: 364700 | E92: 56400 | F92: 62600 | G92: 45100
A93: Options Cancelled During the Period, Total | B93: 342550 | C93: 393850 | D93: 54400 | E93: 14000 | F93: 1200 | G93: 3200
A94: Options Out. at the End of the Period, Total | B94: 995450 | C94: 601600 | D94: 182500 | E94: 112100 | F94: 48300 | G94: NA
A95: Stock Based Compensation (€000)
A96: Stock Options Comp. Exp., Before Tax | B96: 889 | C96: 1129 | D96: 3860 | E96: 4441 | F96: 4762 | G96: 4528
A97: Stock Based Comp. Exp., Before Tax | B97: 889 | C97: 1129 | D97: 3860 | E97: 4441 | F97: 4762 | G97: 4528
A100: Recommended: S&P Capital IQ - Standard | B100: 2019 FY | C100: 2020 FY | D100: 2021 FY | E100: 2022 FY | F100: 2023 FY | G100: 2024 FY
B101: Current/Restated | C101: Current/Restated | D101: Current/Restated | E101: Current/Restated | F101: Current/Restated | G101: Current/Restated
A102: Period Ended | B102: 43830 | C102: 44196 | D102: 44561 | E102: 44926 | F102: 45291 | G102: 45657
A103: Financial Filing Date | B103: 44252 | C103: 44616 | D103: 44985 | E103: 45351 | F103: 45715 | G103: 45715
A104: Spot Exchange Rate | B104: 1 | C104: 1 | D104: 1 | E104: 1 | F104: 1 | G104: 1
A105: Average Exchange Rate | B105: 1 | C105: 1 | D105: 1 | E105: 1 | F105: 1 | G105: 1
A107: Operating Activities (€000)
A108: Net Income - CF | B108: 32833 | C108: 34879 | D108: 95660 | E108: 100437 | F108: 145185 | G108: 106283
A109: Depreciation & Amort. | B109: 9119 | C109: 8962 | D109: 7843 | E109: 7674 | F109: 10302 | G109: 12615
A110: Amort. of Goodwill and Intangibles | B110: 1022 | C110: 931 | D110: 1175 | E110: 1193 | F110: 1308 | G110: 1612
A111: Depreciation & Amort., Total | B111: 10141 | C111: 9893 | D111: 9018 | E111: 8867 | F111: 11610 | G111: 14227
...

Sheet Input AMAT
A2: Applied Materials, Inc. | Income Statement
A3: NASDAQGS:AMAT (MI KEY: 4073928; SPCIQ KEY: 251230)
A5: Source: Recommended
A6: Period Category: Fiscal
A7: Period Type: Years
A8: Reporting Basis: Current/Restated
A9: Sort Order: Latest on Right
A10: Currency: Euro (EUR)
A11: Magnitude: Thousands (K)
A13: Recommended: S&P Capital IQ - Standard | B13: 2019 FY | C13: 2020 FY | D13: 2021 FY | E13: 2022 FY | F13: 2023 FY | G13: 2024 FY
B14: Current/Restated | C14: Current/Restated | D14: Current/Restated | E14: Current/Restated | F14: Current/Restated | G14: Current/Restated
A15: Period Ended | B15: 43765 | C15: 44129 | D15: 44500 | E15: 44864 | F15: 45228 | G15: 45592
A16: Financial Filing Date | B16: 44547 | C16: 44911 | D16: 45275 | E16: 45639 | F16: 46003 | G16: 46003
A17: Spot Exchange Rate | B17: 0.9018 | C17: 0.8448 | D17: 0.8648 | E17: 1.0057 | F17: 0.9441 | G17: 0.924
A18: Average Exchange Rate | B18: 0.88938677 | C18: 0.88947617 | D18: 0.83772769 | E18: 0.93702308 | F18: 0.9317722 | G18: 0.91991899
A20: (€000)
A21: Revenue | B21: 12992162 | C21: 15300769 | D21: 19320514 | E21: 24161140 | F21: 24707803 | G21: 24999719
A22: Total Revenue | B22: 12992162 | C22: 15300769 | D22: 19320514 | E22: 24161140 | F22: 24707803 | G22: 24999719
A23: Cost Of Goods Sold | B23: 7312538 | C23: 8438460.4 | D23: 10177554 | E23: 12923422 | F23: 13168737 | G23: 13135523
A24: Gross Profit | B24: 5679623.9 | C24: 6862308.7 | D24: 9142960 | E24: 11237718 | F24: 11539067 | G24: 11864195
A26: Selling General & Admin Exp. | B26: 853811.3 | C26: 901039.36 | D26: 1029567.3 | E26: 1347439.2 | F26: 1516925.1 | G26: 1653094.4
A27: R & D Exp. | B27: 1826800.4 | C27: 1987089.8 | D27: 2081753.3 | E27: 2596490.9 | F27: 2890357.4 | G27: 2974098.1
A28: Other Operating Exp., Total | B28: 2680611.7 | C28: 2888129.1 | D28: 3111320.6 | E28: 3943930.1 | F28: 4407282.5 | G28: 4627192.5
A29: Operating Income | B29: 2999012.2 | C29: 3974179.5 | D29: 6031639.4 | E29: 7293787.6 | F29: 7131784.4 | G29: 7237002.7
A31: Interest Expense | B31: -210784.66 | C31: -213474.28 | D31: -197703.74 | E31: -213641.26 | F31: -221761.78 | G31: -227219.99
A32: Interest and Invest. Income | B32: 106726.41 | C32: 67600.189 | D32: NA | E32: 29984.738 | F32: 254373.81 | G32: 470998.52
A33: Net Interest Exp. | B33: -104058.25 | C33: -145874.09 | D33: -197703.74 | E33: -183656.52 | F33: 32612.027 | G33: 243778.53
A34: Currency Exchange Gains | B34: NA | C34: -8894.7617 | D34: 24294.103 | E34: NA | F34: NA | G34: NA
A35: Other Non-Operating Inc. | B35: NA | C35: -889.47617 | D35: -8377.2769 | E35: NA | F35: NA | G35: NA
A36: EBT Excl Unusual Items | B36: 2894953.9 | C36: 3818521.2 | D36: 5849852.5 | E36: 7110131.1 | F36: 7164396.5 | G36: 7480781.2
A37: Restructuring Charges | B37: NA | C37: NA | D37: -131523.25 | E37: 3748.0923 | F37: NA | G37: NA
A38: Merger & Related Restruct. Charges | B38: -19566.509 | C38: -71158.094 | D38: NA | E38: NA | F38: NA | G38: NA
A39: Gain (Loss) On Sale Of Invest. | B39: 32017.924 | C39: 8005.2855 | D39: 82935.042 | E39: 6559.1615 | F39: 25157.849 | G39: 18398.38
A40: Other Unusual Items | B40: NA | C40: -49810.666 | D40: -129010.06 | E40: NA | F40: NA | G40: NA
A41: EBT Incl. Unusual Items | B41: 2907405.4 | C41: 3705557.7 | D41: 5672254.2 | E41: 7120438.4 | F41: 7189554.3 | G41: 7499179.6
A43: Income Tax Expense | B43: 500724.75 | C43: 486543.47 | D43: 739713.55 | E43: 1006362.8 | F43: 801324.09 | G43: 896921.02
A44: Earnings from Cont. Ops. | B44: 2406680.6 | C44: 3219014.3 | D44: 4932540.7 | E44: 6114075.6 | F44: 6388230.2 | G44: 6602258.6
A45: Net Income to Company | B45: 2406680.6 | C45: 3219014.3 | D45: 4932540.7 | E45: 6114075.6 | F45: 6388230.2 | G45: 6602258.6
A46: Net Income | B46: 2406680.6 | C46: 3219014.3 | D46: 4932540.7 | E46: 6114075.6 | F46: 6388230.2 | G46: 6602258.6
A47: NI to Common Incl Extra Items | B47: 2406680.6 | C47: 3219014.3 | D47: 4932540.7 | E47: 6114075.6 | F47: 6388230.2 | G47: 6602258.6
A48: NI to Common Excl. Extra Items | B48: 2406680.6 | C48: 3219014.3 | D48: 4932540.7 | E48: 6114075.6 | F48: 6388230.2 | G48: 6602258.6
A49: Per Share Items (€)
A50: Basic EPS | B50: 2.568549 | C50: 3.5143204 | D50: 5.4200982 | E50: 7.0192399 | F50: 7.6051247 | G50: 7.983057
A51: Basic EPS Excl. Extra Items | B51: 2.568549 | C51: 3.5143204 | D51: 5.4200982 | E51: 7.0192399 | F51: 7.6051247 | G51: 7.983057
A52: Weighted Avg. Basic Shares Out. (actual) | B52: 937000000 | C52: 916000000 | D52: 910000000 | E52: 871000000 | F52: 840000000 | G52: 827000000
A53: Diluted EPS Incl. Extra Items | B53: 2.5436462 | C53: 3.4867466 | D53: 5.3614572 | E53: 6.9714517 | F53: 7.5566725 | G53: 7.9205025
A54: Diluted EPS Excl. Extra Items | B54: 2.5436462 | C54: 3.4867466 | D54: 5.3614572 | E54: 6.9714517 | F54: 7.5566725 | G54: 7.9205025
A55: Weighted Avg. Diluted Shares Out. (actual) | B55: 945000000 | C55: 923000000 | D55: 919000000 | E55: 877000000 | F55: 845000000 | G55: 834000000
A56: Normalized Basic EPS | B56: 1.9308587 | C56: 2.6052757 | D56: 4.017742 | E56: 5.1020907 | F56: 5.3306688 | G56: 5.6538221
A57: Normalized Diluted EPS | B57: 1.9148497 | C57: 2.5857072 | D57: 3.9783688 | E57: 5.0674208 | F57: 5.2989885 | G57: 5.6059863
A58: Dividends per Share | B58: 0.73819102 | C58: 0.77384427 | D58: 0.78746403 | E58: 0.95576354 | F58: 1.1367621 | G58: 1.3982769
A59: Payout Ratio (%) | B59: 28.492 | C59: 21.746 | D59: 14.232 | E59: 13.379 | F59: 14.221 | G59: 16.609
A60: Shares per Depositary Receipt (actual) | B60: 0.1 | C60: 0.1 | D60: 0.1 | E60: 0.1 | F60: 0.1 | G60: 0.1
A61: Supplemental Items (€000)
A62: EBITDA | B62: 3321859.6 | C62: 4308622.6 | D62: 6361704.1 | E62: 7709825.9 | F62: 7611647.1 | G62: 7597611
A63: EBITA | B63: 3049707.2 | C63: 4023990.2 | D63: 6072688 | E63: 7293787.6 | F63: 7131784.4 | G63: 7237002.7
A64: EBIT | B64: 2999012.2 | C64: 3974179.5 | D64: 6031639.4 | E64: 7293787.6 | F64: 7131784.4 | G64: 7237002.7
A65: EBITDAR | B65: 3367218.3 | C65: 4369996.4 | D65: 6427884.6 | E65: NA | F65: NA | G65: NA
A66: Effective Tax Rate (%) | B66: 17.222 | C66: 13.13 | D66: 13.041 | E66: 14.133 | F66: 11.146 | G66: 11.96
A67: Current Domestic Taxes | B67: 224125.47 | C67: 233932.23 | D67: 401271.56 | E67: 565961.94 | F67: 710010.42 | G67: 1183935.7
A68: Current Foreign Taxes | B68: 231240.56 | C68: NA | D68: 288178.33 | E68: 257681.35 | F68: 424888.12 | G68: 336690.35
A69: Total Current Taxes | B69: 455366.03 | C69: 233932.23 | D69: 689449.89 | E69: 823643.28 | F69: 1134898.5 | G69: 1520626.1
A70: Deferred Domestic Taxes | B70: 4446.9339 | C70: 67600.189 | D70: -5864.0938 | E70: -65591.615 | F70: -276736.34 | G70: -651302.65
A71: Deferred Foreign Taxes | B71: 40911.791 | C71: NA | D71: 56127.755 | E71: 248311.12 | F71: -56838.104 | G71: 27597.57
A72: Total Deferred Taxes | B72: 45358.725 | C72: 67600.189 | D72: 50263.662 | E72: 182719.5 | F72: -333574.45 | G72: -623705.08
A73: Normalized Net Income | B73: 1809346.2 | C73: 2386575.8 | D73: 3656157.8 | E73: 4443831.9 | F73: 4477747.8 | G73: 4675488.3
A74: Interest on Long-term Debt | B74: 210784.66 | C74: 213474.28 | D74: 197703.74 | E74: NA | F74: NA | G74: NA
A75: Non-Cash Pension Expense | B75: -2668.1603 | C75: -1778.9523 | D75: 837.72769 | E75: NA | F75: NA | G75: NA
A76: Interest and Penalties Recog. on IS - Before Tax | B76: 21345.282 | C76: 21347.428 | D76: 11728.188 | E76: 13118.323 | F76: 31680.255 | G76: 41396.355
A77: Supplemental Operating Expense Items (€000)
A78: Selling and Marketing Expense | B78: 463370.51 | C78: 467864.47 | D78: 510176.16 | E78: 658727.22 | F78: 723055.23 | G78: 769052.28
A79: General and Administrative Expense | B79: 390440.79 | C79: 433174.9 | D79: 519391.17 | E79: 688711.96 | F79: 793869.92 | G79: 884042.15
A80: R&D Expense | B80: 1826800.4 | C80: 1987089.8 | D80: 2081753.3 | E80: 2596490.9 | F80: 2890357.4 | G80: 2974098.1
A81: Net Rental Expense, Total | B81: 45358.725 | C81: 61373.856 | D81: 66180.488 | E81: NA | F81: NA | G81: NA
A82: Imputed Oper. Lease Interest Exp. | B82: 16192.702 | C82: 21386.088 | D82: 21805.677 | E82: NA | F82: NA | G82: NA
A83: Imputed Oper. Lease Depreciation | B83: 29166.023 | C83: 39987.768 | D83: 44374.811 | E83: NA | F83: NA | G83: NA
A84: Stock-Based Comp., COGS | B84: 79155.423 | C84: 91616.046 | D84: 98851.868 | E84: 137742.39 | F84: 167719 | G84: 123269.14
A85: Stock-Based Comp., R&D Exp. | B85: 88049.29 | C85: 103179.24 | D85: 108066.87 | E85: 141490.48 | F85: 166787.22 | G85: 201462.26
A86: Stock-Based Comp., S&M Exp. | B86: 27570.99 | C86: 32021.142 | D86: 36022.291 | E86: 45914.131 | F86: 51247.471 | G86: 66234.167
A87: Stock-Based Comp., G&A Exp. | B87: 39133.018 | C87: 46252.761 | D87: 46912.751 | E87: 61843.523 | F87: 70814.687 | G87: 139827.69
A88: Stock-Based Comp., Total | B88: 233908.72 | C88: 273069.18 | D88: 289853.78 | E88: 386990.53 | F88: 456568.38 | G88: 530793.26
A89: CIQ Restatement Type Code | B89: RC | C89: NC | D89: RC | E89: RC | F89: NC | G89: NC
A90: CIQ Calculation Type Code | B90: REP | C90: REP | D90: REP | E90: REP | F90: REP | G90: REP
A91: Stock Based Compensation (€000)
A92: Stock Based Comp. Exp., Before Tax | B92: 233908.72 | C92: 273069.18 | D92: 289853.78 | E92: 386990.53 | F92: 456568.38 | G92: 530793.26
A93: Stock Based Comp. Exp. Tax Effect | B93: -32907.311 | C93: -34689.571 | D93: -36022.291 | E93: -47788.177 | F93: -58701.649 | G93: -67154.086
A94: Stock Based Comp. Exp., After Tax | B94: 201001.41 | C94: 238379.61 | D94: 253831.49 | E94: 339202.35 | F94: 397866.73 | G94: 463639.17
A97: Recommended: S&P Capital IQ - Standard | B97: 2019 FY | C97: 2020 FY | D97: 2021 FY | E97: 2022 FY | F97: 2023 FY | G97: 2024 FY
B98: Current/Restated | C98: Current/Restated | D98: Current/Restated | E98: Current/Restated | F98: Current/Restated | G98: Current/Restated
A99: Period Ended | B99: 43765 | C99: 44129 | D99: 44500 | E99: 44864 | F99: 45228 | G99: 45592
A100: Financial Filing Date | B100: 44547 | C100: 44911 | D100: 45275 | E100: 45639 | F100: 46003 | G100: 46003
A101: Spot Exchange Rate | B101: 0.9018 | C101: 0.8448 | D101: 0.8648 | E101: 1.0057 | F101: 0.9441 | G101: 0.924
A102: Average Exchange Rate | B102: 0.88938677 | C102: 0.88947617 | D102: 0.83772769 | E102: 0.93702308 | F102: 0.9317722 | G102: 0.91991899
A104: Operating Activities (€000)
A105: Net Income - CF | B105: 2406680.6 | C105: 3219014.3 | D105: 4932540.7 | E105: 6114075.6 | F105: 6388230.2 | G105: 6602258.6
A106: Depreciation & Amort. | B106: 272152.35 | C106: 284632.37 | D106: 289016.05 | E106: 416038.25 | F106: 479862.68 | G106: 360608.24
A107: Amort. of Goodwill and Intangibles | B107: 50695.046 | C107: 49810.666 | D107: 41048.657 | E107: NA | F107: NA | G107: NA
A108: Depreciation & Amort., Total | B108: 322847.4 | C108: 334443.04 | D108: 330064.71 | E108: 416038.25 | F108: 479862.68 | G108: 360608.24
A109: Loss On Sale Of Investment | B109: NA | C109: NA | D109: NA | E109: NA | F109: -14908.355 | G109: -13798.785
A110: Stock-Based Compensation | B110: 233908.72 | C110: 273069.18 | D110: 289853.78 | E110: 386990.53 | F110: 456568.38 | G110: 530793.26
...

Sheet Input LRCX
A2: Lam Research Corporation | Income Statement
A3: NASDAQGS:LRCX (MI KEY: 4069378; SPCIQ KEY: 30655)
A5: Source: Recommended
A6: Period Category: Fiscal
A7: Period Type: Years
A8: Reporting Basis: Current/Restated
A9: Sort Order: Latest on Right
A10: Currency: Euro (EUR)
A11: Magnitude: Thousands (K)
A13: Recommended: S&P Capital IQ - Standard | B13: 2019 FY | C13: 2020 FY | D13: 2021 FY | E13: 2022 FY | F13: 2023 FY | G13: 2024 FY
B14: Current/Restated | C14: Current/Restated | D14: Current/Restated | E14: Current/Restated | F14: Current/Restated | G14: Current/Restated
A15: Period Ended | B15: 43646 | C15: 44010 | D15: 44374 | E15: 44738 | F15: 45102 | G15: 45473
A16: Financial Filing Date | B16: 44425 | C16: 44797 | D16: 45153 | E16: 45533 | F16: 45880 | G16: 45880
A17: Spot Exchange Rate | B17: 0.8788 | C17: 0.8921 | D17: 0.8373 | E17: 0.948 | F17: 0.9189 | G17: 0.9333
A18: Average Exchange Rate | B18: 0.87664962 | C18: 0.90458538 | D18: 0.83852713 | E18: 0.88731128 | F18: 0.9568543 | G18: 0.92466808
A20: (€000)
A21: Revenue | B21: 8462788.8 | C21: 9086321.4 | D21: 12264424 | E21: 15285746 | F21: 16676550 | G21: 13782535
A22: Total Revenue | B22: 8462788.8 | C22: 9086321.4 | D22: 12264424 | E22: 15285746 | F22: 16676550 | G22: 13782535
A23: Cost Of Goods Sold | B23: 4641947.4 | C23: 4917365 | D23: 6557989.9 | E23: 8301002.9 | F23: 9160372.8 | G23: 7220936.4
A24: Gross Profit | B24: 3820841.4 | C24: 4168956.3 | D24: 5706433.7 | E24: 6984743.2 | F24: 7516177.6 | G24: 6561598.2
A26: Selling General & Admin Exp. | B26: 615764.83 | C26: 617360.53 | D26: 695872.7 | E26: 785924.43 | F26: 796823.29 | G26: 802840.28
A27: R & D Exp. | B27: 1044370.2 | C27: 1132913.6 | D27: 1252263.1 | E27: 1423467.4 | F27: 1652642.4 | G27: 1759129.2
A28: Other Operating Exp., Total | B28: 1660135 | C28: 1750274.1 | D28: 1948135.8 | E28: 2209391.8 | F28: 2449465.7 | G28: 2561969.5
A29: Operating Income | B29: 2160706.4 | C29: 2418682.2 | D29: 3758297.9 | E29: 4775351.4 | F29: 5066711.9 | G29: 3999628.7
A31: Interest Expense | B31: -102798.56 | C31: -160509.63 | D31: -174914.24 | E31: -163938.75 | F31: -178416.97 | G31: -171281.82
A32: Interest and Invest. Income | B32: 86587.559 | C32: 77281.443 | D32: 16508.084 | E32: 13495.117 | F32: 132987.44 | G32: 232959.03
A33: Net Interest Exp. | B33: -16211.005 | C33: -83228.187 | D33: -158406.16 | E33: -150443.63 | F33: -45429.528 | G33: 61677.21
A34: Currency Exchange Gains | B34: 724.11258 | C34: -3000.5097 | D34: -5837.8259 | E34: -641.52606 | F34: -6772.6147 | G34: -4472.6195
... A36: EBT Excl Unusual Items | B36: 2144785.5 | C36: 2329287.5 | D36: 3665037.7 | E36: 4607908.7 | F36: 5003894.4 | G36: 4088682.5
A37: Restructuring Charges | B37: NA | C37: NA | D37: NA | E37: NA | F37: -115124.88 | G37: -56924.416
A38: EBT Incl. Unusual Items | B38: 2144785.5 | C38: 2329287.5 | D38: 3665037.7 | E38: 4607908.7 | F38: 4888769.5 | G38: 4031758.1
A40: Income Tax Expense | B40: 223669.26 | C40: 292384.61 | D40: 387689.67 | E40: 521586.42 | F40: 572465.83 | G40: 492339.52
A41: Earnings from Cont. Ops. | B41: 1921116.3 | C41: 2036902.9 | D41: 3277348.1 | E41: 4086322.2 | F41: 4316303.7 | G41: 3539418.6
A42: Net Income to Company | B42: 1921116.3 | C42: 2036902.9 | D42: 3277348.1 | E42: 4086322.2 | F42: 4316303.7 | G42: 3539418.6
A43: Net Income | B43: 1921116.3 | C43: 2036902.9 | D43: 3277348.1 | E43: 4086322.2 | F43: 4316303.7 | G43: 3539418.6
A44: NI to Common Incl Extra Items | B44: 1921116.3 | C44: 2036902.9 | D44: 3277348.1 | E44: 4086322.2 | F44: 4316303.7 | G44: 3539418.6
A45: NI to Common Excl. Extra Items | B45: 1921116.3 | C45: 2036902.9 | D45: 3277348.1 | E45: 4086322.2 | F45: 4316303.7 | G45: 3539418.6
A46: Per Share Items (€)
A47: Basic EPS | B47: 1.2597455 | C47: 1.4066303 | D47: 2.2824709 | E47: 2.9210287 | F47: 3.1863248 | G47: 2.6935581
A48: Basic EPS Excl. Extra Items | B48: 1.2597455 | C48: 1.4066303 | D48: 2.2824709 | E48: 2.9210287 | F48: 3.1863248 | G48: 2.6935581
A49: Weighted Avg. Basic Shares Out. (actual) | B49: 1524780000 | C49: 1448140000 | D49: 1436090000 | E49: 1398990000 | F49: 1354715000 | G49: 1314102000
A50: Diluted EPS Incl. Extra Items | B50: 1.20101 | C50: 1.3659239 | D50: 2.255638 | E50: 2.9059445 | F50: 3.1767563 | G50: 2.6815374
A51: Diluted EPS Excl. Extra Items | B51: 1.20101 | C51: 1.3659239 | D51: 2.255638 | E51: 2.9059445 | F51: 3.1767563 | G51: 2.6815374
A52: Weighted Avg. Diluted Shares Out. (actual) | B52: 1599150000 | C52: 1490900000 | D52: 1453200000 | E52: 1406280000 | F52: 1358336000 | G52: 1319949000
A53: Normalized Basic EPS | B53: 0.87927956 | C53: 1.0049944 | D53: 1.5948786 | E53: 2.0585622 | F53: 2.3088894 | G53: 1.944577
A54: Normalized Diluted EPS | B54: 0.83807703 | C54: 0.97604763 | D54: 1.576431 | E54: 2.0479144 | F54: 2.3021914 | G54: 1.936255
A55: Dividends per Share | B55: 0.38572583 | C55: 0.41610928 | D55: 0.43603411 | E55: 0.53238677 | F55: 0.66022946 | G55: 0.73973446
A56: Payout Ratio (%) | B56: 30.955 | C56: 29.17 | D56: 18.6 | E56: 17.703 | F56: 20.127 | G56: 26.619
A57: Shares per Depositary Receipt (actual) | B57: 0.25 | C57: 0.25 | D57: 0.25 | E57: 0.25 | F57: 0.25 | G57: 0.25
A58: Supplemental Items (€000)
A59: EBITDA | B59: 2431837.4 | C59: 2661586 | D59: 4015852.3 | E59: 5071481.8 | F59: 5394369.4 | G59: 4332230.8
A60: EBITA | B60: 2272303.9 | C60: 2478565.8 | D60: 3817497.9 | E60: 4844561.7 | F60: 5066711.9 | G60: 3999628.7
A61: EBIT | B61: 2160706.4 | C61: 2418682.2 | D61: 3758297.9 | E61: 4775351.4 | F61: 5066711.9 | G61: 3999628.7
A62: EBITDAR | B62: 2456471.3 | C62: 2786375.4 | D62: 4242723.4 | E62: 5362778.1 | F62: 5612245.2 | G62: 4495527.2
A63: Effective Tax Rate (%) | B63: 10.429 | C63: 12.553 | D63: 10.578 | E63: 11.319 | F63: 11.71 | G63: 12.212
A64: Current Domestic Taxes | B64: 131356.3 | C64: 200127.76 | D64: 378247.01 | E64: 568857.93 | F64: 548754.03 | G64: 542028.41
A65: Current Foreign Taxes | B65: 96679.55 | C65: 108338.57 | D65: 136460.23 | E65: 181156.13 | F65: 188349.11 | G65: 132777.71
A66: Total Current Taxes | B66: 228035.85 | C66: 308466.33 | D66: 514707.24 | E66: 750014.06 | F66: 737103.14 | G66: 674806.12
A67: Deferred Domestic Taxes | B67: -5065.2815 | C67: -10795.322 | D67: -123980.43 | E67: -218270.59 | F67: -132994.14 | G67: -186187.47
A68: Deferred Foreign Taxes | B68: 698.68974 | C68: -5286.397 | D68: -3037.1453 | E68: -10157.052 | F68: -31643.172 | G68: 3720.8643
A69: Total Deferred Taxes | B69: -4366.5917 | C69: -16081.719 | D69: -127017.57 | E69: -228427.64 | F69: -164637.31 | G69: -182466.6
A70: Normalized Net Income | B70: 1340491 | C70: 1455804.7 | D70: 2290648.6 | E70: 2879942.9 | F70: 3127434 | G70: 2555426.6
A71: Interest on Long-term Debt | B71: 92990.608 | C71: 159117.47 | D71: 170755.15 | E71: 159630.85 | F71: 171627.13 | G71: 166338.54
A72: Supplemental Operating Expense Items (€000)
A73: R&D Expense | B73: 1044370.2 | C73: 1132913.6 | D73: 1252263.1 | E73: 1423467.4 | F73: 1652642.4 | G73: 1759129.2
A74: Net Rental Expense, Total | B74: 24633.854 | C74: 124789.36 | D74: 226871.06 | E74: 291296.31 | F74: 217875.72 | G74: 163296.38
A75: Imputed Oper. Lease Interest Exp. | B75: 6656.8555 | C75: 33807.934 | D75: 67912.491 | E75: 82879.625 | F75: 62059.721 | G75: 46003.857
A76: Imputed Oper. Lease Depreciation | B76: 17976.999 | C76: 90981.429 | D76: 158958.57 | E76: 208416.68 | F76: 155816 | G76: 117292.53
A77: Stock-Based Comp., Unallocated | B77: 164138.61 | C77: 171144.84 | D77: 184613.49 | E77: 229870.41 | F77: 274234.44 | G77: 270981.38
A78: Stock-Based Comp., Total | B78: 164138.61 | C78: 171144.84 | D78: 184613.49 | E78: 229870.41 | F78: 274234.44 | G78: 270981.38
A79: CIQ Restatement Type Code | B79: NC | C79: NC | D79: NC | E79: NC | F79: NC | G79: NC
A80: CIQ Calculation Type Code | B80: REP | C80: REP | D80: REP | E80: REP | F80: REP | G80: REP
A81: Stock Based Compensation (€000)
A82: Stock Based Comp. Exp., Before Tax | B82: 164138.61 | C82: 171144.84 | D82: 184613.49 | E82: 229870.41 | F82: 274234.44 | G82: 270981.38
A83: Stock Based Comp. Exp. Tax Effect | B83: -41549.685 | C83: -32687.193 | D83: -41350.288 | E83: -33244.005 | F83: -24681.1 | G83: -35282.56
A84: Stock Based Comp. Exp., After Tax | B84: 122588.93 | C84: 138457.65 | D84: 143263.2 | E84: 196626.41 | F84: 249553.34 | G84: 235698.82
A87: Recommended: S&P Capital IQ - Standard | B87: 2019 FY | C87: 2020 FY | D87: 2021 FY | E87: 2022 FY | F87: 2023 FY | G87: 2024 FY
B88: Current/Restated | C88: Current/Restated | D88: Current/Restated | E88: Current/Restated | F88: Current/Restated | G88: Current/Restated
A89: Period Ended | B89: 43646 | C89: 44010 | D89: 44374 | E89: 44738 | F89: 45102 | G89: 45473
A90: Financial Filing Date | B90: 44425 | C90: 44797 | D90: 45153 | E90: 45533 | F90: 45880 | G90: 45880
A91: Spot Exchange Rate | B91: 0.8788 | C91: 0.8921 | D91: 0.8373 | E91: 0.948 | F91: 0.9189 | G91: 0.9333
A92: Average Exchange Rate | B92: 0.87664962 | C92: 0.90458538 | D92: 0.83852713 | E92: 0.88731128 | F92: 0.9568543 | G92: 0.92466808
A94: Operating Activities (€000)
A95: Net Income - CF | B95: 1921116.3 | C95: 2036902.9 | D95: 3277348.1 | E95: 4086322.2 | F95: 4316303.7 | G95: 3539418.6
A96: Depreciation & Amort. | B96: 159533.57 | C96: 183020.24 | D96: 198354.43 | E96: 226920.1 | F96: 327657.53 | G96: 332602.18
A97: Amort. of Goodwill and Intangibles | B97: 111597.5 | C97: 59883.552 | D97: 59200.016 | E97: 69210.28 | F97: NA | G97: NA
A98: Depreciation & Amort., Total | B98: 271131.07 | C98: 242903.79 | D98: 257554.45 | E98: 296130.38 | F98: 327657.53 | G98: 332602.18
A99: Stock-Based Compensation | B99: 164138.61 | C99: 171144.84 | D99: 184613.49 | E99: 229870.41 | F99: 274234.44 | G99: 270981.38
A100: Other Operating Activities | B100: -3029.7011 | C100: -10085.222 | D100: -141601.24 | E100: -268135.71 | F100: -114595.74 | G100: -174520
A101: Change in Acc. Receivable | B101: 641828.5 | C101: -580587.32 | D101: -778931.33 | E101: -1142573 | F101: 1389597.4 | G101: 280584.06
A102: Change In Inventories | B102: 246649.75 | C102: -372334.58 | D102: -664609.06 | E102: -1199062.8 | F102: -920463.21 | G102: 488893.28
A103: Change in Acc. Payable | B103: -115254.88 | C103: 188586.15 | D103: 154804.69 | E103: 148965.37 | F103: -499669.31 | G103: 116451.77
A104: Change in Unearned Rev. | B104: -156108.5 | C104: 68935.738 | D104: 425978.49 | E104: 536444.44 | F104: 156414.1 | G104: -256539.91
A105: Change in Other Net Operating Assets | B105: -186220.54 | C105: 178090.25 | D105: 293614.47 | E105: 62414.363 | F105: 26010.17 | G105: -296066.7
A106: Cash from Ops. | B106: 2784250.6 | C106: 1923556.5 | D106: 3008772 | E106: 2750375.7 | F106: 4955489.1 | G106: 4301804.6
A107: Investing Activity (€000)
A108: Capital Expenditure | B108: -266055.27 | C108: -183847.03 | D108: -292726.47 | E108: -484502.13 | F108: -479927.5 | G108: -366788.09
A109: Cash Acquisitions | B109: NA | C109: NA | D109: NA | E109: NA | F109: -114779.46 | G109: NA
A110: Invest. in Marketable & Equity Securt. | B110: -1162619.7 | C110: -13568.781 | D110: 389514.3 | E110: 1034502 | F110: 93898.026 | G110: 34921.015
A111: Other Investing Activities | B111: -6447.7579 | C111: -23379.009 | D111: -35348.111 | E111: -6721.383 | F111: -10689.019 | G111: -10827.863
...

Sheet Std ASM
A1: Standardized Financial Statements - ASM International NV
A2: (EUR 000)
B3: 2019 | C3: 2020 | D3: 2021 | E3: 2022 | F3: 2023 | G3: 2024
A5: Operating cash % | B5: 0.02 | C5: 0.02 | D5: 0.02 | E5: 0.02 | F5: 0.02 | G5: 0.02
A6: Tax rate (effective) | B6: =IF(ISNUMBER('Input ASM'!B68),'Input ASM'!B68,0) | C6: =IF(ISNUMBER('Input ASM'!C68),'Input ASM'!C68,0) | D6: =IF(ISNUMBER('Input ASM'!D68),'Input ASM'!D68,0) | E6: =IF(ISNUMBER('Input ASM'!E68),'Input ASM'!E68,0) | F6: =IF(ISNUMBER('Input ASM'!F68),'Input ASM'!F68,0) | G6: =IF(ISNUMBER('Input ASM'!G68),'Input ASM'!G68,0)
A8: INCOME STATEMENT
A9: Revenue | B9: =IF(ISNUMBER('Input ASM'!B21),'Input ASM'!B21,0) | C9: =IF(ISNUMBER('Input ASM'!C21),'Input ASM'!C21,0) | D9: =IF(ISNUMBER('Input ASM'!D21),'Input ASM'!D21,0) | E9: =IF(ISNUMBER('Input ASM'!E21),'Input ASM'!E21,0) | F9: =IF(ISNUMBER('Input ASM'!F21),'Input ASM'!F21,0) | G9: =IF(ISNUMBER('Input ASM'!G21),'Input ASM'!G21,0)
A10: Cost of Sales | B10: =IF(ISNUMBER('Input ASM'!B23),'Input ASM'!B23,0) | C10: =IF(ISNUMBER('Input ASM'!C23),'Input ASM'!C23,0) | D10: =IF(ISNUMBER('Input ASM'!D23),'Input ASM'!D23,0) | E10: =IF(ISNUMBER('Input ASM'!E23),'Input ASM'!E23,0) | F10: =IF(ISNUMBER('Input ASM'!F23),'Input ASM'!F23,0) | G10: =IF(ISNUMBER('Input ASM'!G23),'Input ASM'!G23,0)
A11: Gross Profit | B11: =B9-B10 | C11: =C9-C10 | D11: =D9-D10 | E11: =E9-E10 | F11: =F9-F10 | G11: =G9-G10
A12: SG&A | B12: =IF(ISNUMBER('Input ASM'!B26),'Input ASM'!B26,0) | C12: =IF(ISNUMBER('Input ASM'!C26),'Input ASM'!C26,0) | D12: =IF(ISNUMBER('Input ASM'!D26),'Input ASM'!D26,0) | E12: =IF(ISNUMBER('Input ASM'!E26),'Input ASM'!E26,0) | F12: =IF(ISNUMBER('Input ASM'!F26),'Input ASM'!F26,0) | G12: =IF(ISNUMBER('Input ASM'!G26),'Input ASM'!G26,0)
A13: R&D | B13: =IF(ISNUMBER('Input ASM'!B27),'Input ASM'!B27,0) | C13: =IF(ISNUMBER('Input ASM'!C27),'Input ASM'!C27,0) | D13: =IF(ISNUMBER('Input ASM'!D27),'Input ASM'!D27,0) | E13: =IF(ISNUMBER('Input ASM'!E27),'Input ASM'!E27,0) | F13: =IF(ISNUMBER('Input ASM'!F27),'Input ASM'!F27,0) | G13: =IF(ISNUMBER('Input ASM'!G27),'Input ASM'!G27,0)
A14: Depreciation & Amortization | B14: =IF(ISNUMBER('Input ASM'!B113),'Input ASM'!B113,0) | C14: =IF(ISNUMBER('Input ASM'!C113),'Input ASM'!C113,0) | D14: =IF(ISNUMBER('Input ASM'!D113),'Input ASM'!D113,0) | E14: =IF(ISNUMBER('Input ASM'!E113),'Input ASM'!E113,0) | F14: =IF(ISNUMBER('Input ASM'!F113),'Input ASM'!F113,0) | G14: =IF(ISNUMBER('Input ASM'!G113),'Input ASM'!G113,0)
A15: Other Operating Expense | B15: =IF(ISNUMBER('Input ASM'!B29),'Input ASM'!B29,0) | C15: =IF(ISNUMBER('Input ASM'!C29),'Input ASM'!C29,0) | D15: =IF(ISNUMBER('Input ASM'!D29),'Input ASM'!D29,0) | E15: =IF(ISNUMBER('Input ASM'!E29),'Input ASM'!E29,0) | F15: =IF(ISNUMBER('Input ASM'!F29),'Input ASM'!F29,0) | G15: =IF(ISNUMBER('Input ASM'!G29),'Input ASM'!G29,0)
A16: Total Operating Expense | B16: =B10+B12+B13+B14+B15 | C16: =C10+C12+C13+C14+C15 | D16: =D10+D12+D13+D14+D15 | E16: =E10+E12+E13+E14+E15 | F16: =F10+F12+F13+F14+F15 | G16: =G10+G12+G13+G14+G15
A17: Recurring Operating Profit | B17: =B9-B16 | C17: =C9-C16 | D17: =D9-D16 | E17: =E9-E16 | F17: =F9-F16 | G17: =G9-G16
A19: Non-recurring items:
A20: Gain/Loss on Sale of Investments | B20: =IF(ISNUMBER('Input ASM'!B39),'Input ASM'!B39,0) | C20: =IF(ISNUMBER('Input ASM'!C39),'Input ASM'!C39,0) | D20: =IF(ISNUMBER('Input ASM'!D39),'Input ASM'!D39,0) | E20: =IF(ISNUMBER('Input ASM'!E39),'Input ASM'!E39,0) | F20: =IF(ISNUMBER('Input ASM'!F39),'Input ASM'!F39,0) | G20: =IF(ISNUMBER('Input ASM'!G39),'Input ASM'!G39,0)
A21: Gain/Loss on Sale of Assets | B21: =IF(ISNUMBER('Input ASM'!B40),'Input ASM'!B40,0) | C21: =IF(ISNUMBER('Input ASM'!C40),'Input ASM'!C40,0) | D21: =IF(ISNUMBER('Input ASM'!D40),'Input ASM'!D40,0) | E21: =IF(ISNUMBER('Input ASM'!E40),'Input ASM'!E40,0) | F21: =IF(ISNUMBER('Input ASM'!F40),'Input ASM'!F40,0) | G21: =IF(ISNUMBER('Input ASM'!G40),'Input ASM'!G40,0)
A22: Asset Writedown | B22: =IF(ISNUMBER('Input ASM'!B41),'Input ASM'!B41,0) | C22: =IF(ISNUMBER('Input ASM'!C41),'Input ASM'!C41,0) | D22: =IF(ISNUMBER('Input ASM'!D41),'Input ASM'!D41,0) | E22: =IF(ISNUMBER('Input ASM'!E41),'Input ASM'!E41,0) | F22: =IF(ISNUMBER('Input ASM'!F41),'Input ASM'!F41,0) | G22: =IF(ISNUMBER('Input ASM'!G41),'Input ASM'!G41,0)
A23: Other Unusual Items | B23: =IF(ISNUMBER('Input ASM'!B42),'Input ASM'!B42,0) | C23: =IF(ISNUMBER('Input ASM'!C42),'Input ASM'!C42,0) | D23: =IF(ISNUMBER('Input ASM'!D42),'Input ASM'!D42,0) | E23: =IF(ISNUMBER('Input ASM'!E42),'Input ASM'!E42,0) | F23: =IF(ISNUMBER('Input ASM'!F42),'Input ASM'!F42,0) | G23: =IF(ISNUMBER('Input ASM'!G42),'Input ASM'!G42,0)
A24: Total Non-recurring | B24: =SUM(B20:B23) | C24: =SUM(C20:C23) | D24: =SUM(D20:D23) | E24: =SUM(E20:E23) | F24: =SUM(F20:F23) | G24: =SUM(G20:G23)
A25: EBIT | B25: =B17+B24 | C25: =C17+C24 | D25: =D17+D24 | E25: =E17+E24 | F25: =F17+F24 | G25: =G17+G24
A27: Investment Income (Equity Method) | B27: =IF(ISNUMBER('Input ASM'!B36),'Input ASM'!B36,0) | C27: =IF(ISNUMBER('Input ASM'!C36),'Input ASM'!C36,0) | D27: =IF(ISNUMBER('Input ASM'!D36),'Input ASM'!D36,0) | E27: =IF(ISNUMBER('Input ASM'!E36),'Input ASM'!E36,0) | F27: =IF(ISNUMBER('Input ASM'!F36),'Input ASM'!F36,0) | G27: =IF(ISNUMBER('Input ASM'!G36),'Input ASM'!G36,0)
A28: Interest Income | B28: =IF(ISNUMBER('Input ASM'!B34),'Input ASM'!B34,0) | C28: =IF(ISNUMBER('Input ASM'!C34),'Input ASM'!C34,0) | D28: =IF(ISNUMBER('Input ASM'!D34),'Input ASM'!D34,0) | E28: =IF(ISNUMBER('Input ASM'!E34),'Input ASM'!E34,0) | F28: =IF(ISNUMBER('Input ASM'!F34),'Input ASM'!F34,0) | G28: =IF(ISNUMBER('Input ASM'!G34),'Input ASM'!G34,0)
A29: Interest Expense | B29: =IF(ISNUMBER('Input ASM'!B33),'Input ASM'!B33,0) | C29: =IF(ISNUMBER('Input ASM'!C33),'Input ASM'!C33,0) | D29: =IF(ISNUMBER('Input ASM'!D33),'Input ASM'!D33,0) | E29: =IF(ISNUMBER('Input ASM'!E33),'Input ASM'!E33,0) | F29: =IF(ISNUMBER('Input ASM'!F33),'Input ASM'!F33,0) | G29: =IF(ISNUMBER('Input ASM'!G33),'Input ASM'!G33,0)
A30: FX Gains/(Losses) | B30: =IF(ISNUMBER('Input ASM'!B37),'Input ASM'!B37,0) | C30: =IF(ISNUMBER('Input ASM'!C37),'Input ASM'!C37,0) | D30: =IF(ISNUMBER('Input ASM'!D37),'Input ASM'!D37,0) | E30: =IF(ISNUMBER('Input ASM'!E37),'Input ASM'!E37,0) | F30: =IF(ISNUMBER('Input ASM'!F37),'Input ASM'!F37,0) | G30: =IF(ISNUMBER('Input ASM'!G37),'Input ASM'!G37,0)
A31: Profit Before Tax | B31: =B25+B27+B28+B29+B30 | C31: =C25+C27+C28+C29+C30 | D31: =D25+D27+D28+D29+D30 | E31: =E25+E27+E28+E29+E30 | F31: =F25+F27+F28+F29+F30 | G31: =G25+G27+G28+G29+G30
A32: Tax Expense | B32: =IF(ISNUMBER('Input ASM'!B45),'Input ASM'!B45,0) | C32: =IF(ISNUMBER('Input ASM'!C45),'Input ASM'!C45,0) | D32: =IF(ISNUMBER('Input ASM'!D45),'Input ASM'!D45,0) | E32: =IF(ISNUMBER('Input ASM'!E45),'Input ASM'!E45,0) | F32: =IF(ISNUMBER('Input ASM'!F45),'Input ASM'!F45,0) | G32: =IF(ISNUMBER('Input ASM'!G45),'Input ASM'!G45,0)
A33: Net Income | B33: =B31-B32 | C33: =C31-C32 | D33: =D31-D32 | E33: =E31-E32 | F33: =F31-F32 | G33: =G31-G32
A35: Effective Tax Rate | B35: =IF(B31<>0,B32/B31,0) | C35: =IF(C31<>0,C32/C31,0) | D35: =IF(D31<>0,D32/D31,0) | E35: =IF(E31<>0,E32/E31,0) | F35: =IF(F31<>0,F32/F31,0) | G35: =IF(G31<>0,G32/G31,0)
A36: NOPAT | B36: =B17*(1-B35) | C36: =C17*(1-C35) | D36: =D17*(1-D35) | E36: =E17*(1-E35) | F36: =F17*(1-F35) | G36: =G17*(1-G35)
A38: Shares Outstanding (diluted) | B38: =IF(ISNUMBER('Input ASM'!B57),'Input ASM'!B57,0) | C38: =IF(ISNUMBER('Input ASM'!C57),'Input ASM'!C57,0) | D38: =IF(ISNUMBER('Input ASM'!D57),'Input ASM'!D57,0) | E38: =IF(ISNUMBER('Input ASM'!E57),'Input ASM'!E57,0) | F38: =IF(ISNUMBER('Input ASM'!F57),'Input ASM'!F57,0) | G38: =IF(ISNUMBER('Input ASM'!G57),'Input ASM'!G57,0)
A39: EPS (diluted) | B39: =IF(B38<>0,B33/B38*1000,0) | C39: =IF(C38<>0,C33/C38*1000,0) | D39: =IF(D38<>0,D33/D38*1000,0) | E39: =IF(E38<>0,E33/E38*1000,0) | F39: =IF(F38<>0,F33/F38*1000,0) | G39: =IF(G38<>0,G33/G38*1000,0)
A40: Dividends per Share | B40: =IF(ISNUMBER('Input ASM'!B60),'Input ASM'!B60,0) | C40: =IF(ISNUMBER('Input ASM'!C60),'Input ASM'!C60,0) | D40: =IF(ISNUMBER('Input ASM'!D60),'Input ASM'!D60,0) | E40: =IF(ISNUMBER('Input ASM'!E60),'Input ASM'!E60,0) | F40: =IF(ISNUMBER('Input ASM'!F60),'Input ASM'!F60,0) | G40: =IF(ISNUMBER('Input ASM'!G60),'Input ASM'!G60,0)
A43: BALANCE SHEET (Reformulated)
A44: Operating Working Capital:
A45: Trade Receivables | B45: =IF(ISNUMBER('Input ASM'!B167),'Input ASM'!B167,0) | C45: =IF(ISNUMBER('Input ASM'!C167),'Input ASM'!C167,0) | D45: =IF(ISNUMBER('Input ASM'!D167),'Input ASM'!D167,0) | E45: =IF(ISNUMBER('Input ASM'!E167),'Input ASM'!E167,0) | F45: =IF(ISNUMBER('Input ASM'!F167),'Input ASM'!F167,0) | G45: =IF(ISNUMBER('Input ASM'!G167),'Input ASM'!G167,0)
A46: + Other Receivables | B46: =IF(ISNUMBER('Input ASM'!B168),'Input ASM'!B168,0) | C46: =IF(ISNUMBER('Input ASM'!C168),'Input ASM'!C168,0) | D46: =IF(ISNUMBER('Input ASM'!D168),'Input ASM'!D168,0) | E46: =IF(ISNUMBER('Input ASM'!E168),'Input ASM'!E168,0) | F46: =IF(ISNUMBER('Input ASM'!F168),'Input ASM'!F168,0) | G46: =IF(ISNUMBER('Input ASM'!G168),'Input ASM'!G168,0)
A47: + Inventories | B47: =IF(ISNUMBER('Input ASM'!B170),'Input ASM'!B170,0) | C47: =IF(ISNUMBER('Input ASM'!C170),'Input ASM'!C170,0) | D47: =IF(ISNUMBER('Input ASM'!D170),'Input ASM'!D170,0) | E47: =IF(ISNUMBER('Input ASM'!E170),'Input ASM'!E170,0) | F47: =IF(ISNUMBER('Input ASM'!F170),'Input ASM'!F170,0) | G47: =IF(ISNUMBER('Input ASM'!G170),'Input ASM'!G170,0)
A48: + Prepaid & Other CA | B48: =IF(ISNUMBER('Input ASM'!B171),'Input ASM'!B171,0)+IF(ISNUMBER('Input ASM'!B172),'Input ASM'!B172,0) | C48: =IF(ISNUMBER('Input ASM'!C171),'Input ASM'!C171,0)+IF(ISNUMBER('Input ASM'!C172),'Input ASM'!C172,0) | D48: =IF(ISNUMBER('Input ASM'!D171),'Input ASM'!D171,0)+IF(ISNUMBER('Input ASM'!D172),'Input ASM'!D172,0) | E48: =IF(ISNUMBER('Input ASM'!E171),'Input ASM'!E171,0)+IF(ISNUMBER('Input ASM'!E172),'Input ASM'!E172,0) | F48: =IF(ISNUMBER('Input ASM'!F171),'Input ASM'!F171,0)+IF(ISNUMBER('Input ASM'!F172),'Input ASM'!F172,0) | G48: =IF(ISNUMBER('Input ASM'!G171),'Input ASM'!G171,0)+IF(ISNUMBER('Input ASM'!G172),'Input ASM'!G172,0)
A49: - Accounts Payable | B49: =IF(ISNUMBER('Input ASM'!B185),'Input ASM'!B185,0) | C49: =IF(ISNUMBER('Input ASM'!C185),'Input ASM'!C185,0) | D49: =IF(ISNUMBER('Input ASM'!D185),'Input ASM'!D185,0) | E49: =IF(ISNUMBER('Input ASM'!E185),'Input ASM'!E185,0) | F49: =IF(ISNUMBER('Input ASM'!F185),'Input ASM'!F185,0) | G49: =IF(ISNUMBER('Input ASM'!G185),'Input ASM'!G185,0)
A50: - Accrued Expenses | B50: =IF(ISNUMBER('Input ASM'!B186),'Input ASM'!B186,0) | C50: =IF(ISNUMBER('Input ASM'!C186),'Input ASM'!C186,0) | D50: =IF(ISNUMBER('Input ASM'!D186),'Input ASM'!D186,0) | E50: =IF(ISNUMBER('Input ASM'!E186),'Input ASM'!E186,0) | F50: =IF(ISNUMBER('Input ASM'!F186),'Input ASM'!F186,0) | G50: =IF(ISNUMBER('Input ASM'!G186),'Input ASM'!G186,0)
A51: - Unearned Revenue / Contract Liabilities | B51: =IF(ISNUMBER('Input ASM'!B189),'Input ASM'!B189,0) | C51: =IF(ISNUMBER('Input ASM'!C189),'Input ASM'!C189,0) | D51: =IF(ISNUMBER('Input ASM'!D189),'Input ASM'!D189,0) | E51: =IF(ISNUMBER('Input ASM'!E189),'Input ASM'!E189,0) | F51: =IF(ISNUMBER('Input ASM'!F189),'Input ASM'!F189,0) | G51: =IF(ISNUMBER('Input ASM'!G189),'Input ASM'!G189,0)
A52: - Income Taxes Payable | B52: =IF(ISNUMBER('Input ASM'!B188),'Input ASM'!B188,0) | C52: =IF(ISNUMBER('Input ASM'!C188),'Input ASM'!C188,0) | D52: =IF(ISNUMBER('Input ASM'!D188),'Input ASM'!D188,0) | E52: =IF(ISNUMBER('Input ASM'!E188),'Input ASM'!E188,0) | F52: =IF(ISNUMBER('Input ASM'!F188),'Input ASM'!F188,0) | G52: =IF(ISNUMBER('Input ASM'!G188),'Input ASM'!G188,0)
A53: - Other Current Liabilities | B53: =IF(ISNUMBER('Input ASM'!B190),'Input ASM'!B190,0) | C53: =IF(ISNUMBER('Input ASM'!C190),'Input ASM'!C190,0) | D53: =IF(ISNUMBER('Input ASM'!D190),'Input ASM'!D190,0) | E53: =IF(ISNUMBER('Input ASM'!E190),'Input ASM'!E190,0) | F53: =IF(ISNUMBER('Input ASM'!F190),'Input ASM'!F190,0) | G53: =IF(ISNUMBER('Input ASM'!G190),'Input ASM'!G190,0)
A54: =Operating Working Capital | B54: =B45+B46+B47+B48-B49-B50-B51-B52-B53 | C54: =C45+C46+C47+C48-C49-C50-C51-C52-C53 | D54: =D45+D46+D47+D48-D49-D50-D51-D52-D53 | E54: =E45+E46+E47+E48-E49-E50-E51-E52-E53 | F54: =F45+F46+F47+F48-F49-F50-F51-F52-F53 | G54: =G45+G46+G47+G48-G49-G50-G51-G52-G53
A56: Net Non-Current Operating Assets:
A57: PP&E (net, incl. ROU) | B57: =IF(ISNUMBER('Input ASM'!B176),'Input ASM'!B176,0) | C57: =IF(ISNUMBER('Input ASM'!C176),'Input ASM'!C176,0) | D57: =IF(ISNUMBER('Input ASM'!D176),'Input ASM'!D176,0) | E57: =IF(ISNUMBER('Input ASM'!E176),'Input ASM'!E176,0) | F57: =IF(ISNUMBER('Input ASM'!F176),'Input ASM'!F176,0) | G57: =IF(ISNUMBER('Input ASM'!G176),'Input ASM'!G176,0)
A58: + Goodwill | B58: =IF(ISNUMBER('Input ASM'!B178),'Input ASM'!B178,0) | C58: =IF(ISNUMBER('Input ASM'!C178),'Input ASM'!C178,0) | D58: =IF(ISNUMBER('Input ASM'!D178),'Input ASM'!D178,0) | E58: =IF(ISNUMBER('Input ASM'!E178),'Input ASM'!E178,0) | F58: =IF(ISNUMBER('Input ASM'!F178),'Input ASM'!F178,0) | G58: =IF(ISNUMBER('Input ASM'!G178),'Input ASM'!G178,0)
A59: + Other Intangible Assets | B59: =IF(ISNUMBER('Input ASM'!B179),'Input ASM'!B179,0) | C59: =IF(ISNUMBER('Input ASM'!C179),'Input ASM'!C179,0) | D59: =IF(ISNUMBER('Input ASM'!D179),'Input ASM'!D179,0) | E59: =IF(ISNUMBER('Input ASM'!E179),'Input ASM'!E179,0) | F59: =IF(ISNUMBER('Input ASM'!F179),'Input ASM'!F179,0) | G59: =IF(ISNUMBER('Input ASM'!G179),'Input ASM'!G179,0)
A60: + Deferred Tax Assets | B60: =IF(ISNUMBER('Input ASM'!B180),'Input ASM'!B180,0) | C60: =IF(ISNUMBER('Input ASM'!C180),'Input ASM'!C180,0) | D60: =IF(ISNUMBER('Input ASM'!D180),'Input ASM'!D180,0) | E60: =IF(ISNUMBER('Input ASM'!E180),'Input ASM'!E180,0) | F60: =IF(ISNUMBER('Input ASM'!F180),'Input ASM'!F180,0) | G60: =IF(ISNUMBER('Input ASM'!G180),'Input ASM'!G180,0)
A61: + Deferred Charges & LT Intangibles | B61: =IF(ISNUMBER('Input ASM'!B181),'Input ASM'!B181,0) | C61: =IF(ISNUMBER('Input ASM'!C181),'Input ASM'!C181,0) | D61: =IF(ISNUMBER('Input ASM'!D181),'Input ASM'!D181,0) | E61: =IF(ISNUMBER('Input ASM'!E181),'Input ASM'!E181,0) | F61: =IF(ISNUMBER('Input ASM'!F181),'Input ASM'!F181,0) | G61: =IF(ISNUMBER('Input ASM'!G181),'Input ASM'!G181,0)
A62: + Other Non-Current Assets | B62: =IF(ISNUMBER('Input ASM'!B182),'Input ASM'!B182,0) | C62: =IF(ISNUMBER('Input ASM'!C182),'Input ASM'!C182,0) | D62: =IF(ISNUMBER('Input ASM'!D182),'Input ASM'!D182,0) | E62: =IF(ISNUMBER('Input ASM'!E182),'Input ASM'!E182,0) | F62: =IF(ISNUMBER('Input ASM'!F182),'Input ASM'!F182,0) | G62: =IF(ISNUMBER('Input ASM'!G182),'Input ASM'!G182,0)
A63: - Deferred Tax Liabilities | B63: =IF(ISNUMBER('Input ASM'!B193),'Input ASM'!B193,0) | C63: =IF(ISNUMBER('Input ASM'!C193),'Input ASM'!C193,0) | D63: =IF(ISNUMBER('Input ASM'!D193),'Input ASM'!D193,0) | E63: =IF(ISNUMBER('Input ASM'!E193),'Input ASM'!E193,0) | F63: =IF(ISNUMBER('Input ASM'!F193),'Input ASM'!F193,0) | G63: =IF(ISNUMBER('Input ASM'!G193),'Input ASM'!G193,0)
A64: - Other Non-Current Liabilities | B64: =IF(ISNUMBER('Input ASM'!B194),'Input ASM'!B194,0) | C64: =IF(ISNUMBER('Input ASM'!C194),'Input ASM'!C194,0) | D64: =IF(ISNUMBER('Input ASM'!D194),'Input ASM'!D194,0) | E64: =IF(ISNUMBER('Input ASM'!E194),'Input ASM'!E194,0) | F64: =IF(ISNUMBER('Input ASM'!F194),'Input ASM'!F194,0) | G64: =IF(ISNUMBER('Input ASM'!G194),'Input ASM'!G194,0)
A65: =Net Non-Current Operating Assets | B65: =B57+B58+B59+B60+B61+B62-B63-B64 | C65: =C57+C58+C59+C60+C61+C62-C63-C64 | D65: =D57+D58+D59+D60+D61+D62-D63-D64 | E65: =E57+E58+E59+E60+E61+E62-E63-E64 | F65: =F57+F58+F59+F60+F61+F62-F63-F64 | G65: =G57+G58+G59+G60+G61+G62-G63-G64
A67: =Net Operating Assets | B67: =B54+B65 | C67: =C54+C65 | D67: =D54+D65 | E67: =E54+E65 | F67: =F54+F65 | G67: =G54+G65
A69: Investment Assets:
A70: Long-Term Investments | B70: =IF(ISNUMBER('Input ASM'!B177),'Input ASM'!B177,0) | C70: =IF(ISNUMBER('Input ASM'!C177),'Input ASM'!C177,0) | D70: =IF(ISNUMBER('Input ASM'!D177),'Input ASM'!D177,0) | E70: =IF(ISNUMBER('Input ASM'!E177),'Input ASM'!E177,0) | F70: =IF(ISNUMBER('Input ASM'!F177),'Input ASM'!F177,0) | G70: =IF(ISNUMBER('Input ASM'!G177),'Input ASM'!G177,0)
A71: =Total Investment Assets | B71: =B70 | C71: =C70 | D71: =D70 | E71: =E70 | F71: =F70 | G71: =G70
A73: =Business Assets | B73: =B67+B71 | C73: =C67+C71 | D73: =D67+D71 | E73: =E67+E71 | F73: =F67+F71 | G73: =G67+G71
A75: FINANCING
A76: Lease Liabilities (current) | B76: =IF(ISNUMBER('Input ASM'!B187),'Input ASM'!B187,0) | C76: =IF(ISNUMBER('Input ASM'!C187),'Input ASM'!C187,0) | D76: =IF(ISNUMBER('Input ASM'!D187),'Input ASM'!D187,0) | E76: =IF(ISNUMBER('Input ASM'!E187),'Input ASM'!E187,0) | F76: =IF(ISNUMBER('Input ASM'!F187),'Input ASM'!F187,0) | G76: =IF(ISNUMBER('Input ASM'!G187),'Input ASM'!G187,0)
A77: + Lease Liabilities (non-current) | B77: =IF(ISNUMBER('Input ASM'!B192),'Input ASM'!B192,0) | C77: =IF(ISNUMBER('Input ASM'!C192),'Input ASM'!C192,0) | D77: =IF(ISNUMBER('Input ASM'!D192),'Input ASM'!D192,0) | E77: =IF(ISNUMBER('Input ASM'!E192),'Input ASM'!E192,0) | F77: =IF(ISNUMBER('Input ASM'!F192),'Input ASM'!F192,0) | G77: =IF(ISNUMBER('Input ASM'!G192),'Input ASM'!G192,0)
A78: =Total Debt | B78: =B76+B77 | C78: =C76+C77 | D78: =D76+D77 | E78: =E76+E77 | F78: =F76+F77 | G78: =G76+G77
A79: Cash & Equivalents | B79: =IF(ISNUMBER('Input ASM'!B166),'Input ASM'!B166,0) | C79: =IF(ISNUMBER('Input ASM'!C166),'Input ASM'!C166,0) | D79: =IF(ISNUMBER('Input ASM'!D166),'Input ASM'!D166,0) | E79: =IF(ISNUMBER('Input ASM'!E166),'Input ASM'!E166,0) | F79: =IF(ISNUMBER('Input ASM'!F166),'Input ASM'!F166,0) | G79: =IF(ISNUMBER('Input ASM'!G166),'Input ASM'!G166,0)
A80: =Net Debt | B80: =B78-B79 | C80: =C78-C79 | D80: =D78-D79 | E80: =E78-E79 | F80: =F78-F79 | G80: =G78-G79
A81: Group Equity | B81: =IF(ISNUMBER('Input ASM'!B203),'Input ASM'!B203,0) | C81: =IF(ISNUMBER('Input ASM'!C203),'Input ASM'!C203,0) | D81: =IF(ISNUMBER('Input ASM'!D203),'Input ASM'!D203,0) | E81: =IF(ISNUMBER('Input ASM'!E203),'Input ASM'!E203,0) | F81: =IF(ISNUMBER('Input ASM'!F203),'Input ASM'!F203,0) | G81: =IF(ISNUMBER('Input ASM'!G203),'Input ASM'!G203,0)
A82: =Invested Capital | B82: =B80+B81 | C82: =C80+C81 | D82: =D80+D81 | E82: =E80+E81 | F82: =F80+F81 | G82: =G80+G81
A83: BS Check (should = 0) | B83: =B73-B82 | C83: =C73-C82 | D83: =D73-D82 | E83: =E73-E82 | F83: =F73-F82 | G83: =G73-G82
A86: FREE CASH FLOW
A87: NOPAT | B87: =B36 | C87: =C36 | D87: =D36 | E87: =E36 | F87: =F36 | G87: =G36
A88: + D&A | B88: =IF(ISNUMBER('Input ASM'!B113),'Input ASM'!B113,0) | C88: =IF(ISNUMBER('Input ASM'!C113),'Input ASM'!C113,0) | D88: =IF(ISNUMBER('Input ASM'!D113),'Input ASM'!D113,0) | E88: =IF(ISNUMBER('Input ASM'!E113),'Input ASM'!E113,0) | F88: =IF(ISNUMBER('Input ASM'!F113),'Input ASM'!F113,0) | G88: =IF(ISNUMBER('Input ASM'!G113),'Input ASM'!G113,0)
A89: - Change in OWC | B89: 0 | C89: =C54-B54 | D89: =D54-C54 | E89: =E54-D54 | F89: =F54-E54 | G89: =G54-F54
A90: - CapEx | B90: =ABS(IF(ISNUMBER('Input ASM'!B127),'Input ASM'!B127,0)) | C90: =ABS(IF(ISNUMBER('Input ASM'!C127),'Input ASM'!C127,0)) | D90: =ABS(IF(ISNUMBER('Input ASM'!D127),'Input ASM'!D127,0)) | E90: =ABS(IF(ISNUMBER('Input ASM'!E127),'Input ASM'!E127,0)) | F90: =ABS(IF(ISNUMBER('Input ASM'!F127),'Input ASM'!F127,0)) | G90: =ABS(IF(ISNUMBER('Input ASM'!G127),'Input ASM'!G127,0))
A91: - Purchase of Intangibles | B91: =ABS(IF(ISNUMBER('Input ASM'!B130),'Input ASM'!B130,0)) | C91: =ABS(IF(ISNUMBER('Input ASM'!C130),'Input ASM'!C130,0)) | D91: =ABS(IF(ISNUMBER('Input ASM'!D130),'Input ASM'!D130,0)) | E91: =ABS(IF(ISNUMBER('Input ASM'!E130),'Input ASM'!E130,0)) | F91: =ABS(IF(ISNUMBER('Input ASM'!F130),'Input ASM'!F130,0)) | G91: =ABS(IF(ISNUMBER('Input ASM'!G130),'Input ASM'!G130,0))
A92: =Operating CF after investment | B92: =B87+B88-B89-B90-B91 | C92: =C87+C88-C89-C90-C91 | D92: =D87+D88-D89-D90-D91 | E92: =E87+E88-E89-E90-E91 | F92: =F87+F88-F89-F90-F91 | G92: =G87+G88-G89-G90-G91
A94: + Net Investment Profit after tax | B94: =B27*(1-B35) | C94: =C27*(1-C35) | D94: =D27*(1-D35) | E94: =E27*(1-E35) | F94: =F27*(1-F35) | G94: =G27*(1-G35)
A95: - Change in Investment Assets | B95: 0 | C95: =C71-B71 | D95: =D71-C71 | E95: =E71-D71 | F95: =F71-E71 | G95: =G71-F71
A96: =FCF to Debt & Equity | B96: =B92+B94-B95 | C96: =C92+C94-C95 | D96: =D92+D94-D95 | E96: =E92+E94-E95 | F96: =F92+F94-F95 | G96: =G92+G94-G95
A97: - Interest Expense after tax | B97: =B29*(1-B35) | C97: =C29*(1-C35) | D97: =D29*(1-D35) | E97: =E29*(1-E35) | F97: =F29*(1-F35) | G97: =G29*(1-G35)
A98: + Change in Debt | B98: 0 | C98: =C78-B78 | D98: =D78-C78 | E98: =E78-D78 | F98: =F78-E78 | G98: =G78-F78
A99: =FCF to Equity | B99: =B96-B97+B98 | C99: =C96-C97+C98 | D99: =D96-D97+D98 | E99: =E96-E97+E98 | F99: =F96-F97+F98 | G99: =G96-G97+G98

Sheet Std AIXTRON
A1: Standardized Financial Statements - AIXTRON SE
A2: (EUR 000)
B3: 2019 | C3: 2020 | D3: 2021 | E3: 2022 | F3: 2023 | G3: 2024
A5: Operating cash % | B5: 0.02 | C5: 0.02 | D5: 0.02 | E5: 0.02 | F5: 0.02 | G5: 0.02
A6: Tax rate (effective) | B6: =IF(ISNUMBER('Input AIXTRON'!B68),'Input AIXTRON'!B68,0) | C6: =IF(ISNUMBER('Input AIXTRON'!C68),'Input AIXTRON'!C68,0) | D6: =IF(ISNUMBER('Input AIXTRON'!D68),'Input AIXTRON'!D68,0) | E6: =IF(ISNUMBER('Input AIXTRON'!E68),'Input AIXTRON'!E68,0) | F6: =IF(ISNUMBER('Input AIXTRON'!F68),'Input AIXTRON'!F68,0) | G6: =IF(ISNUMBER('Input AIXTRON'!G68),'Input AIXTRON'!G68,0)
A8: INCOME STATEMENT
A9: Revenue | B9: =IF(ISNUMBER('Input AIXTRON'!B21),'Input AIXTRON'!B21,0) | C9: =IF(ISNUMBER('Input AIXTRON'!C21),'Input AIXTRON'!C21,0) | D9: =IF(ISNUMBER('Input AIXTRON'!D21),'Input AIXTRON'!D21,0) | E9: =IF(ISNUMBER('Input AIXTRON'!E21),'Input AIXTRON'!E21,0) | F9: =IF(ISNUMBER('Input AIXTRON'!F21),'Input AIXTRON'!F21,0) | G9: =IF(ISNUMBER('Input AIXTRON'!G21),'Input AIXTRON'!G21,0)
A10: Cost of Sales | B10: =IF(ISNUMBER('Input AIXTRON'!B23),'Input AIXTRON'!B23,0) | C10: =IF(ISNUMBER('Input AIXTRON'!C23),'Input AIXTRON'!C23,0) | D10: =IF(ISNUMBER('Input AIXTRON'!D23),'Input AIXTRON'!D23,0) | E10: =IF(ISNUMBER('Input AIXTRON'!E23),'Input AIXTRON'!E23,0) | F10: =IF(ISNUMBER('Input AIXTRON'!F23),'Input AIXTRON'!F23,0) | G10: =IF(ISNUMBER('Input AIXTRON'!G23),'Input AIXTRON'!G23,0)
A11: Gross Profit | B11: =B9-B10 | C11: =C9-C10 | D11: =D9-D10 | E11: =E9-E10 | F11: =F9-F10 | G11: =G9-G10
A12: SG&A | B12: =IF(ISNUMBER('Input AIXTRON'!B26),'Input AIXTRON'!B26,0) | C12: =IF(ISNUMBER('Input AIXTRON'!C26),'Input AIXTRON'!C26,0) | D12: =IF(ISNUMBER('Input AIXTRON'!D26),'Input AIXTRON'!D26,0) | E12: =IF(ISNUMBER('Input AIXTRON'!E26),'Input AIXTRON'!E26,0) | F12: =IF(ISNUMBER('Input AIXTRON'!F26),'Input AIXTRON'!F26,0) | G12: =IF(ISNUMBER('Input AIXTRON'!G26),'Input AIXTRON'!G26,0)
A13: R&D | B13: =IF(ISNUMBER('Input AIXTRON'!B27),'Input AIXTRON'!B27,0) | C13: =IF(ISNUMBER('Input AIXTRON'!C27),'Input AIXTRON'!C27,0) | D13: =IF(ISNUMBER('Input AIXTRON'!D27),'Input AIXTRON'!D27,0) | E13: =IF(ISNUMBER('Input AIXTRON'!E27),'Input AIXTRON'!E27,0) | F13: =IF(ISNUMBER('Input AIXTRON'!F27),'Input AIXTRON'!F27,0) | G13: =IF(ISNUMBER('Input AIXTRON'!G27),'Input AIXTRON'!G27,0)
A14: Depreciation & Amortization | B14: =IF(ISNUMBER('Input AIXTRON'!B111),'Input AIXTRON'!B111,0) | C14: =IF(ISNUMBER('Input AIXTRON'!C111),'Input AIXTRON'!C111,0) | D14: =IF(ISNUMBER('Input AIXTRON'!D111),'Input AIXTRON'!D111,0) | E14: =IF(ISNUMBER('Input AIXTRON'!E111),'Input AIXTRON'!E111,0) | F14: =IF(ISNUMBER('Input AIXTRON'!F111),'Input AIXTRON'!F111,0) | G14: =IF(ISNUMBER('Input AIXTRON'!G111),'Input AIXTRON'!G111,0)
A15: Other Operating Expense | B15: =IF(ISNUMBER('Input AIXTRON'!B28),'Input AIXTRON'!B28,0) | C15: =IF(ISNUMBER('Input AIXTRON'!C28),'Input AIXTRON'!C28,0) | D15: =IF(ISNUMBER('Input AIXTRON'!D28),'Input AIXTRON'!D28,0) | E15: =IF(ISNUMBER('Input AIXTRON'!E28),'Input AIXTRON'!E28,0) | F15: =IF(ISNUMBER('Input AIXTRON'!F28),'Input AIXTRON'!F28,0) | G15: =IF(ISNUMBER('Input AIXTRON'!G28),'Input AIXTRON'!G28,0)
A16: Total Operating Expense | B16: =B10+B12+B13+B14+B15 | C16: =C10+C12+C13+C14+C15 | D16: =D10+D12+D13+D14+D15 | E16: =E10+E12+E13+E14+E15 | F16: =F10+F12+F13+F14+F15 | G16: =G10+G12+G13+G14+G15
A17: Recurring Operating Profit | B17: =B9-B16 | C17: =C9-C16 | D17: =D9-D16 | E17: =E9-E16 | F17: =F9-F16 | G17: =G9-G16
A19: Non-recurring items:
A20: Gain/Loss on Sale of Investments | B20: =IF(ISNUMBER('Input AIXTRON'!B38),'Input AIXTRON'!B38,0) | C20: =IF(ISNUMBER('Input AIXTRON'!C38),'Input AIXTRON'!C38,0) | D20: =IF(ISNUMBER('Input AIXTRON'!D38),'Input AIXTRON'!D38,0) | E20: =IF(ISNUMBER('Input AIXTRON'!E38),'Input AIXTRON'!E38,0) | F20: =IF(ISNUMBER('Input AIXTRON'!F38),'Input AIXTRON'!F38,0) | G20: =IF(ISNUMBER('Input AIXTRON'!G38),'Input AIXTRON'!G38,0)
A21: Gain/Loss on Sale of Assets | B21: =IF(ISNUMBER('Input AIXTRON'!B39),'Input AIXTRON'!B39,0) | C21: =IF(ISNUMBER('Input AIXTRON'!C39),'Input AIXTRON'!C39,0) | D21: =IF(ISNUMBER('Input AIXTRON'!D39),'Input AIXTRON'!D39,0) | E21: =IF(ISNUMBER('Input AIXTRON'!E39),'Input AIXTRON'!E39,0) | F21: =IF(ISNUMBER('Input AIXTRON'!F39),'Input AIXTRON'!F39,0) | G21: =IF(ISNUMBER('Input AIXTRON'!G39),'Input AIXTRON'!G39,0)
A22: Asset Writedown | B22: =IF(ISNUMBER('Input AIXTRON'!B40),'Input AIXTRON'!B40,0) | C22: =IF(ISNUMBER('Input AIXTRON'!C40),'Input AIXTRON'!C40,0) | D22: =IF(ISNUMBER('Input AIXTRON'!D40),'Input AIXTRON'!D40,0) | E22: =IF(ISNUMBER('Input AIXTRON'!E40),'Input AIXTRON'!E40,0) | F22: =IF(ISNUMBER('Input AIXTRON'!F40),'Input AIXTRON'!F40,0) | G22: =IF(ISNUMBER('Input AIXTRON'!G40),'Input AIXTRON'!G40,0)
A23: Other Unusual Items | B23: =IF(ISNUMBER('Input AIXTRON'!B37),'Input AIXTRON'!B37,0)+IF(ISNUMBER('Input AIXTRON'!B41),'Input AIXTRON'!B41,0) | C23: =IF(ISNUMBER('Input AIXTRON'!C37),'Input AIXTRON'!C37,0)+IF(ISNUMBER('Input AIXTRON'!C41),'Input AIXTRON'!C41,0) | D23: =IF(ISNUMBER('Input AIXTRON'!D37),'Input AIXTRON'!D37,0)+IF(ISNUMBER('Input AIXTRON'!D41),'Input AIXTRON'!D41,0) | E23: =IF(ISNUMBER('Input AIXTRON'!E37),'Input AIXTRON'!E37,0)+IF(ISNUMBER('Input AIXTRON'!E41),'Input AIXTRON'!E41,0) | F23: =IF(ISNUMBER('Input AIXTRON'!F37),'Input AIXTRON'!F37,0)+IF(ISNUMBER('Input AIXTRON'!F41),'Input AIXTRON'!F41,0) | G23: =IF(ISNUMBER('Input AIXTRON'!G37),'Input AIXTRON'!G37,0)+IF(ISNUMBER('Input AIXTRON'!G41),'Input AIXTRON'!G41,0)
A24: Total Non-recurring | B24: =SUM(B20:B23) | C24: =SUM(C20:C23) | D24: =SUM(D20:D23) | E24: =SUM(E20:E23) | F24: =SUM(F20:F23) | G24: =SUM(G20:G23)
A25: EBIT | B25: =B17+B24 | C25: =C17+C24 | D25: =D17+D24 | E25: =E17+E24 | F25: =F17+F24 | G25: =G17+G24
A27: Investment Income (Equity Method) | B27: 0 | C27: 0 | D27: 0 | E27: 0 | F27: 0 | G27: 0
A28: Interest Income | B28: =IF(ISNUMBER('Input AIXTRON'!B33),'Input AIXTRON'!B33,0) | C28: =IF(ISNUMBER('Input AIXTRON'!C33),'Input AIXTRON'!C33,0) | D28: =IF(ISNUMBER('Input AIXTRON'!D33),'Input AIXTRON'!D33,0) | E28: =IF(ISNUMBER('Input AIXTRON'!E33),'Input AIXTRON'!E33,0) | F28: =IF(ISNUMBER('Input AIXTRON'!F33),'Input AIXTRON'!F33,0) | G28: =IF(ISNUMBER('Input AIXTRON'!G33),'Input AIXTRON'!G33,0)
A29: Interest Expense | B29: =IF(ISNUMBER('Input AIXTRON'!B32),'Input AIXTRON'!B32,0) | C29: =IF(ISNUMBER('Input AIXTRON'!C32),'Input AIXTRON'!C32,0) | D29: =IF(ISNUMBER('Input AIXTRON'!D32),'Input AIXTRON'!D32,0) | E29: =IF(ISNUMBER('Input AIXTRON'!E32),'Input AIXTRON'!E32,0) | F29: =IF(ISNUMBER('Input AIXTRON'!F32),'Input AIXTRON'!F32,0) | G29: =IF(ISNUMBER('Input AIXTRON'!G32),'Input AIXTRON'!G32,0)
A30: FX Gains/(Losses) | B30: =IF(ISNUMBER('Input AIXTRON'!B35),'Input AIXTRON'!B35,0) | C30: =IF(ISNUMBER('Input AIXTRON'!C35),'Input AIXTRON'!C35,0) | D30: =IF(ISNUMBER('Input AIXTRON'!D35),'Input AIXTRON'!D35,0) | E30: =IF(ISNUMBER('Input AIXTRON'!E35),'Input AIXTRON'!E35,0) | F30: =IF(ISNUMBER('Input AIXTRON'!F35),'Input AIXTRON'!F35,0) | G30: =IF(ISNUMBER('Input AIXTRON'!G35),'Input AIXTRON'!G35,0)
A31: Profit Before Tax | B31: =B25+B27+B28+B29+B30 | C31: =C25+C27+C28+C29+C30 | D31: =D25+D27+D28+D29+D30 | E31: =E25+E27+E28+E29+E30 | F31: =F25+F27+F28+F29+F30 | G31: =G25+G27+G28+G29+G30
A32: Tax Expense | B32: =IF(ISNUMBER('Input AIXTRON'!B44),'Input AIXTRON'!B44,0) | C32: =IF(ISNUMBER('Input AIXTRON'!C44),'Input AIXTRON'!C44,0) | D32: =IF(ISNUMBER('Input AIXTRON'!D44),'Input AIXTRON'!D44,0) | E32: =IF(ISNUMBER('Input AIXTRON'!E44),'Input AIXTRON'!E44,0) | F32: =IF(ISNUMBER('Input AIXTRON'!F44),'Input AIXTRON'!F44,0) | G32: =IF(ISNUMBER('Input AIXTRON'!G44),'Input AIXTRON'!G44,0)
A33: Net Income | B33: =B31-B32 | C33: =C31-C32 | D33: =D31-D32 | E33: =E31-E32 | F33: =F31-F32 | G33: =G31-G32
A35: Effective Tax Rate | B35: =IF(B31<>0,B32/B31,0) | C35: =IF(C31<>0,C32/C31,0) | D35: =IF(D31<>0,D32/D31,0) | E35: =IF(E31<>0,E32/E31,0) | F35: =IF(F31<>0,F32/F31,0) | G35: =IF(G31<>0,G32/G31,0)
A36: NOPAT | B36: =B17*(1-B35) | C36: =C17*(1-C35) | D36: =D17*(1-D35) | E36: =E17*(1-E35) | F36: =F17*(1-F35) | G36: =G17*(1-G35)
A38: Shares Outstanding (diluted) | B38: =IF(ISNUMBER('Input AIXTRON'!B57),'Input AIXTRON'!B57,0) | C38: =IF(ISNUMBER('Input AIXTRON'!C57),'Input AIXTRON'!C57,0) | D38: =IF(ISNUMBER('Input AIXTRON'!D57),'Input AIXTRON'!D57,0) | E38: =IF(ISNUMBER('Input AIXTRON'!E57),'Input AIXTRON'!E57,0) | F38: =IF(ISNUMBER('Input AIXTRON'!F57),'Input AIXTRON'!F57,0) | G38: =IF(ISNUMBER('Input AIXTRON'!G57),'Input AIXTRON'!G57,0)
A39: EPS (diluted) | B39: =IF(B38<>0,B33/B38*1000,0) | C39: =IF(C38<>0,C33/C38*1000,0) | D39: =IF(D38<>0,D33/D38*1000,0) | E39: =IF(E38<>0,E33/E38*1000,0) | F39: =IF(F38<>0,F33/F38*1000,0) | G39: =IF(G38<>0,G33/G38*1000,0)
A40: Dividends per Share | B40: =IF(ISNUMBER('Input AIXTRON'!B60),'Input AIXTRON'!B60,0) | C40: =IF(ISNUMBER('Input AIXTRON'!C60),'Input AIXTRON'!C60,0) | D40: =IF(ISNUMBER('Input AIXTRON'!D60),'Input AIXTRON'!D60,0) | E40: =IF(ISNUMBER('Input AIXTRON'!E60),'Input AIXTRON'!E60,0) | F40: =IF(ISNUMBER('Input AIXTRON'!F60),'Input AIXTRON'!F60,0) | G40: =IF(ISNUMBER('Input AIXTRON'!G60),'Input AIXTRON'!G60,0)
A43: BALANCE SHEET (Reformulated)
A44: Operating Working Capital:
A45: Trade Receivables | B45: =IF(ISNUMBER('Input AIXTRON'!B167),'Input AIXTRON'!B167,0) | C45: =IF(ISNUMBER('Input AIXTRON'!C167),'Input AIXTRON'!C167,0) | D45: =IF(ISNUMBER('Input AIXTRON'!D167),'Input AIXTRON'!D167,0) | E45: =IF(ISNUMBER('Input AIXTRON'!E167),'Input AIXTRON'!E167,0) | F45: =IF(ISNUMBER('Input AIXTRON'!F167),'Input AIXTRON'!F167,0) | G45: =IF(ISNUMBER('Input AIXTRON'!G167),'Input AIXTRON'!G167,0)
A46: + Other Receivables | B46: =IF(ISNUMBER('Input AIXTRON'!B168),'Input AIXTRON'!B168,0) | C46: =IF(ISNUMBER('Input AIXTRON'!C168),'Input AIXTRON'!C168,0) | D46: =IF(ISNUMBER('Input AIXTRON'!D168),'Input AIXTRON'!D168,0) | E46: =IF(ISNUMBER('Input AIXTRON'!E168),'Input AIXTRON'!E168,0) | F46: =IF(ISNUMBER('Input AIXTRON'!F168),'Input AIXTRON'!F168,0) | G46: =IF(ISNUMBER('Input AIXTRON'!G168),'Input AIXTRON'!G168,0)
A47: + Inventories | B47: =IF(ISNUMBER('Input AIXTRON'!B170),'Input AIXTRON'!B170,0) | C47: =IF(ISNUMBER('Input AIXTRON'!C170),'Input AIXTRON'!C170,0) | D47: =IF(ISNUMBER('Input AIXTRON'!D170),'Input AIXTRON'!D170,0) | E47: =IF(ISNUMBER('Input AIXTRON'!E170),'Input AIXTRON'!E170,0) | F47: =IF(ISNUMBER('Input AIXTRON'!F170),'Input AIXTRON'!F170,0) | G47: =IF(ISNUMBER('Input AIXTRON'!G170),'Input AIXTRON'!G170,0)
A48: + Prepaid & Other CA | B48: =IF(ISNUMBER('Input AIXTRON'!B171),'Input AIXTRON'!B171,0)+IF(ISNUMBER('Input AIXTRON'!B172),'Input AIXTRON'!B172,0) | C48: =IF(ISNUMBER('Input AIXTRON'!C171),'Input AIXTRON'!C171,0)+IF(ISNUMBER('Input AIXTRON'!C172),'Input AIXTRON'!C172,0) | D48: =IF(ISNUMBER('Input AIXTRON'!D171),'Input AIXTRON'!D171,0)+IF(ISNUMBER('Input AIXTRON'!D172),'Input AIXTRON'!D172,0) | E48: =IF(ISNUMBER('Input AIXTRON'!E171),'Input AIXTRON'!E171,0)+IF(ISNUMBER('Input AIXTRON'!E172),'Input AIXTRON'!E172,0) | F48: =IF(ISNUMBER('Input AIXTRON'!F171),'Input AIXTRON'!F171,0)+IF(ISNUMBER('Input AIXTRON'!F172),'Input AIXTRON'!F172,0) | G48: =IF(ISNUMBER('Input AIXTRON'!G171),'Input AIXTRON'!G171,0)+IF(ISNUMBER('Input AIXTRON'!G172),'Input AIXTRON'!G172,0)
A49: - Accounts Payable | B49: =IF(ISNUMBER('Input AIXTRON'!B184),'Input AIXTRON'!B184,0) | C49: =IF(ISNUMBER('Input AIXTRON'!C184),'Input AIXTRON'!C184,0) | D49: =IF(ISNUMBER('Input AIXTRON'!D184),'Input AIXTRON'!D184,0) | E49: =IF(ISNUMBER('Input AIXTRON'!E184),'Input AIXTRON'!E184,0) | F49: =IF(ISNUMBER('Input AIXTRON'!F184),'Input AIXTRON'!F184,0) | G49: =IF(ISNUMBER('Input AIXTRON'!G184),'Input AIXTRON'!G184,0)
A50: - Accrued Expenses | B50: =IF(ISNUMBER('Input AIXTRON'!B185),'Input AIXTRON'!B185,0) | C50: =IF(ISNUMBER('Input AIXTRON'!C185),'Input AIXTRON'!C185,0) | D50: =IF(ISNUMBER('Input AIXTRON'!D185),'Input AIXTRON'!D185,0) | E50: =IF(ISNUMBER('Input AIXTRON'!E185),'Input AIXTRON'!E185,0) | F50: =IF(ISNUMBER('Input AIXTRON'!F185),'Input AIXTRON'!F185,0) | G50: =IF(ISNUMBER('Input AIXTRON'!G185),'Input AIXTRON'!G185,0)
A51: - Unearned Revenue / Contract Liabilities | B51: =IF(ISNUMBER('Input AIXTRON'!B188),'Input AIXTRON'!B188,0) | C51: =IF(ISNUMBER('Input AIXTRON'!C188),'Input AIXTRON'!C188,0) | D51: =IF(ISNUMBER('Input AIXTRON'!D188),'Input AIXTRON'!D188,0) | E51: =IF(ISNUMBER('Input AIXTRON'!E188),'Input AIXTRON'!E188,0) | F51: =IF(ISNUMBER('Input AIXTRON'!F188),'Input AIXTRON'!F188,0) | G51: =IF(ISNUMBER('Input AIXTRON'!G188),'Input AIXTRON'!G188,0)
A52: - Income Taxes Payable | B52: =IF(ISNUMBER('Input AIXTRON'!B187),'Input AIXTRON'!B187,0) | C52: =IF(ISNUMBER('Input AIXTRON'!C187),'Input AIXTRON'!C187,0) | D52: =IF(ISNUMBER('Input AIXTRON'!D187),'Input AIXTRON'!D187,0) | E52: =IF(ISNUMBER('Input AIXTRON'!E187),'Input AIXTRON'!E187,0) | F52: =IF(ISNUMBER('Input AIXTRON'!F187),'Input AIXTRON'!F187,0) | G52: =IF(ISNUMBER('Input AIXTRON'!G187),'Input AIXTRON'!G187,0)
A53: - Other Current Liabilities | B53: =IF(ISNUMBER('Input AIXTRON'!B189),'Input AIXTRON'!B189,0) | C53: =IF(ISNUMBER('Input AIXTRON'!C189),'Input AIXTRON'!C189,0) | D53: =IF(ISNUMBER('Input AIXTRON'!D189),'Input AIXTRON'!D189,0) | E53: =IF(ISNUMBER('Input AIXTRON'!E189),'Input AIXTRON'!E189,0) | F53: =IF(ISNUMBER('Input AIXTRON'!F189),'Input AIXTRON'!F189,0) | G53: =IF(ISNUMBER('Input AIXTRON'!G189),'Input AIXTRON'!G189,0)
A54: =Operating Working Capital | B54: =B45+B46+B47+B48-B49-B50-B51-B52-B53 | C54: =C45+C46+C47+C48-C49-C50-C51-C52-C53 | D54: =D45+D46+D47+D48-D49-D50-D51-D52-D53 | E54: =E45+E46+E47+E48-E49-E50-E51-E52-E53 | F54: =F45+F46+F47+F48-F49-F50-F51-F52-F53 | G54: =G45+G46+G47+G48-G49-G50-G51-G52-G53
A56: Net Non-Current Operating Assets:
A57: PP&E (net, incl. ROU) | B57: =IF(ISNUMBER('Input AIXTRON'!B176),'Input AIXTRON'!B176,0) | C57: =IF(ISNUMBER('Input AIXTRON'!C176),'Input AIXTRON'!C176,0) | D57: =IF(ISNUMBER('Input AIXTRON'!D176),'Input AIXTRON'!D176,0) | E57: =IF(ISNUMBER('Input AIXTRON'!E176),'Input AIXTRON'!E176,0) | F57: =IF(ISNUMBER('Input AIXTRON'!F176),'Input AIXTRON'!F176,0) | G57: =IF(ISNUMBER('Input AIXTRON'!G176),'Input AIXTRON'!G176,0)
A58: + Goodwill | B58: =IF(ISNUMBER('Input AIXTRON'!B178),'Input AIXTRON'!B178,0) | C58: =IF(ISNUMBER('Input AIXTRON'!C178),'Input AIXTRON'!C178,0) | D58: =IF(ISNUMBER('Input AIXTRON'!D178),'Input AIXTRON'!D178,0) | E58: =IF(ISNUMBER('Input AIXTRON'!E178),'Input AIXTRON'!E178,0) | F58: =IF(ISNUMBER('Input AIXTRON'!F178),'Input AIXTRON'!F178,0) | G58: =IF(ISNUMBER('Input AIXTRON'!G178),'Input AIXTRON'!G178,0)
A59: + Other Intangible Assets | B59: =IF(ISNUMBER('Input AIXTRON'!B179),'Input AIXTRON'!B179,0) | C59: =IF(ISNUMBER('Input AIXTRON'!C179),'Input AIXTRON'!C179,0) | D59: =IF(ISNUMBER('Input AIXTRON'!D179),'Input AIXTRON'!D179,0) | E59: =IF(ISNUMBER('Input AIXTRON'!E179),'Input AIXTRON'!E179,0) | F59: =IF(ISNUMBER('Input AIXTRON'!F179),'Input AIXTRON'!F179,0) | G59: =IF(ISNUMBER('Input AIXTRON'!G179),'Input AIXTRON'!G179,0)
A60: + Deferred Tax Assets | B60: =IF(ISNUMBER('Input AIXTRON'!B180),'Input AIXTRON'!B180,0) | C60: =IF(ISNUMBER('Input AIXTRON'!C180),'Input AIXTRON'!C180,0) | D60: =IF(ISNUMBER('Input AIXTRON'!D180),'Input AIXTRON'!D180,0) | E60: =IF(ISNUMBER('Input AIXTRON'!E180),'Input AIXTRON'!E180,0) | F60: =IF(ISNUMBER('Input AIXTRON'!F180),'Input AIXTRON'!F180,0) | G60: =IF(ISNUMBER('Input AIXTRON'!G180),'Input AIXTRON'!G180,0)
A61: + Deferred Charges & LT Intangibles | B61: 0 | C61: 0 | D61: 0 | E61: 0 | F61: 0 | G61: 0
A62: + Other Non-Current Assets | B62: =IF(ISNUMBER('Input AIXTRON'!B181),'Input AIXTRON'!B181,0) | C62: =IF(ISNUMBER('Input AIXTRON'!C181),'Input AIXTRON'!C181,0) | D62: =IF(ISNUMBER('Input AIXTRON'!D181),'Input AIXTRON'!D181,0) | E62: =IF(ISNUMBER('Input AIXTRON'!E181),'Input AIXTRON'!E181,0) | F62: =IF(ISNUMBER('Input AIXTRON'!F181),'Input AIXTRON'!F181,0) | G62: =IF(ISNUMBER('Input AIXTRON'!G181),'Input AIXTRON'!G181,0)
A63: - Deferred Tax Liabilities | B63: =IF(ISNUMBER('Input AIXTRON'!B192),'Input AIXTRON'!B192,0) | C63: =IF(ISNUMBER('Input AIXTRON'!C192),'Input AIXTRON'!C192,0) | D63: =IF(ISNUMBER('Input AIXTRON'!D192),'Input AIXTRON'!D192,0) | E63: =IF(ISNUMBER('Input AIXTRON'!E192),'Input AIXTRON'!E192,0) | F63: =IF(ISNUMBER('Input AIXTRON'!F192),'Input AIXTRON'!F192,0) | G63: =IF(ISNUMBER('Input AIXTRON'!G192),'Input AIXTRON'!G192,0)
A64: - Other Non-Current Liabilities | B64: =IF(ISNUMBER('Input AIXTRON'!B193),'Input AIXTRON'!B193,0) | C64: =IF(ISNUMBER('Input AIXTRON'!C193),'Input AIXTRON'!C193,0) | D64: =IF(ISNUMBER('Input AIXTRON'!D193),'Input AIXTRON'!D193,0) | E64: =IF(ISNUMBER('Input AIXTRON'!E193),'Input AIXTRON'!E193,0) | F64: =IF(ISNUMBER('Input AIXTRON'!F193),'Input AIXTRON'!F193,0) | G64: =IF(ISNUMBER('Input AIXTRON'!G193),'Input AIXTRON'!G193,0)
A65: =Net Non-Current Operating Assets | B65: =B57+B58+B59+B60+B61+B62-B63-B64 | C65: =C57+C58+C59+C60+C61+C62-C63-C64 | D65: =D57+D58+D59+D60+D61+D62-D63-D64 | E65: =E57+E58+E59+E60+E61+E62-E63-E64 | F65: =F57+F58+F59+F60+F61+F62-F63-F64 | G65: =G57+G58+G59+G60+G61+G62-G63-G64
A67: =Net Operating Assets | B67: =B54+B65 | C67: =C54+C65 | D67: =D54+D65 | E67: =E54+E65 | F67: =F54+F65 | G67: =G54+G65
A69: Investment Assets:
A70: Long-Term Investments | B70: =IF(ISNUMBER('Input AIXTRON'!B177),'Input AIXTRON'!B177,0) | C70: =IF(ISNUMBER('Input AIXTRON'!C177),'Input AIXTRON'!C177,0) | D70: =IF(ISNUMBER('Input AIXTRON'!D177),'Input AIXTRON'!D177,0) | E70: =IF(ISNUMBER('Input AIXTRON'!E177),'Input AIXTRON'!E177,0) | F70: =IF(ISNUMBER('Input AIXTRON'!F177),'Input AIXTRON'!F177,0) | G70: =IF(ISNUMBER('Input AIXTRON'!G177),'Input AIXTRON'!G177,0)
A71: =Total Investment Assets | B71: =B70 | C71: =C70 | D71: =D70 | E71: =E70 | F71: =F70 | G71: =G70
A73: =Business Assets | B73: =B67+B71 | C73: =C67+C71 | D73: =D67+D71 | E73: =E67+E71 | F73: =F67+F71 | G73: =G67+G71
A75: FINANCING
A76: Lease Liabilities (current) | B76: =IF(ISNUMBER('Input AIXTRON'!B186),'Input AIXTRON'!B186,0) | C76: =IF(ISNUMBER('Input AIXTRON'!C186),'Input AIXTRON'!C186,0) | D76: =IF(ISNUMBER('Input AIXTRON'!D186),'Input AIXTRON'!D186,0) | E76: =IF(ISNUMBER('Input AIXTRON'!E186),'Input AIXTRON'!E186,0) | F76: =IF(ISNUMBER('Input AIXTRON'!F186),'Input AIXTRON'!F186,0) | G76: =IF(ISNUMBER('Input AIXTRON'!G186),'Input AIXTRON'!G186,0)
A77: + Lease Liabilities (non-current) | B77: =IF(ISNUMBER('Input AIXTRON'!B191),'Input AIXTRON'!B191,0) | C77: =IF(ISNUMBER('Input AIXTRON'!C191),'Input AIXTRON'!C191,0) | D77: =IF(ISNUMBER('Input AIXTRON'!D191),'Input AIXTRON'!D191,0) | E77: =IF(ISNUMBER('Input AIXTRON'!E191),'Input AIXTRON'!E191,0) | F77: =IF(ISNUMBER('Input AIXTRON'!F191),'Input AIXTRON'!F191,0) | G77: =IF(ISNUMBER('Input AIXTRON'!G191),'Input AIXTRON'!G191,0)
A78: =Total Debt | B78: =B76+B77 | C78: =C76+C77 | D78: =D76+D77 | E78: =E76+E77 | F78: =F76+F77 | G78: =G76+G77
A79: Cash & Equivalents | B79: =IF(ISNUMBER('Input AIXTRON'!B166),'Input AIXTRON'!B166,0) | C79: =IF(ISNUMBER('Input AIXTRON'!C166),'Input AIXTRON'!C166,0) | D79: =IF(ISNUMBER('Input AIXTRON'!D166),'Input AIXTRON'!D166,0) | E79: =IF(ISNUMBER('Input AIXTRON'!E166),'Input AIXTRON'!E166,0) | F79: =IF(ISNUMBER('Input AIXTRON'!F166),'Input AIXTRON'!F166,0) | G79: =IF(ISNUMBER('Input AIXTRON'!G166),'Input AIXTRON'!G166,0)
A80: =Net Debt | B80: =B78-B79 | C80: =C78-C79 | D80: =D78-D79 | E80: =E78-E79 | F80: =F78-F79 | G80: =G78-G79
A81: Group Equity | B81: =IF(ISNUMBER('Input AIXTRON'!B202),'Input AIXTRON'!B202,0) | C81: =IF(ISNUMBER('Input AIXTRON'!C202),'Input AIXTRON'!C202,0) | D81: =IF(ISNUMBER('Input AIXTRON'!D202),'Input AIXTRON'!D202,0) | E81: =IF(ISNUMBER('Input AIXTRON'!E202),'Input AIXTRON'!E202,0) | F81: =IF(ISNUMBER('Input AIXTRON'!F202),'Input AIXTRON'!F202,0) | G81: =IF(ISNUMBER('Input AIXTRON'!G202),'Input AIXTRON'!G202,0)
A82: =Invested Capital | B82: =B80+B81 | C82: =C80+C81 | D82: =D80+D81 | E82: =E80+E81 | F82: =F80+F81 | G82: =G80+G81
A83: BS Check (should = 0) | B83: =B73-B82 | C83: =C73-C82 | D83: =D73-D82 | E83: =E73-E82 | F83: =F73-F82 | G83: =G73-G82
A86: FREE CASH FLOW
A87: NOPAT | B87: =B36 | C87: =C36 | D87: =D36 | E87: =E36 | F87: =F36 | G87: =G36
A88: + D&A | B88: =IF(ISNUMBER('Input AIXTRON'!B111),'Input AIXTRON'!B111,0) | C88: =IF(ISNUMBER('Input AIXTRON'!C111),'Input AIXTRON'!C111,0) | D88: =IF(ISNUMBER('Input AIXTRON'!D111),'Input AIXTRON'!D111,0) | E88: =IF(ISNUMBER('Input AIXTRON'!E111),'Input AIXTRON'!E111,0) | F88: =IF(ISNUMBER('Input AIXTRON'!F111),'Input AIXTRON'!F111,0) | G88: =IF(ISNUMBER('Input AIXTRON'!G111),'Input AIXTRON'!G111,0)
A89: - Change in OWC | B89: 0 | C89: =C54-B54 | D89: =D54-C54 | E89: =E54-D54 | F89: =F54-E54 | G89: =G54-F54
A90: - CapEx | B90: =ABS(IF(ISNUMBER('Input AIXTRON'!B125),'Input AIXTRON'!B125,0)) | C90: =ABS(IF(ISNUMBER('Input AIXTRON'!C125),'Input AIXTRON'!C125,0)) | D90: =ABS(IF(ISNUMBER('Input AIXTRON'!D125),'Input AIXTRON'!D125,0)) | E90: =ABS(IF(ISNUMBER('Input AIXTRON'!E125),'Input AIXTRON'!E125,0)) | F90: =ABS(IF(ISNUMBER('Input AIXTRON'!F125),'Input AIXTRON'!F125,0)) | G90: =ABS(IF(ISNUMBER('Input AIXTRON'!G125),'Input AIXTRON'!G125,0))
A91: - Purchase of Intangibles | B91: =ABS(IF(ISNUMBER('Input AIXTRON'!B127),'Input AIXTRON'!B127,0)) | C91: =ABS(IF(ISNUMBER('Input AIXTRON'!C127),'Input AIXTRON'!C127,0)) | D91: =ABS(IF(ISNUMBER('Input AIXTRON'!D127),'Input AIXTRON'!D127,0)) | E91: =ABS(IF(ISNUMBER('Input AIXTRON'!E127),'Input AIXTRON'!E127,0)) | F91: =ABS(IF(ISNUMBER('Input AIXTRON'!F127),'Input AIXTRON'!F127,0)) | G91: =ABS(IF(ISNUMBER('Input AIXTRON'!G127),'Input AIXTRON'!G127,0))
A92: =Operating CF after investment | B92: =B87+B88-B89-B90-B91 | C92: =C87+C88-C89-C90-C91 | D92: =D87+D88-D89-D90-D91 | E92: =E87+E88-E89-E90-E91 | F92: =F87+F88-F89-F90-F91 | G92: =G87+G88-G89-G90-G91
A94: + Net Investment Profit after tax | B94: =B27*(1-B35) | C94: =C27*(1-C35) | D94: =D27*(1-D35) | E94: =E27*(1-E35) | F94: =F27*(1-F35) | G94: =G27*(1-G35)
A95: - Change in Investment Assets | B95: 0 | C95: =C71-B71 | D95: =D71-C71 | E95: =E71-D71 | F95: =F71-E71 | G95: =G71-F71
A96: =FCF to Debt & Equity | B96: =B92+B94-B95 | C96: =C92+C94-C95 | D96: =D92+D94-D95 | E96: =E92+E94-E95 | F96: =F92+F94-F95 | G96: =G92+G94-G95
A97: - Interest Expense after tax | B97: =B29*(1-B35) | C97: =C29*(1-C35) | D97: =D29*(1-D35) | E97: =E29*(1-E35) | F97: =F29*(1-F35) | G97: =G29*(1-G35)
A98: + Change in Debt | B98: 0 | C98: =C78-B78 | D98: =D78-C78 | E98: =E78-D78 | F98: =F78-E78 | G98: =G78-F78
A99: =FCF to Equity | B99: =B96-B97+B98 | C99: =C96-C97+C98 | D99: =D96-D97+D98 | E99: =E96-E97+E98 | F99: =F96-F97+F98 | G99: =G96-G97+G98

Sheet Std AMAT
A1: Standardized Financial Statements - Applied Materials, Inc.
A2: (EUR 000)
B3: 2019 | C3: 2020 | D3: 2021 | E3: 2022 | F3: 2023 | G3: 2024
A5: Operating cash % | B5: 0.02 | C5: 0.02 | D5: 0.02 | E5: 0.02 | F5: 0.02 | G5: 0.02
A6: Tax rate (effective) | B6: =IF(ISNUMBER('Input AMAT'!B66),'Input AMAT'!B66,0) | C6: =IF(ISNUMBER('Input AMAT'!C66),'Input AMAT'!C66,0) | D6: =IF(ISNUMBER('Input AMAT'!D66),'Input AMAT'!D66,0) | E6: =IF(ISNUMBER('Input AMAT'!E66),'Input AMAT'!E66,0) | F6: =IF(ISNUMBER('Input AMAT'!F66),'Input AMAT'!F66,0) | G6: =IF(ISNUMBER('Input AMAT'!G66),'Input AMAT'!G66,0)
A8: INCOME STATEMENT
A9: Revenue | B9: =IF(ISNUMBER('Input AMAT'!B21),'Input AMAT'!B21,0) | C9: =IF(ISNUMBER('Input AMAT'!C21),'Input AMAT'!C21,0) | D9: =IF(ISNUMBER('Input AMAT'!D21),'Input AMAT'!D21,0) | E9: =IF(ISNUMBER('Input AMAT'!E21),'Input AMAT'!E21,0) | F9: =IF(ISNUMBER('Input AMAT'!F21),'Input AMAT'!F21,0) | G9: =IF(ISNUMBER('Input AMAT'!G21),'Input AMAT'!G21,0)
A10: Cost of Sales | B10: =IF(ISNUMBER('Input AMAT'!B23),'Input AMAT'!B23,0) | C10: =IF(ISNUMBER('Input AMAT'!C23),'Input AMAT'!C23,0) | D10: =IF(ISNUMBER('Input AMAT'!D23),'Input AMAT'!D23,0) | E10: =IF(ISNUMBER('Input AMAT'!E23),'Input AMAT'!E23,0) | F10: =IF(ISNUMBER('Input AMAT'!F23),'Input AMAT'!F23,0) | G10: =IF(ISNUMBER('Input AMAT'!G23),'Input AMAT'!G23,0)
A11: Gross Profit | B11: =B9-B10 | C11: =C9-C10 | D11: =D9-D10 | E11: =E9-E10 | F11: =F9-F10 | G11: =G9-G10
A12: SG&A | B12: =IF(ISNUMBER('Input AMAT'!B26),'Input AMAT'!B26,0) | C12: =IF(ISNUMBER('Input AMAT'!C26),'Input AMAT'!C26,0) | D12: =IF(ISNUMBER('Input AMAT'!D26),'Input AMAT'!D26,0) | E12: =IF(ISNUMBER('Input AMAT'!E26),'Input AMAT'!E26,0) | F12: =IF(ISNUMBER('Input AMAT'!F26),'Input AMAT'!F26,0) | G12: =IF(ISNUMBER('Input AMAT'!G26),'Input AMAT'!G26,0)
A13: R&D | B13: =IF(ISNUMBER('Input AMAT'!B27),'Input AMAT'!B27,0) | C13: =IF(ISNUMBER('Input AMAT'!C27),'Input AMAT'!C27,0) | D13: =IF(ISNUMBER('Input AMAT'!D27),'Input AMAT'!D27,0) | E13: =IF(ISNUMBER('Input AMAT'!E27),'Input AMAT'!E27,0) | F13: =IF(ISNUMBER('Input AMAT'!F27),'Input AMAT'!F27,0) | G13: =IF(ISNUMBER('Input AMAT'!G27),'Input AMAT'!G27,0)
A14: Depreciation & Amortization | B14: =IF(ISNUMBER('Input AMAT'!B108),'Input AMAT'!B108,0) | C14: =IF(ISNUMBER('Input AMAT'!C108),'Input AMAT'!C108,0) | D14: =IF(ISNUMBER('Input AMAT'!D108),'Input AMAT'!D108,0) | E14: =IF(ISNUMBER('Input AMAT'!E108),'Input AMAT'!E108,0) | F14: =IF(ISNUMBER('Input AMAT'!F108),'Input AMAT'!F108,0) | G14: =IF(ISNUMBER('Input AMAT'!G108),'Input AMAT'!G108,0)
A15: Other Operating Expense | B15: 0 | C15: 0 | D15: 0 | E15: 0 | F15: 0 | G15: 0
A16: Total Operating Expense | B16: =B10+B12+B13+B14+B15 | C16: =C10+C12+C13+C14+C15 | D16: =D10+D12+D13+D14+D15 | E16: =E10+E12+E13+E14+E15 | F16: =F10+F12+F13+F14+F15 | G16: =G10+G12+G13+G14+G15
A17: Recurring Operating Profit | B17: =B9-B16 | C17: =C9-C16 | D17: =D9-D16 | E17: =E9-E16 | F17: =F9-F16 | G17: =G9-G16
A19: Non-recurring items:
A20: Gain/Loss on Sale of Investments | B20: =IF(ISNUMBER('Input AMAT'!B39),'Input AMAT'!B39,0) | C20: =IF(ISNUMBER('Input AMAT'!C39),'Input AMAT'!C39,0) | D20: =IF(ISNUMBER('Input AMAT'!D39),'Input AMAT'!D39,0) | E20: =IF(ISNUMBER('Input AMAT'!E39),'Input AMAT'!E39,0) | F20: =IF(ISNUMBER('Input AMAT'!F39),'Input AMAT'!F39,0) | G20: =IF(ISNUMBER('Input AMAT'!G39),'Input AMAT'!G39,0)
A21: Gain/Loss on Sale of Assets | B21: 0 | C21: 0 | D21: 0 | E21: 0 | F21: 0 | G21: 0
A22: Asset Writedown | B22: 0 | C22: 0 | D22: 0 | E22: 0 | F22: 0 | G22: 0
A23: Other Unusual Items | B23: =IF(ISNUMBER('Input AMAT'!B40),'Input AMAT'!B40,0)+IF(ISNUMBER('Input AMAT'!B37),'Input AMAT'!B37,0)+IF(ISNUMBER('Input AMAT'!B38),'Input AMAT'!B38,0) | C23: =IF(ISNUMBER('Input AMAT'!C40),'Input AMAT'!C40,0)+IF(ISNUMBER('Input AMAT'!C37),'Input AMAT'!C37,0)+IF(ISNUMBER('Input AMAT'!C38),'Input AMAT'!C38,0) | D23: =IF(ISNUMBER('Input AMAT'!D40),'Input AMAT'!D40,0)+IF(ISNUMBER('Input AMAT'!D37),'Input AMAT'!D37,0)+IF(ISNUMBER('Input AMAT'!D38),'Input AMAT'!D38,0) | E23: =IF(ISNUMBER('Input AMAT'!E40),'Input AMAT'!E40,0)+IF(ISNUMBER('Input AMAT'!E37),'Input AMAT'!E37,0)+IF(ISNUMBER('Input AMAT'!E38),'Input AMAT'!E38,0) | F23: =IF(ISNUMBER('Input AMAT'!F40),'Input AMAT'!F40,0)+IF(ISNUMBER('Input AMAT'!F37),'Input AMAT'!F37,0)+IF(ISNUMBER('Input AMAT'!F38),'Input AMAT'!F38,0) | G23: =IF(ISNUMBER('Input AMAT'!G40),'Input AMAT'!G40,0)+IF(ISNUMBER('Input AMAT'!G37),'Input AMAT'!G37,0)+IF(ISNUMBER('Input AMAT'!G38),'Input AMAT'!G38,0)
A24: Total Non-recurring | B24: =SUM(B20:B23) | C24: =SUM(C20:C23) | D24: =SUM(D20:D23) | E24: =SUM(E20:E23) | F24: =SUM(F20:F23) | G24: =SUM(G20:G23)
A25: EBIT | B25: =B17+B24 | C25: =C17+C24 | D25: =D17+D24 | E25: =E17+E24 | F25: =F17+F24 | G25: =G17+G24
A27: Investment Income (Equity Method) | B27: 0 | C27: 0 | D27: 0 | E27: 0 | F27: 0 | G27: 0
A28: Interest Income | B28: =IF(ISNUMBER('Input AMAT'!B32),'Input AMAT'!B32,0) | C28: =IF(ISNUMBER('Input AMAT'!C32),'Input AMAT'!C32,0) | D28: =IF(ISNUMBER('Input AMAT'!D32),'Input AMAT'!D32,0) | E28: =IF(ISNUMBER('Input AMAT'!E32),'Input AMAT'!E32,0) | F28: =IF(ISNUMBER('Input AMAT'!F32),'Input AMAT'!F32,0) | G28: =IF(ISNUMBER('Input AMAT'!G32),'Input AMAT'!G32,0)
A29: Interest Expense | B29: =IF(ISNUMBER('Input AMAT'!B31),'Input AMAT'!B31,0) | C29: =IF(ISNUMBER('Input AMAT'!C31),'Input AMAT'!C31,0) | D29: =IF(ISNUMBER('Input AMAT'!D31),'Input AMAT'!D31,0) | E29: =IF(ISNUMBER('Input AMAT'!E31),'Input AMAT'!E31,0) | F29: =IF(ISNUMBER('Input AMAT'!F31),'Input AMAT'!F31,0) | G29: =IF(ISNUMBER('Input AMAT'!G31),'Input AMAT'!G31,0)
A30: FX Gains/(Losses) | B30: =IF(ISNUMBER('Input AMAT'!B34),'Input AMAT'!B34,0) | C30: =IF(ISNUMBER('Input AMAT'!C34),'Input AMAT'!C34,0) | D30: =IF(ISNUMBER('Input AMAT'!D34),'Input AMAT'!D34,0) | E30: =IF(ISNUMBER('Input AMAT'!E34),'Input AMAT'!E34,0) | F30: =IF(ISNUMBER('Input AMAT'!F34),'Input AMAT'!F34,0) | G30: =IF(ISNUMBER('Input AMAT'!G34),'Input AMAT'!G34,0)
A31: Profit Before Tax | B31: =B25+B27+B28+B29+B30 | C31: =C25+C27+C28+C29+C30 | D31: =D25+D27+D28+D29+D30 | E31: =E25+E27+E28+E29+E30 | F31: =F25+F27+F28+F29+F30 | G31: =G25+G27+G28+G29+G30
A32: Tax Expense | B32: =IF(ISNUMBER('Input AMAT'!B43),'Input AMAT'!B43,0) | C32: =IF(ISNUMBER('Input AMAT'!C43),'Input AMAT'!C43,0) | D32: =IF(ISNUMBER('Input AMAT'!D43),'Input AMAT'!D43,0) | E32: =IF(ISNUMBER('Input AMAT'!E43),'Input AMAT'!E43,0) | F32: =IF(ISNUMBER('Input AMAT'!F43),'Input AMAT'!F43,0) | G32: =IF(ISNUMBER('Input AMAT'!G43),'Input AMAT'!G43,0)
A33: Net Income | B33: =B31-B32 | C33: =C31-C32 | D33: =D31-D32 | E33: =E31-E32 | F33: =F31-F32 | G33: =G31-G32
A35: Effective Tax Rate | B35: =IF(B31<>0,B32/B31,0) | C35: =IF(C31<>0,C32/C31,0) | D35: =IF(D31<>0,D32/D31,0) | E35: =IF(E31<>0,E32/E31,0) | F35: =IF(F31<>0,F32/F31,0) | G35: =IF(G31<>0,G32/G31,0)
A36: NOPAT | B36: =B17*(1-B35) | C36: =C17*(1-C35) | D36: =D17*(1-D35) | E36: =E17*(1-E35) | F36: =F17*(1-F35) | G36: =G17*(1-G35)
A38: Shares Outstanding (diluted) | B38: =IF(ISNUMBER('Input AMAT'!B55),'Input AMAT'!B55,0) | C38: =IF(ISNUMBER('Input AMAT'!C55),'Input AMAT'!C55,0) | D38: =IF(ISNUMBER('Input AMAT'!D55),'Input AMAT'!D55,0) | E38: =IF(ISNUMBER('Input AMAT'!E55),'Input AMAT'!E55,0) | F38: =IF(ISNUMBER('Input AMAT'!F55),'Input AMAT'!F55,0) | G38: =IF(ISNUMBER('Input AMAT'!G55),'Input AMAT'!G55,0)
A39: EPS (diluted) | B39: =IF(B38<>0,B33/B38*1000,0) | C39: =IF(C38<>0,C33/C38*1000,0) | D39: =IF(D38<>0,D33/D38*1000,0) | E39: =IF(E38<>0,E33/E38*1000,0) | F39: =IF(F38<>0,F33/F38*1000,0) | G39: =IF(G38<>0,G33/G38*1000,0)
A40: Dividends per Share | B40: =IF(ISNUMBER('Input AMAT'!B58),'Input AMAT'!B58,0) | C40: =IF(ISNUMBER('Input AMAT'!C58),'Input AMAT'!C58,0) | D40: =IF(ISNUMBER('Input AMAT'!D58),'Input AMAT'!D58,0) | E40: =IF(ISNUMBER('Input AMAT'!E58),'Input AMAT'!E58,0) | F40: =IF(ISNUMBER('Input AMAT'!F58),'Input AMAT'!F58,0) | G40: =IF(ISNUMBER('Input AMAT'!G58),'Input AMAT'!G58,0)
A43: BALANCE SHEET (Reformulated)
A44: Operating Working Capital:
A45: Trade Receivables | B45: =IF(ISNUMBER('Input AMAT'!B161),'Input AMAT'!B161,0) | C45: =IF(ISNUMBER('Input AMAT'!C161),'Input AMAT'!C161,0) | D45: =IF(ISNUMBER('Input AMAT'!D161),'Input AMAT'!D161,0) | E45: =IF(ISNUMBER('Input AMAT'!E161),'Input AMAT'!E161,0) | F45: =IF(ISNUMBER('Input AMAT'!F161),'Input AMAT'!F161,0) | G45: =IF(ISNUMBER('Input AMAT'!G161),'Input AMAT'!G161,0)
A46: + Other Receivables | B46: 0 | C46: 0 | D46: 0 | E46: 0 | F46: 0 | G46: 0
A47: + Inventories | B47: =IF(ISNUMBER('Input AMAT'!B163),'Input AMAT'!B163,0) | C47: =IF(ISNUMBER('Input AMAT'!C163),'Input AMAT'!C163,0) | D47: =IF(ISNUMBER('Input AMAT'!D163),'Input AMAT'!D163,0) | E47: =IF(ISNUMBER('Input AMAT'!E163),'Input AMAT'!E163,0) | F47: =IF(ISNUMBER('Input AMAT'!F163),'Input AMAT'!F163,0) | G47: =IF(ISNUMBER('Input AMAT'!G163),'Input AMAT'!G163,0)
A48: + Prepaid & Other CA | B48: =IF(ISNUMBER('Input AMAT'!B164),'Input AMAT'!B164,0)+IF(ISNUMBER('Input AMAT'!B165),'Input AMAT'!B165,0) | C48: =IF(ISNUMBER('Input AMAT'!C164),'Input AMAT'!C164,0)+IF(ISNUMBER('Input AMAT'!C165),'Input AMAT'!C165,0) | D48: =IF(ISNUMBER('Input AMAT'!D164),'Input AMAT'!D164,0)+IF(ISNUMBER('Input AMAT'!D165),'Input AMAT'!D165,0) | E48: =IF(ISNUMBER('Input AMAT'!E164),'Input AMAT'!E164,0)+IF(ISNUMBER('Input AMAT'!E165),'Input AMAT'!E165,0) | F48: =IF(ISNUMBER('Input AMAT'!F164),'Input AMAT'!F164,0)+IF(ISNUMBER('Input AMAT'!F165),'Input AMAT'!F165,0) | G48: =IF(ISNUMBER('Input AMAT'!G164),'Input AMAT'!G164,0)+IF(ISNUMBER('Input AMAT'!G165),'Input AMAT'!G165,0)
A49: - Accounts Payable | B49: =IF(ISNUMBER('Input AMAT'!B177),'Input AMAT'!B177,0) | C49: =IF(ISNUMBER('Input AMAT'!C177),'Input AMAT'!C177,0) | D49: =IF(ISNUMBER('Input AMAT'!D177),'Input AMAT'!D177,0) | E49: =IF(ISNUMBER('Input AMAT'!E177),'Input AMAT'!E177,0) | F49: =IF(ISNUMBER('Input AMAT'!F177),'Input AMAT'!F177,0) | G49: =IF(ISNUMBER('Input AMAT'!G177),'Input AMAT'!G177,0)
A50: - Accrued Expenses | B50: =IF(ISNUMBER('Input AMAT'!B178),'Input AMAT'!B178,0) | C50: =IF(ISNUMBER('Input AMAT'!C178),'Input AMAT'!C178,0) | D50: =IF(ISNUMBER('Input AMAT'!D178),'Input AMAT'!D178,0) | E50: =IF(ISNUMBER('Input AMAT'!E178),'Input AMAT'!E178,0) | F50: =IF(ISNUMBER('Input AMAT'!F178),'Input AMAT'!F178,0) | G50: =IF(ISNUMBER('Input AMAT'!G178),'Input AMAT'!G178,0)
A51: - Unearned Revenue / Contract Liabilities | B51: =IF(ISNUMBER('Input AMAT'!B183),'Input AMAT'!B183,0) | C51: =IF(ISNUMBER('Input AMAT'!C183),'Input AMAT'!C183,0) | D51: =IF(ISNUMBER('Input AMAT'!D183),'Input AMAT'!D183,0) | E51: =IF(ISNUMBER('Input AMAT'!E183),'Input AMAT'!E183,0) | F51: =IF(ISNUMBER('Input AMAT'!F183),'Input AMAT'!F183,0) | G51: =IF(ISNUMBER('Input AMAT'!G183),'Input AMAT'!G183,0)
A52: - Income Taxes Payable | B52: =IF(ISNUMBER('Input AMAT'!B182),'Input AMAT'!B182,0) | C52: =IF(ISNUMBER('Input AMAT'!C182),'Input AMAT'!C182,0) | D52: =IF(ISNUMBER('Input AMAT'!D182),'Input AMAT'!D182,0) | E52: =IF(ISNUMBER('Input AMAT'!E182),'Input AMAT'!E182,0) | F52: =IF(ISNUMBER('Input AMAT'!F182),'Input AMAT'!F182,0) | G52: =IF(ISNUMBER('Input AMAT'!G182),'Input AMAT'!G182,0)
A53: - Other Current Liabilities | B53: =IF(ISNUMBER('Input AMAT'!B184),'Input AMAT'!B184,0) | C53: =IF(ISNUMBER('Input AMAT'!C184),'Input AMAT'!C184,0) | D53: =IF(ISNUMBER('Input AMAT'!D184),'Input AMAT'!D184,0) | E53: =IF(ISNUMBER('Input AMAT'!E184),'Input AMAT'!E184,0) | F53: =IF(ISNUMBER('Input AMAT'!F184),'Input AMAT'!F184,0) | G53: =IF(ISNUMBER('Input AMAT'!G184),'Input AMAT'!G184,0)
A54: =Operating Working Capital | B54: =B45+B46+B47+B48-B49-B50-B51-B52-B53 | C54: =C45+C46+C47+C48-C49-C50-C51-C52-C53 | D54: =D45+D46+D47+D48-D49-D50-D51-D52-D53 | E54: =E45+E46+E47+E48-E49-E50-E51-E52-E53 | F54: =F45+F46+F47+F48-F49-F50-F51-F52-F53 | G54: =G45+G46+G47+G48-G49-G50-G51-G52-G53
A56: Net Non-Current Operating Assets:
A57: PP&E (net, incl. ROU) | B57: =IF(ISNUMBER('Input AMAT'!B169),'Input AMAT'!B169,0) | C57: =IF(ISNUMBER('Input AMAT'!C169),'Input AMAT'!C169,0) | D57: =IF(ISNUMBER('Input AMAT'!D169),'Input AMAT'!D169,0) | E57: =IF(ISNUMBER('Input AMAT'!E169),'Input AMAT'!E169,0) | F57: =IF(ISNUMBER('Input AMAT'!F169),'Input AMAT'!F169,0) | G57: =IF(ISNUMBER('Input AMAT'!G169),'Input AMAT'!G169,0)
A58: + Goodwill | B58: =IF(ISNUMBER('Input AMAT'!B171),'Input AMAT'!B171,0) | C58: =IF(ISNUMBER('Input AMAT'!C171),'Input AMAT'!C171,0) | D58: =IF(ISNUMBER('Input AMAT'!D171),'Input AMAT'!D171,0) | E58: =IF(ISNUMBER('Input AMAT'!E171),'Input AMAT'!E171,0) | F58: =IF(ISNUMBER('Input AMAT'!F171),'Input AMAT'!F171,0) | G58: =IF(ISNUMBER('Input AMAT'!G171),'Input AMAT'!G171,0)
A59: + Other Intangible Assets | B59: =IF(ISNUMBER('Input AMAT'!B172),'Input AMAT'!B172,0) | C59: =IF(ISNUMBER('Input AMAT'!C172),'Input AMAT'!C172,0) | D59: =IF(ISNUMBER('Input AMAT'!D172),'Input AMAT'!D172,0) | E59: =IF(ISNUMBER('Input AMAT'!E172),'Input AMAT'!E172,0) | F59: =IF(ISNUMBER('Input AMAT'!F172),'Input AMAT'!F172,0) | G59: =IF(ISNUMBER('Input AMAT'!G172),'Input AMAT'!G172,0)
A60: + Deferred Tax Assets | B60: =IF(ISNUMBER('Input AMAT'!B173),'Input AMAT'!B173,0) | C60: =IF(ISNUMBER('Input AMAT'!C173),'Input AMAT'!C173,0) | D60: =IF(ISNUMBER('Input AMAT'!D173),'Input AMAT'!D173,0) | E60: =IF(ISNUMBER('Input AMAT'!E173),'Input AMAT'!E173,0) | F60: =IF(ISNUMBER('Input AMAT'!F173),'Input AMAT'!F173,0) | G60: =IF(ISNUMBER('Input AMAT'!G173),'Input AMAT'!G173,0)
A61: + Deferred Charges & LT Intangibles | B61: 0 | C61: 0 | D61: 0 | E61: 0 | F61: 0 | G61: 0
A62: + Other Non-Current Assets | B62: =IF(ISNUMBER('Input AMAT'!B174),'Input AMAT'!B174,0) | C62: =IF(ISNUMBER('Input AMAT'!C174),'Input AMAT'!C174,0) | D62: =IF(ISNUMBER('Input AMAT'!D174),'Input AMAT'!D174,0) | E62: =IF(ISNUMBER('Input AMAT'!E174),'Input AMAT'!E174,0) | F62: =IF(ISNUMBER('Input AMAT'!F174),'Input AMAT'!F174,0) | G62: =IF(ISNUMBER('Input AMAT'!G174),'Input AMAT'!G174,0)
A63: - Deferred Tax Liabilities | B63: 0 | C63: 0 | D63: 0 | E63: 0 | F63: 0 | G63: 0
A64: - Other Non-Current Liabilities | B64: =IF(ISNUMBER('Input AMAT'!B189),'Input AMAT'!B189,0)+IF(ISNUMBER('Input AMAT'!B188),'Input AMAT'!B188,0) | C64: =IF(ISNUMBER('Input AMAT'!C189),'Input AMAT'!C189,0)+IF(ISNUMBER('Input AMAT'!C188),'Input AMAT'!C188,0) | D64: =IF(ISNUMBER('Input AMAT'!D189),'Input AMAT'!D189,0)+IF(ISNUMBER('Input AMAT'!D188),'Input AMAT'!D188,0) | E64: =IF(ISNUMBER('Input AMAT'!E189),'Input AMAT'!E189,0)+IF(ISNUMBER('Input AMAT'!E188),'Input AMAT'!E188,0) | F64: =IF(ISNUMBER('Input AMAT'!F189),'Input AMAT'!F189,0)+IF(ISNUMBER('Input AMAT'!F188),'Input AMAT'!F188,0) | G64: =IF(ISNUMBER('Input AMAT'!G189),'Input AMAT'!G189,0)+IF(ISNUMBER('Input AMAT'!G188),'Input AMAT'!G188,0)
A65: =Net Non-Current Operating Assets | B65: =B57+B58+B59+B60+B61+B62-B63-B64 | C65: =C57+C58+C59+C60+C61+C62-C63-C64 | D65: =D57+D58+D59+D60+D61+D62-D63-D64 | E65: =E57+E58+E59+E60+E61+E62-E63-E64 | F65: =F57+F58+F59+F60+F61+F62-F63-F64 | G65: =G57+G58+G59+G60+G61+G62-G63-G64
A67: =Net Operating Assets | B67: =B54+B65 | C67: =C54+C65 | D67: =D54+D65 | E67: =E54+E65 | F67: =F54+F65 | G67: =G54+G65
A69: Investment Assets:
A70: Long-Term Investments | B70: =IF(ISNUMBER('Input AMAT'!B170),'Input AMAT'!B170,0) | C70: =IF(ISNUMBER('Input AMAT'!C170),'Input AMAT'!C170,0) | D70: =IF(ISNUMBER('Input AMAT'!D170),'Input AMAT'!D170,0) | E70: =IF(ISNUMBER('Input AMAT'!E170),'Input AMAT'!E170,0) | F70: =IF(ISNUMBER('Input AMAT'!F170),'Input AMAT'!F170,0) | G70: =IF(ISNUMBER('Input AMAT'!G170),'Input AMAT'!G170,0)
A71: =Total Investment Assets | B71: =B70 | C71: =C70 | D71: =D70 | E71: =E70 | F71: =F70 | G71: =G70
A73: =Business Assets | B73: =B67+B71 | C73: =C67+C71 | D73: =D67+D71 | E73: =E67+E71 | F73: =F67+F71 | G73: =G67+G71
A75: FINANCING
A76: Lease Liabilities (current) | B76: =IF(ISNUMBER('Input AMAT'!B181),'Input AMAT'!B181,0) | C76: =IF(ISNUMBER('Input AMAT'!C181),'Input AMAT'!C181,0) | D76: =IF(ISNUMBER('Input AMAT'!D181),'Input AMAT'!D181,0) | E76: =IF(ISNUMBER('Input AMAT'!E181),'Input AMAT'!E181,0) | F76: =IF(ISNUMBER('Input AMAT'!F181),'Input AMAT'!F181,0) | G76: =IF(ISNUMBER('Input AMAT'!G181),'Input AMAT'!G181,0)
A77: + Lease Liabilities (non-current) | B77: =IF(ISNUMBER('Input AMAT'!B187),'Input AMAT'!B187,0) | C77: =IF(ISNUMBER('Input AMAT'!C187),'Input AMAT'!C187,0) | D77: =IF(ISNUMBER('Input AMAT'!D187),'Input AMAT'!D187,0) | E77: =IF(ISNUMBER('Input AMAT'!E187),'Input AMAT'!E187,0) | F77: =IF(ISNUMBER('Input AMAT'!F187),'Input AMAT'!F187,0) | G77: =IF(ISNUMBER('Input AMAT'!G187),'Input AMAT'!G187,0)
A78: =Total Debt | B78: =IF(ISNUMBER('Input AMAT'!B206),'Input AMAT'!B206,0) | C78: =IF(ISNUMBER('Input AMAT'!C206),'Input AMAT'!C206,0) | D78: =IF(ISNUMBER('Input AMAT'!D206),'Input AMAT'!D206,0) | E78: =IF(ISNUMBER('Input AMAT'!E206),'Input AMAT'!E206,0) | F78: =IF(ISNUMBER('Input AMAT'!F206),'Input AMAT'!F206,0) | G78: =IF(ISNUMBER('Input AMAT'!G206),'Input AMAT'!G206,0)
A79: Cash & Equivalents | B79: =IF(ISNUMBER('Input AMAT'!B160),'Input AMAT'!B160,0) | C79: =IF(ISNUMBER('Input AMAT'!C160),'Input AMAT'!C160,0) | D79: =IF(ISNUMBER('Input AMAT'!D160),'Input AMAT'!D160,0) | E79: =IF(ISNUMBER('Input AMAT'!E160),'Input AMAT'!E160,0) | F79: =IF(ISNUMBER('Input AMAT'!F160),'Input AMAT'!F160,0) | G79: =IF(ISNUMBER('Input AMAT'!G160),'Input AMAT'!G160,0)
A80: =Net Debt | B80: =B78-B79 | C80: =C78-C79 | D80: =D78-D79 | E80: =E78-E79 | F80: =F78-F79 | G80: =G78-G79
A81: Group Equity | B81: =IF(ISNUMBER('Input AMAT'!B198),'Input AMAT'!B198,0) | C81: =IF(ISNUMBER('Input AMAT'!C198),'Input AMAT'!C198,0) | D81: =IF(ISNUMBER('Input AMAT'!D198),'Input AMAT'!D198,0) | E81: =IF(ISNUMBER('Input AMAT'!E198),'Input AMAT'!E198,0) | F81: =IF(ISNUMBER('Input AMAT'!F198),'Input AMAT'!F198,0) | G81: =IF(ISNUMBER('Input AMAT'!G198),'Input AMAT'!G198,0)
A82: =Invested Capital | B82: =B80+B81 | C82: =C80+C81 | D82: =D80+D81 | E82: =E80+E81 | F82: =F80+F81 | G82: =G80+G81
A83: BS Check (should = 0) | B83: =B73-B82 | C83: =C73-C82 | D83: =D73-D82 | E83: =E73-E82 | F83: =F73-F82 | G83: =G73-G82
A86: FREE CASH FLOW
A87: NOPAT | B87: =B36 | C87: =C36 | D87: =D36 | E87: =E36 | F87: =F36 | G87: =G36
A88: + D&A | B88: =IF(ISNUMBER('Input AMAT'!B108),'Input AMAT'!B108,0) | C88: =IF(ISNUMBER('Input AMAT'!C108),'Input AMAT'!C108,0) | D88: =IF(ISNUMBER('Input AMAT'!D108),'Input AMAT'!D108,0) | E88: =IF(ISNUMBER('Input AMAT'!E108),'Input AMAT'!E108,0) | F88: =IF(ISNUMBER('Input AMAT'!F108),'Input AMAT'!F108,0) | G88: =IF(ISNUMBER('Input AMAT'!G108),'Input AMAT'!G108,0)
A89: - Change in OWC | B89: 0 | C89: =C54-B54 | D89: =D54-C54 | E89: =E54-D54 | F89: =F54-E54 | G89: =G54-F54
A90: - CapEx | B90: =ABS(IF(ISNUMBER('Input AMAT'!B120),'Input AMAT'!B120,0)) | C90: =ABS(IF(ISNUMBER('Input AMAT'!C120),'Input AMAT'!C120,0)) | D90: =ABS(IF(ISNUMBER('Input AMAT'!D120),'Input AMAT'!D120,0)) | E90: =ABS(IF(ISNUMBER('Input AMAT'!E120),'Input AMAT'!E120,0)) | F90: =ABS(IF(ISNUMBER('Input AMAT'!F120),'Input AMAT'!F120,0)) | G90: =ABS(IF(ISNUMBER('Input AMAT'!G120),'Input AMAT'!G120,0))
A91: - Purchase of Intangibles | B91: 0 | C91: 0 | D91: 0 | E91: 0 | F91: 0 | G91: 0
A92: =Operating CF after investment | B92: =B87+B88-B89-B90-B91 | C92: =C87+C88-C89-C90-C91 | D92: =D87+D88-D89-D90-D91 | E92: =E87+E88-E89-E90-E91 | F92: =F87+F88-F89-F90-F91 | G92: =G87+G88-G89-G90-G91
A94: + Net Investment Profit after tax | B94: =B27*(1-B35) | C94: =C27*(1-C35) | D94: =D27*(1-D35) | E94: =E27*(1-E35) | F94: =F27*(1-F35) | G94: =G27*(1-G35)
A95: - Change in Investment Assets | B95: 0 | C95: =C71-B71 | D95: =D71-C71 | E95: =E71-D71 | F95: =F71-E71 | G95: =G71-F71
A96: =FCF to Debt & Equity | B96: =B92+B94-B95 | C96: =C92+C94-C95 | D96: =D92+D94-D95 | E96: =E92+E94-E95 | F96: =F92+F94-F95 | G96: =G92+G94-G95
A97: - Interest Expense after tax | B97: =B29*(1-B35) | C97: =C29*(1-C35) | D97: =D29*(1-D35) | E97: =E29*(1-E35) | F97: =F29*(1-F35) | G97: =G29*(1-G35)
A98: + Change in Debt | B98: 0 | C98: =C78-B78 | D98: =D78-C78 | E98: =E78-D78 | F98: =F78-E78 | G98: =G78-F78
A99: =FCF to Equity | B99: =B96-B97+B98 | C99: =C96-C97+C98 | D99: =D96-D97+D98 | E99: =E96-E97+E98 | F99: =F96-F97+F98 | G99: =G96-G97+G98

Sheet Std LRCX
A1: Standardized Financial Statements - Lam Research Corporation
A2: (EUR 000)
B3: 2019 | C3: 2020 | D3: 2021 | E3: 2022 | F3: 2023 | G3: 2024
A5: Operating cash % | B5: 0.02 | C5: 0.02 | D5: 0.02 | E5: 0.02 | F5: 0.02 | G5: 0.02
A6: Tax rate (effective) | B6: =IF(ISNUMBER('Input LRCX'!B63),'Input LRCX'!B63,0) | C6: =IF(ISNUMBER('Input LRCX'!C63),'Input LRCX'!C63,0) | D6: =IF(ISNUMBER('Input LRCX'!D63),'Input LRCX'!D63,0) | E6: =IF(ISNUMBER('Input LRCX'!E63),'Input LRCX'!E63,0) | F6: =IF(ISNUMBER('Input LRCX'!F63),'Input LRCX'!F63,0) | G6: =IF(ISNUMBER('Input LRCX'!G63),'Input LRCX'!G63,0)
A8: INCOME STATEMENT
A9: Revenue | B9: =IF(ISNUMBER('Input LRCX'!B21),'Input LRCX'!B21,0) | C9: =IF(ISNUMBER('Input LRCX'!C21),'Input LRCX'!C21,0) | D9: =IF(ISNUMBER('Input LRCX'!D21),'Input LRCX'!D21,0) | E9: =IF(ISNUMBER('Input LRCX'!E21),'Input LRCX'!E21,0) | F9: =IF(ISNUMBER('Input LRCX'!F21),'Input LRCX'!F21,0) | G9: =IF(ISNUMBER('Input LRCX'!G21),'Input LRCX'!G21,0)
A10: Cost of Sales | B10: =IF(ISNUMBER('Input LRCX'!B23),'Input LRCX'!B23,0) | C10: =IF(ISNUMBER('Input LRCX'!C23),'Input LRCX'!C23,0) | D10: =IF(ISNUMBER('Input LRCX'!D23),'Input LRCX'!D23,0) | E10: =IF(ISNUMBER('Input LRCX'!E23),'Input LRCX'!E23,0) | F10: =IF(ISNUMBER('Input LRCX'!F23),'Input LRCX'!F23,0) | G10: =IF(ISNUMBER('Input LRCX'!G23),'Input LRCX'!G23,0)
A11: Gross Profit | B11: =B9-B10 | C11: =C9-C10 | D11: =D9-D10 | E11: =E9-E10 | F11: =F9-F10 | G11: =G9-G10
A12: SG&A | B12: =IF(ISNUMBER('Input LRCX'!B26),'Input LRCX'!B26,0) | C12: =IF(ISNUMBER('Input LRCX'!C26),'Input LRCX'!C26,0) | D12: =IF(ISNUMBER('Input LRCX'!D26),'Input LRCX'!D26,0) | E12: =IF(ISNUMBER('Input LRCX'!E26),'Input LRCX'!E26,0) | F12: =IF(ISNUMBER('Input LRCX'!F26),'Input LRCX'!F26,0) | G12: =IF(ISNUMBER('Input LRCX'!G26),'Input LRCX'!G26,0)
A13: R&D | B13: =IF(ISNUMBER('Input LRCX'!B27),'Input LRCX'!B27,0) | C13: =IF(ISNUMBER('Input LRCX'!C27),'Input LRCX'!C27,0) | D13: =IF(ISNUMBER('Input LRCX'!D27),'Input LRCX'!D27,0) | E13: =IF(ISNUMBER('Input LRCX'!E27),'Input LRCX'!E27,0) | F13: =IF(ISNUMBER('Input LRCX'!F27),'Input LRCX'!F27,0) | G13: =IF(ISNUMBER('Input LRCX'!G27),'Input LRCX'!G27,0)
A14: Depreciation & Amortization | B14: =IF(ISNUMBER('Input LRCX'!B98),'Input LRCX'!B98,0) | C14: =IF(ISNUMBER('Input LRCX'!C98),'Input LRCX'!C98,0) | D14: =IF(ISNUMBER('Input LRCX'!D98),'Input LRCX'!D98,0) | E14: =IF(ISNUMBER('Input LRCX'!E98),'Input LRCX'!E98,0) | F14: =IF(ISNUMBER('Input LRCX'!F98),'Input LRCX'!F98,0) | G14: =IF(ISNUMBER('Input LRCX'!G98),'Input LRCX'!G98,0)
A15: Other Operating Expense | B15: 0 | C15: 0 | D15: 0 | E15: 0 | F15: 0 | G15: 0
A16: Total Operating Expense | B16: =B10+B12+B13+B14+B15 | C16: =C10+C12+C13+C14+C15 | D16: =D10+D12+D13+D14+D15 | E16: =E10+E12+E13+E14+E15 | F16: =F10+F12+F13+F14+F15 | G16: =G10+G12+G13+G14+G15
A17: Recurring Operating Profit | B17: =B9-B16 | C17: =C9-C16 | D17: =D9-D16 | E17: =E9-E16 | F17: =F9-F16 | G17: =G9-G16
A19: Non-recurring items:
A20: Gain/Loss on Sale of Investments | B20: 0 | C20: 0 | D20: 0 | E20: 0 | F20: 0 | G20: 0
A21: Gain/Loss on Sale of Assets | B21: 0 | C21: 0 | D21: 0 | E21: 0 | F21: 0 | G21: 0
A22: Asset Writedown | B22: 0 | C22: 0 | D22: 0 | E22: 0 | F22: 0 | G22: 0
A23: Other Unusual Items | B23: =IF(ISNUMBER('Input LRCX'!B37),'Input LRCX'!B37,0) | C23: =IF(ISNUMBER('Input LRCX'!C37),'Input LRCX'!C37,0) | D23: =IF(ISNUMBER('Input LRCX'!D37),'Input LRCX'!D37,0) | E23: =IF(ISNUMBER('Input LRCX'!E37),'Input LRCX'!E37,0) | F23: =IF(ISNUMBER('Input LRCX'!F37),'Input LRCX'!F37,0) | G23: =IF(ISNUMBER('Input LRCX'!G37),'Input LRCX'!G37,0)
A24: Total Non-recurring | B24: =SUM(B20:B23) | C24: =SUM(C20:C23) | D24: =SUM(D20:D23) | E24: =SUM(E20:E23) | F24: =SUM(F20:F23) | G24: =SUM(G20:G23)
A25: EBIT | B25: =B17+B24 | C25: =C17+C24 | D25: =D17+D24 | E25: =E17+E24 | F25: =F17+F24 | G25: =G17+G24
A27: Investment Income (Equity Method) | B27: 0 | C27: 0 | D27: 0 | E27: 0 | F27: 0 | G27: 0
A28: Interest Income | B28: =IF(ISNUMBER('Input LRCX'!B32),'Input LRCX'!B32,0) | C28: =IF(ISNUMBER('Input LRCX'!C32),'Input LRCX'!C32,0) | D28: =IF(ISNUMBER('Input LRCX'!D32),'Input LRCX'!D32,0) | E28: =IF(ISNUMBER('Input LRCX'!E32),'Input LRCX'!E32,0) | F28: =IF(ISNUMBER('Input LRCX'!F32),'Input LRCX'!F32,0) | G28: =IF(ISNUMBER('Input LRCX'!G32),'Input LRCX'!G32,0)
A29: Interest Expense | B29: =IF(ISNUMBER('Input LRCX'!B31),'Input LRCX'!B31,0) | C29: =IF(ISNUMBER('Input LRCX'!C31),'Input LRCX'!C31,0) | D29: =IF(ISNUMBER('Input LRCX'!D31),'Input LRCX'!D31,0) | E29: =IF(ISNUMBER('Input LRCX'!E31),'Input LRCX'!E31,0) | F29: =IF(ISNUMBER('Input LRCX'!F31),'Input LRCX'!F31,0) | G29: =IF(ISNUMBER('Input LRCX'!G31),'Input LRCX'!G31,0)
A30: FX Gains/(Losses) | B30: =IF(ISNUMBER('Input LRCX'!B34),'Input LRCX'!B34,0) | C30: =IF(ISNUMBER('Input LRCX'!C34),'Input LRCX'!C34,0) | D30: =IF(ISNUMBER('Input LRCX'!D34),'Input LRCX'!D34,0) | E30: =IF(ISNUMBER('Input LRCX'!E34),'Input LRCX'!E34,0) | F30: =IF(ISNUMBER('Input LRCX'!F34),'Input LRCX'!F34,0) | G30: =IF(ISNUMBER('Input LRCX'!G34),'Input LRCX'!G34,0)
A31: Profit Before Tax | B31: =B25+B27+B28+B29+B30 | C31: =C25+C27+C28+C29+C30 | D31: =D25+D27+D28+D29+D30 | E31: =E25+E27+E28+E29+E30 | F31: =F25+F27+F28+F29+F30 | G31: =G25+G27+G28+G29+G30
A32: Tax Expense | B32: =IF(ISNUMBER('Input LRCX'!B40),'Input LRCX'!B40,0) | C32: =IF(ISNUMBER('Input LRCX'!C40),'Input LRCX'!C40,0) | D32: =IF(ISNUMBER('Input LRCX'!D40),'Input LRCX'!D40,0) | E32: =IF(ISNUMBER('Input LRCX'!E40),'Input LRCX'!E40,0) | F32: =IF(ISNUMBER('Input LRCX'!F40),'Input LRCX'!F40,0) | G32: =IF(ISNUMBER('Input LRCX'!G40),'Input LRCX'!G40,0)
A33: Net Income | B33: =B31-B32 | C33: =C31-C32 | D33: =D31-D32 | E33: =E31-E32 | F33: =F31-F32 | G33: =G31-G32
A35: Effective Tax Rate | B35: =IF(B31<>0,B32/B31,0) | C35: =IF(C31<>0,C32/C31,0) | D35: =IF(D31<>0,D32/D31,0) | E35: =IF(E31<>0,E32/E31,0) | F35: =IF(F31<>0,F32/F31,0) | G35: =IF(G31<>0,G32/G31,0)
A36: NOPAT | B36: =B17*(1-B35) | C36: =C17*(1-C35) | D36: =D17*(1-D35) | E36: =E17*(1-E35) | F36: =F17*(1-F35) | G36: =G17*(1-G35)
A38: Shares Outstanding (diluted) | B38: =IF(ISNUMBER('Input LRCX'!B52),'Input LRCX'!B52,0) | C38: =IF(ISNUMBER('Input LRCX'!C52),'Input LRCX'!C52,0) | D38: =IF(ISNUMBER('Input LRCX'!D52),'Input LRCX'!D52,0) | E38: =IF(ISNUMBER('Input LRCX'!E52),'Input LRCX'!E52,0) | F38: =IF(ISNUMBER('Input LRCX'!F52),'Input LRCX'!F52,0) | G38: =IF(ISNUMBER('Input LRCX'!G52),'Input LRCX'!G52,0)
A39: EPS (diluted) | B39: =IF(B38<>0,B33/B38*1000,0) | C39: =IF(C38<>0,C33/C38*1000,0) | D39: =IF(D38<>0,D33/D38*1000,0) | E39: =IF(E38<>0,E33/E38*1000,0) | F39: =IF(F38<>0,F33/F38*1000,0) | G39: =IF(G38<>0,G33/G38*1000,0)
A40: Dividends per Share | B40: =IF(ISNUMBER('Input LRCX'!B55),'Input LRCX'!B55,0) | C40: =IF(ISNUMBER('Input LRCX'!C55),'Input LRCX'!C55,0) | D40: =IF(ISNUMBER('Input LRCX'!D55),'Input LRCX'!D55,0) | E40: =IF(ISNUMBER('Input LRCX'!E55),'Input LRCX'!E55,0) | F40: =IF(ISNUMBER('Input LRCX'!F55),'Input LRCX'!F55,0) | G40: =IF(ISNUMBER('Input LRCX'!G55),'Input LRCX'!G55,0)
A43: BALANCE SHEET (Reformulated)
A44: Operating Working Capital:
A45: Trade Receivables | B45: =IF(ISNUMBER('Input LRCX'!B152),'Input LRCX'!B152,0) | C45: =IF(ISNUMBER('Input LRCX'!C152),'Input LRCX'!C152,0) | D45: =IF(ISNUMBER('Input LRCX'!D152),'Input LRCX'!D152,0) | E45: =IF(ISNUMBER('Input LRCX'!E152),'Input LRCX'!E152,0) | F45: =IF(ISNUMBER('Input LRCX'!F152),'Input LRCX'!F152,0) | G45: =IF(ISNUMBER('Input LRCX'!G152),'Input LRCX'!G152,0)
A46: + Other Receivables | B46: 0 | C46: 0 | D46: 0 | E46: 0 | F46: 0 | G46: 0
A47: + Inventories | B47: =IF(ISNUMBER('Input LRCX'!B154),'Input LRCX'!B154,0) | C47: =IF(ISNUMBER('Input LRCX'!C154),'Input LRCX'!C154,0) | D47: =IF(ISNUMBER('Input LRCX'!D154),'Input LRCX'!D154,0) | E47: =IF(ISNUMBER('Input LRCX'!E154),'Input LRCX'!E154,0) | F47: =IF(ISNUMBER('Input LRCX'!F154),'Input LRCX'!F154,0) | G47: =IF(ISNUMBER('Input LRCX'!G154),'Input LRCX'!G154,0)
A48: + Prepaid & Other CA | B48: =IF(ISNUMBER('Input LRCX'!B155),'Input LRCX'!B155,0)+IF(ISNUMBER('Input LRCX'!B156),'Input LRCX'!B156,0) | C48: =IF(ISNUMBER('Input LRCX'!C155),'Input LRCX'!C155,0)+IF(ISNUMBER('Input LRCX'!C156),'Input LRCX'!C156,0) | D48: =IF(ISNUMBER('Input LRCX'!D155),'Input LRCX'!D155,0)+IF(ISNUMBER('Input LRCX'!D156),'Input LRCX'!D156,0) | E48: =IF(ISNUMBER('Input LRCX'!E155),'Input LRCX'!E155,0)+IF(ISNUMBER('Input LRCX'!E156),'Input LRCX'!E156,0) | F48: =IF(ISNUMBER('Input LRCX'!F155),'Input LRCX'!F155,0)+IF(ISNUMBER('Input LRCX'!F156),'Input LRCX'!F156,0) | G48: =IF(ISNUMBER('Input LRCX'!G155),'Input LRCX'!G155,0)+IF(ISNUMBER('Input LRCX'!G156),'Input LRCX'!G156,0)
A49: - Accounts Payable | B49: =IF(ISNUMBER('Input LRCX'!B168),'Input LRCX'!B168,0) | C49: =IF(ISNUMBER('Input LRCX'!C168),'Input LRCX'!C168,0) | D49: =IF(ISNUMBER('Input LRCX'!D168),'Input LRCX'!D168,0) | E49: =IF(ISNUMBER('Input LRCX'!E168),'Input LRCX'!E168,0) | F49: =IF(ISNUMBER('Input LRCX'!F168),'Input LRCX'!F168,0) | G49: =IF(ISNUMBER('Input LRCX'!G168),'Input LRCX'!G168,0)
A50: - Accrued Expenses | B50: =IF(ISNUMBER('Input LRCX'!B169),'Input LRCX'!B169,0) | C50: =IF(ISNUMBER('Input LRCX'!C169),'Input LRCX'!C169,0) | D50: =IF(ISNUMBER('Input LRCX'!D169),'Input LRCX'!D169,0) | E50: =IF(ISNUMBER('Input LRCX'!E169),'Input LRCX'!E169,0) | F50: =IF(ISNUMBER('Input LRCX'!F169),'Input LRCX'!F169,0) | G50: =IF(ISNUMBER('Input LRCX'!G169),'Input LRCX'!G169,0)
A51: - Unearned Revenue / Contract Liabilities | B51: =IF(ISNUMBER('Input LRCX'!B173),'Input LRCX'!B173,0) | C51: =IF(ISNUMBER('Input LRCX'!C173),'Input LRCX'!C173,0) | D51: =IF(ISNUMBER('Input LRCX'!D173),'Input LRCX'!D173,0) | E51: =IF(ISNUMBER('Input LRCX'!E173),'Input LRCX'!E173,0) | F51: =IF(ISNUMBER('Input LRCX'!F173),'Input LRCX'!F173,0) | G51: =IF(ISNUMBER('Input LRCX'!G173),'Input LRCX'!G173,0)
A52: - Income Taxes Payable | B52: =IF(ISNUMBER('Input LRCX'!B172),'Input LRCX'!B172,0) | C52: =IF(ISNUMBER('Input LRCX'!C172),'Input LRCX'!C172,0) | D52: =IF(ISNUMBER('Input LRCX'!D172),'Input LRCX'!D172,0) | E52: =IF(ISNUMBER('Input LRCX'!E172),'Input LRCX'!E172,0) | F52: =IF(ISNUMBER('Input LRCX'!F172),'Input LRCX'!F172,0) | G52: =IF(ISNUMBER('Input LRCX'!G172),'Input LRCX'!G172,0)
A53: - Other Current Liabilities | B53: =IF(ISNUMBER('Input LRCX'!B174),'Input LRCX'!B174,0) | C53: =IF(ISNUMBER('Input LRCX'!C174),'Input LRCX'!C174,0) | D53: =IF(ISNUMBER('Input LRCX'!D174),'Input LRCX'!D174,0) | E53: =IF(ISNUMBER('Input LRCX'!E174),'Input LRCX'!E174,0) | F53: =IF(ISNUMBER('Input LRCX'!F174),'Input LRCX'!F174,0) | G53: =IF(ISNUMBER('Input LRCX'!G174),'Input LRCX'!G174,0)
A54: =Operating Working Capital | B54: =B45+B46+B47+B48-B49-B50-B51-B52-B53 | C54: =C45+C46+C47+C48-C49-C50-C51-C52-C53 | D54: =D45+D46+D47+D48-D49-D50-D51-D52-D53 | E54: =E45+E46+E47+E48-E49-E50-E51-E52-E53 | F54: =F45+F46+F47+F48-F49-F50-F51-F52-F53 | G54: =G45+G46+G47+G48-G49-G50-G51-G52-G53
A56: Net Non-Current Operating Assets:
A57: PP&E (net, incl. ROU) | B57: =IF(ISNUMBER('Input LRCX'!B160),'Input LRCX'!B160,0) | C57: =IF(ISNUMBER('Input LRCX'!C160),'Input LRCX'!C160,0) | D57: =IF(ISNUMBER('Input LRCX'!D160),'Input LRCX'!D160,0) | E57: =IF(ISNUMBER('Input LRCX'!E160),'Input LRCX'!E160,0) | F57: =IF(ISNUMBER('Input LRCX'!F160),'Input LRCX'!F160,0) | G57: =IF(ISNUMBER('Input LRCX'!G160),'Input LRCX'!G160,0)
A58: + Goodwill | B58: =IF(ISNUMBER('Input LRCX'!B162),'Input LRCX'!B162,0) | C58: =IF(ISNUMBER('Input LRCX'!C162),'Input LRCX'!C162,0) | D58: =IF(ISNUMBER('Input LRCX'!D162),'Input LRCX'!D162,0) | E58: =IF(ISNUMBER('Input LRCX'!E162),'Input LRCX'!E162,0) | F58: =IF(ISNUMBER('Input LRCX'!F162),'Input LRCX'!F162,0) | G58: =IF(ISNUMBER('Input LRCX'!G162),'Input LRCX'!G162,0)
A59: + Other Intangible Assets | B59: =IF(ISNUMBER('Input LRCX'!B163),'Input LRCX'!B163,0) | C59: =IF(ISNUMBER('Input LRCX'!C163),'Input LRCX'!C163,0) | D59: =IF(ISNUMBER('Input LRCX'!D163),'Input LRCX'!D163,0) | E59: =IF(ISNUMBER('Input LRCX'!E163),'Input LRCX'!E163,0) | F59: =IF(ISNUMBER('Input LRCX'!F163),'Input LRCX'!F163,0) | G59: =IF(ISNUMBER('Input LRCX'!G163),'Input LRCX'!G163,0)
A60: + Deferred Tax Assets | B60: 0 | C60: 0 | D60: 0 | E60: 0 | F60: 0 | G60: 0
A61: + Deferred Charges & LT Intangibles | B61: =IF(ISNUMBER('Input LRCX'!B164),'Input LRCX'!B164,0) | C61: =IF(ISNUMBER('Input LRCX'!C164),'Input LRCX'!C164,0) | D61: =IF(ISNUMBER('Input LRCX'!D164),'Input LRCX'!D164,0) | E61: =IF(ISNUMBER('Input LRCX'!E164),'Input LRCX'!E164,0) | F61: =IF(ISNUMBER('Input LRCX'!F164),'Input LRCX'!F164,0) | G61: =IF(ISNUMBER('Input LRCX'!G164),'Input LRCX'!G164,0)
A62: + Other Non-Current Assets | B62: =IF(ISNUMBER('Input LRCX'!B165),'Input LRCX'!B165,0) | C62: =IF(ISNUMBER('Input LRCX'!C165),'Input LRCX'!C165,0) | D62: =IF(ISNUMBER('Input LRCX'!D165),'Input LRCX'!D165,0) | E62: =IF(ISNUMBER('Input LRCX'!E165),'Input LRCX'!E165,0) | F62: =IF(ISNUMBER('Input LRCX'!F165),'Input LRCX'!F165,0) | G62: =IF(ISNUMBER('Input LRCX'!G165),'Input LRCX'!G165,0)
A63: - Deferred Tax Liabilities | B63: 0 | C63: 0 | D63: 0 | E63: 0 | F63: 0 | G63: 0
A64: - Other Non-Current Liabilities | B64: =IF(ISNUMBER('Input LRCX'!B178),'Input LRCX'!B178,0) | C64: =IF(ISNUMBER('Input LRCX'!C178),'Input LRCX'!C178,0) | D64: =IF(ISNUMBER('Input LRCX'!D178),'Input LRCX'!D178,0) | E64: =IF(ISNUMBER('Input LRCX'!E178),'Input LRCX'!E178,0) | F64: =IF(ISNUMBER('Input LRCX'!F178),'Input LRCX'!F178,0) | G64: =IF(ISNUMBER('Input LRCX'!G178),'Input LRCX'!G178,0)
A65: =Net Non-Current Operating Assets | B65: =B57+B58+B59+B60+B61+B62-B63-B64 | C65: =C57+C58+C59+C60+C61+C62-C63-C64 | D65: =D57+D58+D59+D60+D61+D62-D63-D64 | E65: =E57+E58+E59+E60+E61+E62-E63-E64 | F65: =F57+F58+F59+F60+F61+F62-F63-F64 | G65: =G57+G58+G59+G60+G61+G62-G63-G64
A67: =Net Operating Assets | B67: =B54+B65 | C67: =C54+C65 | D67: =D54+D65 | E67: =E54+E65 | F67: =F54+F65 | G67: =G54+G65
A69: Investment Assets:
A70: Long-Term Investments | B70: =IF(ISNUMBER('Input LRCX'!B161),'Input LRCX'!B161,0) | C70: =IF(ISNUMBER('Input LRCX'!C161),'Input LRCX'!C161,0) | D70: =IF(ISNUMBER('Input LRCX'!D161),'Input LRCX'!D161,0) | E70: =IF(ISNUMBER('Input LRCX'!E161),'Input LRCX'!E161,0) | F70: =IF(ISNUMBER('Input LRCX'!F161),'Input LRCX'!F161,0) | G70: =IF(ISNUMBER('Input LRCX'!G161),'Input LRCX'!G161,0)
A71: =Total Investment Assets | B71: =B70 | C71: =C70 | D71: =D70 | E71: =E70 | F71: =F70 | G71: =G70
A73: =Business Assets | B73: =B67+B71 | C73: =C67+C71 | D73: =D67+D71 | E73: =E67+E71 | F73: =F67+F71 | G73: =G67+G71
A75: FINANCING
A76: Lease Liabilities (current) | B76: =IF(ISNUMBER('Input LRCX'!B171),'Input LRCX'!B171,0) | C76: =IF(ISNUMBER('Input LRCX'!C171),'Input LRCX'!C171,0) | D76: =IF(ISNUMBER('Input LRCX'!D171),'Input LRCX'!D171,0) | E76: =IF(ISNUMBER('Input LRCX'!E171),'Input LRCX'!E171,0) | F76: =IF(ISNUMBER('Input LRCX'!F171),'Input LRCX'!F171,0) | G76: =IF(ISNUMBER('Input LRCX'!G171),'Input LRCX'!G171,0)
A77: + Lease Liabilities (non-current) | B77: =IF(ISNUMBER('Input LRCX'!B177),'Input LRCX'!B177,0) | C77: =IF(ISNUMBER('Input LRCX'!C177),'Input LRCX'!C177,0) | D77: =IF(ISNUMBER('Input LRCX'!D177),'Input LRCX'!D177,0) | E77: =IF(ISNUMBER('Input LRCX'!E177),'Input LRCX'!E177,0) | F77: =IF(ISNUMBER('Input LRCX'!F177),'Input LRCX'!F177,0) | G77: =IF(ISNUMBER('Input LRCX'!G177),'Input LRCX'!G177,0)
A78: =Total Debt | B78: =IF(ISNUMBER('Input LRCX'!B195),'Input LRCX'!B195,0) | C78: =IF(ISNUMBER('Input LRCX'!C195),'Input LRCX'!C195,0) | D78: =IF(ISNUMBER('Input LRCX'!D195),'Input LRCX'!D195,0) | E78: =IF(ISNUMBER('Input LRCX'!E195),'Input LRCX'!E195,0) | F78: =IF(ISNUMBER('Input LRCX'!F195),'Input LRCX'!F195,0) | G78: =IF(ISNUMBER('Input LRCX'!G195),'Input LRCX'!G195,0)
A79: Cash & Equivalents | B79: =IF(ISNUMBER('Input LRCX'!B151),'Input LRCX'!B151,0) | C79: =IF(ISNUMBER('Input LRCX'!C151),'Input LRCX'!C151,0) | D79: =IF(ISNUMBER('Input LRCX'!D151),'Input LRCX'!D151,0) | E79: =IF(ISNUMBER('Input LRCX'!E151),'Input LRCX'!E151,0) | F79: =IF(ISNUMBER('Input LRCX'!F151),'Input LRCX'!F151,0) | G79: =IF(ISNUMBER('Input LRCX'!G151),'Input LRCX'!G151,0)
A80: =Net Debt | B80: =B78-B79 | C80: =C78-C79 | D80: =D78-D79 | E80: =E78-E79 | F80: =F78-F79 | G80: =G78-G79
A81: Group Equity | B81: =IF(ISNUMBER('Input LRCX'!B187),'Input LRCX'!B187,0) | C81: =IF(ISNUMBER('Input LRCX'!C187),'Input LRCX'!C187,0) | D81: =IF(ISNUMBER('Input LRCX'!D187),'Input LRCX'!D187,0) | E81: =IF(ISNUMBER('Input LRCX'!E187),'Input LRCX'!E187,0) | F81: =IF(ISNUMBER('Input LRCX'!F187),'Input LRCX'!F187,0) | G81: =IF(ISNUMBER('Input LRCX'!G187),'Input LRCX'!G187,0)
A82: =Invested Capital | B82: =B80+B81 | C82: =C80+C81 | D82: =D80+D81 | E82: =E80+E81 | F82: =F80+F81 | G82: =G80+G81
A83: BS Check (should = 0) | B83: =B73-B82 | C83: =C73-C82 | D83: =D73-D82 | E83: =E73-E82 | F83: =F73-F82 | G83: =G73-G82
A86: FREE CASH FLOW
A87: NOPAT | B87: =B36 | C87: =C36 | D87: =D36 | E87: =E36 | F87: =F36 | G87: =G36
A88: + D&A | B88: =IF(ISNUMBER('Input LRCX'!B98),'Input LRCX'!B98,0) | C88: =IF(ISNUMBER('Input LRCX'!C98),'Input LRCX'!C98,0) | D88: =IF(ISNUMBER('Input LRCX'!D98),'Input LRCX'!D98,0) | E88: =IF(ISNUMBER('Input LRCX'!E98),'Input LRCX'!E98,0) | F88: =IF(ISNUMBER('Input LRCX'!F98),'Input LRCX'!F98,0) | G88: =IF(ISNUMBER('Input LRCX'!G98),'Input LRCX'!G98,0)
A89: - Change in OWC | B89: 0 | C89: =C54-B54 | D89: =D54-C54 | E89: =E54-D54 | F89: =F54-E54 | G89: =G54-F54
A90: - CapEx | B90: =ABS(IF(ISNUMBER('Input LRCX'!B108),'Input LRCX'!B108,0)) | C90: =ABS(IF(ISNUMBER('Input LRCX'!C108),'Input LRCX'!C108,0)) | D90: =ABS(IF(ISNUMBER('Input LRCX'!D108),'Input LRCX'!D108,0)) | E90: =ABS(IF(ISNUMBER('Input LRCX'!E108),'Input LRCX'!E108,0)) | F90: =ABS(IF(ISNUMBER('Input LRCX'!F108),'Input LRCX'!F108,0)) | G90: =ABS(IF(ISNUMBER('Input LRCX'!G108),'Input LRCX'!G108,0))
A91: - Purchase of Intangibles | B91: 0 | C91: 0 | D91: 0 | E91: 0 | F91: 0 | G91: 0
A92: =Operating CF after investment | B92: =B87+B88-B89-B90-B91 | C92: =C87+C88-C89-C90-C91 | D92: =D87+D88-D89-D90-D91 | E92: =E87+E88-E89-E90-E91 | F92: =F87+F88-F89-F90-F91 | G92: =G87+G88-G89-G90-G91
A94: + Net Investment Profit after tax | B94: =B27*(1-B35) | C94: =C27*(1-C35) | D94: =D27*(1-D35) | E94: =E27*(1-E35) | F94: =F27*(1-F35) | G94: =G27*(1-G35)
A95: - Change in Investment Assets | B95: 0 | C95: =C71-B71 | D95: =D71-C71 | E95: =E71-D71 | F95: =F71-E71 | G95: =G71-F71
A96: =FCF to Debt & Equity | B96: =B92+B94-B95 | C96: =C92+C94-C95 | D96: =D92+D94-D95 | E96: =E92+E94-E95 | F96: =F92+F94-F95 | G96: =G92+G94-G95
A97: - Interest Expense after tax | B97: =B29*(1-B35) | C97: =C29*(1-C35) | D97: =D29*(1-D35) | E97: =E29*(1-E35) | F97: =F29*(1-F35) | G97: =G29*(1-G35)
A98: + Change in Debt | B98: 0 | C98: =C78-B78 | D98: =D78-C78 | E98: =E78-D78 | F98: =F78-E78 | G98: =G78-F78
A99: =FCF to Equity | B99: =B96-B97+B98 | C99: =C96-C97+C98 | D99: =D96-D97+D98 | E99: =E96-E97+E98 | F99: =F96-F97+F98 | G99: =G96-G97+G98

Sheet Adjustments
A1: Accounting Analysis & Adjustments - ASM International NV
A3: Areas Examined
A5: 1. R&D Capitalization Policy
B6: Description: | C6: ASM capitalizes development expenditure (significant amounts).
B7: Finding: | C7: Compare with peers: all semi equipment companies capitalize similarly.
B8: Decision: | C8: No Adjustment
B9: Justification: | C9: Consistent with industry practice and peers.
A11: 2. Equity Method Investment (ASMPT)
B12: Description: | C12: ~25% stake in ASM Pacific Technology.
B13: Finding: | C13: Already separated as Investment Income in standardized IS.
B14: Decision: | C14: No Adjustment
B15: Justification: | C15: No further adjustment needed.
A17: 3. FX Gains/Losses
B18: Description: | C18: Highly volatile: ranged from -23M (2020) to +45M (2024).
B19: Finding: | C19: Already classified below EBIT in standardized IS (non-operating).
B20: Decision: | C20: No Adjustment
B21: Justification: | C21: Already handled in standardization.
A23: 4. Stock-Based Compensation
B24: Description: | C24: EUR 42M in 2024, growing over time.
B25: Finding: | C25: Already included in operating expenses in CapIQ data.
B26: Decision: | C26: No Adjustment
B27: Justification: | C27: No adjustment needed.
A29: 5. Goodwill (LPE Acquisition 2022)
B30: Description: | C30: EUR 321M from LPE acquisition.
B31: Finding: | C31: No impairment charges taken.
B32: Decision: | C32: No Adjustment
B33: Justification: | C33: Monitor for future impairment risk.
A35: 6. Asset Writedowns & Unusual Items
B36: Description: | C36: Small and sporadic.
B37: Finding: | C37: Already classified as non-recurring in standardized IS.
B38: Decision: | C38: No Adjustment
B39: Justification: | C39: No adjustment needed.
A42: Summary
A43: No material adjustments required. The standardization process already handles all analytical reclassifications. Adjusted tabs pass through from Standardized tabs.

Sheet Adj ASM
A1: Standardized Financial Statements - ASM International NV
A2: (EUR 000)
B3: ='Std ASM'!B3 | C3: ='Std ASM'!C3 | D3: ='Std ASM'!D3 | E3: ='Std ASM'!E3 | F3: ='Std ASM'!F3 | G3: ='Std ASM'!G3
A5: Operating cash % | B5: ='Std ASM'!B5 | C5: ='Std ASM'!C5 | D5: ='Std ASM'!D5 | E5: ='Std ASM'!E5 | F5: ='Std ASM'!F5 | G5: ='Std ASM'!G5
A6: Tax rate (effective) | B6: ='Std ASM'!B6 | C6: ='Std ASM'!C6 | D6: ='Std ASM'!D6 | E6: ='Std ASM'!E6 | F6: ='Std ASM'!F6 | G6: ='Std ASM'!G6
A8: INCOME STATEMENT
A9: Revenue | B9: ='Std ASM'!B9 | C9: ='Std ASM'!C9 | D9: ='Std ASM'!D9 | E9: ='Std ASM'!E9 | F9: ='Std ASM'!F9 | G9: ='Std ASM'!G9
A10: Cost of Sales | B10: ='Std ASM'!B10 | C10: ='Std ASM'!C10 | D10: ='Std ASM'!D10 | E10: ='Std ASM'!E10 | F10: ='Std ASM'!F10 | G10: ='Std ASM'!G10
A11: Gross Profit | B11: ='Std ASM'!B11 | C11: ='Std ASM'!C11 | D11: ='Std ASM'!D11 | E11: ='Std ASM'!E11 | F11: ='Std ASM'!F11 | G11: ='Std ASM'!G11
A12: SG&A | B12: ='Std ASM'!B12 | C12: ='Std ASM'!C12 | D12: ='Std ASM'!D12 | E12: ='Std ASM'!E12 | F12: ='Std ASM'!F12 | G12: ='Std ASM'!G12
A13: R&D | B13: ='Std ASM'!B13 | C13: ='Std ASM'!C13 | D13: ='Std ASM'!D13 | E13: ='Std ASM'!E13 | F13: ='Std ASM'!F13 | G13: ='Std ASM'!G13
A14: Depreciation & Amortization | B14: ='Std ASM'!B14 | C14: ='Std ASM'!C14 | D14: ='Std ASM'!D14 | E14: ='Std ASM'!E14 | F14: ='Std ASM'!F14 | G14: ='Std ASM'!G14
A15: Other Operating Expense | B15: ='Std ASM'!B15 | C15: ='Std ASM'!C15 | D15: ='Std ASM'!D15 | E15: ='Std ASM'!E15 | F15: ='Std ASM'!F15 | G15: ='Std ASM'!G15
A16: Total Operating Expense | B16: ='Std ASM'!B16 | C16: ='Std ASM'!C16 | D16: ='Std ASM'!D16 | E16: ='Std ASM'!E16 | F16: ='Std ASM'!F16 | G16: ='Std ASM'!G16
A17: Recurring Operating Profit | B17: ='Std ASM'!B17 | C17: ='Std ASM'!C17 | D17: ='Std ASM'!D17 | E17: ='Std ASM'!E17 | F17: ='Std ASM'!F17 | G17: ='Std ASM'!G17
A19: Non-recurring items:
A20: Gain/Loss on Sale of Investments | B20: ='Std ASM'!B20 | C20: ='Std ASM'!C20 | D20: ='Std ASM'!D20 | E20: ='Std ASM'!E20 | F20: ='Std ASM'!F20 | G20: ='Std ASM'!G20
A21: Gain/Loss on Sale of Assets | B21: ='Std ASM'!B21 | C21: ='Std ASM'!C21 | D21: ='Std ASM'!D21 | E21: ='Std ASM'!E21 | F21: ='Std ASM'!F21 | G21: ='Std ASM'!G21
A22: Asset Writedown | B22: ='Std ASM'!B22 | C22: ='Std ASM'!C22 | D22: ='Std ASM'!D22 | E22: ='Std ASM'!E22 | F22: ='Std ASM'!F22 | G22: ='Std ASM'!G22
A23: Other Unusual Items | B23: ='Std ASM'!B23 | C23: ='Std ASM'!C23 | D23: ='Std ASM'!D23 | E23: ='Std ASM'!E23 | F23: ='Std ASM'!F23 | G23: ='Std ASM'!G23
A24: Total Non-recurring | B24: ='Std ASM'!B24 | C24: ='Std ASM'!C24 | D24: ='Std ASM'!D24 | E24: ='Std ASM'!E24 | F24: ='Std ASM'!F24 | G24: ='Std ASM'!G24
A25: EBIT | B25: ='Std ASM'!B25 | C25: ='Std ASM'!C25 | D25: ='Std ASM'!D25 | E25: ='Std ASM'!E25 | F25: ='Std ASM'!F25 | G25: ='Std ASM'!G25
A27: Investment Income (Equity Method) | B27: ='Std ASM'!B27 | C27: ='Std ASM'!C27 | D27: ='Std ASM'!D27 | E27: ='Std ASM'!E27 | F27: ='Std ASM'!F27 | G27: ='Std ASM'!G27
A28: Interest Income | B28: ='Std ASM'!B28 | C28: ='Std ASM'!C28 | D28: ='Std ASM'!D28 | E28: ='Std ASM'!E28 | F28: ='Std ASM'!F28 | G28: ='Std ASM'!G28
A29: Interest Expense | B29: ='Std ASM'!B29 | C29: ='Std ASM'!C29 | D29: ='Std ASM'!D29 | E29: ='Std ASM'!E29 | F29: ='Std ASM'!F29 | G29: ='Std ASM'!G29
A30: FX Gains/(Losses) | B30: ='Std ASM'!B30 | C30: ='Std ASM'!C30 | D30: ='Std ASM'!D30 | E30: ='Std ASM'!E30 | F30: ='Std ASM'!F30 | G30: ='Std ASM'!G30
A31: Profit Before Tax | B31: ='Std ASM'!B31 | C31: ='Std ASM'!C31 | D31: ='Std ASM'!D31 | E31: ='Std ASM'!E31 | F31: ='Std ASM'!F31 | G31: ='Std ASM'!G31
A32: Tax Expense | B32: ='Std ASM'!B32 | C32: ='Std ASM'!C32 | D32: ='Std ASM'!D32 | E32: ='Std ASM'!E32 | F32: ='Std ASM'!F32 | G32: ='Std ASM'!G32
... A40: Dividends per Share | B40: ='Std ASM'!B40 | C40: ='Std ASM'!C40 | D40: ='Std ASM'!D40 | E40: ='Std ASM'!E40 | F40: ='Std ASM'!F40 | G40: ='Std ASM'!G40
A43: BALANCE SHEET (Reformulated)
A44: Operating Working Capital:
A45: Trade Receivables | B45: ='Std ASM'!B45 | C45: ='Std ASM'!C45 | D45: ='Std ASM'!D45 | E45: ='Std ASM'!E45 | F45: ='Std ASM'!F45 | G45: ='Std ASM'!G45
A46: + Other Receivables | B46: ='Std ASM'!B46 | C46: ='Std ASM'!C46 | D46: ='Std ASM'!D46 | E46: ='Std ASM'!E46 | F46: ='Std ASM'!F46 | G46: ='Std ASM'!G46
A47: + Inventories | B47: ='Std ASM'!B47 | C47: ='Std ASM'!C47 | D47: ='Std ASM'!D47 | E47: ='Std ASM'!E47 | F47: ='Std ASM'!F47 | G47: ='Std ASM'!G47
A48: + Prepaid & Other CA | B48: ='Std ASM'!B48 | C48: ='Std ASM'!C48 | D48: ='Std ASM'!D48 | E48: ='Std ASM'!E48 | F48: ='Std ASM'!F48 | G48: ='Std ASM'!G48
A49: - Accounts Payable | B49: ='Std ASM'!B49 | C49: ='Std ASM'!C49 | D49: ='Std ASM'!D49 | E49: ='Std ASM'!E49 | F49: ='Std ASM'!F49 | G49: ='Std ASM'!G49
A50: - Accrued Expenses | B50: ='Std ASM'!B50 | C50: ='Std ASM'!C50 | D50: ='Std ASM'!D50 | E50: ='Std ASM'!E50 | F50: ='Std ASM'!F50 | G50: ='Std ASM'!G50
A51: - Unearned Revenue / Contract Liabilities | B51: ='Std ASM'!B51 | C51: ='Std ASM'!C51 | D51: ='Std ASM'!D51 | E51: ='Std ASM'!E51 | F51: ='Std ASM'!F51 | G51: ='Std ASM'!G51
A52: - Income Taxes Payable | B52: ='Std ASM'!B52 | C52: ='Std ASM'!C52 | D52: ='Std ASM'!D52 | E52: ='Std ASM'!E52 | F52: ='Std ASM'!F52 | G52: ='Std ASM'!G52
A53: - Other Current Liabilities | B53: ='Std ASM'!B53 | C53: ='Std ASM'!C53 | D53: ='Std ASM'!D53 | E53: ='Std ASM'!E53 | F53: ='Std ASM'!F53 | G53: ='Std ASM'!G53
A54: =Operating Working Capital | B54: ='Std ASM'!B54 | C54: ='Std ASM'!C54 | D54: ='Std ASM'!D54 | E54: ='Std ASM'!E54 | F54: ='Std ASM'!F54 | G54: ='Std ASM'!G54
A56: Net Non-Current Operating Assets:
A57: PP&E (net, incl. ROU) | B57: ='Std ASM'!B57 | C57: ='Std ASM'!C57 | D57: ='Std ASM'!D57 | E57: ='Std ASM'!E57 | F57: ='Std ASM'!F57 | G57: ='Std ASM'!G57
A58: + Goodwill | B58: ='Std ASM'!B58 | C58: ='Std ASM'!C58 | D58: ='Std ASM'!D58 | E58: ='Std ASM'!E58 | F58: ='Std ASM'!F58 | G58: ='Std ASM'!G58
A59: + Other Intangible Assets | B59: ='Std ASM'!B59 | C59: ='Std ASM'!C59 | D59: ='Std ASM'!D59 | E59: ='Std ASM'!E59 | F59: ='Std ASM'!F59 | G59: ='Std ASM'!G59
A60: + Deferred Tax Assets | B60: ='Std ASM'!B60 | C60: ='Std ASM'!C60 | D60: ='Std ASM'!D60 | E60: ='Std ASM'!E60 | F60: ='Std ASM'!F60 | G60: ='Std ASM'!G60
A61: + Deferred Charges & LT Intangibles | B61: ='Std ASM'!B61 | C61: ='Std ASM'!C61 | D61: ='Std ASM'!D61 | E61: ='Std ASM'!E61 | F61: ='Std ASM'!F61 | G61: ='Std ASM'!G61
A62: + Other Non-Current Assets | B62: ='Std ASM'!B62 | C62: ='Std ASM'!C62 | D62: ='Std ASM'!D62 | E62: ='Std ASM'!E62 | F62: ='Std ASM'!F62 | G62: ='Std ASM'!G62
A63: - Deferred Tax Liabilities | B63: ='Std ASM'!B63 | C63: ='Std ASM'!C63 | D63: ='Std ASM'!D63 | E63: ='Std ASM'!E63 | F63: ='Std ASM'!F63 | G63: ='Std ASM'!G63
A64: - Other Non-Current Liabilities | B64: ='Std ASM'!B64 | C64: ='Std ASM'!C64 | D64: ='Std ASM'!D64 | E64: ='Std ASM'!E64 | F64: ='Std ASM'!F64 | G64: ='Std ASM'!G64
A65: =Net Non-Current Operating Assets | B65: ='Std ASM'!B65 | C65: ='Std ASM'!C65 | D65: ='Std ASM'!D65 | E65: ='Std ASM'!E65 | F65: ='Std ASM'!F65 | G65: ='Std ASM'!G65
A67: =Net Operating Assets | B67: ='Std ASM'!B67 | C67: ='Std ASM'!C67 | D67: ='Std ASM'!D67 | E67: ='Std ASM'!E67 | F67: ='Std ASM'!F67 | G67: ='Std ASM'!G67
A69: Investment Assets:
A70: Long-Term Investments | B70: ='Std ASM'!B70 | C70: ='Std ASM'!C70 | D70: ='Std ASM'!D70 | E70: ='Std ASM'!E70 | F70: ='Std ASM'!F70 | G70: ='Std ASM'!G70
A71: =Total Investment Assets | B71: ='Std ASM'!B71 | C71: ='Std ASM'!C71 | D71: ='Std ASM'!D71 | E71: ='Std ASM'!E71 | F71: ='Std ASM'!F71 | G71: ='Std ASM'!G71
A73: =Business Assets | B73: ='Std ASM'!B73 | C73: ='Std ASM'!C73 | D73: ='Std ASM'!D73 | E73: ='Std ASM'!E73 | F73: ='Std ASM'!F73 | G73: ='Std ASM'!G73
A75: FINANCING
A76: Lease Liabilities (current) | B76: ='Std ASM'!B76 | C76: ='Std ASM'!C76 | D76: ='Std ASM'!D76 | E76: ='Std ASM'!E76 | F76: ='Std ASM'!F76 | G76: ='Std ASM'!G76
A77: + Lease Liabilities (non-current) | B77: ='Std ASM'!B77 | C77: ='Std ASM'!C77 | D77: ='Std ASM'!D77 | E77: ='Std ASM'!E77 | F77: ='Std ASM'!F77 | G77: ='Std ASM'!G77
A78: =Total Debt | B78: ='Std ASM'!B78 | C78: ='Std ASM'!C78 | D78: ='Std ASM'!D78 | E78: ='Std ASM'!E78 | F78: ='Std ASM'!F78 | G78: ='Std ASM'!G78
A79: Cash & Equivalents | B79: ='Std ASM'!B79 | C79: ='Std ASM'!C79 | D79: ='Std ASM'!D79 | E79: ='Std ASM'!E79 | F79: ='Std ASM'!F79 | G79: ='Std ASM'!G79
A80: =Net Debt | B80: ='Std ASM'!B80 | C80: ='Std ASM'!C80 | D80: ='Std ASM'!D80 | E80: ='Std ASM'!E80 | F80: ='Std ASM'!F80 | G80: ='Std ASM'!G80
A81: Group Equity | B81: ='Std ASM'!B81 | C81: ='Std ASM'!C81 | D81: ='Std ASM'!D81 | E81: ='Std ASM'!E81 | F81: ='Std ASM'!F81 | G81: ='Std ASM'!G81
A82: =Invested Capital | B82: ='Std ASM'!B82 | C82: ='Std ASM'!C82 | D82: ='Std ASM'!D82 | E82: ='Std ASM'!E82 | F82: ='Std ASM'!F82 | G82: ='Std ASM'!G82
A83: BS Check (should = 0) | B83: ='Std ASM'!B83 | C83: ='Std ASM'!C83 | D83: ='Std ASM'!D83 | E83: ='Std ASM'!E83 | F83: ='Std ASM'!F83 | G83: ='Std ASM'!G83
A86: FREE CASH FLOW
A87: NOPAT | B87: ='Std ASM'!B87 | C87: ='Std ASM'!C87 | D87: ='Std ASM'!D87 | E87: ='Std ASM'!E87 | F87: ='Std ASM'!F87 | G87: ='Std ASM'!G87
A88: + D&A | B88: ='Std ASM'!B88 | C88: ='Std ASM'!C88 | D88: ='Std ASM'!D88 | E88: ='Std ASM'!E88 | F88: ='Std ASM'!F88 | G88: ='Std ASM'!G88
A89: - Change in OWC | B89: ='Std ASM'!B89 | C89: ='Std ASM'!C89 | D89: ='Std ASM'!D89 | E89: ='Std ASM'!E89 | F89: ='Std ASM'!F89 | G89: ='Std ASM'!G89
A90: - CapEx | B90: ='Std ASM'!B90 | C90: ='Std ASM'!C90 | D90: ='Std ASM'!D90 | E90: ='Std ASM'!E90 | F90: ='Std ASM'!F90 | G90: ='Std ASM'!G90
A91: - Purchase of Intangibles | B91: ='Std ASM'!B91 | C91: ='Std ASM'!C91 | D91: ='Std ASM'!D91 | E91: ='Std ASM'!E91 | F91: ='Std ASM'!F91 | G91: ='Std ASM'!G91
A92: =Operating CF after investment | B92: ='Std ASM'!B92 | C92: ='Std ASM'!C92 | D92: ='Std ASM'!D92 | E92: ='Std ASM'!E92 | F92: ='Std ASM'!F92 | G92: ='Std ASM'!G92
A94: + Net Investment Profit after tax | B94: ='Std ASM'!B94 | C94: ='Std ASM'!C94 | D94: ='Std ASM'!D94 | E94: ='Std ASM'!E94 | F94: ='Std ASM'!F94 | G94: ='Std ASM'!G94
A95: - Change in Investment Assets | B95: ='Std ASM'!B95 | C95: ='Std ASM'!C95 | D95: ='Std ASM'!D95 | E95: ='Std ASM'!E95 | F95: ='Std ASM'!F95 | G95: ='Std ASM'!G95
A96: =FCF to Debt & Equity | B96: ='Std ASM'!B96 | C96: ='Std ASM'!C96 | D96: ='Std ASM'!D96 | E96: ='Std ASM'!E96 | F96: ='Std ASM'!F96 | G96: ='Std ASM'!G96
A97: - Interest Expense after tax | B97: ='Std ASM'!B97 | C97: ='Std ASM'!C97 | D97: ='Std ASM'!D97 | E97: ='Std ASM'!E97 | F97: ='Std ASM'!F97 | G97: ='Std ASM'!G97
A98: + Change in Debt | B98: ='Std ASM'!B98 | C98: ='Std ASM'!C98 | D98: ='Std ASM'!D98 | E98: ='Std ASM'!E98 | F98: ='Std ASM'!F98 | G98: ='Std ASM'!G98
A99: =FCF to Equity | B99: ='Std ASM'!B99 | C99: ='Std ASM'!C99 | D99: ='Std ASM'!D99 | E99: ='Std ASM'!E99 | F99: ='Std ASM'!F99 | G99: ='Std ASM'!G99

Sheet Adj AIXTRON
A1: Standardized Financial Statements - AIXTRON SE
A2: (EUR 000)
B3: ='Std AIXTRON'!B3 | C3: ='Std AIXTRON'!C3 | D3: ='Std AIXTRON'!D3 | E3: ='Std AIXTRON'!E3 | F3: ='Std AIXTRON'!F3 | G3: ='Std AIXTRON'!G3
A5: Operating cash % | B5: ='Std AIXTRON'!B5 | C5: ='Std AIXTRON'!C5 | D5: ='Std AIXTRON'!D5 | E5: ='Std AIXTRON'!E5 | F5: ='Std AIXTRON'!F5 | G5: ='Std AIXTRON'!G5
A6: Tax rate (effective) | B6: ='Std AIXTRON'!B6 | C6: ='Std AIXTRON'!C6 | D6: ='Std AIXTRON'!D6 | E6: ='Std AIXTRON'!E6 | F6: ='Std AIXTRON'!F6 | G6: ='Std AIXTRON'!G6
A8: INCOME STATEMENT
A9: Revenue | B9: ='Std AIXTRON'!B9 | C9: ='Std AIXTRON'!C9 | D9: ='Std AIXTRON'!D9 | E9: ='Std AIXTRON'!E9 | F9: ='Std AIXTRON'!F9 | G9: ='Std AIXTRON'!G9
A10: Cost of Sales | B10: ='Std AIXTRON'!B10 | C10: ='Std AIXTRON'!C10 | D10: ='Std AIXTRON'!D10 | E10: ='Std AIXTRON'!E10 | F10: ='Std AIXTRON'!F10 | G10: ='Std AIXTRON'!G10
A11: Gross Profit | B11: ='Std AIXTRON'!B11 | C11: ='Std AIXTRON'!C11 | D11: ='Std AIXTRON'!D11 | E11: ='Std AIXTRON'!E11 | F11: ='Std AIXTRON'!F11 | G11: ='Std AIXTRON'!G11
A12: SG&A | B12: ='Std AIXTRON'!B12 | C12: ='Std AIXTRON'!C12 | D12: ='Std AIXTRON'!D12 | E12: ='Std AIXTRON'!E12 | F12: ='Std AIXTRON'!F12 | G12: ='Std AIXTRON'!G12
A13: R&D | B13: ='Std AIXTRON'!B13 | C13: ='Std AIXTRON'!C13 | D13: ='Std AIXTRON'!D13 | E13: ='Std AIXTRON'!E13 | F13: ='Std AIXTRON'!F13 | G13: ='Std AIXTRON'!G13
A14: Depreciation & Amortization | B14: ='Std AIXTRON'!B14 | C14: ='Std AIXTRON'!C14 | D14: ='Std AIXTRON'!D14 | E14: ='Std AIXTRON'!E14 | F14: ='Std AIXTRON'!F14 | G14: ='Std AIXTRON'!G14
A15: Other Operating Expense | B15: ='Std AIXTRON'!B15 | C15: ='Std AIXTRON'!C15 | D15: ='Std AIXTRON'!D15 | E15: ='Std AIXTRON'!E15 | F15: ='Std AIXTRON'!F15 | G15: ='Std AIXTRON'!G15
A16: Total Operating Expense | B16: ='Std AIXTRON'!B16 | C16: ='Std AIXTRON'!C16 | D16: ='Std AIXTRON'!D16 | E16: ='Std AIXTRON'!E16 | F16: ='Std AIXTRON'!F16 | G16: ='Std AIXTRON'!G16
A17: Recurring Operating Profit | B17: ='Std AIXTRON'!B17 | C17: ='Std AIXTRON'!C17 | D17: ='Std AIXTRON'!D17 | E17: ='Std AIXTRON'!E17 | F17: ='Std AIXTRON'!F17 | G17: ='Std AIXTRON'!G17
A19: Non-recurring items:
A20: Gain/Loss on Sale of Investments | B20: ='Std AIXTRON'!B20 | C20: ='Std AIXTRON'!C20 | D20: ='Std AIXTRON'!D20 | E20: ='Std AIXTRON'!E20 | F20: ='Std AIXTRON'!F20 | G20: ='Std AIXTRON'!G20
A21: Gain/Loss on Sale of Assets | B21: ='Std AIXTRON'!B21 | C21: ='Std AIXTRON'!C21 | D21: ='Std AIXTRON'!D21 | E21: ='Std AIXTRON'!E21 | F21: ='Std AIXTRON'!F21 | G21: ='Std AIXTRON'!G21
A22: Asset Writedown | B22: ='Std AIXTRON'!B22 | C22: ='Std AIXTRON'!C22 | D22: ='Std AIXTRON'!D22 | E22: ='Std AIXTRON'!E22 | F22: ='Std AIXTRON'!F22 | G22: ='Std AIXTRON'!G22
A23: Other Unusual Items | B23: ='Std AIXTRON'!B23 | C23: ='Std AIXTRON'!C23 | D23: ='Std AIXTRON'!D23 | E23: ='Std AIXTRON'!E23 | F23: ='Std AIXTRON'!F23 | G23: ='Std AIXTRON'!G23
A24: Total Non-recurring | B24: ='Std AIXTRON'!B24 | C24: ='Std AIXTRON'!C24 | D24: ='Std AIXTRON'!D24 | E24: ='Std AIXTRON'!E24 | F24: ='Std AIXTRON'!F24 | G24: ='Std AIXTRON'!G24
A25: EBIT | B25: ='Std AIXTRON'!B25 | C25: ='Std AIXTRON'!C25 | D25: ='Std AIXTRON'!D25 | E25: ='Std AIXTRON'!E25 | F25: ='Std AIXTRON'!F25 | G25: ='Std AIXTRON'!G25
A27: Investment Income (Equity Method) | B27: ='Std AIXTRON'!B27 | C27: ='Std AIXTRON'!C27 | D27: ='Std AIXTRON'!D27 | E27: ='Std AIXTRON'!E27 | F27: ='Std AIXTRON'!F27 | G27: ='Std AIXTRON'!G27
A28: Interest Income | B28: ='Std AIXTRON'!B28 | C28: ='Std AIXTRON'!C28 | D28: ='Std AIXTRON'!D28 | E28: ='Std AIXTRON'!E28 | F28: ='Std AIXTRON'!F28 | G28: ='Std AIXTRON'!G28
A29: Interest Expense | B29: ='Std AIXTRON'!B29 | C29: ='Std AIXTRON'!C29 | D29: ='Std AIXTRON'!D29 | E29: ='Std AIXTRON'!E29 | F29: ='Std AIXTRON'!F29 | G29: ='Std AIXTRON'!G29
A30: FX Gains/(Losses) | B30: ='Std AIXTRON'!B30 | C30: ='Std AIXTRON'!C30 | D30: ='Std AIXTRON'!D30 | E30: ='Std AIXTRON'!E30 | F30: ='Std AIXTRON'!F30 | G30: ='Std AIXTRON'!G30
A31: Profit Before Tax | B31: ='Std AIXTRON'!B31 | C31: ='Std AIXTRON'!C31 | D31: ='Std AIXTRON'!D31 | E31: ='Std AIXTRON'!E31 | F31: ='Std AIXTRON'!F31 | G31: ='Std AIXTRON'!G31
A32: Tax Expense | B32: ='Std AIXTRON'!B32 | C32: ='Std AIXTRON'!C32 | D32: ='Std AIXTRON'!D32 | E32: ='Std AIXTRON'!E32 | F32: ='Std AIXTRON'!F32 | G32: ='Std AIXTRON'!G32
... A40: Dividends per Share | B40: ='Std AIXTRON'!B40 | C40: ='Std AIXTRON'!C40 | D40: ='Std AIXTRON'!D40 | E40: ='Std AIXTRON'!E40 | F40: ='Std AIXTRON'!F40 | G40: ='Std AIXTRON'!G40
A43: BALANCE SHEET (Reformulated)
A44: Operating Working Capital:
A45: Trade Receivables | B45: ='Std AIXTRON'!B45 | C45: ='Std AIXTRON'!C45 | D45: ='Std AIXTRON'!D45 | E45: ='Std AIXTRON'!E45 | F45: ='Std AIXTRON'!F45 | G45: ='Std AIXTRON'!G45
A46: + Other Receivables | B46: ='Std AIXTRON'!B46 | C46: ='Std AIXTRON'!C46 | D46: ='Std AIXTRON'!D46 | E46: ='Std AIXTRON'!E46 | F46: ='Std AIXTRON'!F46 | G46: ='Std AIXTRON'!G46
A47: + Inventories | B47: ='Std AIXTRON'!B47 | C47: ='Std AIXTRON'!C47 | D47: ='Std AIXTRON'!D47 | E47: ='Std AIXTRON'!E47 | F47: ='Std AIXTRON'!F47 | G47: ='Std AIXTRON'!G47
A48: + Prepaid & Other CA | B48: ='Std AIXTRON'!B48 | C48: ='Std AIXTRON'!C48 | D48: ='Std AIXTRON'!D48 | E48: ='Std AIXTRON'!E48 | F48: ='Std AIXTRON'!F48 | G48: ='Std AIXTRON'!G48
A49: - Accounts Payable | B49: ='Std AIXTRON'!B49 | C49: ='Std AIXTRON'!C49 | D49: ='Std AIXTRON'!D49 | E49: ='Std AIXTRON'!E49 | F49: ='Std AIXTRON'!F49 | G49: ='Std AIXTRON'!G49
A50: - Accrued Expenses | B50: ='Std AIXTRON'!B50 | C50: ='Std AIXTRON'!C50 | D50: ='Std AIXTRON'!D50 | E50: ='Std AIXTRON'!E50 | F50: ='Std AIXTRON'!F50 | G50: ='Std AIXTRON'!G50
A51: - Unearned Revenue / Contract Liabilities | B51: ='Std AIXTRON'!B51 | C51: ='Std AIXTRON'!C51 | D51: ='Std AIXTRON'!D51 | E51: ='Std AIXTRON'!E51 | F51: ='Std AIXTRON'!F51 | G51: ='Std AIXTRON'!G51
A52: - Income Taxes Payable | B52: ='Std AIXTRON'!B52 | C52: ='Std AIXTRON'!C52 | D52: ='Std AIXTRON'!D52 | E52: ='Std AIXTRON'!E52 | F52: ='Std AIXTRON'!F52 | G52: ='Std AIXTRON'!G52
A53: - Other Current Liabilities | B53: ='Std AIXTRON'!B53 | C53: ='Std AIXTRON'!C53 | D53: ='Std AIXTRON'!D53 | E53: ='Std AIXTRON'!E53 | F53: ='Std AIXTRON'!F53 | G53: ='Std AIXTRON'!G53
A54: =Operating Working Capital | B54: ='Std AIXTRON'!B54 | C54: ='Std AIXTRON'!C54 | D54: ='Std AIXTRON'!D54 | E54: ='Std AIXTRON'!E54 | F54: ='Std AIXTRON'!F54 | G54: ='Std AIXTRON'!G54
A56: Net Non-Current Operating Assets:
A57: PP&E (net, incl. ROU) | B57: ='Std AIXTRON'!B57 | C57: ='Std AIXTRON'!C57 | D57: ='Std AIXTRON'!D57 | E57: ='Std AIXTRON'!E57 | F57: ='Std AIXTRON'!F57 | G57: ='Std AIXTRON'!G57
A58: + Goodwill | B58: ='Std AIXTRON'!B58 | C58: ='Std AIXTRON'!C58 | D58: ='Std AIXTRON'!D58 | E58: ='Std AIXTRON'!E58 | F58: ='Std AIXTRON'!F58 | G58: ='Std AIXTRON'!G58
A59: + Other Intangible Assets | B59: ='Std AIXTRON'!B59 | C59: ='Std AIXTRON'!C59 | D59: ='Std AIXTRON'!D59 | E59: ='Std AIXTRON'!E59 | F59: ='Std AIXTRON'!F59 | G59: ='Std AIXTRON'!G59
A60: + Deferred Tax Assets | B60: ='Std AIXTRON'!B60 | C60: ='Std AIXTRON'!C60 | D60: ='Std AIXTRON'!D60 | E60: ='Std AIXTRON'!E60 | F60: ='Std AIXTRON'!F60 | G60: ='Std AIXTRON'!G60
A61: + Deferred Charges & LT Intangibles | B61: ='Std AIXTRON'!B61 | C61: ='Std AIXTRON'!C61 | D61: ='Std AIXTRON'!D61 | E61: ='Std AIXTRON'!E61 | F61: ='Std AIXTRON'!F61 | G61: ='Std AIXTRON'!G61
A62: + Other Non-Current Assets | B62: ='Std AIXTRON'!B62 | C62: ='Std AIXTRON'!C62 | D62: ='Std AIXTRON'!D62 | E62: ='Std AIXTRON'!E62 | F62: ='Std AIXTRON'!F62 | G62: ='Std AIXTRON'!G62
A63: - Deferred Tax Liabilities | B63: ='Std AIXTRON'!B63 | C63: ='Std AIXTRON'!C63 | D63: ='Std AIXTRON'!D63 | E63: ='Std AIXTRON'!E63 | F63: ='Std AIXTRON'!F63 | G63: ='Std AIXTRON'!G63
A64: - Other Non-Current Liabilities | B64: ='Std AIXTRON'!B64 | C64: ='Std AIXTRON'!C64 | D64: ='Std AIXTRON'!D64 | E64: ='Std AIXTRON'!E64 | F64: ='Std AIXTRON'!F64 | G64: ='Std AIXTRON'!G64
A65: =Net Non-Current Operating Assets | B65: ='Std AIXTRON'!B65 | C65: ='Std AIXTRON'!C65 | D65: ='Std AIXTRON'!D65 | E65: ='Std AIXTRON'!E65 | F65: ='Std AIXTRON'!F65 | G65: ='Std AIXTRON'!G65
A67: =Net Operating Assets | B67: ='Std AIXTRON'!B67 | C67: ='Std AIXTRON'!C67 | D67: ='Std AIXTRON'!D67 | E67: ='Std AIXTRON'!E67 | F67: ='Std AIXTRON'!F67 | G67: ='Std AIXTRON'!G67
A69: Investment Assets:
A70: Long-Term Investments | B70: ='Std AIXTRON'!B70 | C70: ='Std AIXTRON'!C70 | D70: ='Std AIXTRON'!D70 | E70: ='Std AIXTRON'!E70 | F70: ='Std AIXTRON'!F70 | G70: ='Std AIXTRON'!G70
A71: =Total Investment Assets | B71: ='Std AIXTRON'!B71 | C71: ='Std AIXTRON'!C71 | D71: ='Std AIXTRON'!D71 | E71: ='Std AIXTRON'!E71 | F71: ='Std AIXTRON'!F71 | G71: ='Std AIXTRON'!G71
A73: =Business Assets | B73: ='Std AIXTRON'!B73 | C73: ='Std AIXTRON'!C73 | D73: ='Std AIXTRON'!D73 | E73: ='Std AIXTRON'!E73 | F73: ='Std AIXTRON'!F73 | G73: ='Std AIXTRON'!G73
A75: FINANCING
A76: Lease Liabilities (current) | B76: ='Std AIXTRON'!B76 | C76: ='Std AIXTRON'!C76 | D76: ='Std AIXTRON'!D76 | E76: ='Std AIXTRON'!E76 | F76: ='Std AIXTRON'!F76 | G76: ='Std AIXTRON'!G76
A77: + Lease Liabilities (non-current) | B77: ='Std AIXTRON'!B77 | C77: ='Std AIXTRON'!C77 | D77: ='Std AIXTRON'!D77 | E77: ='Std AIXTRON'!E77 | F77: ='Std AIXTRON'!F77 | G77: ='Std AIXTRON'!G77
A78: =Total Debt | B78: ='Std AIXTRON'!B78 | C78: ='Std AIXTRON'!C78 | D78: ='Std AIXTRON'!D78 | E78: ='Std AIXTRON'!E78 | F78: ='Std AIXTRON'!F78 | G78: ='Std AIXTRON'!G78
A79: Cash & Equivalents | B79: ='Std AIXTRON'!B79 | C79: ='Std AIXTRON'!C79 | D79: ='Std AIXTRON'!D79 | E79: ='Std AIXTRON'!E79 | F79: ='Std AIXTRON'!F79 | G79: ='Std AIXTRON'!G79
A80: =Net Debt | B80: ='Std AIXTRON'!B80 | C80: ='Std AIXTRON'!C80 | D80: ='Std AIXTRON'!D80 | E80: ='Std AIXTRON'!E80 | F80: ='Std AIXTRON'!F80 | G80: ='Std AIXTRON'!G80
A81: Group Equity | B81: ='Std AIXTRON'!B81 | C81: ='Std AIXTRON'!C81 | D81: ='Std AIXTRON'!D81 | E81: ='Std AIXTRON'!E81 | F81: ='Std AIXTRON'!F81 | G81: ='Std AIXTRON'!G81
A82: =Invested Capital | B82: ='Std AIXTRON'!B82 | C82: ='Std AIXTRON'!C82 | D82: ='Std AIXTRON'!D82 | E82: ='Std AIXTRON'!E82 | F82: ='Std AIXTRON'!F82 | G82: ='Std AIXTRON'!G82
A83: BS Check (should = 0) | B83: ='Std AIXTRON'!B83 | C83: ='Std AIXTRON'!C83 | D83: ='Std AIXTRON'!D83 | E83: ='Std AIXTRON'!E83 | F83: ='Std AIXTRON'!F83 | G83: ='Std AIXTRON'!G83
A86: FREE CASH FLOW
A87: NOPAT | B87: ='Std AIXTRON'!B87 | C87: ='Std AIXTRON'!C87 | D87: ='Std AIXTRON'!D87 | E87: ='Std AIXTRON'!E87 | F87: ='Std AIXTRON'!F87 | G87: ='Std AIXTRON'!G87
A88: + D&A | B88: ='Std AIXTRON'!B88 | C88: ='Std AIXTRON'!C88 | D88: ='Std AIXTRON'!D88 | E88: ='Std AIXTRON'!E88 | F88: ='Std AIXTRON'!F88 | G88: ='Std AIXTRON'!G88
A89: - Change in OWC | B89: ='Std AIXTRON'!B89 | C89: ='Std AIXTRON'!C89 | D89: ='Std AIXTRON'!D89 | E89: ='Std AIXTRON'!E89 | F89: ='Std AIXTRON'!F89 | G89: ='Std AIXTRON'!G89
A90: - CapEx | B90: ='Std AIXTRON'!B90 | C90: ='Std AIXTRON'!C90 | D90: ='Std AIXTRON'!D90 | E90: ='Std AIXTRON'!E90 | F90: ='Std AIXTRON'!F90 | G90: ='Std AIXTRON'!G90
A91: - Purchase of Intangibles | B91: ='Std AIXTRON'!B91 | C91: ='Std AIXTRON'!C91 | D91: ='Std AIXTRON'!D91 | E91: ='Std AIXTRON'!E91 | F91: ='Std AIXTRON'!F91 | G91: ='Std AIXTRON'!G91
A92: =Operating CF after investment | B92: ='Std AIXTRON'!B92 | C92: ='Std AIXTRON'!C92 | D92: ='Std AIXTRON'!D92 | E92: ='Std AIXTRON'!E92 | F92: ='Std AIXTRON'!F92 | G92: ='Std AIXTRON'!G92
A94: + Net Investment Profit after tax | B94: ='Std AIXTRON'!B94 | C94: ='Std AIXTRON'!C94 | D94: ='Std AIXTRON'!D94 | E94: ='Std AIXTRON'!E94 | F94: ='Std AIXTRON'!F94 | G94: ='Std AIXTRON'!G94
A95: - Change in Investment Assets | B95: ='Std AIXTRON'!B95 | C95: ='Std AIXTRON'!C95 | D95: ='Std AIXTRON'!D95 | E95: ='Std AIXTRON'!E95 | F95: ='Std AIXTRON'!F95 | G95: ='Std AIXTRON'!G95
A96: =FCF to Debt & Equity | B96: ='Std AIXTRON'!B96 | C96: ='Std AIXTRON'!C96 | D96: ='Std AIXTRON'!D96 | E96: ='Std AIXTRON'!E96 | F96: ='Std AIXTRON'!F96 | G96: ='Std AIXTRON'!G96
A97: - Interest Expense after tax | B97: ='Std AIXTRON'!B97 | C97: ='Std AIXTRON'!C97 | D97: ='Std AIXTRON'!D97 | E97: ='Std AIXTRON'!E97 | F97: ='Std AIXTRON'!F97 | G97: ='Std AIXTRON'!G97
A98: + Change in Debt | B98: ='Std AIXTRON'!B98 | C98: ='Std AIXTRON'!C98 | D98: ='Std AIXTRON'!D98 | E98: ='Std AIXTRON'!E98 | F98: ='Std AIXTRON'!F98 | G98: ='Std AIXTRON'!G98
A99: =FCF to Equity | B99: ='Std AIXTRON'!B99 | C99: ='Std AIXTRON'!C99 | D99: ='Std AIXTRON'!D99 | E99: ='Std AIXTRON'!E99 | F99: ='Std AIXTRON'!F99 | G99: ='Std AIXTRON'!G99

Sheet Adj AMAT
A1: Standardized Financial Statements - Applied Materials, Inc.
A2: (EUR 000)
B3: ='Std AMAT'!B3 | C3: ='Std AMAT'!C3 | D3: ='Std AMAT'!D3 | E3: ='Std AMAT'!E3 | F3: ='Std AMAT'!F3 | G3: ='Std AMAT'!G3
A5: Operating cash % | B5: ='Std AMAT'!B5 | C5: ='Std AMAT'!C5 | D5: ='Std AMAT'!D5 | E5: ='Std AMAT'!E5 | F5: ='Std AMAT'!F5 | G5: ='Std AMAT'!G5
A6: Tax rate (effective) | B6: ='Std AMAT'!B6 | C6: ='Std AMAT'!C6 | D6: ='Std AMAT'!D6 | E6: ='Std AMAT'!E6 | F6: ='Std AMAT'!F6 | G6: ='Std AMAT'!G6
A8: INCOME STATEMENT
A9: Revenue | B9: ='Std AMAT'!B9 | C9: ='Std AMAT'!C9 | D9: ='Std AMAT'!D9 | E9: ='Std AMAT'!E9 | F9: ='Std AMAT'!F9 | G9: ='Std AMAT'!G9
A10: Cost of Sales | B10: ='Std AMAT'!B10 | C10: ='Std AMAT'!C10 | D10: ='Std AMAT'!D10 | E10: ='Std AMAT'!E10 | F10: ='Std AMAT'!F10 | G10: ='Std AMAT'!G10
A11: Gross Profit | B11: ='Std AMAT'!B11 | C11: ='Std AMAT'!C11 | D11: ='Std AMAT'!D11 | E11: ='Std AMAT'!E11 | F11: ='Std AMAT'!F11 | G11: ='Std AMAT'!G11
A12: SG&A | B12: ='Std AMAT'!B12 | C12: ='Std AMAT'!C12 | D12: ='Std AMAT'!D12 | E12: ='Std AMAT'!E12 | F12: ='Std AMAT'!F12 | G12: ='Std AMAT'!G12
A13: R&D | B13: ='Std AMAT'!B13 | C13: ='Std AMAT'!C13 | D13: ='Std AMAT'!D13 | E13: ='Std AMAT'!E13 | F13: ='Std AMAT'!F13 | G13: ='Std AMAT'!G13
A14: Depreciation & Amortization | B14: ='Std AMAT'!B14 | C14: ='Std AMAT'!C14 | D14: ='Std AMAT'!D14 | E14: ='Std AMAT'!E14 | F14: ='Std AMAT'!F14 | G14: ='Std AMAT'!G14
A15: Other Operating Expense | B15: ='Std AMAT'!B15 | C15: ='Std AMAT'!C15 | D15: ='Std AMAT'!D15 | E15: ='Std AMAT'!E15 | F15: ='Std AMAT'!F15 | G15: ='Std AMAT'!G15
A16: Total Operating Expense | B16: ='Std AMAT'!B16 | C16: ='Std AMAT'!C16 | D16: ='Std AMAT'!D16 | E16: ='Std AMAT'!E16 | F16: ='Std AMAT'!F16 | G16: ='Std AMAT'!G16
A17: Recurring Operating Profit | B17: ='Std AMAT'!B17 | C17: ='Std AMAT'!C17 | D17: ='Std AMAT'!D17 | E17: ='Std AMAT'!E17 | F17: ='Std AMAT'!F17 | G17: ='Std AMAT'!G17
A19: Non-recurring items:
A20: Gain/Loss on Sale of Investments | B20: ='Std AMAT'!B20 | C20: ='Std AMAT'!C20 | D20: ='Std AMAT'!D20 | E20: ='Std AMAT'!E20 | F20: ='Std AMAT'!F20 | G20: ='Std AMAT'!G20
A21: Gain/Loss on Sale of Assets | B21: ='Std AMAT'!B21 | C21: ='Std AMAT'!C21 | D21: ='Std AMAT'!D21 | E21: ='Std AMAT'!E21 | F21: ='Std AMAT'!F21 | G21: ='Std AMAT'!G21
A22: Asset Writedown | B22: ='Std AMAT'!B22 | C22: ='Std AMAT'!C22 | D22: ='Std AMAT'!D22 | E22: ='Std AMAT'!E22 | F22: ='Std AMAT'!F22 | G22: ='Std AMAT'!G22
A23: Other Unusual Items | B23: ='Std AMAT'!B23 | C23: ='Std AMAT'!C23 | D23: ='Std AMAT'!D23 | E23: ='Std AMAT'!E23 | F23: ='Std AMAT'!F23 | G23: ='Std AMAT'!G23
A24: Total Non-recurring | B24: ='Std AMAT'!B24 | C24: ='Std AMAT'!C24 | D24: ='Std AMAT'!D24 | E24: ='Std AMAT'!E24 | F24: ='Std AMAT'!F24 | G24: ='Std AMAT'!G24
A25: EBIT | B25: ='Std AMAT'!B25 | C25: ='Std AMAT'!C25 | D25: ='Std AMAT'!D25 | E25: ='Std AMAT'!E25 | F25: ='Std AMAT'!F25 | G25: ='Std AMAT'!G25
A27: Investment Income (Equity Method) | B27: ='Std AMAT'!B27 | C27: ='Std AMAT'!C27 | D27: ='Std AMAT'!D27 | E27: ='Std AMAT'!E27 | F27: ='Std AMAT'!F27 | G27: ='Std AMAT'!G27
A28: Interest Income | B28: ='Std AMAT'!B28 | C28: ='Std AMAT'!C28 | D28: ='Std AMAT'!D28 | E28: ='Std AMAT'!E28 | F28: ='Std AMAT'!F28 | G28: ='Std AMAT'!G28
A29: Interest Expense | B29: ='Std AMAT'!B29 | C29: ='Std AMAT'!C29 | D29: ='Std AMAT'!D29 | E29: ='Std AMAT'!E29 | F29: ='Std AMAT'!F29 | G29: ='Std AMAT'!G29
A30: FX Gains/(Losses) | B30: ='Std AMAT'!B30 | C30: ='Std AMAT'!C30 | D30: ='Std AMAT'!D30 | E30: ='Std AMAT'!E30 | F30: ='Std AMAT'!F30 | G30: ='Std AMAT'!G30
A31: Profit Before Tax | B31: ='Std AMAT'!B31 | C31: ='Std AMAT'!C31 | D31: ='Std AMAT'!D31 | E31: ='Std AMAT'!E31 | F31: ='Std AMAT'!F31 | G31: ='Std AMAT'!G31
A32: Tax Expense | B32: ='Std AMAT'!B32 | C32: ='Std AMAT'!C32 | D32: ='Std AMAT'!D32 | E32: ='Std AMAT'!E32 | F32: ='Std AMAT'!F32 | G32: ='Std AMAT'!G32
... A40: Dividends per Share | B40: ='Std AMAT'!B40 | C40: ='Std AMAT'!C40 | D40: ='Std AMAT'!D40 | E40: ='Std AMAT'!E40 | F40: ='Std AMAT'!F40 | G40: ='Std AMAT'!G40
A43: BALANCE SHEET (Reformulated)
A44: Operating Working Capital:
A45: Trade Receivables | B45: ='Std AMAT'!B45 | C45: ='Std AMAT'!C45 | D45: ='Std AMAT'!D45 | E45: ='Std AMAT'!E45 | F45: ='Std AMAT'!F45 | G45: ='Std AMAT'!G45
A46: + Other Receivables | B46: ='Std AMAT'!B46 | C46: ='Std AMAT'!C46 | D46: ='Std AMAT'!D46 | E46: ='Std AMAT'!E46 | F46: ='Std AMAT'!F46 | G46: ='Std AMAT'!G46
A47: + Inventories | B47: ='Std AMAT'!B47 | C47: ='Std AMAT'!C47 | D47: ='Std AMAT'!D47 | E47: ='Std AMAT'!E47 | F47: ='Std AMAT'!F47 | G47: ='Std AMAT'!G47
A48: + Prepaid & Other CA | B48: ='Std AMAT'!B48 | C48: ='Std AMAT'!C48 | D48: ='Std AMAT'!D48 | E48: ='Std AMAT'!E48 | F48: ='Std AMAT'!F48 | G48: ='Std AMAT'!G48
A49: - Accounts Payable | B49: ='Std AMAT'!B49 | C49: ='Std AMAT'!C49 | D49: ='Std AMAT'!D49 | E49: ='Std AMAT'!E49 | F49: ='Std AMAT'!F49 | G49: ='Std AMAT'!G49
A50: - Accrued Expenses | B50: ='Std AMAT'!B50 | C50: ='Std AMAT'!C50 | D50: ='Std AMAT'!D50 | E50: ='Std AMAT'!E50 | F50: ='Std AMAT'!F50 | G50: ='Std AMAT'!G50
A51: - Unearned Revenue / Contract Liabilities | B51: ='Std AMAT'!B51 | C51: ='Std AMAT'!C51 | D51: ='Std AMAT'!D51 | E51: ='Std AMAT'!E51 | F51: ='Std AMAT'!F51 | G51: ='Std AMAT'!G51
A52: - Income Taxes Payable | B52: ='Std AMAT'!B52 | C52: ='Std AMAT'!C52 | D52: ='Std AMAT'!D52 | E52: ='Std AMAT'!E52 | F52: ='Std AMAT'!F52 | G52: ='Std AMAT'!G52
A53: - Other Current Liabilities | B53: ='Std AMAT'!B53 | C53: ='Std AMAT'!C53 | D53: ='Std AMAT'!D53 | E53: ='Std AMAT'!E53 | F53: ='Std AMAT'!F53 | G53: ='Std AMAT'!G53
A54: =Operating Working Capital | B54: ='Std AMAT'!B54 | C54: ='Std AMAT'!C54 | D54: ='Std AMAT'!D54 | E54: ='Std AMAT'!E54 | F54: ='Std AMAT'!F54 | G54: ='Std AMAT'!G54
A56: Net Non-Current Operating Assets:
A57: PP&E (net, incl. ROU) | B57: ='Std AMAT'!B57 | C57: ='Std AMAT'!C57 | D57: ='Std AMAT'!D57 | E57: ='Std AMAT'!E57 | F57: ='Std AMAT'!F57 | G57: ='Std AMAT'!G57
A58: + Goodwill | B58: ='Std AMAT'!B58 | C58: ='Std AMAT'!C58 | D58: ='Std AMAT'!D58 | E58: ='Std AMAT'!E58 | F58: ='Std AMAT'!F58 | G58: ='Std AMAT'!G58
A59: + Other Intangible Assets | B59: ='Std AMAT'!B59 | C59: ='Std AMAT'!C59 | D59: ='Std AMAT'!D59 | E59: ='Std AMAT'!E59 | F59: ='Std AMAT'!F59 | G59: ='Std AMAT'!G59
A60: + Deferred Tax Assets | B60: ='Std AMAT'!B60 | C60: ='Std AMAT'!C60 | D60: ='Std AMAT'!D60 | E60: ='Std AMAT'!E60 | F60: ='Std AMAT'!F60 | G60: ='Std AMAT'!G60
A61: + Deferred Charges & LT Intangibles | B61: ='Std AMAT'!B61 | C61: ='Std AMAT'!C61 | D61: ='Std AMAT'!D61 | E61: ='Std AMAT'!E61 | F61: ='Std AMAT'!F61 | G61: ='Std AMAT'!G61
A62: + Other Non-Current Assets | B62: ='Std AMAT'!B62 | C62: ='Std AMAT'!C62 | D62: ='Std AMAT'!D62 | E62: ='Std AMAT'!E62 | F62: ='Std AMAT'!F62 | G62: ='Std AMAT'!G62
A63: - Deferred Tax Liabilities | B63: ='Std AMAT'!B63 | C63: ='Std AMAT'!C63 | D63: ='Std AMAT'!D63 | E63: ='Std AMAT'!E63 | F63: ='Std AMAT'!F63 | G63: ='Std AMAT'!G63
A64: - Other Non-Current Liabilities | B64: ='Std AMAT'!B64 | C64: ='Std AMAT'!C64 | D64: ='Std AMAT'!D64 | E64: ='Std AMAT'!E64 | F64: ='Std AMAT'!F64 | G64: ='Std AMAT'!G64
A65: =Net Non-Current Operating Assets | B65: ='Std AMAT'!B65 | C65: ='Std AMAT'!C65 | D65: ='Std AMAT'!D65 | E65: ='Std AMAT'!E65 | F65: ='Std AMAT'!F65 | G65: ='Std AMAT'!G65
A67: =Net Operating Assets | B67: ='Std AMAT'!B67 | C67: ='Std AMAT'!C67 | D67: ='Std AMAT'!D67 | E67: ='Std AMAT'!E67 | F67: ='Std AMAT'!F67 | G67: ='Std AMAT'!G67
A69: Investment Assets:
A70: Long-Term Investments | B70: ='Std AMAT'!B70 | C70: ='Std AMAT'!C70 | D70: ='Std AMAT'!D70 | E70: ='Std AMAT'!E70 | F70: ='Std AMAT'!F70 | G70: ='Std AMAT'!G70
A71: =Total Investment Assets | B71: ='Std AMAT'!B71 | C71: ='Std AMAT'!C71 | D71: ='Std AMAT'!D71 | E71: ='Std AMAT'!E71 | F71: ='Std AMAT'!F71 | G71: ='Std AMAT'!G71
A73: =Business Assets | B73: ='Std AMAT'!B73 | C73: ='Std AMAT'!C73 | D73: ='Std AMAT'!D73 | E73: ='Std AMAT'!E73 | F73: ='Std AMAT'!F73 | G73: ='Std AMAT'!G73
A75: FINANCING
A76: Lease Liabilities (current) | B76: ='Std AMAT'!B76 | C76: ='Std AMAT'!C76 | D76: ='Std AMAT'!D76 | E76: ='Std AMAT'!E76 | F76: ='Std AMAT'!F76 | G76: ='Std AMAT'!G76
A77: + Lease Liabilities (non-current) | B77: ='Std AMAT'!B77 | C77: ='Std AMAT'!C77 | D77: ='Std AMAT'!D77 | E77: ='Std AMAT'!E77 | F77: ='Std AMAT'!F77 | G77: ='Std AMAT'!G77
A78: =Total Debt | B78: ='Std AMAT'!B78 | C78: ='Std AMAT'!C78 | D78: ='Std AMAT'!D78 | E78: ='Std AMAT'!E78 | F78: ='Std AMAT'!F78 | G78: ='Std AMAT'!G78
A79: Cash & Equivalents | B79: ='Std AMAT'!B79 | C79: ='Std AMAT'!C79 | D79: ='Std AMAT'!D79 | E79: ='Std AMAT'!E79 | F79: ='Std AMAT'!F79 | G79: ='Std AMAT'!G79
A80: =Net Debt | B80: ='Std AMAT'!B80 | C80: ='Std AMAT'!C80 | D80: ='Std AMAT'!D80 | E80: ='Std AMAT'!E80 | F80: ='Std AMAT'!F80 | G80: ='Std AMAT'!G80
A81: Group Equity | B81: ='Std AMAT'!B81 | C81: ='Std AMAT'!C81 | D81: ='Std AMAT'!D81 | E81: ='Std AMAT'!E81 | F81: ='Std AMAT'!F81 | G81: ='Std AMAT'!G81
A82: =Invested Capital | B82: ='Std AMAT'!B82 | C82: ='Std AMAT'!C82 | D82: ='Std AMAT'!D82 | E82: ='Std AMAT'!E82 | F82: ='Std AMAT'!F82 | G82: ='Std AMAT'!G82
A83: BS Check (should = 0) | B83: ='Std AMAT'!B83 | C83: ='Std AMAT'!C83 | D83: ='Std AMAT'!D83 | E83: ='Std AMAT'!E83 | F83: ='Std AMAT'!F83 | G83: ='Std AMAT'!G83
A86: FREE CASH FLOW
A87: NOPAT | B87: ='Std AMAT'!B87 | C87: ='Std AMAT'!C87 | D87: ='Std AMAT'!D87 | E87: ='Std AMAT'!E87 | F87: ='Std AMAT'!F87 | G87: ='Std AMAT'!G87
A88: + D&A | B88: ='Std AMAT'!B88 | C88: ='Std AMAT'!C88 | D88: ='Std AMAT'!D88 | E88: ='Std AMAT'!E88 | F88: ='Std AMAT'!F88 | G88: ='Std AMAT'!G88
A89: - Change in OWC | B89: ='Std AMAT'!B89 | C89: ='Std AMAT'!C89 | D89: ='Std AMAT'!D89 | E89: ='Std AMAT'!E89 | F89: ='Std AMAT'!F89 | G89: ='Std AMAT'!G89
A90: - CapEx | B90: ='Std AMAT'!B90 | C90: ='Std AMAT'!C90 | D90: ='Std AMAT'!D90 | E90: ='Std AMAT'!E90 | F90: ='Std AMAT'!F90 | G90: ='Std AMAT'!G90
A91: - Purchase of Intangibles | B91: ='Std AMAT'!B91 | C91: ='Std AMAT'!C91 | D91: ='Std AMAT'!D91 | E91: ='Std AMAT'!E91 | F91: ='Std AMAT'!F91 | G91: ='Std AMAT'!G91
A92: =Operating CF after investment | B92: ='Std AMAT'!B92 | C92: ='Std AMAT'!C92 | D92: ='Std AMAT'!D92 | E92: ='Std AMAT'!E92 | F92: ='Std AMAT'!F92 | G92: ='Std AMAT'!G92
A94: + Net Investment Profit after tax | B94: ='Std AMAT'!B94 | C94: ='Std AMAT'!C94 | D94: ='Std AMAT'!D94 | E94: ='Std AMAT'!E94 | F94: ='Std AMAT'!F94 | G94: ='Std AMAT'!G94
A95: - Change in Investment Assets | B95: ='Std AMAT'!B95 | C95: ='Std AMAT'!C95 | D95: ='Std AMAT'!D95 | E95: ='Std AMAT'!E95 | F95: ='Std AMAT'!F95 | G95: ='Std AMAT'!G95
A96: =FCF to Debt & Equity | B96: ='Std AMAT'!B96 | C96: ='Std AMAT'!C96 | D96: ='Std AMAT'!D96 | E96: ='Std AMAT'!E96 | F96: ='Std AMAT'!F96 | G96: ='Std AMAT'!G96
A97: - Interest Expense after tax | B97: ='Std AMAT'!B97 | C97: ='Std AMAT'!C97 | D97: ='Std AMAT'!D97 | E97: ='Std AMAT'!E97 | F97: ='Std AMAT'!F97 | G97: ='Std AMAT'!G97
A98: + Change in Debt | B98: ='Std AMAT'!B98 | C98: ='Std AMAT'!C98 | D98: ='Std AMAT'!D98 | E98: ='Std AMAT'!E98 | F98: ='Std AMAT'!F98 | G98: ='Std AMAT'!G98
A99: =FCF to Equity | B99: ='Std AMAT'!B99 | C99: ='Std AMAT'!C99 | D99: ='Std AMAT'!D99 | E99: ='Std AMAT'!E99 | F99: ='Std AMAT'!F99 | G99: ='Std AMAT'!G99

Sheet Adj LRCX
A1: Standardized Financial Statements - Lam Research Corporation
A2: (EUR 000)
B3: ='Std LRCX'!B3 | C3: ='Std LRCX'!C3 | D3: ='Std LRCX'!D3 | E3: ='Std LRCX'!E3 | F3: ='Std LRCX'!F3 | G3: ='Std LRCX'!G3
A5: Operating cash % | B5: ='Std LRCX'!B5 | C5: ='Std LRCX'!C5 | D5: ='Std LRCX'!D5 | E5: ='Std LRCX'!E5 | F5: ='Std LRCX'!F5 | G5: ='Std LRCX'!G5
A6: Tax rate (effective) | B6: ='Std LRCX'!B6 | C6: ='Std LRCX'!C6 | D6: ='Std LRCX'!D6 | E6: ='Std LRCX'!E6 | F6: ='Std LRCX'!F6 | G6: ='Std LRCX'!G6
A8: INCOME STATEMENT
A9: Revenue | B9: ='Std LRCX'!B9 | C9: ='Std LRCX'!C9 | D9: ='Std LRCX'!D9 | E9: ='Std LRCX'!E9 | F9: ='Std LRCX'!F9 | G9: ='Std LRCX'!G9
A10: Cost of Sales | B10: ='Std LRCX'!B10 | C10: ='Std LRCX'!C10 | D10: ='Std LRCX'!D10 | E10: ='Std LRCX'!E10 | F10: ='Std LRCX'!F10 | G10: ='Std LRCX'!G10
A11: Gross Profit | B11: ='Std LRCX'!B11 | C11: ='Std LRCX'!C11 | D11: ='Std LRCX'!D11 | E11: ='Std LRCX'!E11 | F11: ='Std LRCX'!F11 | G11: ='Std LRCX'!G11
A12: SG&A | B12: ='Std LRCX'!B12 | C12: ='Std LRCX'!C12 | D12: ='Std LRCX'!D12 | E12: ='Std LRCX'!E12 | F12: ='Std LRCX'!F12 | G12: ='Std LRCX'!G12
A13: R&D | B13: ='Std LRCX'!B13 | C13: ='Std LRCX'!C13 | D13: ='Std LRCX'!D13 | E13: ='Std LRCX'!E13 | F13: ='Std LRCX'!F13 | G13: ='Std LRCX'!G13
A14: Depreciation & Amortization | B14: ='Std LRCX'!B14 | C14: ='Std LRCX'!C14 | D14: ='Std LRCX'!D14 | E14: ='Std LRCX'!E14 | F14: ='Std LRCX'!F14 | G14: ='Std LRCX'!G14
A15: Other Operating Expense | B15: ='Std LRCX'!B15 | C15: ='Std LRCX'!C15 | D15: ='Std LRCX'!D15 | E15: ='Std LRCX'!E15 | F15: ='Std LRCX'!F15 | G15: ='Std LRCX'!G15
A16: Total Operating Expense | B16: ='Std LRCX'!B16 | C16: ='Std LRCX'!C16 | D16: ='Std LRCX'!D16 | E16: ='Std LRCX'!E16 | F16: ='Std LRCX'!F16 | G16: ='Std LRCX'!G16
A17: Recurring Operating Profit | B17: ='Std LRCX'!B17 | C17: ='Std LRCX'!C17 | D17: ='Std LRCX'!D17 | E17: ='Std LRCX'!E17 | F17: ='Std LRCX'!F17 | G17: ='Std LRCX'!G17
A19: Non-recurring items:
A20: Gain/Loss on Sale of Investments | B20: ='Std LRCX'!B20 | C20: ='Std LRCX'!C20 | D20: ='Std LRCX'!D20 | E20: ='Std LRCX'!E20 | F20: ='Std LRCX'!F20 | G20: ='Std LRCX'!G20
A21: Gain/Loss on Sale of Assets | B21: ='Std LRCX'!B21 | C21: ='Std LRCX'!C21 | D21: ='Std LRCX'!D21 | E21: ='Std LRCX'!E21 | F21: ='Std LRCX'!F21 | G21: ='Std LRCX'!G21
A22: Asset Writedown | B22: ='Std LRCX'!B22 | C22: ='Std LRCX'!C22 | D22: ='Std LRCX'!D22 | E22: ='Std LRCX'!E22 | F22: ='Std LRCX'!F22 | G22: ='Std LRCX'!G22
A23: Other Unusual Items | B23: ='Std LRCX'!B23 | C23: ='Std LRCX'!C23 | D23: ='Std LRCX'!D23 | E23: ='Std LRCX'!E23 | F23: ='Std LRCX'!F23 | G23: ='Std LRCX'!G23
A24: Total Non-recurring | B24: ='Std LRCX'!B24 | C24: ='Std LRCX'!C24 | D24: ='Std LRCX'!D24 | E24: ='Std LRCX'!E24 | F24: ='Std LRCX'!F24 | G24: ='Std LRCX'!G24
A25: EBIT | B25: ='Std LRCX'!B25 | C25: ='Std LRCX'!C25 | D25: ='Std LRCX'!D25 | E25: ='Std LRCX'!E25 | F25: ='Std LRCX'!F25 | G25: ='Std LRCX'!G25
A27: Investment Income (Equity Method) | B27: ='Std LRCX'!B27 | C27: ='Std LRCX'!C27 | D27: ='Std LRCX'!D27 | E27: ='Std LRCX'!E27 | F27: ='Std LRCX'!F27 | G27: ='Std LRCX'!G27
A28: Interest Income | B28: ='Std LRCX'!B28 | C28: ='Std LRCX'!C28 | D28: ='Std LRCX'!D28 | E28: ='Std LRCX'!E28 | F28: ='Std LRCX'!F28 | G28: ='Std LRCX'!G28
A29: Interest Expense | B29: ='Std LRCX'!B29 | C29: ='Std LRCX'!C29 | D29: ='Std LRCX'!D29 | E29: ='Std LRCX'!E29 | F29: ='Std LRCX'!F29 | G29: ='Std LRCX'!G29
A30: FX Gains/(Losses) | B30: ='Std LRCX'!B30 | C30: ='Std LRCX'!C30 | D30: ='Std LRCX'!D30 | E30: ='Std LRCX'!E30 | F30: ='Std LRCX'!F30 | G30: ='Std LRCX'!G30
A31: Profit Before Tax | B31: ='Std LRCX'!B31 | C31: ='Std LRCX'!C31 | D31: ='Std LRCX'!D31 | E31: ='Std LRCX'!E31 | F31: ='Std LRCX'!F31 | G31: ='Std LRCX'!G31
A32: Tax Expense | B32: ='Std LRCX'!B32 | C32: ='Std LRCX'!C32 | D32: ='Std LRCX'!D32 | E32: ='Std LRCX'!E32 | F32: ='Std LRCX'!F32 | G32: ='Std LRCX'!G32
... A40: Dividends per Share | B40: ='Std LRCX'!B40 | C40: ='Std LRCX'!C40 | D40: ='Std LRCX'!D40 | E40: ='Std LRCX'!E40 | F40: ='Std LRCX'!F40 | G40: ='Std LRCX'!G40
A43: BALANCE SHEET (Reformulated)
A44: Operating Working Capital:
A45: Trade Receivables | B45: ='Std LRCX'!B45 | C45: ='Std LRCX'!C45 | D45: ='Std LRCX'!D45 | E45: ='Std LRCX'!E45 | F45: ='Std LRCX'!F45 | G45: ='Std LRCX'!G45
A46: + Other Receivables | B46: ='Std LRCX'!B46 | C46: ='Std LRCX'!C46 | D46: ='Std LRCX'!D46 | E46: ='Std LRCX'!E46 | F46: ='Std LRCX'!F46 | G46: ='Std LRCX'!G46
A47: + Inventories | B47: ='Std LRCX'!B47 | C47: ='Std LRCX'!C47 | D47: ='Std LRCX'!D47 | E47: ='Std LRCX'!E47 | F47: ='Std LRCX'!F47 | G47: ='Std LRCX'!G47
A48: + Prepaid & Other CA | B48: ='Std LRCX'!B48 | C48: ='Std LRCX'!C48 | D48: ='Std LRCX'!D48 | E48: ='Std LRCX'!E48 | F48: ='Std LRCX'!F48 | G48: ='Std LRCX'!G48
A49: - Accounts Payable | B49: ='Std LRCX'!B49 | C49: ='Std LRCX'!C49 | D49: ='Std LRCX'!D49 | E49: ='Std LRCX'!E49 | F49: ='Std LRCX'!F49 | G49: ='Std LRCX'!G49
A50: - Accrued Expenses | B50: ='Std LRCX'!B50 | C50: ='Std LRCX'!C50 | D50: ='Std LRCX'!D50 | E50: ='Std LRCX'!E50 | F50: ='Std LRCX'!F50 | G50: ='Std LRCX'!G50
A51: - Unearned Revenue / Contract Liabilities | B51: ='Std LRCX'!B51 | C51: ='Std LRCX'!C51 | D51: ='Std LRCX'!D51 | E51: ='Std LRCX'!E51 | F51: ='Std LRCX'!F51 | G51: ='Std LRCX'!G51
A52: - Income Taxes Payable | B52: ='Std LRCX'!B52 | C52: ='Std LRCX'!C52 | D52: ='Std LRCX'!D52 | E52: ='Std LRCX'!E52 | F52: ='Std LRCX'!F52 | G52: ='Std LRCX'!G52
A53: - Other Current Liabilities | B53: ='Std LRCX'!B53 | C53: ='Std LRCX'!C53 | D53: ='Std LRCX'!D53 | E53: ='Std LRCX'!E53 | F53: ='Std LRCX'!F53 | G53: ='Std LRCX'!G53
A54: =Operating Working Capital | B54: ='Std LRCX'!B54 | C54: ='Std LRCX'!C54 | D54: ='Std LRCX'!D54 | E54: ='Std LRCX'!E54 | F54: ='Std LRCX'!F54 | G54: ='Std LRCX'!G54
A56: Net Non-Current Operating Assets:
A57: PP&E (net, incl. ROU) | B57: ='Std LRCX'!B57 | C57: ='Std LRCX'!C57 | D57: ='Std LRCX'!D57 | E57: ='Std LRCX'!E57 | F57: ='Std LRCX'!F57 | G57: ='Std LRCX'!G57
A58: + Goodwill | B58: ='Std LRCX'!B58 | C58: ='Std LRCX'!C58 | D58: ='Std LRCX'!D58 | E58: ='Std LRCX'!E58 | F58: ='Std LRCX'!F58 | G58: ='Std LRCX'!G58
A59: + Other Intangible Assets | B59: ='Std LRCX'!B59 | C59: ='Std LRCX'!C59 | D59: ='Std LRCX'!D59 | E59: ='Std LRCX'!E59 | F59: ='Std LRCX'!F59 | G59: ='Std LRCX'!G59
A60: + Deferred Tax Assets | B60: ='Std LRCX'!B60 | C60: ='Std LRCX'!C60 | D60: ='Std LRCX'!D60 | E60: ='Std LRCX'!E60 | F60: ='Std LRCX'!F60 | G60: ='Std LRCX'!G60
A61: + Deferred Charges & LT Intangibles | B61: ='Std LRCX'!B61 | C61: ='Std LRCX'!C61 | D61: ='Std LRCX'!D61 | E61: ='Std LRCX'!E61 | F61: ='Std LRCX'!F61 | G61: ='Std LRCX'!G61
A62: + Other Non-Current Assets | B62: ='Std LRCX'!B62 | C62: ='Std LRCX'!C62 | D62: ='Std LRCX'!D62 | E62: ='Std LRCX'!E62 | F62: ='Std LRCX'!F62 | G62: ='Std LRCX'!G62
A63: - Deferred Tax Liabilities | B63: ='Std LRCX'!B63 | C63: ='Std LRCX'!C63 | D63: ='Std LRCX'!D63 | E63: ='Std LRCX'!E63 | F63: ='Std LRCX'!F63 | G63: ='Std LRCX'!G63
A64: - Other Non-Current Liabilities | B64: ='Std LRCX'!B64 | C64: ='Std LRCX'!C64 | D64: ='Std LRCX'!D64 | E64: ='Std LRCX'!E64 | F64: ='Std LRCX'!F64 | G64: ='Std LRCX'!G64
A65: =Net Non-Current Operating Assets | B65: ='Std LRCX'!B65 | C65: ='Std LRCX'!C65 | D65: ='Std LRCX'!D65 | E65: ='Std LRCX'!E65 | F65: ='Std LRCX'!F65 | G65: ='Std LRCX'!G65
A67: =Net Operating Assets | B67: ='Std LRCX'!B67 | C67: ='Std LRCX'!C67 | D67: ='Std LRCX'!D67 | E67: ='Std LRCX'!E67 | F67: ='Std LRCX'!F67 | G67: ='Std LRCX'!G67
A69: Investment Assets:
A70: Long-Term Investments | B70: ='Std LRCX'!B70 | C70: ='Std LRCX'!C70 | D70: ='Std LRCX'!D70 | E70: ='Std LRCX'!E70 | F70: ='Std LRCX'!F70 | G70: ='Std LRCX'!G70
A71: =Total Investment Assets | B71: ='Std LRCX'!B71 | C71: ='Std LRCX'!C71 | D71: ='Std LRCX'!D71 | E71: ='Std LRCX'!E71 | F71: ='Std LRCX'!F71 | G71: ='Std LRCX'!G71
A73: =Business Assets | B73: ='Std LRCX'!B73 | C73: ='Std LRCX'!C73 | D73: ='Std LRCX'!D73 | E73: ='Std LRCX'!E73 | F73: ='Std LRCX'!F73 | G73: ='Std LRCX'!G73
A75: FINANCING
A76: Lease Liabilities (current) | B76: ='Std LRCX'!B76 | C76: ='Std LRCX'!C76 | D76: ='Std LRCX'!D76 | E76: ='Std LRCX'!E76 | F76: ='Std LRCX'!F76 | G76: ='Std LRCX'!G76
A77: + Lease Liabilities (non-current) | B77: ='Std LRCX'!B77 | C77: ='Std LRCX'!C77 | D77: ='Std LRCX'!D77 | E77: ='Std LRCX'!E77 | F77: ='Std LRCX'!F77 | G77: ='Std LRCX'!G77
A78: =Total Debt | B78: ='Std LRCX'!B78 | C78: ='Std LRCX'!C78 | D78: ='Std LRCX'!D78 | E78: ='Std LRCX'!E78 | F78: ='Std LRCX'!F78 | G78: ='Std LRCX'!G78
A79: Cash & Equivalents | B79: ='Std LRCX'!B79 | C79: ='Std LRCX'!C79 | D79: ='Std LRCX'!D79 | E79: ='Std LRCX'!E79 | F79: ='Std LRCX'!F79 | G79: ='Std LRCX'!G79
A80: =Net Debt | B80: ='Std LRCX'!B80 | C80: ='Std LRCX'!C80 | D80: ='Std LRCX'!D80 | E80: ='Std LRCX'!E80 | F80: ='Std LRCX'!F80 | G80: ='Std LRCX'!G80
A81: Group Equity | B81: ='Std LRCX'!B81 | C81: ='Std LRCX'!C81 | D81: ='Std LRCX'!D81 | E81: ='Std LRCX'!E81 | F81: ='Std LRCX'!F81 | G81: ='Std LRCX'!G81
A82: =Invested Capital | B82: ='Std LRCX'!B82 | C82: ='Std LRCX'!C82 | D82: ='Std LRCX'!D82 | E82: ='Std LRCX'!E82 | F82: ='Std LRCX'!F82 | G82: ='Std LRCX'!G82
A83: BS Check (should = 0) | B83: ='Std LRCX'!B83 | C83: ='Std LRCX'!C83 | D83: ='Std LRCX'!D83 | E83: ='Std LRCX'!E83 | F83: ='Std LRCX'!F83 | G83: ='Std LRCX'!G83
A86: FREE CASH FLOW
A87: NOPAT | B87: ='Std LRCX'!B87 | C87: ='Std LRCX'!C87 | D87: ='Std LRCX'!D87 | E87: ='Std LRCX'!E87 | F87: ='Std LRCX'!F87 | G87: ='Std LRCX'!G87
A88: + D&A | B88: ='Std LRCX'!B88 | C88: ='Std LRCX'!C88 | D88: ='Std LRCX'!D88 | E88: ='Std LRCX'!E88 | F88: ='Std LRCX'!F88 | G88: ='Std LRCX'!G88
A89: - Change in OWC | B89: ='Std LRCX'!B89 | C89: ='Std LRCX'!C89 | D89: ='Std LRCX'!D89 | E89: ='Std LRCX'!E89 | F89: ='Std LRCX'!F89 | G89: ='Std LRCX'!G89
A90: - CapEx | B90: ='Std LRCX'!B90 | C90: ='Std LRCX'!C90 | D90: ='Std LRCX'!D90 | E90: ='Std LRCX'!E90 | F90: ='Std LRCX'!F90 | G90: ='Std LRCX'!G90
A91: - Purchase of Intangibles | B91: ='Std LRCX'!B91 | C91: ='Std LRCX'!C91 | D91: ='Std LRCX'!D91 | E91: ='Std LRCX'!E91 | F91: ='Std LRCX'!F91 | G91: ='Std LRCX'!G91
A92: =Operating CF after investment | B92: ='Std LRCX'!B92 | C92: ='Std LRCX'!C92 | D92: ='Std LRCX'!D92 | E92: ='Std LRCX'!E92 | F92: ='Std LRCX'!F92 | G92: ='Std LRCX'!G92
A94: + Net Investment Profit after tax | B94: ='Std LRCX'!B94 | C94: ='Std LRCX'!C94 | D94: ='Std LRCX'!D94 | E94: ='Std LRCX'!E94 | F94: ='Std LRCX'!F94 | G94: ='Std LRCX'!G94
A95: - Change in Investment Assets | B95: ='Std LRCX'!B95 | C95: ='Std LRCX'!C95 | D95: ='Std LRCX'!D95 | E95: ='Std LRCX'!E95 | F95: ='Std LRCX'!F95 | G95: ='Std LRCX'!G95
A96: =FCF to Debt & Equity | B96: ='Std LRCX'!B96 | C96: ='Std LRCX'!C96 | D96: ='Std LRCX'!D96 | E96: ='Std LRCX'!E96 | F96: ='Std LRCX'!F96 | G96: ='Std LRCX'!G96
A97: - Interest Expense after tax | B97: ='Std LRCX'!B97 | C97: ='Std LRCX'!C97 | D97: ='Std LRCX'!D97 | E97: ='Std LRCX'!E97 | F97: ='Std LRCX'!F97 | G97: ='Std LRCX'!G97
A98: + Change in Debt | B98: ='Std LRCX'!B98 | C98: ='Std LRCX'!C98 | D98: ='Std LRCX'!D98 | E98: ='Std LRCX'!E98 | F98: ='Std LRCX'!F98 | G98: ='Std LRCX'!G98
A99: =FCF to Equity | B99: ='Std LRCX'!B99 | C99: ='Std LRCX'!C99 | D99: ='Std LRCX'!D99 | E99: ='Std LRCX'!E99 | F99: ='Std LRCX'!F99 | G99: ='Std LRCX'!G99

Sheet Ratio Definitions
A1: Ratio Definitions & Formulas
A3: Profitability
B4: ROE | C4: Net Income / Average Total Equity
B5: DuPont Decomposition | C5: ROS x Asset Turnover x Financial Leverage
B6: RNOA | C6: NOPAT Margin x NOA Turnover
B7: Gross Profit Margin | C7: Gross Profit / Revenue
B8: EBIT Margin | C8: EBIT / Revenue
B9: NOPAT Margin | C9: NOPAT / Revenue
A11: Asset Management
B12: Receivables Turnover | C12: Revenue / Avg Trade Receivables
B13: Days Receivable | C13: 365 / Receivables Turnover
B14: Inventory Turnover | C14: COGS / Avg Inventory
B15: Days Inventory | C15: 365 / Inventory Turnover
B16: Payables Turnover | C16: COGS / Avg Trade Payables
B17: Days Payable | C17: 365 / Payables Turnover
B18: Cash Conversion Cycle | C18: Days Inventory + Days Receivable - Days Payable
A20: Liquidity
B21: OWC / Revenue | C21: Operating Working Capital / Revenue
B22: Cash / Total Debt | C22: Cash & Equivalents / Total Debt
A24: Solvency
B25: Debt-to-Equity | C25: Total Debt / Total Equity
B26: Interest Coverage | C26: EBIT / |Interest Expense|
A28: Growth
B29: Revenue Growth | C29: (Revenue_t / Revenue_{t-1}) - 1
B30: Sustainable Growth | C30: (1 - Payout Ratio) x ROE

Sheet Ratios ASM
A1: Ratio Analysis - ASM
A2: (derived from Adjusted statements)
B3: 2019 | C3: 2020 | D3: 2021 | E3: 2022 | F3: 2023 | G3: 2024
A5: PROFITABILITY
A6: ROE | B6: N/A | C6: =IF(AVERAGE('Adj ASM'!B81,'Adj ASM'!C81)=0,0,'Adj ASM'!C33/AVERAGE('Adj ASM'!B81,'Adj ASM'!C81)) | D6: =IF(AVERAGE('Adj ASM'!C81,'Adj ASM'!D81)=0,0,'Adj ASM'!D33/AVERAGE('Adj ASM'!C81,'Adj ASM'!D81)) | E6: =IF(AVERAGE('Adj ASM'!D81,'Adj ASM'!E81)=0,0,'Adj ASM'!E33/AVERAGE('Adj ASM'!D81,'Adj ASM'!E81)) | F6: =IF(AVERAGE('Adj ASM'!E81,'Adj ASM'!F81)=0,0,'Adj ASM'!F33/AVERAGE('Adj ASM'!E81,'Adj ASM'!F81)) | G6: =IF(AVERAGE('Adj ASM'!F81,'Adj ASM'!G81)=0,0,'Adj ASM'!G33/AVERAGE('Adj ASM'!F81,'Adj ASM'!G81))
A7: Net Profit Margin (ROS) | B7: =IF('Adj ASM'!B9=0,0,'Adj ASM'!B33/'Adj ASM'!B9) | C7: =IF('Adj ASM'!C9=0,0,'Adj ASM'!C33/'Adj ASM'!C9) | D7: =IF('Adj ASM'!D9=0,0,'Adj ASM'!D33/'Adj ASM'!D9) | E7: =IF('Adj ASM'!E9=0,0,'Adj ASM'!E33/'Adj ASM'!E9) | F7: =IF('Adj ASM'!F9=0,0,'Adj ASM'!F33/'Adj ASM'!F9) | G7: =IF('Adj ASM'!G9=0,0,'Adj ASM'!G33/'Adj ASM'!G9)
A8: x Asset Turnover | B8: N/A | C8: =IF(AVERAGE('Adj ASM'!B73,'Adj ASM'!C73)=0,0,'Adj ASM'!C9/AVERAGE('Adj ASM'!B73,'Adj ASM'!C73)) | D8: =IF(AVERAGE('Adj ASM'!C73,'Adj ASM'!D73)=0,0,'Adj ASM'!D9/AVERAGE('Adj ASM'!C73,'Adj ASM'!D73)) | E8: =IF(AVERAGE('Adj ASM'!D73,'Adj ASM'!E73)=0,0,'Adj ASM'!E9/AVERAGE('Adj ASM'!D73,'Adj ASM'!E73)) | F8: =IF(AVERAGE('Adj ASM'!E73,'Adj ASM'!F73)=0,0,'Adj ASM'!F9/AVERAGE('Adj ASM'!E73,'Adj ASM'!F73)) | G8: =IF(AVERAGE('Adj ASM'!F73,'Adj ASM'!G73)=0,0,'Adj ASM'!G9/AVERAGE('Adj ASM'!F73,'Adj ASM'!G73))
A9: = ROA | B9: N/A | C9: =C7*C8 | D9: =D7*D8 | E9: =E7*E8 | F9: =F7*F8 | G9: =G7*G8
A10: x Financial Leverage | B10: N/A | C10: =IF(AVERAGE('Adj ASM'!B81,'Adj ASM'!C81)=0,0,AVERAGE('Adj ASM'!B73,'Adj ASM'!C73)/AVERAGE('Adj ASM'!B81,'Adj ASM'!C81)) | D10: =IF(AVERAGE('Adj ASM'!C81,'Adj ASM'!D81)=0,0,AVERAGE('Adj ASM'!C73,'Adj ASM'!D73)/AVERAGE('Adj ASM'!C81,'Adj ASM'!D81)) | E10: =IF(AVERAGE('Adj ASM'!D81,'Adj ASM'!E81)=0,0,AVERAGE('Adj ASM'!D73,'Adj ASM'!E73)/AVERAGE('Adj ASM'!D81,'Adj ASM'!E81)) | F10: =IF(AVERAGE('Adj ASM'!E81,'Adj ASM'!F81)=0,0,AVERAGE('Adj ASM'!E73,'Adj ASM'!F73)/AVERAGE('Adj ASM'!E81,'Adj ASM'!F81)) | G10: =IF(AVERAGE('Adj ASM'!F81,'Adj ASM'!G81)=0,0,AVERAGE('Adj ASM'!F73,'Adj ASM'!G73)/AVERAGE('Adj ASM'!F81,'Adj ASM'!G81))
A11: = ROE check (ROA x Leverage) | B11: N/A | C11: =C9*C10 | D11: =D9*D10 | E11: =E9*E10 | F11: =F9*F10 | G11: =G9*G10
A13: RNOA | B13: N/A | C13: =IF(AVERAGE('Adj ASM'!B67,'Adj ASM'!C67)=0,0,'Adj ASM'!C36/AVERAGE('Adj ASM'!B67,'Adj ASM'!C67)) | D13: =IF(AVERAGE('Adj ASM'!C67,'Adj ASM'!D67)=0,0,'Adj ASM'!D36/AVERAGE('Adj ASM'!C67,'Adj ASM'!D67)) | E13: =IF(AVERAGE('Adj ASM'!D67,'Adj ASM'!E67)=0,0,'Adj ASM'!E36/AVERAGE('Adj ASM'!D67,'Adj ASM'!E67)) | F13: =IF(AVERAGE('Adj ASM'!E67,'Adj ASM'!F67)=0,0,'Adj ASM'!F36/AVERAGE('Adj ASM'!E67,'Adj ASM'!F67)) | G13: =IF(AVERAGE('Adj ASM'!F67,'Adj ASM'!G67)=0,0,'Adj ASM'!G36/AVERAGE('Adj ASM'!F67,'Adj ASM'!G67))
A14: NOPAT Margin | B14: =IF('Adj ASM'!B9=0,0,'Adj ASM'!B36/'Adj ASM'!B9) | C14: =IF('Adj ASM'!C9=0,0,'Adj ASM'!C36/'Adj ASM'!C9) | D14: =IF('Adj ASM'!D9=0,0,'Adj ASM'!D36/'Adj ASM'!D9) | E14: =IF('Adj ASM'!E9=0,0,'Adj ASM'!E36/'Adj ASM'!E9) | F14: =IF('Adj ASM'!F9=0,0,'Adj ASM'!F36/'Adj ASM'!F9) | G14: =IF('Adj ASM'!G9=0,0,'Adj ASM'!G36/'Adj ASM'!G9)
A15: x NOA Turnover | B15: N/A | C15: =IF(AVERAGE('Adj ASM'!B67,'Adj ASM'!C67)=0,0,'Adj ASM'!C9/AVERAGE('Adj ASM'!B67,'Adj ASM'!C67)) | D15: =IF(AVERAGE('Adj ASM'!C67,'Adj ASM'!D67)=0,0,'Adj ASM'!D9/AVERAGE('Adj ASM'!C67,'Adj ASM'!D67)) | E15: =IF(AVERAGE('Adj ASM'!D67,'Adj ASM'!E67)=0,0,'Adj ASM'!E9/AVERAGE('Adj ASM'!D67,'Adj ASM'!E67)) | F15: =IF(AVERAGE('Adj ASM'!E67,'Adj ASM'!F67)=0,0,'Adj ASM'!F9/AVERAGE('Adj ASM'!E67,'Adj ASM'!F67)) | G15: =IF(AVERAGE('Adj ASM'!F67,'Adj ASM'!G67)=0,0,'Adj ASM'!G9/AVERAGE('Adj ASM'!F67,'Adj ASM'!G67))
A17: Gross Profit Margin | B17: =IF('Adj ASM'!B9=0,0,'Adj ASM'!B11/'Adj ASM'!B9) | C17: =IF('Adj ASM'!C9=0,0,'Adj ASM'!C11/'Adj ASM'!C9) | D17: =IF('Adj ASM'!D9=0,0,'Adj ASM'!D11/'Adj ASM'!D9) | E17: =IF('Adj ASM'!E9=0,0,'Adj ASM'!E11/'Adj ASM'!E9) | F17: =IF('Adj ASM'!F9=0,0,'Adj ASM'!F11/'Adj ASM'!F9) | G17: =IF('Adj ASM'!G9=0,0,'Adj ASM'!G11/'Adj ASM'!G9)
A18: EBIT Margin | B18: =IF('Adj ASM'!B9=0,0,'Adj ASM'!B25/'Adj ASM'!B9) | C18: =IF('Adj ASM'!C9=0,0,'Adj ASM'!C25/'Adj ASM'!C9) | D18: =IF('Adj ASM'!D9=0,0,'Adj ASM'!D25/'Adj ASM'!D9) | E18: =IF('Adj ASM'!E9=0,0,'Adj ASM'!E25/'Adj ASM'!E9) | F18: =IF('Adj ASM'!F9=0,0,'Adj ASM'!F25/'Adj ASM'!F9) | G18: =IF('Adj ASM'!G9=0,0,'Adj ASM'!G25/'Adj ASM'!G9)
A19: NOPAT Margin | B19: =IF('Adj ASM'!B9=0,0,'Adj ASM'!B36/'Adj ASM'!B9) | C19: =IF('Adj ASM'!C9=0,0,'Adj ASM'!C36/'Adj ASM'!C9) | D19: =IF('Adj ASM'!D9=0,0,'Adj ASM'!D36/'Adj ASM'!D9) | E19: =IF('Adj ASM'!E9=0,0,'Adj ASM'!E36/'Adj ASM'!E9) | F19: =IF('Adj ASM'!F9=0,0,'Adj ASM'!F36/'Adj ASM'!F9) | G19: =IF('Adj ASM'!G9=0,0,'Adj ASM'!G36/'Adj ASM'!G9)
A21: COMMON-SIZE INCOME STATEMENT
A22: Revenue | B22: =1 | C22: =1 | D22: =1 | E22: =1 | F22: =1 | G22: =1
A23: Cost of Sales / Revenue | B23: =IF('Adj ASM'!B9=0,0,'Adj ASM'!B10/'Adj ASM'!B9) | C23: =IF('Adj ASM'!C9=0,0,'Adj ASM'!C10/'Adj ASM'!C9) | D23: =IF('Adj ASM'!D9=0,0,'Adj ASM'!D10/'Adj ASM'!D9) | E23: =IF('Adj ASM'!E9=0,0,'Adj ASM'!E10/'Adj ASM'!E9) | F23: =IF('Adj ASM'!F9=0,0,'Adj ASM'!F10/'Adj ASM'!F9) | G23: =IF('Adj ASM'!G9=0,0,'Adj ASM'!G10/'Adj ASM'!G9)
A24: SG&A / Revenue | B24: =IF('Adj ASM'!B9=0,0,'Adj ASM'!B12/'Adj ASM'!B9) | C24: =IF('Adj ASM'!C9=0,0,'Adj ASM'!C12/'Adj ASM'!C9) | D24: =IF('Adj ASM'!D9=0,0,'Adj ASM'!D12/'Adj ASM'!D9) | E24: =IF('Adj ASM'!E9=0,0,'Adj ASM'!E12/'Adj ASM'!E9) | F24: =IF('Adj ASM'!F9=0,0,'Adj ASM'!F12/'Adj ASM'!F9) | G24: =IF('Adj ASM'!G9=0,0,'Adj ASM'!G12/'Adj ASM'!G9)
A25: R&D / Revenue | B25: =IF('Adj ASM'!B9=0,0,'Adj ASM'!B13/'Adj ASM'!B9) | C25: =IF('Adj ASM'!C9=0,0,'Adj ASM'!C13/'Adj ASM'!C9) | D25: =IF('Adj ASM'!D9=0,0,'Adj ASM'!D13/'Adj ASM'!D9) | E25: =IF('Adj ASM'!E9=0,0,'Adj ASM'!E13/'Adj ASM'!E9) | F25: =IF('Adj ASM'!F9=0,0,'Adj ASM'!F13/'Adj ASM'!F9) | G25: =IF('Adj ASM'!G9=0,0,'Adj ASM'!G13/'Adj ASM'!G9)
A27: ASSET MANAGEMENT
A28: Receivables Turnover | B28: N/A | C28: =IF(AVERAGE('Adj ASM'!B45,'Adj ASM'!C45)=0,0,'Adj ASM'!C9/AVERAGE('Adj ASM'!B45,'Adj ASM'!C45)) | D28: =IF(AVERAGE('Adj ASM'!C45,'Adj ASM'!D45)=0,0,'Adj ASM'!D9/AVERAGE('Adj ASM'!C45,'Adj ASM'!D45)) | E28: =IF(AVERAGE('Adj ASM'!D45,'Adj ASM'!E45)=0,0,'Adj ASM'!E9/AVERAGE('Adj ASM'!D45,'Adj ASM'!E45)) | F28: =IF(AVERAGE('Adj ASM'!E45,'Adj ASM'!F45)=0,0,'Adj ASM'!F9/AVERAGE('Adj ASM'!E45,'Adj ASM'!F45)) | G28: =IF(AVERAGE('Adj ASM'!F45,'Adj ASM'!G45)=0,0,'Adj ASM'!G9/AVERAGE('Adj ASM'!F45,'Adj ASM'!G45))
A29: Days Receivable | B29: N/A | C29: =IF(C28=0,0,365/C28) | D29: =IF(D28=0,0,365/D28) | E29: =IF(E28=0,0,365/E28) | F29: =IF(F28=0,0,365/F28) | G29: =IF(G28=0,0,365/G28)
A30: Inventory Turnover | B30: N/A | C30: =IF(AVERAGE('Adj ASM'!B47,'Adj ASM'!C47)=0,0,'Adj ASM'!C10/AVERAGE('Adj ASM'!B47,'Adj ASM'!C47)) | D30: =IF(AVERAGE('Adj ASM'!C47,'Adj ASM'!D47)=0,0,'Adj ASM'!D10/AVERAGE('Adj ASM'!C47,'Adj ASM'!D47)) | E30: =IF(AVERAGE('Adj ASM'!D47,'Adj ASM'!E47)=0,0,'Adj ASM'!E10/AVERAGE('Adj ASM'!D47,'Adj ASM'!E47)) | F30: =IF(AVERAGE('Adj ASM'!E47,'Adj ASM'!F47)=0,0,'Adj ASM'!F10/AVERAGE('Adj ASM'!E47,'Adj ASM'!F47)) | G30: =IF(AVERAGE('Adj ASM'!F47,'Adj ASM'!G47)=0,0,'Adj ASM'!G10/AVERAGE('Adj ASM'!F47,'Adj ASM'!G47))
A31: Days Inventory | B31: N/A | C31: =IF(C30=0,0,365/C30) | D31: =IF(D30=0,0,365/D30) | E31: =IF(E30=0,0,365/E30) | F31: =IF(F30=0,0,365/F30) | G31: =IF(G30=0,0,365/G30)
A32: Payables Turnover | B32: N/A | C32: =IF(AVERAGE('Adj ASM'!B49,'Adj ASM'!C49)=0,0,'Adj ASM'!C10/AVERAGE('Adj ASM'!B49,'Adj ASM'!C49)) | D32: =IF(AVERAGE('Adj ASM'!C49,'Adj ASM'!D49)=0,0,'Adj ASM'!D10/AVERAGE('Adj ASM'!C49,'Adj ASM'!D49)) | E32: =IF(AVERAGE('Adj ASM'!D49,'Adj ASM'!E49)=0,0,'Adj ASM'!E10/AVERAGE('Adj ASM'!D49,'Adj ASM'!E49)) | F32: =IF(AVERAGE('Adj ASM'!E49,'Adj ASM'!F49)=0,0,'Adj ASM'!F10/AVERAGE('Adj ASM'!E49,'Adj ASM'!F49)) | G32: =IF(AVERAGE('Adj ASM'!F49,'Adj ASM'!G49)=0,0,'Adj ASM'!G10/AVERAGE('Adj ASM'!F49,'Adj ASM'!G49))
A33: Days Payable | B33: N/A | C33: =IF(C32=0,0,365/C32) | D33: =IF(D32=0,0,365/D32) | E33: =IF(E32=0,0,365/E32) | F33: =IF(F32=0,0,365/F32) | G33: =IF(G32=0,0,365/G32)
A34: Cash Conversion Cycle | B34: N/A | C34: =C31+C29-C33 | D34: =D31+D29-D33 | E34: =E31+E29-E33 | F34: =F31+F29-F33 | G34: =G31+G29-G33
A36: OWC / Revenue | B36: =IF('Adj ASM'!B9=0,0,'Adj ASM'!B54/'Adj ASM'!B9) | C36: =IF('Adj ASM'!C9=0,0,'Adj ASM'!C54/'Adj ASM'!C9) | D36: =IF('Adj ASM'!D9=0,0,'Adj ASM'!D54/'Adj ASM'!D9) | E36: =IF('Adj ASM'!E9=0,0,'Adj ASM'!E54/'Adj ASM'!E9) | F36: =IF('Adj ASM'!F9=0,0,'Adj ASM'!F54/'Adj ASM'!F9) | G36: =IF('Adj ASM'!G9=0,0,'Adj ASM'!G54/'Adj ASM'!G9)
A37: PP&E / Revenue | B37: =IF('Adj ASM'!B9=0,0,'Adj ASM'!B57/'Adj ASM'!B9) | C37: =IF('Adj ASM'!C9=0,0,'Adj ASM'!C57/'Adj ASM'!C9) | D37: =IF('Adj ASM'!D9=0,0,'Adj ASM'!D57/'Adj ASM'!D9) | E37: =IF('Adj ASM'!E9=0,0,'Adj ASM'!E57/'Adj ASM'!E9) | F37: =IF('Adj ASM'!F9=0,0,'Adj ASM'!F57/'Adj ASM'!F9) | G37: =IF('Adj ASM'!G9=0,0,'Adj ASM'!G57/'Adj ASM'!G9)
A39: LIQUIDITY & SOLVENCY
A40: Cash / Total Debt | B40: =IF('Adj ASM'!B78=0,0,'Adj ASM'!B79/'Adj ASM'!B78) | C40: =IF('Adj ASM'!C78=0,0,'Adj ASM'!C79/'Adj ASM'!C78) | D40: =IF('Adj ASM'!D78=0,0,'Adj ASM'!D79/'Adj ASM'!D78) | E40: =IF('Adj ASM'!E78=0,0,'Adj ASM'!E79/'Adj ASM'!E78) | F40: =IF('Adj ASM'!F78=0,0,'Adj ASM'!F79/'Adj ASM'!F78) | G40: =IF('Adj ASM'!G78=0,0,'Adj ASM'!G79/'Adj ASM'!G78)
A41: Debt-to-Equity | B41: =IF('Adj ASM'!B81=0,0,'Adj ASM'!B78/'Adj ASM'!B81) | C41: =IF('Adj ASM'!C81=0,0,'Adj ASM'!C78/'Adj ASM'!C81) | D41: =IF('Adj ASM'!D81=0,0,'Adj ASM'!D78/'Adj ASM'!D81) | E41: =IF('Adj ASM'!E81=0,0,'Adj ASM'!E78/'Adj ASM'!E81) | F41: =IF('Adj ASM'!F81=0,0,'Adj ASM'!F78/'Adj ASM'!F81) | G41: =IF('Adj ASM'!G81=0,0,'Adj ASM'!G78/'Adj ASM'!G81)
A42: Interest Coverage | B42: =IF(ABS('Adj ASM'!B29)=0,0,'Adj ASM'!B25/ABS('Adj ASM'!B29)) | C42: =IF(ABS('Adj ASM'!C29)=0,0,'Adj ASM'!C25/ABS('Adj ASM'!C29)) | D42: =IF(ABS('Adj ASM'!D29)=0,0,'Adj ASM'!D25/ABS('Adj ASM'!D29)) | E42: =IF(ABS('Adj ASM'!E29)=0,0,'Adj ASM'!E25/ABS('Adj ASM'!E29)) | F42: =IF(ABS('Adj ASM'!F29)=0,0,'Adj ASM'!F25/ABS('Adj ASM'!F29)) | G42: =IF(ABS('Adj ASM'!G29)=0,0,'Adj ASM'!G25/ABS('Adj ASM'!G29))
A44: GROWTH
A45: Revenue Growth | B45: N/A | C45: =IF('Adj ASM'!B9=0,0,'Adj ASM'!C9/'Adj ASM'!B9-1) | D45: =IF('Adj ASM'!C9=0,0,'Adj ASM'!D9/'Adj ASM'!C9-1) | E45: =IF('Adj ASM'!D9=0,0,'Adj ASM'!E9/'Adj ASM'!D9-1) | F45: =IF('Adj ASM'!E9=0,0,'Adj ASM'!F9/'Adj ASM'!E9-1) | G45: =IF('Adj ASM'!F9=0,0,'Adj ASM'!G9/'Adj ASM'!F9-1)
A46: Sustainable Growth | B46: N/A | C46: =IF('Adj ASM'!C33=0,0,(1-'Adj ASM'!C40*'Adj ASM'!C38/1000/'Adj ASM'!C33)*C6) | D46: =IF('Adj ASM'!D33=0,0,(1-'Adj ASM'!D40*'Adj ASM'!D38/1000/'Adj ASM'!D33)*D6) | E46: =IF('Adj ASM'!E33=0,0,(1-'Adj ASM'!E40*'Adj ASM'!E38/1000/'Adj ASM'!E33)*E6) | F46: =IF('Adj ASM'!F33=0,0,(1-'Adj ASM'!F40*'Adj ASM'!F38/1000/'Adj ASM'!F33)*F6) | G46: =IF('Adj ASM'!G33=0,0,(1-'Adj ASM'!G40*'Adj ASM'!G38/1000/'Adj ASM'!G33)*G6)

Sheet Ratios AIXTRON
A1: Ratio Analysis - AIXTRON
A2: (derived from Adjusted statements)
B3: 2019 | C3: 2020 | D3: 2021 | E3: 2022 | F3: 2023 | G3: 2024
A5: PROFITABILITY
A6: ROE | B6: N/A | C6: =IF(AVERAGE('Adj AIXTRON'!B81,'Adj AIXTRON'!C81)=0,0,'Adj AIXTRON'!C33/AVERAGE('Adj AIXTRON'!B81,'Adj AIXTRON'!C81)) | D6: =IF(AVERAGE('Adj AIXTRON'!C81,'Adj AIXTRON'!D81)=0,0,'Adj AIXTRON'!D33/AVERAGE('Adj AIXTRON'!C81,'Adj AIXTRON'!D81)) | E6: =IF(AVERAGE('Adj AIXTRON'!D81,'Adj AIXTRON'!E81)=0,0,'Adj AIXTRON'!E33/AVERAGE('Adj AIXTRON'!D81,'Adj AIXTRON'!E81)) | F6: =IF(AVERAGE('Adj AIXTRON'!E81,'Adj AIXTRON'!F81)=0,0,'Adj AIXTRON'!F33/AVERAGE('Adj AIXTRON'!E81,'Adj AIXTRON'!F81)) | G6: =IF(AVERAGE('Adj AIXTRON'!F81,'Adj AIXTRON'!G81)=0,0,'Adj AIXTRON'!G33/AVERAGE('Adj AIXTRON'!F81,'Adj AIXTRON'!G81))
A7: Net Profit Margin (ROS) | B7: =IF('Adj AIXTRON'!B9=0,0,'Adj AIXTRON'!B33/'Adj AIXTRON'!B9) | C7: =IF('Adj AIXTRON'!C9=0,0,'Adj AIXTRON'!C33/'Adj AIXTRON'!C9) | D7: =IF('Adj AIXTRON'!D9=0,0,'Adj AIXTRON'!D33/'Adj AIXTRON'!D9) | E7: =IF('Adj AIXTRON'!E9=0,0,'Adj AIXTRON'!E33/'Adj AIXTRON'!E9) | F7: =IF('Adj AIXTRON'!F9=0,0,'Adj AIXTRON'!F33/'Adj AIXTRON'!F9) | G7: =IF('Adj AIXTRON'!G9=0,0,'Adj AIXTRON'!G33/'Adj AIXTRON'!G9)
A8: x Asset Turnover | B8: N/A | C8: =IF(AVERAGE('Adj AIXTRON'!B73,'Adj AIXTRON'!C73)=0,0,'Adj AIXTRON'!C9/AVERAGE('Adj AIXTRON'!B73,'Adj AIXTRON'!C73)) | D8: =IF(AVERAGE('Adj AIXTRON'!C73,'Adj AIXTRON'!D73)=0,0,'Adj AIXTRON'!D9/AVERAGE('Adj AIXTRON'!C73,'Adj AIXTRON'!D73)) | E8: =IF(AVERAGE('Adj AIXTRON'!D73,'Adj AIXTRON'!E73)=0,0,'Adj AIXTRON'!E9/AVERAGE('Adj AIXTRON'!D73,'Adj AIXTRON'!E73)) | F8: =IF(AVERAGE('Adj AIXTRON'!E73,'Adj AIXTRON'!F73)=0,0,'Adj AIXTRON'!F9/AVERAGE('Adj AIXTRON'!E73,'Adj AIXTRON'!F73)) | G8: =IF(AVERAGE('Adj AIXTRON'!F73,'Adj AIXTRON'!G73)=0,0,'Adj AIXTRON'!G9/AVERAGE('Adj AIXTRON'!F73,'Adj AIXTRON'!G73))
A9: = ROA | B9: N/A | C9: =C7*C8 | D9: =D7*D8 | E9: =E7*E8 | F9: =F7*F8 | G9: =G7*G8
A10: x Financial Leverage | B10: N/A | C10: =IF(AVERAGE('Adj AIXTRON'!B81,'Adj AIXTRON'!C81)=0,0,AVERAGE('Adj AIXTRON'!B73,'Adj AIXTRON'!C73)/AVERAGE('Adj AIXTRON'!B81,'Adj AIXTRON'!C81)) | D10: =IF(AVERAGE('Adj AIXTRON'!C81,'Adj AIXTRON'!D81)=0,0,AVERAGE('Adj AIXTRON'!C73,'Adj AIXTRON'!D73)/AVERAGE('Adj AIXTRON'!C81,'Adj AIXTRON'!D81)) | E10: =IF(AVERAGE('Adj AIXTRON'!D81,'Adj AIXTRON'!E81)=0,0,AVERAGE('Adj AIXTRON'!D73,'Adj AIXTRON'!E73)/AVERAGE('Adj AIXTRON'!D81,'Adj AIXTRON'!E81)) | F10: =IF(AVERAGE('Adj AIXTRON'!E81,'Adj AIXTRON'!F81)=0,0,AVERAGE('Adj AIXTRON'!E73,'Adj AIXTRON'!F73)/AVERAGE('Adj AIXTRON'!E81,'Adj AIXTRON'!F81)) | G10: =IF(AVERAGE('Adj AIXTRON'!F81,'Adj AIXTRON'!G81)=0,0,AVERAGE('Adj AIXTRON'!F73,'Adj AIXTRON'!G73)/AVERAGE('Adj AIXTRON'!F81,'Adj AIXTRON'!G81))
A11: = ROE check (ROA x Leverage) | B11: N/A | C11: =C9*C10 | D11: =D9*D10 | E11: =E9*E10 | F11: =F9*F10 | G11: =G9*G10
A13: RNOA | B13: N/A | C13: =IF(AVERAGE('Adj AIXTRON'!B67,'Adj AIXTRON'!C67)=0,0,'Adj AIXTRON'!C36/AVERAGE('Adj AIXTRON'!B67,'Adj AIXTRON'!C67)) | D13: =IF(AVERAGE('Adj AIXTRON'!C67,'Adj AIXTRON'!D67)=0,0,'Adj AIXTRON'!D36/AVERAGE('Adj AIXTRON'!C67,'Adj AIXTRON'!D67)) | E13: =IF(AVERAGE('Adj AIXTRON'!D67,'Adj AIXTRON'!E67)=0,0,'Adj AIXTRON'!E36/AVERAGE('Adj AIXTRON'!D67,'Adj AIXTRON'!E67)) | F13: =IF(AVERAGE('Adj AIXTRON'!E67,'Adj AIXTRON'!F67)=0,0,'Adj AIXTRON'!F36/AVERAGE('Adj AIXTRON'!E67,'Adj AIXTRON'!F67)) | G13: =IF(AVERAGE('Adj AIXTRON'!F67,'Adj AIXTRON'!G67)=0,0,'Adj AIXTRON'!G36/AVERAGE('Adj AIXTRON'!F67,'Adj AIXTRON'!G67))
A14: NOPAT Margin | B14: =IF('Adj AIXTRON'!B9=0,0,'Adj AIXTRON'!B36/'Adj AIXTRON'!B9) | C14: =IF('Adj AIXTRON'!C9=0,0,'Adj AIXTRON'!C36/'Adj AIXTRON'!C9) | D14: =IF('Adj AIXTRON'!D9=0,0,'Adj AIXTRON'!D36/'Adj AIXTRON'!D9) | E14: =IF('Adj AIXTRON'!E9=0,0,'Adj AIXTRON'!E36/'Adj AIXTRON'!E9) | F14: =IF('Adj AIXTRON'!F9=0,0,'Adj AIXTRON'!F36/'Adj AIXTRON'!F9) | G14: =IF('Adj AIXTRON'!G9=0,0,'Adj AIXTRON'!G36/'Adj AIXTRON'!G9)
