Workbook

Sheet Modified
C2: EFP | D2: EFP | E2: EFP | F2: EFP | G2: EFP | H2: PH
C3: 1 | D3: 2 | E3: 3 | F3: 4 | G3: 5 | H3: 6
A4: NOPAT | C4: 100 | D4: =C4*(1+$C13) -> 109 | E4: =D4*(1+$C13) -> 118.81 | F4: =E4*(1+$C13) -> 129.5029 | G4: =F4*(1+$C13) -> 141.15816 | H4: =G4*(1+H13) -> 149.62765 | I4: =H4*(1+I13) -> 158.60531
A5: Depreciation Expense | C5: 20 | D5: 21.8 | E5: 23.8 | F5: 25.9 | G5: 28.2
A6: Operating Investment | C6: 76.3 | D6: 83.1 | E6: 90.6 | F6: 98.7 | G6: 107.6
A7: Change in IC | C7: =C6-C5 -> 56.3 | D7: =D6-D5 -> 61.3 | E7: =E6-E5 -> 66.8 | F7: =F6-F5 -> 72.8 | G7: =(H4-G4)/H17 -> 70.579081 | H7: =(I4-H4)/I17 -> 74.813825 | I7: =I4*I13/I17 -> 79.302655
A8: FCFi | C8: =C4-C7 -> 43.7 | D8: =D4-D7 -> 47.7 | E8: =E4-E7 -> 52.01 | F8: =F4-F7 -> 56.7029 | G8: =G4-G7 -> 70.57908 | H8: =H4-H7 -> 74.813825 | I8: =I4-I7 -> 79.302655
A9: Discount Factor | C9: =1/(1+C15)^C3 -> 0.89285714 | D9: =1/(1+D15)^D3 -> 0.79719388 | E9: =1/(1+E15)^E3 -> 0.71178025 | F9: =1/(1+F15)^F3 -> 0.63551808 | G9: =1/(1+G15)^G3 -> 0.56742686 | H9: =1/(1+H15)^H3 -> 0.50663112
A10: PVFCFi | C10: =C8*C9 -> 39.017857 | D10: =D8*D9 -> 38.026148 | E10: =E8*E9 -> 37.019691 | F10: =F8*F9 -> 36.035718 | G10: =G8*G9 -> 40.048466 | H10: =H8*H9 -> 37.903012
A12: IC0 | B12: 800
A13: g | C13: 0.09 | D13: 0.09 | E13: 0.09 | F13: 0.09 | G13: 0.09 | H13: 0.06 | I13: 0.06
A15: r | C15: 0.12 | D15: =C15 -> 0.12 | E15: =D15 -> 0.12 | F15: =E15 -> 0.12 | G15: =F15 -> 0.12 | H15: =G15 -> 0.12 | I15: =H15 -> 0.12 | J15: 0.12
A17: RONIC (Desired) | D17: =(D4-C4)/(C6-C5) -> 0.1598579 | E17: =(E4-D4)/(D6-D5) -> 0.16003263 | F17: =(F4-E4)/(E6-E5) -> 0.16007335 | G17: =(G4-F4)/(F6-F5) -> 0.16009974 | H17: 0.12 | I17: 0.12
A18: RONIC (Actual) | D18: =(D4-C4)/(C7) -> 0.1598579 | E18: =(E4-D4)/(D7) -> 0.16003263 | F18: =(F4-E4)/(E7) -> 0.16007335 | G18: =(G4-F4)/(F7) -> 0.16009974 | H18: =(H4-G4)/(G7) -> 0.12 | I18: =(I4-H4)/(H7) -> 0.12
A20: DCF Analysis
A22: PVFCF (EFP) | B22: =C10+D10+E10+F10+G10 -> 190.14788
A23: CV (5) | B23: =H8/(H15-H13) -> 1246.8971
A24: CV(0) | B24: =B23/(1+G15) ^5 -> 707.52289
A25: EV(0) | B25: =B24+B22 -> 897.67077
A28: ANOPAT Analysis
A30: ICi | B30: =B12 -> 800 | C30: =B30+C7 -> 856.3 | D30: =C30+D7 -> 917.6 | E30: =D30+E7 -> 984.4 | F30: =E30+F7 -> 1057.2 | G30: =F30+G7 -> 1127.7791 | H30: =G30+H7 -> 1202.5929 | I30: =H30+I7 -> 1281.8956
A31: ANOPATi | C31: =C4-(C15*B30) -> 4 | D31: =D4-(D15*C30) -> 6.244 | E31: =E4-(E15*D30) -> 8.698 | F31: =F4-(F15*E30) -> 11.3749 | G31: =G4-(G15*F30) -> 14.294161 | H31: =H4-(H15*G30) -> 14.294161 | I31: =I4-(I15*H30) -> 14.294161
A32: PV(ANOPATi) | C32: =C31*C9 -> 3.5714286 | D32: =D31*D9 -> 4.9776786 | E32: =E31*E9 -> 6.1910646 | F32: =F31*F9 -> 7.2289546 | G32: =G31*G9 -> 8.1108908
A35: PVANOPAT (EFP) | B35: =SUM(C32:G32) -> 30.080017
A36: CV (5) | B36: =H31/H15 -> 119.11801
A37: CV(0) | B37: =B36/(1+H15)^5 -> 67.590757
A38: IC0 | B38: =B30 -> 800
A39: EV(0) | B39: =B38+B37+B35 -> 897.67077
A41: ROIC | C41: =C4/B30 -> 0.125 | D41: =D4/C30 -> 0.12729184 | E41: =E4/D30 -> 0.12947908 | F41: =F4/E30 -> 0.13155516 | G41: =G4/F30 -> 0.13352077 | H41: =H4/G30 -> 0.13267461 | I41: =I4/H30 -> 0.13188612

Sheet Original
C2: =Modified!C2 -> EFP | D2: =Modified!D2 -> EFP | E2: =Modified!E2 -> EFP | F2: =Modified!F2 -> EFP | G2: =Modified!G2 -> EFP | H2: =Modified!H2 -> PH
C3: =Modified!C3 -> 1 | D3: =Modified!D3 -> 2 | E3: =Modified!E3 -> 3 | F3: =Modified!F3 -> 4 | G3: =Modified!G3 -> 5 | H3: =Modified!H3 -> 6
A5: NOPAT | C5: =Modified!C4 -> 100 | D5: =Modified!D4 -> 109 | E5: =Modified!E4 -> 118.81 | F5: =Modified!F4 -> 129.5029 | G5: =Modified!G4 -> 141.15816 | H5: =Modified!H4 -> 149.62765
A6: Depreciation Expense | C6: =Modified!C5 -> 20 | D6: =Modified!D5 -> 21.8 | E6: =Modified!E5 -> 23.8 | F6: =Modified!F5 -> 25.9 | G6: 28.22
A7: Operating Investment | C7: =Modified!C6 -> 76.3 | D7: =Modified!D6 -> 83.1 | E7: =Modified!E6 -> 90.6 | F7: =Modified!F6 -> 98.7 | G7: =Modified!G6 -> 107.6
A8: Change in IC | C8: =Modified!C7 -> 56.3 | D8: =Modified!D7 -> 61.3 | E8: =Modified!E7 -> 66.8 | F8: =Modified!F7 -> 72.8 | G8: =G7-G6 -> 79.38 | H8: =H5*H14/H50 -> 74.813825
A9: FCFi | C9: =Modified!C8 -> 43.7 | D9: =Modified!D8 -> 47.7 | E9: =Modified!E8 -> 52.01 | F9: =Modified!F8 -> 56.7029 | G9: =G5-G8 -> 61.778161 | H9: =H5-H8 -> 74.813825
A10: Discount Factor | C10: =Modified!C9 -> 0.89285714 | D10: =Modified!D9 -> 0.79719388 | E10: =Modified!E9 -> 0.71178025 | F10: =Modified!F9 -> 0.63551808 | G10: =Modified!G9 -> 0.56742686 | H10: =Modified!H9 -> 0.50663112
A11: PVFCFi | C11: =Modified!C10 -> 39.017857 | D11: =Modified!D10 -> 38.026148 | E11: =Modified!E10 -> 37.019691 | F11: =Modified!F10 -> 36.035718 | G11: =Modified!G10 -> 40.048466 | H11: =Modified!H10 -> 37.903012
A13: IC0 | B13: 800
A14: g | D14: =(D5-C5)/C5 -> 0.09 | E14: =(E5-D5)/D5 -> 0.09 | F14: =(F5-E5)/E5 -> 0.09 | G14: =(G5-F5)/F5 -> 0.09 | H14: =(H5-G5)/G5 -> 0.06
A16: r | B16: 0.12 | C16: 0.12 | D16: 0.12 | E16: 0.12 | F16: 0.12 | G16: 0.12 | H16: 0.12
A19: FCF6 | B19: =H9 -> 74.813825 | C19: >> | D19: (1+6%) FCF5 | E19: =(1+H14)*G9 -> 65.484851
A23: DCF Analysis
A25: PVFCF (EFP) | B25: =C11+D11+E11+F11+G11 -> 190.14788
A26: CV (5) | B26: =H9/(H16-H14) -> 1246.8971
A27: CV(0) | B27: =B26/(1+G16) ^5 -> 707.52289
A28: EV(0) | B28: =B27+B25 -> 897.67077
A31: ANOPAT Analysis
C33: EFP | D33: EFP | E33: EFP | F33: EFP | G33: EFP | H33: EFP
C34: 1 | D34: =C34+1 -> 2 | E34: =D34+1 -> 3 | F34: =E34+1 -> 4 | G34: =F34+1 -> 5 | H34: =G34+1 -> 6
A36: Ici | B36: =B13 -> 800 | C36: =B36+C8 -> 856.3 | D36: =C36+D8 -> 917.6 | E36: =D36+E8 -> 984.4 | F36: =E36+F8 -> 1057.2 | G36: =F36+G8 -> 1136.58
A37: ANOPATi | C37: =C5-(B16*B36) -> 4 | D37: =D5-(C16*C36) -> 6.244 | E37: =E5-(D16*D36) -> 8.698 | F37: =F5-(E16*E36) -> 11.3749 | G37: =G5-(F16*F36) -> 14.294161 | H37: =H5-(G16*G36) -> 13.238051
A38: PV(ANOPATi) | C38: =C37/(1+C16)^C3 -> 3.5714286 | D38: =D37/(1+D16)^D3 -> 4.9776786 | E38: =E37/(1+E16)^E3 -> 6.1910646 | F38: =F37/(1+F16)^F3 -> 7.2289546 | G38: =G37/(1+G16)^G3 -> 8.1108908
A41: PVANOPAT (EFP) | B41: =SUM(C38:G38) -> 30.080017
A42: CV (5) | B42: =H37/H16 -> 110.31709
A43: CV(0) | B43: =B42/(1+B16)^5 -> 62.596879
A44: IC0 | B44: =B13 -> 800
A45: EV(0) | B45: =B41+B43+B44 -> 892.6769
A49: RONIC (Actual) | D49: =((D5-C5)/((C8))) -> 0.1598579 | E49: =((E5-D5)/((D8))) -> 0.16003263 | F49: =((F5-E5)/((E8))) -> 0.16007335 | G49: =((G5-F5)/((F8))) -> 0.16009974 | H49: =((H5-G5)/((G8))) -> 0.10669551 | I49: 0.12
A50: RONIC (Planned) | D50: 0.16 | E50: 0.16 | F50: 0.16 | G50: 0.16 | H50: 0.12 | I50: 0.12
