Workbook
Name asd: #REF!
Name Forecast: #REF!
Name Forecast: #REF!
Name IQ_CH: 110000
Name IQ_CQ: 5000
Name IQ_CY: 10000
Name IQ_DAILY: 500000
Name IQ_FH: 100000
Name IQ_FQ: 500
Name IQ_FY: 1000
Name IQ_LTM: 2000
Name IQ_MONTH: 15000
Name IQ_NTM: 6000
Name IQ_WEEK: 50000
Name IQ_YTD: 3000
Name rampup: #REF!
Name Step_1: #REF!
Name Step_1: #REF!
Name Step_2: #REF!
Name Step_2: #REF!
Name Step_3: #REF!
Name Step_3: #REF!
Name Step_4: #REF!
Name Step_4: #REF!
Name Step_5: #REF!
Name Step_5: #REF!
Name Step_6: #REF!
Name Step_6: #REF!
Name Step1: #REF!
Name Step2: #REF!
Name Step3: #REF!
Name Step4: #REF!
Name Step5: #REF!
Name Step6: #REF!

Sheet BioNTech Financial Analysis>>>
B45: <<< End of sheet >>>

Sheet Adjustments Slide Output
C2: BioNTech | E2: Astra Zeneca | G2: Moderna | I2: Sanofi | K2: GSK | M2: Takeda
B3: Depreciation policy adjustment | C3: 2020 | D3: =C3+3 -> 2023 | E3: 2020 | F3: =E3+3 -> 2023 | G3: 2020 | H3: =G3+3 -> 2023 | I3: 2020 | J3: =I3+3 -> 2023 | K3: 2020 | L3: =K3+3 -> 2023 | M3: 2020 | N3: =M3+3 -> 2023
B4: PP/E over PP/E + intangibles | C4: ='BionTech Ratios'!H40 -> 0.62342945 | D4: ='BionTech Ratios'!K40 -> 0.79022248 | E4: ='Astra Zeneca Ratios'!H40 -> 0.21842537 | F4: ='Astra Zeneca Ratios'!K40 -> 0.14906814 | G4: ='Moderna Ratios'!H40 -> 0.95768087 | H4: ='Moderna Ratios'!K40 -> 0.69335496 | I4: ='Sanofi Ratios'!H40 -> 0.15729014 | J4: ='Sanofi Ratios'!K40 -> 0.14776535 | K4: ='GSK Ratios'!H40 -> 0.22872429 | L4: ='GSK Ratios'!K40 -> 0.33536586 | M4: ='Takeda Ratios'!H40 -> 0.15609811 | N4: ='Takeda Ratios'!K40 -> 0.19112822
B5: Depreciation (% of non-current operating assets) | C5: ='BionTech Ratios'!H38 -> 0.16295011 | D5: ='BionTech Ratios'!K38 -> 0.17511697 | E5: ='Astra Zeneca Ratios'!H38 -> 0.063550355 | F5: ='Astra Zeneca Ratios'!K38 -> 0.052849078 | G5: ='Moderna Ratios'!H38 -> 0.1402021 | H5: ='Moderna Ratios'!K38 -> 0.26347133 | I5: ='Sanofi Ratios'!H38 -> 0.043580406 | J5: ='Sanofi Ratios'!K38 -> 0.03634536 | K5: ='GSK Ratios'!H38 -> 0.052812283 | L5: ='GSK Ratios'!K38 -> 0.039171095 | M5: ='Takeda Ratios'!H38 -> 0.018164495 | N5: ='Takeda Ratios'!K38 -> 0.012150903
B6: Implied useful life | C6: ='BionTech Ratios'!H39 -> 6.1368475 | D6: ='BionTech Ratios'!K39 -> 5.7104689 | E6: ='Astra Zeneca Ratios'!H39 -> 15.735553 | F6: ='Astra Zeneca Ratios'!K39 -> 18.921806 | G6: ='Moderna Ratios'!H39 -> 7.1325606 | H6: ='Moderna Ratios'!K39 -> 3.7954793 | I6: ='Sanofi Ratios'!H39 -> 22.946092 | J6: ='Sanofi Ratios'!K39 -> 27.513829 | K6: ='GSK Ratios'!H39 -> 18.934989 | L6: ='GSK Ratios'!K39 -> 25.529028 | M6: ='Takeda Ratios'!H39 -> 55.052453 | N6: ='Takeda Ratios'!K39 -> 82.298412

Sheet Dashboard Slide Output
C2: BioNTech | H2: Astra Zeneca | M2: Moderna | R2: Sanofi | W2: GSK | AB2: Takeda | AH2: Industry avg.* | AI2: BioNTech | AJ2: Industry avg.* | AK2: BioNTech | AL2: Industry avg.* | AM2: BioNTech | AN2: Industry avg.* | AO2: BioNTech | AP2: Industry avg.* | AQ2: BioNTech | AS2: *excluding Moderna
B3: Ratio analysis | C3: 2019 | D3: 2020 | E3: 2021 | F3: 2022 | G3: 2023 | H3: 2019 | I3: 2020 | J3: 2021 | K3: 2022 | L3: 2023 | M3: 2019 | N3: 2020 | O3: 2021 | P3: 2022 | Q3: 2023 | R3: 2019 | S3: 2020 | T3: 2021 | U3: 2022 | V3: 2023 | W3: 2019 | X3: 2020 | Y3: 2021 | Z3: 2022 | AA3: 2023 | AB3: 2019 | AC3: 2020 | AD3: 2021 | AE3: 2022 | AF3: 2023 | AH3: 2019 | AI3: =AH3 -> 2019 | AJ3: 2020 | AK3: =AJ3 -> 2020 | AL3: 2021 | AM3: =AL3 -> 2021 | AN3: 2022 | AO3: =AN3 -> 2022 | AP3: 2023 | AQ3: =AP3 -> 2023
A5: x | B5: Decomposition of ROE
B6: Net profit margin (ROS) | C6: =+'BionTech Ratios'!G8 -> -1.6500921 | D6: =+'BionTech Ratios'!H8 -> 0.031515654 | E6: =+'BionTech Ratios'!I8 -> 0.54237565 | F6: =+'BionTech Ratios'!J8 -> 0.54500711 | G6: =+'BionTech Ratios'!K8 -> 0.2435978 | H6: =+'Astra Zeneca Ratios'!G8 -> 0.050319815 | I6: =+'Astra Zeneca Ratios'!H8 -> 0.11811994 | J6: =+'Astra Zeneca Ratios'!I8 -> 0.0030734728 | K6: =+'Astra Zeneca Ratios'!J8 -> 0.074248582 | L6: =+'Astra Zeneca Ratios'!K8 -> 0.13012158 | M6: =+'Moderna Ratios'!G8 -> -8.5666978 | N6: =+'Moderna Ratios'!H8 -> -0.93026056 | O6: =+'Moderna Ratios'!I8 -> 0.66060313 | P6: =+'Moderna Ratios'!J8 -> 0.43409645 | Q6: =+'Moderna Ratios'!K8 -> -0.68837627 | R6: =+'Sanofi Ratios'!G8 -> 0.076692089 | S6: =+'Sanofi Ratios'!H8 -> 0.32995263 | T6: =+'Sanofi Ratios'!I8 -> 0.16028079 | U6: =+'Sanofi Ratios'!J8 -> 0.20055081 | V6: =+'Sanofi Ratios'!K8 -> 0.12401177 | W6: =+'GSK Ratios'!G8 -> 0.15607038 | X6: =+'GSK Ratios'!H8 -> 0.20953439 | Y6: =+'GSK Ratios'!I8 -> 0.14237124 | Z6: =+'GSK Ratios'!J8 -> 0.16781473 | AA6: =+'GSK Ratios'!K8 -> 0.17501982 | AB6: =+'Takeda Ratios'!G8 -> 0.0041569725 | AC6: =+'Takeda Ratios'!H8 -> 0.056447463 | AD6: =+'Takeda Ratios'!I8 -> 0.12656836 | AE6: =+'Takeda Ratios'!J8 -> 0.069595524 | AF6: =+'Takeda Ratios'!K8 -> 0.042774069 | AH6: =AVERAGE(H6,R6,W6,AB6) -> 0.071809814 | AI6: =C6 -> -1.6500921 | AJ6: =AVERAGE(I6,S6,X6,AC6) -> 0.17851361 | AK6: =D6 -> 0.031515654 | AL6: =AVERAGE(J6,T6,Y6,AD6) -> 0.10807347 | AM6: =E6 -> 0.54237565 | AN6: =AVERAGE(K6,U6,Z6,AE6) -> 0.12805241 | AO6: =F6 -> 0.54500711 | AP6: =AVERAGE(L6,V6,AA6,AF6) -> 0.11798181 | AQ6: =G6 -> 0.2435978
B7: × Asset turnover | C7: =+'BionTech Ratios'!G9 -> 0.14972774 | D7: =+'BionTech Ratios'!H9 -> 0.30953901 | E7: =+'BionTech Ratios'!I9 -> 2.0911655 | F7: =+'BionTech Ratios'!J9 -> 0.88522855 | G7: =+'BionTech Ratios'!K9 -> 0.16501964 | H7: =+'Astra Zeneca Ratios'!G9 -> 0.40464257 | I7: =+'Astra Zeneca Ratios'!H9 -> 0.42742084 | J7: =+'Astra Zeneca Ratios'!I9 -> 0.43007935 | K7: =+'Astra Zeneca Ratios'!J9 -> 0.46130157 | L7: =+'Astra Zeneca Ratios'!K9 -> 0.46620346 | M7: =+'Moderna Ratios'!G9 -> 0.034248392 | N7: =+'Moderna Ratios'!H9 -> 0.18999301 | O7: =+'Moderna Ratios'!I9 -> 1.1286351 | P7: =+'Moderna Ratios'!J9 -> 0.79871252 | Q7: =+'Moderna Ratios'!K9 -> 0.30996763 | R7: =+'Sanofi Ratios'!G9 -> 0.33593408 | S7: =+'Sanofi Ratios'!H9 -> 0.32917994 | T7: =+'Sanofi Ratios'!I9 -> 0.33389444 | U7: =+'Sanofi Ratios'!J9 -> 0.32639575 | V7: =+'Sanofi Ratios'!K9 -> 0.3247336 | W7: =+'GSK Ratios'!G9 -> 0.48508677 | X7: =+'GSK Ratios'!H9 -> 0.29814702 | Y7: =+'GSK Ratios'!I9 -> 0.31238223 | Z7: =+'GSK Ratios'!J9 -> 0.42471307 | AA7: =+'GSK Ratios'!K9 -> 0.51358952 | AB7: =+'Takeda Ratios'!G9 -> 0.34732494 | AC7: =+'Takeda Ratios'!H9 -> 0.25739257 | AD7: =+'Takeda Ratios'!I9 -> 0.27480826 | AE7: =+'Takeda Ratios'!J9 -> 0.29688703 | AF7: =+'Takeda Ratios'!K9 -> 0.29389344 | AH7: =AVERAGE(H7,R7,W7,AB7) -> 0.39324709 | AI7: =C7 -> 0.14972774 | AJ7: =AVERAGE(I7,S7,X7,AC7) -> 0.32803509 | AK7: =D7 -> 0.30953901 | AL7: =AVERAGE(J7,T7,Y7,AD7) -> 0.33779107 | AM7: =E7 -> 2.0911655 | AN7: =AVERAGE(K7,U7,Z7,AE7) -> 0.37732436 | AO7: =F7 -> 0.88522855 | AP7: =AVERAGE(L7,V7,AA7,AF7) -> 0.399605 | AQ7: =G7 -> 0.16501964
B8: = Return on assets (ROA) | C8: =+'BionTech Ratios'!G10 -> -0.24706456 | D8: =+'BionTech Ratios'!H10 -> 0.0097553243 | E8: =+'BionTech Ratios'!I10 -> 1.1341973 | F8: =+'BionTech Ratios'!J10 -> 0.48245585 | G8: =+'BionTech Ratios'!K10 -> 0.040198421 | H8: =+'Astra Zeneca Ratios'!G10 -> 0.02036154 | I8: =+'Astra Zeneca Ratios'!H10 -> 0.050486925 | J8: =+'Astra Zeneca Ratios'!I10 -> 0.0013218372 | K8: =+'Astra Zeneca Ratios'!J10 -> 0.034250988 | L8: =+'Astra Zeneca Ratios'!K10 -> 0.060663132 | M8: =+'Moderna Ratios'!G10 -> -0.29339562 | N8: =+'Moderna Ratios'!H10 -> -0.176743 | O8: =+'Moderna Ratios'!I10 -> 0.74557989 | P8: =+'Moderna Ratios'!J10 -> 0.34671827 | Q8: =+'Moderna Ratios'!K10 -> -0.21337436 | R8: =+'Sanofi Ratios'!G10 -> 0.025763487 | S8: =+'Sanofi Ratios'!H10 -> 0.10861379 | T8: =+'Sanofi Ratios'!I10 -> 0.053516865 | U8: =+'Sanofi Ratios'!J10 -> 0.065458933 | V8: =+'Sanofi Ratios'!K10 -> 0.040270789 | W8: =+'GSK Ratios'!G10 -> 0.075707677 | X8: =+'GSK Ratios'!H10 -> 0.062472055 | Y8: =+'GSK Ratios'!I10 -> 0.044474244 | Z8: =+'GSK Ratios'!J10 -> 0.071273111 | AA8: =+'GSK Ratios'!K10 -> 0.089888347 | AB8: =+'Takeda Ratios'!G10 -> 0.0014438202 | AC8: =+'Takeda Ratios'!H10 -> 0.014529158 | AD8: =+'Takeda Ratios'!I10 -> 0.034782031 | AE8: =+'Takeda Ratios'!J10 -> 0.020662009 | AF8: =+'Takeda Ratios'!K10 -> 0.012571019 | AH8: =AVERAGE(H8,R8,W8,AB8) -> 0.030819131 | AI8: =C8 -> -0.24706456 | AJ8: =AVERAGE(I8,S8,X8,AC8) -> 0.059025481 | AK8: =D8 -> 0.0097553243 | AL8: =AVERAGE(J8,T8,Y8,AD8) -> 0.033523744 | AM8: =E8 -> 1.1341973 | AN8: =AVERAGE(K8,U8,Z8,AE8) -> 0.04791126 | AO8: =F8 -> 0.48245585 | AP8: =AVERAGE(L8,V8,AA8,AF8) -> 0.050848322 | AQ8: =G8 -> 0.040198421
B9: × Financial Leverage | C9: =+'BionTech Ratios'!G11 -> 1.9074928 | D9: =+'BionTech Ratios'!H11 -> 1.6706483 | E9: =+'BionTech Ratios'!I11 -> 1.3681655 | F9: =+'BionTech Ratios'!J11 -> 1.2241238 | G9: =+'BionTech Ratios'!K11 -> 1.1484783 | H9: =+'Astra Zeneca Ratios'!G11 -> 4.2601848 | I9: =+'Astra Zeneca Ratios'!H11 -> 4.2358134 | J9: =+'Astra Zeneca Ratios'!I11 -> 3.1100648 | K9: =+'Astra Zeneca Ratios'!J11 -> 2.6426498 | L9: =+'Astra Zeneca Ratios'!K11 -> 2.5925688 | M9: =+'Moderna Ratios'!G11 -> 1.3132882 | N9: =+'Moderna Ratios'!H11 -> 2.3608836 | O9: =+'Moderna Ratios'!I11 -> 1.9055022 | P9: =+'Moderna Ratios'!J11 -> 1.512863 | Q9: =+'Moderna Ratios'!K11 -> 1.3430569 | R9: =+'Sanofi Ratios'!G11 -> 1.8943728 | S9: =+'Sanofi Ratios'!H11 -> 1.8536846 | T9: =+'Sanofi Ratios'!I11 -> 1.7738863 | U9: =+'Sanofi Ratios'!J11 -> 1.712851 | V9: =+'Sanofi Ratios'!K11 -> 1.6934952 | W9: =+'GSK Ratios'!G11 -> 6.1621251 | X9: =+'GSK Ratios'!H11 -> 4.0950431 | Y9: =+'GSK Ratios'!I11 -> 3.7823462 | Z9: =+'GSK Ratios'!J11 -> 4.4028177 | AA9: =+'GSK Ratios'!K11 -> 5.1978934 | AB9: =+'Takeda Ratios'!G11 -> 2.7161262 | AC9: =+'Takeda Ratios'!H11 -> 2.660841 | AD9: =+'Takeda Ratios'!I11 -> 2.5080938 | AE9: =+'Takeda Ratios'!J11 -> 2.2804708 | AF9: =+'Takeda Ratios'!K11 -> 2.1481836 | AH9: =AVERAGE(H9,R9,W9,AB9) -> 3.7582022 | AI9: =C9 -> 1.9074928 | AJ9: =AVERAGE(I9,S9,X9,AC9) -> 3.2113455 | AK9: =D9 -> 1.6706483 | AL9: =AVERAGE(J9,T9,Y9,AD9) -> 2.7935978 | AM9: =E9 -> 1.3681655 | AN9: =AVERAGE(K9,U9,Z9,AE9) -> 2.7596973 | AO9: =F9 -> 1.2241238 | AP9: =AVERAGE(L9,V9,AA9,AF9) -> 2.9080352 | AQ9: =G9 -> 1.1484783
B10: = Return on equity (ROE) | C10: =+'BionTech Ratios'!G12 -> -0.47127386 | D10: =+'BionTech Ratios'!H12 -> 0.016297716 | E10: =+'BionTech Ratios'!I12 -> 1.5517696 | F10: =+'BionTech Ratios'!J12 -> 0.59058571 | G10: =+'BionTech Ratios'!K12 -> 0.046167016 | H10: =+'Astra Zeneca Ratios'!G12 -> 0.086743921 | I10: =+'Astra Zeneca Ratios'!H12 -> 0.21385319 | J10: =+'Astra Zeneca Ratios'!I12 -> 0.0041109993 | K10: =+'Astra Zeneca Ratios'!J12 -> 0.090513366 | L10: =+'Astra Zeneca Ratios'!K12 -> 0.15727334 | M10: =+'Moderna Ratios'!G12 -> -0.385313 | N10: =+'Moderna Ratios'!H12 -> -0.41726965 | O10: =+'Moderna Ratios'!I12 -> 1.4207041 | P10: =+'Moderna Ratios'!J12 -> 0.52453725 | Q10: =+'Moderna Ratios'!K12 -> -0.2865739 | R10: =+'Sanofi Ratios'!G12 -> 0.048805648 | S10: =+'Sanofi Ratios'!H12 -> 0.20133571 | T10: =+'Sanofi Ratios'!I12 -> 0.094932833 | U10: =+'Sanofi Ratios'!J12 -> 0.1121214 | V10: =+'Sanofi Ratios'!K12 -> 0.068198388 | W10: =+'GSK Ratios'!G12 -> 0.46652018 | X10: =+'GSK Ratios'!H12 -> 0.25582575 | Y10: =+'GSK Ratios'!I12 -> 0.16821699 | Z10: =+'GSK Ratios'!J12 -> 0.31380252 | AA10: =+'GSK Ratios'!K12 -> 0.46723005 | AB10: =+'Takeda Ratios'!G12 -> 0.003921598 | AC10: =+'Takeda Ratios'!H12 -> 0.038659779 | AD10: =+'Takeda Ratios'!I12 -> 0.087236598 | AE10: =+'Takeda Ratios'!J12 -> 0.047119107 | AF10: =+'Takeda Ratios'!K12 -> 0.027004856 | AH10: =AVERAGE(H10,R10,W10,AB10) -> 0.15149784 | AI10: =C10 -> -0.47127386 | AJ10: =AVERAGE(I10,S10,X10,AC10) -> 0.17741861 | AK10: =D10 -> 0.016297716 | AL10: =AVERAGE(J10,T10,Y10,AD10) -> 0.088624355 | AM10: =E10 -> 1.5517696 | AN10: =AVERAGE(K10,U10,Z10,AE10) -> 0.1408891 | AO10: =F10 -> 0.59058571 | AP10: =AVERAGE(L10,V10,AA10,AF10) -> 0.17992666 | AQ10: =G10 -> 0.046167016
B12: Decomposition of RNOA
B13: Net Operating Profit Margin | C13: =+'BionTech Ratios'!G16 -> -1.6560866 | D13: =+'BionTech Ratios'!H16 -> 0.072266224 | E13: =+'BionTech Ratios'!I16 -> 0.54625377 | F13: =+'BionTech Ratios'!J16 -> 0.53943052 | G13: =+'BionTech Ratios'!K16 -> 0.2033603 | H13: =+'Astra Zeneca Ratios'!G16 -> 0.050319815 | I13: =+'Astra Zeneca Ratios'!H16 -> 0.11811994 | J13: =+'Astra Zeneca Ratios'!I16 -> 0.0030734728 | K13: =+'Astra Zeneca Ratios'!J16 -> 0.074248582 | L13: =+'Astra Zeneca Ratios'!K16 -> 0.13012158 | M13: =+'Moderna Ratios'!G16 -> -8.5666978 | N13: =+'Moderna Ratios'!H16 -> -0.93026056 | O13: =+'Moderna Ratios'!I16 -> 0.66060313 | P13: =+'Moderna Ratios'!J16 -> 0.43409645 | Q13: =+'Moderna Ratios'!K16 -> -0.68837627 | R13: =+'Sanofi Ratios'!G16 -> 0.076692089 | S13: =+'Sanofi Ratios'!H16 -> 0.32995263 | T13: =+'Sanofi Ratios'!I16 -> 0.16028079 | U13: =+'Sanofi Ratios'!J16 -> 0.20055081 | V13: =+'Sanofi Ratios'!K16 -> 0.12401177 | W13: =+'GSK Ratios'!G16 -> 0.15680007 | X13: =+'GSK Ratios'!H16 -> 0.21104585 | Y13: =+'GSK Ratios'!I16 -> 0.14366132 | Z13: =+'GSK Ratios'!J16 -> 0.16863215 | AA13: =+'GSK Ratios'!K16 -> 0.17613364 | AB13: =+'Takeda Ratios'!G16 -> 0.0052042531 | AC13: =+'Takeda Ratios'!H16 -> 0.058279239 | AD13: =+'Takeda Ratios'!I16 -> 0.12752956 | AE13: =+'Takeda Ratios'!J16 -> 0.070306446 | AF13: =+'Takeda Ratios'!K16 -> 0.043828044 | AH13: =AVERAGE(H13,R13,W13,AB13) -> 0.072254058 | AI13: =C13 -> -1.6560866 | AJ13: =AVERAGE(I13,S13,X13,AC13) -> 0.17934942 | AK13: =D13 -> 0.072266224 | AL13: =AVERAGE(J13,T13,Y13,AD13) -> 0.10863629 | AM13: =E13 -> 0.54625377 | AN13: =AVERAGE(K13,U13,Z13,AE13) -> 0.1284345 | AO13: =F13 -> 0.53943052 | AP13: =AVERAGE(L13,V13,AA13,AF13) -> 0.11852376 | AQ13: =G13 -> 0.2033603
B14: × Net Operating Asset Turnover | C14: =+'BionTech Ratios'!G17 -> -2.5810975 | D14: =+'BionTech Ratios'!H17 -> 2.0104252 | E14: =+'BionTech Ratios'!I17 -> 3.2012382 | F14: =+'BionTech Ratios'!J17 -> 1.8605481 | G14: =+'BionTech Ratios'!K17 -> 0.50939765 | H14: =+'Astra Zeneca Ratios'!G17 -> 0.76102786 | I14: =+'Astra Zeneca Ratios'!H17 -> 0.82850143 | J14: =+'Astra Zeneca Ratios'!I17 -> 0.71431685 | K14: =+'Astra Zeneca Ratios'!J17 -> 0.69730988 | L14: =+'Astra Zeneca Ratios'!K17 -> 0.71170839 | M14: =+'Moderna Ratios'!G17 -> -1.6970081 | N14: =+'Moderna Ratios'!H17 -> -0.73307656 | O14: =+'Moderna Ratios'!I17 -> -9.2139921 | P14: =+'Moderna Ratios'!J17 -> 25.812795 | Q14: =+'Moderna Ratios'!K17 -> 2.6697392 | R14: =+'Sanofi Ratios'!G17 -> 0.49359446 | S14: =+'Sanofi Ratios'!H17 -> 0.49168443 | T14: =+'Sanofi Ratios'!I17 -> 0.49004523 | U14: =+'Sanofi Ratios'!J17 -> 0.47768001 | V14: =+'Sanofi Ratios'!K17 -> 0.48197207 | W14: =+'GSK Ratios'!G17 -> 0.89187875 | X14: =+'GSK Ratios'!H17 -> 0.53721839 | Y14: =+'GSK Ratios'!I17 -> 0.58446901 | Z14: =+'GSK Ratios'!J17 -> 0.82239206 | AA14: =+'GSK Ratios'!K17 -> 1.0333967 | AB14: =+'Takeda Ratios'!G17 -> 0.46154454 | AC14: =+'Takeda Ratios'!H17 -> 0.33692916 | AD14: =+'Takeda Ratios'!I17 -> 0.36690055 | AE14: =+'Takeda Ratios'!J17 -> 0.39493164 | AF14: =+'Takeda Ratios'!K17 -> 0.36392835 | AH14: =AVERAGE(H14,R14,W14,AB14) -> 0.6520114 | AI14: =C14 -> -2.5810975 | AJ14: =AVERAGE(I14,S14,X14,AC14) -> 0.54858335 | AK14: =D14 -> 2.0104252 | AL14: =AVERAGE(J14,T14,Y14,AD14) -> 0.53893291 | AM14: =E14 -> 3.2012382 | AN14: =AVERAGE(K14,U14,Z14,AE14) -> 0.5980784 | AO14: =F14 -> 1.8605481 | AP14: =AVERAGE(L14,V14,AA14,AF14) -> 0.64775139 | AQ14: =G14 -> 0.50939765
B15: = Return on Net Operating Assets | C15: =+'BionTech Ratios'!G18 -> 4.2745209 | D15: =+'BionTech Ratios'!H18 -> 0.14528584 | E15: =+'BionTech Ratios'!I18 -> 1.7486885 | F15: =+'BionTech Ratios'!J18 -> 1.0036364 | G15: =+'BionTech Ratios'!K18 -> 0.10359126 | H15: =+'Astra Zeneca Ratios'!G18 -> 0.038294781 | I15: =+'Astra Zeneca Ratios'!H18 -> 0.097862539 | J15: =+'Astra Zeneca Ratios'!I18 -> 0.0021954334 | K15: =+'Astra Zeneca Ratios'!J18 -> 0.05177427 | L15: =+'Astra Zeneca Ratios'!K18 -> 0.092608624 | M15: =+'Moderna Ratios'!G18 -> 14.537755 | N15: =+'Moderna Ratios'!H18 -> 0.68195221 | O15: =+'Moderna Ratios'!I18 -> -6.086792 | P15: =+'Moderna Ratios'!J18 -> 11.205243 | Q15: =+'Moderna Ratios'!K18 -> -1.8377851 | R15: =+'Sanofi Ratios'!G18 -> 0.03785479 | S15: =+'Sanofi Ratios'!H18 -> 0.16223257 | T15: =+'Sanofi Ratios'!I18 -> 0.078544838 | U15: =+'Sanofi Ratios'!J18 -> 0.095799115 | V15: =+'Sanofi Ratios'!K18 -> 0.059770211 | W15: =+'GSK Ratios'!G18 -> 0.13984665 | X15: =+'GSK Ratios'!H18 -> 0.11337771 | Y15: =+'GSK Ratios'!I18 -> 0.083965592 | Z15: =+'GSK Ratios'!J18 -> 0.13868175 | AA15: =+'GSK Ratios'!K18 -> 0.18201593 | AB15: =+'Takeda Ratios'!G18 -> 0.0024019947 | AC15: =+'Takeda Ratios'!H18 -> 0.019635975 | AD15: =+'Takeda Ratios'!I18 -> 0.046790665 | AE15: =+'Takeda Ratios'!J18 -> 0.02776624 | AF15: =+'Takeda Ratios'!K18 -> 0.015950268 | AH15: =AVERAGE(H15,R15,W15,AB15) -> 0.054599555 | AI15: =TEXT(C15, "0%") & "**" -> 427%** | AJ15: =AVERAGE(I15,S15,X15,AC15) -> 0.0982772 | AK15: =D15 -> 0.14528584 | AL15: =AVERAGE(J15,T15,Y15,AD15) -> 0.052874132 | AM15: =E15 -> 1.7486885 | AN15: =AVERAGE(K15,U15,Z15,AE15) -> 0.078505342 | AO15: =F15 -> 1.0036364 | AP15: =AVERAGE(L15,V15,AA15,AF15) -> 0.087586259 | AQ15: =G15 -> 0.10359126
B17: Other key profitability ratios
B18: Gross profit margin | C18: =+'BionTech Ratios'!G44 -> 0.83977901 | D18: =+'BionTech Ratios'!H44 -> 0.87704748 | E18: =+'BionTech Ratios'!I44 -> 0.84657501 | F18: =+'BionTech Ratios'!J44 -> 0.82698462 | G18: =+'BionTech Ratios'!K44 -> 0.84294318 | H18: =+'Astra Zeneca Ratios'!G44 -> 0.80118109 | I18: =+'Astra Zeneca Ratios'!H44 -> 0.8029079 | J18: =+'Astra Zeneca Ratios'!I44 -> 0.67915655 | K18: =+'Astra Zeneca Ratios'!J44 -> 0.80516786 | L18: =+'Astra Zeneca Ratios'!K44 -> 0.82449631 | M18: =+'Moderna Ratios'!G44 -> -7.2666791 | N18: =+'Moderna Ratios'!H44 -> -0.71606449 | O18: =+'Moderna Ratios'!I44 -> 0.75052787 | P18: =+'Moderna Ratios'!J44 -> 0.5477859 | Q18: =+'Moderna Ratios'!K44 -> -0.39281547 | R18: =+'Sanofi Ratios'!G44 -> 0.68175175 | S18: =+'Sanofi Ratios'!H44 -> 0.67604164 | T18: =+'Sanofi Ratios'!I44 -> 0.68727505 | U18: =+'Sanofi Ratios'!J44 -> 0.7055131 | V18: =+'Sanofi Ratios'!K44 -> 0.69303559 | W18: =+'GSK Ratios'!G44 -> 0.68027493 | X18: =+'GSK Ratios'!H44 -> 0.69939229 | Y18: =+'GSK Ratios'!I44 -> 0.67472466 | Z18: =+'GSK Ratios'!J44 -> 0.67920476 | AA18: =+'GSK Ratios'!K44 -> 0.72342389 | AB18: =+'Takeda Ratios'!G44 -> 0.72106007 | AC18: =+'Takeda Ratios'!H44 -> 0.63973568 | AD18: =+'Takeda Ratios'!I44 -> 0.69065874 | AE18: =+'Takeda Ratios'!J44 -> 0.67810995 | AF18: =+'Takeda Ratios'!K44 -> 0.67761089 | AH18: =AVERAGE(H18,R18,W18,AB18) -> 0.72106696 | AI18: =C18 -> 0.83977901 | AJ18: =AVERAGE(I18,S18,X18,AC18) -> 0.70451938 | AK18: =D18 -> 0.87704748 | AL18: =AVERAGE(J18,T18,Y18,AD18) -> 0.68295375 | AM18: =E18 -> 0.84657501 | AN18: =AVERAGE(K18,U18,Z18,AE18) -> 0.71699892 | AO18: =F18 -> 0.82698462 | AP18: =AVERAGE(L18,V18,AA18,AF18) -> 0.72964167 | AQ18: =G18 -> 0.84294318
B19: EBITDA margin | C19: =+'BionTech Ratios'!G45 -> -1.9456722 | D19: =+'BionTech Ratios'!H45 -> -0.2477711 | E19: =+'BionTech Ratios'!I45 -> 0.80500298 | F19: =+'BionTech Ratios'!J45 -> 0.7423024 | G19: =+'BionTech Ratios'!K45 -> 0.26881383 | H19: =+'Astra Zeneca Ratios'!G45 -> -0.015830153 | I19: =+'Astra Zeneca Ratios'!H45 -> 0.068339722 | J19: =+'Astra Zeneca Ratios'!I45 -> -0.094288654 | K19: =+'Astra Zeneca Ratios'!J45 -> -0.039683441 | L19: =+'Astra Zeneca Ratios'!K45 -> 0.071314751 | M19: =+'Moderna Ratios'!G45 -> -10.105243 | N19: =+'Moderna Ratios'!H45 -> -1.1927205 | O19: =+'Moderna Ratios'!I45 -> 0.69896916 | P19: =+'Moderna Ratios'!J45 -> 0.46723082 | Q19: =+'Moderna Ratios'!K45 -> -0.59768452 | R19: =+'Sanofi Ratios'!G45 -> -0.0011161011 | S19: =+'Sanofi Ratios'!H45 -> 0.3053333 | T19: =+'Sanofi Ratios'!I45 -> 0.13268666 | U19: =+'Sanofi Ratios'!J45 -> 0.18214073 | V19: =+'Sanofi Ratios'!K45 -> 0.084093508 | W19: =+'GSK Ratios'!G45 -> 0.14113883 | X19: =+'GSK Ratios'!H45 -> 0.16276587 | Y19: =+'GSK Ratios'!I45 -> 0.090662441 | Z19: =+'GSK Ratios'!J45 -> 0.15359432 | AA19: =+'GSK Ratios'!K45 -> 0.15441182 | AB19: =+'Takeda Ratios'!G45 -> -0.0122057 | AC19: =+'Takeda Ratios'!H45 -> 0.064554723 | AD19: =+'Takeda Ratios'!I45 -> 0.13957242 | AE19: =+'Takeda Ratios'!J45 -> 0.054394059 | AF19: =+'Takeda Ratios'!K45 -> 0.062961157 | AH19: =AVERAGE(H19,R19,W19,AB19) -> 0.027996719 | AI19: =C19 -> -1.9456722 | AJ19: =AVERAGE(I19,S19,X19,AC19) -> 0.1502484 | AK19: =D19 -> -0.2477711 | AL19: =AVERAGE(J19,T19,Y19,AD19) -> 0.067158218 | AM19: =E19 -> 0.80500298 | AN19: =AVERAGE(K19,U19,Z19,AE19) -> 0.087611417 | AO19: =F19 -> 0.7423024 | AP19: =AVERAGE(L19,V19,AA19,AF19) -> 0.093195309 | AQ19: =G19 -> 0.26881383
B21: Asset management ratios
B22: PP&E turnover | C22: =+'BionTech Ratios'!G55 -> 0.82264002 | D22: =+'BionTech Ratios'!H55 -> 2.0304718 | E22: =+'BionTech Ratios'!I55 -> 44.039684 | F22: =+'BionTech Ratios'!J55 -> 25.41192 | G22: =+'BionTech Ratios'!K55 -> 4.057155 | H22: =+'Astra Zeneca Ratios'!G54 -> 2.8826184 | I22: =+'Astra Zeneca Ratios'!H54 -> 2.9046863 | J22: =+'Astra Zeneca Ratios'!I54 -> 3.5606724 | K22: =+'Astra Zeneca Ratios'!J54 -> 4.3295753 | L22: =+'Astra Zeneca Ratios'!K54 -> 4.2103907 | M22: =+'Moderna Ratios'!G54 -> 0.24270031 | N22: =+'Moderna Ratios'!H54 -> 2.45872 | O22: =+'Moderna Ratios'!I54 -> 20.393091 | P22: =+'Moderna Ratios'!J54 -> 11.390819 | Q22: =+'Moderna Ratios'!K54 -> 2.8748262 | R22: =+'Sanofi Ratios'!G54 -> 3.4977924 | S22: =+'Sanofi Ratios'!H54 -> 3.3081622 | T22: =+'Sanofi Ratios'!I54 -> 3.3024236 | U22: =+'Sanofi Ratios'!J54 -> 3.2112182 | V22: =+'Sanofi Ratios'!K54 -> 3.3061766 | W22: =+'GSK Ratios'!G54 -> 2.6853841 | X22: =+'GSK Ratios'!H54 -> 1.9642623 | Y22: =+'GSK Ratios'!I54 -> 2.0507632 | Z22: =+'GSK Ratios'!J54 -> 2.5668748 | AA22: =+'GSK Ratios'!K54 -> 2.7436194 | AB22: =+'Takeda Ratios'!G54 -> 2.9056943 | AC22: =+'Takeda Ratios'!H54 -> 1.9850567 | AD22: =+'Takeda Ratios'!I54 -> 1.9424458 | AE22: =+'Takeda Ratios'!J54 -> 2.0477972 | AF22: =+'Takeda Ratios'!K54 -> 1.9583968 | AH22: =AVERAGE(H22,R22,W22,AB22) -> 2.9928723 | AI22: =C22 -> 0.82264002 | AJ22: =AVERAGE(I22,S22,X22,AC22) -> 2.5405419 | AK22: =D22 -> 2.0304718 | AL22: =AVERAGE(J22,T22,Y22,AD22) -> 2.7140762 | AM22: =E22 -> 44.039684 | AN22: =AVERAGE(K22,U22,Z22,AE22) -> 3.0388664 | AO22: =F22 -> 25.41192 | AP22: =AVERAGE(L22,V22,AA22,AF22) -> 3.0546459 | AQ22: =G22 -> 4.057155
B24: Days’ receivables | C24: =+'BionTech Ratios'!G57 -> 51.134254 | D24: =+'BionTech Ratios'!H57 -> 66.212606 | E24: =+'BionTech Ratios'!I57 -> 119.01416 | F24: =+'BionTech Ratios'!J57 -> 203.04981 | G24: =+'BionTech Ratios'!K57 -> 438.39592 | H24: =+'Astra Zeneca Ratios'!G56 -> 48.013336 | I24: =+'Astra Zeneca Ratios'!H56 -> 48.61867 | J24: =+'Astra Zeneca Ratios'!I56 -> 47.85005 | K24: =+'Astra Zeneca Ratios'!J56 -> 51.413805 | L24: =+'Astra Zeneca Ratios'!K56 -> 60.981837 | M24: =+'Moderna Ratios'!G56 -> 52.979104 | N24: =+'Moderna Ratios'!H56 -> 291.83069 | O24: =+'Moderna Ratios'!I56 -> 45.259302 | P24: =+'Moderna Ratios'!J56 -> 40.48275 | Q24: =+'Moderna Ratios'!K56 -> 60.723784 | R24: =+'Sanofi Ratios'!G56 -> 72.691664 | S24: =+'Sanofi Ratios'!H56 -> 74.314004 | T24: =+'Sanofi Ratios'!I56 -> 69.192597 | U24: =+'Sanofi Ratios'!J56 -> 71.421199 | V24: =+'Sanofi Ratios'!K56 -> 73.810115 | W24: =+'GSK Ratios'!G56 -> 57.37516 | X24: =+'GSK Ratios'!H56 -> 83.399532 | Y24: =+'GSK Ratios'!I56 -> 85.600901 | Z24: =+'GSK Ratios'!J56 -> 71.252592 | AA24: =+'GSK Ratios'!K56 -> 66.965374 | AB24: =+'Takeda Ratios'!G56 -> 73.178707 | AC24: =+'Takeda Ratios'!H56 -> 89.046083 | AD24: =+'Takeda Ratios'!I56 -> 79.111858 | AE24: =+'Takeda Ratios'!J56 -> 65.931628 | AF24: =+'Takeda Ratios'!K56 -> 62.950564 | AH24: =AVERAGE(H24,R24,W24,AB24) -> 62.814717 | AI24: =C24 -> 51.134254 | AJ24: =AVERAGE(I24,S24,X24,AC24) -> 73.844572 | AK24: =D24 -> 66.212606 | AL24: =AVERAGE(J24,T24,Y24,AD24) -> 70.438852 | AM24: =E24 -> 119.01416 | AN24: =AVERAGE(K24,U24,Z24,AE24) -> 65.004806 | AO24: =F24 -> 203.04981 | AP24: =AVERAGE(L24,V24,AA24,AF24) -> 66.176972 | AQ24: =G24 -> 438.39592
B25: Days’ inventories | C25: =+'BionTech Ratios'!G59 -> 181.14828 | D25: =+'BionTech Ratios'!H59 -> 230.1511 | E25: =+'BionTech Ratios'!I59 -> 35.029366 | F25: =+'BionTech Ratios'!J59 -> 56.620367 | G25: =+'BionTech Ratios'!K59 -> 239.26976 | H25: =+'Astra Zeneca Ratios'!G58 -> 223.16319 | I25: =+'Astra Zeneca Ratios'!H58 -> 239.98693 | J25: =+'Astra Zeneca Ratios'!I58 -> 198.30319 | K25: =+'Astra Zeneca Ratios'!J58 -> 269.23669 | L25: =+'Astra Zeneca Ratios'!K58 -> 225.21954 | M25: =+IFERROR('Moderna Ratios'!G58,"N/A") -> N/A | N25: =+'Moderna Ratios'!H58 -> 5.722032 | O25: =+'Moderna Ratios'!I58 -> 71.934791 | P25: =+'Moderna Ratios'!J58 -> 56.74244 | Q25: =+'Moderna Ratios'!K58 -> 26.029634 | R25: =+'Sanofi Ratios'!G58 -> 232.53006 | S25: =+'Sanofi Ratios'!H58 -> 243.04312 | T25: =+'Sanofi Ratios'!I58 -> 250.75994 | U25: =+'Sanofi Ratios'!J58 -> 268.05123 | V25: =+'Sanofi Ratios'!K58 -> 265.68508 | W25: =+'GSK Ratios'!G58 -> 191.82484 | X25: =+'GSK Ratios'!H58 -> 299.59727 | Y25: =+'GSK Ratios'!I58 -> 261.50698 | Z25: =+'GSK Ratios'!J58 -> 206.94158 | AA25: =+'GSK Ratios'!K58 -> 226.50694 | AB25: =+'Takeda Ratios'!G58 -> 203.08273 | AC25: =+'Takeda Ratios'!H58 -> 236.29755 | AD25: =+'Takeda Ratios'!I58 -> 262.69105 | AE25: =+'Takeda Ratios'!J58 -> 249.61842 | AF25: =+'Takeda Ratios'!K58 -> 286.05073 | AH25: =AVERAGE(H25,R25,W25,AB25) -> 212.6502 | AI25: =C25 -> 181.14828 | AJ25: =AVERAGE(I25,S25,X25,AC25) -> 254.73122 | AK25: =D25 -> 230.1511 | AL25: =AVERAGE(J25,T25,Y25,AD25) -> 243.31529 | AM25: =E25 -> 35.029366 | AN25: =AVERAGE(K25,U25,Z25,AE25) -> 248.46198 | AO25: =F25 -> 56.620367 | AP25: =AVERAGE(L25,V25,AA25,AF25) -> 250.86557 | AQ25: =G25 -> 239.26976
B26: Days’ payables | C26: =+'BionTech Ratios'!G61 -> 643.64483 | D26: =+'BionTech Ratios'!H61 -> 372.74266 | E26: =+'BionTech Ratios'!I61 -> 16.216383 | F26: =+'BionTech Ratios'!J61 -> 21.882471 | G26: =+'BionTech Ratios'!K61 -> 167.48583 | H26: =+'Astra Zeneca Ratios'!G60 -> 128.13801 | I26: =+'Astra Zeneca Ratios'!H60 -> 136.98978 | J26: =+'Astra Zeneca Ratios'!I60 -> 78.061439 | K26: =+'Astra Zeneca Ratios'!J60 -> 106.62031 | L26: =+'Astra Zeneca Ratios'!K60 -> 129.30566 | M26: =+'Moderna Ratios'!G60 -> 13.640131 | N26: =+'Moderna Ratios'!H60 -> 3.1322775 | O26: =+'Moderna Ratios'!I60 -> 12.941357 | P26: =+'Moderna Ratios'!J60 -> 15.665963 | Q26: =+'Moderna Ratios'!K60 -> 18.897724 | R26: =+'Sanofi Ratios'!G60 -> 155.62124 | S26: =+'Sanofi Ratios'!H60 -> 157.72675 | T26: =+'Sanofi Ratios'!I60 -> 168.59848 | U26: =+'Sanofi Ratios'!J60 -> 197.04609 | V26: =+'Sanofi Ratios'!K60 -> 201.71012 | W26: =+'GSK Ratios'!G60 -> 130.88676 | X26: =+'GSK Ratios'!H60 -> 213.12799 | Y26: =+'GSK Ratios'!I60 -> 197.65539 | Z26: =+'GSK Ratios'!J60 -> 159.16614 | AA26: =+'GSK Ratios'!K60 -> 161.27504 | AB26: =+'Takeda Ratios'!G60 -> 107.95345 | AC26: =+'Takeda Ratios'!H60 -> 96.005125 | AD26: =+'Takeda Ratios'!I60 -> 114.90617 | AE26: =+'Takeda Ratios'!J60 -> 105.23813 | AF26: =+'Takeda Ratios'!K60 -> 117.94975 | AH26: =AVERAGE(H26,R26,W26,AB26) -> 130.64987 | AI26: =C26 -> 643.64483 | AJ26: =AVERAGE(I26,S26,X26,AC26) -> 150.96241 | AK26: =D26 -> 372.74266 | AL26: =AVERAGE(J26,T26,Y26,AD26) -> 139.80537 | AM26: =E26 -> 16.216383 | AN26: =AVERAGE(K26,U26,Z26,AE26) -> 142.01767 | AO26: =F26 -> 21.882471 | AP26: =AVERAGE(L26,V26,AA26,AF26) -> 152.56014 | AQ26: =G26 -> 167.48583
B27: Cash conversion cycle | C27: =+'BionTech Ratios'!G62 -> -411.3623 | D27: =+'BionTech Ratios'!H62 -> -76.378962 | E27: =+'BionTech Ratios'!I62 -> 137.82714 | F27: =+'BionTech Ratios'!J62 -> 237.7877 | G27: =+'BionTech Ratios'!K62 -> 510.17984 | H27: =+'Astra Zeneca Ratios'!G61 -> 143.03851 | I27: =+'Astra Zeneca Ratios'!H61 -> 151.61582 | J27: =+'Astra Zeneca Ratios'!I61 -> 168.09181 | K27: =+'Astra Zeneca Ratios'!J61 -> 214.03018 | L27: =+'Astra Zeneca Ratios'!K61 -> 156.89572 | M27: =+IFERROR('Moderna Ratios'!G61,"N/A") -> N/A | N27: =+'Moderna Ratios'!H61 -> 294.42044 | O27: =+'Moderna Ratios'!I61 -> 104.25274 | P27: =+'Moderna Ratios'!J61 -> 81.559227 | Q27: =+'Moderna Ratios'!K61 -> 67.855694 | R27: =+'Sanofi Ratios'!G61 -> 149.60048 | S27: =+'Sanofi Ratios'!H61 -> 159.63038 | T27: =+'Sanofi Ratios'!I61 -> 151.35405 | U27: =+'Sanofi Ratios'!J61 -> 142.42634 | V27: =+'Sanofi Ratios'!K61 -> 137.78507 | W27: =+'GSK Ratios'!G61 -> 118.31324 | X27: =+'GSK Ratios'!H61 -> 169.86881 | Y27: =+'GSK Ratios'!I61 -> 149.45249 | Z27: =+'GSK Ratios'!J61 -> 119.02804 | AA27: =+'GSK Ratios'!K61 -> 132.19727 | AB27: =+'Takeda Ratios'!G61 -> 168.30798 | AC27: =+'Takeda Ratios'!H61 -> 229.33851 | AD27: =+'Takeda Ratios'!I61 -> 226.89674 | AE27: =+'Takeda Ratios'!J61 -> 210.31192 | AF27: =+'Takeda Ratios'!K61 -> 231.05154 | AH27: =AVERAGE(H27,R27,W27,AB27) -> 144.81505 | AI27: =C27 -> -411.3623 | AJ27: =AVERAGE(I27,S27,X27,AC27) -> 177.61338 | AK27: =D27 -> -76.378962 | AL27: =AVERAGE(J27,T27,Y27,AD27) -> 173.94877 | AM27: =E27 -> 137.82714 | AN27: =AVERAGE(K27,U27,Z27,AE27) -> 171.44912 | AO27: =F27 -> 237.7877 | AP27: =AVERAGE(L27,V27,AA27,AF27) -> 164.4824 | AQ27: =G27 -> 510.17984
B29: Solvency ratios
B30: Debt-to-equity | C30: =+'BionTech Ratios'!G74 -> 0.097582881 | D30: =+'BionTech Ratios'!H74 -> 0.16850498 | E30: =+'BionTech Ratios'!I74 -> 0.040827711 | F30: =+'BionTech Ratios'!J74 -> 0.0160786 | G30: =+'BionTech Ratios'!K74 -> 0.010701835 | H30: =+'Astra Zeneca Ratios'!G73 -> 1.6311232 | I30: =+'Astra Zeneca Ratios'!H73 -> 1.62418 | J30: =+'Astra Zeneca Ratios'!I73 -> 1.1130268 | K30: =+'Astra Zeneca Ratios'!J73 -> 0.89164405 | L30: =+'Astra Zeneca Ratios'!K73 -> 0.83334241 | M30: =+'Moderna Ratios'!G73 -> 0.063100118 | N30: =+'Moderna Ratios'!H73 -> 0.10026805 | O30: =+'Moderna Ratios'!I73 -> 0.068760944 | P30: =+'Moderna Ratios'!J73 -> 0.063574341 | Q30: =+'Moderna Ratios'!K73 -> 0.073861217 | R30: =+'Sanofi Ratios'!G73 -> 0.48785355 | S30: =+'Sanofi Ratios'!H73 -> 0.4611698 | T30: =+'Sanofi Ratios'!I73 -> 0.39546276 | U30: =+'Sanofi Ratios'!J73 -> 0.3371618 | V30: =+'Sanofi Ratios'!K73 -> 0.2935554 | W30: =+'GSK Ratios'!G73 -> 2.8183341 | X30: =+'GSK Ratios'!H73 -> 1.6588459 | Y30: =+'GSK Ratios'!I73 -> 1.3748711 | Z30: =+'GSK Ratios'!J73 -> 1.6051355 | AA30: =+'GSK Ratios'!K73 -> 1.9148282 | AB30: =+'Takeda Ratios'!G73 -> 1.235481 | AC30: =+'Takeda Ratios'!H73 -> 1.1778722 | AD30: =+'Takeda Ratios'!I73 -> 0.99990007 | AE30: =+'Takeda Ratios'!J73 -> 0.82190953 | AF30: =+'Takeda Ratios'!K73 -> 0.79493856 | AH30: =AVERAGE(H30,R30,W30,AB30) -> 1.543198 | AI30: =C30 -> 0.097582881 | AJ30: =AVERAGE(I30,S30,X30,AC30) -> 1.230517 | AK30: =D30 -> 0.16850498 | AL30: =AVERAGE(J30,T30,Y30,AD30) -> 0.97081516 | AM30: =E30 -> 0.040827711 | AN30: =AVERAGE(K30,U30,Z30,AE30) -> 0.91396271 | AO30: =F30 -> 0.0160786 | AP30: =AVERAGE(L30,V30,AA30,AF30) -> 0.95916614 | AQ30: =G30 -> 0.010701835
B31: Debt-to-invested capital | C31: =+'BionTech Ratios'!G75 -> 0.088907072 | D31: =+'BionTech Ratios'!H75 -> 0.14420562 | E31: =+'BionTech Ratios'!I75 -> 0.039226195 | F31: =+'BionTech Ratios'!J75 -> 0.015824169 | G31: =+'BionTech Ratios'!K75 -> 0.010588518 | H31: =+'Astra Zeneca Ratios'!G74 -> 0.61993418 | I31: =+'Astra Zeneca Ratios'!H74 -> 0.61892857 | J31: =+'Astra Zeneca Ratios'!I74 -> 0.52674523 | K31: =+'Astra Zeneca Ratios'!J74 -> 0.47135932 | L31: =+'Astra Zeneca Ratios'!K74 -> 0.45454815 | M31: =+'Moderna Ratios'!G74 -> 0.059354821 | N31: =+'Moderna Ratios'!H74 -> 0.091130564 | O31: =+'Moderna Ratios'!I74 -> 0.064337066 | P31: =+'Moderna Ratios'!J74 -> 0.059774234 | Q31: =+'Moderna Ratios'!K74 -> 0.068780971 | R31: =+'Sanofi Ratios'!G74 -> 0.32789084 | S31: =+'Sanofi Ratios'!H74 -> 0.31561685 | T31: =+'Sanofi Ratios'!I74 -> 0.28339184 | U31: =+'Sanofi Ratios'!J74 -> 0.25214735 | V31: =+'Sanofi Ratios'!K74 -> 0.22693686 | W31: =+'GSK Ratios'!G74 -> 0.73810568 | X31: =+'GSK Ratios'!H74 -> 0.62389697 | Y31: =+'GSK Ratios'!I74 -> 0.57892451 | Z31: =+'GSK Ratios'!J74 -> 0.6161428 | AA31: =+'GSK Ratios'!K74 -> 0.6569266 | AB31: =+'Takeda Ratios'!G74 -> 0.55266898 | AC31: =+'Takeda Ratios'!H74 -> 0.54083623 | AD31: =+'Takeda Ratios'!I74 -> 0.49997502 | AE31: =+'Takeda Ratios'!J74 -> 0.45112533 | AF31: =+'Takeda Ratios'!K74 -> 0.44287787 | AH31: =AVERAGE(H31,R31,W31,AB31) -> 0.55964992 | AI31: =C31 -> 0.088907072 | AJ31: =AVERAGE(I31,S31,X31,AC31) -> 0.52481965 | AK31: =D31 -> 0.14420562 | AL31: =AVERAGE(J31,T31,Y31,AD31) -> 0.47225915 | AM31: =E31 -> 0.039226195 | AN31: =AVERAGE(K31,U31,Z31,AE31) -> 0.4476937 | AO31: =F31 -> 0.015824169 | AP31: =AVERAGE(L31,V31,AA31,AF31) -> 0.44532237 | AQ31: =G31 -> 0.010588518
B32: Interest coverage (earnings based) | C32: =+'BionTech Ratios'!G76 -> 87.7 | D32: =+'BionTech Ratios'!H76 -> 0.24307692 | E32: =+'BionTech Ratios'!I76 -> -51.31629 | F32: =+'BionTech Ratios'!J76 -> -687.40212 | G32: =+'BionTech Ratios'!K76 -> -51.627615 | H32: =+'Astra Zeneca Ratios'!G75 -> -3.9846139 | I32: =+'Astra Zeneca Ratios'!H75 -> -7.306234 | J32: =+'Astra Zeneca Ratios'!I75 -> -1.6585057 | K32: =+'Astra Zeneca Ratios'!J75 -> -4.7273693 | L32: =+'Astra Zeneca Ratios'!K75 -> -7.6595548 | M32: =+IFERROR('Moderna Ratios'!G75,"N/A") -> N/A | N32: =+'Moderna Ratios'!H75 -> 72.402577 | O32: =+'Moderna Ratios'!I75 -> -783.4839 | P32: =+'Moderna Ratios'!J75 -> -332.17392 | Q32: =+'Moderna Ratios'!K75 -> 101.73629 | R32: =+'Sanofi Ratios'!G75 -> -7.5275735 | S32: =+'Sanofi Ratios'!H75 -> -32.799564 | T32: =+'Sanofi Ratios'!I75 -> -23.649171 | U32: =+'Sanofi Ratios'!J75 -> -26.855721 | V32: =+'Sanofi Ratios'!K75 -> -12.382003 | W32: =+'GSK Ratios'!G75 -> -9.0935 | X32: =+'GSK Ratios'!H75 -> -8.125592 | Y32: =+'GSK Ratios'!I75 -> -6.7230976 | Z32: =+'GSK Ratios'!J75 -> -8.8717923 | AA32: =+'GSK Ratios'!K75 -> -10.540843 | AB32: =+'Takeda Ratios'!G75 -> -1.8134132 | AC32: =+'Takeda Ratios'!H75 -> -2.5530348 | AD32: =+'Takeda Ratios'!I75 -> -6.2806327 | AE32: =+'Takeda Ratios'!J75 -> -4.5850221 | AF32: =+'Takeda Ratios'!K75 -> -2.8923008 | AH32: =AVERAGE(H32,R32,W32,AB32) -> -5.6047752 | AI32: =C32 -> 87.7 | AJ32: =AVERAGE(I32,S32,X32,AC32) -> -12.696106 | AK32: =D32 -> 0.24307692 | AL32: =AVERAGE(J32,T32,Y32,AD32) -> -9.5778518 | AM32: =E32 -> -51.31629 | AN32: =AVERAGE(K32,U32,Z32,AE32) -> -11.259976 | AO32: =F32 -> -687.40212 | AP32: =AVERAGE(L32,V32,AA32,AF32) -> -8.3686754 | AQ32: =G32 -> -51.627615
B34: Sustainable growth rate
B35: ROE | C35: =+'BionTech Ratios'!G83 -> -0.47127386 | D35: =+'BionTech Ratios'!H83 -> 0.016297716 | E35: =+'BionTech Ratios'!I83 -> 1.5517696 | F35: =+'BionTech Ratios'!J83 -> 0.59058571 | G35: =+'BionTech Ratios'!K83 -> 0.046167016 | H35: =+'Astra Zeneca Ratios'!G82 -> 0.086743921 | I35: =+'Astra Zeneca Ratios'!H82 -> 0.21385319 | J35: =+'Astra Zeneca Ratios'!I82 -> 0.0041109993 | K35: =+'Astra Zeneca Ratios'!J82 -> 0.090513366 | L35: =+'Astra Zeneca Ratios'!K82 -> 0.15727334 | M35: =+'Moderna Ratios'!G82 -> -0.385313 | N35: =+'Moderna Ratios'!H82 -> -0.41726965 | O35: =+'Moderna Ratios'!I82 -> 1.4207041 | P35: =+'Moderna Ratios'!J82 -> 0.52453725 | Q35: =+'Moderna Ratios'!K82 -> -0.2865739 | R35: =+'Sanofi Ratios'!G82 -> 0.048805648 | S35: =+'Sanofi Ratios'!H82 -> 0.20133571 | T35: =+'Sanofi Ratios'!I82 -> 0.094932833 | U35: =+'Sanofi Ratios'!J82 -> 0.1121214 | V35: =+'Sanofi Ratios'!K82 -> 0.068198388 | W35: =+'GSK Ratios'!G82 -> 0.46652018 | X35: =+'GSK Ratios'!H82 -> 0.25582575 | Y35: =+'GSK Ratios'!I82 -> 0.16821699 | Z35: =+'GSK Ratios'!J82 -> 0.31380252 | AA35: =+'GSK Ratios'!K82 -> 0.46723005 | AB35: =+'Takeda Ratios'!G82 -> 0.003921598 | AC35: =+'Takeda Ratios'!H82 -> 0.038659779 | AD35: =+'Takeda Ratios'!I82 -> 0.087236598 | AE35: =+'Takeda Ratios'!J82 -> 0.047119107 | AF35: =+'Takeda Ratios'!K82 -> 0.027004856 | AH35: =AVERAGE(H35,R35,W35,AB35) -> 0.15149784 | AI35: =C35 -> -0.47127386 | AJ35: =AVERAGE(I35,S35,X35,AC35) -> 0.17741861 | AK35: =D35 -> 0.016297716 | AL35: =AVERAGE(J35,T35,Y35,AD35) -> 0.088624355 | AM35: =E35 -> 1.5517696 | AN35: =AVERAGE(K35,U35,Z35,AE35) -> 0.1408891 | AO35: =F35 -> 0.59058571 | AP35: =AVERAGE(L35,V35,AA35,AF35) -> 0.17992666 | AQ35: =G35 -> 0.046167016
B36: × Dividend payout ratio | C36: =+'BionTech Ratios'!G84 -> 0 | D36: =+'BionTech Ratios'!H84 -> 0 | E36: =+'BionTech Ratios'!I84 -> 0 | F36: =+'BionTech Ratios'!J84 -> 0.051333418 | G36: =+'BionTech Ratios'!K84 -> 0 | H36: =+'Astra Zeneca Ratios'!G83 -> 2.9274696 | I36: =+'Astra Zeneca Ratios'!H83 -> 1.1361328 | J36: =+'Astra Zeneca Ratios'!I83 -> 33.5304 | K36: =+'Astra Zeneca Ratios'!J83 -> 1.362284 | L36: =+'Astra Zeneca Ratios'!K83 -> 0.75339713 | M36: =+'Moderna Ratios'!G83 -> 0 | N36: =+'Moderna Ratios'!H83 -> 0 | O36: =+'Moderna Ratios'!I83 -> 0 | P36: =+'Moderna Ratios'!J83 -> 0 | Q36: =+'Moderna Ratios'!K83 -> 0 | R36: =+'Sanofi Ratios'!G83 -> 1.3284823 | S36: =+'Sanofi Ratios'!H83 -> 0.31930251 | T36: =+'Sanofi Ratios'!I83 -> 0.6383182 | U36: =+'Sanofi Ratios'!J83 -> 0.51565013 | V36: =+'Sanofi Ratios'!K83 -> 0.87367595 | W36: =+'GSK Ratios'!G83 -> 0 | X36: =+'GSK Ratios'!H83 -> 0 | Y36: =+'GSK Ratios'!I83 -> 0 | Z36: =+'GSK Ratios'!J83 -> 0 | AA36: =+'GSK Ratios'!K83 -> 0 | AB36: =+'Takeda Ratios'!G83 -> 20.917647 | AC36: =+'Takeda Ratios'!H83 -> 1.5671108 | AD36: =+'Takeda Ratios'!I83 -> 0.64215133 | AE36: =+'Takeda Ratios'!J83 -> 1.0186167 | AF36: =+'Takeda Ratios'!K83 -> 1.6177063 | AH36: =AVERAGE(H36,R36,W36,AB36) -> 6.2933997 | AI36: =C36 -> 0 | AJ36: =AVERAGE(I36,S36,X36,AC36) -> 0.75563653 | AK36: =D36 -> 0 | AL36: =AVERAGE(J36,T36,Y36,AD36) -> 8.7027175 | AM36: =E36 -> 0 | AN36: =AVERAGE(K36,U36,Z36,AE36) -> 0.7241377 | AO36: =F36 -> 0.051333418 | AP36: =AVERAGE(L36,V36,AA36,AF36) -> 0.81119485 | AQ36: =G36 -> 0
A37: x | B37: Sustainable growth rate | C37: =+'BionTech Ratios'!G85 -> -0.47127386 | D37: =+'BionTech Ratios'!H85 -> 0.016297716 | E37: =+'BionTech Ratios'!I85 -> 1.5517696 | F37: =+'BionTech Ratios'!J85 -> 0.56026893 | G37: =+'BionTech Ratios'!K85 -> 0.046167016 | H37: =+'Astra Zeneca Ratios'!G84 -> -0.16719627 | I37: =+'Astra Zeneca Ratios'!H84 -> -0.029112433 | J37: =+'Astra Zeneca Ratios'!I84 -> -0.13373245 | K37: =+'Astra Zeneca Ratios'!J84 -> -0.032791541 | L37: =+'Astra Zeneca Ratios'!K84 -> 0.038784058 | M37: {=IFERROR(+'Moderna Ratios'!G84,_xleta.N/A)} -> -0.385313 | N37: =+'Moderna Ratios'!H84 -> -0.41726965 | O37: =+'Moderna Ratios'!I84 -> 1.4207041 | P37: =+'Moderna Ratios'!J84 -> 0.52453725 | Q37: =+'Moderna Ratios'!K84 -> -0.2865739 | R37: =+'Sanofi Ratios'!G84 -> -0.016031793 | S37: =+'Sanofi Ratios'!H84 -> 0.13704871 | T37: =+'Sanofi Ratios'!I84 -> 0.034335478 | U37: =+'Sanofi Ratios'!J84 -> 0.054305986 | V37: =+'Sanofi Ratios'!K84 -> 0.0086150965 | W37: =+'GSK Ratios'!G84 -> 0.46652018 | X37: =+'GSK Ratios'!H84 -> 0.25582575 | Y37: =+'GSK Ratios'!I84 -> 0.16821699 | Z37: =+'GSK Ratios'!J84 -> 0.31380252 | AA37: =+'GSK Ratios'!K84 -> 0.46723005 | AB37: =+'Takeda Ratios'!G84 -> -0.078109003 | AC37: =+'Takeda Ratios'!H84 -> -0.021924379 | AD37: =+'Takeda Ratios'!I84 -> 0.0312175 | AE37: =+'Takeda Ratios'!J84 -> -0.00087720176 | AF37: =+'Takeda Ratios'!K84 -> -0.01668107 | AH37: =AVERAGE(H37,R37,W37,AB37) -> 0.051295779 | AI37: =C37 -> -0.47127386 | AJ37: =AVERAGE(I37,S37,X37,AC37) -> 0.085459413 | AK37: =D37 -> 0.016297716 | AL37: =AVERAGE(J37,T37,Y37,AD37) -> 0.025009379 | AM37: =E37 -> 1.5517696 | AN37: =AVERAGE(K37,U37,Z37,AE37) -> 0.08360994 | AO37: =F37 -> 0.56026893 | AP37: =AVERAGE(L37,V37,AA37,AF37) -> 0.12448703 | AQ37: =G37 -> 0.046167016

Sheet Football field
B2: Comps
B3: Metric | D3: Comps | F3: EV | G3: Net Debt | H3: Equity Value | I3: Shares | J3: Share Price | L3: Key Assumptions
B4: EV/ NTM Revenue | D4: ='Public comps'!J16 -> 2.7870309 | F4: =$Q4*D4 -> 7803.6865 | G4: =($N$6-$N$7) -> -15838.037 | H4: =+F4-G4 -> 23641.723 | I4: =$N$5 -> 239.9708 | J4: =H4/I4 -> 98.519165 | L4: Current Price | N4: ='DCF Model with IRR'!C25 -> 93.14232 | P4: Revenue (NTM) | Q4: ='DCF Model with IRR'!$H$31 -> 2800
B5: EV/ LTM Revenue | D5: ='Public comps'!H16 -> 2.4898284 | F5: =$Q5*D5 -> 9508.6545 | G5: =($N$6-$N$7) -> -15838.037 | H5: =+F5-G5 -> 25346.691 | I5: =$N$5 -> 239.9708 | J5: =H5/I5 -> 105.62406 | L5: Shares Outstanding (m) | N5: ='DCF Model with IRR'!C26 -> 239.9708 | P5: Revenue (LTM) | Q5: ='DCF Model with IRR'!$G$31 -> 3819
B6: P/E | D6: n.a. | L6: Net Debt ($000) | N6: =('Public comps'!F5-'Public comps'!E5) -> -15838.037 | P6: EBIT | Q6: ='DCF Model with IRR'!G39 -> 690.4
P7: Earnings | Q7: ='Public comps'!R5 -> -1207.431
B8: Lo | H8: =MIN(H4:H6) -> 23641.723 | I8: =$N$5 -> 239.9708 | J8: =H8/I8 -> 98.519165
B9: Hi | H9: =MAX(H4:H6) -> 25346.691 | I9: =$N$5 -> 239.9708 | J9: =H9/I9 -> 105.62406
B12: Football Field Data
D13: lo | E13: lo | F13: hi | G13: hi | J13: Price (model)
B14: Comps | D14: =J8 -> 98.519165 | E14: =J8 -> 98.519165 | F14: =J9 -> 105.62406 | G14: =J9 -> 105.62406 | J14: =AVERAGE(J4:J5) -> 102.07161
B15: PV of FCF | D15: =E15 -> 56.260757 | E15: =J15*$E$17 -> 56.260757 | F15: =J15*$F$17 -> 68.763148 | G15: =F15 -> 68.763148 | J15: ='DCF Model with IRR'!C64 -> 62.511953
B16: PV of ANOPAT | D16: =E16 -> 62.379103 | E16: =J16*$E$17 -> 62.379103 | F16: =J16*$F$17 -> 76.241126 | G16: =F16 -> 76.241126 | J16: ='DCF Model with IRR'!C90 -> 69.310114
E17: 0.9 | F17: 1.1 | I17: Avg. | J17: =AVERAGE(J14:J16) -> 77.96456
B21: Valuation Summary

Sheet >>>Valuation>>>

Sheet DCF Model with IRR
C2: Historicals | H2: Forecast
C3: 2019 | D3: =C3+1 -> 2020 | E3: =D3+1 -> 2021 | F3: =E3+1 -> 2022 | G3: =F3+1 -> 2023 | H3: =G3+1 -> 2024 | I3: =H3+1 -> 2025 | J3: =I3+1 -> 2026 | K3: =J3+1 -> 2027 | L3: =K3+1 -> 2028
H4: 1 | I4: 2 | J4: 3 | K4: 4 | L4: 5
A5: x | B5: Assumptions
B7: Income Statement
B8: Revenue Growth (% YoY) | C8: =('BionTech Adjusted'!G8/'BionTech Adjusted'!F8)-1 -> -0.14873604 | D8: =('BionTech Adjusted'!H8/'BionTech Adjusted'!G8)-1 -> 3.4410681 | E8: =('BionTech Adjusted'!I8/'BionTech Adjusted'!H8)-1 -> 38.346258 | F8: =('BionTech Adjusted'!J8/'BionTech Adjusted'!I8)-1 -> -0.087797141 | G8: =('BionTech Adjusted'!K8/'BionTech Adjusted'!J8)-1 -> -0.77938373 | H8: =('Revenue forecasts'!C46/G31)-1 -> -0.26682378 | I8: =('Revenue forecasts'!D46/'Revenue forecasts'!C46)-1 -> -0.19642857 | J8: =('Revenue forecasts'!E46/'Revenue forecasts'!D46)-1 -> -0.032222222 | K8: =('Revenue forecasts'!F46/'Revenue forecasts'!E46)-1 -> -0.085258324 | L8: =('Revenue forecasts'!G46/'Revenue forecasts'!F46)-1 -> 0.032168587 | M8: > Calculated in Revenue Forcast Sheet
B9: Cost of Goods Sold (% of Revenue) | C9: =C32/C31 -> -0.16022099 | D9: =D32/D31 -> -0.12295252 | E9: =E32/E31 -> -0.15342499 | F9: =F32/F31 -> -0.17301538 | G9: =G32/G31 -> -0.15705682 | H9: =AVERAGE(C9:G9) -> -0.15333414 | I9: =H9 -> -0.15333414 | J9: =I9 -> -0.15333414 | K9: =J9 -> -0.15333414 | L9: =K9 -> -0.15333414 | M9: > Based on Average of prior 5 years
B11: SG&A (% of Revenue) | C11: =C36/C31 -> -0.44383057 | D11: =D36/D31 -> -0.22496372 | E11: =E36/E31 -> -0.017242197 | F11: =F36/F31 -> -0.031264081 | G11: =G36/G31 -> -0.14603299 | H11: =G11 -> -0.14603299 | I11: =H11 -> -0.14603299 | J11: =I11 -> -0.14603299 | K11: =J11 -> -0.14603299 | L11: =K11 -> -0.14603299 | M11: > remains flat
B12: R&D (% of Revenue) | C12: =-C37/C31 -> 2.0856354 | D12: =-D37/D31 -> 1.3373419 | E12: =-E37/E31 -> 0.050019234 | F12: =-F37/F31 -> 0.088789528 | G12: =-G37/G31 -> 0.46690233 | H12: 0.8 | I12: 1.1764978 | J12: 1.1476739 | K12: 1.2021688 | L12: 1.1771782 | M12: > Analyst consensus
B13: Other Operating Income/ Expenses (% of Revenue) | C13: =C38/C31 -> 0.018416206 | D13: =D38/D31 -> 0.51441012 | E13: =E38/E31 -> 0.02608462 | F13: =F38/F31 -> 0.0234134 | G13: =G38/G31 -> -0.049227546 | H13: 0.02 | I13: 0.02 | J13: 0.02 | K13: 0.02 | L13: 0.02
B15: Other
B16: Tax Rate | H16: 0.3 | I16: 0.3 | J16: 0.3 | K16: 0.3 | L16: 0.3 | M16: > German tax rate
A18: x | B18: PV of FCF Valuation
B20: Assumptions
B21: Tax Rate | C21: ='WACC Analysis'!C12 -> 0.3
B22: WACC | C22: ='WACC Analysis'!C19 -> 0.086676583
B23: Perpetural Growth Rate | C23: 0.02
B24: EV / NTM Revenue Multiple | C24: ='Public comps'!J16 -> 2.7870309
B25: Current Price | C25: ='Public comps'!C5 -> 93.14232 | D25: *As of 25/03/2025
B26: Shares Outstanding (m) | C26: ='Public comps'!D5 -> 239.9708
B27: Cash | C27: ='BionTech Adjusted'!AM45 -> 11663.7
B28: Debt | C28: =SUM('BionTech Adjusted'!AN57,'BionTech Adjusted'!AN64) -> 0
B29: Terminal Revenue Growth Rate | C29: 0.05
B31: Revenue | C31: ='BionTech Adjusted'!AI8 -> 108.6 | D31: ='BionTech Adjusted'!AJ8 -> 482.3 | E31: ='BionTech Adjusted'!AK8 -> 18976.7 | F31: ='BionTech Adjusted'!AL8 -> 17310.6 | G31: ='BionTech Adjusted'!AM8 -> 3819 | H31: ='Revenue forecasts'!C46 -> 2800 | I31: ='Revenue forecasts'!D46 -> 2250 | J31: ='Revenue forecasts'!E46 -> 2177.5 | K31: ='Revenue forecasts'!F46 -> 1991.85 | L31: ='Revenue forecasts'!G46 -> 2055.925
B32: Cost of Goods Sold (COGS) | C32: ='BionTech Adjusted'!AI24 -> -17.4 | D32: ='BionTech Adjusted'!AJ24 -> -59.3 | E32: ='BionTech Adjusted'!AK24 -> -2911.5 | F32: ='BionTech Adjusted'!AL24 -> -2995 | G32: ='BionTech Adjusted'!AM24 -> -599.8 | H32: =H31*H9 -> -429.33559 | I32: =I31*I9 -> -345.00182 | J32: =J31*J9 -> -333.88509 | K32: =K31*K9 -> -305.41861 | L32: =L31*L9 -> -315.24349
B33: Gross Profit | C33: =C31+C32 -> 91.2 | D33: =D31+D32 -> 423 | E33: =E31+E32 -> 16065.2 | F33: =F31+F32 -> 14315.6 | G33: =G31+G32 -> 3219.2 | H33: =H31+H32 -> 2370.6644 | I33: =I31+I32 -> 1904.9982 | J33: =J31+J32 -> 1843.6149 | ... L33: =L31+L32 -> 1740.6815
B34: Gross Margin (%) | C34: =C33/C31 -> 0.83977901 | D34: =D33/D31 -> 0.87704748 | E34: =E33/E31 -> 0.84657501 | F34: =F33/F31 -> 0.82698462 | G34: =G33/G31 -> 0.84294318 | H34: =H33/H31 -> 0.84666586 | I34: =I33/I31 -> 0.84666586 | J34: =J33/J31 -> 0.84666586 | ... L34: =L33/L31 -> 0.84666586
B35: Operating Income/Expenses | C35: =SUM(C36:C38) -> -272.7 | D35: =SUM(D36:D38) -> -505.4 | E35: =SUM(E36:E38) -> -781.4 | F35: =SUM(F36:F38) -> -1672.9 | G35: =SUM(G36:G38) -> -2528.8 | H35: =SUM(H36:H38) -> -2592.8924 | I35: =SUM(I36:I38) -> -2930.6942 | J35: =SUM(J36:J38) -> -2773.4968 | ... L35: =SUM(L36:L38) -> -2679.3044
B36: SG&A | C36: ='BionTech Adjusted'!AI25 -> -48.2 | D36: ='BionTech Adjusted'!AJ25 -> -108.5 | E36: ='BionTech Adjusted'!AK25 -> -327.2 | F36: ='BionTech Adjusted'!AL25 -> -541.2 | G36: ='BionTech Adjusted'!AM25 -> -557.7 | H36: =H$31*H11 -> -408.89238 | I36: =I$31*I11 -> -328.57423 | J36: =J$31*J11 -> -317.98684 | K36: =K$31*K11 -> -290.87582 | L36: =L$31*L11 -> -300.23288
B37: R&D | C37: ='BionTech Adjusted'!AI26 -> -226.5 | D37: ='BionTech Adjusted'!AJ26 -> -645 | E37: ='BionTech Adjusted'!AK26 -> -949.2 | F37: ='BionTech Adjusted'!AL26 -> -1537 | G37: ='BionTech Adjusted'!AM26 -> -1783.1 | H37: =-H12*H31 -> -2240 | I37: =-I12*I31 -> -2647.12 | J37: =-J12*J31 -> -2499.06 | K37: =-K12*K31 -> -2394.54 | L37: =-L12*L31 -> -2420.19
B38: Other Operating Income/Expenses | C38: ='BionTech Adjusted'!AI27 -> 2 | D38: ='BionTech Adjusted'!AJ27 -> 248.1 | E38: ='BionTech Adjusted'!AK27 -> 495 | F38: ='BionTech Adjusted'!AL27 -> 405.3 | G38: ='BionTech Adjusted'!AM27 -> -188 | H38: =H$31*H13 -> 56 | I38: =I$31*I13 -> 45 | J38: =J$31*J13 -> 43.55 | K38: =K$31*K13 -> 39.837 | L38: =L$31*L13 -> 41.1185
B39: Operating Profit | C39: =C33+C35 -> -181.5 | D39: =D33+D35 -> -82.4 | E39: =E33+E35 -> 15283.8 | F39: =F33+F35 -> 12642.7 | G39: =G33+G35 -> 690.4 | H39: =H33+H35 -> -222.22797 | I39: =I33+I35 -> -1025.6961 | J39: =J33+J35 -> -929.88193 | ... L39: =L33+L35 -> -938.62287
B40: Operating Margin (%) | C40: =C39/C31 -> -1.6712707 | D40: =D39/D31 -> -0.17084802 | E40: =E39/E31 -> 0.8053982 | F40: =F39/F31 -> 0.73034441 | G40: =G39/G31 -> 0.18078031 | H40: =H39/H31 -> -0.079367133 | I40: =I39/I31 -> -0.45586491 | J40: =J39/J31 -> -0.42704107 | ... L40: =L39/L31 -> -0.45654529
B41: Taxes | C41: ='BionTech Adjusted'!AI16 -> 0.2 | D41: ='BionTech Adjusted'!AJ16 -> 161 | E41: ='BionTech Adjusted'!AK16 -> -4753.9 | F41: ='BionTech Adjusted'!AL16 -> -3519.7 | G41: ='BionTech Adjusted'!AM16 -> -255.8 | H41: =-H39*(H16) -> 66.668392 | I41: =-I39*(I16) -> 307.70882 | J41: =-J39*(J16) -> 278.96458 | K41: =-K39*(K16) -> 287.74423 | L41: =-L39*(L16) -> 281.58686
B42: NOPAT | C42: =SUM(C39:C41) -> -182.97127 | D42: =SUM(D39:D41) -> 78.429152 | E42: =SUM(E39:E41) -> 10530.705 | F42: =SUM(F39:F41) -> 9123.7303 | G42: =SUM(G39:G41) -> 434.78078 | H42: =SUM(H39:H41) -> -155.63895 | I42: =SUM(I39:I41) -> -718.4431 | J42: =SUM(J39:J41) -> -651.34439 | ... L42: =SUM(L39:L41) -> -657.49256
B43: Plus: D&A | H43: =-H117 -> 134.4 | I43: =-I117 -> 108 | J43: =-J117 -> 104.52 | K43: =-K117 -> 95.6088 | L43: =-L117 -> 98.6844
B44: Less: Capex | H44: =-H116 -> -168 | I44: =-I116 -> -135 | J44: =-J116 -> -130.65 | K44: =-K116 -> -119.511 | L44: =-L116 -> -123.3555
B45: Less: Changes in NWC | H45: =H107 -> 1677.8075 | I45: =I107 -> 94.598522 | J45: =J107 -> 12.469805 | K45: =K107 -> 31.931301 | L45: =L107 -> -11.020728
B46: Free Cash Flow | H46: =SUM(H42:H45) -> 1488.5686 | I46: =SUM(I42:I45) -> -650.84458 | J46: =SUM(J42:J45) -> -665.00459 | K46: =SUM(K42:K45) -> -663.85563 | L46: =SUM(L42:L45) -> -693.18438
B48: Discounted Free Cash Flow | H48: =H46/(1+$C$22)^H4 -> 1369.8359 | I48: =I46/(1+$C$22)^I4 -> -551.15871 | J48: =J46/(1+$C$22)^J4 -> -518.23139 | K48: =K46/(1+$C$22)^K4 -> -476.07175 | L48: =L46/(1+$C$22)^L4 -> -457.45379
B49: Sum | C49: =SUM(H48:L48) -> -633.07976
B51: Terminal Value
B52: Revenue NTM | C52: =L31*(1+C29) -> 2158.7213
B53: EV / NTM Revenue Multiple | C53: =C24 -> 2.7870309
B54: Terminal Value | C54: =C52*C53 -> 6016.4228
B56: Present Value of Terminal Value | C56: =C54/(1+C22)^L4 -> 3970.4233
B58: Intrinsic Value
B59: Enterprise Value | C59: =C56+C49 -> 3337.3435
B60: Plus: Cash | C60: =C27 -> 11663.7
B61: Less: Debt | C61: =C28 -> 0
B62: Equity Value | C62: =C59+C60-C61 -> 15001.044
B64: Implied Price per Share | C64: =C62/C26 -> 62.511953
B65: Difference to actual | C65: =(C64/$C$25)-1 -> -0.32885553
A67: x | B67: PV of ANOPAT Valuation
B70: NOPAT | H70: =H42 -> -155.63895 | I70: =I42 -> -718.4431 | J70: =J42 -> -651.34439 | K70: =K42 -> -671.88473 | L70: =L42 -> -657.49256
B71: Beginning Net operating assets (t-1) | H71: =G123 -> 4142.5 | I71: =H123 -> 2498.2925 | J71: =I123 -> 2430.694 | K71: =J123 -> 2444.3541 | L71: =K123 -> 2436.325
B72: Capital Charge | H72: =+H71*$C$22 -> 359.05774 | I72: =+I71*$C$22 -> 216.54345 | J72: =+J71*$C$22 -> 210.68425 | K72: =+K71*$C$22 -> 211.86826 | L72: =+L71*$C$22 -> 211.17233
B73: ANOPAT | H73: =H70-H72 -> -514.69669 | I73: =I70-I72 -> -934.98655 | J73: =J70-J72 -> -862.02864 | K73: =K70-K72 -> -883.753 | L73: =L70-L72 -> -868.66489
B74: PV of ANOPAT | H74: =H73/(1+$C$22)^H4 -> -473.64294 | I74: =I73/(1+$C$22)^I4 -> -791.7804 | J74: =J73/(1+$C$22)^J4 -> -671.77025 | K74: =K73/(1+$C$22)^K4 -> -633.76707 | L74: =L73/(1+$C$22)^L4 -> -573.25879
B75: Sum | C75: =SUM(H74:L74) -> -3144.2195
H76: =H74-H48 -> -1843.4788 | I76: =I74-I48 -> -240.62169 | J76: =J74-J48 -> -153.53886 | K76: =K74-K48 -> -157.69532 | L76: =L74-L48 -> -115.805
B77: Terminal Value
B78: Revenue NTM | C78: =L31*(1+C29) -> 2158.7213
B79: EV / NTM Revenue Multiple | C79: =C24 -> 2.7870309
B80: Terminal Value | C80: =C78*C79 -> 6016.4228
B82: Present Value of Terminal Value | C82: =C80/(1+C22)^L4 -> 3970.4233
B84: Intrinsic Value
B85: Enterprise Value | C85: =C75+C82+G123 -> 4968.7038
B86: Plus: Cash | C86: =C27 -> 11663.7
B87: Less: Debt | C87: =C28 -> 0
B88: Equity Value | C88: =C85+C86-C87 -> 16632.404
B90: Implied Price per Share | C90: =C88/C26 -> 69.310114
B91: Difference to actual | C91: =(C90/$C$25)-1 -> -0.25586872
A93: x | B93: Supporting Schedules
B95: Working Capital Schedule
B97: Accounts Receivable (Days) | C97: ='BionTech Ratios'!G57 -> 51.134254 | D97: ='BionTech Ratios'!H57 -> 66.212606 | E97: ='BionTech Ratios'!I57 -> 119.01416 | F97: ='BionTech Ratios'!J57 -> 203.04981 | G97: ='BionTech Ratios'!K57 -> 438.39592 | H97: 58.67343 | I97: 58.67343 | J97: 58.67343 | K97: 58.67343 | L97: 58.67343 | M97: > average adjusted
B98: Inventory (Days) | C98: ='BionTech Ratios'!G59 -> 181.14828 | D98: ='BionTech Ratios'!H59 -> 230.1511 | E98: ='BionTech Ratios'!I59 -> 35.029366 | F98: ='BionTech Ratios'!J59 -> 56.620367 | G98: ='BionTech Ratios'!K59 -> 239.26976 | H98: 45.824867 | I98: 45.824867 | J98: 45.824867 | K98: 45.824867 | L98: 45.824867 | M98: > average adjusted
B99: Accounts Payable (Days) | C99: ='BionTech Ratios'!G61 -> 643.64483 | D99: ='BionTech Ratios'!H61 -> 372.74266 | E99: ='BionTech Ratios'!I61 -> 16.216383 | F99: ='BionTech Ratios'!J61 -> 21.882471 | G99: ='BionTech Ratios'!K61 -> 167.48583 | H99: 19.049427 | I99: 19.049427 | J99: 19.049427 | K99: 19.049427 | L99: 19.049427 | M99: > average adjusted
B100: Cash Conversion Cycle | C100: =C97+C98-C99 -> -411.3623 | D100: =D97+D98-D99 -> -76.378962 | E100: =E97+E98-E99 -> 137.82714 | F100: =F97+F98-F99 -> 237.7877 | G100: =G97+G98-G99 -> 510.17984 | H100: =H97+H98-H99 -> 85.44887 | I100: =I97+I98-I99 -> 85.44887 | J100: =J97+J98-J99 -> 85.44887 | ... L100: =L97+L98-L99 -> 85.44887
B102: Operating Working Capital
B103: Trade receivables | C103: ='BionTech Adjusted'!AI118 -> 11.913 | D103: ='BionTech Adjusted'!AJ118 -> 165.5 | E103: ='BionTech Adjusted'!AK118 -> 12381.7 | F103: ='BionTech Adjusted'!AL118 -> 7145.6 | G103: ='BionTech Adjusted'!AM118 -> 2155.7 | H103: =(H97/365)*H31 -> 450.09755 | I103: =(I97/365)*I31 -> 361.68553 | J103: =(J97/365)*J31 -> 350.03122 | K103: =(K97/365)*K31 -> 320.18814 | L103: =(L97/365)*L31 -> 330.48814
B104: Inventories | C104: ='BionTech Adjusted'!AI119 -> 11.722 | D104: ='BionTech Adjusted'!AJ119 -> 64.1 | E104: ='BionTech Adjusted'!AK119 -> 502.5 | F104: ='BionTech Adjusted'!AL119 -> 439.6 | G104: ='BionTech Adjusted'!AM119 -> 357.7 | H104: =(H98/365)*(-H32) -> 53.902045 | I104: =(I98/365)*(-I32) -> 43.314143 | J104: =(J98/365)*(-J32) -> 41.918465 | K104: =(K98/365)*(-K32) -> 38.344567 | L104: =(L98/365)*(-L32) -> 39.578058
B105: Trade payables | C105: ='BionTech Adjusted'!AI121 -> 20.498 | D105: ='BionTech Adjusted'!AJ121 -> 102.3 | E105: ='BionTech Adjusted'!AK121 -> 160 | F105: ='BionTech Adjusted'!AL121 -> 204.1 | G105: ='BionTech Adjusted'!AM121 -> 354 | H105: =(H99/365)*(-H32) -> 22.407115 | I105: =(I99/365)*(-I32) -> 18.005718 | J105: =(J99/365)*(-J32) -> 17.425533 | K105: =(K99/365)*(-K32) -> 15.939862 | L105: =(L99/365)*(-L32) -> 16.452624
B106: = Ending operating working capital | C106: =SUM(C103:C104)-C105 -> 3.137 | D106: =SUM(D103:D104)-D105 -> 127.3 | E106: =SUM(E103:E104)-E105 -> 12724.2 | F106: =SUM(F103:F104)-F105 -> 7381.1 | G106: =SUM(G103:G104)-G105 -> 2159.4 | H106: =SUM(H103:H104)-H105 -> 481.59248 | I106: =SUM(I103:I104)-I105 -> 386.99395 | J106: =SUM(J103:J104)-J105 -> 374.52415 | ... L106: =SUM(L103:L104)-L105 -> 353.61358
B107: Change in NWC | D107: =C106-D106 -> -124.163 | E107: =D106-E106 -> -12596.9 | F107: =E106-F106 -> 5343.1 | G107: =F106-G106 -> 5221.7 | H107: =G106-H106 -> 1677.8075 | I107: =H106-I106 -> 94.598522 | J107: =I106-J106 -> 12.469805 | K107: =J106-K106 -> 31.931301 | L107: =K106-L106 -> -11.020728
B110: Net Operating Assets Schedule
B112: Depreciation (% of Revenue) | H112: 0.048 | I112: 0.048 | J112: 0.048 | K112: 0.048 | L112: 0.048
B113: Capex (% of Revenue) | H113: 0.06 | I113: 0.06 | J113: 0.06 | K113: 0.06 | L113: 0.06
B115: Beg. Non-Current Operating Assets | H115: =G118 -> 1983.1 | I115: =H118 -> 2016.7 | J115: =I118 -> 2043.7 | K115: =J118 -> 2069.83 | L115: =K118 -> 2093.7322
B116: + Capex | H116: =H113*H31 -> 168 | I116: =I113*I31 -> 135 | J116: =J113*J31 -> 130.65 | K116: =K113*K31 -> 119.511 | L116: =L113*L31 -> 123.3555
B117: - D&A | H117: =-H112*H31 -> -134.4 | I117: =-I112*I31 -> -108 | J117: =-J112*J31 -> -104.52 | K117: =-K112*K31 -> -95.6088 | L117: =-L112*L31 -> -98.6844
B118: Ending Non-Current Operating Assets | G118: ='BionTech Adjusted'!K129 -> 1983.1 | H118: =SUM(H115:H117) -> 2016.7 | I118: =SUM(I115:I117) -> 2043.7 | J118: =SUM(J115:J117) -> 2069.83 | K118: =SUM(K115:K117) -> 2093.7322 | L118: =SUM(L115:L117) -> 2118.4033
B120: Invested Capital Schedule
B121: Net working capital | G121: =G106 -> 2159.4 | H121: =H106 -> 481.59248 | I121: =I106 -> 386.99395 | J121: =J106 -> 374.52415 | K121: =K106 -> 342.59285 | L121: =L106 -> 353.61358
B122: + Net non-current operating assets | G122: =G118 -> 1983.1 | H122: =H118 -> 2016.7 | I122: =I118 -> 2043.7 | J122: =J118 -> 2069.83 | K122: =K118 -> 2093.7322 | L122: =L118 -> 2118.4033
B123: = Net operating assets | G123: =SUM(G121:G122) -> 4142.5 | H123: =SUM(H121:H122) -> 2498.2925 | I123: =SUM(I121:I122) -> 2430.694 | J123: =SUM(J121:J122) -> 2444.3541 | K123: =SUM(K121:K122) -> 2436.325 | L123: =SUM(L121:L122) -> 2472.0169
A127: x | B127: Charts and Graphs
C130: Sensitising WACC against terminal value multiple
E131: WACC
C132: EV / NTM Revenue | D132: =C64 -> 62.511953 | E132: =F132-0.01 -> 0.066676583 | F132: =G132-0.01 -> 0.076676583 | G132: 0.086676583 | H132: =G132+0.01 -> 0.096676583 | I132: =H132+0.01 -> 0.10667658
...

Sheet Revenue forecasts
B2: Revenue by type (EUR m) | C2: 2024 | D2: 2025 | E2: 2026 | F2: 2027 | G2: 2028 | H2: 2029
A3: x | B3: Existing product sales (Comirnaty COVID-19) | C3: 2750 | D3: =C3*(1+D4) -> 2200 | E3: =D3*(1+E4) -> 1870 | F3: =E3*(1+F4) -> 1589.5 | G3: =F3*(1+G4) -> 1351.075 | H3: =G3*(1+H4) -> 1351.075
B4: Volume decline | D4: -0.2 | E4: -0.15 | F4: -0.15 | G4: -0.15 | I4: > normalisation of Covid vaccine market from ('29)
A6: x | B6: Pipeline product sales – oncology | E6: =E13+E21 -> 112.5 | F6: =F13+F21 -> 225 | G6: =G13+G21 -> 416.25 | H6: =H13+H21 -> 562.5
B7: BNT122 TAM (cases m) | E7: 0.15 | F7: 0.15 | G7: 0.15 | H7: 0.15
B8: Penetration (share) | E8: 0.05 | F8: =E8+0.05 -> 0.1 | G8: 0.17 | H8: =G8+0.05 -> 0.22
B9: BNT122 SOM (cases m) | E9: =E7*E8 -> 0.0075 | F9: =F7*F8 -> 0.015 | G9: =G7*G8 -> 0.0255 | H9: =H7*H8 -> 0.033
B11: BNT122 pricing | E11: 50000 | F11: 50000 | G11: 50000 | H11: 50000
B12: BNT122 PoS | E12: 0.3 | F12: 0.3 | G12: 0.3 | H12: 0.3
B13: BNT122 sales | E13: =E9*E11*E12 -> 112.5 | F13: =F9*F11*F12 -> 225 | G13: =G9*G11*G12 -> 382.5 | H13: =H9*H11*H12 -> 495
B15: BNT116 TAM (cases m) | G15: 0.1 | H15: 0.1
B16: Penetration (share) | G16: 0.03 | H16: 0.06
B17: BNT116 SOM (cases m) | G17: =G15*G16 -> 0.003 | H17: =H15*H16 -> 0.006
B19: BNT116 pricing | G19: 75000 | H19: 75000
B20: BNT116 PoS | G20: 0.15 | H20: 0.15
B21: BNT116 sales | G21: =G17*G19*G20 -> 33.75 | H21: =H17*H19*H20 -> 67.5
A23: x | B23: Pipeline product sales – new vaccines | E23: =E32+E40 -> 45 | F23: =F32+F40 -> 127.35 | G23: =G32+G40 -> 238.6 | H23: =H32+H40 -> 292.35
B24: Shingles vaccine market | G24: 5300 | H24: 6000
B25: Pricing | G25: 150 | H25: 150
B26: Shingles TAM (doses m) | G26: =G24/G25 -> 35.333333 | H26: =H24/H25 -> 40
B27: Penetration (share) | G27: 0.05 | H27: 0.05
B28: Shingles SOM (doses m) | G28: =G26*G27 -> 1.7666667 | H28: =H26*H27 -> 2
B30: Shingles pricing | G30: 150 | H30: 150
B31: Shingles PoS | G31: 0.25 | H31: 0.25
B32: Shingles sales | G32: =G28*G30*G31 -> 66.25 | H32: =H28*H30*H31 -> 75
B34: Flu TAM (doses m) | E34: 150 | F34: 150 | G34: 150 | H34: 150 | I34: > US & EU only
B35: Penetration (share) | E35: 0.02 | F35: =E35+0.0366 -> 0.0566 | G35: =F35+0.02 -> 0.0766 | H35: =G35+0.02 -> 0.0966
B36: Flu SOM (doses m) | E36: =E34*E35 -> 3 | F36: =F34*F35 -> 8.49 | G36: =G34*G35 -> 11.49 | H36: =H34*H35 -> 14.49
B38: Flu pricing | E38: 30 | F38: 30 | G38: 30 | H38: 30
B39: Flu PoS | E39: 0.5 | F39: 0.5 | G39: 0.5 | H39: 0.5
B40: Flu sales | E40: =E36*E38*E39 -> 45 | F40: =F36*F38*F39 -> 127.35 | G40: =G36*G38*G39 -> 172.35 | H40: =H36*H38*H39 -> 217.35
A42: x | B42: Partnership & milestone revenue | C42: =SUM(C43:C44) -> 50 | D42: =SUM(D43:D44) -> 50 | E42: =SUM(E43:E44) -> 150 | F42: =SUM(F43:F44) -> 50 | G42: =SUM(G43:G44) -> 50 | H42: =SUM(H43:H44) -> 50
B43: Collaboration revenue | C43: 50 | D43: 50 | E43: 50 | F43: 50 | G43: 50 | H43: 50
B44: Milestone bump | E44: 100
B46: Total revenue | C46: =C42+C23+C6+C3 -> 2800 | D46: =D42+D23+D6+D3 -> 2250 | E46: =E42+E23+E6+E3 -> 2177.5 | F46: =F42+F23+F6+F3 -> 1991.85 | G46: =G42+G23+G6+G3 -> 2055.925 | H46: =H42+H23+H6+H3 -> 2255.925

Sheet Public comps
B2: Date | D2: 45741
B3: (in EUR m)
A4: x | B4: Company name | C4: Price close | D4: Shares oust. (m) | E4: Market Cap | F4: Enterprise Value | G4: Revenue (LTM) | H4: EV / Revenue (LTM) | I4: Revenue (NTM) | J4: EV / Revenue (NTM) | K4: EBITDA (LTM) | L4: EV / EBITDA (LTM) | M4: EBITDA (NTM) | N4: EV / EBITDA (NTM) | O4: Net Income (LTM) | P4: EPS (LTM) | Q4: P / E (LTM) | R4: Net Income (NTM) | S4: EPS (NTM) | T4: P / E (NTM)
B5: BioNTech SE | C5: 93.14232 | D5: 239.9708 | E5: 22351.437 | F5: 6513.4007 | G5: 2751.1 | H5: =$F5/G5 -> 2.3675623 | I5: 2117.5833 | J5: =$F5/I5 -> 3.0758652 | K5: -1033.1 | L5: =$F5/K5 -> -6.3047146 | M5: -1492.0414 | N5: =$F5/M5 -> -4.3654288 | O5: -665.3 | P5: =O5/$D5 -> -2.7724206 | Q5: =C5/P5 -> -33.596028 | R5: -1207.431 | S5: =R5/D5 -> -5.0315748 | T5: =C5/S5 -> -18.511564
B7: Selected Biotech peers
B8: Moderna, Inc. | C8: 31.624335 | D8: 386.6226 | E8: 12226.683 | F8: 4108.1967 | G8: 2991.9574 | H8: =$F8/G8 -> 1.3730799 | I8: 2076.8646 | J8: =$F8/I8 -> 1.9780764 | K8: -3472.7417 | L8: =$F8/K8 -> -1.1829837 | M8: -3681.3596 | N8: =$F8/M8 -> -1.1159455 | O8: -3292.4476 | P8: =O8/$D8 -> -8.5159211 | Q8: =C8/P8 -> -3.7135542 | R8: -3750.8234 | S8: =R8/D8 -> -9.701511 | T8: =C8/S8 -> -3.259733
B9: AstraZeneca PLC | C9: 136.83143 | D9: 1550.6072 | E9: 212171.8 | F9: 236050.66 | G9: 49995.091 | H9: =$F9/G9 -> 4.7214768 | I9: 54519.631 | J9: =$F9/I9 -> 4.3296452 | K9: 16242.187 | L9: =$F9/K9 -> 14.533182 | M9: 19299.581 | N9: =$F9/M9 -> 12.23087 | O9: 6510.0038 | P9: =O9/$D9 -> 4.1983578 | Q9: =C9/P9 -> 32.591656 | R9: 13117.008 | S9: =R9/D9 -> 8.459272 | T9: =C9/S9 -> 16.17532
B10: GSK plc | C10: 17.743161 | D10: 4076.7539 | E10: 72334.501 | F10: 86762.02 | G10: 37066.156 | H10: =$F10/G10 -> 2.3407342 | I10: 39342.573 | J10: =$F10/I10 -> 2.205296 | K10: 9820.594 | L10: =$F10/K10 -> 8.8347019 | M10: 13144.504 | N10: =$F10/M10 -> 6.6006309 | O10: 3486.175 | P10: =O10/$D10 -> 0.85513501 | Q10: =C10/P10 -> 20.748959 | R10: 8346.9543 | S10: =R10/D10 -> 2.0474511 | T10: =C10/S10 -> 8.6659754
B11: Sanofi | C11: 103.88 | D11: 1224.035 | E11: 127152.75 | F11: 137859.75 | G11: 44286 | H11: =$F11/G11 -> 3.1129421 | I11: 46188.493 | J11: =$F11/I11 -> 2.9847208 | K11: 11664 | L11: =$F11/K11 -> 11.819252 | M11: 14351.209 | N11: =$F11/M11 -> 9.6061421 | O11: 5618 | P11: =O11/$D11 -> 4.5897381 | Q11: =C11/P11 -> 22.6331 | R11: 10189.54 | S11: =R11/D11 -> 8.3245493 | T11: =C11/S11 -> 12.478754
B12: Takeda Pharmaceutical Company Limited | C12: 27.928515 | D12: 1529.4981 | E12: 42716.612 | F12: 73060.806 | G12: 27970.201 | H12: =$F12/G12 -> 2.6120944 | I12: 28215.985 | J12: =$F12/I12 -> 2.589341 | K12: 7724.248 | L12: =$F12/K12 -> 9.4586302 | M12: 7825.2334 | N12: =$F12/M12 -> 9.3365657 | O12: 1272.0427 | P12: =O12/$D12 -> 0.8316733 | Q12: =C12/P12 -> 33.581114 | R12: 1446.4214 | S12: =R12/D12 -> 0.9456837 | T12: =C12/S12 -> 29.532618
D15: Min | E15: =MIN(E5:E12) -> 12226.683 | F15: =MIN(F5:F12) -> 4108.1967 | G15: =MIN(G5:G12) -> 2751.1 | H15: =MIN(H5:H12) -> 1.3730799 | I15: =MIN(I5:I12) -> 2076.8646 | J15: =MIN(J5:J12) -> 1.9780764 | K15: =MIN(K5:K12) -> -3472.7417 | L15: =MIN(L5:L12) -> -6.3047146 | ... T15: =MIN(T5:T12) -> -18.511564
D16: Median | E16: =MEDIAN(E5:E12) -> 57525.556 | F16: =MEDIAN(F5:F12) -> 79911.413 | G16: =MEDIAN(G5:G12) -> 32518.179 | H16: =MEDIAN(H5:H12) -> 2.4898284 | I16: =MEDIAN(I5:I12) -> 33779.279 | J16: =MEDIAN(J5:J12) -> 2.7870309 | K16: =MEDIAN(K5:K12) -> 8772.421 | L16: =MEDIAN(L5:L12) -> 9.1466661 | ... T16: =MEDIAN(T5:T12) -> 10.572365
D17: Average | E17: =AVERAGE(E5:E12) -> 81492.298 | F17: =AVERAGE(F5:F12) -> 90725.807 | G17: =AVERAGE(G5:G12) -> 27510.084 | H17: =AVERAGE(H5:H12) -> 2.7546483 | I17: =AVERAGE(I5:I12) -> 28743.522 | J17: =AVERAGE(J5:J12) -> 2.8604908 | K17: =AVERAGE(K5:K12) -> 6824.1978 | L17: =AVERAGE(L5:L12) -> 6.1930114 | ... T17: =AVERAGE(T5:T12) -> 7.5135617
D18: Max | E18: =MAX(E5:E12) -> 212171.8 | F18: =MAX(F5:F12) -> 236050.66 | G18: =MAX(G5:G12) -> 49995.091 | H18: =MAX(H5:H12) -> 4.7214768 | I18: =MAX(I5:I12) -> 54519.631 | J18: =MAX(J5:J12) -> 4.3296452 | K18: =MAX(K5:K12) -> 16242.187 | L18: =MAX(L5:L12) -> 14.533182 | ... T18: =MAX(T5:T12) -> 29.532618
G30: 1000

Sheet WACC Analysis
B2: WACC calculation
L3: Sensitising WACC based on capital structure and levered Beta
A4: x | B4: Input | C4: Value | D4: Comment | E4: Source: | N4: Debt / Value
B5: Risk-free rate | C5: 0.0435 | D5: Yield on 10y U.S. government bond | E5: https://www.marketwatch.com/investing/bond/tmubmusd10y?countrycode=bx | M5: =$C$19 -> 0.086676583 | N5: 0.0097073453 | O5: =N5+0.04 -> 0.049707345 | P5: =O5+0.04 -> 0.089707345 | Q5: =P5+0.04 -> 0.12970735 | R5: =Q5+0.04 -> 0.16970735
B6: Equity Beta | C6: 1.005 | D6: Based on 5y-monthly regression (against S&P 500) | E6: Bloomberg (LSE) | L6: Equity Beta | M6: =M7-0.1 -> 0.805 | N6: 0.078100648 | O6: 0.077046388 | P6: 0.075992128 | Q6: 0.074937868 | R6: 0.073883608
B7: Equity risk premium (ERP) | C7: 0.0433 | D7: Implied current U.S. ERP | E7: https://pages.stern.nyu.edu/~adamodar/New_Home_Page/datafile/ctryprem.html | M7: =M8-0.1 -> 0.905 | N7: 0.082388616 | O7: 0.081161156 | P7: 0.079933696 | Q7: 0.078706236 | R7: 0.077478776
B8: Cost of equity | C8: =C5+C6*C7 -> 0.0870165 | M8: 1.005 | N8: 0.086676583 | O8: 0.085275923 | P8: 0.083875263 | Q8: 0.082474603 | R8: 0.081073943
M9: =M8+0.1 -> 1.105 | N9: 0.09096455 | O9: 0.08939069 | P9: 0.08781683 | Q9: 0.08624297 | R9: 0.08466911
B10: Interest rate | C10: =-'BionTech Adjusted'!K14/SUM('BionTech Adjusted'!K57,'BionTech Adjusted'!K64) -> 0.10908261 | M10: =M9+0.1 -> 1.205 | N10: 0.095252517 | O10: 0.093505457 | P10: 0.091758397 | Q10: 0.090011337 | R10: 0.088264277
B11: Pre-tax cost of debt | C11: =5.2%/(1-C12) -> 0.074285714 | D11: Based on AlphaSpread security analysis | E11: https://www.alphaspread.com/security/nasdaq/bntx/discount-rate | M11: =M10+0.1 -> 1.305 | N11: 0.099540484 | O11: 0.097620224 | P11: 0.095699964 | Q11: 0.093779704 | R11: 0.091859444
B12: Marginal tax rate | C12: 0.3 | D12: German corporate tax rate | E12: https://kpmg.com/dk/en/home/insights/2016/11/tax-rates-online/corporate-tax-rates-table.html
B13: Post-tax cost of debt | C13: =C11*(1-C12) -> 0.052
B15: Debt | C15: ='BionTech Adjusted'!K57+'BionTech Adjusted'!K64 -> 219.1 | E15: total debt
B16: Equity | C16: ='Public comps'!E5 -> 22351.437 | E16: market cap
B17: Debt / Value | C17: =C15/SUM(C15:C16) -> 0.0097073453 | D17: Current capital structure
B18: Equity / Value | C18: =1-C17 -> 0.99029265
B19: WACC | C19: =C17*C13+C8*C18 -> 0.086676583
L23: Sensitising WACC based on capital structure and cost of debt
N24: Debt / Value
M25: =C19 -> 0.086676583 | N25: 0.0097073453 | O25: =N25+0.04 -> 0.049707345 | P25: =O25+0.04 -> 0.089707345 | Q25: =P25+0.04 -> 0.12970735 | R25: =Q25+0.04 -> 0.16970735
L26: Pre-tax cost of debt | M26: =M27-0.02 -> 0.034285714 | N26: 0.086404777 | O26: 0.083884117 | P26: 0.081363457 | Q26: 0.078842797 | R26: 0.076322137
M27: =M28-0.02 -> 0.054285714 | N27: 0.08654068 | O27: 0.08458002 | P27: 0.08261936 | Q27: 0.0806587 | R27: 0.07869804
M28: 0.074285714 | N28: 0.086676583 | O28: 0.085275923 | P28: 0.083875263 | Q28: 0.082474603 | R28: 0.081073943
M29: =M28+0.02 -> 0.094285714 | N29: 0.086812486 | O29: 0.085971826 | P29: 0.085131166 | Q29: 0.084290506 | R29: 0.083449846
M30: =M29+0.02 -> 0.11428571 | N30: 0.086948388 | O30: 0.086667728 | P30: 0.086387068 | Q30: 0.086106408 | R30: 0.085825748

Sheet >>>Adjusted Statements>>>

Sheet BionTech Adjusted
C2: 2015 | D2: 2016 | E2: 2017 | F2: =E2+1 -> 2018 | G2: =F2+1 -> 2019 | H2: =G2+1 -> 2020 | I2: =H2+1 -> 2021 | J2: =I2+1 -> 2022 | K2: =J2+1 -> 2023 | L2: =K2+1 -> 2024 | M2: =L2+1 -> 2025 | ... Q2: =P2+1 -> 2029 | S2: 2017 | T2: =S2+1 -> 2018 | U2: =T2+1 -> 2019 | V2: =U2+1 -> 2020 | W2: =V2+1 -> 2021 | X2: =W2+1 -> 2022 | Y2: =X2+1 -> 2023 | Z2: =Y2+1 -> 2024 | AA2: =Z2+1 -> 2025 | ... AE2: =AD2+1 -> 2029 | AG2: 2017 | AH2: =AG2+1 -> 2018 | AI2: =AH2+1 -> 2019 | AJ2: =AI2+1 -> 2020 | AK2: =AJ2+1 -> 2021 | AL2: =AK2+1 -> 2022 | AM2: =AL2+1 -> 2023 | AN2: =AM2+1 -> 2024 | AO2: =AN2+1 -> 2025 | ... AS2: =AR2+1 -> 2029
B3: Operating cash percentage | D3: 0.05 | E3: 0.05 | F3: 0.05 | G3: 0.05 | H3: 0.05 | I3: 0.05 | J3: 0.05 | K3: 0.05 | L3: 0.05 | M3: 0.05 | N3: 0.05 | O3: 0.05 | P3: 0.05 | Q3: 0.05 | AG3: =E3 -> 0.05 | AH3: =F3 -> 0.05 | AI3: =G3 -> 0.05 | AJ3: =H3 -> 0.05 | AK3: =I3 -> 0.05 | AL3: =J3 -> 0.05 | AM3: =K3 -> 0.05 | AN3: =L3 -> 0.05 | ... AS3: =Q3 -> 0.05
B4: Tax Rate | D4: 0.31 | E4: =-E16/E10 -> -0.00073435817 | F4: =-F16/F10 -> -0.011141234 | G4: =-G16/G10 -> 0.0011019284 | H4: =-H16/H10 -> 1.9538835 | I4: =-I16/I10 -> 0.31104176 | J4: =-J16/J10 -> 0.27839781 | K4: =-K16/K10 -> 0.37050985
A7: x | B7: INCOME STATEMENT
B8: Revenue | E8: ='BionTech Standardized'!E5 -> 61.598 | F8: ='BionTech Standardized'!F5 -> 127.575 | G8: ='BionTech Standardized'!G5 -> 108.6 | H8: ='BionTech Standardized'!H5 -> 482.3 | I8: ='BionTech Standardized'!I5 -> 18976.7 | J8: ='BionTech Standardized'!J5 -> 17310.6 | K8: ='BionTech Standardized'!K5 -> 3819 | AG8: =E8+S8 -> 61.598 | AH8: =F8+T8 -> 127.575 | AI8: =G8+U8 -> 108.6 | AJ8: =H8+V8 -> 482.3 | AK8: =I8+W8 -> 18976.7 | AL8: =J8+X8 -> 17310.6 | AM8: =K8+Y8 -> 3819 | AN8: ='Revenue forecasts'!C46 -> 2800 | AO8: ='Revenue forecasts'!D46 -> 2250 | AP8: ='Revenue forecasts'!E46 -> 2177.5 | AQ8: ='Revenue forecasts'!F46 -> 1991.85 | AR8: ='Revenue forecasts'!G46 -> 2055.925 | AS8: ='Revenue forecasts'!H46 -> 2255.925
B9: Operating expenses | E9: =SUM('BionTech Standardized'!E6:E10) -> -122.876 | F9: =SUM('BionTech Standardized'!F6:F10) -> -181.429 | G9: =SUM('BionTech Standardized'!G6:G10) -> -290.1 | H9: =SUM('BionTech Standardized'!H6:H10) -> -564.7 | I9: =SUM('BionTech Standardized'!I6:I10) -> -3692.9 | J9: =SUM('BionTech Standardized'!J6:J10) -> -4667.9 | K9: =SUM('BionTech Standardized'!K6:K10) -> -3128.6 | AG9: =E9+S9 -> -122.876 | AH9: =F9+T9 -> -181.429 | AI9: =G9+U9 -> -290.1 | AJ9: =H9+V9 -> -564.7 | AK9: =I9+W9 -> -3692.9 | AL9: =J9+X9 -> -4667.9 | AM9: =K9+Y9 -> -3128.6 | AN9: =L9+Z9 -> 0 | ... AS9: =Q9+AE9 -> 0
B10: Operating profit | E10: =SUM(E8:E9) -> -61.278 | F10: =SUM(F8:F9) -> -53.854 | G10: =SUM(G8:G9) -> -181.5 | H10: =SUM(H8:H9) -> -82.4 | I10: =SUM(I8:I9) -> 15283.8 | J10: =SUM(J8:J9) -> 12642.7 | K10: =SUM(K8:K9) -> 690.4 | S10: =SUM(S8:S9) -> 0 | T10: =SUM(T8:T9) -> 0 | U10: =SUM(U8:U9) -> 0 | V10: =SUM(V8:V9) -> 0 | W10: =SUM(W8:W9) -> 0 | X10: =SUM(X8:X9) -> 0 | Y10: =SUM(Y8:Y9) -> 0 | Z10: =SUM(Z8:Z9) -> 0 | ... AE10: =SUM(AE8:AE9) -> 0 | AG10: =SUM(AG8:AG9) -> -61.278 | AH10: =SUM(AH8:AH9) -> -53.854 | AI10: =SUM(AI8:AI9) -> -181.5 | AJ10: =SUM(AJ8:AJ9) -> -82.4 | AK10: =SUM(AK8:AK9) -> 15283.8 | AL10: =SUM(AL8:AL9) -> 12642.7 | AM10: =SUM(AM8:AM9) -> 690.4 | AN10: =SUM(AN8:AN9) -> 2800 | ... AS10: =SUM(AS8:AS9) -> 2255.925
B11: Investment Income | E11: ='BionTech Standardized'!E13 -> 0 | F11: ='BionTech Standardized'!F13 -> 0 | G11: ='BionTech Standardized'!G13 -> 0 | H11: ='BionTech Standardized'!H13 -> 0 | I11: ='BionTech Standardized'!I13 -> 0 | J11: ='BionTech Standardized'!J13 -> 216.8 | K11: ='BionTech Standardized'!K13 -> 162 | AG11: =E11+S11 -> 0 | AH11: =F11+T11 -> 0 | AI11: =G11+U11 -> 0 | AJ11: =H11+V11 -> 0 | AK11: =I11+W11 -> 0 | AL11: =J11+X11 -> 216.8 | AM11: =K11+Y11 -> 162 | AN11: =L11+Z11 -> 0 | ... AS11: =Q11+AE11 -> 0
B12: Net non-recurring income or expense | E12: ='BionTech Standardized'!E14 -> 0 | F12: ='BionTech Standardized'!F14 -> 0 | G12: ='BionTech Standardized'!G14 -> 0 | H12: ='BionTech Standardized'!H14 -> 0 | I12: ='BionTech Standardized'!I14 -> 0 | J12: ='BionTech Standardized'!J14 -> 0 | K12: ='BionTech Standardized'!K14 -> 0 | AG12: =E12+S12 -> 0 | AH12: =F12+T12 -> 0 | AI12: =G12+U12 -> 0 | AJ12: =H12+V12 -> 0 | AK12: =I12+W12 -> 0 | AL12: =J12+X12 -> 0 | AM12: =K12+Y12 -> 0 | AN12: =L12+Z12 -> 0 | ... AS12: =Q12+AE12 -> 0
B13: Interest income | E13: ='BionTech Standardized'!E11 -> 2.133 | F13: ='BionTech Standardized'!F11 -> 8.046 | G13: ='BionTech Standardized'!G11 -> 4.1 | H13: ='BionTech Standardized'!H11 -> 1.6 | I13: ='BionTech Standardized'!I11 -> 67.7 | J13: ='BionTech Standardized'!J11 -> 113.5 | K13: ='BionTech Standardized'!K11 -> 357.6 | AG13: =E13+S13 -> 2.133 | AH13: =F13+T13 -> 8.046 | AI13: =G13+U13 -> 4.1 | AJ13: =H13+V13 -> 1.6 | AK13: =I13+W13 -> 67.7 | AL13: =J13+X13 -> 113.5 | AM13: =K13+Y13 -> 357.6 | AN13: =L13+Z13 -> 0 | ... AS13: =Q13+AE13 -> 0
B14: Interest expense | E14: ='BionTech Standardized'!E12 -> -26.759 | F14: ='BionTech Standardized'!F12 -> -1.855 | G14: ='BionTech Standardized'!G12 -> -2 | H14: ='BionTech Standardized'!H12 -> -65 | I14: ='BionTech Standardized'!I12 -> -305.1 | J14: ='BionTech Standardized'!J12 -> -18.9 | K14: ='BionTech Standardized'!K12 -> -23.9 | AG14: =E14+S14 -> -26.759 | AH14: =F14+T14 -> -1.855 | AI14: =G14+U14 -> -2 | AJ14: =H14+V14 -> -65 | AK14: =I14+W14 -> -305.1 | AL14: =J14+X14 -> -18.9 | AM14: =K14+Y14 -> -23.9 | AN14: =L14+Z14 -> 0 | ... AS14: =Q14+AE14 -> 0
B15: Profit before taxes | E15: =SUM(E10:E14) -> -85.904 | F15: =SUM(F10:F14) -> -47.663 | G15: =SUM(G10:G14) -> -179.4 | H15: =SUM(H10:H14) -> -145.8 | I15: =SUM(I10:I14) -> 15046.4 | J15: =SUM(J10:J14) -> 12954.1 | K15: =SUM(K10:K14) -> 1186.1 | S15: =SUM(S10:S14) -> 0 | T15: =SUM(T10:T14) -> 0 | U15: =SUM(U10:U14) -> 0 | V15: =SUM(V10:V14) -> 0 | W15: =SUM(W10:W14) -> 0 | X15: =SUM(X10:X14) -> 0 | Y15: =SUM(Y10:Y14) -> 0 | Z15: =SUM(Z10:Z14) -> 0 | ... AE15: =SUM(AE10:AE14) -> 0 | AG15: =E15+S15 -> -85.904 | AH15: =F15+T15 -> -47.663 | AI15: =G15+U15 -> -179.4 | AJ15: =H15+V15 -> -145.8 | AK15: =I15+W15 -> 15046.4 | AL15: =J15+X15 -> 12954.1 | AM15: =K15+Y15 -> 1186.1 | AN15: =L15+Z15 -> 0 | ... AS15: =Q15+AE15 -> 0
B16: Tax expense | E16: ='BionTech Standardized'!E15 -> -0.045 | F16: ='BionTech Standardized'!F15 -> -0.6 | G16: ='BionTech Standardized'!G15 -> 0.2 | H16: ='BionTech Standardized'!H15 -> 161 | I16: ='BionTech Standardized'!I15 -> -4753.9 | J16: ='BionTech Standardized'!J15 -> -3519.7 | K16: ='BionTech Standardized'!K15 -> -255.8 | AG16: =E16+S16 -> -0.045 | AH16: =F16+T16 -> -0.6 | AI16: =G16+U16 -> 0.2 | AJ16: =H16+V16 -> 161 | AK16: =I16+W16 -> -4753.9 | AL16: =J16+X16 -> -3519.7 | AM16: =K16+Y16 -> -255.8 | AN16: =L16+Z16 -> 0 | ... AS16: =Q16+AE16 -> 0
B17: Profit after taxes | E17: =SUM(E15:E16) -> -85.949 | F17: =SUM(F15:F16) -> -48.263 | G17: =SUM(G15:G16) -> -179.2 | H17: =SUM(H15:H16) -> 15.2 | I17: =SUM(I15:I16) -> 10292.5 | J17: =SUM(J15:J16) -> 9434.4 | K17: =SUM(K15:K16) -> 930.3 | S17: =SUM(S15:S16) -> 0 | T17: =SUM(T15:T16) -> 0 | U17: =SUM(U15:U16) -> 0 | V17: =SUM(V15:V16) -> 0 | W17: =SUM(W15:W16) -> 0 | X17: =SUM(X15:X16) -> 0 | Y17: =SUM(Y15:Y16) -> 0 | Z17: =SUM(Z15:Z16) -> 0 | ... AE17: =SUM(AE15:AE16) -> 0 | AG17: =E17+S17 -> -85.949 | AH17: =F17+T17 -> -48.263 | AI17: =G17+U17 -> -179.2 | AJ17: =H17+V17 -> 15.2 | AK17: =I17+W17 -> 10292.5 | AL17: =J17+X17 -> 9434.4 | AM17: =K17+Y17 -> 930.3 | AN17: =L17+Z17 -> 0 | ... AS17: =Q17+AE17 -> 0
B18: Profit/loss to non-controlling interest | E18: ='BionTech Standardized'!E16 -> 0.297 | F18: ='BionTech Standardized'!F16 -> 0.243 | G18: ='BionTech Standardized'!G16 -> 0.0001 | H18: ='BionTech Standardized'!H16 -> 0 | I18: ='BionTech Standardized'!I16 -> 0 | J18: ='BionTech Standardized'!J16 -> 0 | K18: ='BionTech Standardized'!K16 -> 0
B19: Profit/Loss of Discontinued Operations | E19: ='BionTech Standardized'!E17 -> 0 | F19: ='BionTech Standardized'!F17 -> 0 | G19: ='BionTech Standardized'!G17 -> 0 | H19: ='BionTech Standardized'!H17 -> 0 | I19: ='BionTech Standardized'!I17 -> 0 | J19: ='BionTech Standardized'!J17 -> 0 | K19: ='BionTech Standardized'!K17 -> 0 | AG19: =E19+S19 -> 0 | AH19: =F19+T19 -> 0 | AI19: =G19+U19 -> 0 | AJ19: =H19+V19 -> 0 | AK19: =I19+W19 -> 0 | AL19: =J19+X19 -> 0 | AM19: =K19+Y19 -> 0 | AN19: =L19+Z19 -> 0 | ... AS19: =Q19+AE19 -> 0
B20: Profit/loss to ordinary shareholders | E20: =SUM(E17:E19) -> -85.652 | F20: =SUM(F17:F19) -> -48.02 | G20: =SUM(G17:G19) -> -179.1999 | H20: =SUM(H17:H19) -> 15.2 | I20: =SUM(I17:I19) -> 10292.5 | J20: =SUM(J17:J19) -> 9434.4 | K20: =SUM(K17:K19) -> 930.3 | S20: =SUM(S17:S19) -> 0 | T20: =SUM(T17:T19) -> 0 | U20: =SUM(U17:U19) -> 0 | V20: =SUM(V17:V19) -> 0 | W20: =SUM(W17:W19) -> 0 | X20: =SUM(X17:X19) -> 0 | Y20: =SUM(Y17:Y19) -> 0 | Z20: =SUM(Z17:Z19) -> 0 | ... AE20: =SUM(AE17:AE19) -> 0 | AG20: =E20+S20 -> -85.652 | AH20: =F20+T20 -> -48.02 | AI20: =G20+U20 -> -179.1999 | AJ20: =H20+V20 -> 15.2 | AK20: =I20+W20 -> 10292.5 | AL20: =J20+X20 -> 9434.4 | AM20: =K20+Y20 -> 930.3 | AN20: =L20+Z20 -> 0 | ... AS20: =Q20+AE20 -> 0
A22: x | B22: OPERATING EXPENSES
B23: Classification by function:
B24: Cost of Sales (by function) | E24: -9.3 | F24: -13.7 | G24: -17.4 | H24: -59.3 | I24: -2911.5 | J24: -2995 | K24: -599.8 | AG24: =E24+S24 -> -9.3 | AH24: =F24+T24 -> -13.7 | AI24: =G24+U24 -> -17.4 | AJ24: =H24+V24 -> -59.3 | AK24: =I24+W24 -> -2911.5 | AL24: =J24+X24 -> -2995 | AM24: =K24+Y24 -> -599.8 | AN24: =L24+Z24 -> 0 | ... AS24: =Q24+AE24 -> 0
B25: SG&A (by function) | E25: -30.1 | F25: -29.4 | G25: -48.2 | H25: -108.5 | I25: -327.2 | J25: -541.2 | K25: -557.7 | AG25: =E25+S25 -> -30.1 | AH25: =F25+T25 -> -29.4 | AI25: =G25+U25 -> -48.2 | AJ25: =H25+V25 -> -108.5 | AK25: =I25+W25 -> -327.2 | AL25: =J25+X25 -> -541.2 | AM25: =K25+Y25 -> -557.7 | AN25: =L25+Z25 -> 0 | ... AS25: =Q25+AE25 -> 0
B26: R&D Expenses | E26: -85.5 | F26: -143 | G26: -226.5 | H26: -645 | I26: -949.2 | J26: -1537 | K26: -1783.1 | AG26: =E26 -> -85.5 | AH26: =F26 -> -143 | AI26: =G26 -> -226.5 | AJ26: =H26 -> -645 | AK26: =I26 -> -949.2 | AL26: =J26 -> -1537 | AM26: =K26 -> -1783.1
B27: Other Operating Income, Net of Other Operating Expense (by function) | E27: 2.1 | F27: 4.7 | G27: 2 | H27: 248.1 | I27: 495 | J27: 405.3 | K27: -188 | AG27: =E27+S27 -> 2.1 | AH27: =F27+T27 -> 4.7 | AI27: =G27+U27 -> 2 | AJ27: =H27+V27 -> 248.1 | AK27: =I27+W27 -> 495 | AL27: =J27+X27 -> 405.3 | AM27: =K27+Y27 -> -188 | AN27: =L27+Z27 -> 0 | ... AS27: =Q27+AE27 -> 0
B28: Classification by nature:
B29: Cost of Materials (by nature) | AG29: =E29+S29 -> 0 | AH29: =F29+T29 -> 0 | AI29: =G29+U29 -> 0 | AJ29: =H29+V29 -> 0 | AK29: =I29+W29 -> 0 | AL29: =J29+X29 -> 0 | AM29: =K29+Y29 -> 0 | AN29: =L29+Z29 -> 0 | ... AS29: =Q29+AE29 -> 0
B30: Personnel Expenses (by nature) | AG30: =E30+S30 -> 0 | AH30: =F30+T30 -> 0 | AI30: =G30+U30 -> 0 | AJ30: =H30+V30 -> 0 | AK30: =I30+W30 -> 0 | AL30: =J30+X30 -> 0 | AM30: =K30+Y30 -> 0 | AN30: =L30+Z30 -> 0 | ... AS30: =Q30+AE30 -> 0
B31: Depreciation and Amortization (by nature) | E31: 10.5 | F31: 22 | G31: 33.9 | H31: 38.7 | I31: 75.2 | J31: 123.3 | K31: 183.4 | AG31: =E31+S31 -> 10.5 | AH31: =F31+T31 -> 22 | AI31: =G31+U31 -> 33.9 | AJ31: =H31+V31 -> 38.7 | AK31: =I31+W31 -> 75.2 | AL31: =J31+X31 -> 123.3 | AM31: =K31+Y31 -> 183.4 | AN31: =L31+Z31 -> 0 | ... AS31: =Q31+AE31 -> 0
B32: Other Operating Income, Net of Other Operating Expense (by nature) | AG32: =E32+S32 -> 0 | AH32: =F32+T32 -> 0 | AI32: =G32+U32 -> 0 | AJ32: =H32+V32 -> 0 | AK32: =I32+W32 -> 0 | AL32: =J32+X32 -> 0 | AM32: =K32+Y32 -> 0 | AN32: =L32+Z32 -> 0 | ... AS32: =Q32+AE32 -> 0
A34: x | B34: BALANCE SHEET
B35: ASSETS
B36: Non-Current Tangible Assets | D36: =SUM('BionTech Standardized'!D35) -> 60.584 | E36: =SUM('BionTech Standardized'!E35) -> 101.521 | F36: =SUM('BionTech Standardized'!F35) -> 115.966 | G36: =SUM('BionTech Standardized'!G35) -> 148.062 | H36: =SUM('BionTech Standardized'!H35) -> 327 | I36: =SUM('BionTech Standardized'!I35) -> 534.8 | J36: =SUM('BionTech Standardized'!J35) -> 827.6 | K36: =SUM('BionTech Standardized'!K35) -> 1055 | AG36: =E36+T36 -> 101.521 | AH36: =F36+U36 -> 115.966 | AI36: =G36+V36 -> 148.062 | AJ36: =H36+W36 -> 327 | AK36: =I36+X36 -> 534.8 | AL36: =J36+Y36 -> 827.6 | AM36: =K36+Z36 -> 1055 | AO36: =M36+AA36 -> 0 | AP36: =N36+AB36 -> 0 | AQ36: =O36+AC36 -> 0 | AR36: =P36+AD36 -> 0 | AS36: =Q36+AE36 -> 0
B37: Non-Current Intangible Assets | D37: =SUM('BionTech Standardized'!D36) -> 11.184 | E37: =SUM('BionTech Standardized'!E36) -> 83.537 | F37: =SUM('BionTech Standardized'!F36) -> 88.042 | G37: =SUM('BionTech Standardized'!G36) -> 89.434 | H37: =SUM('BionTech Standardized'!H36) -> 163.5 | I37: =SUM('BionTech Standardized'!I36) -> 202.4 | J37: =SUM('BionTech Standardized'!J36) -> 219.7 | K37: =SUM('BionTech Standardized'!K36) -> 1166.6 | AG37: =E37+T37 -> 83.537 | AH37: =F37+U37 -> 88.042 | AI37: =G37+V37 -> 89.434 | AJ37: =H37+W37 -> 163.5 | AK37: =I37+X37 -> 202.4 | AL37: =J37+Y37 -> 219.7 | AM37: =K37+Z37 -> 1166.6 | AO37: =M37+AA37 -> 0 | AP37: =N37+AB37 -> 0 | AQ37: =O37+AC37 -> 0 | AR37: =P37+AD37 -> 0 | AS37: =Q37+AE37 -> 0
B38: Other Non-Operating Investments | D38: ='BionTech Standardized'!D37 -> 0.066 | E38: ='BionTech Standardized'!E37 -> 0.019 | F38: ='BionTech Standardized'!F37 -> 0.018 | G38: ='BionTech Standardized'!G37 -> 0 | H38: ='BionTech Standardized'!H37 -> 0 | I38: ='BionTech Standardized'!I37 -> 21.3 | J38: ='BionTech Standardized'!J37 -> 80.2 | K38: ='BionTech Standardized'!K37 -> 1176.1 | AG38: =E38+T38 -> 0.019 | AH38: =F38+U38 -> 0.018 | AI38: =G38+V38 -> 0 | AJ38: =H38+W38 -> 0 | AK38: =I38+X38 -> 21.3 | AL38: =J38+Y38 -> 80.2 | AM38: =K38+Z38 -> 1176.1 | AO38: =M38+AA38 -> 0 | AP38: =N38+AB38 -> 0 | AQ38: =O38+AC38 -> 0 | AR38: =P38+AD38 -> 0 | AS38: =Q38+AE38 -> 0
B39: Deferred Tax Asset | D39: ='BionTech Standardized'!D38 -> 0.002 | E39: ='BionTech Standardized'!E38 -> 0.687 | F39: ='BionTech Standardized'!F38 -> 0.891 | G39: ='BionTech Standardized'!G38 -> 0.756 | H39: ='BionTech Standardized'!H38 -> 162.1 | I39: ='BionTech Standardized'!I38 -> 0.4 | J39: ='BionTech Standardized'!J38 -> 230 | K39: ='BionTech Standardized'!K38 -> 260.4 | AG39: =E39+T39 -> 0.687 | AH39: =F39+U39 -> 0.891 | AI39: =G39+V39 -> 0.756 | AJ39: =H39+W39 -> 162.1 | AK39: =I39+X39 -> 0.4 | AL39: =J39+Y39 -> 230 | AM39: =K39+Z39 -> 260.4 | AO39: =M39+AA39 -> 0 | AP39: =N39+AB39 -> 0 | AQ39: =O39+AC39 -> 0 | AR39: =P39+AD39 -> 0 | AS39: =Q39+AE39 -> 0
B40: Total Non-Current Assets | D40: =SUM(D36:D39) -> 71.836 | E40: =SUM(E36:E39) -> 185.764 | F40: =SUM(F36:F39) -> 204.917 | G40: =SUM(G36:G39) -> 238.252 | H40: =SUM(H36:H39) -> 652.6 | I40: =SUM(I36:I39) -> 758.9 | J40: =SUM(J36:J39) -> 1357.5 | K40: =SUM(K36:K39) -> 3658.1 | S40: =SUM(S36:S39) -> 0 | T40: =SUM(T36:T39) -> 0 | U40: =SUM(U36:U39) -> 0 | V40: =SUM(V36:V39) -> 0 | W40: =SUM(W36:W39) -> 0 | X40: =SUM(X36:X39) -> 0 | Y40: =SUM(Y36:Y39) -> 0 | Z40: =SUM(Z36:Z39) -> 0 | ... AE40: =SUM(AE36:AE39) -> 0 | AG40: =E40+T40 -> 185.764 | AH40: =F40+U40 -> 204.917 | AI40: =G40+V40 -> 238.252 | AJ40: =H40+W40 -> 652.6 | AK40: =I40+X40 -> 758.9 | AL40: =J40+Y40 -> 1357.5 | AM40: =K40+Z40 -> 3658.1 | AO40: =M40+AA40 -> 0 | AP40: =N40+AB40 -> 0 | AQ40: =O40+AC40 -> 0 | AR40: =P40+AD40 -> 0 | AS40: =Q40+AE40 -> 0
B42: Inventories | D42: ='BionTech Standardized'!D33 -> 3.266 | E42: ='BionTech Standardized'!E33 -> 3.876 | F42: ='BionTech Standardized'!F33 -> 5.789 | G42: ='BionTech Standardized'!G33 -> 11.722 | H42: ='BionTech Standardized'!H33 -> 64.1 | I42: ='BionTech Standardized'!I33 -> 502.5 | J42: ='BionTech Standardized'!J33 -> 439.6 | K42: ='BionTech Standardized'!K33 -> 357.7 | AG42: =E42+T42 -> 3.876 | AH42: =F42+U42 -> 5.789 | AI42: =G42+V42 -> 11.722 | AJ42: =H42+W42 -> 64.1 | AK42: =I42+X42 -> 502.5 | AL42: =J42+Y42 -> 439.6 | AM42: =K42+Z42 -> 357.7 | AO42: =M42+AA42 -> 0 | AP42: =N42+AB42 -> 0 | AQ42: =O42+AC42 -> 0 | AR42: =P42+AD42 -> 0 | AS42: =Q42+AE42 -> 0
B43: Trade Receivables | D43: ='BionTech Standardized'!D32 -> 3.161 | E43: ='BionTech Standardized'!E32 -> 4.575 | F43: ='BionTech Standardized'!F32 -> 18.938 | G43: ='BionTech Standardized'!G32 -> 11.913 | H43: ='BionTech Standardized'!H32 -> 165.5 | I43: ='BionTech Standardized'!I32 -> 12381.7 | J43: ='BionTech Standardized'!J32 -> 7145.6 | K43: ='BionTech Standardized'!K32 -> 2155.7 | AG43: =E43+T43 -> 4.575 | AH43: =F43+U43 -> 18.938 | AI43: =G43+V43 -> 11.913 | AJ43: =H43+W43 -> 165.5 | AK43: =I43+X43 -> 12381.7 | AL43: =J43+Y43 -> 7145.6 | AM43: =K43+Z43 -> 2155.7 | AO43: =M43+AA43 -> 0 | AP43: =N43+AB43 -> 0 | AQ43: =O43+AC43 -> 0 | AR43: =P43+AD43 -> 0 | AS43: =Q43+AE43 -> 0
B44: Other Current Assets | D44: ='BionTech Standardized'!D34 -> 8.016 | E44: ='BionTech Standardized'!E34 -> 8.392 | F44: ='BionTech Standardized'!F34 -> 11.847 | G44: ='BionTech Standardized'!G34 -> 16.611 | H44: ='BionTech Standardized'!H34 -> 226.2 | I44: ='BionTech Standardized'!I34 -> 495 | J44: ='BionTech Standardized'!J34 -> 461.3 | K44: ='BionTech Standardized'!K34 -> 5171.1 | AG44: =E44+T44 -> 8.392 | AH44: =F44+U44 -> 11.847 | AI44: =G44+V44 -> 16.611 | AJ44: =H44+W44 -> 226.2 | AK44: =I44+X44 -> 495 | AL44: =J44+Y44 -> 461.3 | AM44: =K44+Z44 -> 5171.1 | AO44: =M44+AA44 -> 0 | AP44: =N44+AB44 -> 0 | AQ44: =O44+AC44 -> 0 | AR44: =P44+AD44 -> 0 | AS44: =Q44+AE44 -> 0
B45: Cash and Cash Equivalents | D45: ='BionTech Standardized'!D31 -> 303.68 | E45: ='BionTech Standardized'!E31 -> 172.106 | F45: ='BionTech Standardized'!F31 -> 411.495 | G45: ='BionTech Standardized'!G31 -> 519.149 | H45: ='BionTech Standardized'!H31 -> 1210.2 | I45: ='BionTech Standardized'!I31 -> 1692.7 | J45: ='BionTech Standardized'!J31 -> 13875.1 | K45: ='BionTech Standardized'!K31 -> 11663.7 | AG45: =E45+T45 -> 172.106 | AH45: =F45+U45 -> 411.495 | AI45: =G45+V45 -> 519.149 | AJ45: =H45+W45 -> 1210.2 | AK45: =I45+X45 -> 1692.7 | AL45: =J45+Y45 -> 13875.1 | AM45: =K45+Z45 -> 11663.7 | AO45: =M45+AA45 -> 0 | AP45: =N45+AB45 -> 0 | AQ45: =O45+AC45 -> 0 | AR45: =P45+AD45 -> 0 | AS45: =Q45+AE45 -> 0
B46: Total Current Assets | D46: =SUM(D42:D45) -> 318.123 | E46: =SUM(E42:E45) -> 188.949 | F46: =SUM(F42:F45) -> 448.069 | G46: =SUM(G42:G45) -> 559.395 | H46: =SUM(H42:H45) -> 1666 | I46: =SUM(I42:I45) -> 15071.9 | J46: =SUM(J42:J45) -> 21921.6 | K46: =SUM(K42:K45) -> 19348.2 | S46: =SUM(S42:S45) -> 0 | T46: =SUM(T42:T45) -> 0 | U46: =SUM(U42:U45) -> 0 | V46: =SUM(V42:V45) -> 0 | W46: =SUM(W42:W45) -> 0 | X46: =SUM(X42:X45) -> 0 | Y46: =SUM(Y42:Y45) -> 0 | Z46: =SUM(Z42:Z45) -> 0 | ... AE46: =SUM(AE42:AE45) -> 0 | AG46: =E46+T46 -> 188.949 | AH46: =F46+U46 -> 448.069 | AI46: =G46+V46 -> 559.395 | AJ46: =H46+W46 -> 1666 | AK46: =I46+X46 -> 15071.9 | AL46: =J46+Y46 -> 21921.6 | AM46: =K46+Z46 -> 19348.2 | AO46: =M46+AA46 -> 0 | AP46: =N46+AB46 -> 0 | AQ46: =O46+AC46 -> 0 | AR46: =P46+AD46 -> 0 | AS46: =Q46+AE46 -> 0
B49: Total Assets | D49: =SUM(D40,D46) -> 389.959 | E49: =SUM(E40,E46) -> 374.713 | F49: =SUM(F40,F46) -> 652.986 | G49: =SUM(G40,G46) -> 797.647 | H49: =SUM(H40,H46) -> 2318.6 | I49: =SUM(I40,I46) -> 15830.8 | J49: =SUM(J40,J46) -> 23279.1 | K49: =SUM(K40,K46) -> 23006.3 | S49: =SUM(S40,S46) -> 0 | T49: =SUM(T40,T46) -> 0 | U49: =SUM(U40,U46) -> 0 | V49: =SUM(V40,V46) -> 0 | W49: =SUM(W40,W46) -> 0 | X49: =SUM(X40,X46) -> 0 | Y49: =SUM(Y40,Y46) -> 0 | Z49: =SUM(Z40,Z46) -> 0 | ... AE49: =SUM(AE40,AE46) -> 0 | AG49: =E49+S49 -> 374.713 | AH49: =F49+T49 -> 652.986 | AI49: =G49+U49 -> 797.647 | AJ49: =H49+V49 -> 2318.6 | AK49: =I49+W49 -> 15830.8 | AL49: =J49+X49 -> 23279.1 | AM49: =K49+Y49 -> 23006.3 | AO49: =M49+AA49 -> 0 | AP49: =N49+AB49 -> 0 | AQ49: =O49+AC49 -> 0 | AR49: =P49+AD49 -> 0 | AS49: =Q49+AE49 -> 0
B51: LIABILITIES AND SHAREHOLDERS' EQUITY
B52: Ordinary Shareholders' Equity | D52: ='BionTech Standardized'!D50 -> 30.471 | E52: ='BionTech Standardized'!E50 -> -49.296 | F52: ='BionTech Standardized'!F50 -> 266.153 | G52: ='BionTech Standardized'!G50 -> 493.492 | H52: ='BionTech Standardized'!H50 -> 1371.8 | I52: ='BionTech Standardized'!I50 -> 11893.7 | J52: ='BionTech Standardized'!J50 -> 20055.6 | K52: ='BionTech Standardized'!K50 -> 20245.9 | AG52: =E52+S52 -> -49.296 | AH52: =F52+T52 -> 266.153 | AI52: =G52+U52 -> 493.492 | AJ52: =H52+V52 -> 1371.8 | AK52: =I52+W52 -> 11893.7 | AL52: =J52+X52 -> 20055.6 | AM52: =K52+Y52 -> 20245.9 | AO52: =M52+AA52 -> 0 | AP52: =N52+AB52 -> 0 | AQ52: =O52+AC52 -> 0 | AR52: =P52+AD52 -> 0 | AS52: =Q52+AE52 -> 0
B53: Preference Shares | D53: ='BionTech Standardized'!D51 -> 0 | E53: ='BionTech Standardized'!E51 -> 0 | F53: ='BionTech Standardized'!F51 -> 0 | G53: ='BionTech Standardized'!G51 -> 0 | H53: ='BionTech Standardized'!H51 -> 0 | I53: ='BionTech Standardized'!I51 -> 0 | J53: ='BionTech Standardized'!J51 -> 0 | K53: ='BionTech Standardized'!K51 -> 0 | AG53: =E53+S53 -> 0 | AH53: =F53+T53 -> 0 | AI53: =G53+U53 -> 0 | AJ53: =H53+V53 -> 0 | AK53: =I53+W53 -> 0 | AL53: =J53+X53 -> 0 | AM53: =K53+Y53 -> 0
B54: Non-Controlling Interest in Equity | D54: ='BionTech Standardized'!D49 -> 1.387 | E54: ='BionTech Standardized'!E49 -> 1.09 | F54: ='BionTech Standardized'!F49 -> 0.847 | G54: ='BionTech Standardized'!G49 -> 0 | H54: ='BionTech Standardized'!H49 -> 0 | I54: ='BionTech Standardized'!I49 -> 0 | J54: ='BionTech Standardized'!J49 -> 0 | K54: ='BionTech Standardized'!K49 -> 0 | AG54: =E54+S54 -> 1.09 | AH54: =F54+T54 -> 0.847 | AI54: =G54+U54 -> 0 | AJ54: =H54+V54 -> 0 | AK54: =I54+W54 -> 0 | AL54: =J54+X54 -> 0 | AM54: =K54+Y54 -> 0 | AO54: =M54+AA54 -> 0 | AP54: =N54+AB54 -> 0 | AQ54: =O54+AC54 -> 0 | AR54: =P54+AD54 -> 0 | AS54: =Q54+AE54 -> 0
AG55: =E55+S55 -> 0 | AH55: =F55+T55 -> 0 | AI55: =G55+U55 -> 0 | AJ55: =H55+V55 -> 0 | AK55: =I55+W55 -> 0 | AL55: =J55+X55 -> 0 | AM55: =K55+Y55 -> 0
AG56: =E56+S56 -> 0 | AH56: =F56+T56 -> 0 | AI56: =G56+U56 -> 0 | AJ56: =H56+V56 -> 0 | AK56: =I56+W56 -> 0 | AL56: =J56+X56 -> 0 | AM56: =K56+Y56 -> 0
B57: Non-Current Debt | D57: ='BionTech Standardized'!D46 -> 0 | E57: ='BionTech Standardized'!E46 -> 0 | F57: ='BionTech Standardized'!F46 -> 0 | G57: ='BionTech Standardized'!G46 -> 68.904 | H57: ='BionTech Standardized'!H46 -> 231 | I57: ='BionTech Standardized'!I46 -> 171.6 | J57: ='BionTech Standardized'!J46 -> 176.2 | K57: ='BionTech Standardized'!K46 -> 191 | AG57: =E57+S57 -> 0 | AH57: =F57+T57 -> 0 | AI57: =G57+U57 -> 68.904 | AJ57: =H57+V57 -> 231 | AK57: =I57+W57 -> 171.6 | AL57: =J57+X57 -> 176.2 | AM57: =K57+Y57 -> 191 | AO57: =M57+AA57 -> 0 | AP57: =N57+AB57 -> 0 | AQ57: =O57+AC57 -> 0 | AR57: =P57+AD57 -> 0 | AS57: =Q57+AE57 -> 0
B58: Deferred Tax Liability | D58: ='BionTech Standardized'!D47 -> 0 | E58: ='BionTech Standardized'!E47 -> 0 | F58: ='BionTech Standardized'!F47 -> 0 | G58: ='BionTech Standardized'!G47 -> 0 | H58: ='BionTech Standardized'!H47 -> 0.2 | I58: ='BionTech Standardized'!I47 -> 66.7 | J58: ='BionTech Standardized'!J47 -> 6.2 | K58: ='BionTech Standardized'!K47 -> 39.7 | AG58: =E58+S58 -> 0 | AH58: =F58+T58 -> 0 | AI58: =G58+U58 -> 0 | AJ58: =H58+V58 -> 0.2 | AK58: =I58+W58 -> 66.7 | AL58: =J58+X58 -> 6.2 | AM58: =K58+Y58 -> 39.7 | AO58: =M58+AA58 -> 0 | AP58: =N58+AB58 -> 0 | AQ58: =O58+AC58 -> 0 | AR58: =P58+AD58 -> 0 | AS58: =Q58+AE58 -> 0
B59: Other Non-Current Liabilities (non interest bearing) | D59: ='BionTech Standardized'!D48 -> 301.465 | E59: ='BionTech Standardized'!E48 -> 264.375 | F59: ='BionTech Standardized'!F48 -> 259.865 | G59: ='BionTech Standardized'!G48 -> 97.109 | H59: ='BionTech Standardized'!H48 -> 109.6 | I59: ='BionTech Standardized'!I48 -> 212.8 | J59: ='BionTech Standardized'!J48 -> 80.1 | K59: ='BionTech Standardized'!K48 -> 459.2 | AG59: =E59+S59 -> 264.375 | AH59: =F59+T59 -> 259.865 | AI59: =G59+U59 -> 97.109 | AJ59: =H59+V59 -> 109.6 | AK59: =I59+W59 -> 212.8 | AL59: =J59+X59 -> 80.1 | AM59: =K59+Y59 -> 459.2 | AO59: =M59+AA59 -> 0 | AP59: =N59+AB59 -> 0 | AQ59: =O59+AC59 -> 0 | AR59: =P59+AD59 -> 0 | AS59: =Q59+AE59 -> 0
B60: Non-Current Liabilities | D60: =SUM(D57:D59) -> 301.465 | E60: =SUM(E57:E59) -> 264.375 | F60: =SUM(F57:F59) -> 259.865 | G60: =SUM(G57:G59) -> 166.013 | H60: =SUM(H57:H59) -> 340.8 | I60: =SUM(I57:I59) -> 451.1 | J60: =SUM(J57:J59) -> 262.5 | K60: =SUM(K57:K59) -> 689.9 | ... Q60: =SUM(Q57:Q59) -> 0 | S60: =SUM(S57:S59) -> 0 | T60: =SUM(T57:T59) -> 0 | U60: =SUM(U57:U59) -> 0 | V60: =SUM(V57:V59) -> 0 | W60: =SUM(W57:W59) -> 0 | X60: =SUM(X57:X59) -> 0 | Y60: =SUM(Y57:Y59) -> 0 | Z60: =SUM(Z57:Z59) -> 0 | ... AE60: =SUM(AE57:AE59) -> 0 | AG60: =E60+S60 -> 264.375 | AH60: =F60+T60 -> 259.865 | AI60: =G60+U60 -> 166.013 | AJ60: =H60+V60 -> 340.8 | AK60: =I60+W60 -> 451.1 | AL60: =J60+X60 -> 262.5 | AM60: =K60+Y60 -> 689.9 | AO60: =M60+AA60 -> 0 | AP60: =N60+AB60 -> 0 | AQ60: =O60+AC60 -> 0 | AR60: =P60+AD60 -> 0 | AS60: =Q60+AE60 -> 0
AG61: =E61+S61 -> 0 | AH61: =F61+T61 -> 0 | AI61: =G61+U61 -> 0 | AJ61: =H61+V61 -> 0 | AK61: =I61+W61 -> 0 | AL61: =J61+X61 -> 0 | AM61: =K61+Y61 -> 0
B62: Trade Payables | D62: ='BionTech Standardized'!D44 -> 6.218 | E62: ='BionTech Standardized'!E44 -> 52.538 | F62: ='BionTech Standardized'!F44 -> 41.721 | G62: ='BionTech Standardized'!G44 -> 20.498 | H62: ='BionTech Standardized'!H44 -> 102.3 | I62: ='BionTech Standardized'!I44 -> 160 | J62: ='BionTech Standardized'!J44 -> 204.1 | K62: ='BionTech Standardized'!K44 -> 354 | AG62: =E62+S62 -> 52.538 | AH62: =F62+T62 -> 41.721 | AI62: =G62+U62 -> 20.498 | AJ62: =H62+V62 -> 102.3 | AK62: =I62+W62 -> 160 | AL62: =J62+X62 -> 204.1 | AM62: =K62+Y62 -> 354 | AO62: =M62+AA62 -> 0 | AP62: =N62+AB62 -> 0 | AQ62: =O62+AC62 -> 0 | AR62: =P62+AD62 -> 0 | AS62: =Q62+AE62 -> 0
B63: Other Current Liabilities | D63: ='BionTech Standardized'!D45 -> 50.418 | E63: ='BionTech Standardized'!E45 -> 106.006 | F63: ='BionTech Standardized'!F45 -> 84.4 | G63: ='BionTech Standardized'!G45 -> 112.337 | H63: ='BionTech Standardized'!H45 -> 494.6 | I63: ='BionTech Standardized'!I45 -> 3196.1 | J63: ='BionTech Standardized'!J45 -> 2720.9 | K63: ='BionTech Standardized'!K45 -> 1688.4 | AG63: =E63+S63 -> 106.006 | AH63: =F63+T63 -> 84.4 | AI63: =G63+U63 -> 112.337 | AJ63: =H63+V63 -> 494.6 | AK63: =I63+W63 -> 3196.1 | AL63: =J63+X63 -> 2720.9 | AM63: =K63+Y63 -> 1688.4 | AO63: =M63+AA63 -> 0 | AP63: =N63+AB63 -> 0 | AQ63: =O63+AC63 -> 0 | AR63: =P63+AD63 -> 0 | AS63: =Q63+AE63 -> 0
B64: Current Debt | D64: ='BionTech Standardized'!D43 -> 0 | E64: ='BionTech Standardized'!E43 -> 0 | F64: ='BionTech Standardized'!F43 -> 0 | G64: ='BionTech Standardized'!G43 -> 5.307 | H64: ='BionTech Standardized'!H43 -> 9.1 | I64: ='BionTech Standardized'!I43 -> 129.9 | J64: ='BionTech Standardized'!J43 -> 36 | K64: ='BionTech Standardized'!K43 -> 28.1 | AG64: =E64+S64 -> 0 | AH64: =F64+T64 -> 0 | AI64: =G64+U64 -> 5.307 | AJ64: =H64+V64 -> 9.1 | AK64: =I64+W64 -> 129.9 | AL64: =J64+X64 -> 36 | AM64: =K64+Y64 -> 28.1 | AO64: =M64+AA64 -> 0 | AP64: =N64+AB64 -> 0 | AQ64: =O64+AC64 -> 0 | AR64: =P64+AD64 -> 0 | AS64: =Q64+AE64 -> 0
B65: Current Liabilities | D65: =SUM(D62:D64) -> 56.636 | E65: =SUM(E62:E64) -> 158.544 | F65: =SUM(F62:F64) -> 126.121 | G65: =SUM(G62:G64) -> 138.142 | H65: =SUM(H62:H64) -> 606 | I65: =SUM(I62:I64) -> 3486 | J65: =SUM(J62:J64) -> 2961 | K65: =SUM(K62:K64) -> 2070.5 | ... Q65: =SUM(Q62:Q64) -> 0 | S65: =SUM(S62:S64) -> 0 | T65: =SUM(T62:T64) -> 0 | U65: =SUM(U62:U64) -> 0 | V65: =SUM(V62:V64) -> 0 | W65: =SUM(W62:W64) -> 0 | X65: =SUM(X62:X64) -> 0 | Y65: =SUM(Y62:Y64) -> 0 | Z65: =SUM(Z62:Z64) -> 0 | ... AE65: =SUM(AE62:AE64) -> 0 | AG65: =E65+S65 -> 158.544 | AH65: =F65+T65 -> 126.121 | AI65: =G65+U65 -> 138.142 | AJ65: =H65+V65 -> 606 | AK65: =I65+W65 -> 3486 | AL65: =J65+X65 -> 2961 | AM65: =K65+Y65 -> 2070.5 | AO65: =M65+AA65 -> 0 | AP65: =N65+AB65 -> 0 | AQ65: =O65+AC65 -> 0 | AR65: =P65+AD65 -> 0 | AS65: =Q65+AE65 -> 0
AG67: =E67+S67 -> 0 | AH67: =F67+T67 -> 0 | AI67: =G67+U67 -> 0 | AJ67: =H67+V67 -> 0 | AK67: =I67+W67 -> 0 | AL67: =J67+X67 -> 0 | AM67: =K67+Y67 -> 0
B68: Total Liabilities and Shareholders' Equity | D68: =SUM(D52:D54,D60,D65) -> 389.959 | E68: =SUM(E52:E54,E60,E65) -> 374.713 | F68: =SUM(F52:F54,F60,F65) -> 652.986 | G68: =SUM(G52:G54,G60,G65) -> 797.647 | H68: =SUM(H52:H54,H60,H65) -> 2318.6 | I68: =SUM(I52:I54,I60,I65) -> 15830.8 | J68: =SUM(J52:J54,J60,J65) -> 23279.1 | K68: =SUM(K52:K54,K60,K65) -> 23006.3 | AG68: =E68+S68 -> 374.713 | AH68: =F68+T68 -> 652.986 | AI68: =G68+U68 -> 797.647 | AJ68: =H68+V68 -> 2318.6 | AK68: =I68+W68 -> 15830.8 | AL68: =J68+X68 -> 23279.1 | AM68: =K68+Y68 -> 23006.3 | AO68: =M68+AA68 -> 0 | AP68: =N68+AB68 -> 0 | AQ68: =O68+AC68 -> 0 | AR68: =P68+AD68 -> 0 | AS68: =Q68+AE68 -> 0
B69: Check | D69: =D49-D68 -> 0 | E69: =E49-E68 -> 0 | F69: =F49-F68 -> 0 | G69: =G49-G68 -> 0 | H69: =H49-H68 -> 0 | I69: =I49-I68 -> 0 | J69: =J49-J68 -> 0 | K69: =K49-K68 -> 0 | L69: =L68-L49 -> 0 | M69: =M68-M49 -> 0 | N69: =N68-N49 -> 0 | O69: =O68-O49 -> 0 | P69: =P68-P49 -> 0 | Q69: =Q68-Q49 -> 0
A70: x | B70: CASH FLOW STATEMENT
B71: Profit Before Interest and Tax | E71: ='BionTech Standardized'!E56 -> -87.985 | F71: ='BionTech Standardized'!F56 -> -49.61 | G71: ='BionTech Standardized'!G56 -> -179.2 | H71: ='BionTech Standardized'!H56 -> -125.1 | I71: ='BionTech Standardized'!I56 -> 15347.9 | J71: ='BionTech Standardized'!J56 -> 12707.7 | K71: ='BionTech Standardized'!K56 -> 674.4 | AG71: =E71+S71 -> -87.985 | AH71: =F71+T71 -> -49.61 | AI71: =G71+U71 -> -179.2 | AJ71: =H71+V71 -> -125.1 | AK71: =I71+W71 -> 15347.9 | AL71: =J71+X71 -> 12707.7 | AM71: =K71+Y71 -> 674.4 | AN71: =L71+Z71 -> 0 | ... AS71: =Q71+AE71 -> 0
B72: Taxes Paid | E72: ='BionTech Standardized'!E60 -> -0.045 | F72: ='BionTech Standardized'!F60 -> -0.304 | G72: ='BionTech Standardized'!G60 -> 0.2 | H72: ='BionTech Standardized'!H60 -> 0.5 | I72: ='BionTech Standardized'!I60 -> -3457.9 | J72: ='BionTech Standardized'!J60 -> -4222.1 | K72: ='BionTech Standardized'!K60 -> -482.9 | AG72: =E72+S72 -> -0.045 | AH72: =F72+T72 -> -0.304 | AI72: =G72+U72 -> 0.2 | AJ72: =H72+V72 -> 0.5 | AK72: =I72+W72 -> -3457.9 | AL72: =J72+X72 -> -4222.1 | AM72: =K72+Y72 -> -482.9 | AN72: =L72+Z72 -> 0 | ... AS72: =Q72+AE72 -> 0
B73: Non-Operating Losses (Gains) | E73: ='BionTech Standardized'!E58 -> 24.913 | F73: ='BionTech Standardized'!F58 -> 0.529 | G73: ='BionTech Standardized'!G58 -> 0.6 | H73: ='BionTech Standardized'!H58 -> 135.6 | I73: ='BionTech Standardized'!I58 -> -414.6 | J73: ='BionTech Standardized'!J58 -> 385.4 | K73: ='BionTech Standardized'!K58 -> -116.3 | AG73: =E73+S73 -> 24.913 | AH73: =F73+T73 -> 0.529 | AI73: =G73+U73 -> 0.6 | AJ73: =H73+V73 -> 135.6 | AK73: =I73+W73 -> -414.6 | AL73: =J73+X73 -> 385.4 | AM73: =K73+Y73 -> -116.3 | AN73: =L73+Z73 -> 0 | ... AS73: =Q73+AE73 -> 0
B74: Non-Current Operating Accruals | E74: ='BionTech Standardized'!E59 -> 16.439 | F74: ='BionTech Standardized'!F59 -> 29.625 | G74: ='BionTech Standardized'!G59 -> 64.1 | H74: ='BionTech Standardized'!H59 -> 70.8 | I74: ='BionTech Standardized'!I59 -> 155.7 | J74: ='BionTech Standardized'!J59 -> 180.1 | K74: ='BionTech Standardized'!K59 -> -531.4 | AG74: =E74+S74 -> 16.439 | AH74: =F74+T74 -> 29.625 | AI74: =G74+U74 -> 64.1 | AJ74: =H74+V74 -> 70.8 | AK74: =I74+W74 -> 155.7 | AL74: =J74+X74 -> 180.1 | AM74: =K74+Y74 -> -531.4 | AN74: =L74+Z74 -> 0 | ... AS74: =Q74+AE74 -> 0
B75: Operating Cash Flow before Working Capital Investments | E75: =SUM(E71:E74) -> -46.678 | F75: =SUM(F71:F74) -> -19.76 | G75: =SUM(G71:G74) -> -114.3 | H75: =SUM(H71:H74) -> 81.8 | I75: =SUM(I71:I74) -> 11631.1 | J75: =SUM(J71:J74) -> 9051.1 | K75: =SUM(K71:K74) -> -456.2 | L75: =SUM(L71:L74) -> 0 | ... Q75: =SUM(Q71:Q74) -> 0 | S75: =SUM(S71:S74) -> 0 | T75: =SUM(T71:T74) -> 0 | U75: =SUM(U71:U74) -> 0 | V75: =SUM(V71:V74) -> 0 | W75: =SUM(W71:W74) -> 0 | X75: =SUM(X71:X74) -> 0 | Y75: =SUM(Y71:Y74) -> 0 | Z75: =SUM(Z71:Z74) -> 0 | ... AE75: =SUM(AE71:AE74) -> 0 | AG75: =E75+S75 -> -46.678 | AH75: =F75+T75 -> -19.76 | AI75: =G75+U75 -> -114.3 | AJ75: =H75+V75 -> 81.8 | AK75: =I75+W75 -> 11631.1 | AL75: =J75+X75 -> 9051.1 | AM75: =K75+Y75 -> -456.2 | AN75: =L75+Z75 -> 0 | ... AS75: =Q75+AE75 -> 0
B77: Net (Investments in) or Liquidation of Operating Working Capital | E77: ='BionTech Standardized'!E63 -> -7.964 | F77: ='BionTech Standardized'!F63 -> -41.065 | G77: ='BionTech Standardized'!G63 -> -83.5 | H77: ='BionTech Standardized'!H63 -> -93.1 | I77: ='BionTech Standardized'!I63 -> -10730.4 | J77: ='BionTech Standardized'!J63 -> 4518.5 | K77: ='BionTech Standardized'!K63 -> 5574.8 | AG77: =E77+S77 -> -7.964 | AH77: =F77+T77 -> -41.065 | AI77: =G77+U77 -> -83.5 | AJ77: =H77+V77 -> -93.1 | AK77: =I77+W77 -> -10730.4 | AL77: =J77+X77 -> 4518.5 | AM77: =K77+Y77 -> 5574.8 | AN77: =L77+Z77 -> 0 | ... AS77: =Q77+AE77 -> 0
B78: Operating Cash Flow before Investment in Non-Current Assets | E78: =SUM(E77,E75) -> -54.642 | F78: =SUM(F77,F75) -> -60.825 | G78: =SUM(G77,G75) -> -197.8 | H78: =SUM(H77,H75) -> -11.3 | I78: =SUM(I77,I75) -> 900.7 | J78: =SUM(J77,J75) -> 13569.6 | K78: =SUM(K77,K75) -> 5118.6 | L78: =SUM(L75:L77) -> 0 | M78: =SUM(M75:M77) -> 0 | N78: =SUM(N75:N77) -> 0 | O78: =SUM(O75:O77) -> 0 | P78: =SUM(P75:P77) -> 0 | Q78: =SUM(Q75:Q77) -> 0 | S78: =SUM(S75:S77) -> 0 | T78: =SUM(T75:T77) -> 0 | U78: =SUM(U75:U77) -> 0 | V78: =SUM(V75:V77) -> 0 | W78: =SUM(W75:W77) -> 0 | X78: =SUM(X75:X77) -> 0 | Y78: =SUM(Y75:Y77) -> 0 | Z78: =SUM(Z75:Z77) -> 0 | ... AE78: =SUM(AE75:AE77) -> 0 | AG78: =E78+S78 -> -54.642 | AH78: =F78+T78 -> -60.825 | AI78: =G78+U78 -> -197.8 | AJ78: =H78+V78 -> -11.3 | AK78: =I78+W78 -> 900.7 | AL78: =J78+X78 -> 13569.6 | AM78: =K78+Y78 -> 5118.6 | AN78: =L78+Z78 -> 0 | ... AS78: =Q78+AE78 -> 0
B80: Interest Received | E80: ='BionTech Standardized'!E61 -> 2.133 | F80: ='BionTech Standardized'!F61 -> 1.996 | G80: ='BionTech Standardized'!G61 -> 0.0013 | H80: ='BionTech Standardized'!H61 -> 1.4 | I80: ='BionTech Standardized'!I61 -> 1.2 | J80: ='BionTech Standardized'!J61 -> 29.3 | K80: ='BionTech Standardized'!K61 -> 258.2 | AG80: =E80+S80 -> 2.133 | AH80: =F80+T80 -> 1.996 | AI80: =G80+U80 -> 0.0013 | AJ80: =H80+V80 -> 1.4 | AK80: =I80+W80 -> 1.2 | AL80: =J80+X80 -> 29.3 | AM80: =K80+Y80 -> 258.2 | AN80: =L80+Z80 -> 0 | ... AS80: =Q80+AE80 -> 0
B81: Dividends received | E81: ='BionTech Standardized'!E62 -> 0 | F81: ='BionTech Standardized'!F62 -> 0 | G81: ='BionTech Standardized'!G62 -> 0 | H81: ='BionTech Standardized'!H62 -> 0 | I81: ='BionTech Standardized'!I62 -> 0 | J81: ='BionTech Standardized'!J62 -> 0 | K81: ='BionTech Standardized'!K62 -> 0 | AG81: =E81+S81 -> 0 | AH81: =F81+T81 -> 0 | AI81: =G81+U81 -> 0 | AJ81: =H81+V81 -> 0 | AK81: =I81+W81 -> 0 | AL81: =J81+X81 -> 0 | AM81: =K81+Y81 -> 0 | AN81: =L81+Z81 -> 0 | ... AS81: =Q81+AE81 -> 0
B82: Net (Investments in) or Liquidation of Non-Current Operating or Investment Assets | E82: ='BionTech Standardized'!E64 -> -52.549 | F82: ='BionTech Standardized'!F64 -> -66.452 | G82: ='BionTech Standardized'!G64 -> -77.2 | H82: ='BionTech Standardized'!H64 -> -144.8 | I82: ='BionTech Standardized'!I64 -> -566.1 | J82: ='BionTech Standardized'!J64 -> -35.3 | K82: ='BionTech Standardized'!K64 -> -6954.5 | AG82: =E82+S82 -> -52.549 | AH82: =F82+T82 -> -66.452 | AI82: =G82+U82 -> -77.2 | AJ82: =H82+V82 -> -144.8 | AK82: =I82+W82 -> -566.1 | AL82: =J82+X82 -> -35.3 | AM82: =K82+Y82 -> -6954.5 | AN82: =L82+Z82 -> 0 | ... AS82: =Q82+AE82 -> 0
B83: Free Cash Flow Available to Debt and Equity | E83: =SUM(E80:E82,E78) -> -105.058 | F83: =SUM(F80:F82,F78) -> -125.281 | G83: =SUM(G80:G82,G78) -> -274.9987 | H83: =SUM(H80:H82,H78) -> -154.7 | I83: =SUM(I80:I82,I78) -> 335.8 | J83: =SUM(J80:J82,J78) -> 13563.6 | K83: =SUM(K80:K82,K78) -> -1577.7 | L83: =SUM(L78:L82) -> 0 | M83: =SUM(M78:M82) -> 0 | N83: =SUM(N78:N82) -> 0 | O83: =SUM(O78:O82) -> 0 | P83: =SUM(P78:P82) -> 0 | Q83: =SUM(Q78:Q82) -> 0 | S83: =SUM(S78:S82) -> 0 | T83: =SUM(T78:T82) -> 0 | U83: =SUM(U78:U82) -> 0 | V83: =SUM(V78:V82) -> 0 | W83: =SUM(W78:W82) -> 0 | X83: =SUM(X78:X82) -> 0 | Y83: =SUM(Y78:Y82) -> 0 | Z83: =SUM(Z78:Z82) -> 0 | ... AE83: =SUM(AE78:AE82) -> 0 | AG83: =E83+S83 -> -105.058 | AH83: =F83+T83 -> -125.281 | AI83: =G83+U83 -> -274.9987 | AJ83: =H83+V83 -> -154.7 | AK83: =I83+W83 -> 335.8 | AL83: =J83+X83 -> 13563.6 | AM83: =K83+Y83 -> -1577.7 | AN83: =L83+Z83 -> 0 | ... AS83: =Q83+AE83 -> 0
B85: Interest Paid | E85: ='BionTech Standardized'!E68 -> -0.053 | F85: ='BionTech Standardized'!F68 -> -0.048 | G85: ='BionTech Standardized'!G68 -> -0.002 | H85: ='BionTech Standardized'!H68 -> -3.6 | I85: ='BionTech Standardized'!I68 -> -12.2 | J85: ='BionTech Standardized'!J68 -> -21.5 | K85: ='BionTech Standardized'!K68 -> -5.4 | S85: =S14*E103 -> 0 | T85: =T14*F103 -> 0 | U85: =U14*G103 -> 0 | V85: =V14*H103 -> 0 | W85: =W14*I103 -> 0 | X85: =X14*J103 -> 0 | Y85: =Y14*K103 -> 0 | Z85: =Z14*L103 -> 0 | ... AE85: =AE14*Q103 -> 0 | AG85: =E85+S85 -> -0.053 | AH85: =F85+T85 -> -0.048 | AI85: =G85+U85 -> -0.002 | AJ85: =H85+V85 -> -3.6 | AK85: =I85+W85 -> -12.2 | AL85: =J85+X85 -> -21.5 | AM85: =K85+Y85 -> -5.4 | AN85: =L85+Z85 -> 0 | ... AS85: =Q85+AE85 -> 0
B86: Net Debt (Repayment) or Issuance | E86: ='BionTech Standardized'!E67 -> -1.643 | F86: ='BionTech Standardized'!F67 -> 3.452 | G86: ='BionTech Standardized'!G67 -> 7.9 | H86: ='BionTech Standardized'!H67 -> 141.7 | I86: ='BionTech Standardized'!I67 -> -66.7 | J86: ='BionTech Standardized'!J67 -> -59.1 | K86: ='BionTech Standardized'!K67 -> -40.1 | S86: =-S74-S82 -> 0 | T86: =-T74-T82 -> 0 | U86: =-U74-U82 -> 0 | V86: =-V74-V82 -> 0 | W86: =-W74-W82 -> 0 | X86: =-X74-X82 -> 0 | Y86: =-Y74-Y82 -> 0 | Z86: =-Z74-Z82 -> 0 | ... AE86: =-AE74-AE82 -> 0 | AG86: =E86+S86 -> -1.643 | AH86: =F86+T86 -> 3.452 | AI86: =G86+U86 -> 7.9 | AJ86: =H86+V86 -> 141.7 | AK86: =I86+W86 -> -66.7 | AL86: =J86+X86 -> -59.1 | AM86: =K86+Y86 -> -40.1 | AN86: =L86+Z86 -> 0 | ... AS86: =Q86+AE86 -> 0
B87: Free Cash Flow Available to Equity | E87: =SUM(E85:E86,E83) -> -106.754 | F87: =SUM(F85:F86,F83) -> -121.877 | G87: =SUM(G85:G86,G83) -> -267.1007 | H87: =SUM(H85:H86,H83) -> -16.6 | I87: =SUM(I85:I86,I83) -> 256.9 | J87: =SUM(J85:J86,J83) -> 13483 | K87: =SUM(K85:K86,K83) -> -1623.2 | L87: =SUM(L83:L86) -> 0 | M87: =SUM(M83:M86) -> 0 | N87: =SUM(N83:N86) -> 0 | O87: =SUM(O83:O86) -> 0 | P87: =SUM(P83:P86) -> 0 | Q87: =SUM(Q83:Q86) -> 0 | S87: =SUM(S83:S86) -> 0 | T87: =SUM(T83:T86) -> 0 | U87: =SUM(U83:U86) -> 0 | V87: =SUM(V83:V86) -> 0 | W87: =SUM(W83:W86) -> 0 | X87: =SUM(X83:X86) -> 0 | Y87: =SUM(Y83:Y86) -> 0 | Z87: =SUM(Z83:Z86) -> 0 | ... AE87: =SUM(AE83:AE86) -> 0 | AG87: =E87+S87 -> -106.754 | AH87: =F87+T87 -> -121.877 | AI87: =G87+U87 -> -267.1007 | AJ87: =H87+V87 -> -16.6 | AK87: =I87+W87 -> 256.9 | AL87: =J87+X87 -> 13483 | AM87: =K87+Y87 -> -1623.2 | AN87: =L87+Z87 -> 0 | ... AS87: =Q87+AE87 -> 0
B89: Dividend (Payments) | E89: ='BionTech Standardized'!E69 -> 0 | F89: ='BionTech Standardized'!F69 -> 0 | G89: ='BionTech Standardized'!G69 -> 0 | H89: ='BionTech Standardized'!H69 -> 0 | I89: ='BionTech Standardized'!I69 -> 0 | J89: ='BionTech Standardized'!J69 -> -484.3 | K89: ='BionTech Standardized'!K69 -> 0 | AG89: =E89+S89 -> 0 | AH89: =F89+T89 -> 0 | AI89: =G89+U89 -> 0 | AJ89: =H89+V89 -> 0 | AK89: =I89+W89 -> 0 | AL89: =J89+X89 -> -484.3 | AM89: =K89+Y89 -> 0 | AN89: =L89+Z89 -> 0 | ... AS89: =Q89+AE89 -> 0
B90: Net share (Repurchase) or Issuance | E90: ='BionTech Standardized'!E70 -> 0 | F90: ='BionTech Standardized'!F70 -> 361.725 | G90: ='BionTech Standardized'!G70 -> 375.4 | H90: ='BionTech Standardized'!H70 -> 753 | I90: ='BionTech Standardized'!I70 -> 160.9 | J90: ='BionTech Standardized'!J70 -> -875.9 | K90: ='BionTech Standardized'!K70 -> -738.5 | AG90: =E90+S90 -> 0 | AH90: =F90+T90 -> 361.725 | AI90: =G90+U90 -> 375.4 | AJ90: =H90+V90 -> 753 | AK90: =I90+W90 -> 160.9 | AL90: =J90+X90 -> -875.9 | AM90: =K90+Y90 -> -738.5 | AN90: =L90+Z90 -> 0 | ... AS90: =Q90+AE90 -> 0
B91: Misc. Cash Flow & Exchange rate | E91: ='BionTech Standardized'!E71 -> -24.819 | F91: ='BionTech Standardized'!F71 -> -0.459 | G91: ='BionTech Standardized'!G71 -> 0 | H91: ='BionTech Standardized'!H71 -> -45.3 | I91: ='BionTech Standardized'!I71 -> 64.7 | J91: ='BionTech Standardized'!J71 -> 59.6 | K91: ='BionTech Standardized'!K71 -> 150.3
B92: Net Increase (Decrease) in Cash Balance | E92: =SUM(E87,E91) -> -131.573 | F92: =SUM(F87,F91) -> -122.336 | G92: =SUM(G87,G91) -> -267.1007 | H92: =SUM(H87,H91) -> -61.9 | I92: =SUM(I87,I91) -> 321.6 | J92: =SUM(J87,J91) -> 13542.6 | K92: =SUM(K87,K91) -> -1472.9 | L92: =SUM(L87:L90) -> 0 | M92: =SUM(M87:M90) -> 0 | N92: =SUM(N87:N90) -> 0 | O92: =SUM(O87:O90) -> 0 | P92: =SUM(P87:P90) -> 0 | Q92: =SUM(Q87:Q90) -> 0 | S92: =SUM(S87:S90) -> 0 | T92: =SUM(T87:T90) -> 0 | U92: =SUM(U87:U90) -> 0 | V92: =SUM(V87:V90) -> 0 | W92: =SUM(W87:W90) -> 0 | X92: =SUM(X87:X90) -> 0 | Y92: =SUM(Y87:Y90) -> 0 | Z92: =SUM(Z87:Z90) -> 0 | ... AE92: =SUM(AE87:AE90) -> 0 | AG92: =E92+S92 -> -131.573 | AH92: =F92+T92 -> -122.336 | AI92: =G92+U92 -> -267.1007 | AJ92: =H92+V92 -> -61.9 | AK92: =I92+W92 -> 321.6 | AL92: =J92+X92 -> 13542.6 | AM92: =K92+Y92 -> -1472.9 | AN92: =L92+Z92 -> 0 | ... AS92: =Q92+AE92 -> 0
A94: x | B94: CONDENSED STATEMENTS OF EARNINGS
B95: Revenue | D95: =D8 -> 0 | E95: =E8 -> 61.598 | F95: =F8 -> 127.575 | G95: =G8 -> 108.6 | H95: =H8 -> 482.3 | I95: =I8 -> 18976.7 | J95: =J8 -> 17310.6 | K95: =K8 -> 3819 | ... AE95: =AE8 -> 0 | AG95: =AG8 -> 61.598 | AH95: =AH8 -> 127.575 | AI95: =AI8 -> 108.6 | AJ95: =AJ8 -> 482.3 | AK95: =AK8 -> 18976.7 | AL95: =AL8 -> 17310.6 | AM95: =AM8 -> 3819
B96: Net operating profit after tax | D96: =D100 -> 0 | E96: =E100 -> -78.31494 | F96: =F100 -> -50.18221 | G96: =G100 -> -179.851 | H96: =H100 -> 34.854 | I96: =I100 -> 10366.094 | J96: =J100 -> 9337.866 | K96: =K100 -> 776.633 | ... AE96: =AE100 -> 0 | AG96: =AG100 -> -85.949 | AH96: =AH100 -> -48.263 | AI96: =AI100 -> -179.2 | AJ96: =AJ100 -> 15.2 | AK96: =AK100 -> 10292.5 | AL96: =AL100 -> 9434.4 | AM96: =AM100 -> 930.3 | AN96: =AN100 -> 0 | ... AS96: =AS100 -> 0
B97: Profit or loss | D97: =D17 -> 0 | E97: =E17 -> -85.949 | F97: =F17 -> -48.263 | G97: =G17 -> -179.2 | H97: =H17 -> 15.2 | I97: =I17 -> 10292.5 | J97: =J17 -> 9434.4 | K97: =K17 -> 930.3 | ... AE97: =AE17 -> 0 | AG97: =AG17 -> -85.949 | AH97: =AH17 -> -48.263 | AI97: =AI17 -> -179.2 | AJ97: =AJ17 -> 15.2 | AK97: =AK17 -> 10292.5 | AL97: =AL17 -> 9434.4 | AM97: =AM17 -> 930.3 | AN97: =AN17 -> 0 | ... AS97: =AS17 -> 0
B98: – Investment profit after tax | D98: =-D105 -> 0 | E98: =-E105 -> -0.66123 | F98: =-F105 -> -2.49426 | G98: =-G105 -> -1.271 | H98: =-H105 -> -0.496 | I98: =-I105 -> -20.987 | J98: =-J105 -> -102.393 | K98: =-K105 -> -161.076 | ... AE98: =-AE105 -> 0 | AG98: =-AG105 -> 0 | AH98: =-AH105 -> 0 | AI98: =-AI105 -> 0 | AJ98: =-AJ105 -> 0 | AK98: =-AK105 -> 0 | AL98: =-AL105 -> 0 | AM98: =-AM105 -> 0 | AN98: =-AN105 -> 0 | ... AS98: =-AS105 -> 0
B99: + Interest expense after tax | D99: =D109 -> 0 | E99: =E109 -> 8.29529 | F99: =F109 -> 0.57505 | G99: =G109 -> 0.62 | H99: =H109 -> 20.15 | I99: =I109 -> 94.581 | J99: =J109 -> 5.859 | K99: =K109 -> 7.409 | ... AE99: =AE109 -> 0 | AG99: =AG109 -> 0 | AH99: =AH109 -> 0 | AI99: =AI109 -> 0 | AJ99: =AJ109 -> 0 | AK99: =AK109 -> 0 | AL99: =AL109 -> 0 | AM99: =AM109 -> 0 | AN99: =AN109 -> 0 | ... AS99: =AS109 -> 0
B100: = Net operating profit after tax | D100: =SUM(D97:D99) -> 0 | E100: =SUM(E97:E99) -> -78.31494 | F100: =SUM(F97:F99) -> -50.18221 | G100: =SUM(G97:G99) -> -179.851 | H100: =SUM(H97:H99) -> 34.854 | I100: =SUM(I97:I99) -> 10366.094 | J100: =SUM(J97:J99) -> 9337.866 | K100: =SUM(K97:K99) -> 776.633 | ... AE100: =SUM(AE97:AE99) -> 0 | AG100: =SUM(AG97:AG99) -> -85.949 | AH100: =SUM(AH97:AH99) -> -48.263 | AI100: =SUM(AI97:AI99) -> -179.2 | AJ100: =SUM(AJ97:AJ99) -> 15.2 | AK100: =SUM(AK97:AK99) -> 10292.5 | AL100: =SUM(AL97:AL99) -> 9434.4 | AM100: =SUM(AM97:AM99) -> 930.3 | AN100: =SUM(AN97:AN99) -> 0 | ... AS100: =SUM(AS97:AS99) -> 0
B101: of which: Net non-recurring expense after tax | D101: =D104 -> 0 | E101: =E104 -> 0 | F101: =F104 -> 0 | G101: =G104 -> 0 | H101: =H104 -> 0 | I101: =I104 -> 0 | J101: =J104 -> 0 | K101: =K104 -> 0 | ... AE101: =AE104 -> 0 | AG101: =AG104 -> 0 | AH101: =AH104 -> 0 | AI101: =AI104 -> 0 | AJ101: =AJ104 -> 0 | AK101: =AK104 -> 0 | AL101: =AL104 -> 0 | AM101: =AM104 -> 0 | AN101: =AN104 -> 0 | ... AS101: =AS104 -> 0
B102: = Net non-recurring expense (income) | D102: =-D12 -> 0 | E102: =-E12 -> 0 | F102: =-F12 -> 0 | G102: =-G12 -> 0 | H102: =-H12 -> 0 | I102: =-I12 -> 0 | J102: =-J12 -> 0 | K102: =-K12 -> 0 | ... AE102: =-AE12 -> 0 | AG102: =-AG12 -> 0 | AH102: =-AH12 -> 0 | AI102: =-AI12 -> 0 | AJ102: =-AJ12 -> 0 | AK102: =-AK12 -> 0 | AL102: =-AL12 -> 0 | AM102: =-AM12 -> 0 | AN102: =-AN12 -> 0 | ... AS102: =-AS12 -> 0
B103: x (1 – Tax rate) | E103: =$D$4 -> 0.31 | F103: =$D$4 -> 0.31 | G103: =$D$4 -> 0.31 | H103: =$D$4 -> 0.31 | I103: =$D$4 -> 0.31 | J103: =$D$4 -> 0.31 | K103: =$D$4 -> 0.31
B104: = Net non-recurring expense after tax | D104: =D103*D102 -> 0 | E104: =E103*E102 -> 0 | F104: =F103*F102 -> 0 | G104: =G103*G102 -> 0 | H104: =H103*H102 -> 0 | I104: =I103*I102 -> 0 | J104: =J103*J102 -> 0 | K104: =K103*K102 -> 0 | ... AE104: =AE103*AE102 -> 0 | AG104: =AG103*AG102 -> 0 | AH104: =AH103*AH102 -> 0 | AI104: =AI103*AI102 -> 0 | AJ104: =AJ103*AJ102 -> 0 | AK104: =AK103*AK102 -> 0 | AL104: =AL103*AL102 -> 0 | AM104: =AM103*AM102 -> 0 | AN104: =AN103*AN102 -> 0 | ... AS104: =AS103*AS102 -> 0
B105: + Net investment profit after tax | D105: =D108 -> 0 | E105: =E108 -> 0.66123 | F105: =F108 -> 2.49426 | G105: =G108 -> 1.271 | H105: =H108 -> 0.496 | I105: =I108 -> 20.987 | J105: =J108 -> 102.393 | K105: =K108 -> 161.076 | ... AE105: =AE108 -> 0 | AG105: =AG108 -> 0 | AH105: =AH108 -> 0 | AI105: =AI108 -> 0 | AJ105: =AJ108 -> 0 | AK105: =AK108 -> 0 | AL105: =AL108 -> 0 | AM105: =AM108 -> 0 | AN105: =AN108 -> 0 | ... AS105: =AS108 -> 0
B106: = Investment and interest income | D106: =D11+D13 -> 0 | E106: =E11+E13 -> 2.133 | F106: =F11+F13 -> 8.046 | G106: =G11+G13 -> 4.1 | H106: =H11+H13 -> 1.6 | I106: =I11+I13 -> 67.7 | J106: =J11+J13 -> 330.3 | K106: =K11+K13 -> 519.6 | ... AE106: =AE11+AE13 -> 0 | AG106: =AG11+AG13 -> 2.133 | AH106: =AH11+AH13 -> 8.046 | AI106: =AI11+AI13 -> 4.1 | AJ106: =AJ11+AJ13 -> 1.6 | AK106: =AK11+AK13 -> 67.7 | AL106: =AL11+AL13 -> 330.3 | AM106: =AM11+AM13 -> 519.6 | AN106: =AN11+AN13 -> 0 | ... AS106: =AS11+AS13 -> 0
B107: x (1 – Tax rate) | E107: =$D$4 -> 0.31 | F107: =$D$4 -> 0.31 | G107: =$D$4 -> 0.31 | H107: =$D$4 -> 0.31 | I107: =$D$4 -> 0.31 | J107: =$D$4 -> 0.31 | K107: =$D$4 -> 0.31
B108: = Net investment profit after tax | D108: =D107*D106 -> 0 | E108: =E107*E106 -> 0.66123 | F108: =F107*F106 -> 2.49426 | G108: =G107*G106 -> 1.271 | H108: =H107*H106 -> 0.496 | I108: =I107*I106 -> 20.987 | J108: =J107*J106 -> 102.393 | K108: =K107*K106 -> 161.076 | ... AE108: =AE107*AE106 -> 0 | AG108: =AG107*AG106 -> 0 | AH108: =AH107*AH106 -> 0 | AI108: =AI107*AI106 -> 0 | AJ108: =AJ107*AJ106 -> 0 | AK108: =AK107*AK106 -> 0 | AL108: =AL107*AL106 -> 0 | AM108: =AM107*AM106 -> 0 | AN108: =AN107*AN106 -> 0 | ... AS108: =AS107*AS106 -> 0
B109: – Interest expense after tax | D109: =D112 -> 0 | E109: =E112 -> 8.29529 | F109: =F112 -> 0.57505 | G109: =G112 -> 0.62 | H109: =H112 -> 20.15 | I109: =I112 -> 94.581 | J109: =J112 -> 5.859 | K109: =K112 -> 7.409 | ... AE109: =AE112 -> 0 | AG109: =AG112 -> 0 | AH109: =AH112 -> 0 | AI109: =AI112 -> 0 | AJ109: =AJ112 -> 0 | AK109: =AK112 -> 0 | AL109: =AL112 -> 0 | AM109: =AM112 -> 0 | AN109: =AN112 -> 0 | ... AS109: =AS112 -> 0
B110: = Interest expense | D110: =-(D14) -> 0 | E110: =-(E14) -> 26.759 | F110: =-(F14) -> 1.855 | G110: =-(G14) -> 2 | H110: =-(H14) -> 65 | I110: =-(I14) -> 305.1 | J110: =-(J14) -> 18.9 | K110: =-(K14) -> 23.9 | ... AE110: =-(AE14) -> 0 | AG110: =-(AG14) -> 26.759 | AH110: =-(AH14) -> 1.855 | AI110: =-(AI14) -> 2 | AJ110: =-(AJ14) -> 65 | AK110: =-(AK14) -> 305.1 | AL110: =-(AL14) -> 18.9 | AM110: =-(AM14) -> 23.9 | AN110: =-(AN14) -> 0 | ... AS110: =-(AS14) -> 0
B111: x (1 – Tax rate) | E111: =$D$4 -> 0.31 | F111: =$D$4 -> 0.31 | G111: =$D$4 -> 0.31 | H111: =$D$4 -> 0.31 | I111: =$D$4 -> 0.31 | J111: =$D$4 -> 0.31 | K111: =$D$4 -> 0.31
B112: = Interest expense after tax | D112: =D111*D110 -> 0 | E112: =E111*E110 -> 8.29529 | F112: =F111*F110 -> 0.57505 | G112: =G111*G110 -> 0.62 | H112: =H111*H110 -> 20.15 | I112: =I111*I110 -> 94.581 | J112: =J111*J110 -> 5.859 | K112: =K111*K110 -> 7.409 | ... AE112: =AE111*AE110 -> 0 | AG112: =AG111*AG110 -> 0 | AH112: =AH111*AH110 -> 0 | AI112: =AI111*AI110 -> 0 | AJ112: =AJ111*AJ110 -> 0 | AK112: =AK111*AK110 -> 0 | AL112: =AL111*AL110 -> 0 | AM112: =AM111*AM110 -> 0 | AN112: =AN111*AN110 -> 0 | ... AS112: =AS111*AS110 -> 0
B113: = Profit or loss | D113: =D100+D105-D109 -> 0 | E113: =E100+E105-E109 -> -85.949 | F113: =F100+F105-F109 -> -48.263 | G113: =G100+G105-G109 -> -179.2 | H113: =H100+H105-H109 -> 15.2 | I113: =I100+I105-I109 -> 10292.5 | J113: =J100+J105-J109 -> 9434.4 | K113: =K100+K105-K109 -> 930.3 | ... AE113: =AE100+AE105-AE109 -> 0 | AG113: =AG100+AG105-AG109 -> -85.949 | AH113: =AH100+AH105-AH109 -> -48.263 | AI113: =AI100+AI105-AI109 -> -179.2 | AJ113: =AJ100+AJ105-AJ109 -> 15.2 | AK113: =AK100+AK105-AK109 -> 10292.5 | AL113: =AL100+AL105-AL109 -> 9434.4 | AM113: =AM100+AM105-AM109 -> 930.3 | AN113: =AN100+AN105-AN109 -> 0 | ... AS113: =AS100+AS105-AS109 -> 0
A115: x | B115: CONDENSED BALANCE SHEETS
B116: Ending operating working capital
...

Sheet Astra Zeneca Adjusted
B2: Assumptions: | C2: 2015 | D2: =C2+1 -> 2016 | E2: =D2+1 -> 2017 | F2: =E2+1 -> 2018 | G2: =F2+1 -> 2019 | H2: =G2+1 -> 2020 | I2: =H2+1 -> 2021 | J2: =I2+1 -> 2022 | K2: =J2+1 -> 2023 | ... Q2: =P2+1 -> 2029
B3: Operating cash percentage | E3: 0.05 | F3: 0.05 | G3: 0.05 | H3: 0.05 | I3: 0.05 | J3: 0.05 | K3: 0.05 | L3: 0.05 | M3: 0.05 | N3: 0.05 | O3: 0.05 | P3: 0.05 | Q3: 0.05
B4: Tax Rate | E4: =-E17/E11 -> -0.2206541 | F4: =-F17/F11 -> -0.051167342 | G4: =-G17/G11 -> 0.12860577 | H4: =-H17/H11 -> 0.20057167 | I4: =-I17/I11 -> -0.15839923 | J4: =-J17/J11 -> -0.093994744 | K4: =-K17/K11 -> 0.10062219
B5: Pre-Adjustment (from Standardized)
A8: x | B8: INCOME STATEMENT
B9: Revenue | C9: ='Astra Zeneca Standardized'!C5 -> 22275.975 | D9: ='Astra Zeneca Standardized'!D5 -> 20799.792 | E9: ='Astra Zeneca Standardized'!E5 -> 19923.863 | F9: ='Astra Zeneca Standardized'!F5 -> 18722.875 | G9: ='Astra Zeneca Standardized'!G5 -> 21783.049 | H9: ='Astra Zeneca Standardized'!H5 -> 23346.583 | I9: ='Astra Zeneca Standardized'!I5 -> 31653.119 | J9: ='Astra Zeneca Standardized'!J5 -> 42191.755 | ... L9: ='Astra Zeneca Standardized'!L5 -> 49995.091
B10: Operating expenses | C10: =SUM('Astra Zeneca Standardized'!C6:C10) -> -19143.021 | D10: =SUM('Astra Zeneca Standardized'!D6:D10) -> -17882.649 | E10: =SUM('Astra Zeneca Standardized'!E6:E10) -> -17347.464 | F10: =SUM('Astra Zeneca Standardized'!F6:F10) -> -17778.679 | G10: =SUM('Astra Zeneca Standardized'!G6:G10) -> -19553.289 | H10: =SUM('Astra Zeneca Standardized'!H6:H10) -> -19970.508 | I10: =SUM('Astra Zeneca Standardized'!I6:I10) -> -29623.671 | J10: =SUM('Astra Zeneca Standardized'!J6:J10) -> -34175.977 | ... L10: =SUM('Astra Zeneca Standardized'!L6:L10) -> -38203.857
B11: Operating profit | C11: =SUM(C9:C10) -> 3132.954 | D11: =SUM(D9:D10) -> 2917.143 | E11: =SUM(E9:E10) -> 2576.399 | F11: =SUM(F9:F10) -> 944.196 | G11: =SUM(G9:G10) -> 2229.76 | H11: =SUM(H9:H10) -> 3376.075 | I11: =SUM(I9:I10) -> 2029.448 | J11: =SUM(J9:J10) -> 8015.778 | ... L11: =SUM(L9:L10) -> 11791.234
B12: Investment Income | C12: ='Astra Zeneca Standardized'!C13 -> -29.752 | D12: ='Astra Zeneca Standardized'!D13 -> -48.83 | E12: ='Astra Zeneca Standardized'!E13 -> 81.593 | F12: ='Astra Zeneca Standardized'!F13 -> -95.776 | G12: ='Astra Zeneca Standardized'!G13 -> -103.627 | H12: ='Astra Zeneca Standardized'!H13 -> -23.683 | I12: ='Astra Zeneca Standardized'!I13 -> 602.321 | J12: ='Astra Zeneca Standardized'!J13 -> -4.757 | ... L12: ='Astra Zeneca Standardized'!L13 -> -25.888
B13: Net non-recurring income or expense | C13: ='Astra Zeneca Standardized'!C14 -> -15.326 | D13: ='Astra Zeneca Standardized'!D14 -> 862.664 | E13: ='Astra Zeneca Standardized'!E14 -> -181.811 | F13: ='Astra Zeneca Standardized'!F14 -> 1359.505 | G13: ='Astra Zeneca Standardized'!G14 -> -175.987 | H13: ='Astra Zeneca Standardized'!H14 -> 662.233 | I13: ='Astra Zeneca Standardized'!I14 -> -2235.861 | J13: ='Astra Zeneca Standardized'!J14 -> -4836.484 | ... L13: ='Astra Zeneca Standardized'!L14 -> -2751.565
B14: Interest income | C14: ='Astra Zeneca Standardized'!C11 -> 32.456 | D14: ='Astra Zeneca Standardized'!D11 -> 38.883 | E14: ='Astra Zeneca Standardized'!E11 -> 87.802 | F14: ='Astra Zeneca Standardized'!F11 -> 111.88 | G14: ='Astra Zeneca Standardized'!G11 -> 129.533 | H14: ='Astra Zeneca Standardized'!H11 -> 67.539 | I14: ='Astra Zeneca Standardized'!I11 -> 36.376 | J14: ='Astra Zeneca Standardized'!J11 -> 77.056 | ... L14: ='Astra Zeneca Standardized'!L11 -> 318.982
B15: Interest expense | C15: ='Astra Zeneca Standardized'!C12 -> -353.415 | D15: ='Astra Zeneca Standardized'!D12 -> -557.929 | E15: ='Astra Zeneca Standardized'!E12 -> -588.891 | F15: ='Astra Zeneca Standardized'!F12 -> -630.594 | G15: ='Astra Zeneca Standardized'!G12 -> -696.8 | H15: ='Astra Zeneca Standardized'!H12 -> -647.322 | I15: ='Astra Zeneca Standardized'!I12 -> -656.462 | J15: ='Astra Zeneca Standardized'!J12 -> -872.356 | ... L15: ='Astra Zeneca Standardized'!L12 -> -1297.193
B16: Profit before taxes | C16: =SUM(C11:C15) -> 2766.917 | D16: =SUM(D11:D15) -> 3211.931 | E16: =SUM(E11:E15) -> 1975.092 | F16: =SUM(F11:F15) -> 1689.211 | G16: =SUM(G11:G15) -> 1382.879 | H16: =SUM(H11:H15) -> 3434.842 | I16: =SUM(I11:I15) -> -224.178 | J16: =SUM(J11:J15) -> 2379.237 | ... L16: =SUM(L11:L15) -> 8035.57
B17: Tax expense | C17: ='Astra Zeneca Standardized'!C15 -> -219.081 | D17: ='Astra Zeneca Standardized'!D15 -> -132.022 | E17: ='Astra Zeneca Standardized'!E15 -> 568.493 | F17: ='Astra Zeneca Standardized'!F15 -> 48.312 | G17: ='Astra Zeneca Standardized'!G15 -> -286.76 | H17: ='Astra Zeneca Standardized'!H15 -> -677.145 | I17: ='Astra Zeneca Standardized'!I15 -> 321.463 | J17: ='Astra Zeneca Standardized'!J15 -> 753.441 | ... L17: ='Astra Zeneca Standardized'!L15 -> -1525.565
B18: Profit after taxes | C18: =SUM(C16:C17) -> 2547.836 | D18: =SUM(D16:D17) -> 3079.909 | E18: =SUM(E16:E17) -> 2543.585 | F18: =SUM(F16:F17) -> 1737.523 | G18: =SUM(G16:G17) -> 1096.119 | H18: =SUM(H16:H17) -> 2757.697 | I18: =SUM(I16:I17) -> 97.285 | J18: =SUM(J16:J17) -> 3132.678 | ... L18: =SUM(L16:L17) -> 6510.005
B19: Profit/loss to non-controlling interest | C19: ='Astra Zeneca Standardized'!C16 -> -0.902 | D19: ='Astra Zeneca Standardized'!D16 -> 84.096 | E19: ='Astra Zeneca Standardized'!E16 -> 117.956 | F19: ='Astra Zeneca Standardized'!F16 -> 88.995 | G19: ='Astra Zeneca Standardized'!G16 -> 96.48 | H19: ='Astra Zeneca Standardized'!H16 -> 45.611 | I19: ='Astra Zeneca Standardized'!I16 -> -2.538 | J19: ='Astra Zeneca Standardized'!J16 -> -4.757 | ... L19: ='Astra Zeneca Standardized'!L16 -> -5.548
B20: Profit/Loss of Discontinued Operations | C20: ='Astra Zeneca Standardized'!C17 -> 0 | D20: ='Astra Zeneca Standardized'!D17 -> 0 | E20: ='Astra Zeneca Standardized'!E17 -> 0 | F20: ='Astra Zeneca Standardized'!F17 -> 0 | G20: ='Astra Zeneca Standardized'!G17 -> 0 | H20: ='Astra Zeneca Standardized'!H17 -> 0 | I20: ='Astra Zeneca Standardized'!I17 -> 0 | J20: ='Astra Zeneca Standardized'!J17 -> 0 | ... L20: ='Astra Zeneca Standardized'!L17 -> 0
B21: Profit/loss to ordinary shareholders | C21: =SUM(C18:C20) -> 2546.934 | D21: =SUM(D18:D20) -> 3164.005 | E21: =SUM(E18:E20) -> 2661.541 | F21: =SUM(F18:F20) -> 1826.518 | G21: =SUM(G18:G20) -> 1192.599 | H21: =SUM(H18:H20) -> 2803.308 | I21: =SUM(I18:I20) -> 94.747 | J21: =SUM(J18:J20) -> 3127.921 | ... L21: =SUM(L18:L20) -> 6504.457
A23: x | B23: OPERATING EXPENSES
B24: Classification by function:
B25: Cost of Sales (by function) | C25: =+'Astra Zeneca Standardized'!C6 -> -4046.243 | D25: =+'Astra Zeneca Standardized'!D6 -> -3613.424 | E25: =+'Astra Zeneca Standardized'!E6 -> -3669.042 | F25: =+'Astra Zeneca Standardized'!F6 -> -3817.466 | G25: =+'Astra Zeneca Standardized'!G6 -> -4330.882 | H25: =+'Astra Zeneca Standardized'!H6 -> -4601.427 | I25: =+'Astra Zeneca Standardized'!I6 -> -10155.696 | J25: =+'Astra Zeneca Standardized'!J6 -> -8220.31 | ... L25: =+'Astra Zeneca Standardized'!L6 -> -8911.151
B26: SG&A (by function) | C26: =+'Astra Zeneca Standardized'!C8 -> -9938.9 | D26: =+'Astra Zeneca Standardized'!D8 -> -8810.207 | E26: =+'Astra Zeneca Standardized'!E8 -> -8342.037 | F26: =+'Astra Zeneca Standardized'!F8 -> -9172.429 | G26: =+'Astra Zeneca Standardized'!G8 -> -10217.951 | H26: =+'Astra Zeneca Standardized'!H8 -> -10162.434 | I26: =+'Astra Zeneca Standardized'!I8 -> -12412.706 | J26: =+'Astra Zeneca Standardized'!J8 -> -16609.953 | ... L26: =+'Astra Zeneca Standardized'!L8 -> -17985.954
B27: R&D Expenses | C27: =+'Astra Zeneca Standardized'!C9 -> -5102.883 | D27: =+'Astra Zeneca Standardized'!D9 -> -5135.293 | E27: =+'Astra Zeneca Standardized'!E9 -> -4837.956 | F27: =+'Astra Zeneca Standardized'!F9 -> -4491.286 | G27: =+'Astra Zeneca Standardized'!G9 -> -4778.442 | H27: =+'Astra Zeneca Standardized'!H9 -> -5175.947 | I27: =+'Astra Zeneca Standardized'!I9 -> -6809.096 | J27: =+'Astra Zeneca Standardized'!J9 -> -9198.261 | ... L27: =+'Astra Zeneca Standardized'!L9 -> -11319.696
B28: Other Operating Income, Net of Other Operating Expense (by function) | C28: =+'Astra Zeneca Standardized'!C10 -> -54.995 | D28: =+'Astra Zeneca Standardized'!D10 -> -323.725 | E28: =+'Astra Zeneca Standardized'!E10 -> -498.429 | F28: =+'Astra Zeneca Standardized'!F10 -> -297.498 | G28: =+'Astra Zeneca Standardized'!G10 -> -226.014 | H28: =+'Astra Zeneca Standardized'!H10 -> -30.7 | I28: =+'Astra Zeneca Standardized'!I10 -> -246.173 | J28: =+'Astra Zeneca Standardized'!J10 -> -147.453 | ... L28: =+'Astra Zeneca Standardized'!L10 -> 12.944
B29: Classification by nature:
B30: Cost of Materials (by nature)
B31: Personnel Expenses (by nature)
B32: Depreciation and Amortization (by nature)
B33: Other Operating Income, Net of Other Operating Expense (by nature)
A35: x | B35: BALANCE SHEET
B36: ASSETS
B37: Non-Current Tangible Assets | C37: =SUM('Astra Zeneca Standardized'!C35) -> 7034.148 | D37: =SUM('Astra Zeneca Standardized'!D35) -> 7611.202 | E37: =SUM('Astra Zeneca Standardized'!E35) -> 7396.93 | F37: =SUM('Astra Zeneca Standardized'!F35) -> 7019.515 | G37: =SUM('Astra Zeneca Standardized'!G35) -> 8093.862 | H37: =SUM('Astra Zeneca Standardized'!H35) -> 7981.253 | I37: =SUM('Astra Zeneca Standardized'!I35) -> 9798.04 | J37: =SUM('Astra Zeneca Standardized'!J35) -> 9691.98 | ... L37: =SUM('Astra Zeneca Standardized'!L35) -> 12323.918
B38: Non-Current Intangible Assets | C38: =SUM('Astra Zeneca Standardized'!C36) -> 31714.432 | D38: =SUM('Astra Zeneca Standardized'!D36) -> 37211.161 | E38: =SUM('Astra Zeneca Standardized'!E36) -> 31657.226 | F38: =SUM('Astra Zeneca Standardized'!F36) -> 29403.885 | G38: =SUM('Astra Zeneca Standardized'!G36) -> 28961.641 | H38: =SUM('Astra Zeneca Standardized'!H36) -> 26807.461 | I38: =SUM('Astra Zeneca Standardized'!I36) -> 54854.251 | J38: =SUM('Astra Zeneca Standardized'!J36) -> 55325.134 | ... L38: =SUM('Astra Zeneca Standardized'!L36) -> 56217.312
B39: Other Non-Operating Investments | C39: =SUM('Astra Zeneca Standardized'!C37) -> 615.948 | D39: =SUM('Astra Zeneca Standardized'!D37) -> 844.846 | E39: =SUM('Astra Zeneca Standardized'!E37) -> 932.736 | F39: =SUM('Astra Zeneca Standardized'!F37) -> 854.185 | G39: =SUM('Astra Zeneca Standardized'!G37) -> 1347.343 | H39: =SUM('Astra Zeneca Standardized'!H37) -> 974.46 | I39: =SUM('Astra Zeneca Standardized'!I37) -> 1109.677 | J39: =SUM('Astra Zeneca Standardized'!J37) -> 1068.569 | ... L39: =SUM('Astra Zeneca Standardized'!L37) -> 1835.21
B40: Deferred Tax Asset | C40: ='Astra Zeneca Standardized'!C38 -> 1191.386 | D40: ='Astra Zeneca Standardized'!D38 -> 1044.916 | E40: ='Astra Zeneca Standardized'!E38 -> 1822.999 | F40: ='Astra Zeneca Standardized'!F38 -> 2077.819 | G40: ='Astra Zeneca Standardized'!G38 -> 2422.01 | H40: ='Astra Zeneca Standardized'!H38 -> 2810.565 | I40: ='Astra Zeneca Standardized'!I38 -> 3807.369 | J40: ='Astra Zeneca Standardized'!J38 -> 3053.189 | ... L40: ='Astra Zeneca Standardized'!L38 -> 5164.667
B41: Total Non-Current Assets | C41: =SUM(C37:C40) -> 40555.914 | D41: =SUM(D37:D40) -> 46712.125 | E41: =SUM(E37:E40) -> 41809.891 | F41: =SUM(F37:F40) -> 39355.404 | G41: =SUM(G37:G40) -> 40824.856 | H41: =SUM(H37:H40) -> 38573.739 | I41: =SUM(I37:I40) -> 69569.337 | J41: =SUM(J37:J40) -> 69138.872 | ... L41: =SUM(L37:L40) -> 75541.107
B43: Inventories | C43: ='Astra Zeneca Standardized'!C33 -> 1973.06 | D43: ='Astra Zeneca Standardized'!D33 -> 2213.099 | E43: ='Astra Zeneca Standardized'!E33 -> 2527.548 | F43: ='Astra Zeneca Standardized'!F33 -> 2524.126 | G43: ='Astra Zeneca Standardized'!G33 -> 2845.282 | H43: ='Astra Zeneca Standardized'!H33 -> 3289.62 | I43: ='Astra Zeneca Standardized'!I33 -> 7898.752 | J43: ='Astra Zeneca Standardized'!J33 -> 4396.854 | ... L43: ='Astra Zeneca Standardized'!L33 -> 5107.679
B44: Trade Receivables | C44: ='Astra Zeneca Standardized'!C32 -> 4265.603 | D44: ='Astra Zeneca Standardized'!D32 -> 2449.201 | E44: ='Astra Zeneca Standardized'!E32 -> 2333.506 | F44: ='Astra Zeneca Standardized'!F32 -> 2615.833 | G44: ='Astra Zeneca Standardized'!G32 -> 3194.594 | H44: ='Astra Zeneca Standardized'!H32 -> 3111.405 | I44: ='Astra Zeneca Standardized'!I32 -> 5303.058 | J44: ='Astra Zeneca Standardized'!J32 -> 6748.268 | ... L44: ='Astra Zeneca Standardized'!L32 -> 8018.902
B45: Other Current Assets | C45: ='Astra Zeneca Standardized'!C34 -> 2189.424 | D45: ='Astra Zeneca Standardized'!D34 -> 2316.453 | E45: ='Astra Zeneca Standardized'!E34 -> 2297.695 | F45: ='Astra Zeneca Standardized'!F34 -> 4222.89 | G45: ='Astra Zeneca Standardized'!G34 -> 3010.137 | H45: ='Astra Zeneca Standardized'!H34 -> 3139.202 | I45: ='Astra Zeneca Standardized'!I34 -> 4262.847 | J45: ='Astra Zeneca Standardized'!J34 -> 4165.736 | ... L45: ='Astra Zeneca Standardized'!L34 -> 6518.859
B46: Cash and Cash Equivalents | C46: ='Astra Zeneca Standardized'!C31 -> 6309.557 | D46: ='Astra Zeneca Standardized'!D31 -> 5596.277 | E46: ='Astra Zeneca Standardized'!E31 -> 3792.571 | F46: ='Astra Zeneca Standardized'!F31 -> 4254.331 | G46: ='Astra Zeneca Standardized'!G31 -> 4818.178 | H46: ='Astra Zeneca Standardized'!H31 -> 6436.995 | I46: ='Astra Zeneca Standardized'!I31 -> 5611.693 | J46: ='Astra Zeneca Standardized'!J31 -> 5829.411 | ... L46: ='Astra Zeneca Standardized'!L31 -> 5300.859
B47: Total Current Assets | C47: =SUM(C43:C46) -> 14737.644 | D47: =SUM(D43:D46) -> 12575.03 | E47: =SUM(E43:E46) -> 10951.32 | F47: =SUM(F43:F46) -> 13617.18 | G47: =SUM(G43:G46) -> 13868.191 | H47: =SUM(H43:H46) -> 15977.222 | I47: =SUM(I43:I46) -> 23076.35 | J47: =SUM(J43:J46) -> 21140.269 | ... L47: =SUM(L43:L46) -> 24946.299
B50: Total Assets | C50: =SUM(C41,C47) -> 55293.558 | D50: =SUM(D41,D47) -> 59287.155 | E50: =SUM(E41,E47) -> 52761.211 | F50: =SUM(F41,F47) -> 52972.584 | G50: =SUM(G41,G47) -> 54693.047 | H50: =SUM(H41,H47) -> 54550.961 | I50: =SUM(I41,I47) -> 92645.687 | J50: =SUM(J41,J47) -> 90279.141 | ... L50: =SUM(L41,L47) -> 100487.41
B52: LIABILITIES AND SHAREHOLDERS' EQUITY
B53: Ordinary Shareholders' Equity | C53: ='Astra Zeneca Standardized'!C50 -> 17023.743 | D53: ='Astra Zeneca Standardized'!D50 -> 14084.563 | E53: ='Astra Zeneca Standardized'!E50 -> 12458.688 | F53: ='Astra Zeneca Standardized'!F50 -> 10889.552 | G53: ='Astra Zeneca Standardized'!G50 -> 11697.47 | H53: ='Astra Zeneca Standardized'!H50 -> 12770.986 | I53: ='Astra Zeneca Standardized'!I50 -> 34528.352 | J53: ='Astra Zeneca Standardized'!J50 -> 34655.521 | ... L53: ='Astra Zeneca Standardized'!L50 -> 39395.197
B54: Preference Shares | C54: ='Astra Zeneca Standardized'!C51 -> 0 | D54: ='Astra Zeneca Standardized'!D51 -> 0 | E54: ='Astra Zeneca Standardized'!E51 -> 0 | F54: ='Astra Zeneca Standardized'!F51 -> 0 | G54: ='Astra Zeneca Standardized'!G51 -> 0 | H54: ='Astra Zeneca Standardized'!H51 -> 0 | I54: ='Astra Zeneca Standardized'!I51 -> 0 | J54: ='Astra Zeneca Standardized'!J51 -> 0 | ... L54: ='Astra Zeneca Standardized'!L51 -> 0
B55: Non-Controlling Interest in Equity | C55: ='Astra Zeneca Standardized'!C49 -> 17.493 | D55: ='Astra Zeneca Standardized'!D49 -> 1720.983 | E55: ='Astra Zeneca Standardized'!E49 -> 1400.77 | F55: ='Astra Zeneca Standardized'!F49 -> 1376.478 | G55: ='Astra Zeneca Standardized'!G49 -> 1309.026 | H55: ='Astra Zeneca Standardized'!H49 -> 13.08 | I55: ='Astra Zeneca Standardized'!I49 -> 16.707 | J55: ='Astra Zeneca Standardized'!J49 -> 19.65 | ... L55: ='Astra Zeneca Standardized'!L49 -> 82.102
B58: Non-Current Debt | C58: ='Astra Zeneca Standardized'!C46 -> 14834.319 | D58: ='Astra Zeneca Standardized'!D46 -> 17736.081 | E58: ='Astra Zeneca Standardized'!E46 -> 16631.016 | F58: ='Astra Zeneca Standardized'!F46 -> 18963.26 | G58: ='Astra Zeneca Standardized'!G46 -> 18880.627 | H58: ='Astra Zeneca Standardized'!H46 -> 19207.163 | I58: ='Astra Zeneca Standardized'!I46 -> 28950.952 | J58: ='Astra Zeneca Standardized'!J46 -> 24141.997 | ... L58: ='Astra Zeneca Standardized'!L46 -> 28072.918
B59: Deferred Tax Liability | C59: ='Astra Zeneca Standardized'!C47 -> 2453.666 | D59: ='Astra Zeneca Standardized'!D47 -> 3751.079 | E59: ='Astra Zeneca Standardized'!E47 -> 3327.036 | F59: ='Astra Zeneca Standardized'!F47 -> 2869.992 | G59: ='Astra Zeneca Standardized'!G47 -> 2218.839 | H59: ='Astra Zeneca Standardized'!H47 -> 2385.465 | I59: ='Astra Zeneca Standardized'!I47 -> 5456.936 | J59: ='Astra Zeneca Standardized'!J47 -> 2754.701 | ... L59: ='Astra Zeneca Standardized'!L47 -> 3192.3
B60: Other Non-Current Liabilities (non interest bearing) | C60: ='Astra Zeneca Standardized'!C48 -> 7274.451 | D60: ='Astra Zeneca Standardized'!D48 -> 7528.708 | E60: ='Astra Zeneca Standardized'!E48 -> 5299.939 | F60: ='Astra Zeneca Standardized'!F48 -> 4643.868 | G60: ='Astra Zeneca Standardized'!G48 -> 4443.025 | H60: ='Astra Zeneca Standardized'!H48 -> 3573.293 | I60: ='Astra Zeneca Standardized'!I48 -> 3825.835 | J60: ='Astra Zeneca Standardized'!J48 -> 4104.916 | ... L60: ='Astra Zeneca Standardized'!L48 -> 2829.121
B61: Non-Current Liabilities | C61: =SUM(C58:C60) -> 24562.436 | D61: =SUM(D58:D60) -> 29015.868 | E61: =SUM(E58:E60) -> 25257.991 | F61: =SUM(F58:F60) -> 26477.12 | G61: =SUM(G58:G60) -> 25542.491 | H61: =SUM(H58:H60) -> 25165.921 | I61: =SUM(I58:I60) -> 38233.723 | J61: =SUM(J58:J60) -> 31001.614 | ... Q61: =SUM(Q58:Q60) -> 0
B63: Trade Payables | C63: ='Astra Zeneca Standardized'!C44 -> 3193.908 | D63: ='Astra Zeneca Standardized'!D44 -> 1592.976 | E63: ='Astra Zeneca Standardized'!E44 -> 1902.948 | F63: ='Astra Zeneca Standardized'!F44 -> 1502.248 | G63: ='Astra Zeneca Standardized'!G44 -> 1580.811 | H63: ='Astra Zeneca Standardized'!H44 -> 1921.125 | I63: ='Astra Zeneca Standardized'!I44 -> 2483.143 | J63: ='Astra Zeneca Standardized'!J44 -> 2386.035 | ... L63: ='Astra Zeneca Standardized'!L44 -> 3515.876
B64: Other Current Liabilities | C64: ='Astra Zeneca Standardized'!C45 -> 9644.333 | D64: ='Astra Zeneca Standardized'!D45 -> 10668.198 | E64: ='Astra Zeneca Standardized'!E45 -> 9849.525 | F64: ='Astra Zeneca Standardized'!F45 -> 11171.66 | G64: ='Astra Zeneca Standardized'!G45 -> 12740.057 | H64: ='Astra Zeneca Standardized'!H45 -> 12702.316 | I64: ='Astra Zeneca Standardized'!I45 -> 14840.825 | J64: ='Astra Zeneca Standardized'!J45 -> 16132.403 | ... L64: ='Astra Zeneca Standardized'!L45 -> 20766.849
B65: Current Debt | C65: ='Astra Zeneca Standardized'!C43 -> 851.647 | D65: ='Astra Zeneca Standardized'!D43 -> 2204.564 | E65: ='Astra Zeneca Standardized'!E43 -> 1891.289 | F65: ='Astra Zeneca Standardized'!F43 -> 1555.525 | G65: ='Astra Zeneca Standardized'!G43 -> 1823.191 | H65: ='Astra Zeneca Standardized'!H43 -> 1977.533 | I65: ='Astra Zeneca Standardized'!I43 -> 2542.935 | J65: ='Astra Zeneca Standardized'!J43 -> 6083.922 | ... L65: ='Astra Zeneca Standardized'!L43 -> 2633.043
B66: Current Liabilities | C66: =SUM(C63:C65) -> 13689.888 | D66: =SUM(D63:D65) -> 14465.738 | E66: =SUM(E63:E65) -> 13643.762 | F66: =SUM(F63:F65) -> 14229.433 | G66: =SUM(G63:G65) -> 16144.059 | H66: =SUM(H63:H65) -> 16600.974 | I66: =SUM(I63:I65) -> 19866.903 | J66: =SUM(J63:J65) -> 24602.36 | ... Q66: =SUM(Q63:Q65) -> 0
B69: Total Liabilities and Shareholders' Equity | C69: =SUM(C53:C55,C61,C66) -> 55293.56 | D69: =SUM(D53:D55,D61,D66) -> 59287.152 | E69: =SUM(E53:E55,E61,E66) -> 52761.211 | F69: =SUM(F53:F55,F61,F66) -> 52972.583 | G69: =SUM(G53:G55,G61,G66) -> 54693.046 | H69: =SUM(H53:H55,H61,H66) -> 54550.961 | I69: =SUM(I53:I55,I61,I66) -> 92645.685 | J69: =SUM(J53:J55,J61,J66) -> 90279.145 | ... L69: =SUM(L53:L55,L61,L66) -> 100487.41
B70: Check | C70: =C50-C69 -> -0.002 | D70: =D50-D69 -> 0.003 | E70: =E50-E69 -> 0 | F70: =F50-F69 -> 0.001 | G70: =G50-G69 -> 0.001 | H70: =H50-H69 -> 0 | I70: =I50-I69 -> 0.002 | J70: =J50-J69 -> -0.004 | ... L70: =L50-L69 -> 0 | M70: =M69-M50 -> 0 | N70: =N69-N50 -> 0 | O70: =O69-O50 -> 0 | P70: =P69-P50 -> 0 | Q70: =Q69-Q50 -> 0
A71: x | B71: CASH FLOW STATEMENT
B72: Profit Before Interest and Tax | C72: ='Astra Zeneca Standardized'!C56 -> 2713.723 | D72: ='Astra Zeneca Standardized'!D56 -> 3628.796 | E72: ='Astra Zeneca Standardized'!E56 -> 3906.727 | F72: ='Astra Zeneca Standardized'!F56 -> 2617.305 | G72: ='Astra Zeneca Standardized'!G56 -> 1732.174 | H72: ='Astra Zeneca Standardized'!H56 -> 2841.025 | I72: ='Astra Zeneca Standardized'!I56 -> 1109.048 | J72: ='Astra Zeneca Standardized'!J56 -> 4830.775 | ... L72: ='Astra Zeneca Standardized'!L56 -> 6595.066
B73: Taxes Paid | C73: ='Astra Zeneca Standardized'!C60 -> 219.081 | D73: ='Astra Zeneca Standardized'!D60 -> 132.022 | E73: ='Astra Zeneca Standardized'!E60 -> -568.493 | F73: ='Astra Zeneca Standardized'!F60 -> -48.312 | G73: ='Astra Zeneca Standardized'!G60 -> 286.76 | H73: ='Astra Zeneca Standardized'!H60 -> 677.145 | I73: ='Astra Zeneca Standardized'!I60 -> -321.463 | J73: ='Astra Zeneca Standardized'!J60 -> -753.441 | ... L73: ='Astra Zeneca Standardized'!L60 -> 1525.565
B74: Non-Operating Losses (Gains) | C74: ='Astra Zeneca Standardized'!C58 -> -928.617 | D74: ='Astra Zeneca Standardized'!D58 -> -1172.825 | E74: ='Astra Zeneca Standardized'!E58 -> -1461.585 | F74: ='Astra Zeneca Standardized'!F58 -> -1495.117 | G74: ='Astra Zeneca Standardized'!G58 -> -1006.787 | H74: ='Astra Zeneca Standardized'!H58 -> -901.69 | I74: ='Astra Zeneca Standardized'!I58 -> -1032.912 | J74: ='Astra Zeneca Standardized'!J58 -> -200.727 | ... L74: ='Astra Zeneca Standardized'!L58 -> -29.587
B75: Non-Current Operating Accruals | C75: ='Astra Zeneca Standardized'!C59 -> 1422.675 | D75: ='Astra Zeneca Standardized'!D59 -> 919.633 | E75: ='Astra Zeneca Standardized'!E59 -> 2017.663 | F75: ='Astra Zeneca Standardized'!F59 -> 2429.142 | G75: ='Astra Zeneca Standardized'!G59 -> 2775.589 | H75: ='Astra Zeneca Standardized'!H59 -> 1991.087 | I75: ='Astra Zeneca Standardized'!I59 -> 4272.921 | J75: ='Astra Zeneca Standardized'!J59 -> 2829.209 | ... L75: ='Astra Zeneca Standardized'!L59 -> 5317.289
B76: Operating Cash Flow before Working Capital Investments | C76: =SUM(C72:C75) -> 3426.862 | D76: =SUM(D72:D75) -> 3507.626 | E76: =SUM(E72:E75) -> 3894.312 | F76: =SUM(F72:F75) -> 3503.018 | G76: =SUM(G72:G75) -> 3787.736 | H76: =SUM(H72:H75) -> 4607.567 | I76: =SUM(I72:I75) -> 4027.594 | J76: =SUM(J72:J75) -> 6705.816 | ... Q76: =SUM(Q72:Q75) -> 0
B78: Net (Investments in) or Liquidation of Operating Working Capital | C78: ='Astra Zeneca Standardized'!C63 -> -44.176 | D78: ='Astra Zeneca Standardized'!D63 -> 837.345 | E78: ='Astra Zeneca Standardized'!E63 -> -44.345 | F78: ='Astra Zeneca Standardized'!F63 -> -541.598 | G78: ='Astra Zeneca Standardized'!G63 -> -309.093 | H78: ='Astra Zeneca Standardized'!H63 -> 316.645 | I78: ='Astra Zeneca Standardized'!I63 -> 1709.677 | J78: ='Astra Zeneca Standardized'!J63 -> 3574.09 | ... L78: ='Astra Zeneca Standardized'!L63 -> -825.655
B79: Operating Cash Flow before Investment in Non-Current Assets | C79: =SUM(C78,C76) -> 3382.686 | D79: =SUM(D78,D76) -> 4344.971 | E79: =SUM(E78,E76) -> 3849.967 | F79: =SUM(F78,F76) -> 2961.42 | G79: =SUM(G78,G76) -> 3478.643 | H79: =SUM(H78,H76) -> 4924.212 | I79: =SUM(I78,I76) -> 5737.271 | J79: =SUM(J78,J76) -> 10279.906 | ... L79: =SUM(L78,L76) -> 12582.678 | M79: =SUM(M76:M78) -> 0 | N79: =SUM(N76:N78) -> 0 | O79: =SUM(O76:O78) -> 0 | P79: =SUM(P76:P78) -> 0 | Q79: =SUM(Q76:Q78) -> 0
B81: Interest Received | C81: ='Astra Zeneca Standardized'!C61 -> -32.456 | D81: ='Astra Zeneca Standardized'!D61 -> -38.883 | E81: ='Astra Zeneca Standardized'!E61 -> -87.802 | F81: ='Astra Zeneca Standardized'!F61 -> -111.88 | G81: ='Astra Zeneca Standardized'!G61 -> -129.533 | H81: ='Astra Zeneca Standardized'!H61 -> -67.539 | I81: ='Astra Zeneca Standardized'!I61 -> -36.376 | J81: ='Astra Zeneca Standardized'!J61 -> -77.056 | ... L81: ='Astra Zeneca Standardized'!L61 -> -318.982
B82: Dividends received | C82: ='Astra Zeneca Standardized'!C62 -> 0 | D82: ='Astra Zeneca Standardized'!D62 -> 0 | E82: ='Astra Zeneca Standardized'!E62 -> 0 | F82: ='Astra Zeneca Standardized'!F62 -> 0 | G82: ='Astra Zeneca Standardized'!G62 -> 0 | H82: ='Astra Zeneca Standardized'!H62 -> 0 | I82: ='Astra Zeneca Standardized'!I62 -> 0 | J82: ='Astra Zeneca Standardized'!J62 -> 0 | ... L82: ='Astra Zeneca Standardized'!L62 -> 0
B83: Net (Investments in) or Liquidation of Non-Current Operating or Investment Assets | C83: ='Astra Zeneca Standardized'!C64 -> -3821.752 | D83: ='Astra Zeneca Standardized'!D64 -> -3588.96 | E83: ='Astra Zeneca Standardized'!E64 -> -2064.709 | F83: ='Astra Zeneca Standardized'!F64 -> 816.282 | G83: ='Astra Zeneca Standardized'!G64 -> -586.874 | H83: ='Astra Zeneca Standardized'!H64 -> -249.922 | I83: ='Astra Zeneca Standardized'!I64 -> -9354.538 | J83: ='Astra Zeneca Standardized'!J64 -> -2815.784 | ... L83: ='Astra Zeneca Standardized'!L64 -> -7378.202
B84: Free Cash Flow Available to Debt and Equity | C84: =SUM(C81:C83,C79) -> -471.522 | D84: =SUM(D81:D83,D79) -> 717.128 | E84: =SUM(E81:E83,E79) -> 1697.456 | F84: =SUM(F81:F83,F79) -> 3665.822 | G84: =SUM(G81:G83,G79) -> 2762.236 | H84: =SUM(H81:H83,H79) -> 4606.751 | I84: =SUM(I81:I83,I79) -> -3653.643 | J84: =SUM(J81:J83,J79) -> 7387.066 | ... L84: =SUM(L81:L83,L79) -> 4885.494 | M84: =SUM(M79:M83) -> 0 | N84: =SUM(N79:N83) -> 0 | O84: =SUM(O79:O83) -> 0 | P84: =SUM(P79:P83) -> 0 | Q84: =SUM(Q79:Q83) -> 0
B86: Interest Paid | C86: ='Astra Zeneca Standardized'!C68 -> -353.415 | D86: ='Astra Zeneca Standardized'!D68 -> -557.929 | E86: ='Astra Zeneca Standardized'!E68 -> -588.891 | F86: ='Astra Zeneca Standardized'!F68 -> -630.594 | G86: ='Astra Zeneca Standardized'!G68 -> -696.8 | H86: ='Astra Zeneca Standardized'!H68 -> -647.322 | I86: ='Astra Zeneca Standardized'!I68 -> -656.462 | J86: ='Astra Zeneca Standardized'!J68 -> -872.356 | ... L86: ='Astra Zeneca Standardized'!L68 -> -1297.193
B87: Net Debt (Repayment) or Issuance | C87: ='Astra Zeneca Standardized'!C67 -> 3895.681 | D87: ='Astra Zeneca Standardized'!D67 -> 1980.33 | E87: ='Astra Zeneca Standardized'!E67 -> 478.918 | F87: ='Astra Zeneca Standardized'!F67 -> 1191.688 | G87: ='Astra Zeneca Standardized'!G67 -> -1516.881 | H87: ='Astra Zeneca Standardized'!H67 -> 1174.478 | I87: ='Astra Zeneca Standardized'!I67 -> 6324.363 | J87: ='Astra Zeneca Standardized'!J67 -> -2250.811 | ... L87: ='Astra Zeneca Standardized'!L67 -> 603.755
B88: Free Cash Flow Available to Equity | C88: =SUM(C86:C87,C84) -> 3070.744 | D88: =SUM(D86:D87,D84) -> 2139.529 | E88: =SUM(E86:E87,E84) -> 1587.483 | F88: =SUM(F86:F87,F84) -> 4226.916 | G88: =SUM(G86:G87,G84) -> 548.555 | H88: =SUM(H86:H87,H84) -> 5133.907 | I88: =SUM(I86:I87,I84) -> 2014.258 | J88: =SUM(J86:J87,J84) -> 4263.899 | ... L88: =SUM(L86:L87,L84) -> 4192.056 | M88: =SUM(M84:M87) -> 0 | N88: =SUM(N84:N87) -> 0 | O88: =SUM(O84:O87) -> 0 | P88: =SUM(P84:P87) -> 0 | Q88: =SUM(Q84:Q87) -> 0
B90: Dividend (Payments) | C90: ='Astra Zeneca Standardized'!C69 -> -3142.871 | D90: ='Astra Zeneca Standardized'!D69 -> -3220.07 | E90: ='Astra Zeneca Standardized'!E69 -> -3120.947 | F90: ='Astra Zeneca Standardized'!F69 -> -2952.942 | G90: ='Astra Zeneca Standardized'!G69 -> -3208.855 | H90: ='Astra Zeneca Standardized'!H69 -> -3133.11 | I90: ='Astra Zeneca Standardized'!I69 -> -3262.005 | J90: ='Astra Zeneca Standardized'!J69 -> -4267.597 | ... L90: ='Astra Zeneca Standardized'!L69 -> -4258.639
B91: Net share (Repurchase) or Issuance | C91: ='Astra Zeneca Standardized'!C70 -> 38.767 | D91: ='Astra Zeneca Standardized'!D70 -> 42.5 | E91: ='Astra Zeneca Standardized'!E70 -> 38.136 | F91: ='Astra Zeneca Standardized'!F70 -> 28.817 | G91: ='Astra Zeneca Standardized'!G70 -> 3149.001 | H91: ='Astra Zeneca Standardized'!H70 -> 26.314 | I91: ='Astra Zeneca Standardized'!I70 -> 24.533 | J91: ='Astra Zeneca Standardized'!J70 -> 27.588 | ... L91: ='Astra Zeneca Standardized'!L70 -> -39.757
B92: Misc. Cash Flow & Exchange rate | C92: ='Astra Zeneca Standardized'!C71 -> -68.519 | D92: ='Astra Zeneca Standardized'!D71 -> 18.989 | E92: ='Astra Zeneca Standardized'!E71 -> -58.534 | F92: ='Astra Zeneca Standardized'!F71 -> -32.208 | G92: ='Astra Zeneca Standardized'!G71 -> 4.467 | H92: ='Astra Zeneca Standardized'!H71 -> 10.526 | I92: ='Astra Zeneca Standardized'!I71 -> -52.449 | J92: ='Astra Zeneca Standardized'!J71 -> -76.105 | ... L92: ='Astra Zeneca Standardized'!L71 -> -85.986
B93: Net Increase (Decrease) in Cash Balance | C93: =SUM(C88,C92) -> 3002.225 | D93: =SUM(D88,D92) -> 2158.518 | E93: =SUM(E88,E92) -> 1528.949 | F93: =SUM(F88,F92) -> 4194.708 | G93: =SUM(G88,G92) -> 553.022 | H93: =SUM(H88,H92) -> 5144.433 | I93: =SUM(I88,I92) -> 1961.809 | J93: =SUM(J88,J92) -> 4187.794 | ... L93: =SUM(L88,L92) -> 4106.07 | M93: =SUM(M88:M91) -> 0 | N93: =SUM(N88:N91) -> 0 | O93: =SUM(O88:O91) -> 0 | P93: =SUM(P88:P91) -> 0 | Q93: =SUM(Q88:Q91) -> 0
A95: x | B95: CONDENSED STATEMENTS OF EARNINGS
B96: Revenue | C96: =C9 -> 22275.975 | D96: =D9 -> 20799.792 | E96: =E9 -> 19923.863 | F96: =F9 -> 18722.875 | G96: =G9 -> 21783.049 | H96: =H9 -> 23346.583 | I96: =I9 -> 31653.119 | J96: =J9 -> 42191.755 | ... R96: =R9 -> 0
B97: Net operating profit after tax | C97: =C101 -> 2547.836 | D97: =D101 -> 3079.909 | E97: =E101 -> 2543.585 | F97: =F101 -> 1737.523 | G97: =G101 -> 1096.119 | H97: =H101 -> 2757.697 | I97: =I101 -> 97.285 | J97: =J101 -> 3132.678 | ... R97: =R101 -> 0
B98: Profit or loss | C98: =C18 -> 2547.836 | D98: =D18 -> 3079.909 | E98: =E18 -> 2543.585 | F98: =F18 -> 1737.523 | G98: =G18 -> 1096.119 | H98: =H18 -> 2757.697 | I98: =I18 -> 97.285 | J98: =J18 -> 3132.678 | ... R98: =R18 -> 0
B99: – Investment profit after tax | C99: =-C106 -> 0 | D99: =-D106 -> 0 | E99: =-E106 -> 0 | F99: =-F106 -> 0 | G99: =-G106 -> 0 | H99: =-H106 -> 0 | I99: =-I106 -> 0 | J99: =-J106 -> 0 | ... R99: =-R106 -> 0
B100: + Interest expense after tax | C100: =C110 -> 0 | D100: =D110 -> 0 | E100: =E110 -> 0 | F100: =F110 -> 0 | G100: =G110 -> 0 | H100: =H110 -> 0 | I100: =I110 -> 0 | J100: =J110 -> 0 | ... R100: =R110 -> 0
B101: = Net operating profit after tax | C101: =SUM(C98:C100) -> 2547.836 | D101: =SUM(D98:D100) -> 3079.909 | E101: =SUM(E98:E100) -> 2543.585 | F101: =SUM(F98:F100) -> 1737.523 | G101: =SUM(G98:G100) -> 1096.119 | H101: =SUM(H98:H100) -> 2757.697 | I101: =SUM(I98:I100) -> 97.285 | J101: =SUM(J98:J100) -> 3132.678 | ... R101: =SUM(R98:R100) -> 0
B102: of which: Net non-recurring expense after tax | C102: =C105 -> 0 | D102: =D105 -> 0 | E102: =E105 -> 0 | F102: =F105 -> 0 | G102: =G105 -> 0 | H102: =H105 -> 0 | I102: =I105 -> 0 | J102: =J105 -> 0 | ... R102: =R105 -> 0
B103: = Net non-recurring expense (income) | C103: =-C13 -> 15.326 | D103: =-D13 -> -862.664 | E103: =-E13 -> 181.811 | F103: =-F13 -> -1359.505 | G103: =-G13 -> 175.987 | H103: =-H13 -> -662.233 | I103: =-I13 -> 2235.861 | J103: =-J13 -> 4836.484 | ... R103: =-R13 -> 0
B104: x (1 – Tax rate) | C104: =$C$4 -> 0 | D104: =$C$4 -> 0 | E104: =$C$4 -> 0 | F104: =$C$4 -> 0 | G104: =$C$4 -> 0 | H104: =$C$4 -> 0 | I104: =$C$4 -> 0 | J104: =$C$4 -> 0 | ... L104: =$C$4 -> 0
B105: = Net non-recurring expense after tax | C105: =C104*C103 -> 0 | D105: =D104*D103 -> 0 | E105: =E104*E103 -> 0 | F105: =F104*F103 -> 0 | G105: =G104*G103 -> 0 | H105: =H104*H103 -> 0 | I105: =I104*I103 -> 0 | J105: =J104*J103 -> 0 | ... R105: =R104*R103 -> 0
B106: + Net investment profit after tax | C106: =C109 -> 0 | D106: =D109 -> 0 | E106: =E109 -> 0 | F106: =F109 -> 0 | G106: =G109 -> 0 | H106: =H109 -> 0 | I106: =I109 -> 0 | J106: =J109 -> 0 | ... R106: =R109 -> 0
B107: = Investment and interest income | C107: =C12+C14 -> 2.704 | D107: =D12+D14 -> -9.947 | E107: =E12+E14 -> 169.395 | F107: =F12+F14 -> 16.104 | G107: =G12+G14 -> 25.906 | H107: =H12+H14 -> 43.856 | I107: =I12+I14 -> 638.697 | J107: =J12+J14 -> 72.299 | ... R107: =R12+R14 -> 0
B108: x (1 – Tax rate) | C108: =$C$4 -> 0 | D108: =$C$4 -> 0 | E108: =$C$4 -> 0 | F108: =$C$4 -> 0 | G108: =$C$4 -> 0 | H108: =$C$4 -> 0 | I108: =$C$4 -> 0 | J108: =$C$4 -> 0 | ... L108: =$C$4 -> 0
B109: = Net investment profit after tax | C109: =C108*C107 -> 0 | D109: =D108*D107 -> 0 | E109: =E108*E107 -> 0 | F109: =F108*F107 -> 0 | G109: =G108*G107 -> 0 | H109: =H108*H107 -> 0 | I109: =I108*I107 -> 0 | J109: =J108*J107 -> 0 | ... R109: =R108*R107 -> 0
B110: – Interest expense after tax | C110: =C113 -> 0 | D110: =D113 -> 0 | E110: =E113 -> 0 | F110: =F113 -> 0 | G110: =G113 -> 0 | H110: =H113 -> 0 | I110: =I113 -> 0 | J110: =J113 -> 0 | ... R110: =R113 -> 0
B111: = Interest expense | C111: =-(C15) -> 353.415 | D111: =-(D15) -> 557.929 | E111: =-(E15) -> 588.891 | F111: =-(F15) -> 630.594 | G111: =-(G15) -> 696.8 | H111: =-(H15) -> 647.322 | I111: =-(I15) -> 656.462 | J111: =-(J15) -> 872.356 | ... R111: =-(R15) -> 0
B112: x (1 – Tax rate) | C112: =$C$4 -> 0 | D112: =$C$4 -> 0 | E112: =$C$4 -> 0 | F112: =$C$4 -> 0 | G112: =$C$4 -> 0 | H112: =$C$4 -> 0 | I112: =$C$4 -> 0 | J112: =$C$4 -> 0 | ... L112: =$C$4 -> 0
B113: = Interest expense after tax | C113: =C112*C111 -> 0 | D113: =D112*D111 -> 0 | E113: =E112*E111 -> 0 | F113: =F112*F111 -> 0 | G113: =G112*G111 -> 0 | H113: =H112*H111 -> 0 | I113: =I112*I111 -> 0 | J113: =J112*J111 -> 0 | ... R113: =R112*R111 -> 0
B114: = Profit or loss | C114: =C101+C106-C110 -> 2547.836 | D114: =D101+D106-D110 -> 3079.909 | E114: =E101+E106-E110 -> 2543.585 | F114: =F101+F106-F110 -> 1737.523 | G114: =G101+G106-G110 -> 1096.119 | H114: =H101+H106-H110 -> 2757.697 | I114: =I101+I106-I110 -> 97.285 | J114: =J101+J106-J110 -> 3132.678 | ... R114: =R101+R106-R110 -> 0
A116: x | B116: CONDENSED BALANCE SHEETS
B117: Ending operating working capital
B118: Operating cash | C118: =MIN(C3*C9,C46) -> 0 | D118: =MIN(D3*D9,D46) -> 0 | E118: =MIN(E3*E9,E46) -> 996.19315 | F118: =MIN(F3*F9,F46) -> 936.14375 | G118: =MIN(G3*G9,G46) -> 1089.1525 | H118: =MIN(H3*H9,H46) -> 1167.3292 | I118: =MIN(I3*I9,I46) -> 1582.656 | J118: =MIN(J3*J9,J46) -> 2109.5878 | ... R118: =MIN(R3*R9,R46) -> 0
B119: + Trade receivables | C119: =C44 -> 4265.603 | D119: =D44 -> 2449.201 | E119: =E44 -> 2333.506 | F119: =F44 -> 2615.833 | G119: =G44 -> 3194.594 | H119: =H44 -> 3111.405 | I119: =I44 -> 5303.058 | J119: =J44 -> 6748.268 | ... R119: =R44 -> 0
B120: + Inventories | C120: =C43 -> 1973.06 | D120: =D43 -> 2213.099 | E120: =E43 -> 2527.548 | F120: =F43 -> 2524.126 | G120: =G43 -> 2845.282 | H120: =H43 -> 3289.62 | I120: =I43 -> 7898.752 | J120: =J43 -> 4396.854 | ... R120: =R43 -> 0
...

Sheet Moderna Adjusted
B2: Assumptions: | C2: 2015 | D2: =C2+1 -> 2016 | E2: =D2+1 -> 2017 | F2: =E2+1 -> 2018 | G2: =F2+1 -> 2019 | H2: =G2+1 -> 2020 | I2: =H2+1 -> 2021 | J2: =I2+1 -> 2022 | K2: =J2+1 -> 2023 | ... Q2: =P2+1 -> 2029
B3: Operating cash percentage | E3: 0.05 | F3: 0.05 | G3: 0.05 | H3: 0.05 | I3: 0.05 | J3: 0.05 | K3: 0.05 | L3: 0.05 | M3: 0.05 | N3: 0.05 | O3: 0.05 | P3: 0.05 | Q3: 0.05
B4: Tax Rate | E4: =-E17/E11 -> 0.00029721041 | F4: =-F17/F11 -> -0.00078795907 | G4: =-G17/G11 -> 0.0018308147 | H4: =-H17/H11 -> -0.0039312605 | I4: =-I17/I11 -> 0.081453081 | J4: =-J17/J11 -> 0.12876861 | K4: =-K17/K11 -> -0.18211849
B5: Pre-Adjustment (from Standardized)
A8: x | B8: INCOME STATEMENT
B9: Revenue | D9: ='Moderna Standardized'!D5 -> 98.018 | E9: ='Moderna Standardized'!E5 -> 182.543 | F9: ='Moderna Standardized'!F5 -> 114.48 | G9: ='Moderna Standardized'!G5 -> 53.6 | H9: ='Moderna Standardized'!H5 -> 704.336 | I9: ='Moderna Standardized'!I5 -> 15625.645 | J9: ='Moderna Standardized'!J5 -> 18325.174 | K9: ='Moderna Standardized'!K5 -> 6333.465 | L9: ='Moderna Standardized'!L5 -> 2991.957
B10: Operating expenses | D10: =SUM('Moderna Standardized'!D6:D10) -> -300.366 | E10: =SUM('Moderna Standardized'!E6:E10) -> -421.431 | F10: =SUM('Moderna Standardized'!F6:F10) -> -464.752 | G10: =SUM('Moderna Standardized'!G6:G10) -> -541.361 | H10: =SUM('Moderna Standardized'!H6:H10) -> -1373.587 | I10: =SUM('Moderna Standardized'!I6:I10) -> -4377.82 | J10: =SUM('Moderna Standardized'!J6:J10) -> -9363.79 | K10: =SUM('Moderna Standardized'!K6:K10) -> -10253.962 | L10: =SUM('Moderna Standardized'!L6:L10) -> -6639.446
B11: Operating profit | D11: =SUM(D9:D10) -> -202.348 | E11: =SUM(E9:E10) -> -238.888 | F11: =SUM(F9:F10) -> -350.272 | G11: =SUM(G9:G10) -> -487.761 | H11: =SUM(H9:H10) -> -669.251 | I11: =SUM(I9:I10) -> 11247.825 | J11: =SUM(J9:J10) -> 8961.384 | K11: =SUM(K9:K10) -> -3920.497 | L11: =SUM(L9:L10) -> -3647.489
B12: Investment Income | D12: ='Moderna Standardized'!D13 -> 0 | E12: ='Moderna Standardized'!E13 -> 0 | F12: ='Moderna Standardized'!F13 -> 0 | G12: ='Moderna Standardized'!G13 -> 0 | H12: ='Moderna Standardized'!H13 -> 0 | I12: ='Moderna Standardized'!I13 -> 0 | J12: ='Moderna Standardized'!J13 -> 0 | K12: ='Moderna Standardized'!K13 -> 0 | L12: ='Moderna Standardized'!L13 -> 0
B13: Net non-recurring income or expense | D13: ='Moderna Standardized'!D14 -> -2.324 | E13: ='Moderna Standardized'!E14 -> -1.546 | F13: ='Moderna Standardized'!F14 -> 4.179 | G13: ='Moderna Standardized'!G14 -> -7.147 | H13: ='Moderna Standardized'!H14 -> 3.509 | I13: ='Moderna Standardized'!I14 -> -10.151 | J13: ='Moderna Standardized'!J14 -> -15.221 | K13: ='Moderna Standardized'!K14 -> -79.538 | L13: ='Moderna Standardized'!L14 -> -58.249
B14: Interest income | D14: ='Moderna Standardized'!D11 -> 10.229 | E14: ='Moderna Standardized'!E11 -> 13.512 | F14: ='Moderna Standardized'!F11 -> 22.904 | G14: ='Moderna Standardized'!G11 -> 34.84 | H14: ='Moderna Standardized'!H11 -> 21.928 | I14: ='Moderna Standardized'!I11 -> 15.227 | J14: ='Moderna Standardized'!J11 -> 190.263 | K14: ='Moderna Standardized'!K11 -> 389.368 | L14: ='Moderna Standardized'!L11 -> 392.949
B15: Interest expense | D15: ='Moderna Standardized'!D12 -> -0.126 | E15: ='Moderna Standardized'!E12 -> -0.117 | F15: ='Moderna Standardized'!F12 -> -2.624 | G15: ='Moderna Standardized'!G12 -> 0 | H15: ='Moderna Standardized'!H12 -> -8.771 | I15: ='Moderna Standardized'!I12 -> -14.381 | J15: ='Moderna Standardized'!J12 -> -27.588 | K15: ='Moderna Standardized'!K12 -> -35.145 | L15: ='Moderna Standardized'!L12 -> -22.19
B16: Profit before taxes | D16: =SUM(D11:D15) -> -194.569 | E16: =SUM(E11:E15) -> -227.039 | F16: =SUM(F11:F15) -> -325.813 | G16: =SUM(G11:G15) -> -460.068 | H16: =SUM(H11:H15) -> -652.585 | I16: =SUM(I11:I15) -> 11238.52 | J16: =SUM(J11:J15) -> 9108.838 | K16: =SUM(K11:K15) -> -3645.812 | L16: =SUM(L11:L15) -> -3334.979
B17: Tax expense | D17: ='Moderna Standardized'!D15 -> -0.943 | E17: ='Moderna Standardized'!E15 -> 0.071 | F17: ='Moderna Standardized'!F15 -> -0.276 | G17: ='Moderna Standardized'!G15 -> 0.893 | H17: ='Moderna Standardized'!H15 -> -2.631 | I17: ='Moderna Standardized'!I15 -> -916.17 | J17: ='Moderna Standardized'!J15 -> -1153.945 | K17: ='Moderna Standardized'!K15 -> -713.995 | L17: ='Moderna Standardized'!L15 -> 42.531
B18: Profit after taxes | D18: =SUM(D16:D17) -> -195.512 | E18: =SUM(E16:E17) -> -226.968 | F18: =SUM(F16:F17) -> -326.089 | G18: =SUM(G16:G17) -> -459.175 | H18: =SUM(H16:H17) -> -655.216 | I18: =SUM(I16:I17) -> 10322.35 | J18: =SUM(J16:J17) -> 7954.893 | K18: =SUM(K16:K17) -> -4359.807 | L18: =SUM(L16:L17) -> -3292.448
B19: Profit/loss to non-controlling interest | D19: ='Moderna Standardized'!D16 -> 0 | E19: ='Moderna Standardized'!E16 -> 0 | F19: ='Moderna Standardized'!F16 -> 0 | G19: ='Moderna Standardized'!G16 -> 0 | H19: ='Moderna Standardized'!H16 -> 0 | I19: ='Moderna Standardized'!I16 -> 0 | J19: ='Moderna Standardized'!J16 -> 0 | K19: ='Moderna Standardized'!K16 -> 0 | L19: ='Moderna Standardized'!L16 -> 0
B20: Profit/Loss of Discontinued Operations | D20: ='Moderna Standardized'!D17 -> 0 | E20: ='Moderna Standardized'!E17 -> 0 | F20: ='Moderna Standardized'!F17 -> 0 | G20: ='Moderna Standardized'!G17 -> 0 | H20: ='Moderna Standardized'!H17 -> 0 | I20: ='Moderna Standardized'!I17 -> 0 | J20: ='Moderna Standardized'!J17 -> 0 | K20: ='Moderna Standardized'!K17 -> 0 | L20: ='Moderna Standardized'!L17 -> 0
B21: Profit/loss to ordinary shareholders | D21: =SUM(D18:D20) -> -195.512 | E21: =SUM(E18:E20) -> -226.968 | F21: =SUM(F18:F20) -> -326.089 | G21: =SUM(G18:G20) -> -459.175 | H21: =SUM(H18:H20) -> -655.216 | I21: =SUM(I18:I20) -> 10322.35 | J21: =SUM(J18:J20) -> 7954.893 | K21: =SUM(K18:K20) -> -4359.807 | L21: =SUM(L18:L20) -> -3292.448
A23: x | B23: OPERATING EXPENSES
B24: Classification by function:
B25: Cost of Sales (by function) | D25: =+'Moderna Standardized'!D6 -> -248.416 | E25: =+'Moderna Standardized'!E6 -> -364.03 | F25: =+'Moderna Standardized'!F6 -> -384.867 | G25: =+'Moderna Standardized'!G6 -> -443.094 | H25: =+'Moderna Standardized'!H6 -> -1208.686 | I25: =+'Moderna Standardized'!I6 -> -3898.163 | J25: =+'Moderna Standardized'!J6 -> -8286.902 | K25: =+'Moderna Standardized'!K6 -> -8821.348 | L25: =+'Moderna Standardized'!L6 -> -5553.983
B26: SG&A (by function) | D26: =+'Moderna Standardized'!D8 -> -51.95 | E26: =+'Moderna Standardized'!E8 -> -57.401 | F26: =+'Moderna Standardized'!F8 -> -79.885 | G26: =+'Moderna Standardized'!G8 -> -98.267 | H26: =+'Moderna Standardized'!H8 -> -164.901 | I26: =+'Moderna Standardized'!I8 -> -479.657 | J26: =+'Moderna Standardized'!J8 -> -1076.888 | K26: =+'Moderna Standardized'!K8 -> -1432.614 | L26: =+'Moderna Standardized'!L8 -> -1085.463
B27: R&D Expenses | D27: =+'Moderna Standardized'!D9 -> 0 | E27: =+'Moderna Standardized'!E9 -> 0 | F27: =+'Moderna Standardized'!F9 -> 0 | G27: =+'Moderna Standardized'!G9 -> 0 | H27: =+'Moderna Standardized'!H9 -> 0 | I27: =+'Moderna Standardized'!I9 -> 0 | J27: =+'Moderna Standardized'!J9 -> 0 | K27: =+'Moderna Standardized'!K9 -> 0 | L27: =+'Moderna Standardized'!L9 -> 0
B28: Other Operating Income, Net of Other Operating Expense (by function) | D28: =+'Moderna Standardized'!D10 -> 0 | E28: =+'Moderna Standardized'!E10 -> 0 | F28: =+'Moderna Standardized'!F10 -> 0 | G28: =+'Moderna Standardized'!G10 -> 0 | H28: =+'Moderna Standardized'!H10 -> 0 | I28: =+'Moderna Standardized'!I10 -> 0 | J28: =+'Moderna Standardized'!J10 -> 0 | K28: =+'Moderna Standardized'!K10 -> 0 | L28: =+'Moderna Standardized'!L10 -> 0
B29: Classification by nature:
B30: Cost of Materials (by nature)
B31: Personnel Expenses (by nature)
B32: Depreciation and Amortization (by nature)
B33: Other Operating Income, Net of Other Operating Expense (by nature)
A35: x | B35: BALANCE SHEET
B36: ASSETS
B37: Non-Current Tangible Assets | D37: =SUM('Moderna Standardized'!D35) -> 77 | E37: =SUM('Moderna Standardized'!E35) -> 115.785 | F37: =SUM('Moderna Standardized'!F35) -> 185.141 | G37: =SUM('Moderna Standardized'!G35) -> 256.556 | H37: =SUM('Moderna Standardized'!H35) -> 316.373 | I37: =SUM('Moderna Standardized'!I35) -> 1216.072 | J37: =SUM('Moderna Standardized'!J35) -> 2001.462 | K37: =SUM('Moderna Standardized'!K35) -> 2404.693 | L37: =SUM('Moderna Standardized'!L35) -> 2854.235
B38: Non-Current Intangible Assets | D38: =SUM('Moderna Standardized'!D36) -> 11.599 | E38: =SUM('Moderna Standardized'!E36) -> 13.645 | F38: =SUM('Moderna Standardized'!F36) -> 12.381 | G38: =SUM('Moderna Standardized'!G36) -> 11.337 | H38: =SUM('Moderna Standardized'!H36) -> 10.628 | I38: =SUM('Moderna Standardized'!I36) -> 40.448 | J38: =SUM('Moderna Standardized'!J36) -> 885.172 | K38: =SUM('Moderna Standardized'!K36) -> 633.29 | L38: =SUM('Moderna Standardized'!L36) -> 560.222
B39: Other Non-Operating Investments | D39: =SUM('Moderna Standardized'!D37) -> 224.315 | E39: =SUM('Moderna Standardized'!E37) -> 121.465 | F39: =SUM('Moderna Standardized'!F37) -> 151.089 | G39: =SUM('Moderna Standardized'!G37) -> 142.564 | H39: =SUM('Moderna Standardized'!H37) -> 522.383 | I39: =SUM('Moderna Standardized'!I37) -> 6017.05 | J39: =SUM('Moderna Standardized'!J37) -> 7822.452 | K39: =SUM('Moderna Standardized'!K37) -> 4290.992 | L39: =SUM('Moderna Standardized'!L37) -> 2422.477
B40: Deferred Tax Asset | D40: ='Moderna Standardized'!D38 -> 0 | E40: ='Moderna Standardized'!E38 -> 0 | F40: ='Moderna Standardized'!F38 -> 0 | G40: ='Moderna Standardized'!G38 -> 0 | H40: ='Moderna Standardized'!H38 -> 0 | I40: ='Moderna Standardized'!I38 -> 286.652 | J40: ='Moderna Standardized'!J38 -> 918.857 | K40: ='Moderna Standardized'!K38 -> 0 | L40: ='Moderna Standardized'!L38 -> 0
B41: Total Non-Current Assets | D41: =SUM(D37:D40) -> 312.914 | E41: =SUM(E37:E40) -> 250.895 | F41: =SUM(F37:F40) -> 348.611 | G41: =SUM(G37:G40) -> 410.457 | H41: =SUM(H37:H40) -> 849.384 | I41: =SUM(I37:I40) -> 7560.222 | J41: =SUM(J37:J40) -> 11627.943 | K41: =SUM(K37:K40) -> 7328.975 | L41: =SUM(L37:L40) -> 5836.934
B43: Inventories | D43: ='Moderna Standardized'!D33 -> 0 | E43: ='Moderna Standardized'!E33 -> 0 | F43: ='Moderna Standardized'!F33 -> 0 | G43: ='Moderna Standardized'!G33 -> 0 | H43: ='Moderna Standardized'!H33 -> 38.423 | I43: ='Moderna Standardized'!I33 -> 1519.43 | J43: ='Moderna Standardized'!J33 -> 1092.898 | K43: ='Moderna Standardized'!K33 -> 182.749 | L43: ='Moderna Standardized'!L33 -> 113.01
B44: Trade Receivables | D44: ='Moderna Standardized'!D32 -> 12.823 | E44: ='Moderna Standardized'!E32 -> 11.174 | F44: ='Moderna Standardized'!F32 -> 10.992 | G44: ='Moderna Standardized'!G32 -> 4.784 | H44: ='Moderna Standardized'!H32 -> 1137.143 | I44: ='Moderna Standardized'!I32 -> 2791.778 | J44: ='Moderna Standardized'!J32 -> 1329.63 | K44: ='Moderna Standardized'!K32 -> 806.992 | L44: ='Moderna Standardized'!L32 -> 345.792
B45: Other Current Assets | D45: ='Moderna Standardized'!D34 -> 14.689 | E45: ='Moderna Standardized'!E34 -> 11.473 | F45: ='Moderna Standardized'!F34 -> 25.323 | G45: ='Moderna Standardized'!G34 -> 18.21 | H45: ='Moderna Standardized'!H34 -> 206.012 | I45: ='Moderna Standardized'!I34 -> 387.771 | J45: ='Moderna Standardized'!J34 -> 879.558 | K45: ='Moderna Standardized'!K34 -> 567.246 | L45: ='Moderna Standardized'!L34 -> 578.575
B46: Cash and Cash Equivalents | D46: ='Moderna Standardized'!D31 -> 1003.327 | E46: ='Moderna Standardized'!E31 -> 629.621 | F46: ='Moderna Standardized'!F31 -> 1328.814 | G46: ='Moderna Standardized'!G31 -> 982.883 | H46: ='Moderna Standardized'!H31 -> 3767.04 | I46: ='Moderna Standardized'!I31 -> 9432.251 | J46: ='Moderna Standardized'!J31 -> 9265.302 | K46: ='Moderna Standardized'!K31 -> 7784.039 | L46: ='Moderna Standardized'!L31 -> 6785.447
B47: Total Current Assets | D47: =SUM(D43:D46) -> 1030.839 | E47: =SUM(E43:E46) -> 652.268 | F47: =SUM(F43:F46) -> 1365.129 | G47: =SUM(G43:G46) -> 1005.877 | H47: =SUM(H43:H46) -> 5148.618 | I47: =SUM(I43:I46) -> 14131.23 | J47: =SUM(J43:J46) -> 12567.388 | K47: =SUM(K43:K46) -> 9341.026 | L47: =SUM(L43:L46) -> 7822.824
B50: Total Assets | D50: =SUM(D41,D47) -> 1343.753 | E50: =SUM(E41,E47) -> 903.163 | F50: =SUM(F41,F47) -> 1713.74 | G50: =SUM(G41,G47) -> 1416.334 | H50: =SUM(H41,H47) -> 5998.002 | I50: =SUM(I41,I47) -> 21691.452 | J50: =SUM(J41,J47) -> 24195.331 | K50: =SUM(K41,K47) -> 16670.001 | L50: =SUM(L41,L47) -> 13659.758
B52: LIABILITIES AND SHAREHOLDERS' EQUITY
B53: Ordinary Shareholders' Equity | D53: ='Moderna Standardized'!D50 -> -317.467 | E53: ='Moderna Standardized'!E50 -> -459.177 | F53: ='Moderna Standardized'!F50 -> 1336.513 | G53: ='Moderna Standardized'!G50 -> 1046.874 | H53: ='Moderna Standardized'!H50 -> 2093.618 | I53: ='Moderna Standardized'!I50 -> 12437.698 | J53: ='Moderna Standardized'!J50 -> 17893.391 | K53: ='Moderna Standardized'!K50 -> 12533.714 | L53: ='Moderna Standardized'!L50 -> 10529.276
B54: Preference Shares | D54: ='Moderna Standardized'!D51 -> 1115.71 | E54: ='Moderna Standardized'!E51 -> 979.923 | F54: ='Moderna Standardized'!F51 -> 0 | G54: ='Moderna Standardized'!G51 -> 0 | H54: ='Moderna Standardized'!H51 -> 0 | I54: ='Moderna Standardized'!I51 -> 0 | J54: ='Moderna Standardized'!J51 -> 0 | K54: ='Moderna Standardized'!K51 -> 0 | L54: ='Moderna Standardized'!L51 -> 0
B55: Non-Controlling Interest in Equity | D55: ='Moderna Standardized'!D49 -> 0 | E55: ='Moderna Standardized'!E49 -> 0 | F55: ='Moderna Standardized'!F49 -> 0 | G55: ='Moderna Standardized'!G49 -> 0 | H55: ='Moderna Standardized'!H49 -> 0 | I55: ='Moderna Standardized'!I49 -> 0 | J55: ='Moderna Standardized'!J49 -> 0 | K55: ='Moderna Standardized'!K49 -> 0 | L55: ='Moderna Standardized'!L49 -> 0
B58: Non-Current Debt | D58: ='Moderna Standardized'!D46 -> 11.853 | E58: ='Moderna Standardized'!E46 -> 13.064 | F58: ='Moderna Standardized'!F46 -> 29.249 | G58: ='Moderna Standardized'!G46 -> 117.95 | H58: ='Moderna Standardized'!H46 -> 169.223 | I58: ='Moderna Standardized'!I46 -> 619.907 | J58: ='Moderna Standardized'!J46 -> 939.443 | K58: ='Moderna Standardized'!K46 -> 1101.925 | L58: ='Moderna Standardized'!L46 -> 685.789
B59: Deferred Tax Liability | D59: ='Moderna Standardized'!D47 -> 0 | E59: ='Moderna Standardized'!E47 -> 0 | F59: ='Moderna Standardized'!F47 -> 0 | G59: ='Moderna Standardized'!G47 -> 0 | H59: ='Moderna Standardized'!H47 -> 0 | I59: ='Moderna Standardized'!I47 -> 0 | J59: ='Moderna Standardized'!J47 -> 0 | K59: ='Moderna Standardized'!K47 -> 0 | L59: ='Moderna Standardized'!L47 -> 0
B60: Other Non-Current Liabilities (non interest bearing) | D60: ='Moderna Standardized'!D48 -> 379.288 | E60: ='Moderna Standardized'!E48 -> 209.903 | F60: ='Moderna Standardized'!F48 -> 153.383 | G60: ='Moderna Standardized'!G48 -> 123.981 | H60: ='Moderna Standardized'!H48 -> 147.151 | I60: ='Moderna Standardized'!I48 -> 607.597 | J60: ='Moderna Standardized'!J48 -> 756.046 | K60: ='Moderna Standardized'!K48 -> 306.693 | L60: ='Moderna Standardized'!L48 -> 313.917
B61: Non-Current Liabilities | D61: =SUM(D58:D60) -> 391.141 | E61: =SUM(E58:E60) -> 222.967 | F61: =SUM(F58:F60) -> 182.632 | G61: =SUM(G58:G60) -> 241.931 | H61: =SUM(H58:H60) -> 316.374 | I61: =SUM(I58:I60) -> 1227.504 | J61: =SUM(J58:J60) -> 1695.489 | K61: =SUM(K58:K60) -> 1408.618 | ... Q61: =SUM(Q58:Q60) -> 0
B63: Trade Payables | D63: ='Moderna Standardized'!D44 -> 26.698 | E63: ='Moderna Standardized'!E44 -> 17.26 | F63: ='Moderna Standardized'!F44 -> 27.259 | G63: ='Moderna Standardized'!G44 -> 6.318 | H63: ='Moderna Standardized'!H44 -> 14.715 | I63: ='Moderna Standardized'!I44 -> 265.549 | J63: ='Moderna Standardized'!J44 -> 455.686 | K63: ='Moderna Standardized'!K44 -> 470.444 | L63: ='Moderna Standardized'!L44 -> 391.19
B64: Other Current Liabilities | D64: ='Moderna Standardized'!D45 -> 127.671 | E64: ='Moderna Standardized'!E45 -> 142.189 | F64: ='Moderna Standardized'!F45 -> 167.338 | G64: ='Moderna Standardized'!G45 -> 118.019 | H64: ='Moderna Standardized'!H45 -> 3548.768 | I64: ='Moderna Standardized'!I45 -> 7575.17 | J64: ='Moderna Standardized'!J45 -> 3967.369 | K64: ='Moderna Standardized'!K45 -> 2234.609 | L64: ='Moderna Standardized'!L45 -> 1703.848
B65: Current Debt | D65: ='Moderna Standardized'!D43 -> 0 | E65: ='Moderna Standardized'!E43 -> 0 | F65: ='Moderna Standardized'!F43 -> 0 | G65: ='Moderna Standardized'!G43 -> 3.193 | H65: ='Moderna Standardized'!H43 -> 24.525 | I65: ='Moderna Standardized'!I43 -> 185.532 | J65: ='Moderna Standardized'!J43 -> 183.397 | K65: ='Moderna Standardized'!K43 -> 22.618 | L65: ='Moderna Standardized'!L43 -> 35.738
B66: Current Liabilities | D66: =SUM(D63:D65) -> 154.369 | E66: =SUM(E63:E65) -> 159.449 | F66: =SUM(F63:F65) -> 194.597 | G66: =SUM(G63:G65) -> 127.53 | H66: =SUM(H63:H65) -> 3588.008 | I66: =SUM(I63:I65) -> 8026.251 | J66: =SUM(J63:J65) -> 4606.452 | K66: =SUM(K63:K65) -> 2727.671 | ... Q66: =SUM(Q63:Q65) -> 0
B69: Total Liabilities and Shareholders' Equity | C69: =SUM(C53:C55,C61,C66) -> 0 | D69: =SUM(D53:D55,D61,D66) -> 1343.753 | E69: =SUM(E53:E55,E61,E66) -> 903.162 | F69: =SUM(F53:F55,F61,F66) -> 1713.742 | G69: =SUM(G53:G55,G61,G66) -> 1416.335 | H69: =SUM(H53:H55,H61,H66) -> 5998 | I69: =SUM(I53:I55,I61,I66) -> 21691.453 | J69: =SUM(J53:J55,J61,J66) -> 24195.332 | ... L69: =SUM(L53:L55,L61,L66) -> 13659.758
B70: Check | D70: =D50-D69 -> 0 | E70: =E50-E69 -> 0.001 | F70: =F50-F69 -> -0.002 | G70: =G50-G69 -> -0.001 | H70: =H50-H69 -> 0.002 | I70: =I50-I69 -> -0.001 | J70: =J50-J69 -> -0.001 | K70: =K50-K69 -> -0.002 | L70: =L50-L69 -> 0 | M70: =M69-M50 -> 0 | N70: =N69-N50 -> 0 | O70: =O69-O50 -> 0 | P70: =P69-P50 -> 0 | Q70: =Q69-Q50 -> 0
A71: x | B71: CASH FLOW STATEMENT
B72: Profit Before Interest and Tax | D72: ='Moderna Standardized'!D56 -> -204.672 | E72: ='Moderna Standardized'!E56 -> -240.434 | F72: ='Moderna Standardized'!F56 -> -346.093 | G72: ='Moderna Standardized'!G56 -> -494.908 | H72: ='Moderna Standardized'!H56 -> -665.742 | I72: ='Moderna Standardized'!I56 -> 11237.674 | J72: ='Moderna Standardized'!J56 -> 8946.163 | K72: ='Moderna Standardized'!K56 -> -4000.035 | L72: ='Moderna Standardized'!L56 -> -3705.738
B73: Taxes Paid | D73: ='Moderna Standardized'!D60 -> -0.943 | E73: ='Moderna Standardized'!E60 -> 0.071 | F73: ='Moderna Standardized'!F60 -> -0.276 | G73: ='Moderna Standardized'!G60 -> 0.893 | H73: ='Moderna Standardized'!H60 -> -2.631 | I73: ='Moderna Standardized'!I60 -> -175.113 | J73: ='Moderna Standardized'!J60 -> -1153.945 | K73: ='Moderna Standardized'!K60 -> -713.995 | L73: ='Moderna Standardized'!L60 -> 42.531
B74: Non-Operating Losses (Gains) | D74: ='Moderna Standardized'!D58 -> 2.241 | E74: ='Moderna Standardized'!E58 -> 0.963 | F74: ='Moderna Standardized'!F58 -> -0.827 | G74: ='Moderna Standardized'!G58 -> -3.573 | H74: ='Moderna Standardized'!H58 -> 8.771 | I74: ='Moderna Standardized'!I58 -> 45.682 | J74: ='Moderna Standardized'!J58 -> 29.491 | K74: ='Moderna Standardized'!K58 -> -24.046 | L74: ='Moderna Standardized'!L58 -> -39.757
B75: Non-Current Operating Accruals | D75: ='Moderna Standardized'!D59 -> 52.454 | E75: ='Moderna Standardized'!E59 -> 87.205 | F75: ='Moderna Standardized'!F59 -> 88.363 | G75: ='Moderna Standardized'!G59 -> 107.2 | H75: ='Moderna Standardized'!H59 -> 299.978 | I75: ='Moderna Standardized'!I59 -> 539.72 | J75: ='Moderna Standardized'!J59 -> -1690.486 | K75: ='Moderna Standardized'!K59 -> 2246.493 | L75: ='Moderna Standardized'!L59 -> 453.972
B76: Operating Cash Flow before Working Capital Investments | D76: =SUM(D72:D75) -> -150.92 | E76: =SUM(E72:E75) -> -152.195 | F76: =SUM(F72:F75) -> -258.833 | G76: =SUM(G72:G75) -> -390.388 | H76: =SUM(H72:H75) -> -359.624 | I76: =SUM(I72:I75) -> 11647.963 | J76: =SUM(J72:J75) -> 6131.223 | K76: =SUM(K72:K75) -> -2491.583 | ... Q76: =SUM(Q72:Q75) -> 0
B78: Net (Investments in) or Liquidation of Operating Working Capital | D78: ='Moderna Standardized'!D63 -> 201.16 | E78: ='Moderna Standardized'!E63 -> -155.188 | F78: ='Moderna Standardized'!F63 -> -41.88 | G78: ='Moderna Standardized'!G63 -> -54.494 | H78: ='Moderna Standardized'!H63 -> 2124.411 | I78: ='Moderna Standardized'!I63 -> -126.894 | J78: ='Moderna Standardized'!J63 -> -1555.399 | K78: ='Moderna Standardized'!K63 -> -746.365 | L78: ='Moderna Standardized'!L63 -> 100.78
B79: Operating Cash Flow before Investment in Non-Current Assets | D79: =SUM(D78,D76) -> 50.24 | E79: =SUM(E78,E76) -> -307.383 | F79: =SUM(F78,F76) -> -300.713 | G79: =SUM(G78,G76) -> -444.882 | H79: =SUM(H78,H76) -> 1764.787 | I79: =SUM(I78,I76) -> 11521.069 | J79: =SUM(J78,J76) -> 4575.824 | K79: =SUM(K78,K76) -> -3237.948 | L79: =SUM(L78,L76) -> -3148.212 | M79: =SUM(M76:M78) -> 0 | N79: =SUM(N76:N78) -> 0 | O79: =SUM(O76:O78) -> 0 | P79: =SUM(P76:P78) -> 0 | Q79: =SUM(Q76:Q78) -> 0
B81: Interest Received | D81: ='Moderna Standardized'!D61 -> 10.229 | E81: ='Moderna Standardized'!E61 -> 13.512 | F81: ='Moderna Standardized'!F61 -> 22.904 | G81: ='Moderna Standardized'!G61 -> 34.84 | H81: ='Moderna Standardized'!H61 -> 21.928 | I81: ='Moderna Standardized'!I61 -> 15.227 | J81: ='Moderna Standardized'!J61 -> 190.263 | K81: ='Moderna Standardized'!K61 -> 389.368 | L81: ='Moderna Standardized'!L61 -> 392.949
B82: Dividends received | D82: ='Moderna Standardized'!D62 -> 0 | E82: ='Moderna Standardized'!E62 -> 0 | F82: ='Moderna Standardized'!F62 -> 0 | G82: ='Moderna Standardized'!G62 -> 0 | H82: ='Moderna Standardized'!H62 -> 0 | I82: ='Moderna Standardized'!I62 -> 0 | J82: ='Moderna Standardized'!J62 -> 0 | K82: ='Moderna Standardized'!K62 -> 0 | L82: ='Moderna Standardized'!L62 -> 0
B83: Net (Investments in) or Liquidation of Non-Current Operating or Investment Assets | D83: ='Moderna Standardized'!D64 -> -586.51 | E83: ='Moderna Standardized'!E64 -> 370.154 | F83: ='Moderna Standardized'!F64 -> -316.224 | G83: ='Moderna Standardized'!G64 -> -13.4 | H83: ='Moderna Standardized'!H64 -> -1466.562 | I83: ='Moderna Standardized'!I64 -> -7210.079 | J83: ='Moderna Standardized'!J64 -> -4924.005 | K83: ='Moderna Standardized'!K64 -> 3889.976 | L83: ='Moderna Standardized'!L64 -> 1802.016
B84: Free Cash Flow Available to Debt and Equity | D84: =SUM(D81:D83,D79) -> -526.041 | E84: =SUM(E81:E83,E79) -> 76.283 | F84: =SUM(F81:F83,F79) -> -594.033 | G84: =SUM(G81:G83,G79) -> -423.442 | H84: =SUM(H81:H83,H79) -> 320.153 | I84: =SUM(I81:I83,I79) -> 4326.217 | J84: =SUM(J81:J83,J79) -> -157.918 | K84: =SUM(K81:K83,K79) -> 1041.396 | L84: =SUM(L81:L83,L79) -> -953.247 | M84: =SUM(M79:M83) -> 0 | N84: =SUM(N79:N83) -> 0 | O84: =SUM(O79:O83) -> 0 | P84: =SUM(P79:P83) -> 0 | Q84: =SUM(Q79:Q83) -> 0
B86: Interest Paid | D86: ='Moderna Standardized'!D68 -> -0.126 | E86: ='Moderna Standardized'!E68 -> -0.117 | F86: ='Moderna Standardized'!F68 -> -2.624 | G86: ='Moderna Standardized'!G68 -> 0 | H86: ='Moderna Standardized'!H68 -> -8.771 | I86: ='Moderna Standardized'!I68 -> -14.381 | J86: ='Moderna Standardized'!J68 -> -27.588 | K86: ='Moderna Standardized'!K68 -> -35.145 | L86: ='Moderna Standardized'!L68 -> -22.19
B87: Net Debt (Repayment) or Issuance | D87: ='Moderna Standardized'!D67 -> 0 | E87: ='Moderna Standardized'!E67 -> 1.276 | F87: ='Moderna Standardized'!F67 -> 8.019 | G87: ='Moderna Standardized'!G67 -> 0.893 | H87: ='Moderna Standardized'!H67 -> -5.263 | I87: ='Moderna Standardized'!I67 -> -118.434 | J87: ='Moderna Standardized'!J67 -> -175.042 | K87: ='Moderna Standardized'!K67 -> -249.713 | L87: ='Moderna Standardized'!L67 -> -9.246
B88: Free Cash Flow Available to Equity | D88: =SUM(D86:D87,D84) -> -526.167 | E88: =SUM(E86:E87,E84) -> 77.442 | F88: =SUM(F86:F87,F84) -> -588.638 | G88: =SUM(G86:G87,G84) -> -422.549 | H88: =SUM(H86:H87,H84) -> 306.119 | I88: =SUM(I86:I87,I84) -> 4193.402 | J88: =SUM(J86:J87,J84) -> -360.548 | K88: =SUM(K86:K87,K84) -> 756.538 | L88: =SUM(L86:L87,L84) -> -984.683 | M88: =SUM(M84:M87) -> 0 | N88: =SUM(N84:N87) -> 0 | O88: =SUM(O84:O87) -> 0 | P88: =SUM(P84:P87) -> 0 | Q88: =SUM(Q84:Q87) -> 0
B90: Dividend (Payments) | D90: ='Moderna Standardized'!D69 -> -0.572 | E90: ='Moderna Standardized'!E69 -> -1.315 | F90: ='Moderna Standardized'!F69 -> 0 | G90: ='Moderna Standardized'!G69 -> 0 | H90: ='Moderna Standardized'!H69 -> 0 | I90: ='Moderna Standardized'!I69 -> 0 | J90: ='Moderna Standardized'!J69 -> 0 | K90: ='Moderna Standardized'!K69 -> 0 | L90: ='Moderna Standardized'!L69 -> 0
B91: Net share (Repurchase) or Issuance | D91: ='Moderna Standardized'!D70 -> 428.206 | E91: ='Moderna Standardized'!E70 -> 0.188 | F91: ='Moderna Standardized'!F70 -> 1031.819 | G91: ='Moderna Standardized'!G70 -> 45.56 | H91: ='Moderna Standardized'!H70 -> 1788.469 | I91: ='Moderna Standardized'!I70 -> -620.086 | J91: ='Moderna Standardized'!J70 -> -3105.091 | K91: ='Moderna Standardized'!K70 -> -1023.824 | L91: ='Moderna Standardized'!L70 -> 61.023
B92: Misc. Cash Flow & Exchange rate | D92: ='Moderna Standardized'!D71 -> 0 | E92: ='Moderna Standardized'!E71 -> 0 | F92: ='Moderna Standardized'!F71 -> 0 | G92: ='Moderna Standardized'!G71 -> 0 | H92: ='Moderna Standardized'!H71 -> 0 | I92: ='Moderna Standardized'!I71 -> 0 | J92: ='Moderna Standardized'!J71 -> 0 | K92: ='Moderna Standardized'!K71 -> 0 | L92: ='Moderna Standardized'!L71 -> 0
B93: Net Increase (Decrease) in Cash Balance | D93: =SUM(D88,D92) -> -526.167 | E93: =SUM(E88,E92) -> 77.442 | F93: =SUM(F88,F92) -> -588.638 | G93: =SUM(G88,G92) -> -422.549 | H93: =SUM(H88,H92) -> 306.119 | I93: =SUM(I88,I92) -> 4193.402 | J93: =SUM(J88,J92) -> -360.548 | K93: =SUM(K88,K92) -> 756.538 | L93: =SUM(L88,L92) -> -984.683 | M93: =SUM(M88:M91) -> 0 | N93: =SUM(N88:N91) -> 0 | O93: =SUM(O88:O91) -> 0 | P93: =SUM(P88:P91) -> 0 | Q93: =SUM(Q88:Q91) -> 0
A95: x | B95: CONDENSED STATEMENTS OF EARNINGS
B96: Revenue | D96: =D9 -> 98.018 | E96: =E9 -> 182.543 | F96: =F9 -> 114.48 | G96: =G9 -> 53.6 | H96: =H9 -> 704.336 | I96: =I9 -> 15625.645 | J96: =J9 -> 18325.174 | K96: =K9 -> 6333.465 | ... R96: =R9 -> 0
B97: Net operating profit after tax | D97: =D101 -> -195.512 | E97: =E101 -> -226.968 | F97: =F101 -> -326.089 | G97: =G101 -> -459.175 | H97: =H101 -> -655.216 | I97: =I101 -> 10322.35 | J97: =J101 -> 7954.893 | K97: =K101 -> -4359.807 | ... R97: =R101 -> 0
B98: Profit or loss | D98: =D18 -> -195.512 | E98: =E18 -> -226.968 | F98: =F18 -> -326.089 | G98: =G18 -> -459.175 | H98: =H18 -> -655.216 | I98: =I18 -> 10322.35 | J98: =J18 -> 7954.893 | K98: =K18 -> -4359.807 | ... R98: =R18 -> 0
B99: – Investment profit after tax | D99: =-D106 -> 0 | E99: =-E106 -> 0 | F99: =-F106 -> 0 | G99: =-G106 -> 0 | H99: =-H106 -> 0 | I99: =-I106 -> 0 | J99: =-J106 -> 0 | K99: =-K106 -> 0 | ... R99: =-R106 -> 0
B100: + Interest expense after tax | D100: =D110 -> 0 | E100: =E110 -> 0 | F100: =F110 -> 0 | G100: =G110 -> 0 | H100: =H110 -> 0 | I100: =I110 -> 0 | J100: =J110 -> 0 | K100: =K110 -> 0 | ... R100: =R110 -> 0
B101: = Net operating profit after tax | D101: =SUM(D98:D100) -> -195.512 | E101: =SUM(E98:E100) -> -226.968 | F101: =SUM(F98:F100) -> -326.089 | G101: =SUM(G98:G100) -> -459.175 | H101: =SUM(H98:H100) -> -655.216 | I101: =SUM(I98:I100) -> 10322.35 | J101: =SUM(J98:J100) -> 7954.893 | K101: =SUM(K98:K100) -> -4359.807 | ... R101: =SUM(R98:R100) -> 0
B102: of which: Net non-recurring expense after tax | D102: =D105 -> 0 | E102: =E105 -> 0 | F102: =F105 -> 0 | G102: =G105 -> 0 | H102: =H105 -> 0 | I102: =I105 -> 0 | J102: =J105 -> 0 | K102: =K105 -> 0 | ... R102: =R105 -> 0
B103: = Net non-recurring expense (income) | D103: =-D13 -> 2.324 | E103: =-E13 -> 1.546 | F103: =-F13 -> -4.179 | G103: =-G13 -> 7.147 | H103: =-H13 -> -3.509 | I103: =-I13 -> 10.151 | J103: =-J13 -> 15.221 | K103: =-K13 -> 79.538 | ... R103: =-R13 -> 0
B104: x (1 – Tax rate) | D104: =$C$4 -> 0 | E104: =$C$4 -> 0 | F104: =$C$4 -> 0 | G104: =$C$4 -> 0 | H104: =$C$4 -> 0 | I104: =$C$4 -> 0 | J104: =$C$4 -> 0 | K104: =$C$4 -> 0 | L104: =$C$4 -> 0
B105: = Net non-recurring expense after tax | D105: =D104*D103 -> 0 | E105: =E104*E103 -> 0 | F105: =F104*F103 -> 0 | G105: =G104*G103 -> 0 | H105: =H104*H103 -> 0 | I105: =I104*I103 -> 0 | J105: =J104*J103 -> 0 | K105: =K104*K103 -> 0 | ... R105: =R104*R103 -> 0
B106: + Net investment profit after tax | D106: =D109 -> 0 | E106: =E109 -> 0 | F106: =F109 -> 0 | G106: =G109 -> 0 | H106: =H109 -> 0 | I106: =I109 -> 0 | J106: =J109 -> 0 | K106: =K109 -> 0 | ... R106: =R109 -> 0
B107: = Investment and interest income | D107: =D12+D14 -> 10.229 | E107: =E12+E14 -> 13.512 | F107: =F12+F14 -> 22.904 | G107: =G12+G14 -> 34.84 | H107: =H12+H14 -> 21.928 | I107: =I12+I14 -> 15.227 | J107: =J12+J14 -> 190.263 | K107: =K12+K14 -> 389.368 | ... R107: =R12+R14 -> 0
B108: x (1 – Tax rate) | D108: =$C$4 -> 0 | E108: =$C$4 -> 0 | F108: =$C$4 -> 0 | G108: =$C$4 -> 0 | H108: =$C$4 -> 0 | I108: =$C$4 -> 0 | J108: =$C$4 -> 0 | K108: =$C$4 -> 0 | L108: =$C$4 -> 0
B109: = Net investment profit after tax | D109: =D108*D107 -> 0 | E109: =E108*E107 -> 0 | F109: =F108*F107 -> 0 | G109: =G108*G107 -> 0 | H109: =H108*H107 -> 0 | I109: =I108*I107 -> 0 | J109: =J108*J107 -> 0 | K109: =K108*K107 -> 0 | ... R109: =R108*R107 -> 0
B110: – Interest expense after tax | D110: =D113 -> 0 | E110: =E113 -> 0 | F110: =F113 -> 0 | G110: =G113 -> 0 | H110: =H113 -> 0 | I110: =I113 -> 0 | J110: =J113 -> 0 | K110: =K113 -> 0 | ... R110: =R113 -> 0
B111: = Interest expense | D111: =-(D15) -> 0.126 | E111: =-(E15) -> 0.117 | F111: =-(F15) -> 2.624 | G111: =-(G15) -> 0 | H111: =-(H15) -> 8.771 | I111: =-(I15) -> 14.381 | J111: =-(J15) -> 27.588 | K111: =-(K15) -> 35.145 | ... R111: =-(R15) -> 0
B112: x (1 – Tax rate) | D112: =$C$4 -> 0 | E112: =$C$4 -> 0 | F112: =$C$4 -> 0 | G112: =$C$4 -> 0 | H112: =$C$4 -> 0 | I112: =$C$4 -> 0 | J112: =$C$4 -> 0 | K112: =$C$4 -> 0 | L112: =$C$4 -> 0
B113: = Interest expense after tax | D113: =D112*D111 -> 0 | E113: =E112*E111 -> 0 | F113: =F112*F111 -> 0 | G113: =G112*G111 -> 0 | H113: =H112*H111 -> 0 | I113: =I112*I111 -> 0 | J113: =J112*J111 -> 0 | K113: =K112*K111 -> 0 | ... R113: =R112*R111 -> 0
B114: = Profit or loss | D114: =D101+D106-D110 -> -195.512 | E114: =E101+E106-E110 -> -226.968 | F114: =F101+F106-F110 -> -326.089 | G114: =G101+G106-G110 -> -459.175 | H114: =H101+H106-H110 -> -655.216 | I114: =I101+I106-I110 -> 10322.35 | J114: =J101+J106-J110 -> 7954.893 | K114: =K101+K106-K110 -> -4359.807 | ... R114: =R101+R106-R110 -> 0
A116: x | B116: CONDENSED BALANCE SHEETS
B117: Ending operating working capital
B118: Operating cash | D118: =MIN(D3*D9,D46) -> 0 | E118: =MIN(E3*E9,E46) -> 9.12715 | F118: =MIN(F3*F9,F46) -> 5.724 | G118: =MIN(G3*G9,G46) -> 2.68 | H118: =MIN(H3*H9,H46) -> 35.2168 | I118: =MIN(I3*I9,I46) -> 781.28225 | J118: =MIN(J3*J9,J46) -> 916.2587 | K118: =MIN(K3*K9,K46) -> 316.67325 | ... R118: =MIN(R3*R9,R46) -> 0
B119: + Trade receivables | D119: =D44 -> 12.823 | E119: =E44 -> 11.174 | F119: =F44 -> 10.992 | G119: =G44 -> 4.784 | H119: =H44 -> 1137.143 | I119: =I44 -> 2791.778 | J119: =J44 -> 1329.63 | K119: =K44 -> 806.992 | ... R119: =R44 -> 0
B120: + Inventories | D120: =D43 -> 0 | E120: =E43 -> 0 | F120: =F43 -> 0 | G120: =G43 -> 0 | H120: =H43 -> 38.423 | I120: =I43 -> 1519.43 | J120: =J43 -> 1092.898 | K120: =K43 -> 182.749 | ... R120: =R43 -> 0
...

Sheet Sanofi Adjusted
B2: Assumptions: | C2: 2015 | D2: =C2+1 -> 2016 | E2: =D2+1 -> 2017 | F2: =E2+1 -> 2018 | G2: =F2+1 -> 2019 | H2: =G2+1 -> 2020 | I2: =H2+1 -> 2021 | J2: =I2+1 -> 2022 | K2: =J2+1 -> 2023 | ... Q2: =P2+1 -> 2029
B3: Operating cash percentage | E3: 0.05 | F3: 0.05 | G3: 0.05 | H3: 0.05 | I3: 0.05 | J3: 0.05 | K3: 0.05 | L3: 0.05 | M3: 0.05 | N3: 0.05 | O3: 0.05 | P3: 0.05 | Q3: 0.05
B4: Tax Rate | E4: =-E17/E11 -> 0.23676612 | F4: =-F17/F11 -> 0.079847278 | G4: =-G17/G11 -> 0.017788886 | H4: =-H17/H11 -> 0.23842196 | I4: =-I17/I11 -> 0.18190309 | J4: =-J17/J11 -> 0.18389365 | K4: =-K17/K11 -> 0.12523088
B5: Pre-Adjustment (from Standardized)
A8: x | B8: INCOME STATEMENT
B9: Revenue | C9: ='Sanofi Standardized'!C5 -> 34861 | D9: ='Sanofi Standardized'!D5 -> 34696 | E9: ='Sanofi Standardized'!E5 -> 36221 | F9: ='Sanofi Standardized'!F5 -> 35677 | G9: ='Sanofi Standardized'!G5 -> 37631 | H9: ='Sanofi Standardized'!H5 -> 37369 | I9: ='Sanofi Standardized'!I5 -> 39175 | J9: ='Sanofi Standardized'!J5 -> 40304 | ... L9: ='Sanofi Standardized'!L5 -> 44286
B10: Operating expenses | C10: =SUM('Sanofi Standardized'!C6:C10) -> -27890 | D10: =SUM('Sanofi Standardized'!D6:D10) -> -27178 | E10: =SUM('Sanofi Standardized'!E6:E10) -> -28948 | F10: =SUM('Sanofi Standardized'!F6:F10) -> -29653 | G10: =SUM('Sanofi Standardized'!G6:G10) -> -30829 | H10: =SUM('Sanofi Standardized'!H6:H10) -> -29790 | I10: =SUM('Sanofi Standardized'!I6:I10) -> -30610 | J10: =SUM('Sanofi Standardized'!J6:J10) -> -29923 | ... L10: =SUM('Sanofi Standardized'!L6:L10) -> -35417
B11: Operating profit | C11: =SUM(C9:C10) -> 6971 | D11: =SUM(D9:D10) -> 7518 | E11: =SUM(E9:E10) -> 7273 | F11: =SUM(F9:F10) -> 6024 | G11: =SUM(G9:G10) -> 6802 | H11: =SUM(H9:H10) -> 7579 | I11: =SUM(I9:I10) -> 8565 | J11: =SUM(J9:J10) -> 10381 | ... L11: =SUM(L9:L10) -> 8869
B12: Investment Income | C12: ='Sanofi Standardized'!C13 -> -22 | D12: ='Sanofi Standardized'!D13 -> -110 | E12: ='Sanofi Standardized'!E13 -> 85 | F12: ='Sanofi Standardized'!F13 -> 562 | G12: ='Sanofi Standardized'!G13 -> 255 | H12: ='Sanofi Standardized'!H13 -> 7747 | I12: ='Sanofi Standardized'!I13 -> 42 | J12: ='Sanofi Standardized'!J13 -> 56 | ... L12: ='Sanofi Standardized'!L13 -> 60
B13: Net non-recurring income or expense | C13: ='Sanofi Standardized'!C14 -> -1369 | D13: ='Sanofi Standardized'!D14 -> -1293 | E13: ='Sanofi Standardized'!E14 -> -1452 | F13: ='Sanofi Standardized'!F14 -> -1283 | G13: ='Sanofi Standardized'!G14 -> -3597 | H13: ='Sanofi Standardized'!H14 -> -767 | I13: ='Sanofi Standardized'!I14 -> -411 | J13: ='Sanofi Standardized'!J14 -> -282 | ... L13: ='Sanofi Standardized'!L14 -> -1943
B14: Interest income | C14: ='Sanofi Standardized'!C11 -> 57 | D14: ='Sanofi Standardized'!D11 -> 56 | E14: ='Sanofi Standardized'!E11 -> 56 | F14: ='Sanofi Standardized'!F11 -> 72 | G14: ='Sanofi Standardized'!G11 -> 91 | H14: ='Sanofi Standardized'!H11 -> 37 | I14: ='Sanofi Standardized'!I11 -> 3 | J14: ='Sanofi Standardized'!J11 -> 239 | ... L14: ='Sanofi Standardized'!L11 -> 413
B15: Interest expense | C15: ='Sanofi Standardized'!C12 -> -416 | D15: ='Sanofi Standardized'!D12 -> -360 | E15: ='Sanofi Standardized'!E12 -> -346 | F15: ='Sanofi Standardized'!F12 -> -471 | G15: ='Sanofi Standardized'!G12 -> -544 | H15: ='Sanofi Standardized'!H12 -> -459 | I15: ='Sanofi Standardized'!I12 -> -362 | J15: ='Sanofi Standardized'!J12 -> -402 | ... L15: ='Sanofi Standardized'!L12 -> -641
B16: Profit before taxes | C16: =SUM(C11:C15) -> 5221 | D16: =SUM(D11:D15) -> 5811 | E16: =SUM(E11:E15) -> 5616 | F16: =SUM(F11:F15) -> 4904 | G16: =SUM(G11:G15) -> 3007 | H16: =SUM(H11:H15) -> 14137 | I16: =SUM(I11:I15) -> 7837 | J16: =SUM(J11:J15) -> 9992 | ... L16: =SUM(L11:L15) -> 6758
B17: Tax expense | C17: ='Sanofi Standardized'!C15 -> -709 | D17: ='Sanofi Standardized'!D15 -> -1325 | E17: ='Sanofi Standardized'!E15 -> -1722 | F17: ='Sanofi Standardized'!F15 -> -481 | G17: ='Sanofi Standardized'!G15 -> -121 | H17: ='Sanofi Standardized'!H15 -> -1807 | I17: ='Sanofi Standardized'!I15 -> -1558 | J17: ='Sanofi Standardized'!J15 -> -1909 | ... L17: ='Sanofi Standardized'!L15 -> -1204
B18: Profit after taxes | C18: =SUM(C16:C17) -> 4512 | D18: =SUM(D16:D17) -> 4486 | E18: =SUM(E16:E17) -> 3894 | F18: =SUM(F16:F17) -> 4423 | G18: =SUM(G16:G17) -> 2886 | H18: =SUM(H16:H17) -> 12330 | I18: =SUM(I16:I17) -> 6279 | J18: =SUM(J16:J17) -> 8083 | ... L18: =SUM(L16:L17) -> 5554
B19: Profit/loss to non-controlling interest | C19: ='Sanofi Standardized'!C16 -> -124 | D19: ='Sanofi Standardized'!D16 -> 314 | E19: ='Sanofi Standardized'!E16 -> 4643 | F19: ='Sanofi Standardized'!F16 -> -13 | G19: ='Sanofi Standardized'!G16 -> -101 | H19: ='Sanofi Standardized'!H16 -> 0 | I19: ='Sanofi Standardized'!I16 -> 0 | J19: ='Sanofi Standardized'!J16 -> 401 | ... L19: ='Sanofi Standardized'!L16 -> 64
B20: Profit/Loss of Discontinued Operations | C20: ='Sanofi Standardized'!C17 -> -101 | D20: ='Sanofi Standardized'!D17 -> -91 | E20: ='Sanofi Standardized'!E17 -> -121 | F20: ='Sanofi Standardized'!F17 -> -104 | G20: ='Sanofi Standardized'!G17 -> -31 | H20: ='Sanofi Standardized'!H17 -> -36 | I20: ='Sanofi Standardized'!I17 -> -56 | J20: ='Sanofi Standardized'!J17 -> -113 | ... L20: ='Sanofi Standardized'!L17 -> -58
B21: Profit/loss to ordinary shareholders | C21: =SUM(C18:C20) -> 4287 | D21: =SUM(D18:D20) -> 4709 | E21: =SUM(E18:E20) -> 8416 | F21: =SUM(F18:F20) -> 4306 | G21: =SUM(G18:G20) -> 2754 | H21: =SUM(H18:H20) -> 12294 | I21: =SUM(I18:I20) -> 6223 | J21: =SUM(J18:J20) -> 8371 | ... L21: =SUM(L18:L20) -> 5560
A23: x | B23: OPERATING EXPENSES
B24: Classification by function:
B25: Cost of Sales (by function) | C25: =+'Sanofi Standardized'!C6 -> -10919 | D25: =+'Sanofi Standardized'!D6 -> -10701 | E25: =+'Sanofi Standardized'!E6 -> -11447 | F25: =+'Sanofi Standardized'!F6 -> -11321 | G25: =+'Sanofi Standardized'!G6 -> -11976 | H25: =+'Sanofi Standardized'!H6 -> -12106 | I25: =+'Sanofi Standardized'!I6 -> -12251 | J25: =+'Sanofi Standardized'!J6 -> -11869 | ... L25: =+'Sanofi Standardized'!L6 -> -13195
B26: SG&A (by function) | C26: =+'Sanofi Standardized'!C8 -> -9496 | D26: =+'Sanofi Standardized'!D8 -> -9592 | E26: =+'Sanofi Standardized'!E8 -> -10164 | F26: =+'Sanofi Standardized'!F8 -> -9934 | G26: =+'Sanofi Standardized'!G8 -> -9967 | H26: =+'Sanofi Standardized'!H8 -> -9448 | I26: =+'Sanofi Standardized'!I8 -> -9599 | J26: =+'Sanofi Standardized'!J8 -> -8785 | ... L26: =+'Sanofi Standardized'!L8 -> -9247
B27: R&D Expenses | C27: =+'Sanofi Standardized'!C9 -> -5082 | D27: =+'Sanofi Standardized'!D9 -> -5172 | E27: =+'Sanofi Standardized'!E9 -> -5472 | F27: =+'Sanofi Standardized'!F9 -> -5894 | G27: =+'Sanofi Standardized'!G9 -> -6020 | H27: =+'Sanofi Standardized'!H9 -> -5530 | I27: =+'Sanofi Standardized'!I9 -> -5692 | J27: =+'Sanofi Standardized'!J9 -> -6501 | ... L27: =+'Sanofi Standardized'!L9 -> -7394
B28: Other Operating Income, Net of Other Operating Expense (by function) | C28: =+'Sanofi Standardized'!C10 -> -256 | D28: =+'Sanofi Standardized'!D10 -> -21 | E28: =+'Sanofi Standardized'!E10 -> 1 | F28: =+'Sanofi Standardized'!F10 -> -334 | G28: =+'Sanofi Standardized'!G10 -> -720 | H28: =+'Sanofi Standardized'!H10 -> -1025 | I28: =+'Sanofi Standardized'!I10 -> -1488 | J28: =+'Sanofi Standardized'!J10 -> -1190 | ... L28: =+'Sanofi Standardized'!L10 -> -3832
B29: Classification by nature:
B30: Cost of Materials (by nature)
B31: Personnel Expenses (by nature)
B32: Depreciation and Amortization (by nature)
B33: Other Operating Income, Net of Other Operating Expense (by nature)
A35: x | B35: BALANCE SHEET
B36: ASSETS
B37: Non-Current Tangible Assets | C37: =SUM('Sanofi Standardized'!C35) -> 10112 | D37: =SUM('Sanofi Standardized'!D35) -> 12839 | E37: =SUM('Sanofi Standardized'!E35) -> 9712 | F37: =SUM('Sanofi Standardized'!F35) -> 10029 | G37: =SUM('Sanofi Standardized'!G35) -> 11488 | H37: =SUM('Sanofi Standardized'!H35) -> 11104 | I37: =SUM('Sanofi Standardized'!I35) -> 12621 | J37: =SUM('Sanofi Standardized'!J35) -> 12481 | ... L37: =SUM('Sanofi Standardized'!L35) -> 12469
B38: Non-Current Intangible Assets | C38: =SUM('Sanofi Standardized'!C36) -> 52254 | D38: =SUM('Sanofi Standardized'!D36) -> 51166 | E38: =SUM('Sanofi Standardized'!E36) -> 54043 | F38: =SUM('Sanofi Standardized'!F36) -> 66588 | G38: =SUM('Sanofi Standardized'!G36) -> 61549 | H38: =SUM('Sanofi Standardized'!H36) -> 63242 | I38: =SUM('Sanofi Standardized'!I36) -> 69948 | J38: =SUM('Sanofi Standardized'!J36) -> 71984 | ... L38: =SUM('Sanofi Standardized'!L36) -> 66515
B39: Other Non-Operating Investments | C39: =SUM('Sanofi Standardized'!C37) -> 4561 | D39: =SUM('Sanofi Standardized'!D37) -> 2892 | E39: =SUM('Sanofi Standardized'!E37) -> 5379 | F39: =SUM('Sanofi Standardized'!F37) -> 5531 | G39: =SUM('Sanofi Standardized'!G37) -> 5266 | H39: =SUM('Sanofi Standardized'!H37) -> 2105 | I39: =SUM('Sanofi Standardized'!I37) -> 2422 | J39: =SUM('Sanofi Standardized'!J37) -> 2765 | ... L39: =SUM('Sanofi Standardized'!L37) -> 3259
B40: Deferred Tax Asset | C40: ='Sanofi Standardized'!C38 -> 4714 | D40: ='Sanofi Standardized'!D38 -> 4670 | E40: ='Sanofi Standardized'!E38 -> 4291 | F40: ='Sanofi Standardized'!F38 -> 4613 | G40: ='Sanofi Standardized'!G38 -> 5391 | H40: ='Sanofi Standardized'!H38 -> 4176 | I40: ='Sanofi Standardized'!I38 -> 4598 | J40: ='Sanofi Standardized'!J38 -> 5381 | ... L40: ='Sanofi Standardized'!L38 -> 7967
B41: Total Non-Current Assets | C41: =SUM(C37:C40) -> 71641 | D41: =SUM(D37:D40) -> 71567 | E41: =SUM(E37:E40) -> 73425 | F41: =SUM(F37:F40) -> 86761 | G41: =SUM(G37:G40) -> 83694 | H41: =SUM(H37:H40) -> 80627 | I41: =SUM(I37:I40) -> 89589 | J41: =SUM(J37:J40) -> 92611 | ... L41: =SUM(L37:L40) -> 90210
B43: Inventories | C43: ='Sanofi Standardized'!C33 -> 6516 | D43: ='Sanofi Standardized'!D33 -> 6896 | E43: ='Sanofi Standardized'!E33 -> 6818 | F43: ='Sanofi Standardized'!F33 -> 7477 | G43: ='Sanofi Standardized'!G33 -> 7994 | H43: ='Sanofi Standardized'!H33 -> 8352 | I43: ='Sanofi Standardized'!I33 -> 8715 | J43: ='Sanofi Standardized'!J33 -> 8960 | ... L43: ='Sanofi Standardized'!L33 -> 9431
B44: Trade Receivables | C44: ='Sanofi Standardized'!C32 -> 7386 | D44: ='Sanofi Standardized'!D32 -> 7311 | E44: ='Sanofi Standardized'!E32 -> 7216 | F44: ='Sanofi Standardized'!F32 -> 7260 | G44: ='Sanofi Standardized'!G32 -> 7937 | H44: ='Sanofi Standardized'!H32 -> 7491 | I44: ='Sanofi Standardized'!I32 -> 7568 | J44: ='Sanofi Standardized'!J32 -> 8424 | ... L44: ='Sanofi Standardized'!L32 -> 7677
B45: Other Current Assets | C45: ='Sanofi Standardized'!C34 -> 7630 | D45: ='Sanofi Standardized'!D34 -> 8632 | E45: ='Sanofi Standardized'!E34 -> 2039 | F45: ='Sanofi Standardized'!F34 -> 2985 | G45: ='Sanofi Standardized'!G34 -> 3578 | H45: ='Sanofi Standardized'!H34 -> 4028 | I45: ='Sanofi Standardized'!I34 -> 4272 | J45: ='Sanofi Standardized'!J34 -> 3991 | ... L45: ='Sanofi Standardized'!L34 -> 18039
B46: Cash and Cash Equivalents | C46: ='Sanofi Standardized'!C31 -> 9148 | D46: ='Sanofi Standardized'!D31 -> 10273 | E46: ='Sanofi Standardized'!E31 -> 10315 | F46: ='Sanofi Standardized'!F31 -> 6925 | G46: ='Sanofi Standardized'!G31 -> 9427 | H46: ='Sanofi Standardized'!H31 -> 13915 | I46: ='Sanofi Standardized'!I31 -> 10098 | J46: ='Sanofi Standardized'!J31 -> 12736 | ... L46: ='Sanofi Standardized'!L31 -> 7441
B47: Total Current Assets | C47: =SUM(C43:C46) -> 30680 | D47: =SUM(D43:D46) -> 33112 | E47: =SUM(E43:E46) -> 26388 | F47: =SUM(F43:F46) -> 24647 | G47: =SUM(G43:G46) -> 28936 | H47: =SUM(H43:H46) -> 33786 | I47: =SUM(I43:I46) -> 30653 | J47: =SUM(J43:J46) -> 34111 | ... L47: =SUM(L43:L46) -> 42588
B50: Total Assets | C50: =SUM(C41,C47) -> 102321 | D50: =SUM(D41,D47) -> 104679 | E50: =SUM(E41,E47) -> 99813 | F50: =SUM(F41,F47) -> 111408 | G50: =SUM(G41,G47) -> 112630 | H50: =SUM(H41,H47) -> 114413 | I50: =SUM(I41,I47) -> 120242 | J50: =SUM(J41,J47) -> 126722 | ... L50: =SUM(L41,L47) -> 132798
B52: LIABILITIES AND SHAREHOLDERS' EQUITY
B53: Ordinary Shareholders' Equity | C53: ='Sanofi Standardized'!C50 -> 58049 | D53: ='Sanofi Standardized'!D50 -> 57552 | E53: ='Sanofi Standardized'!E50 -> 58070 | F53: ='Sanofi Standardized'!F50 -> 58876 | G53: ='Sanofi Standardized'!G50 -> 59056 | H53: ='Sanofi Standardized'!H50 -> 63106 | I53: ='Sanofi Standardized'!I50 -> 68681 | J53: ='Sanofi Standardized'!J50 -> 74784 | ... L53: ='Sanofi Standardized'!L50 -> 77507
B54: Preference Shares | C54: ='Sanofi Standardized'!C51 -> 0 | D54: ='Sanofi Standardized'!D51 -> 0 | E54: ='Sanofi Standardized'!E51 -> 0 | F54: ='Sanofi Standardized'!F51 -> 0 | G54: ='Sanofi Standardized'!G51 -> 0 | H54: ='Sanofi Standardized'!H51 -> 0 | I54: ='Sanofi Standardized'!I51 -> 0 | J54: ='Sanofi Standardized'!J51 -> 0 | ... L54: ='Sanofi Standardized'!L51 -> 0
B55: Non-Controlling Interest in Equity | C55: ='Sanofi Standardized'!C49 -> 161 | D55: ='Sanofi Standardized'!D49 -> 170 | E55: ='Sanofi Standardized'!E49 -> 169 | F55: ='Sanofi Standardized'!F49 -> 159 | G55: ='Sanofi Standardized'!G49 -> 174 | H55: ='Sanofi Standardized'!H49 -> 146 | I55: ='Sanofi Standardized'!I49 -> 350 | J55: ='Sanofi Standardized'!J49 -> 368 | ... L55: ='Sanofi Standardized'!L49 -> 350
B58: Non-Current Debt | C58: ='Sanofi Standardized'!C46 -> 17426 | D58: ='Sanofi Standardized'!D46 -> 21192 | E58: ='Sanofi Standardized'!E46 -> 18285 | F58: ='Sanofi Standardized'!F46 -> 25529 | G58: ='Sanofi Standardized'!G46 -> 24717 | H58: ='Sanofi Standardized'!H46 -> 23952 | I58: ='Sanofi Standardized'!I46 -> 21909 | J58: ='Sanofi Standardized'!J46 -> 18800 | ... L58: ='Sanofi Standardized'!L46 -> 15428
B59: Deferred Tax Liability | C59: ='Sanofi Standardized'!C47 -> 2895 | D59: ='Sanofi Standardized'!D47 -> 2292 | E59: ='Sanofi Standardized'!E47 -> 1605 | F59: ='Sanofi Standardized'!F47 -> 3414 | G59: ='Sanofi Standardized'!G47 -> 2294 | H59: ='Sanofi Standardized'!H47 -> 1770 | I59: ='Sanofi Standardized'!I47 -> 1617 | J59: ='Sanofi Standardized'!J47 -> 1841 | ... L59: ='Sanofi Standardized'!L47 -> 2166
B60: Other Non-Current Liabilities (non interest bearing) | C60: ='Sanofi Standardized'!C48 -> 5982 | D60: ='Sanofi Standardized'!D48 -> 5835 | E60: ='Sanofi Standardized'!E48 -> 6221 | F60: ='Sanofi Standardized'!F48 -> 6054 | G60: ='Sanofi Standardized'!G48 -> 6002 | H60: ='Sanofi Standardized'!H48 -> 6159 | I60: ='Sanofi Standardized'!I48 -> 6390 | J60: ='Sanofi Standardized'!J48 -> 6955 | ... L60: ='Sanofi Standardized'!L48 -> 8185
B61: Non-Current Liabilities | C61: =SUM(C58:C60) -> 26303 | D61: =SUM(D58:D60) -> 29319 | E61: =SUM(E58:E60) -> 26111 | F61: =SUM(F58:F60) -> 34997 | G61: =SUM(G58:G60) -> 33013 | H61: =SUM(H58:H60) -> 31881 | I61: =SUM(I58:I60) -> 29916 | J61: =SUM(J58:J60) -> 27596 | ... Q61: =SUM(Q58:Q60) -> 0
B63: Trade Payables | C63: ='Sanofi Standardized'!C44 -> 3817 | D63: ='Sanofi Standardized'!D44 -> 4297 | E63: ='Sanofi Standardized'!E44 -> 4633 | F63: ='Sanofi Standardized'!F44 -> 5041 | G63: ='Sanofi Standardized'!G44 -> 5313 | H63: ='Sanofi Standardized'!H44 -> 5295 | I63: ='Sanofi Standardized'!I44 -> 6180 | J63: ='Sanofi Standardized'!J44 -> 6813 | ... L63: ='Sanofi Standardized'!L44 -> 7551
B64: Other Current Liabilities | C64: ='Sanofi Standardized'!C45 -> 10551 | D64: ='Sanofi Standardized'!D45 -> 11575 | E64: ='Sanofi Standardized'!E45 -> 9555 | F64: ='Sanofi Standardized'!F45 -> 9702 | G64: ='Sanofi Standardized'!G45 -> 10257 | H64: ='Sanofi Standardized'!H45 -> 10986 | I64: ='Sanofi Standardized'!I45 -> 11662 | J64: ='Sanofi Standardized'!J45 -> 12710 | ... L64: ='Sanofi Standardized'!L45 -> 17134
B65: Current Debt | C65: ='Sanofi Standardized'!C43 -> 3440 | D65: ='Sanofi Standardized'!D43 -> 1766 | E65: ='Sanofi Standardized'!E43 -> 1275 | F65: ='Sanofi Standardized'!F43 -> 2633 | G65: ='Sanofi Standardized'!G43 -> 4817 | H65: ='Sanofi Standardized'!H43 -> 2999 | I65: ='Sanofi Standardized'!I43 -> 3453 | J65: ='Sanofi Standardized'!J43 -> 4451 | ... L65: ='Sanofi Standardized'!L43 -> 4477
B66: Current Liabilities | C66: =SUM(C63:C65) -> 17808 | D66: =SUM(D63:D65) -> 17638 | E66: =SUM(E63:E65) -> 15463 | F66: =SUM(F63:F65) -> 17376 | G66: =SUM(G63:G65) -> 20387 | H66: =SUM(H63:H65) -> 19280 | I66: =SUM(I63:I65) -> 21295 | J66: =SUM(J63:J65) -> 23974 | ... Q66: =SUM(Q63:Q65) -> 0
