Workbook

Sheet Financial Statements
A1: Standard accounts | C1: Income Statement in millions (IFRS) | D1: 2020 | E1: 2019 | F1: 2018 | G1: 2017 | H1: 2016 | I1: 2015 | J1: 2014 | K1: 2013 | L1: 2012 | M1: 2011 | N1: 2010 | O1: 2009 | P1: 2008 | Q1: 2007 | R1: 2006
A3: Revenue | C3: Net sales | D3: 187031 | E3: 232755 | F3: 210400 | G3: 200004 | H3: 192267 | I3: 180861 | J3: 151419 | K3: 128562 | L3: 120799 | M3: 109999 | N3: 108483 | O3: 101393 | P3: 88532 | Q3: 78346 | R3: 68400
A4: Cost of Sales (by function) | C4: Cost of goods sold | D4: -93487 | E4: -110302 | F4: -99513 | G4: -91914 | H4: -86090 | I4: -77694 | J4: -62367 | K4: -52529 | L4: -48928 | M4: -43852 | N4: -40214 | O4: -38919 | P4: -34064 | Q4: -30499 | R4: -27736
C5: Gross profit | D5: =D3+D4 -> 93544 | E5: =E3+E4 -> 122453 | F5: =F3+F4 -> 110887 | G5: =G3+G4 -> 108090 | H5: =H3+H4 -> 106177 | I5: =I3+I4 -> 103167 | J5: =J3+J4 -> 89052 | K5: =K3+K4 -> 76033 | ... R5: =R3+R4 -> 40664
A7: SG&A (by function) | C7: Selling expenses | D7: -81425 | E7: -96279 | F7: -87512 | G7: -80427 | H7: -75729 | I7: -70292 | J7: -58525 | K7: -49878 | L7: -46608 | M7: -42517 | N7: -40751 | O7: -38224 | P7: -32185 | Q7: -27687 | R7: -23971
A8: SG&A (by function) | C8: Administrative expenses | D8: =-9020-D9 -> -9013 | E8: =-8828-E9 -> -8812 | F8: =-7882-F9 -> -7868 | G8: =-7094-G9 -> -7081 | H8: =-6625-H9 -> -6607 | I8: =-5933-I9 -> -5912 | J8: =-4944-J9 -> -4918 | K8: =-3987-K9 -> -3965 | L8: =-3509-L9 -> -3484 | M8: =-3251-M9 -> -3222 | N8: =-2859-N9 -> -2847 | O8: =-2606-O9 -> -2595 | P8: =-2145-P9 -> -2135 | Q8: =-1778-Q9 -> -1770 | R8: =-1395-R9 -> -1386
A9: Interest Expense | C9: Interest on the provision for pensions | D9: -7 | E9: -16 | F9: -14 | G9: -13 | H9: -18 | I9: -21 | J9: -26 | K9: -22 | L9: -25 | M9: -29 | N9: -12 | O9: -11 | P9: -10 | Q9: -8 | R9: -9
C10: Operating profit | D10: =SUM(D5:D9) -> 3099 | E10: =SUM(E5:E9) -> 17346 | F10: =SUM(F5:F9) -> 15493 | G10: =SUM(G5:G9) -> 20569 | H10: =SUM(H5:H9) -> 23823 | I10: =SUM(I5:I9) -> 26942 | J10: =SUM(J5:J9) -> 25583 | K10: =SUM(K5:K9) -> 22168 | ... R10: =SUM(R5:R9) -> 15298
A11: Interest Income | C11: Interest income (incl finance lease) | D11: 252 | E11: 376 | F11: 292 | G11: 281 | H11: 224 | I11: 310 | J11: 328 | K11: 367 | L11: 536 | M11: 568 | N11: 356 | O11: 467 | P11: 1060 | Q11: 793 | R11: 515
A12: Interest Expense | C12: Interest expense and similar items (incl finance lease) | D12: -1299 | E12: -331 | F12: -146 | G12: -41 | H12: -8 | I12: -10 | J12: -16 | K12: -9 | L12: -5 | M12: -5 | N12: -7 | O12: -8 | P12: -8 | Q12: -5 | R12: -5
C13: Profit after financial items | D13: =SUM(D10:D12) -> 2052 | E13: =SUM(E10:E12) -> 17391 | F13: =SUM(F10:F12) -> 15639 | G13: =SUM(G10:G12) -> 20809 | H13: =SUM(H10:H12) -> 24039 | I13: =SUM(I10:I12) -> 27242 | J13: =SUM(J10:J12) -> 25895 | K13: =SUM(K10:K12) -> 22526 | ... R13: =SUM(R10:R12) -> 15808
A14: Tax Expense | C14: Tax | D14: -809 | E14: -3948 | F14: -2987 | G14: -4625 | H14: -5403 | I14: -6344 | J14: -5919 | K14: -5374 | L14: -5418 | M14: -5121 | N14: -6327 | O14: -5719 | P14: -5896 | Q14: -5582 | R14: -5011
A15: Profit/Loss to Ordinary Shareholders | C15: Profit for the year | D15: =SUM(D13:D14) -> 1243 | E15: =SUM(E13:E14) -> 13443 | F15: =SUM(F13:F14) -> 12652 | G15: =SUM(G13:G14) -> 16184 | H15: =SUM(H13:H14) -> 18636 | I15: =SUM(I13:I14) -> 20898 | J15: =SUM(J13:J14) -> 19976 | K15: =SUM(K13:K14) -> 17152 | ... R15: =SUM(R13:R14) -> 10797
C19: Pro Forma IS Items in millions (IFRS) | D19: 2020 | E19: 2019 | F19: 2018 | G19: 2017 | H19: 2016 | I19: 2015 | J19: 2014 | K19: 2013 | L19: 2012 | M19: 2011 | N19: 2010 | O19: 2009 | P19: 2008 | Q19: 2007 | R19: 2006
A21: Personnel Expenses (by nature) | C21: Salaries, other remuneration and payroll overheads | D21: =-88-29771-7100-D9 -> -36952 | E21: =-72-34114-8215-E9 -> -42385 | F21: =-45-31045-7467-F9 -> -38543 | G21: =-48-28620-6979-G9 -> -35634 | H21: =-32579-H9 -> -32561 | I21: =-29973-I9 -> -29952 | J21: =-25074-J9 -> -25048 | K21: =-21445-K9 -> -21423 | L21: =-19918-L9 -> -19893 | M21: =-140-14857-3537-M9 -> -18505 | N21: =-115-13423-3102-N9 -> -16628 | O21: =-125-14058-3335-O9 -> -17507 | P21: =-101-11696-2697-P9 -> -14484 | Q21: =-83-9846-2247-Q9 -> -12168 | R21: =-82-8842-2076-R9 -> -10991
A22: Depreciation and Amortization (by nature) | C22: Depreciation - within cost of goods sold | D22: -1949 | E22: -570 | F22: -558 | G22: -736 | H22: -847 | I22: -725 | J22: -568 | K22: -470 | L22: -415 | M22: -366 | N22: -336 | O22: -310 | P22: -245 | Q22: -203 | R22: -172
A23: Depreciation and Amortization (by nature) | C23: Depreciation - within selling expenses | D23: -22755 | E23: -9887 | F23: -8566 | G23: -7175 | H23: -6256 | I23: -5262 | J23: -4159 | K23: -3463 | L23: -3065 | M23: -2698 | N23: -2540 | O23: -2350 | P23: -1505 | Q23: -1505 | R23: -1374
A24: Depreciation and Amortization (by nature) | C24: Depreciation - within administrative expenses | D24: -1249 | E24: -594 | F24: -547 | G24: -577 | H24: -502 | I24: -412 | J24: -318 | K24: -258 | L24: -225 | M24: -198 | N24: -185 | O24: -170 | P24: -106 | Q24: -132 | R24: -78
A25: Cost of Materials (by nature) | C25: Cost of goods sold excluding depreciation | D25: =D4-D22 -> -91538 | E25: =E4-E22 -> -109732 | F25: =F4-F22 -> -98955 | G25: =G4-G22 -> -91178 | H25: =H4-H22 -> -85243 | I25: =I4-I22 -> -76969 | J25: =J4-J22 -> -61799 | K25: =K4-K22 -> -52059 | ... R25: =R4-R22 -> -27564
C29: Balance Sheet in millions (IFRS) | D29: 2020 | E29: 2019 | F29: 2018 | G29: 2017 | H29: 2016 | I29: 2015 | J29: 2014 | K29: 2013 | L29: 2012 | M29: 2011 | N29: 2010 | O29: 2009 | P29: 2008 | Q29: 2007 | R29: 2006
A31: Non-Current Intangible Assets | C31: Brands | D31: 0 | E31: 0 | F31: 0 | G31: 18 | H31: 66 | I31: 114 | J31: 161 | K31: 208 | L31: 255 | M31: 302 | N31: 349 | O31: 396 | P31: 443 | Q31: 0 | R31: 0
A32: Non-Current Intangible Assets | C32: Customer relations | D32: 0 | E32: 0 | F32: 0 | G32: 8 | H32: 20 | I32: 32 | J32: 45 | K32: 58 | L32: 71 | M32: 84 | N32: 97 | O32: 110 | P32: 123 | Q32: 0 | R32: 0
A33: Non-Current Tangible Assets | C33: Leasehold and similar rights | D33: 191 | E33: 411 | F33: 508 | G33: 592 | H33: 630 | I33: 660 | J33: 509 | K33: 591 | L33: 537 | M33: 585 | N33: 688 | O33: 744 | P33: 659 | Q33: 266 | R33: 222
A34: Non-Current Intangible Assets | C34: Goodwill | D34: 64 | E34: 64 | F34: 64 | G34: 64 | H34: 64 | I34: 64 | J34: 64 | K34: 64 | L34: 64 | M34: 64 | N34: 64 | O34: 424 | P34: 431 | Q34: 0 | R34: 0
A35: Non-Current Intangible Assets | C35: Capitalised development expenditure | D35: 10177 | E35: 10973 | F35: 9046 | G35: 6361 | H35: 4567 | I35: 3245 | J35: 2183 | K35: 1355 | L35: 631 | M35: 0 | N35: 0 | O35: 0 | P35: 0 | Q35: 0 | R35: 0
A36: Non-Current Tangible Assets | C36: Buildings and land | D36: 745 | E36: 813 | F36: 831 | G36: 824 | H36: 850 | I36: 797 | J36: 804 | K36: 814 | L36: 805 | M36: 804 | N36: 656 | O36: 492 | P36: 480 | Q36: 466 | R36: 420
A37: Non-Current Tangible Assets | C37: Equipment, tools, fixtures and fittings | D37: 30894 | E37: 40079 | F37: 41608 | G37: 38994 | H37: 37843 | I37: 32165 | J37: 26144 | K37: 21372 | L37: 18326 | M37: 16589 | N37: 14813 | O37: 14319 | P37: 11961 | Q37: 8821 | R37: 7134
A38: Non-Current Tangible Assets | C38: Right-of-use assets | D38: 59535
A39: Minority Equity Investments | C39: Participations in associated companies | D39: 247 | E39: 210 | F39: 126
A40: Other Non-Operating Investments | C40: Other shares and participating rights | D40: 539 | E40: 429 | F40: 352
A41: Other Non-Operating Investments | C41: Long-term receivables | D41: 907 | E41: 912 | F41: 885 | G41: 1039 | H41: 1014 | I41: 862 | J41: 709 | K41: 659 | L41: 628 | M41: 608 | N41: 518 | O41: 551 | P41: 476 | Q41: 253 | R41: 155
A42: Deferred Tax Asset | C42: Deferred tax receivables | D42: 5714 | E42: 4322 | F42: 3794 | G42: 2916 | H42: 2862 | I42: 2338 | J42: 2237 | K42: 1367 | L42: 1624 | M42: 1234 | N42: 1065 | O42: 1246 | P42: 1299 | Q42: 883 | R42: 102
C43: Total fixed assets | D43: =SUM(D31:D42) -> 109013 | E43: =SUM(E31:E42) -> 58213 | F43: =SUM(F31:F42) -> 57214 | G43: =SUM(G31:G42) -> 50816 | H43: =SUM(H31:H42) -> 47916 | I43: =SUM(I31:I42) -> 40277 | J43: =SUM(J31:J42) -> 32856 | K43: =SUM(K31:K42) -> 26488 | ... R43: =SUM(R31:R42) -> 8033
A45: Inventories | C45: Stock-in-trade | D45: 38209 | E45: 37823 | F45: 37721 | G45: 33712 | H45: 31732 | I45: 24833 | J45: 19403 | K45: 16695 | L45: 15213 | M45: 13819 | N45: 11487 | O45: 10240 | P45: 8500 | Q45: 7969 | R45: 7220
A46: Trade Receivables | C46: Accounts receivable | D46: 3086 | E46: 5879 | F46: 6329 | G46: 5297 | H46: 4881 | I46: 4021 | J46: 3659 | K46: 3107 | L46: 2207 | M46: 2337 | N46: 2258 | O46: 1990 | P46: 1991 | Q46: 1122 | R46: 865
A47: Other Current Assets | C47: Tax receivables | D47: 1686 | E47: 1555 | F47: 1448 | G47: 2375 | H47: 0 | I47: 0 | J47: 0 | K47: 0 | L47: 0 | M47: 0 | N47: 0 | O47: 0 | P47: 0 | Q47: 0
A48: Other Current Assets | C48: Other receivables | D48: =2397-D49 -> 1667 | E48: =1736-E49 -> 1075 | F48: =1607-F49 -> 1235 | G48: =1874-G49 -> 1377 | H48: =2533-H49 -> 1685 | I48: =1469+379-I49 -> 1141 | J48: 1027 | K48: =907-186 -> 721 | L48: =1533-158 -> 1375 | M48: =1375-456 -> 919 | N48: =1453-457 -> 996 | O48: =889-260 -> 629 | P48: =1206-660 -> 546 | Q48: =356-7 -> 349 | R48: 249
A49: Derivatives - Asset | C49: Forward contracts | D49: 730 | E49: 661 | F49: 372 | G49: 497 | H49: 848 | I49: 707 | J49: 443 | K49: =186 -> 186 | L49: 158 | M49: 456 | N49: 457 | O49: 260 | P49: 660 | Q49: 7 | R49: 0
A50: Other Current Assets | C50: Prepaid expenses | D50: 3440 | E50: 2967 | F50: 2881 | G50: 2770 | H50: 2071 | I50: 1884 | J50: 1516 | K50: 1255 | L50: 1136 | M50: 1110 | N50: 876 | O50: 937 | P50: 948 | Q50: 634 | R50: 563
A51: Cash and Cash Equivalents | C51: Short-term investments | D51: 960 | E51: 2242 | F51: 1162 | G51: 601 | H51: 1134 | I51: 1026 | J51: 2602 | K51: 3306 | L51: 2995 | M51: 6958 | N51: 8167 | O51: 3001 | P51: 0 | Q51: 4900 | R51: 8748
A52: Cash and Cash Equivalents | C52: Cash and cash equivalents | D52: =16540-D51 -> 15580 | E52: 10070 | F52: 10428 | G52: 9117 | H52: 8312 | I52: 11924 | J52: 14091 | K52: 13918 | L52: 14148 | M52: 14319 | N52: 16691 | O52: 19024 | P52: 22726 | Q52: 16064 | R52: 9877
C53: Total current assets | D53: =SUM(D45:D52) -> 65358 | E53: =SUM(E45:E52) -> 62272 | F53: =SUM(F45:F52) -> 61576 | G53: =SUM(G45:G52) -> 55746 | H53: =SUM(H45:H52) -> 50663 | I53: =SUM(I45:I52) -> 45536 | J53: =SUM(J45:J52) -> 42741 | K53: =SUM(K45:K52) -> 39188 | ... R53: =SUM(R45:R52) -> 27522
A55: Total Assets | C55: Total assets | D55: =D43+D53 -> 174371 | E55: =E43+E53 -> 120485 | F55: =F43+F53 -> 118790 | G55: =G43+G53 -> 106562 | H55: =H43+H53 -> 98579 | I55: =I43+I53 -> 85813 | J55: =J43+J53 -> 75597 | K55: =K43+K53 -> 65676 | ... R55: =R43+R53 -> 35555
A57: Ordinary Shareholders' Equity | C57: Share capital | D57: 207 | E57: 207 | F57: 207 | G57: 207 | H57: 207 | I57: 207 | J57: 207 | K57: 207 | L57: 207 | M57: 207 | N57: 207 | O57: 207 | P57: 207 | Q57: 207 | R57: 207
A58: Ordinary Shareholders' Equity | C58: Reserves | D58: 990 | E58: 4592 | F58: 3322 | G58: 1015 | H58: 2651 | I58: 1904 | J58: 204 | K58: -1916 | L58: -1900 | M58: -487 | N58: -369 | O58: 1514 | P58: 1410 | Q58: 263 | R58: 22
A59: Ordinary Shareholders' Equity | C59: Retained earnings | D59: 53426 | E59: 52270 | F59: 55017 | G59: 58491 | H59: 58378 | I59: 55938 | J59: 51145 | K59: 46957 | L59: 45528 | M59: 44384 | N59: 44334 | O59: 38892 | P59: 35333 | Q59: 31623 | R59: 27550
C60: Equity | D60: =SUM(D57:D59) -> 54623 | E60: =SUM(E57:E59) -> 57069 | F60: =SUM(F57:F59) -> 58546 | G60: =SUM(G57:G59) -> 59713 | H60: =SUM(H57:H59) -> 61236 | I60: =SUM(I57:I59) -> 58049 | J60: =SUM(J57:J59) -> 51556 | K60: =SUM(K57:K59) -> 45248 | ... R60: =SUM(R57:R59) -> 27779
A62: Non-Current Debt | C62: Provisions for pensions | D62: 612 | E62: 510 | F62: 445 | G62: 445 | H62: 527 | I62: 449 | J62: 451 | K62: 309 | L62: 377 | M62: 377 | N62: 257 | O62: 254 | P62: 228 | Q62: 156 | R62: 130
A63: Non-Current Debt | C63: Other provisions | D63: 0 | E63: 0 | F63: 0 | G63: 0 | H63: 213 | I63: 0 | J63: 0 | K63: 0 | L63: 0 | M63: 0 | N63: 0 | O63: 0 | P63: 368 | Q63: 0 | R63: 0
A64: Non-Current Debt | C64: Other interest-bearing liabilities | D64: 50458 | E64: 234 | F64: 322 | G64: 350 | H64: 0 | I64: 0 | J64: 0 | K64: 0 | L64: 0 | M64: 0 | N64: 0 | O64: 0 | P64: 0 | Q64: 0 | R64: 0
A65: Non-Current Debt | C65: Liabilities to credit institutions | D65: 8433 | E65: 10413 | F65: 10170
A66: Deferred Tax Liability | C66: Deferred tax liabilities | D66: 3988 | E66: 4423 | F66: 5088 | G66: 5331 | H66: 4898 | I66: 4378 | J66: 3287 | K66: 2722 | L66: 1951 | M66: 950 | N66: 906 | O66: 2038 | P66: 1818 | Q66: 651 | R66: 650
C67: Total non-current liabilities | D67: =SUM(D62:D66) -> 63491 | E67: =SUM(E62:E66) -> 15580 | F67: =SUM(F62:F66) -> 16025 | G67: =SUM(G62:G66) -> 6126 | H67: =SUM(H62:H66) -> 5638 | I67: =SUM(I62:I66) -> 4827 | J67: =SUM(J62:J66) -> 3738 | K67: =SUM(K62:K66) -> 3031 | ... R67: =SUM(R62:R66) -> 780
A69: Trade Payables | C69: Accounts payable | D69: 9511 | E69: 7838 | F69: 6800 | G69: 7215 | H69: 7262 | I69: 6000 | J69: 5520 | K69: 4870 | L69: 4234 | M69: 4307 | N69: 3965 | O69: 3667 | P69: 3658 | Q69: 2483 | R69: 1942
A70: Other Current Liabilities | C70: Tax liabilities | D70: 1708 | E70: 2752 | F70: 1163 | G70: 918 | H70: 434 | I70: 0 | J70: 1154 | K70: 797 | L70: 0 | M70: 1851 | N70: 2304 | O70: 439 | P70: 1279 | Q70: 2036 | R70: 1224
A71: Current Debt | C71: Liabilities to credit institutions | D71: 7899 | E71: 6904 | F71: 9153 | G71: 9745 | H71: 2068 | I71: 0 | J71: 0 | K71: 0 | L71: 0 | M71: 0 | N71: 0 | O71: 0 | P71: 0 | Q71: 0 | R71: 0
A72: Current Debt | C72: Interest-bearing liabilities | D72: 13275 | E72: 147 | F72: 136 | G72: 125 | H72: 59 | I72: 0 | J72: 0 | K72: 0 | L72: 0 | M72: 0 | N72: 0 | O72: 0 | P72: 0 | Q72: 0 | R72: 0
A73: Derivatives - Liability | C73: Forward contracts | D73: 560 | E73: 479 | F73: 238 | G73: 903 | H73: 1176 | I73: 302 | J73: 254 | K73: 285 | L73: 222 | M73: 150 | N73: 176 | O73: 335 | P73: 1234 | Q73: 132 | R73: 0
A74: Other Current Liabilities | C74: Other liabilities | D74: =3983-D73 -> 3423 | E74: =4476-E73 -> 3997 | F74: =3800-F73 -> 3562 | G74: =3672-G73 -> 2769 | H74: =5036-H73 -> 3860 | I74: =3192-I73 -> 2890 | J74: 2693 | K74: =3360-285 -> 3075 | L74: 2543 | M74: =2428-150 -> 2278 | N74: =2202-176 -> 2026 | O74: =2531-335 -> 2196 | P74: =3255-1234 -> 2021 | Q74: =1468-132 -> 1336 | R74: 1560
A75: Other Current Liabilities | C75: Accrued expenses and prepaid income | D75: 19881 | E75: 25719 | F75: 23167 | G75: 19048 | H75: 16846 | I75: 13745 | J75: 10682 | K75: 8370 | L75: 7011 | M75: 6171 | N75: 5376 | O75: 4453 | P75: 3687 | Q75: 2847 | R75: 2270
C76: Total current liabilities | D76: =SUM(D69:D75) -> 56257 | E76: =SUM(E69:E75) -> 47836 | F76: =SUM(F69:F75) -> 44219 | G76: =SUM(G69:G75) -> 40723 | H76: =SUM(H69:H75) -> 31705 | I76: =SUM(I69:I75) -> 22937 | J76: =SUM(J69:J75) -> 20303 | K76: =SUM(K69:K75) -> 17397 | ... R76: =SUM(R69:R75) -> 6996
A78: Total Liabilities and Shareholders' Equity | C78: Total liabilities and shareholders' equity | D78: =D60+D67+D76 -> 174371 | E78: =E60+E67+E76 -> 120485 | F78: =F60+F67+F76 -> 118790 | G78: =G60+G67+G76 -> 106562 | H78: =H60+H67+H76 -> 98579 | I78: =I60+I67+I76 -> 85813 | J78: =J60+J67+J76 -> 75597 | K78: =K60+K67+K76 -> 65676 | ... R78: =R60+R67+R76 -> 35555
C82: Cash flow statement in millions (IFRS) | D82: 2020 | E82: 2019 | F82: 2018 | G82: 2017 | H82: 2016 | I82: 2015 | J82: 2014 | K82: 2013 | L82: 2012 | M82: 2011 | N82: 2010 | O82: 2009 | P82: 2008 | Q82: 2007 | R82: 2006
C84: Operating activities
A85: Profit Before Interest and Tax | C85: Profit after financial items | D85: 2052 | E85: 17391 | F85: 15639 | G85: 20809 | H85: 24039 | I85: 27242 | J85: 25895 | K85: 22526 | L85: 22285 | M85: 20942 | N85: 25008 | O85: 22103 | P85: 21190 | Q85: 19170 | R85: 15808
A86: Profit Before Interest and Tax | C86: Net interest expense (income) | D86: =-SUM(D87:D89) -> 1054 | E86: =-SUM(E87:E89) -> -29 | F86: =-SUM(F87:F89) -> -132 | G86: =-SUM(G87:G89) -> -227 | H86: =-SUM(H87:H89) -> -198 | I86: =-SUM(I87:I89) -> -279 | J86: =-SUM(J87:J89) -> -286 | K86: =-SUM(K87:K89) -> -336 | ... R86: =-SUM(R87:R89) -> -501
A87: Interest Paid | C87: Interest paid | D87: =D12 -> -1299 | E87: =E12 -> -331 | F87: =F12 -> -146 | G87: =G12 -> -41 | H87: =H12 -> -8 | I87: =I12 -> -10 | J87: =J12 -> -16 | K87: =K12 -> -9 | L87: -5 | M87: -5 | N87: -7 | O87: -8 | P87: -8 | Q87: -5 | R87: -5
A88: Interest Received | C88: Interest received | D88: =D11 -> 252 | E88: =E11 -> 376 | F88: =F11 -> 292 | G88: =G11 -> 281 | H88: =H11 -> 224 | I88: =I11 -> 310 | J88: =J11 -> 328 | K88: =K11 -> 367 | L88: 536 | M88: 568 | N88: 356 | O88: 467 | P88: 1060 | Q88: 793 | R88: 515
A89: Interest Paid | C89: Interest on the provision for pensions | D89: =D9 -> -7 | E89: =E9 -> -16 | F89: =F9 -> -14 | G89: =G9 -> -13 | H89: =H9 -> -18 | I89: =I9 -> -21 | J89: =J9 -> -26 | K89: =K9 -> -22 | ... R89: =R9 -> -9
C90: Adjustment for:
A91: Non-Current Operating Accruals | C91: Provisions for pensions | D91: 22 | E91: -12 | F91: 0 | G91: 9 | H91: -9 | I91: 28 | J91: -20 | K91: -68 | L91: 10 | M91: 120 | N91: 3 | O91: 26 | P91: 72 | Q91: 27 | R91: 52
A92: Non-Current Operating Accruals | C92: Depreciation | D92: 25953 | E92: 11051 | F92: 9671 | G92: 8488 | H92: 7605 | I92: 6399 | J92: 5045 | K92: 4191 | L92: 3705 | M92: 3262 | N92: 3061 | O92: 2830 | P92: 2202 | Q92: 1814 | R92: 1624
A93: Taxes Paid | C93: Tax paid | D93: -3719 | E93: -3700 | F93: -3098 | G93: -6051 | H93: -4470 | I93: -7022 | J93: -5971 | K93: -3059 | L93: -7021 | M93: -5666 | N93: -5451 | O93: -6468 | P93: -5940 | Q93: -5557 | R93: -5565
A94: Non-Current Operating Accruals | C94: Other | D94: 0 | E94: 23 | F94: 39 | G94: -20 | H94: 0 | I94: 0 | J94: 0 | K94: 0 | L94: 0 | M94: 0 | N94: 0 | O94: 0 | P94: 0 | Q94: 0 | R94: 0
A95: Net (Investments in) or Liquidation of Operating Working Capital | C95: Changes in current receivables | D95: 1373 | E95: 753 | F95: -587 | G95: -1115 | H95: -1817 | I95: -249 | J95: -888 | K95: -839 | L95: -8 | M95: -244 | N95: -778 | O95: -71 | P95: -1343 | Q95: -421 | R95: -317
A96: Net (Investments in) or Liquidation of Operating Working Capital | C96: Changes in stock-in-trade | D96: -1980 | E96: 273 | F96: -3489 | G96: -2414 | H96: -6511 | I96: -5105 | J96: -2327 | K96: -1439 | L96: -1607 | M96: -2331 | N96: -1557 | O96: -1740 | P96: -183 | Q96: -615 | R96: -748
A97: Net (Investments in) or Liquidation of Operating Working Capital | C97: Changes in current liabilities | D97: 2199 | E97: 3207 | F97: 3112 | G97: 1881 | H97: 4938 | I97: 2774 | J97: 2422 | K97: 2528 | L97: 1536 | M97: 1337 | N97: 1552 | O97: 1293 | P97: 1968 | Q97: 963 | R97: 1201
C98: Cash flow from current operations | D98: =SUM(D85:D97) -> 25900 | E98: =SUM(E85:E97) -> 28986 | F98: =SUM(F85:F97) -> 21287 | G98: =SUM(G85:G97) -> 21587 | H98: =SUM(H85:H97) -> 23775 | I98: =SUM(I85:I97) -> 24067 | J98: =SUM(J85:J97) -> 24156 | K98: =SUM(K85:K97) -> 23840 | ... R98: =SUM(R85:R97) -> 12055
A100: Net (Investments in) or Liquidation of Non-Current Operating or Investment Assets | C100: Investment in leasehold and similar rights | D100: -48 | E100: -47 | F100: -64 | G100: -102 | H100: -139 | I100: -324 | J100: -35 | K100: -179 | L100: -125 | M100: -71 | N100: -147 | O100: -180 | P100: -446 | Q100: -86 | R100: -30
A101: Net (Investments in) or Liquidation of Non-Current Operating or Investment Assets | C101: Investment in other intangible assets | D101: -1448 | E101: -2909 | F101: -3207 | G101: -2058 | H101: -1476 | I101: -1140 | J101: -868 | K101: -738 | L101: -631 | M101: 0 | N101: 0 | O101: 0 | P101: 0 | Q101: 0 | R101: 0
A102: Net (Investments in) or Liquidation of Non-Current Operating or Investment Assets | C102: Investment in buildings and land | D102: 0 | E102: 0 | F102: -5 | G102: -27 | H102: -60 | I102: -2 | J102: -21 | K102: -23 | L102: -63 | M102: -157 | N102: -209 | O102: -25 | P102: -23 | Q102: -56 | R102: 6
A103: Net (Investments in) or Liquidation of Non-Current Operating or Investment Assets | C103: Investment in fixed assets | D103: -3606 | E103: -7384 | F103: -9552 | G103: -10284 | H103: -11671 | I103: -10593 | J103: -8467 | K103: -7087 | L103: -6008 | M103: -4946 | N103: -4603 | O103: -5481 | P103: -4724 | Q103: -3466 | R103: -1958
A104: Net (Investments in) or Liquidation of Non-Current Operating or Investment Assets | C104: Other investments | D104: -142 | E104: -188 | F104: -324 | G104: -25 | H104: -152 | I104: 2449 | J104: 683 | K104: -342 | L104: 3926 | M104: 1118 | N104: -5170 | O104: -3069 | P104: 4103 | Q104: 3752 | R104: -2413
C105: Cash flow from investing activities | D105: =SUM(D100:D104) -> -5244 | E105: =SUM(E100:E104) -> -10528 | F105: =SUM(F100:F104) -> -13152 | G105: =SUM(G100:G104) -> -12496 | H105: =SUM(H100:H104) -> -13498 | I105: =SUM(I100:I104) -> -9610 | J105: =SUM(J100:J104) -> -8708 | K105: =SUM(K100:K104) -> -8369 | ... R105: =SUM(R100:R104) -> -4395
A107: Net Debt (Repayment) or Issuance | C107: Short-term loans | D107: 995 | E107: -2249 | F107: -592 | G107: 7677 | H107: 2068 | I107: 0 | J107: 0 | K107: 0 | L107: 0 | M107: 0 | N107: 0 | O107: 0 | P107: 0 | Q107: 0 | R107: 0
A108: Net Debt (Repayment) or Issuance | C108: Long-term loans | D108: -1980 | E108: 243 | F108: 10170
A109: Net Debt (Repayment) or Issuance | C109: Amortisation lease | D109: -14174 | E109: -149 | F109: -126 | G109: -57 | H109: 0 | I109: 0 | J109: 0 | K109: 0 | L109: 0 | M109: 0 | N109: 0 | O109: 0 | P109: 0 | Q109: 0 | R109: 0
A110: Dividend (Payments) | C110: Dividend | D110: 0 | E110: -16137 | F110: -16137 | G110: -16137 | H110: -16137 | I110: -16137 | J110: -15723 | K110: -15723 | L110: -15723 | M110: -15723 | N110: -13239 | O110: -12825 | P110: -11584 | Q110: -9515 | R110: -7861
C111: Cash flows from financing activities | D111: =SUM(D107:D110) -> -15159 | E111: =SUM(E107:E110) -> -18292 | F111: =SUM(F107:F110) -> -6685 | G111: =SUM(G107:G110) -> -8517 | H111: =SUM(H107:H110) -> -14069 | I111: =SUM(I107:I110) -> -16137 | J111: =SUM(J107:J110) -> -15723 | K111: =SUM(K107:K110) -> -15723 | ... R111: =SUM(R107:R110) -> -7861
C114: Cash and cash equivalents at beginning of year | D114: 12312 | E114: 11590 | F114: 9718 | G114: 9446 | H114: 12950 | I114: 14091 | J114: 13918 | K114: 14148 | L114: 14319 | M114: 16691 | N114: 19024 | O114: 22726 | P114: 16064 | Q114: 9877 | R114: 10496
C115: Cash flow for the year | D115: =D98+D105+D111 -> 5497 | E115: =E98+E105+E111 -> 166 | F115: =F98+F105+F111 -> 1450 | G115: =G98+G105+G111 -> 574 | H115: =H98+H105+H111 -> -3792 | I115: =I98+I105+I111 -> -1680 | J115: =J98+J105+J111 -> -275 | K115: =K98+K105+K111 -> -252 | ... R115: =R98+R105+R111 -> -201
C116: Exchange rate effect | D116: -1269 | E116: 556 | F116: 422 | G116: -302 | H116: 288 | I116: 539 | J116: 448 | K116: 22 | L116: -447 | M116: -13 | N116: -803 | O116: -95 | P116: 1370 | Q116: 177 | R116: -418
C117: Cash and cash equivalents at end of year | D117: =SUM(D114:D116) -> 16540 | E117: =SUM(E114:E116) -> 12312 | F117: =SUM(F114:F116) -> 11590 | G117: =SUM(G114:G116) -> 9718 | H117: =SUM(H114:H116) -> 9446 | I117: =SUM(I114:I116) -> 12950 | J117: =SUM(J114:J116) -> 14091 | K117: =SUM(K114:K116) -> 13918 | ... R117: =SUM(R114:R116) -> 9877
A184: Revenue
A185: Cost of Sales (by function)
A186: SG&A (by function)
A187: Cost of Materials (by nature)
A188: Personnel Expenses (by nature)
A189: Depreciation and Amortization (by nature)
A190: Other Operating Income, Net of Other Operating Expense (by function)
...

Sheet Standardized Statements
B1: 2020 | C1: 2019 | D1: 2018 | E1: 2017 | F1: 2016 | G1: 2015 | H1: 2014 | I1: 2013 | J1: 2012 | K1: 2011 | L1: 2010 | M1: 2009 | N1: 2008 | O1: 2007 | P1: 2006
A2: INCOME STATEMENT
B3: =DSUM('Financial Statements'!$A$1:$R$170,"2020",$R$3:$R$4) -> 1043098 | C3: =DSUM('Financial Statements'!$A$1:$R$170,"2019",$R$3:$R$4) -> 774831 | D3: =DSUM('Financial Statements'!$A$1:$R$170,"2018",$R$3:$R$4) -> 765028 | E3: =DSUM('Financial Statements'!$A$1:$R$170,"2017",$R$3:$R$4) -> 712543 | F3: =DSUM('Financial Statements'!$A$1:$R$170,"2016",$R$3:$R$4) -> 674732 | G3: =DSUM('Financial Statements'!$A$1:$R$170,"2015",$R$3:$R$4) -> 629290 | H3: =DSUM('Financial Statements'!$A$1:$R$170,"2014",$R$3:$R$4) -> 575846 | I3: =DSUM('Financial Statements'!$A$1:$R$170,"2013",$R$3:$R$4) -> 504785 | J3: =DSUM('Financial Statements'!$A$1:$R$170,"2012",$R$3:$R$4) -> 473455 | K3: =DSUM('Financial Statements'!$A$1:$R$170,"2011",$R$3:$R$4) -> 464938 | L3: =DSUM('Financial Statements'!$A$1:$R$170,"2010",$R$3:$R$4) -> 487175 | M3: =DSUM('Financial Statements'!$A$1:$R$170,"2009",$R$3:$R$4) -> 441978 | N3: =DSUM('Financial Statements'!$A$1:$R$170,"2008",$R$3:$R$4) -> 445743 | O3: =DSUM('Financial Statements'!$A$1:$R$170,"2007",$R$3:$R$4) -> 368844 | P3: =DSUM('Financial Statements'!$A$1:$R$170,"2006",$R$3:$R$4) -> 291885 | R3: Standard accounts
A4: Revenue | B4: 187031 | C4: 232755 | D4: 210400 | E4: 200004 | F4: 192267 | G4: 180861 | H4: 151419 | I4: 128562 | J4: 120799 | K4: 109999 | L4: 108483 | M4: 101393 | N4: 88532 | O4: 78346 | P4: 68400
A5: Cost of Sales (by function) | B5: -93487 | C5: -110302 | D5: -99513 | E5: -91914 | F5: -86090 | G5: -77694 | H5: -62367 | I5: -52529 | J5: -48928 | K5: -43852 | L5: -40214 | M5: -38919 | N5: -34064 | O5: -30499 | P5: -27736
A6: SG&A (by function) | B6: -90438 | C6: -105091 | D6: -95380 | E6: -87508 | F6: -82336 | G6: -76204 | H6: -63443 | I6: -53843 | J6: -50092 | K6: -45739 | L6: -43598 | M6: -40819 | N6: -34320 | O6: -29457 | P6: -25357
A7: Other Operating Income, Net of Other Operating Expense (by function) | B7: 0 | C7: 0 | D7: 0 | E7: 0 | F7: 0 | G7: 0 | H7: 0 | I7: 0 | J7: 0 | K7: 0 | L7: 0 | M7: 0 | N7: 0 | O7: 0 | P7: 0
A8: Investment Income | B8: 0 | C8: 0 | D8: 0 | E8: 0 | F8: 0 | G8: 0 | H8: 0 | I8: 0 | J8: 0 | K8: 0 | L8: 0 | M8: 0 | N8: 0 | O8: 0 | P8: 0
A9: Interest Income | B9: 252 | C9: 376 | D9: 292 | E9: 281 | F9: 224 | G9: 310 | H9: 328 | I9: 367 | J9: 536 | K9: 568 | L9: 356 | M9: 467 | N9: 1060 | O9: 793 | P9: 515
A10: Interest Expense | B10: -1306 | C10: -347 | D10: -160 | E10: -54 | F10: -26 | G10: -31 | H10: -42 | I10: -31 | J10: -30 | K10: -34 | L10: -19 | M10: -19 | N10: -18 | O10: -13 | P10: -14
A11: Net Non-Recurring Income or Expense | B11: 0 | C11: 0 | D11: 0 | E11: 0 | F11: 0 | G11: 0 | H11: 0 | I11: 0 | J11: 0 | K11: 0 | L11: 0 | M11: 0 | N11: 0 | O11: 0 | P11: 0
A12: Tax Expense | B12: -809 | C12: -3948 | D12: -2987 | E12: -4625 | F12: -5403 | G12: -6344 | H12: -5919 | I12: -5374 | J12: -5418 | K12: -5121 | L12: -6327 | M12: -5719 | N12: -5896 | O12: -5582 | P12: -5011
A13: Profit/Loss to Non-Controlling Interest | B13: 0 | C13: 0 | D13: 0 | E13: 0 | F13: 0 | G13: 0 | H13: 0 | I13: 0 | J13: 0 | K13: 0 | L13: 0 | M13: 0 | N13: 0 | O13: 0 | P13: 0
A14: Profit/Loss to Ordinary Shareholders | B14: =SUM(B4:B13) -> 1243 | C14: =SUM(C4:C13) -> 13443 | D14: =SUM(D4:D13) -> 12652 | E14: =SUM(E4:E13) -> 16184 | F14: =SUM(F4:F13) -> 18636 | G14: =SUM(G4:G13) -> 20898 | H14: =SUM(H4:H13) -> 19976 | I14: =SUM(I4:I13) -> 17152 | ... P14: =SUM(P4:P13) -> 10797
A16: PRO FORMA ITEMS
B17: =DSUM('Financial Statements'!$A$1:$R$170,"2020",$R$3:$R$4) -> 1043098 | C17: =DSUM('Financial Statements'!$A$1:$R$170,"2019",$R$3:$R$4) -> 774831 | D17: =DSUM('Financial Statements'!$A$1:$R$170,"2018",$R$3:$R$4) -> 765028 | E17: =DSUM('Financial Statements'!$A$1:$R$170,"2017",$R$3:$R$4) -> 712543 | F17: =DSUM('Financial Statements'!$A$1:$R$170,"2016",$R$3:$R$4) -> 674732 | G17: =DSUM('Financial Statements'!$A$1:$R$170,"2015",$R$3:$R$4) -> 629290 | H17: =DSUM('Financial Statements'!$A$1:$R$170,"2014",$R$3:$R$4) -> 575846 | I17: =DSUM('Financial Statements'!$A$1:$R$170,"2013",$R$3:$R$4) -> 504785 | J17: =DSUM('Financial Statements'!$A$1:$R$170,"2012",$R$3:$R$4) -> 473455 | K17: =DSUM('Financial Statements'!$A$1:$R$170,"2011",$R$3:$R$4) -> 464938 | L17: =DSUM('Financial Statements'!$A$1:$R$170,"2010",$R$3:$R$4) -> 487175 | M17: =DSUM('Financial Statements'!$A$1:$R$170,"2009",$R$3:$R$4) -> 441978 | N17: =DSUM('Financial Statements'!$A$1:$R$170,"2008",$R$3:$R$4) -> 445743 | O17: =DSUM('Financial Statements'!$A$1:$R$170,"2007",$R$3:$R$4) -> 368844 | P17: =DSUM('Financial Statements'!$A$1:$R$170,"2006",$R$3:$R$4) -> 291885
A18: Profit/Loss of Discontinued Operations | B18: 0 | C18: 0 | D18: 0 | E18: 0 | F18: 0 | G18: 0 | H18: 0 | I18: 0 | J18: 0 | K18: 0 | L18: 0 | M18: 0 | N18: 0 | O18: 0 | P18: 0
A19: Cost of Materials (by nature) | B19: -91538 | C19: -109732 | D19: -98955 | E19: -91178 | F19: -85243 | G19: -76969 | H19: -61799 | I19: -52059 | J19: -48513 | K19: -43486 | L19: -39878 | M19: -38609 | N19: -33819 | O19: -30296 | P19: -27564
A20: Personnel Expenses (by nature) | B20: -36952 | C20: -42385 | D20: -38543 | E20: -35634 | F20: -32561 | G20: -29952 | H20: -25048 | I20: -21423 | J20: -19893 | K20: -18505 | L20: -16628 | M20: -17507 | N20: -14484 | O20: -12168 | P20: -10991
A21: Depreciation and Amortization (by nature) | B21: -25953 | C21: -11051 | D21: -9671 | E21: -8488 | F21: -7605 | G21: -6399 | H21: -5045 | I21: -4191 | J21: -3705 | K21: -3262 | L21: -3061 | M21: -2830 | N21: -1856 | O21: -1840 | P21: -1624
A22: Other Operating Income, Net of Other Operating Expense (by nature) | B22: 0 | C22: 0 | D22: 0 | E22: 0 | F22: 0 | G22: 0 | H22: 0 | I22: 0 | J22: 0 | K22: 0 | L22: 0 | M22: 0 | N22: 0 | O22: 0 | P22: 0
A24: BALANCE SHEET - ASSETS
B25: =DSUM('Financial Statements'!$A$1:$R$170,"2020",$R$3:$R$4) -> 1043098 | C25: =DSUM('Financial Statements'!$A$1:$R$170,"2019",$R$3:$R$4) -> 774831 | D25: =DSUM('Financial Statements'!$A$1:$R$170,"2018",$R$3:$R$4) -> 765028 | E25: =DSUM('Financial Statements'!$A$1:$R$170,"2017",$R$3:$R$4) -> 712543 | F25: =DSUM('Financial Statements'!$A$1:$R$170,"2016",$R$3:$R$4) -> 674732 | G25: =DSUM('Financial Statements'!$A$1:$R$170,"2015",$R$3:$R$4) -> 629290 | H25: =DSUM('Financial Statements'!$A$1:$R$170,"2014",$R$3:$R$4) -> 575846 | I25: =DSUM('Financial Statements'!$A$1:$R$170,"2013",$R$3:$R$4) -> 504785 | J25: =DSUM('Financial Statements'!$A$1:$R$170,"2012",$R$3:$R$4) -> 473455 | K25: =DSUM('Financial Statements'!$A$1:$R$170,"2011",$R$3:$R$4) -> 464938 | L25: =DSUM('Financial Statements'!$A$1:$R$170,"2010",$R$3:$R$4) -> 487175 | M25: =DSUM('Financial Statements'!$A$1:$R$170,"2009",$R$3:$R$4) -> 441978 | N25: =DSUM('Financial Statements'!$A$1:$R$170,"2008",$R$3:$R$4) -> 445743 | O25: =DSUM('Financial Statements'!$A$1:$R$170,"2007",$R$3:$R$4) -> 368844 | P25: =DSUM('Financial Statements'!$A$1:$R$170,"2006",$R$3:$R$4) -> 291885
A26: Cash and Cash Equivalents | B26: 16540 | C26: 12312 | D26: 11590 | E26: 9718 | F26: 9446 | G26: 12950 | H26: 16693 | I26: 17224 | J26: 17143 | K26: 21277 | L26: 24858 | M26: 22025 | N26: 22726 | O26: 20964 | P26: 18625
A27: Trade Receivables | B27: 3086 | C27: 5879 | D27: 6329 | E27: 5297 | F27: 4881 | G27: 4021 | H27: 3659 | I27: 3107 | J27: 2207 | K27: 2337 | L27: 2258 | M27: 1990 | N27: 1991 | O27: 1122 | P27: 865
A28: Inventories | B28: 38209 | C28: 37823 | D28: 37721 | E28: 33712 | F28: 31732 | G28: 24833 | H28: 19403 | I28: 16695 | J28: 15213 | K28: 13819 | L28: 11487 | M28: 10240 | N28: 8500 | O28: 7969 | P28: 7220
A29: Other Current Assets | B29: 6793 | C29: 5597 | D29: 5564 | E29: 6522 | F29: 3756 | G29: 3025 | H29: 2543 | I29: 1976 | J29: 2511 | K29: 2029 | L29: 1872 | M29: 1566 | N29: 1494 | O29: 983 | P29: 812
A30: Non-Current Tangible Assets | B30: 91365 | C30: 41303 | D30: 42947 | E30: 40410 | F30: 39323 | G30: 33622 | H30: 27457 | I30: 22777 | J30: 19668 | K30: 17978 | L30: 16157 | M30: 15555 | N30: 13100 | O30: 9553 | P30: 7776
A31: Non-Current Intangible Assets | B31: 10241 | C31: 11037 | D31: 9110 | E31: 6451 | F31: 4717 | G31: 3455 | H31: 2453 | I31: 1685 | J31: 1021 | K31: 450 | L31: 510 | M31: 930 | N31: 997 | O31: 0 | P31: 0
A32: Minority Equity Investments | B32: 247 | C32: 210 | D32: 126 | E32: 0 | F32: 0 | G32: 0 | H32: 0 | I32: 0 | J32: 0 | K32: 0 | L32: 0 | M32: 0 | N32: 0 | O32: 0 | P32: 0
A33: Other Non-Operating Investments | B33: 1446 | C33: 1341 | D33: 1237 | E33: 1039 | F33: 1014 | G33: 862 | H33: 709 | I33: 659 | J33: 628 | K33: 608 | L33: 518 | M33: 551 | N33: 476 | O33: 253 | P33: 155
A34: Deferred Tax Asset | B34: 5714 | C34: 4322 | D34: 3794 | E34: 2916 | F34: 2862 | G34: 2338 | H34: 2237 | I34: 1367 | J34: 1624 | K34: 1234 | L34: 1065 | M34: 1246 | N34: 1299 | O34: 883 | P34: 102
A35: Derivatives - Asset | B35: 730 | C35: 661 | D35: 372 | E35: 497 | F35: 848 | G35: 707 | H35: 443 | I35: 186 | J35: 158 | K35: 456 | L35: 457 | M35: 260 | N35: 660 | O35: 7 | P35: 0
A36: Assets Held For Sale | B36: 0 | C36: 0 | D36: 0 | E36: 0 | F36: 0 | G36: 0 | H36: 0 | I36: 0 | J36: 0 | K36: 0 | L36: 0 | M36: 0 | N36: 0 | O36: 0 | P36: 0
A37: Total Assets | B37: =SUM(B26:B36) -> 174371 | C37: =SUM(C26:C36) -> 120485 | D37: =SUM(D26:D36) -> 118790 | E37: =SUM(E26:E36) -> 106562 | F37: =SUM(F26:F36) -> 98579 | G37: =SUM(G26:G36) -> 85813 | H37: =SUM(H26:H36) -> 75597 | I37: =SUM(I26:I36) -> 65676 | ... P37: =SUM(P26:P36) -> 35555
A39: BALANCE SHEET - EQUITY & LIABILITIES
B40: =DSUM('Financial Statements'!$A$1:$R$170,"2020",$R$3:$R$4) -> 1043098 | C40: =DSUM('Financial Statements'!$A$1:$R$170,"2019",$R$3:$R$4) -> 774831 | D40: =DSUM('Financial Statements'!$A$1:$R$170,"2018",$R$3:$R$4) -> 765028 | E40: =DSUM('Financial Statements'!$A$1:$R$170,"2017",$R$3:$R$4) -> 712543 | F40: =DSUM('Financial Statements'!$A$1:$R$170,"2016",$R$3:$R$4) -> 674732 | G40: =DSUM('Financial Statements'!$A$1:$R$170,"2015",$R$3:$R$4) -> 629290 | H40: =DSUM('Financial Statements'!$A$1:$R$170,"2014",$R$3:$R$4) -> 575846 | I40: =DSUM('Financial Statements'!$A$1:$R$170,"2013",$R$3:$R$4) -> 504785 | J40: =DSUM('Financial Statements'!$A$1:$R$170,"2012",$R$3:$R$4) -> 473455 | K40: =DSUM('Financial Statements'!$A$1:$R$170,"2011",$R$3:$R$4) -> 464938 | L40: =DSUM('Financial Statements'!$A$1:$R$170,"2010",$R$3:$R$4) -> 487175 | M40: =DSUM('Financial Statements'!$A$1:$R$170,"2009",$R$3:$R$4) -> 441978 | N40: =DSUM('Financial Statements'!$A$1:$R$170,"2008",$R$3:$R$4) -> 445743 | O40: =DSUM('Financial Statements'!$A$1:$R$170,"2007",$R$3:$R$4) -> 368844 | P40: =DSUM('Financial Statements'!$A$1:$R$170,"2006",$R$3:$R$4) -> 291885
A41: Current Debt | B41: 21174 | C41: 7051 | D41: 9289 | E41: 9870 | F41: 2127 | G41: 0 | H41: 0 | I41: 0 | J41: 0 | K41: 0 | L41: 0 | M41: 0 | N41: 0 | O41: 0 | P41: 0
A42: Trade Payables | B42: 9511 | C42: 7838 | D42: 6800 | E42: 7215 | F42: 7262 | G42: 6000 | H42: 5520 | I42: 4870 | J42: 4234 | K42: 4307 | L42: 3965 | M42: 3667 | N42: 3658 | O42: 2483 | P42: 1942
A43: Other Current Liabilities | B43: 25012 | C43: 32468 | D43: 27892 | E43: 22735 | F43: 21140 | G43: 16635 | H43: 14529 | I43: 12242 | J43: 9554 | K43: 10300 | L43: 9706 | M43: 7088 | N43: 6987 | O43: 6219 | P43: 5054
A44: Non-Current Debt | B44: 59503 | C44: 11157 | D44: 10937 | E44: 795 | F44: 740 | G44: 449 | H44: 451 | I44: 309 | J44: 377 | K44: 377 | L44: 257 | M44: 254 | N44: 596 | O44: 156 | P44: 130
A45: Deferred Tax Liability | B45: 3988 | C45: 4423 | D45: 5088 | E45: 5331 | F45: 4898 | G45: 4378 | H45: 3287 | I45: 2722 | J45: 1951 | K45: 950 | L45: 906 | M45: 2038 | N45: 1818 | O45: 651 | P45: 650
A46: Derivatives - Liability | B46: 560 | C46: 479 | D46: 238 | E46: 903 | F46: 1176 | G46: 302 | H46: 254 | I46: 285 | J46: 222 | K46: 150 | L46: 176 | M46: 335 | N46: 1234 | O46: 132 | P46: 0
A47: Other Non-Current Liabilities (non interest bearing) | B47: 0 | C47: 0 | D47: 0 | E47: 0 | F47: 0 | G47: 0 | H47: 0 | I47: 0 | J47: 0 | K47: 0 | L47: 0 | M47: 0 | N47: 0 | O47: 0 | P47: 0
A48: Non-Controlling Interest in Equity | B48: 0 | C48: 0 | D48: 0 | E48: 0 | F48: 0 | G48: 0 | H48: 0 | I48: 0 | J48: 0 | K48: 0 | L48: 0 | M48: 0 | N48: 0 | O48: 0 | P48: 0
A49: Preference Shares | B49: 0 | C49: 0 | D49: 0 | E49: 0 | F49: 0 | G49: 0 | H49: 0 | I49: 0 | J49: 0 | K49: 0 | L49: 0 | M49: 0 | N49: 0 | O49: 0 | P49: 0
A50: Ordinary Shareholders' Equity | B50: 54623 | C50: 57069 | D50: 58546 | E50: 59713 | F50: 61236 | G50: 58049 | H50: 51556 | I50: 45248 | J50: 43835 | K50: 44104 | L50: 44172 | M50: 40613 | N50: 36950 | O50: 32093 | P50: 27779
A51: Liabilities Held For Sale | B51: 0 | C51: 0 | D51: 0 | E51: 0 | F51: 0 | G51: 0 | H51: 0 | I51: 0 | J51: 0 | K51: 0 | L51: 0 | M51: 0 | N51: 0 | O51: 0 | P51: 0
A52: Total Liabilities and Shareholders' Equity | B52: =SUM(B41:B51) -> 174371 | C52: =SUM(C41:C51) -> 120485 | D52: =SUM(D41:D51) -> 118790 | E52: =SUM(E41:E51) -> 106562 | F52: =SUM(F41:F51) -> 98579 | G52: =SUM(G41:G51) -> 85813 | H52: =SUM(H41:H51) -> 75597 | I52: =SUM(I41:I51) -> 65676 | ... P52: =SUM(P41:P51) -> 35555
A54: CASH FLOW STATEMENT
B55: =DSUM('Financial Statements'!$A$1:$R$170,"2020",$R$3:$R$4) -> 1043098 | C55: =DSUM('Financial Statements'!$A$1:$R$170,"2019",$R$3:$R$4) -> 774831 | D55: =DSUM('Financial Statements'!$A$1:$R$170,"2018",$R$3:$R$4) -> 765028 | E55: =DSUM('Financial Statements'!$A$1:$R$170,"2017",$R$3:$R$4) -> 712543 | F55: =DSUM('Financial Statements'!$A$1:$R$170,"2016",$R$3:$R$4) -> 674732 | G55: =DSUM('Financial Statements'!$A$1:$R$170,"2015",$R$3:$R$4) -> 629290 | H55: =DSUM('Financial Statements'!$A$1:$R$170,"2014",$R$3:$R$4) -> 575846 | I55: =DSUM('Financial Statements'!$A$1:$R$170,"2013",$R$3:$R$4) -> 504785 | J55: =DSUM('Financial Statements'!$A$1:$R$170,"2012",$R$3:$R$4) -> 473455 | K55: =DSUM('Financial Statements'!$A$1:$R$170,"2011",$R$3:$R$4) -> 464938 | L55: =DSUM('Financial Statements'!$A$1:$R$170,"2010",$R$3:$R$4) -> 487175 | M55: =DSUM('Financial Statements'!$A$1:$R$170,"2009",$R$3:$R$4) -> 441978 | N55: =DSUM('Financial Statements'!$A$1:$R$170,"2008",$R$3:$R$4) -> 445743 | O55: =DSUM('Financial Statements'!$A$1:$R$170,"2007",$R$3:$R$4) -> 368844 | P55: =DSUM('Financial Statements'!$A$1:$R$170,"2006",$R$3:$R$4) -> 291885
A56: Profit Before Interest and Tax | B56: 3106 | C56: 17362 | D56: 15507 | E56: 20582 | F56: 23841 | G56: 26963 | H56: 25609 | I56: 22190 | J56: 21779 | K56: 20408 | L56: 24671 | M56: 21655 | N56: 20148 | O56: 18390 | P56: 15307
A57: Non-Operating Losses (Gains) | B57: 0 | C57: 0 | D57: 0 | E57: 0 | F57: 0 | G57: 0 | H57: 0 | I57: 0 | J57: 0 | K57: 0 | L57: 0 | M57: 0 | N57: 0 | O57: 0 | P57: 0
A58: Non-Current Operating Accruals | B58: 25975 | C58: 11062 | D58: 9710 | E58: 8477 | F58: 7596 | G58: 6427 | H58: 5025 | I58: 4123 | J58: 3715 | K58: 3382 | L58: 3064 | M58: 2856 | N58: 2274 | O58: 1841 | P58: 1676
A59: Taxes Paid | B59: -3719 | C59: -3700 | D59: -3098 | E59: -6051 | F59: -4470 | G59: -7022 | H59: -5971 | I59: -3059 | J59: -7021 | K59: -5666 | L59: -5451 | M59: -6468 | N59: -5940 | O59: -5557 | P59: -5565
A60: Interest Received | B60: 252 | C60: 376 | D60: 292 | E60: 281 | F60: 224 | G60: 310 | H60: 328 | I60: 367 | J60: 536 | K60: 568 | L60: 356 | M60: 467 | N60: 1060 | O60: 793 | P60: 515
A61: Dividends received | B61: 0 | C61: 0 | D61: 0 | E61: 0 | F61: 0 | G61: 0 | H61: 0 | I61: 0 | J61: 0 | K61: 0 | L61: 0 | M61: 0 | N61: 0 | O61: 0 | P61: 0
A62: Net (Investments in) or Liquidation of Operating Working Capital | B62: 1592 | C62: 4233 | D62: -964 | E62: -1648 | F62: -3390 | G62: -2580 | H62: -793 | I62: 250 | J62: -79 | K62: -1238 | L62: -783 | M62: -518 | N62: 442 | O62: -73 | P62: 136
A63: Net (Investments in) or Liquidation of Non-Current Operating or Investment Assets | B63: -5244 | C63: -10528 | D63: -13152 | E63: -12496 | F63: -13498 | G63: -9610 | H63: -8708 | I63: -8369 | J63: -2901 | K63: -4056 | L63: -10129 | M63: -8755 | N63: -1090 | O63: 144 | P63: -4395
A64: Free Cash Flow | B64: =SUM(B56:B63) -> 21962 | C64: =SUM(C56:C63) -> 18805 | D64: =SUM(D56:D63) -> 8295 | E64: =SUM(E56:E63) -> 9145 | F64: =SUM(F56:F63) -> 10303 | G64: =SUM(G56:G63) -> 14488 | H64: =SUM(H56:H63) -> 15490 | I64: =SUM(I56:I63) -> 15502 | ... P64: =SUM(P56:P63) -> 7674
B65: =DSUM('Financial Statements'!$A$1:$R$170,"2020",$R$3:$R$4) -> 1043098 | C65: =DSUM('Financial Statements'!$A$1:$R$170,"2019",$R$3:$R$4) -> 774831 | D65: =DSUM('Financial Statements'!$A$1:$R$170,"2018",$R$3:$R$4) -> 765028 | E65: =DSUM('Financial Statements'!$A$1:$R$170,"2017",$R$3:$R$4) -> 712543 | F65: =DSUM('Financial Statements'!$A$1:$R$170,"2016",$R$3:$R$4) -> 674732 | G65: =DSUM('Financial Statements'!$A$1:$R$170,"2015",$R$3:$R$4) -> 629290 | H65: =DSUM('Financial Statements'!$A$1:$R$170,"2014",$R$3:$R$4) -> 575846 | I65: =DSUM('Financial Statements'!$A$1:$R$170,"2013",$R$3:$R$4) -> 504785 | J65: =DSUM('Financial Statements'!$A$1:$R$170,"2012",$R$3:$R$4) -> 473455 | K65: =DSUM('Financial Statements'!$A$1:$R$170,"2011",$R$3:$R$4) -> 464938 | L65: =DSUM('Financial Statements'!$A$1:$R$170,"2010",$R$3:$R$4) -> 487175 | M65: =DSUM('Financial Statements'!$A$1:$R$170,"2009",$R$3:$R$4) -> 441978 | N65: =DSUM('Financial Statements'!$A$1:$R$170,"2008",$R$3:$R$4) -> 445743 | O65: =DSUM('Financial Statements'!$A$1:$R$170,"2007",$R$3:$R$4) -> 368844 | P65: =DSUM('Financial Statements'!$A$1:$R$170,"2006",$R$3:$R$4) -> 291885
A66: Net Debt (Repayment) or Issuance | B66: -15159 | C66: -2155 | D66: 9452 | E66: 7620 | F66: 2068 | G66: 0 | H66: 0 | I66: 0 | J66: 0 | K66: 0 | L66: 0 | M66: 0 | N66: 0 | O66: 0 | P66: 0
A67: Interest Paid | B67: -1306 | C67: -347 | D67: -160 | E67: -54 | F67: -26 | G67: -31 | H67: -42 | I67: -31 | J67: -30 | K67: -34 | L67: -19 | M67: -19 | N67: -18 | O67: -13 | P67: -14
A68: Dividend (Payments) | B68: 0 | C68: -16137 | D68: -16137 | E68: -16137 | F68: -16137 | G68: -16137 | H68: -15723 | I68: -15723 | J68: -15723 | K68: -15723 | L68: -13239 | M68: -12825 | N68: -11584 | O68: -9515 | P68: -7861
A69: Net Share (Repurchase) or Issuance | B69: 0 | C69: 0 | D69: 0 | E69: 0 | F69: 0 | G69: 0 | H69: 0 | I69: 0 | J69: 0 | K69: 0 | L69: 0 | M69: 0 | N69: 0 | O69: 0 | P69: 0
A70: Net Cash Flow | B70: =B64+SUM(B66:B69) -> 5497 | C70: =C64+SUM(C66:C69) -> 166 | D70: =D64+SUM(D66:D69) -> 1450 | E70: =E64+SUM(E66:E69) -> 574 | F70: =F64+SUM(F66:F69) -> -3792 | G70: =G64+SUM(G66:G69) -> -1680 | H70: =H64+SUM(H66:H69) -> -275 | I70: =I64+SUM(I66:I69) -> -252 | ... P70: =P64+SUM(P66:P69) -> -201

Sheet Lease adjustments
A1: Minimum operating lease payments | B1: 2020 | C1: 2019 | D1: 2018 | E1: 2017 | F1: 2016 | G1: 2015 | H1: 2014 | I1: 2013 | J1: 2012 | K1: 2011 | L1: 2010 | M1: 2009 | N1: 2008 | O1: 2007 | P1: 2006 | R1: Notes
A2: Within one year | B2: 0 | C2: 16234 | D2: 16234 | E2: 16219 | F2: 16068 | G2: 14626 | H2: 13210 | I2: 11363 | J2: 10080 | K2: 9942 | L2: 9546 | M2: 9383 | N2: 8918 | O2: 6801 | P2: 6169
A3: In two to five years | B3: 0 | C3: 36562 | D3: 37535 | E3: 41788 | F3: 41605 | G3: 41732 | H3: 39680 | I3: 31446 | J3: 27800 | K3: 28085 | L3: 27255 | M3: 26416 | N3: 26368 | O3: 19732 | P3: 17689
A4: Over five years | B4: 0 | C4: 18110 | D4: 16413 | E4: 20330 | F4: 23820 | G4: 28965 | H4: 25727 | I4: 20831 | J4: 17440 | K4: 18273 | L4: 17878 | M4: 18546 | N4: 18728 | O4: 12478 | P4: 11593
A6: Interest rate | B6: 0.02 | C6: 0.02 | D6: 0.02 | E6: 0.02 | F6: 0.0205 | G6: 0.0215 | H6: 0.019 | I6: 0.021 | J6: 0.0185 | K6: 0.032 | L6: 0.028 | M6: 0.0305 | N6: 0.0515 | O6: 0.0475 | P6: 0.044 | R6: AA Corporate bond yield (BOFA ML Corporate Bond Index)
A7: Actual lease payment | B7: 0 | C7: =26347-5225 -> 21122 | D7: =24801-4428 -> 20373 | E7: 19126 | F7: 20554 | G7: 20554 | H7: 17176 | I7: 15044 | J7: 14056 | K7: 12993 | L7: 12891 | M7: 12249 | N7: 9776 | O7: 8467 | P7: 7549 | R7: Actual lease payment in 2007 (8,467) is higher than minimum operating lease payments within one year in 2006 (6,169) listed in the previous year, because the firm signed up new leasese in 2007 and paid some of the new leaseses
A8: Tax rate | B8: 0.22 | C8: 0.22 | D8: 0.22 | E8: 0.22 | F8: 0.22 | G8: 0.22 | H8: 0.22 | I8: 0.22 | J8: 0.263 | K8: 0.263 | L8: 0.263 | M8: 0.28 | N8: 0.28 | O8: 0.28 | P8: 0.28
A10: 1 | B10: =B2 -> 0 | C10: =C2 -> 16234 | D10: =D2 -> 16234 | E10: =E2 -> 16219 | F10: =F2 -> 16068 | G10: =G2 -> 14626 | H10: =H2 -> 13210 | I10: =I2 -> 11363 | ... P10: =P2 -> 6169
A11: 2 | B11: =B$3/4 -> 0 | C11: =C$3/4 -> 9140.5 | D11: =D$3/4 -> 9383.75 | E11: =E$3/4 -> 10447 | F11: =F$3/4 -> 10401.25 | G11: =G$3/4 -> 10433 | H11: =H$3/4 -> 9920 | I11: =I$3/4 -> 7861.5 | ... P11: =P$3/4 -> 4422.25
A12: 3 | B12: =B$3/4 -> 0 | C12: =C$3/4 -> 9140.5 | D12: =D$3/4 -> 9383.75 | E12: =E$3/4 -> 10447 | F12: =F$3/4 -> 10401.25 | G12: =G$3/4 -> 10433 | H12: =H$3/4 -> 9920 | I12: =I$3/4 -> 7861.5 | ... P12: =P$3/4 -> 4422.25
A13: 4 | B13: =B$3/4 -> 0 | C13: =C$3/4 -> 9140.5 | D13: =D$3/4 -> 9383.75 | E13: =E$3/4 -> 10447 | F13: =F$3/4 -> 10401.25 | G13: =G$3/4 -> 10433 | H13: =H$3/4 -> 9920 | I13: =I$3/4 -> 7861.5 | ... P13: =P$3/4 -> 4422.25
A14: 5 | B14: =B$3/4 -> 0 | C14: =C$3/4 -> 9140.5 | D14: =D$3/4 -> 9383.75 | E14: =E$3/4 -> 10447 | F14: =F$3/4 -> 10401.25 | G14: =G$3/4 -> 10433 | H14: =H$3/4 -> 9920 | I14: =I$3/4 -> 7861.5 | ... P14: =P$3/4 -> 4422.25
A15: 6 | B15: =0 -> 0 | C15: =C14 -> 9140.5 | D15: =D14 -> 9383.75 | E15: =E14 -> 10447 | F15: =F14 -> 10401.25 | G15: =G14 -> 10433 | H15: =H14 -> 9920 | I15: =I14 -> 7861.5 | J15: =J14 -> 6950 | ... P15: =P14 -> 4422.25 | R15: The allocation of minimum operating leases payments over five years is based on assumptions.
A16: 7 | B16: 0 | C16: =C4-C15 -> 8969.5 | D16: =D4-D15 -> 7029.25 | E16: =E4-E15 -> 9883 | F16: =F15 -> 10401.25 | G16: =G15 -> 10433 | H16: =H15 -> 9920 | I16: =I15 -> 7861.5 | J16: =J15 -> 6950 | K16: =K15 -> 7021.25 | L16: =L15 -> 6813.75 | M16: =M15 -> 6604 | ... P16: =P15 -> 4422.25
A17: 8 | F17: =F4-F15-F16 -> 3017.5 | G17: =G4-G15-G16 -> 8099 | H17: =H4-H15-H16 -> 5887 | I17: =I4-I15-I16 -> 5108 | J17: =J4-J15-J16 -> 3540 | K17: =K4-K15-K16 -> 4230.5 | L17: =L4-L15-L16 -> 4250.5 | M17: =M4-M15-M16 -> 5338 | ... P17: =P4-P15-P16 -> 2748.5
A20: Total present value/Total finance lease obligation | B20: =NPV(B6,B10:B17) -> 0 | C20: =NPV(C6,C10:C17) -> 65962.78 | D20: =NPV(D6,D10:D17) -> 65397.744 | E20: =NPV(E6,E10:E17) -> 72780.718 | F20: =NPV(F6,F10:F17) -> 75305.85 | G20: =NPV(G6,G10:G17) -> 78071.029 | H20: =NPV(H6,H10:H17) -> 72742.396 | I20: =NPV(I6,I10:I17) -> 58439.615 | ... P20: =NPV(P6,P10:P17) -> 29775.325
A21: Present value Yr 2 onwards | B21: =NPV(B6,0,B11:B17) -> 0 | C21: =NPV(C6,0,C11:C17) -> 50047.094 | D21: =NPV(D6,0,D11:D17) -> 49482.057 | E21: =NPV(E6,0,E11:E17) -> 56879.738 | F21: =NPV(F6,0,F11:F17) -> 59560.627 | G21: =NPV(G6,0,G11:G17) -> 63752.87 | H21: =NPV(H6,0,H11:H17) -> 59778.706 | I21: =NPV(I6,0,I11:I17) -> 47310.33 | ... P21: =NPV(P6,0,P11:P17) -> 23866.321 | R21: This is the present value of minimum operating lease payments from Year 2 onwards. This number times (1+interest rate) will be the carrying value of current finance lease obligations at the end of the following year.
A22: Current portion of finance lease obligation | B22: =B10-B20*B6 -> 0 | C22: =C10-C20*C6 -> 14914.744 | D22: =D10-D20*D6 -> 14926.045 | E22: =E10-E20*E6 -> 14763.386 | F22: =F10-F20*F6 -> 14524.23 | G22: =G10-G20*G6 -> 12947.473 | H22: =H10-H20*H6 -> 11827.894 | I22: =I10-I20*I6 -> 10135.768 | ... P22: =P10-P20*P6 -> 4858.8857 | R22: Minimum lease payment next year - Finance lease obligation * (1+interest rate)
A24: PV of New lease commitments | B24: 0 | C24: =(C20-(1+D6)*D21)+(C7-D2) -> 20379.082 | D24: =(D20-(1+E6)*E21)+(D7-E2) -> 11534.411 | E24: =(E20-(1+F6)*F21)+(E7-F2) -> 15057.099 | F24: =(F20-(1+G6)*G21)+(F7-G2) -> 16110.293 | G24: =(G20-(1+H6)*H21)+(G7-H2) -> 24500.528 | H24: =(H20-(1+I6)*I21)+(H7-I2) -> 30251.549 | I24: =(I20-(1+J6)*J21)+(I7-J2) -> 21162.138 | J24: =(J20-(1+K6)*K21)+(J7-K2) -> 14307.112 | ... O24: =(O20-(1+P6)*P21)+(O7-P2) -> 9771.4003 | R24: PV of New lease commitments in 2007=[ Total finance lease obligation in 2007 - Carrying value of 2006 finance lease obligation (i.e. 23,866) times (1+interest rate)) ]+Payment of new leases during the year (i.e. 8,467-6,169)
A26: Interest expense | C26: =D20*D6 -> 1307.9549 | D26: =E20*E6 -> 1455.6144 | E26: =F20*F6 -> 1543.7699 | F26: =G20*G6 -> 1678.5271 | G26: =H20*H6 -> 1382.1055 | H26: =I20*I6 -> 1227.2319 | I26: =J20*J6 -> 950.36557 | J26: =K20*K6 -> 1585.1163 | ... O26: =P20*P6 -> 1310.1143 | R26: Interest expense=Carrying value of Finance Lease Obligation * Interest rate
A27: Total lease repayment | C27: =C7-C26 -> 19814.045 | D27: =D7-D26 -> 18917.386 | E27: =E7-E26 -> 17582.23 | F27: =F7-F26 -> 18875.473 | G27: =G7-G26 -> 19171.894 | H27: =H7-H26 -> 15948.768 | I27: =I7-I26 -> 14093.634 | J27: =J7-J26 -> 12470.884 | ... O27: =O7-O26 -> 7156.8857 | R27: Lease repayment=Actual lease payment - Interest expense; this number is higher than current portion of finance lease obligation in the previous year, because the firm paid new leases signed in current year
A28: Lease repayment of new lease | C28: =C27-D22 -> 4888 | D28: =D27-E22 -> 4154 | E28: =E27-F22 -> 3058 | F28: =F27-G22 -> 5928 | G28: =G27-H22 -> 7344 | H28: =H27-I22 -> 5813 | I28: =I27-J22 -> 4964 | J28: =J27-K22 -> 4114 | ... O28: =O27-P22 -> 2298 | R28: The difference between total lease repayment and current portfion of finance lease obligation of the previous year
A29: Depreciation expense | C29: =C27 -> 19814.045 | D29: =D27 -> 18917.386 | E29: =E27 -> 17582.23 | F29: =F27 -> 18875.473 | G29: =G27 -> 19171.894 | H29: =H27 -> 15948.768 | I29: =I27 -> 14093.634 | J29: =J27 -> 12470.884 | ... O29: =O27 -> 7156.8857 | R29: For simplicity, we assume depreciation expense=lease repayment. In this way, the adjustments would have 0 impact on pre-tax profit and shareholder's equity.
A31: Adjustments:
A32: Non-current tangible assets | B32: 0 | C32: =D20+C24-C29 -> 65962.78 | D32: =E20+D24-D29 -> 65397.744 | E32: =F20+E24-E29 -> 72780.718 | F32: =G20+F24-F29 -> 75305.85 | G32: =H20+G24-G29 -> 78071.029 | H32: =I20+H24-H29 -> 72742.396 | I32: =J20+I24-I29 -> 58439.615 | J32: =K20+J24-J29 -> 51371.112 | ... O32: =P20+O24-O29 -> 32389.84 | P32: =P20 -> 29775.325
A33: Current debt | B33: 0 | C33: =C22 -> 14914.744 | D33: =D22 -> 14926.045 | E33: =E22 -> 14763.386 | F33: =F22 -> 14524.23 | G33: =G22 -> 12947.473 | H33: =H22 -> 11827.894 | I33: =I22 -> 10135.768 | J33: =J22 -> 9129.6344 | ... P33: =P22 -> 4858.8857
A34: Non-current debt | B34: 0 | C34: =C20-C33 -> 51048.036 | D34: =D20-D33 -> 50471.699 | E34: =E20-E33 -> 58017.333 | F34: =F20-F33 -> 60781.619 | G34: =G20-G33 -> 65123.557 | H34: =H20-H33 -> 60914.502 | I34: =I20-I33 -> 48303.847 | J34: =J20-J33 -> 42241.477 | ... P34: =P20-P33 -> 24916.439
A35: Deferred tax liability | B35: 0 | C35: =-C41 -> 0 | D35: =-D41 -> 0 | E35: =-E41 -> -4.0017767e-13 | F35: =-F41 -> 0 | G35: =-G41 -> 0 | H35: =-H41 -> 0 | I35: =-I41 -> 0 | J35: =-J41 -> 0 | ... O35: =-O41 -> 0
A36: Equity | B36: 0 | C36: =C42 -> 1.5916157e-12 | D36: =D42 -> 6.8212103e-13 | E36: =E42 -> -1.4188117e-12 | F36: =F42 -> -2.2737368e-13 | G36: =G42 -> 0 | H36: =H42 -> -2.2737368e-13 | I36: =I42 -> 3.4106051e-13 | J36: =J42 -> 4.5474735e-13 | ... O36: =O42 -> 2.2737368e-13
A38: Cost of sales/SG&A (Lease expense) | B38: 0 | C38: =C7 -> 21122 | D38: =D7 -> 20373 | E38: =E7 -> 19126 | F38: =F7 -> 20554 | G38: =G7 -> 20554 | H38: =H7 -> 17176 | I38: =I7 -> 15044 | J38: =J7 -> 14056 | ... O38: =O7 -> 8467
A39: Cost of sales/SG&A (Lease expense) | B39: 0 | C39: =-C29 -> -19814.045 | D39: =-D29 -> -18917.386 | E39: =-E29 -> -17582.23 | F39: =-F29 -> -18875.473 | G39: =-G29 -> -19171.894 | H39: =-H29 -> -15948.768 | I39: =-I29 -> -14093.634 | J39: =-J29 -> -12470.884 | ... O39: =-O29 -> -7156.8857
A40: Interest expense | B40: 0 | C40: =-C26 -> -1307.9549 | D40: =-D26 -> -1455.6144 | E40: =-E26 -> -1543.7699 | F40: =-F26 -> -1678.5271 | G40: =-G26 -> -1382.1055 | H40: =-H26 -> -1227.2319 | I40: =-I26 -> -950.36557 | J40: =-J26 -> -1585.1163 | ... O40: =-O26 -> -1310.1143
A41: Tax expense | B41: 0 | C41: =-C8*SUM(C38:C40) -> 0 | D41: =-D8*SUM(D38:D40) -> 0 | E41: =-E8*SUM(E38:E40) -> 4.0017767e-13 | F41: =-F8*SUM(F38:F40) -> 0 | G41: =-G8*SUM(G38:G40) -> 0 | H41: =-H8*SUM(H38:H40) -> 0 | I41: =-I8*SUM(I38:I40) -> 0 | J41: =-J8*SUM(J38:J40) -> 0 | ... O41: =-O8*SUM(O38:O40) -> 0
A42: Net profit | B42: 0 | C42: =SUM(C38:C41) -> 1.5916157e-12 | D42: =SUM(D38:D41) -> 6.8212103e-13 | E42: =SUM(E38:E41) -> -1.4188117e-12 | F42: =SUM(F38:F41) -> -2.2737368e-13 | G42: =SUM(G38:G41) -> 0 | H42: =SUM(H38:H41) -> -2.2737368e-13 | I42: =SUM(I38:I41) -> 3.4106051e-13 | J42: =SUM(J38:J41) -> 4.5474735e-13 | ... O42: =SUM(O38:O41) -> 2.2737368e-13

Sheet Adjusted Statements
A1: Assumptions: | B1: 2020 | C1: 2019 | D1: 2018 | E1: 2017 | F1: 2016 | G1: 2015 | H1: 2014 | I1: 2013 | J1: 2012 | K1: 2011 | L1: 2010 | M1: 2009 | N1: 2008 | O1: 2007 | P1: 2006 | AH1: 2020 | AI1: 2019 | AJ1: 2018 | AK1: 2017 | AL1: 2016 | AM1: 2015 | AN1: 2014 | AO1: 2013 | AP1: 2012 | AQ1: 2011 | AR1: 2010 | AS1: 2009 | AT1: 2008 | AU1: 2007 | AV1: 2006
A2: Operating cash percentage | B2: 0.05 | C2: 0.05 | D2: 0.05 | E2: 0.05 | F2: 0.05 | G2: 0.05 | H2: 0.05 | I2: 0.05 | J2: 0.05 | K2: 0.05 | L2: 0.05 | M2: 0.05 | N2: 0.05 | O2: 0.05 | P2: 0.05 | AH2: =B2 -> 0.05 | AI2: =C2 -> 0.05 | AJ2: =D2 -> 0.05 | AK2: =E2 -> 0.05 | AL2: =F2 -> 0.05 | AM2: =G2 -> 0.05 | AN2: =H2 -> 0.05 | AO2: =I2 -> 0.05 | ... AV2: =P2 -> 0.05
B4: 2 | C4: 3 | D4: 4 | E4: 5 | F4: 6 | G4: 7 | H4: 8 | I4: 9 | J4: 10 | K4: 11 | L4: 12 | M4: 13 | N4: 14 | O4: 15 | P4: 16
A5: INCOME STATEMENT | B5: 2020 | C5: 2019 | D5: 2018 | E5: 2017 | F5: 2016 | G5: 2015 | H5: 2014 | I5: 2013 | J5: 2012 | K5: 2011 | L5: 2010 | M5: 2009 | N5: 2008 | O5: 2007 | P5: 2006 | R5: Adj 2020 | S5: Adj 2019 | T5: Adj 2018 | U5: Adj 2017 | V5: Adj 2016 | W5: Adj 2015 | X5: Adj 2014 | Y5: Adj 2013 | Z5: Adj 2012 | AA5: Adj 2011 | AB5: Adj 2010 | AC5: Adj 2009 | AD5: Adj 2008 | AE5: Adj 2007 | AF5: Adj 2006 | AH5: 2020 | AI5: 2019 | AJ5: 2018 | AK5: 2017 | AL5: 2016 | AM5: 2015 | AN5: 2014 | AO5: 2013 | AP5: 2012 | AQ5: 2011 | AR5: 2010 | AS5: 2009 | AT5: 2008 | AU5: 2007 | AV5: 2006
A6: Revenue | B6: =VLOOKUP($A6,'Standardized Statements'!$A:$Q,B$4,FALSE) -> 187031 | C6: =VLOOKUP($A6,'Standardized Statements'!$A:$Q,C$4,FALSE) -> 232755 | D6: =VLOOKUP($A6,'Standardized Statements'!$A:$Q,D$4,FALSE) -> 210400 | E6: =VLOOKUP($A6,'Standardized Statements'!$A:$Q,E$4,FALSE) -> 200004 | F6: =VLOOKUP($A6,'Standardized Statements'!$A:$Q,F$4,FALSE) -> 192267 | G6: =VLOOKUP($A6,'Standardized Statements'!$A:$Q,G$4,FALSE) -> 180861 | H6: =VLOOKUP($A6,'Standardized Statements'!$A:$Q,H$4,FALSE) -> 151419 | I6: =VLOOKUP($A6,'Standardized Statements'!$A:$Q,I$4,FALSE) -> 128562 | ... P6: =VLOOKUP($A6,'Standardized Statements'!$A:$Q,P$4,FALSE) -> 68400 | AH6: =B6+R6 -> 187031 | AI6: =C6+S6 -> 232755 | AJ6: =D6+T6 -> 210400 | AK6: =E6+U6 -> 200004 | AL6: =F6+V6 -> 192267 | AM6: =G6+W6 -> 180861 | AN6: =H6+X6 -> 151419 | AO6: =I6+Y6 -> 128562 | ... AV6: =P6+AF6 -> 68400
A7: Operating expenses | B7: =IF(SUM(B21:B23)<>0,SUM(B21:B23),SUM(B25:B28)) -> -183925 | C7: =IF(SUM(C21:C23)<>0,SUM(C21:C23),SUM(C25:C28)) -> -215393 | D7: =IF(SUM(D21:D23)<>0,SUM(D21:D23),SUM(D25:D28)) -> -194893 | E7: =IF(SUM(E21:E23)<>0,SUM(E21:E23),SUM(E25:E28)) -> -179422 | F7: =IF(SUM(F21:F23)<>0,SUM(F21:F23),SUM(F25:F28)) -> -168426 | G7: =IF(SUM(G21:G23)<>0,SUM(G21:G23),SUM(G25:G28)) -> -153898 | H7: =IF(SUM(H21:H23)<>0,SUM(H21:H23),SUM(H25:H28)) -> -125810 | I7: =IF(SUM(I21:I23)<>0,SUM(I21:I23),SUM(I25:I28)) -> -106372 | ... P7: =IF(SUM(P21:P23)<>0,SUM(P21:P23),SUM(P25:P28)) -> -53093 | R7: =IF(SUM(R21:R23)<>0,SUM(R21:R23),SUM(R25:R28)) -> 0 | S7: =IF(SUM(S21:S23)<>0,SUM(S21:S23),SUM(S25:S28)) -> 1307.9549 | T7: =IF(SUM(T21:T23)<>0,SUM(T21:T23),SUM(T25:T28)) -> 1455.6144 | U7: =IF(SUM(U21:U23)<>0,SUM(U21:U23),SUM(U25:U28)) -> 1543.7699 | V7: =IF(SUM(V21:V23)<>0,SUM(V21:V23),SUM(V25:V28)) -> 1678.5271 | W7: =IF(SUM(W21:W23)<>0,SUM(W21:W23),SUM(W25:W28)) -> 1382.1055 | X7: =IF(SUM(X21:X23)<>0,SUM(X21:X23),SUM(X25:X28)) -> 1227.2319 | Y7: =IF(SUM(Y21:Y23)<>0,SUM(Y21:Y23),SUM(Y25:Y28)) -> 950.36557 | ... AF7: =IF(SUM(AF21:AF23)<>0,SUM(AF21:AF23),SUM(AF25:AF28)) -> 0 | AH7: =B7+R7 -> -183925 | AI7: =C7+S7 -> -214085.05 | AJ7: =D7+T7 -> -193437.39 | AK7: =E7+U7 -> -177878.23 | AL7: =F7+V7 -> -166747.47 | AM7: =G7+W7 -> -152515.89 | AN7: =H7+X7 -> -124582.77 | AO7: =I7+Y7 -> -105421.63 | ... AV7: =P7+AF7 -> -53093
A8: Operating profit | B8: =SUM(B6:B7) -> 3106 | C8: =SUM(C6:C7) -> 17362 | D8: =SUM(D6:D7) -> 15507 | E8: =SUM(E6:E7) -> 20582 | F8: =SUM(F6:F7) -> 23841 | G8: =SUM(G6:G7) -> 26963 | H8: =SUM(H6:H7) -> 25609 | I8: =SUM(I6:I7) -> 22190 | ... P8: =SUM(P6:P7) -> 15307 | R8: =SUM(R6:R7) -> 0 | S8: =SUM(S6:S7) -> 1307.9549 | T8: =SUM(T6:T7) -> 1455.6144 | U8: =SUM(U6:U7) -> 1543.7699 | V8: =SUM(V6:V7) -> 1678.5271 | W8: =SUM(W6:W7) -> 1382.1055 | X8: =SUM(X6:X7) -> 1227.2319 | Y8: =SUM(Y6:Y7) -> 950.36557 | ... AF8: =SUM(AF6:AF7) -> 0 | AH8: =B8+R8 -> 3106 | AI8: =C8+S8 -> 18669.955 | AJ8: =D8+T8 -> 16962.614 | AK8: =E8+U8 -> 22125.77 | AL8: =F8+V8 -> 25519.527 | AM8: =G8+W8 -> 28345.106 | AN8: =H8+X8 -> 26836.232 | AO8: =I8+Y8 -> 23140.366 | ... AV8: =P8+AF8 -> 15307
A9: Investment Income | B9: =VLOOKUP($A9,'Standardized Statements'!$A:$Q,B$4,FALSE) -> 0 | C9: =VLOOKUP($A9,'Standardized Statements'!$A:$Q,C$4,FALSE) -> 0 | D9: =VLOOKUP($A9,'Standardized Statements'!$A:$Q,D$4,FALSE) -> 0 | E9: =VLOOKUP($A9,'Standardized Statements'!$A:$Q,E$4,FALSE) -> 0 | F9: =VLOOKUP($A9,'Standardized Statements'!$A:$Q,F$4,FALSE) -> 0 | G9: =VLOOKUP($A9,'Standardized Statements'!$A:$Q,G$4,FALSE) -> 0 | H9: =VLOOKUP($A9,'Standardized Statements'!$A:$Q,H$4,FALSE) -> 0 | I9: =VLOOKUP($A9,'Standardized Statements'!$A:$Q,I$4,FALSE) -> 0 | ... P9: =VLOOKUP($A9,'Standardized Statements'!$A:$Q,P$4,FALSE) -> 0 | AH9: =B9+R9 -> 0 | AI9: =C9+S9 -> 0 | AJ9: =D9+T9 -> 0 | AK9: =E9+U9 -> 0 | AL9: =F9+V9 -> 0 | AM9: =G9+W9 -> 0 | AN9: =H9+X9 -> 0 | AO9: =I9+Y9 -> 0 | ... AV9: =P9+AF9 -> 0
A10: Net non-recurring income or expense | B10: =VLOOKUP($A10,'Standardized Statements'!$A:$Q,B$4,FALSE) -> 0 | C10: =VLOOKUP($A10,'Standardized Statements'!$A:$Q,C$4,FALSE) -> 0 | D10: =VLOOKUP($A10,'Standardized Statements'!$A:$Q,D$4,FALSE) -> 0 | E10: =VLOOKUP($A10,'Standardized Statements'!$A:$Q,E$4,FALSE) -> 0 | F10: =VLOOKUP($A10,'Standardized Statements'!$A:$Q,F$4,FALSE) -> 0 | G10: =VLOOKUP($A10,'Standardized Statements'!$A:$Q,G$4,FALSE) -> 0 | H10: =VLOOKUP($A10,'Standardized Statements'!$A:$Q,H$4,FALSE) -> 0 | I10: =VLOOKUP($A10,'Standardized Statements'!$A:$Q,I$4,FALSE) -> 0 | ... P10: =VLOOKUP($A10,'Standardized Statements'!$A:$Q,P$4,FALSE) -> 0 | AH10: =B10+R10 -> 0 | AI10: =C10+S10 -> 0 | AJ10: =D10+T10 -> 0 | AK10: =E10+U10 -> 0 | AL10: =F10+V10 -> 0 | AM10: =G10+W10 -> 0 | AN10: =H10+X10 -> 0 | AO10: =I10+Y10 -> 0 | ... AV10: =P10+AF10 -> 0
A11: Interest income | B11: =VLOOKUP($A11,'Standardized Statements'!$A:$Q,B$4,FALSE) -> 252 | C11: =VLOOKUP($A11,'Standardized Statements'!$A:$Q,C$4,FALSE) -> 376 | D11: =VLOOKUP($A11,'Standardized Statements'!$A:$Q,D$4,FALSE) -> 292 | E11: =VLOOKUP($A11,'Standardized Statements'!$A:$Q,E$4,FALSE) -> 281 | F11: =VLOOKUP($A11,'Standardized Statements'!$A:$Q,F$4,FALSE) -> 224 | G11: =VLOOKUP($A11,'Standardized Statements'!$A:$Q,G$4,FALSE) -> 310 | H11: =VLOOKUP($A11,'Standardized Statements'!$A:$Q,H$4,FALSE) -> 328 | I11: =VLOOKUP($A11,'Standardized Statements'!$A:$Q,I$4,FALSE) -> 367 | ... P11: =VLOOKUP($A11,'Standardized Statements'!$A:$Q,P$4,FALSE) -> 515 | AH11: =B11+R11 -> 252 | AI11: =C11+S11 -> 376 | AJ11: =D11+T11 -> 292 | AK11: =E11+U11 -> 281 | AL11: =F11+V11 -> 224 | AM11: =G11+W11 -> 310 | AN11: =H11+X11 -> 328 | AO11: =I11+Y11 -> 367 | ... AV11: =P11+AF11 -> 515
A12: Interest expense | B12: =VLOOKUP($A12,'Standardized Statements'!$A:$Q,B$4,FALSE) -> -1306 | C12: =VLOOKUP($A12,'Standardized Statements'!$A:$Q,C$4,FALSE) -> -347 | D12: =VLOOKUP($A12,'Standardized Statements'!$A:$Q,D$4,FALSE) -> -160 | E12: =VLOOKUP($A12,'Standardized Statements'!$A:$Q,E$4,FALSE) -> -54 | F12: =VLOOKUP($A12,'Standardized Statements'!$A:$Q,F$4,FALSE) -> -26 | G12: =VLOOKUP($A12,'Standardized Statements'!$A:$Q,G$4,FALSE) -> -31 | H12: =VLOOKUP($A12,'Standardized Statements'!$A:$Q,H$4,FALSE) -> -42 | I12: =VLOOKUP($A12,'Standardized Statements'!$A:$Q,I$4,FALSE) -> -31 | ... P12: =VLOOKUP($A12,'Standardized Statements'!$A:$Q,P$4,FALSE) -> -14 | R12: ='Lease adjustments'!B40 -> 0 | S12: ='Lease adjustments'!C40 -> -1307.9549 | T12: ='Lease adjustments'!D40 -> -1455.6144 | U12: ='Lease adjustments'!E40 -> -1543.7699 | V12: ='Lease adjustments'!F40 -> -1678.5271 | W12: ='Lease adjustments'!G40 -> -1382.1055 | X12: ='Lease adjustments'!H40 -> -1227.2319 | Y12: ='Lease adjustments'!I40 -> -950.36557 | ... AF12: ='Lease adjustments'!P40 -> 0 | AH12: =B12+R12 -> -1306 | AI12: =C12+S12 -> -1654.9549 | AJ12: =D12+T12 -> -1615.6144 | AK12: =E12+U12 -> -1597.7699 | AL12: =F12+V12 -> -1704.5271 | AM12: =G12+W12 -> -1413.1055 | AN12: =H12+X12 -> -1269.2319 | AO12: =I12+Y12 -> -981.36557 | ... AV12: =P12+AF12 -> -14
A13: Profit before taxes | B13: =SUM(B8:B12) -> 2052 | C13: =SUM(C8:C12) -> 17391 | D13: =SUM(D8:D12) -> 15639 | E13: =SUM(E8:E12) -> 20809 | F13: =SUM(F8:F12) -> 24039 | G13: =SUM(G8:G12) -> 27242 | H13: =SUM(H8:H12) -> 25895 | I13: =SUM(I8:I12) -> 22526 | ... P13: =SUM(P8:P12) -> 15808 | R13: =SUM(R8:R12) -> 0 | S13: =SUM(S8:S12) -> 0 | T13: =SUM(T8:T12) -> 0 | U13: =SUM(U8:U12) -> -1.8189894e-12 | V13: =SUM(V8:V12) -> 0 | W13: =SUM(W8:W12) -> 0 | X13: =SUM(X8:X12) -> 0 | Y13: =SUM(Y8:Y12) -> 0 | ... AF13: =SUM(AF8:AF12) -> 0 | AH13: =B13+R13 -> 2052 | AI13: =C13+S13 -> 17391 | AJ13: =D13+T13 -> 15639 | AK13: =E13+U13 -> 20809 | AL13: =F13+V13 -> 24039 | AM13: =G13+W13 -> 27242 | AN13: =H13+X13 -> 25895 | AO13: =I13+Y13 -> 22526 | ... AV13: =P13+AF13 -> 15808
A14: Tax expense | B14: =VLOOKUP($A14,'Standardized Statements'!$A:$Q,B$4,FALSE) -> -809 | C14: =VLOOKUP($A14,'Standardized Statements'!$A:$Q,C$4,FALSE) -> -3948 | D14: =VLOOKUP($A14,'Standardized Statements'!$A:$Q,D$4,FALSE) -> -2987 | E14: =VLOOKUP($A14,'Standardized Statements'!$A:$Q,E$4,FALSE) -> -4625 | F14: =VLOOKUP($A14,'Standardized Statements'!$A:$Q,F$4,FALSE) -> -5403 | G14: =VLOOKUP($A14,'Standardized Statements'!$A:$Q,G$4,FALSE) -> -6344 | H14: =VLOOKUP($A14,'Standardized Statements'!$A:$Q,H$4,FALSE) -> -5919 | I14: =VLOOKUP($A14,'Standardized Statements'!$A:$Q,I$4,FALSE) -> -5374 | ... P14: =VLOOKUP($A14,'Standardized Statements'!$A:$Q,P$4,FALSE) -> -5011 | R14: ='Lease adjustments'!B41 -> 0 | S14: ='Lease adjustments'!C41 -> 0 | T14: ='Lease adjustments'!D41 -> 0 | U14: ='Lease adjustments'!E41 -> 4.0017767e-13 | V14: ='Lease adjustments'!F41 -> 0 | W14: ='Lease adjustments'!G41 -> 0 | X14: ='Lease adjustments'!H41 -> 0 | Y14: ='Lease adjustments'!I41 -> 0 | ... AF14: ='Lease adjustments'!P41 -> 0 | AH14: =B14+R14 -> -809 | AI14: =C14+S14 -> -3948 | AJ14: =D14+T14 -> -2987 | AK14: =E14+U14 -> -4625 | AL14: =F14+V14 -> -5403 | AM14: =G14+W14 -> -6344 | AN14: =H14+X14 -> -5919 | AO14: =I14+Y14 -> -5374 | ... AV14: =P14+AF14 -> -5011
A15: Profit after taxes | B15: =SUM(B13:B14) -> 1243 | C15: =SUM(C13:C14) -> 13443 | D15: =SUM(D13:D14) -> 12652 | E15: =SUM(E13:E14) -> 16184 | F15: =SUM(F13:F14) -> 18636 | G15: =SUM(G13:G14) -> 20898 | H15: =SUM(H13:H14) -> 19976 | I15: =SUM(I13:I14) -> 17152 | ... P15: =SUM(P13:P14) -> 10797 | R15: =SUM(R13:R14) -> 0 | S15: =SUM(S13:S14) -> 0 | T15: =SUM(T13:T14) -> 0 | U15: =SUM(U13:U14) -> -1.4188117e-12 | V15: =SUM(V13:V14) -> 0 | W15: =SUM(W13:W14) -> 0 | X15: =SUM(X13:X14) -> 0 | Y15: =SUM(Y13:Y14) -> 0 | ... AF15: =SUM(AF13:AF14) -> 0 | AH15: =B15+R15 -> 1243 | AI15: =C15+S15 -> 13443 | AJ15: =D15+T15 -> 12652 | AK15: =E15+U15 -> 16184 | AL15: =F15+V15 -> 18636 | AM15: =G15+W15 -> 20898 | AN15: =H15+X15 -> 19976 | AO15: =I15+Y15 -> 17152 | ... AV15: =P15+AF15 -> 10797
A16: Profit/loss to non-controlling interest | B16: =VLOOKUP($A16,'Standardized Statements'!$A:$Q,B$4,FALSE) -> 0 | C16: =VLOOKUP($A16,'Standardized Statements'!$A:$Q,C$4,FALSE) -> 0 | D16: =VLOOKUP($A16,'Standardized Statements'!$A:$Q,D$4,FALSE) -> 0 | E16: =VLOOKUP($A16,'Standardized Statements'!$A:$Q,E$4,FALSE) -> 0 | F16: =VLOOKUP($A16,'Standardized Statements'!$A:$Q,F$4,FALSE) -> 0 | G16: =VLOOKUP($A16,'Standardized Statements'!$A:$Q,G$4,FALSE) -> 0 | H16: =VLOOKUP($A16,'Standardized Statements'!$A:$Q,H$4,FALSE) -> 0 | I16: =VLOOKUP($A16,'Standardized Statements'!$A:$Q,I$4,FALSE) -> 0 | ... P16: =VLOOKUP($A16,'Standardized Statements'!$A:$Q,P$4,FALSE) -> 0 | AH16: =B16+R16 -> 0 | AI16: =C16+S16 -> 0 | AJ16: =D16+T16 -> 0 | AK16: =E16+U16 -> 0 | AL16: =F16+V16 -> 0 | AM16: =G16+W16 -> 0 | AN16: =H16+X16 -> 0 | AO16: =I16+Y16 -> 0 | ... AV16: =P16+AF16 -> 0
A17: Profit/loss to ordinary shareholders | B17: =SUM(B15:B16) -> 1243 | C17: =SUM(C15:C16) -> 13443 | D17: =SUM(D15:D16) -> 12652 | E17: =SUM(E15:E16) -> 16184 | F17: =SUM(F15:F16) -> 18636 | G17: =SUM(G15:G16) -> 20898 | H17: =SUM(H15:H16) -> 19976 | I17: =SUM(I15:I16) -> 17152 | ... P17: =SUM(P15:P16) -> 10797 | R17: =SUM(R15:R16) -> 0 | S17: =SUM(S15:S16) -> 0 | T17: =SUM(T15:T16) -> 0 | U17: =SUM(U15:U16) -> -1.4188117e-12 | V17: =SUM(V15:V16) -> 0 | W17: =SUM(W15:W16) -> 0 | X17: =SUM(X15:X16) -> 0 | Y17: =SUM(Y15:Y16) -> 0 | ... AF17: =SUM(AF15:AF16) -> 0 | AH17: =B17+R17 -> 1243 | AI17: =C17+S17 -> 13443 | AJ17: =D17+T17 -> 12652 | AK17: =E17+U17 -> 16184 | AL17: =F17+V17 -> 18636 | AM17: =G17+W17 -> 20898 | AN17: =H17+X17 -> 19976 | AO17: =I17+Y17 -> 17152 | ... AV17: =P17+AF17 -> 10797
A19: OPERATING EXPENSES | B19: 2020 | C19: 2019 | D19: 2018 | E19: 2017 | F19: 2016 | G19: 2015 | H19: 2014 | I19: 2013 | J19: 2012 | K19: 2011 | L19: 2010 | M19: 2009 | N19: 2008 | O19: 2007 | P19: 2006 | AH19: 2020 | AI19: 2019 | AJ19: 2018 | AK19: 2017 | AL19: 2016 | AM19: 2015 | AN19: 2014 | AO19: 2013 | AP19: 2012 | AQ19: 2011 | AR19: 2010 | AS19: 2009 | AT19: 2008 | AU19: 2007 | AV19: 2006
A20: Classification by function:
A21: Cost of Sales (by function) | B21: =VLOOKUP($A21,'Standardized Statements'!$A:$Q,B$4,FALSE) -> -93487 | C21: =VLOOKUP($A21,'Standardized Statements'!$A:$Q,C$4,FALSE) -> -110302 | D21: =VLOOKUP($A21,'Standardized Statements'!$A:$Q,D$4,FALSE) -> -99513 | E21: =VLOOKUP($A21,'Standardized Statements'!$A:$Q,E$4,FALSE) -> -91914 | F21: =VLOOKUP($A21,'Standardized Statements'!$A:$Q,F$4,FALSE) -> -86090 | G21: =VLOOKUP($A21,'Standardized Statements'!$A:$Q,G$4,FALSE) -> -77694 | H21: =VLOOKUP($A21,'Standardized Statements'!$A:$Q,H$4,FALSE) -> -62367 | I21: =VLOOKUP($A21,'Standardized Statements'!$A:$Q,I$4,FALSE) -> -52529 | ... P21: =VLOOKUP($A21,'Standardized Statements'!$A:$Q,P$4,FALSE) -> -27736 | AH21: =B21+R21 -> -93487 | AI21: =C21+S21 -> -110302 | AJ21: =D21+T21 -> -99513 | AK21: =E21+U21 -> -91914 | AL21: =F21+V21 -> -86090 | AM21: =G21+W21 -> -77694 | AN21: =H21+X21 -> -62367 | AO21: =I21+Y21 -> -52529 | ... AV21: =P21+AF21 -> -27736
A22: SG&A (by function) | B22: =VLOOKUP($A22,'Standardized Statements'!$A:$Q,B$4,FALSE) -> -90438 | C22: =VLOOKUP($A22,'Standardized Statements'!$A:$Q,C$4,FALSE) -> -105091 | D22: =VLOOKUP($A22,'Standardized Statements'!$A:$Q,D$4,FALSE) -> -95380 | E22: =VLOOKUP($A22,'Standardized Statements'!$A:$Q,E$4,FALSE) -> -87508 | F22: =VLOOKUP($A22,'Standardized Statements'!$A:$Q,F$4,FALSE) -> -82336 | G22: =VLOOKUP($A22,'Standardized Statements'!$A:$Q,G$4,FALSE) -> -76204 | H22: =VLOOKUP($A22,'Standardized Statements'!$A:$Q,H$4,FALSE) -> -63443 | I22: =VLOOKUP($A22,'Standardized Statements'!$A:$Q,I$4,FALSE) -> -53843 | ... P22: =VLOOKUP($A22,'Standardized Statements'!$A:$Q,P$4,FALSE) -> -25357 | R22: =SUM(R27:R28) -> 0 | S22: =SUM(S27:S28) -> 1307.9549 | T22: =SUM(T27:T28) -> 1455.6144 | U22: =SUM(U27:U28) -> 1543.7699 | V22: =SUM(V27:V28) -> 1678.5271 | W22: =SUM(W27:W28) -> 1382.1055 | X22: =SUM(X27:X28) -> 1227.2319 | Y22: =SUM(Y27:Y28) -> 950.36557 | ... AF22: =SUM(AF27:AF28) -> 0 | AH22: =B22+R22 -> -90438 | AI22: =C22+S22 -> -103783.05 | AJ22: =D22+T22 -> -93924.386 | AK22: =E22+U22 -> -85964.23 | AL22: =F22+V22 -> -80657.473 | AM22: =G22+W22 -> -74821.894 | AN22: =H22+X22 -> -62215.768 | AO22: =I22+Y22 -> -52892.634 | ... AV22: =P22+AF22 -> -25357
A23: Other Operating Income, Net of Other Operating Expense (by function) | B23: =VLOOKUP($A23,'Standardized Statements'!$A:$Q,B$4,FALSE) -> 0 | C23: =VLOOKUP($A23,'Standardized Statements'!$A:$Q,C$4,FALSE) -> 0 | D23: =VLOOKUP($A23,'Standardized Statements'!$A:$Q,D$4,FALSE) -> 0 | E23: =VLOOKUP($A23,'Standardized Statements'!$A:$Q,E$4,FALSE) -> 0 | F23: =VLOOKUP($A23,'Standardized Statements'!$A:$Q,F$4,FALSE) -> 0 | G23: =VLOOKUP($A23,'Standardized Statements'!$A:$Q,G$4,FALSE) -> 0 | H23: =VLOOKUP($A23,'Standardized Statements'!$A:$Q,H$4,FALSE) -> 0 | I23: =VLOOKUP($A23,'Standardized Statements'!$A:$Q,I$4,FALSE) -> 0 | ... P23: =VLOOKUP($A23,'Standardized Statements'!$A:$Q,P$4,FALSE) -> 0 | AH23: =B23+R23 -> 0 | AI23: =C23+S23 -> 0 | AJ23: =D23+T23 -> 0 | AK23: =E23+U23 -> 0 | AL23: =F23+V23 -> 0 | AM23: =G23+W23 -> 0 | AN23: =H23+X23 -> 0 | AO23: =I23+Y23 -> 0 | ... AV23: =P23+AF23 -> 0
A24: Classification by nature:
A25: Cost of Materials (by nature) | B25: =IF(VLOOKUP($A25,'Standardized Statements'!$A:$Q,B$4,FALSE)=0,B$21,VLOOKUP($A25,'Standardized Statements'!$A:$Q,B$4,FALSE)) -> -91538 | C25: =IF(VLOOKUP($A25,'Standardized Statements'!$A:$Q,C$4,FALSE)=0,C$21,VLOOKUP($A25,'Standardized Statements'!$A:$Q,C$4,FALSE)) -> -109732 | D25: =IF(VLOOKUP($A25,'Standardized Statements'!$A:$Q,D$4,FALSE)=0,D$21,VLOOKUP($A25,'Standardized Statements'!$A:$Q,D$4,FALSE)) -> -98955 | E25: =IF(VLOOKUP($A25,'Standardized Statements'!$A:$Q,E$4,FALSE)=0,E$21,VLOOKUP($A25,'Standardized Statements'!$A:$Q,E$4,FALSE)) -> -91178 | F25: =IF(VLOOKUP($A25,'Standardized Statements'!$A:$Q,F$4,FALSE)=0,F$21,VLOOKUP($A25,'Standardized Statements'!$A:$Q,F$4,FALSE)) -> -85243 | G25: =IF(VLOOKUP($A25,'Standardized Statements'!$A:$Q,G$4,FALSE)=0,G$21,VLOOKUP($A25,'Standardized Statements'!$A:$Q,G$4,FALSE)) -> -76969 | H25: =IF(VLOOKUP($A25,'Standardized Statements'!$A:$Q,H$4,FALSE)=0,H$21,VLOOKUP($A25,'Standardized Statements'!$A:$Q,H$4,FALSE)) -> -61799 | I25: =IF(VLOOKUP($A25,'Standardized Statements'!$A:$Q,I$4,FALSE)=0,I$21,VLOOKUP($A25,'Standardized Statements'!$A:$Q,I$4,FALSE)) -> -52059 | ... P25: =IF(VLOOKUP($A25,'Standardized Statements'!$A:$Q,P$4,FALSE)=0,P$21,VLOOKUP($A25,'Standardized Statements'!$A:$Q,P$4,FALSE)) -> -27564 | AH25: =B25+R25 -> -91538 | AI25: =C25+S25 -> -109732 | AJ25: =D25+T25 -> -98955 | AK25: =E25+U25 -> -91178 | AL25: =F25+V25 -> -85243 | AM25: =G25+W25 -> -76969 | AN25: =H25+X25 -> -61799 | AO25: =I25+Y25 -> -52059 | ... AV25: =P25+AF25 -> -27564
A26: Personnel Expenses (by nature) | B26: =VLOOKUP($A26,'Standardized Statements'!$A:$Q,B$4,FALSE) -> -36952 | C26: =VLOOKUP($A26,'Standardized Statements'!$A:$Q,C$4,FALSE) -> -42385 | D26: =VLOOKUP($A26,'Standardized Statements'!$A:$Q,D$4,FALSE) -> -38543 | E26: =VLOOKUP($A26,'Standardized Statements'!$A:$Q,E$4,FALSE) -> -35634 | F26: =VLOOKUP($A26,'Standardized Statements'!$A:$Q,F$4,FALSE) -> -32561 | G26: =VLOOKUP($A26,'Standardized Statements'!$A:$Q,G$4,FALSE) -> -29952 | H26: =VLOOKUP($A26,'Standardized Statements'!$A:$Q,H$4,FALSE) -> -25048 | I26: =VLOOKUP($A26,'Standardized Statements'!$A:$Q,I$4,FALSE) -> -21423 | ... P26: =VLOOKUP($A26,'Standardized Statements'!$A:$Q,P$4,FALSE) -> -10991 | AH26: =B26+R26 -> -36952 | AI26: =C26+S26 -> -42385 | AJ26: =D26+T26 -> -38543 | AK26: =E26+U26 -> -35634 | AL26: =F26+V26 -> -32561 | AM26: =G26+W26 -> -29952 | AN26: =H26+X26 -> -25048 | AO26: =I26+Y26 -> -21423 | ... AV26: =P26+AF26 -> -10991
A27: Depreciation and Amortization (by nature) | B27: =VLOOKUP($A27,'Standardized Statements'!$A:$Q,B$4,FALSE) -> -25953 | C27: =VLOOKUP($A27,'Standardized Statements'!$A:$Q,C$4,FALSE) -> -11051 | D27: =VLOOKUP($A27,'Standardized Statements'!$A:$Q,D$4,FALSE) -> -9671 | E27: =VLOOKUP($A27,'Standardized Statements'!$A:$Q,E$4,FALSE) -> -8488 | F27: =VLOOKUP($A27,'Standardized Statements'!$A:$Q,F$4,FALSE) -> -7605 | G27: =VLOOKUP($A27,'Standardized Statements'!$A:$Q,G$4,FALSE) -> -6399 | H27: =VLOOKUP($A27,'Standardized Statements'!$A:$Q,H$4,FALSE) -> -5045 | I27: =VLOOKUP($A27,'Standardized Statements'!$A:$Q,I$4,FALSE) -> -4191 | ... P27: =VLOOKUP($A27,'Standardized Statements'!$A:$Q,P$4,FALSE) -> -1624 | R27: ='Lease adjustments'!B39 -> 0 | S27: ='Lease adjustments'!C39 -> -19814.045 | T27: ='Lease adjustments'!D39 -> -18917.386 | U27: ='Lease adjustments'!E39 -> -17582.23 | V27: ='Lease adjustments'!F39 -> -18875.473 | W27: ='Lease adjustments'!G39 -> -19171.894 | X27: ='Lease adjustments'!H39 -> -15948.768 | Y27: ='Lease adjustments'!I39 -> -14093.634 | ... AF27: ='Lease adjustments'!P39 -> 0 | AH27: =B27+R27 -> -25953 | AI27: =C27+S27 -> -30865.045 | AJ27: =D27+T27 -> -28588.386 | AK27: =E27+U27 -> -26070.23 | AL27: =F27+V27 -> -26480.473 | AM27: =G27+W27 -> -25570.894 | AN27: =H27+X27 -> -20993.768 | AO27: =I27+Y27 -> -18284.634 | ... AV27: =P27+AF27 -> -1624
A28: Other Operating Income, Net of Other Operating Expense (by nature) | B28: =IF(SUM(B21:B23)<>0,SUM(B21:B23)-SUM(B25:B27),VLOOKUP($A28,'Standardized Statements'!$A:$Q,B$4,FALSE)) -> -29482 | C28: =IF(SUM(C21:C23)<>0,SUM(C21:C23)-SUM(C25:C27),VLOOKUP($A28,'Standardized Statements'!$A:$Q,C$4,FALSE)) -> -52225 | D28: =IF(SUM(D21:D23)<>0,SUM(D21:D23)-SUM(D25:D27),VLOOKUP($A28,'Standardized Statements'!$A:$Q,D$4,FALSE)) -> -47724 | E28: =IF(SUM(E21:E23)<>0,SUM(E21:E23)-SUM(E25:E27),VLOOKUP($A28,'Standardized Statements'!$A:$Q,E$4,FALSE)) -> -44122 | F28: =IF(SUM(F21:F23)<>0,SUM(F21:F23)-SUM(F25:F27),VLOOKUP($A28,'Standardized Statements'!$A:$Q,F$4,FALSE)) -> -43017 | G28: =IF(SUM(G21:G23)<>0,SUM(G21:G23)-SUM(G25:G27),VLOOKUP($A28,'Standardized Statements'!$A:$Q,G$4,FALSE)) -> -40578 | H28: =IF(SUM(H21:H23)<>0,SUM(H21:H23)-SUM(H25:H27),VLOOKUP($A28,'Standardized Statements'!$A:$Q,H$4,FALSE)) -> -33918 | I28: =IF(SUM(I21:I23)<>0,SUM(I21:I23)-SUM(I25:I27),VLOOKUP($A28,'Standardized Statements'!$A:$Q,I$4,FALSE)) -> -28699 | ... P28: =IF(SUM(P21:P23)<>0,SUM(P21:P23)-SUM(P25:P27),VLOOKUP($A28,'Standardized Statements'!$A:$Q,P$4,FALSE)) -> -12914 | R28: ='Lease adjustments'!B38 -> 0 | S28: ='Lease adjustments'!C38 -> 21122 | T28: ='Lease adjustments'!D38 -> 20373 | U28: ='Lease adjustments'!E38 -> 19126 | V28: ='Lease adjustments'!F38 -> 20554 | W28: ='Lease adjustments'!G38 -> 20554 | X28: ='Lease adjustments'!H38 -> 17176 | Y28: ='Lease adjustments'!I38 -> 15044 | ... AF28: ='Lease adjustments'!P38 -> 0 | AH28: =B28+R28 -> -29482 | AI28: =C28+S28 -> -31103 | AJ28: =D28+T28 -> -27351 | AK28: =E28+U28 -> -24996 | AL28: =F28+V28 -> -22463 | AM28: =G28+W28 -> -20024 | AN28: =H28+X28 -> -16742 | AO28: =I28+Y28 -> -13655 | ... AV28: =P28+AF28 -> -12914
A30: BALANCE SHEET | B30: 2020 | C30: 2019 | D30: 2018 | E30: 2017 | F30: 2016 | G30: 2015 | H30: 2014 | I30: 2013 | J30: 2012 | K30: 2011 | L30: 2010 | M30: 2009 | N30: 2008 | O30: 2007 | P30: 2006 | AH30: 2020 | AI30: 2019 | AJ30: 2018 | AK30: 2017 | AL30: 2016 | AM30: 2015 | AN30: 2014 | AO30: 2013 | AP30: 2012 | AQ30: 2011 | AR30: 2010 | AS30: 2009 | AT30: 2008 | AU30: 2007 | AV30: 2006
A31: ASSETS
A32: Non-Current Tangible Assets | B32: =VLOOKUP($A32,'Standardized Statements'!$A:$Q,B$4,FALSE) -> 91365 | C32: =VLOOKUP($A32,'Standardized Statements'!$A:$Q,C$4,FALSE) -> 41303 | D32: =VLOOKUP($A32,'Standardized Statements'!$A:$Q,D$4,FALSE) -> 42947 | E32: =VLOOKUP($A32,'Standardized Statements'!$A:$Q,E$4,FALSE) -> 40410 | F32: =VLOOKUP($A32,'Standardized Statements'!$A:$Q,F$4,FALSE) -> 39323 | G32: =VLOOKUP($A32,'Standardized Statements'!$A:$Q,G$4,FALSE) -> 33622 | H32: =VLOOKUP($A32,'Standardized Statements'!$A:$Q,H$4,FALSE) -> 27457 | I32: =VLOOKUP($A32,'Standardized Statements'!$A:$Q,I$4,FALSE) -> 22777 | ... P32: =VLOOKUP($A32,'Standardized Statements'!$A:$Q,P$4,FALSE) -> 7776 | R32: ='Lease adjustments'!B32 -> 0 | S32: ='Lease adjustments'!C32 -> 65962.78 | T32: ='Lease adjustments'!D32 -> 65397.744 | U32: ='Lease adjustments'!E32 -> 72780.718 | V32: ='Lease adjustments'!F32 -> 75305.85 | W32: ='Lease adjustments'!G32 -> 78071.029 | X32: ='Lease adjustments'!H32 -> 72742.396 | Y32: ='Lease adjustments'!I32 -> 58439.615 | ... AF32: ='Lease adjustments'!P32 -> 29775.325 | AH32: =B32+R32 -> 91365 | AI32: =C32+S32 -> 107265.78 | AJ32: =D32+T32 -> 108344.74 | AK32: =E32+U32 -> 113190.72 | AL32: =F32+V32 -> 114628.85 | AM32: =G32+W32 -> 111693.03 | AN32: =H32+X32 -> 100199.4 | AO32: =I32+Y32 -> 81216.615 | ... AV32: =P32+AF32 -> 37551.325
A33: Non-Current Intangible Assets | B33: =VLOOKUP($A33,'Standardized Statements'!$A:$Q,B$4,FALSE) -> 10241 | C33: =VLOOKUP($A33,'Standardized Statements'!$A:$Q,C$4,FALSE) -> 11037 | D33: =VLOOKUP($A33,'Standardized Statements'!$A:$Q,D$4,FALSE) -> 9110 | E33: =VLOOKUP($A33,'Standardized Statements'!$A:$Q,E$4,FALSE) -> 6451 | F33: =VLOOKUP($A33,'Standardized Statements'!$A:$Q,F$4,FALSE) -> 4717 | G33: =VLOOKUP($A33,'Standardized Statements'!$A:$Q,G$4,FALSE) -> 3455 | H33: =VLOOKUP($A33,'Standardized Statements'!$A:$Q,H$4,FALSE) -> 2453 | I33: =VLOOKUP($A33,'Standardized Statements'!$A:$Q,I$4,FALSE) -> 1685 | ... P33: =VLOOKUP($A33,'Standardized Statements'!$A:$Q,P$4,FALSE) -> 0 | AH33: =B33+R33 -> 10241 | AI33: =C33+S33 -> 11037 | AJ33: =D33+T33 -> 9110 | AK33: =E33+U33 -> 6451 | AL33: =F33+V33 -> 4717 | AM33: =G33+W33 -> 3455 | AN33: =H33+X33 -> 2453 | AO33: =I33+Y33 -> 1685 | ... AV33: =P33+AF33 -> 0
A34: Minority Equity Investments | B34: =VLOOKUP($A34,'Standardized Statements'!$A:$Q,B$4,FALSE) -> 247 | C34: =VLOOKUP($A34,'Standardized Statements'!$A:$Q,C$4,FALSE) -> 210 | D34: =VLOOKUP($A34,'Standardized Statements'!$A:$Q,D$4,FALSE) -> 126 | E34: =VLOOKUP($A34,'Standardized Statements'!$A:$Q,E$4,FALSE) -> 0 | F34: =VLOOKUP($A34,'Standardized Statements'!$A:$Q,F$4,FALSE) -> 0 | G34: =VLOOKUP($A34,'Standardized Statements'!$A:$Q,G$4,FALSE) -> 0 | H34: =VLOOKUP($A34,'Standardized Statements'!$A:$Q,H$4,FALSE) -> 0 | I34: =VLOOKUP($A34,'Standardized Statements'!$A:$Q,I$4,FALSE) -> 0 | ... P34: =VLOOKUP($A34,'Standardized Statements'!$A:$Q,P$4,FALSE) -> 0 | AH34: =B34+R34 -> 247 | AI34: =C34+S34 -> 210 | AJ34: =D34+T34 -> 126 | AK34: =E34+U34 -> 0 | AL34: =F34+V34 -> 0 | AM34: =G34+W34 -> 0 | AN34: =H34+X34 -> 0 | AO34: =I34+Y34 -> 0 | ... AV34: =P34+AF34 -> 0
A35: Other Non-Operating Investments | B35: =VLOOKUP($A35,'Standardized Statements'!$A:$Q,B$4,FALSE) -> 1446 | C35: =VLOOKUP($A35,'Standardized Statements'!$A:$Q,C$4,FALSE) -> 1341 | D35: =VLOOKUP($A35,'Standardized Statements'!$A:$Q,D$4,FALSE) -> 1237 | E35: =VLOOKUP($A35,'Standardized Statements'!$A:$Q,E$4,FALSE) -> 1039 | F35: =VLOOKUP($A35,'Standardized Statements'!$A:$Q,F$4,FALSE) -> 1014 | G35: =VLOOKUP($A35,'Standardized Statements'!$A:$Q,G$4,FALSE) -> 862 | H35: =VLOOKUP($A35,'Standardized Statements'!$A:$Q,H$4,FALSE) -> 709 | I35: =VLOOKUP($A35,'Standardized Statements'!$A:$Q,I$4,FALSE) -> 659 | ... P35: =VLOOKUP($A35,'Standardized Statements'!$A:$Q,P$4,FALSE) -> 155 | AH35: =B35+R35 -> 1446 | AI35: =C35+S35 -> 1341 | AJ35: =D35+T35 -> 1237 | AK35: =E35+U35 -> 1039 | AL35: =F35+V35 -> 1014 | AM35: =G35+W35 -> 862 | AN35: =H35+X35 -> 709 | AO35: =I35+Y35 -> 659 | ... AV35: =P35+AF35 -> 155
A36: Deferred Tax Asset | B36: =VLOOKUP($A36,'Standardized Statements'!$A:$Q,B$4,FALSE) -> 5714 | C36: =VLOOKUP($A36,'Standardized Statements'!$A:$Q,C$4,FALSE) -> 4322 | D36: =VLOOKUP($A36,'Standardized Statements'!$A:$Q,D$4,FALSE) -> 3794 | E36: =VLOOKUP($A36,'Standardized Statements'!$A:$Q,E$4,FALSE) -> 2916 | F36: =VLOOKUP($A36,'Standardized Statements'!$A:$Q,F$4,FALSE) -> 2862 | G36: =VLOOKUP($A36,'Standardized Statements'!$A:$Q,G$4,FALSE) -> 2338 | H36: =VLOOKUP($A36,'Standardized Statements'!$A:$Q,H$4,FALSE) -> 2237 | I36: =VLOOKUP($A36,'Standardized Statements'!$A:$Q,I$4,FALSE) -> 1367 | ... P36: =VLOOKUP($A36,'Standardized Statements'!$A:$Q,P$4,FALSE) -> 102 | R36: =(-'Lease adjustments'!B35)+R58 -> 0 | S36: =(-'Lease adjustments'!C35)+S58 -> 0 | T36: =(-'Lease adjustments'!D35)+T58 -> 0 | U36: =(-'Lease adjustments'!E35)+U58 -> 0 | V36: =(-'Lease adjustments'!F35)+V58 -> 0 | W36: =(-'Lease adjustments'!G35)+W58 -> 0 | X36: =(-'Lease adjustments'!H35)+X58 -> 0 | Y36: =(-'Lease adjustments'!I35)+Y58 -> 0 | ... AF36: =(-'Lease adjustments'!P35)+AF58 -> -650 | AH36: =B36+R36 -> 5714 | AI36: =C36+S36 -> 4322 | AJ36: =D36+T36 -> 3794 | AK36: =E36+U36 -> 2916 | AL36: =F36+V36 -> 2862 | AM36: =G36+W36 -> 2338 | AN36: =H36+X36 -> 2237 | AO36: =I36+Y36 -> 1367 | ... AV36: =P36+AF36 -> -548
A37: Derivatives - Asset | B37: =VLOOKUP($A37,'Standardized Statements'!$A:$Q,B$4,FALSE) -> 730 | C37: =VLOOKUP($A37,'Standardized Statements'!$A:$Q,C$4,FALSE) -> 661 | D37: =VLOOKUP($A37,'Standardized Statements'!$A:$Q,D$4,FALSE) -> 372 | E37: =VLOOKUP($A37,'Standardized Statements'!$A:$Q,E$4,FALSE) -> 497 | F37: =VLOOKUP($A37,'Standardized Statements'!$A:$Q,F$4,FALSE) -> 848 | G37: =VLOOKUP($A37,'Standardized Statements'!$A:$Q,G$4,FALSE) -> 707 | H37: =VLOOKUP($A37,'Standardized Statements'!$A:$Q,H$4,FALSE) -> 443 | I37: =VLOOKUP($A37,'Standardized Statements'!$A:$Q,I$4,FALSE) -> 186 | ... P37: =VLOOKUP($A37,'Standardized Statements'!$A:$Q,P$4,FALSE) -> 0 | AH37: =B37+R37 -> 730 | AI37: =C37+S37 -> 661 | AJ37: =D37+T37 -> 372 | AK37: =E37+U37 -> 497 | AL37: =F37+V37 -> 848 | AM37: =G37+W37 -> 707 | AN37: =H37+X37 -> 443 | AO37: =I37+Y37 -> 186 | ... AV37: =P37+AF37 -> 0
A38: Total Non-Current Assets | B38: =SUM(B32:B37) -> 109743 | C38: =SUM(C32:C37) -> 58874 | D38: =SUM(D32:D37) -> 57586 | E38: =SUM(E32:E37) -> 51313 | F38: =SUM(F32:F37) -> 48764 | G38: =SUM(G32:G37) -> 40984 | H38: =SUM(H32:H37) -> 33299 | I38: =SUM(I32:I37) -> 26674 | ... P38: =SUM(P32:P37) -> 8033 | R38: =SUM(R32:R37) -> 0 | S38: =SUM(S32:S37) -> 65962.78 | T38: =SUM(T32:T37) -> 65397.744 | U38: =SUM(U32:U37) -> 72780.718 | V38: =SUM(V32:V37) -> 75305.85 | W38: =SUM(W32:W37) -> 78071.029 | X38: =SUM(X32:X37) -> 72742.396 | Y38: =SUM(Y32:Y37) -> 58439.615 | ... AF38: =SUM(AF32:AF37) -> 29125.325 | AH38: =B38+R38 -> 109743 | AI38: =C38+S38 -> 124836.78 | AJ38: =D38+T38 -> 122983.74 | AK38: =E38+U38 -> 124093.72 | AL38: =F38+V38 -> 124069.85 | AM38: =G38+W38 -> 119055.03 | AN38: =H38+X38 -> 106041.4 | AO38: =I38+Y38 -> 85113.615 | ... AV38: =P38+AF38 -> 37158.325
A40: Inventories | B40: =VLOOKUP($A40,'Standardized Statements'!$A:$Q,B$4,FALSE) -> 38209 | C40: =VLOOKUP($A40,'Standardized Statements'!$A:$Q,C$4,FALSE) -> 37823 | D40: =VLOOKUP($A40,'Standardized Statements'!$A:$Q,D$4,FALSE) -> 37721 | E40: =VLOOKUP($A40,'Standardized Statements'!$A:$Q,E$4,FALSE) -> 33712 | F40: =VLOOKUP($A40,'Standardized Statements'!$A:$Q,F$4,FALSE) -> 31732 | G40: =VLOOKUP($A40,'Standardized Statements'!$A:$Q,G$4,FALSE) -> 24833 | H40: =VLOOKUP($A40,'Standardized Statements'!$A:$Q,H$4,FALSE) -> 19403 | I40: =VLOOKUP($A40,'Standardized Statements'!$A:$Q,I$4,FALSE) -> 16695 | ... P40: =VLOOKUP($A40,'Standardized Statements'!$A:$Q,P$4,FALSE) -> 7220 | AH40: =B40+R40 -> 38209 | AI40: =C40+S40 -> 37823 | AJ40: =D40+T40 -> 37721 | AK40: =E40+U40 -> 33712 | AL40: =F40+V40 -> 31732 | AM40: =G40+W40 -> 24833 | AN40: =H40+X40 -> 19403 | AO40: =I40+Y40 -> 16695 | ... AV40: =P40+AF40 -> 7220
A41: Trade Receivables | B41: =VLOOKUP($A41,'Standardized Statements'!$A:$Q,B$4,FALSE) -> 3086 | C41: =VLOOKUP($A41,'Standardized Statements'!$A:$Q,C$4,FALSE) -> 5879 | D41: =VLOOKUP($A41,'Standardized Statements'!$A:$Q,D$4,FALSE) -> 6329 | E41: =VLOOKUP($A41,'Standardized Statements'!$A:$Q,E$4,FALSE) -> 5297 | F41: =VLOOKUP($A41,'Standardized Statements'!$A:$Q,F$4,FALSE) -> 4881 | G41: =VLOOKUP($A41,'Standardized Statements'!$A:$Q,G$4,FALSE) -> 4021 | H41: =VLOOKUP($A41,'Standardized Statements'!$A:$Q,H$4,FALSE) -> 3659 | I41: =VLOOKUP($A41,'Standardized Statements'!$A:$Q,I$4,FALSE) -> 3107 | ... P41: =VLOOKUP($A41,'Standardized Statements'!$A:$Q,P$4,FALSE) -> 865 | AH41: =B41+R41 -> 3086 | AI41: =C41+S41 -> 5879 | AJ41: =D41+T41 -> 6329 | AK41: =E41+U41 -> 5297 | AL41: =F41+V41 -> 4881 | AM41: =G41+W41 -> 4021 | AN41: =H41+X41 -> 3659 | AO41: =I41+Y41 -> 3107 | ... AV41: =P41+AF41 -> 865
A42: Other Current Assets | B42: =VLOOKUP($A42,'Standardized Statements'!$A:$Q,B$4,FALSE) -> 6793 | C42: =VLOOKUP($A42,'Standardized Statements'!$A:$Q,C$4,FALSE) -> 5597 | D42: =VLOOKUP($A42,'Standardized Statements'!$A:$Q,D$4,FALSE) -> 5564 | E42: =VLOOKUP($A42,'Standardized Statements'!$A:$Q,E$4,FALSE) -> 6522 | F42: =VLOOKUP($A42,'Standardized Statements'!$A:$Q,F$4,FALSE) -> 3756 | G42: =VLOOKUP($A42,'Standardized Statements'!$A:$Q,G$4,FALSE) -> 3025 | H42: =VLOOKUP($A42,'Standardized Statements'!$A:$Q,H$4,FALSE) -> 2543 | I42: =VLOOKUP($A42,'Standardized Statements'!$A:$Q,I$4,FALSE) -> 1976 | ... P42: =VLOOKUP($A42,'Standardized Statements'!$A:$Q,P$4,FALSE) -> 812 | AH42: =B42+R42 -> 6793 | AI42: =C42+S42 -> 5597 | AJ42: =D42+T42 -> 5564 | AK42: =E42+U42 -> 6522 | AL42: =F42+V42 -> 3756 | AM42: =G42+W42 -> 3025 | AN42: =H42+X42 -> 2543 | AO42: =I42+Y42 -> 1976 | ... AV42: =P42+AF42 -> 812
A43: Cash and Cash Equivalents | B43: =VLOOKUP($A43,'Standardized Statements'!$A:$Q,B$4,FALSE) -> 16540 | C43: =VLOOKUP($A43,'Standardized Statements'!$A:$Q,C$4,FALSE) -> 12312 | D43: =VLOOKUP($A43,'Standardized Statements'!$A:$Q,D$4,FALSE) -> 11590 | E43: =VLOOKUP($A43,'Standardized Statements'!$A:$Q,E$4,FALSE) -> 9718 | F43: =VLOOKUP($A43,'Standardized Statements'!$A:$Q,F$4,FALSE) -> 9446 | G43: =VLOOKUP($A43,'Standardized Statements'!$A:$Q,G$4,FALSE) -> 12950 | H43: =VLOOKUP($A43,'Standardized Statements'!$A:$Q,H$4,FALSE) -> 16693 | I43: =VLOOKUP($A43,'Standardized Statements'!$A:$Q,I$4,FALSE) -> 17224 | ... P43: =VLOOKUP($A43,'Standardized Statements'!$A:$Q,P$4,FALSE) -> 18625 | AH43: =B43+R43 -> 16540 | AI43: =C43+S43 -> 12312 | AJ43: =D43+T43 -> 11590 | AK43: =E43+U43 -> 9718 | AL43: =F43+V43 -> 9446 | AM43: =G43+W43 -> 12950 | AN43: =H43+X43 -> 16693 | AO43: =I43+Y43 -> 17224 | ... AV43: =P43+AF43 -> 18625
A44: Total Current Assets | B44: =SUM(B40:B43) -> 64628 | C44: =SUM(C40:C43) -> 61611 | D44: =SUM(D40:D43) -> 61204 | E44: =SUM(E40:E43) -> 55249 | F44: =SUM(F40:F43) -> 49815 | G44: =SUM(G40:G43) -> 44829 | H44: =SUM(H40:H43) -> 42298 | I44: =SUM(I40:I43) -> 39002 | ... P44: =SUM(P40:P43) -> 27522 | R44: =SUM(R40:R43) -> 0 | S44: =SUM(S40:S43) -> 0 | T44: =SUM(T40:T43) -> 0 | U44: =SUM(U40:U43) -> 0 | V44: =SUM(V40:V43) -> 0 | W44: =SUM(W40:W43) -> 0 | X44: =SUM(X40:X43) -> 0 | Y44: =SUM(Y40:Y43) -> 0 | ... AF44: =SUM(AF40:AF43) -> 0 | AH44: =B44+R44 -> 64628 | AI44: =C44+S44 -> 61611 | AJ44: =D44+T44 -> 61204 | AK44: =E44+U44 -> 55249 | AL44: =F44+V44 -> 49815 | AM44: =G44+W44 -> 44829 | AN44: =H44+X44 -> 42298 | AO44: =I44+Y44 -> 39002 | ... AV44: =P44+AF44 -> 27522
A46: Assets Held For Sale | B46: =VLOOKUP($A46,'Standardized Statements'!$A:$Q,B$4,FALSE) -> 0 | C46: =VLOOKUP($A46,'Standardized Statements'!$A:$Q,C$4,FALSE) -> 0 | D46: =VLOOKUP($A46,'Standardized Statements'!$A:$Q,D$4,FALSE) -> 0 | E46: =VLOOKUP($A46,'Standardized Statements'!$A:$Q,E$4,FALSE) -> 0 | F46: =VLOOKUP($A46,'Standardized Statements'!$A:$Q,F$4,FALSE) -> 0 | G46: =VLOOKUP($A46,'Standardized Statements'!$A:$Q,G$4,FALSE) -> 0 | H46: =VLOOKUP($A46,'Standardized Statements'!$A:$Q,H$4,FALSE) -> 0 | I46: =VLOOKUP($A46,'Standardized Statements'!$A:$Q,I$4,FALSE) -> 0 | ... P46: =VLOOKUP($A46,'Standardized Statements'!$A:$Q,P$4,FALSE) -> 0 | AH46: =B46+R46 -> 0 | AI46: =C46+S46 -> 0 | AJ46: =D46+T46 -> 0 | AK46: =E46+U46 -> 0 | AL46: =F46+V46 -> 0 | AM46: =G46+W46 -> 0 | AN46: =H46+X46 -> 0 | AO46: =I46+Y46 -> 0 | ... AV46: =P46+AF46 -> 0
A48: Total Assets | B48: =SUM(B38,B44,B46) -> 174371 | C48: =SUM(C38,C44,C46) -> 120485 | D48: =SUM(D38,D44,D46) -> 118790 | E48: =SUM(E38,E44,E46) -> 106562 | F48: =SUM(F38,F44,F46) -> 98579 | G48: =SUM(G38,G44,G46) -> 85813 | H48: =SUM(H38,H44,H46) -> 75597 | I48: =SUM(I38,I44,I46) -> 65676 | ... P48: =SUM(P38,P44,P46) -> 35555 | R48: =SUM(R38,R44,R46) -> 0 | S48: =SUM(S38,S44,S46) -> 65962.78 | T48: =SUM(T38,T44,T46) -> 65397.744 | U48: =SUM(U38,U44,U46) -> 72780.718 | V48: =SUM(V38,V44,V46) -> 75305.85 | W48: =SUM(W38,W44,W46) -> 78071.029 | X48: =SUM(X38,X44,X46) -> 72742.396 | Y48: =SUM(Y38,Y44,Y46) -> 58439.615 | ... AF48: =SUM(AF38,AF44,AF46) -> 29125.325 | AH48: =B48+R48 -> 174371 | AI48: =C48+S48 -> 186447.78 | AJ48: =D48+T48 -> 184187.74 | AK48: =E48+U48 -> 179342.72 | AL48: =F48+V48 -> 173884.85 | AM48: =G48+W48 -> 163884.03 | AN48: =H48+X48 -> 148339.4 | AO48: =I48+Y48 -> 124115.61 | ... AV48: =P48+AF48 -> 64680.325
A50: LIABILITIES AND SHAREHOLDERS' EQUITY
A51: Ordinary Shareholders' Equity | B51: =VLOOKUP($A51,'Standardized Statements'!$A:$Q,B$4,FALSE) -> 54623 | C51: =VLOOKUP($A51,'Standardized Statements'!$A:$Q,C$4,FALSE) -> 57069 | D51: =VLOOKUP($A51,'Standardized Statements'!$A:$Q,D$4,FALSE) -> 58546 | E51: =VLOOKUP($A51,'Standardized Statements'!$A:$Q,E$4,FALSE) -> 59713 | F51: =VLOOKUP($A51,'Standardized Statements'!$A:$Q,F$4,FALSE) -> 61236 | G51: =VLOOKUP($A51,'Standardized Statements'!$A:$Q,G$4,FALSE) -> 58049 | H51: =VLOOKUP($A51,'Standardized Statements'!$A:$Q,H$4,FALSE) -> 51556 | I51: =VLOOKUP($A51,'Standardized Statements'!$A:$Q,I$4,FALSE) -> 45248 | ... P51: =VLOOKUP($A51,'Standardized Statements'!$A:$Q,P$4,FALSE) -> 27779 | R51: ='Lease adjustments'!B36 -> 0 | S51: ='Lease adjustments'!C36 -> 1.5916157e-12 | T51: ='Lease adjustments'!D36 -> 6.8212103e-13 | U51: ='Lease adjustments'!E36 -> -1.4188117e-12 | V51: ='Lease adjustments'!F36 -> -2.2737368e-13 | W51: ='Lease adjustments'!G36 -> 0 | X51: ='Lease adjustments'!H36 -> -2.2737368e-13 | Y51: ='Lease adjustments'!I36 -> 3.4106051e-13 | ... AF51: ='Lease adjustments'!P36 -> 0 | AH51: =B51+R51 -> 54623 | AI51: =C51+S51 -> 57069 | AJ51: =D51+T51 -> 58546 | AK51: =E51+U51 -> 59713 | AL51: =F51+V51 -> 61236 | AM51: =G51+W51 -> 58049 | AN51: =H51+X51 -> 51556 | AO51: =I51+Y51 -> 45248 | ... AV51: =P51+AF51 -> 27779
A53: Non-Controlling Interest in Equity | B53: =VLOOKUP($A53,'Standardized Statements'!$A:$Q,B$4,FALSE) -> 0 | C53: =VLOOKUP($A53,'Standardized Statements'!$A:$Q,C$4,FALSE) -> 0 | D53: =VLOOKUP($A53,'Standardized Statements'!$A:$Q,D$4,FALSE) -> 0 | E53: =VLOOKUP($A53,'Standardized Statements'!$A:$Q,E$4,FALSE) -> 0 | F53: =VLOOKUP($A53,'Standardized Statements'!$A:$Q,F$4,FALSE) -> 0 | G53: =VLOOKUP($A53,'Standardized Statements'!$A:$Q,G$4,FALSE) -> 0 | H53: =VLOOKUP($A53,'Standardized Statements'!$A:$Q,H$4,FALSE) -> 0 | I53: =VLOOKUP($A53,'Standardized Statements'!$A:$Q,I$4,FALSE) -> 0 | ... P53: =VLOOKUP($A53,'Standardized Statements'!$A:$Q,P$4,FALSE) -> 0 | AH53: =B53+R53 -> 0 | AI53: =C53+S53 -> 0 | AJ53: =D53+T53 -> 0 | AK53: =E53+U53 -> 0 | AL53: =F53+V53 -> 0 | AM53: =G53+W53 -> 0 | AN53: =H53+X53 -> 0 | AO53: =I53+Y53 -> 0 | ... AV53: =P53+AF53 -> 0
A55: Preference Shares | B55: =VLOOKUP($A55,'Standardized Statements'!$A:$Q,B$4,FALSE) -> 0 | C55: =VLOOKUP($A55,'Standardized Statements'!$A:$Q,C$4,FALSE) -> 0 | D55: =VLOOKUP($A55,'Standardized Statements'!$A:$Q,D$4,FALSE) -> 0 | E55: =VLOOKUP($A55,'Standardized Statements'!$A:$Q,E$4,FALSE) -> 0 | F55: =VLOOKUP($A55,'Standardized Statements'!$A:$Q,F$4,FALSE) -> 0 | G55: =VLOOKUP($A55,'Standardized Statements'!$A:$Q,G$4,FALSE) -> 0 | H55: =VLOOKUP($A55,'Standardized Statements'!$A:$Q,H$4,FALSE) -> 0 | I55: =VLOOKUP($A55,'Standardized Statements'!$A:$Q,I$4,FALSE) -> 0 | ... P55: =VLOOKUP($A55,'Standardized Statements'!$A:$Q,P$4,FALSE) -> 0 | AH55: =B55+R55 -> 0 | AI55: =C55+S55 -> 0 | AJ55: =D55+T55 -> 0 | AK55: =E55+U55 -> 0 | AL55: =F55+V55 -> 0 | AM55: =G55+W55 -> 0 | AN55: =H55+X55 -> 0 | AO55: =I55+Y55 -> 0 | ... AV55: =P55+AF55 -> 0
A57: Non-Current Debt | B57: =VLOOKUP($A57,'Standardized Statements'!$A:$Q,B$4,FALSE) -> 59503 | C57: =VLOOKUP($A57,'Standardized Statements'!$A:$Q,C$4,FALSE) -> 11157 | D57: =VLOOKUP($A57,'Standardized Statements'!$A:$Q,D$4,FALSE) -> 10937 | E57: =VLOOKUP($A57,'Standardized Statements'!$A:$Q,E$4,FALSE) -> 795 | F57: =VLOOKUP($A57,'Standardized Statements'!$A:$Q,F$4,FALSE) -> 740 | G57: =VLOOKUP($A57,'Standardized Statements'!$A:$Q,G$4,FALSE) -> 449 | H57: =VLOOKUP($A57,'Standardized Statements'!$A:$Q,H$4,FALSE) -> 451 | I57: =VLOOKUP($A57,'Standardized Statements'!$A:$Q,I$4,FALSE) -> 309 | ... P57: =VLOOKUP($A57,'Standardized Statements'!$A:$Q,P$4,FALSE) -> 130 | R57: ='Lease adjustments'!B34 -> 0 | S57: ='Lease adjustments'!C34 -> 51048.036 | T57: ='Lease adjustments'!D34 -> 50471.699 | U57: ='Lease adjustments'!E34 -> 58017.333 | V57: ='Lease adjustments'!F34 -> 60781.619 | W57: ='Lease adjustments'!G34 -> 65123.557 | X57: ='Lease adjustments'!H34 -> 60914.502 | Y57: ='Lease adjustments'!I34 -> 48303.847 | ... AF57: ='Lease adjustments'!P34 -> 24916.439 | AH57: =B57+R57 -> 59503 | AI57: =C57+S57 -> 62205.036 | AJ57: =D57+T57 -> 61408.699 | AK57: =E57+U57 -> 58812.333 | AL57: =F57+V57 -> 61521.619 | AM57: =G57+W57 -> 65572.557 | AN57: =H57+X57 -> 61365.502 | AO57: =I57+Y57 -> 48612.847 | ... AV57: =P57+AF57 -> 25046.439
A58: Deferred Tax Liability | B58: =VLOOKUP($A58,'Standardized Statements'!$A:$Q,B$4,FALSE) -> 3988 | C58: =VLOOKUP($A58,'Standardized Statements'!$A:$Q,C$4,FALSE) -> 4423 | D58: =VLOOKUP($A58,'Standardized Statements'!$A:$Q,D$4,FALSE) -> 5088 | E58: =VLOOKUP($A58,'Standardized Statements'!$A:$Q,E$4,FALSE) -> 5331 | F58: =VLOOKUP($A58,'Standardized Statements'!$A:$Q,F$4,FALSE) -> 4898 | G58: =VLOOKUP($A58,'Standardized Statements'!$A:$Q,G$4,FALSE) -> 4378 | H58: =VLOOKUP($A58,'Standardized Statements'!$A:$Q,H$4,FALSE) -> 3287 | I58: =VLOOKUP($A58,'Standardized Statements'!$A:$Q,I$4,FALSE) -> 2722 | ... P58: =VLOOKUP($A58,'Standardized Statements'!$A:$Q,P$4,FALSE) -> 650 | R58: =MAX(-B58,'Lease adjustments'!B35) -> 0 | S58: =MAX(-C58,'Lease adjustments'!C35) -> 0 | T58: =MAX(-D58,'Lease adjustments'!D35) -> 0 | U58: =MAX(-E58,'Lease adjustments'!E35) -> -4.0017767e-13 | V58: =MAX(-F58,'Lease adjustments'!F35) -> 0 | W58: =MAX(-G58,'Lease adjustments'!G35) -> 0 | X58: =MAX(-H58,'Lease adjustments'!H35) -> 0 | Y58: =MAX(-I58,'Lease adjustments'!I35) -> 0 | ... AF58: =MAX(-P58,'Lease adjustments'!P35) -> -650 | AH58: =B58+R58 -> 3988 | AI58: =C58+S58 -> 4423 | AJ58: =D58+T58 -> 5088 | AK58: =E58+U58 -> 5331 | AL58: =F58+V58 -> 4898 | AM58: =G58+W58 -> 4378 | AN58: =H58+X58 -> 3287 | AO58: =I58+Y58 -> 2722 | ... AV58: =P58+AF58 -> 0
A59: Derivatives - Liability | B59: =VLOOKUP($A59,'Standardized Statements'!$A:$Q,B$4,FALSE) -> 560 | C59: =VLOOKUP($A59,'Standardized Statements'!$A:$Q,C$4,FALSE) -> 479 | D59: =VLOOKUP($A59,'Standardized Statements'!$A:$Q,D$4,FALSE) -> 238 | E59: =VLOOKUP($A59,'Standardized Statements'!$A:$Q,E$4,FALSE) -> 903 | F59: =VLOOKUP($A59,'Standardized Statements'!$A:$Q,F$4,FALSE) -> 1176 | G59: =VLOOKUP($A59,'Standardized Statements'!$A:$Q,G$4,FALSE) -> 302 | H59: =VLOOKUP($A59,'Standardized Statements'!$A:$Q,H$4,FALSE) -> 254 | I59: =VLOOKUP($A59,'Standardized Statements'!$A:$Q,I$4,FALSE) -> 285 | ... P59: =VLOOKUP($A59,'Standardized Statements'!$A:$Q,P$4,FALSE) -> 0 | AH59: =B59+R59 -> 560 | AI59: =C59+S59 -> 479 | AJ59: =D59+T59 -> 238 | AK59: =E59+U59 -> 903 | AL59: =F59+V59 -> 1176 | AM59: =G59+W59 -> 302 | AN59: =H59+X59 -> 254 | AO59: =I59+Y59 -> 285 | ... AV59: =P59+AF59 -> 0
A60: Other Non-Current Liabilities (non interest bearing) | B60: =VLOOKUP($A60,'Standardized Statements'!$A:$Q,B$4,FALSE) -> 0 | C60: =VLOOKUP($A60,'Standardized Statements'!$A:$Q,C$4,FALSE) -> 0 | D60: =VLOOKUP($A60,'Standardized Statements'!$A:$Q,D$4,FALSE) -> 0 | E60: =VLOOKUP($A60,'Standardized Statements'!$A:$Q,E$4,FALSE) -> 0 | F60: =VLOOKUP($A60,'Standardized Statements'!$A:$Q,F$4,FALSE) -> 0 | G60: =VLOOKUP($A60,'Standardized Statements'!$A:$Q,G$4,FALSE) -> 0 | H60: =VLOOKUP($A60,'Standardized Statements'!$A:$Q,H$4,FALSE) -> 0 | I60: =VLOOKUP($A60,'Standardized Statements'!$A:$Q,I$4,FALSE) -> 0 | ... P60: =VLOOKUP($A60,'Standardized Statements'!$A:$Q,P$4,FALSE) -> 0 | AH60: =B60+R60 -> 0 | AI60: =C60+S60 -> 0 | AJ60: =D60+T60 -> 0 | AK60: =E60+U60 -> 0 | AL60: =F60+V60 -> 0 | AM60: =G60+W60 -> 0 | AN60: =H60+X60 -> 0 | AO60: =I60+Y60 -> 0 | ... AV60: =P60+AF60 -> 0
A61: Non-Current Liabilities | B61: =SUM(B57:B60) -> 64051 | C61: =SUM(C57:C60) -> 16059 | D61: =SUM(D57:D60) -> 16263 | E61: =SUM(E57:E60) -> 7029 | F61: =SUM(F57:F60) -> 6814 | G61: =SUM(G57:G60) -> 5129 | H61: =SUM(H57:H60) -> 3992 | I61: =SUM(I57:I60) -> 3316 | ... P61: =SUM(P57:P60) -> 780 | R61: =SUM(R57:R60) -> 0 | S61: =SUM(S57:S60) -> 51048.036 | T61: =SUM(T57:T60) -> 50471.699 | U61: =SUM(U57:U60) -> 58017.333 | V61: =SUM(V57:V60) -> 60781.619 | W61: =SUM(W57:W60) -> 65123.557 | X61: =SUM(X57:X60) -> 60914.502 | Y61: =SUM(Y57:Y60) -> 48303.847 | ... AF61: =SUM(AF57:AF60) -> 24266.439 | AH61: =B61+R61 -> 64051 | AI61: =C61+S61 -> 67107.036 | AJ61: =D61+T61 -> 66734.699 | AK61: =E61+U61 -> 65046.333 | AL61: =F61+V61 -> 67595.619 | AM61: =G61+W61 -> 70252.557 | AN61: =H61+X61 -> 64906.502 | AO61: =I61+Y61 -> 51619.847 | ... AV61: =P61+AF61 -> 25046.439
A63: Trade Payables | B63: =VLOOKUP($A63,'Standardized Statements'!$A:$Q,B$4,FALSE) -> 9511 | C63: =VLOOKUP($A63,'Standardized Statements'!$A:$Q,C$4,FALSE) -> 7838 | D63: =VLOOKUP($A63,'Standardized Statements'!$A:$Q,D$4,FALSE) -> 6800 | E63: =VLOOKUP($A63,'Standardized Statements'!$A:$Q,E$4,FALSE) -> 7215 | F63: =VLOOKUP($A63,'Standardized Statements'!$A:$Q,F$4,FALSE) -> 7262 | G63: =VLOOKUP($A63,'Standardized Statements'!$A:$Q,G$4,FALSE) -> 6000 | H63: =VLOOKUP($A63,'Standardized Statements'!$A:$Q,H$4,FALSE) -> 5520 | I63: =VLOOKUP($A63,'Standardized Statements'!$A:$Q,I$4,FALSE) -> 4870 | ... P63: =VLOOKUP($A63,'Standardized Statements'!$A:$Q,P$4,FALSE) -> 1942 | AH63: =B63+R63 -> 9511 | AI63: =C63+S63 -> 7838 | AJ63: =D63+T63 -> 6800 | AK63: =E63+U63 -> 7215 | AL63: =F63+V63 -> 7262 | AM63: =G63+W63 -> 6000 | AN63: =H63+X63 -> 5520 | AO63: =I63+Y63 -> 4870 | ... AV63: =P63+AF63 -> 1942
A64: Other Current Liabilities | B64: =VLOOKUP($A64,'Standardized Statements'!$A:$Q,B$4,FALSE) -> 25012 | C64: =VLOOKUP($A64,'Standardized Statements'!$A:$Q,C$4,FALSE) -> 32468 | D64: =VLOOKUP($A64,'Standardized Statements'!$A:$Q,D$4,FALSE) -> 27892 | E64: =VLOOKUP($A64,'Standardized Statements'!$A:$Q,E$4,FALSE) -> 22735 | F64: =VLOOKUP($A64,'Standardized Statements'!$A:$Q,F$4,FALSE) -> 21140 | G64: =VLOOKUP($A64,'Standardized Statements'!$A:$Q,G$4,FALSE) -> 16635 | H64: =VLOOKUP($A64,'Standardized Statements'!$A:$Q,H$4,FALSE) -> 14529 | I64: =VLOOKUP($A64,'Standardized Statements'!$A:$Q,I$4,FALSE) -> 12242 | ... P64: =VLOOKUP($A64,'Standardized Statements'!$A:$Q,P$4,FALSE) -> 5054 | AH64: =B64+R64 -> 25012 | AI64: =C64+S64 -> 32468 | AJ64: =D64+T64 -> 27892 | AK64: =E64+U64 -> 22735 | AL64: =F64+V64 -> 21140 | AM64: =G64+W64 -> 16635 | AN64: =H64+X64 -> 14529 | AO64: =I64+Y64 -> 12242 | ... AV64: =P64+AF64 -> 5054
A65: Current Debt | B65: =VLOOKUP($A65,'Standardized Statements'!$A:$Q,B$4,FALSE) -> 21174 | C65: =VLOOKUP($A65,'Standardized Statements'!$A:$Q,C$4,FALSE) -> 7051 | D65: =VLOOKUP($A65,'Standardized Statements'!$A:$Q,D$4,FALSE) -> 9289 | E65: =VLOOKUP($A65,'Standardized Statements'!$A:$Q,E$4,FALSE) -> 9870 | F65: =VLOOKUP($A65,'Standardized Statements'!$A:$Q,F$4,FALSE) -> 2127 | G65: =VLOOKUP($A65,'Standardized Statements'!$A:$Q,G$4,FALSE) -> 0 | H65: =VLOOKUP($A65,'Standardized Statements'!$A:$Q,H$4,FALSE) -> 0 | I65: =VLOOKUP($A65,'Standardized Statements'!$A:$Q,I$4,FALSE) -> 0 | ... P65: =VLOOKUP($A65,'Standardized Statements'!$A:$Q,P$4,FALSE) -> 0 | R65: ='Lease adjustments'!B33 -> 0 | S65: ='Lease adjustments'!C33 -> 14914.744 | T65: ='Lease adjustments'!D33 -> 14926.045 | U65: ='Lease adjustments'!E33 -> 14763.386 | V65: ='Lease adjustments'!F33 -> 14524.23 | W65: ='Lease adjustments'!G33 -> 12947.473 | X65: ='Lease adjustments'!H33 -> 11827.894 | Y65: ='Lease adjustments'!I33 -> 10135.768 | ... AF65: ='Lease adjustments'!P33 -> 4858.8857 | AH65: =B65+R65 -> 21174 | AI65: =C65+S65 -> 21965.744 | AJ65: =D65+T65 -> 24215.045 | AK65: =E65+U65 -> 24633.386 | AL65: =F65+V65 -> 16651.23 | AM65: =G65+W65 -> 12947.473 | AN65: =H65+X65 -> 11827.894 | AO65: =I65+Y65 -> 10135.768 | ... AV65: =P65+AF65 -> 4858.8857
A66: Current Liabilities | B66: =SUM(B63:B65) -> 55697 | C66: =SUM(C63:C65) -> 47357 | D66: =SUM(D63:D65) -> 43981 | E66: =SUM(E63:E65) -> 39820 | F66: =SUM(F63:F65) -> 30529 | G66: =SUM(G63:G65) -> 22635 | H66: =SUM(H63:H65) -> 20049 | I66: =SUM(I63:I65) -> 17112 | ... P66: =SUM(P63:P65) -> 6996 | R66: =SUM(R63:R65) -> 0 | S66: =SUM(S63:S65) -> 14914.744 | T66: =SUM(T63:T65) -> 14926.045 | U66: =SUM(U63:U65) -> 14763.386 | V66: =SUM(V63:V65) -> 14524.23 | W66: =SUM(W63:W65) -> 12947.473 | X66: =SUM(X63:X65) -> 11827.894 | Y66: =SUM(Y63:Y65) -> 10135.768 | ... AF66: =SUM(AF63:AF65) -> 4858.8857 | AH66: =B66+R66 -> 55697 | AI66: =C66+S66 -> 62271.744 | AJ66: =D66+T66 -> 58907.045 | AK66: =E66+U66 -> 54583.386 | AL66: =F66+V66 -> 45053.23 | AM66: =G66+W66 -> 35582.473 | AN66: =H66+X66 -> 31876.894 | AO66: =I66+Y66 -> 27247.768 | ... AV66: =P66+AF66 -> 11854.886
A68: Liabilities Held For Sale | B68: =VLOOKUP($A68,'Standardized Statements'!$A:$Q,B$4,FALSE) -> 0 | C68: =VLOOKUP($A68,'Standardized Statements'!$A:$Q,C$4,FALSE) -> 0 | D68: =VLOOKUP($A68,'Standardized Statements'!$A:$Q,D$4,FALSE) -> 0 | E68: =VLOOKUP($A68,'Standardized Statements'!$A:$Q,E$4,FALSE) -> 0 | F68: =VLOOKUP($A68,'Standardized Statements'!$A:$Q,F$4,FALSE) -> 0 | G68: =VLOOKUP($A68,'Standardized Statements'!$A:$Q,G$4,FALSE) -> 0 | H68: =VLOOKUP($A68,'Standardized Statements'!$A:$Q,H$4,FALSE) -> 0 | I68: =VLOOKUP($A68,'Standardized Statements'!$A:$Q,I$4,FALSE) -> 0 | ... P68: =VLOOKUP($A68,'Standardized Statements'!$A:$Q,P$4,FALSE) -> 0 | AH68: =B68+R68 -> 0 | AI68: =C68+S68 -> 0 | AJ68: =D68+T68 -> 0 | AK68: =E68+U68 -> 0 | AL68: =F68+V68 -> 0 | AM68: =G68+W68 -> 0 | AN68: =H68+X68 -> 0 | AO68: =I68+Y68 -> 0 | ... AV68: =P68+AF68 -> 0
A70: Total Liabilities and Shareholders' Equity | B70: =SUM(B51,B53,B55,B61,B66,B68) -> 174371 | C70: =SUM(C51,C53,C55,C61,C66,C68) -> 120485 | D70: =SUM(D51,D53,D55,D61,D66,D68) -> 118790 | E70: =SUM(E51,E53,E55,E61,E66,E68) -> 106562 | F70: =SUM(F51,F53,F55,F61,F66,F68) -> 98579 | G70: =SUM(G51,G53,G55,G61,G66,G68) -> 85813 | H70: =SUM(H51,H53,H55,H61,H66,H68) -> 75597 | I70: =SUM(I51,I53,I55,I61,I66,I68) -> 65676 | ... P70: =SUM(P51,P53,P55,P61,P66,P68) -> 35555 | R70: =SUM(R51,R53,R55,R61,R66,R68) -> 0 | S70: =SUM(S51,S53,S55,S61,S66,S68) -> 65962.78 | T70: =SUM(T51,T53,T55,T61,T66,T68) -> 65397.744 | U70: =SUM(U51,U53,U55,U61,U66,U68) -> 72780.718 | V70: =SUM(V51,V53,V55,V61,V66,V68) -> 75305.85 | W70: =SUM(W51,W53,W55,W61,W66,W68) -> 78071.029 | X70: =SUM(X51,X53,X55,X61,X66,X68) -> 72742.396 | Y70: =SUM(Y51,Y53,Y55,Y61,Y66,Y68) -> 58439.615 | ... AF70: =SUM(AF51,AF53,AF55,AF61,AF66,AF68) -> 29125.325 | AH70: =B70+R70 -> 174371 | AI70: =C70+S70 -> 186447.78 | AJ70: =D70+T70 -> 184187.74 | AK70: =E70+U70 -> 179342.72 | AL70: =F70+V70 -> 173884.85 | AM70: =G70+W70 -> 163884.03 | AN70: =H70+X70 -> 148339.4 | AO70: =I70+Y70 -> 124115.61 | ... AV70: =P70+AF70 -> 64680.325
A72: CASH FLOW STATEMENT | B72: 2020 | C72: 2019 | D72: 2018 | E72: 2017 | F72: 2016 | G72: 2015 | H72: 2014 | I72: 2013 | J72: 2012 | K72: 2011 | L72: 2010 | M72: 2009 | N72: 2008 | O72: 2007 | P72: 2006 | AH72: 2020 | AI72: 2019 | AJ72: 2018 | AK72: 2017 | AL72: 2016 | AM72: 2015 | AN72: 2014 | AO72: 2013 | AP72: 2012 | AQ72: 2011 | AR72: 2010 | AS72: 2009 | AT72: 2008 | AU72: 2007 | AV72: 2006
A73: Profit Before Interest and Tax | B73: =VLOOKUP($A73,'Standardized Statements'!$A:$Q,B$4,FALSE) -> 3106 | C73: =VLOOKUP($A73,'Standardized Statements'!$A:$Q,C$4,FALSE) -> 17362 | D73: =VLOOKUP($A73,'Standardized Statements'!$A:$Q,D$4,FALSE) -> 15507 | E73: =VLOOKUP($A73,'Standardized Statements'!$A:$Q,E$4,FALSE) -> 20582 | F73: =VLOOKUP($A73,'Standardized Statements'!$A:$Q,F$4,FALSE) -> 23841 | G73: =VLOOKUP($A73,'Standardized Statements'!$A:$Q,G$4,FALSE) -> 26963 | H73: =VLOOKUP($A73,'Standardized Statements'!$A:$Q,H$4,FALSE) -> 25609 | I73: =VLOOKUP($A73,'Standardized Statements'!$A:$Q,I$4,FALSE) -> 22190 | ... P73: =VLOOKUP($A73,'Standardized Statements'!$A:$Q,P$4,FALSE) -> 15307 | R73: =-R12 -> 0 | S73: =-S12 -> 1307.9549 | T73: =-T12 -> 1455.6144 | U73: =-U12 -> 1543.7699 | V73: =-V12 -> 1678.5271 | W73: =-W12 -> 1382.1055 | X73: =-X12 -> 1227.2319 | Y73: =-Y12 -> 950.36557 | ... AF73: =-AF12 -> 0 | AH73: =B73+R73 -> 3106 | AI73: =C73+S73 -> 18669.955 | AJ73: =D73+T73 -> 16962.614 | AK73: =E73+U73 -> 22125.77 | AL73: =F73+V73 -> 25519.527 | AM73: =G73+W73 -> 28345.106 | AN73: =H73+X73 -> 26836.232 | AO73: =I73+Y73 -> 23140.366 | ... AV73: =P73+AF73 -> 15307
A74: Taxes Paid | B74: =VLOOKUP($A74,'Standardized Statements'!$A:$Q,B$4,FALSE)+(1-B104)*(B87/B104) -> -4006.32 | C74: =VLOOKUP($A74,'Standardized Statements'!$A:$Q,C$4,FALSE)+(1-C104)*(C87/C104) -> -3776.34 | D74: =VLOOKUP($A74,'Standardized Statements'!$A:$Q,D$4,FALSE)+(1-D104)*(D87/D104) -> -3133.2 | E74: =VLOOKUP($A74,'Standardized Statements'!$A:$Q,E$4,FALSE)+(1-E104)*(E87/E104) -> -6062.88 | F74: =VLOOKUP($A74,'Standardized Statements'!$A:$Q,F$4,FALSE)+(1-F104)*(F87/F104) -> -4475.72 | G74: =VLOOKUP($A74,'Standardized Statements'!$A:$Q,G$4,FALSE)+(1-G104)*(G87/G104) -> -7028.82 | H74: =VLOOKUP($A74,'Standardized Statements'!$A:$Q,H$4,FALSE)+(1-H104)*(H87/H104) -> -5980.24 | I74: =VLOOKUP($A74,'Standardized Statements'!$A:$Q,I$4,FALSE)+(1-I104)*(I87/I104) -> -3065.82 | ... P74: =VLOOKUP($A74,'Standardized Statements'!$A:$Q,P$4,FALSE)+(1-P104)*(P87/P104) -> -5568.92 | R74: =R12-R87 -> 0 | S74: =S12-S87 -> -287.75007 | T74: =T12-T87 -> -320.23516 | U74: =U12-U87 -> -339.62938 | V74: =V12-V87 -> -369.27597 | W74: =W12-W87 -> -304.06322 | X74: =X12-X87 -> -269.99102 | Y74: =Y12-Y87 -> -209.08042 | ... AF74: =AF12-AF87 -> 0 | AH74: =B74+R74 -> -4006.32 | AI74: =C74+S74 -> -4064.0901 | AJ74: =D74+T74 -> -3453.4352 | AK74: =E74+U74 -> -6402.5094 | AL74: =F74+V74 -> -4844.996 | AM74: =G74+W74 -> -7332.8832 | AN74: =H74+X74 -> -6250.231 | AO74: =I74+Y74 -> -3274.9004 | ... AV74: =P74+AF74 -> -5568.92
A75: Non-Operating Losses (Gains) | B75: =VLOOKUP($A75,'Standardized Statements'!$A:$Q,B$4,FALSE) -> 0 | C75: =VLOOKUP($A75,'Standardized Statements'!$A:$Q,C$4,FALSE) -> 0 | D75: =VLOOKUP($A75,'Standardized Statements'!$A:$Q,D$4,FALSE) -> 0 | E75: =VLOOKUP($A75,'Standardized Statements'!$A:$Q,E$4,FALSE) -> 0 | F75: =VLOOKUP($A75,'Standardized Statements'!$A:$Q,F$4,FALSE) -> 0 | G75: =VLOOKUP($A75,'Standardized Statements'!$A:$Q,G$4,FALSE) -> 0 | H75: =VLOOKUP($A75,'Standardized Statements'!$A:$Q,H$4,FALSE) -> 0 | I75: =VLOOKUP($A75,'Standardized Statements'!$A:$Q,I$4,FALSE) -> 0 | ... P75: =VLOOKUP($A75,'Standardized Statements'!$A:$Q,P$4,FALSE) -> 0 | AH75: =B75+R75 -> 0 | AI75: =C75+S75 -> 0 | AJ75: =D75+T75 -> 0 | AK75: =E75+U75 -> 0 | AL75: =F75+V75 -> 0 | AM75: =G75+W75 -> 0 | AN75: =H75+X75 -> 0 | AO75: =I75+Y75 -> 0 | ... AV75: =P75+AF75 -> 0
A76: Non-Current Operating Accruals | B76: =VLOOKUP($A76,'Standardized Statements'!$A:$Q,B$4,FALSE) -> 25975 | C76: =VLOOKUP($A76,'Standardized Statements'!$A:$Q,C$4,FALSE) -> 11062 | D76: =VLOOKUP($A76,'Standardized Statements'!$A:$Q,D$4,FALSE) -> 9710 | E76: =VLOOKUP($A76,'Standardized Statements'!$A:$Q,E$4,FALSE) -> 8477 | F76: =VLOOKUP($A76,'Standardized Statements'!$A:$Q,F$4,FALSE) -> 7596 | G76: =VLOOKUP($A76,'Standardized Statements'!$A:$Q,G$4,FALSE) -> 6427 | H76: =VLOOKUP($A76,'Standardized Statements'!$A:$Q,H$4,FALSE) -> 5025 | I76: =VLOOKUP($A76,'Standardized Statements'!$A:$Q,I$4,FALSE) -> 4123 | ... P76: =VLOOKUP($A76,'Standardized Statements'!$A:$Q,P$4,FALSE) -> 1676 | R76: ='Lease adjustments'!B29 -> 0 | S76: ='Lease adjustments'!C29 -> 19814.045 | T76: ='Lease adjustments'!D29 -> 18917.386 | U76: ='Lease adjustments'!E29 -> 17582.23 | V76: ='Lease adjustments'!F29 -> 18875.473 | W76: ='Lease adjustments'!G29 -> 19171.894 | X76: ='Lease adjustments'!H29 -> 15948.768 | Y76: ='Lease adjustments'!I29 -> 14093.634 | ... AF76: ='Lease adjustments'!P29 -> 0 | AH76: =B76+R76 -> 25975 | AI76: =C76+S76 -> 30876.045 | AJ76: =D76+T76 -> 28627.386 | AK76: =E76+U76 -> 26059.23 | AL76: =F76+V76 -> 26471.473 | AM76: =G76+W76 -> 25598.894 | AN76: =H76+X76 -> 20973.768 | AO76: =I76+Y76 -> 18216.634 | ... AV76: =P76+AF76 -> 1676
A77: Operating Cash Flow before Working Capital Investments | B77: =SUM(B73:B76) -> 25074.68 | C77: =SUM(C73:C76) -> 24647.66 | D77: =SUM(D73:D76) -> 22083.8 | E77: =SUM(E73:E76) -> 22996.12 | F77: =SUM(F73:F76) -> 26961.28 | G77: =SUM(G73:G76) -> 26361.18 | H77: =SUM(H73:H76) -> 24653.76 | I77: =SUM(I73:I76) -> 23247.18 | ... P77: =SUM(P73:P76) -> 11414.08 | R77: =SUM(R73:R76) -> 0 | S77: =SUM(S73:S76) -> 20834.25 | T77: =SUM(T73:T76) -> 20052.765 | U77: =SUM(U73:U76) -> 18786.371 | V77: =SUM(V73:V76) -> 20184.724 | W77: =SUM(W73:W76) -> 20249.937 | X77: =SUM(X73:X76) -> 16906.009 | Y77: =SUM(Y73:Y76) -> 14834.92 | ... AF77: =SUM(AF73:AF76) -> 0 | AH77: =B77+R77 -> 25074.68 | AI77: =C77+S77 -> 45481.91 | AJ77: =D77+T77 -> 42136.565 | AK77: =E77+U77 -> 41782.491 | AL77: =F77+V77 -> 47146.004 | AM77: =G77+W77 -> 46611.117 | AN77: =H77+X77 -> 41559.769 | AO77: =I77+Y77 -> 38082.1 | ... AV77: =P77+AF77 -> 11414.08
A79: Net (Investments in) or Liquidation of Operating Working Capital | B79: =VLOOKUP($A79,'Standardized Statements'!$A:$Q,B$4,FALSE) -> 1592 | C79: =VLOOKUP($A79,'Standardized Statements'!$A:$Q,C$4,FALSE) -> 4233 | D79: =VLOOKUP($A79,'Standardized Statements'!$A:$Q,D$4,FALSE) -> -964 | E79: =VLOOKUP($A79,'Standardized Statements'!$A:$Q,E$4,FALSE) -> -1648 | F79: =VLOOKUP($A79,'Standardized Statements'!$A:$Q,F$4,FALSE) -> -3390 | G79: =VLOOKUP($A79,'Standardized Statements'!$A:$Q,G$4,FALSE) -> -2580 | H79: =VLOOKUP($A79,'Standardized Statements'!$A:$Q,H$4,FALSE) -> -793 | I79: =VLOOKUP($A79,'Standardized Statements'!$A:$Q,I$4,FALSE) -> 250 | ... P79: =VLOOKUP($A79,'Standardized Statements'!$A:$Q,P$4,FALSE) -> 136 | AH79: =B79+R79 -> 1592 | AI79: =C79+S79 -> 4233 | AJ79: =D79+T79 -> -964 | AK79: =E79+U79 -> -1648 | AL79: =F79+V79 -> -3390 | AM79: =G79+W79 -> -2580 | AN79: =H79+X79 -> -793 | AO79: =I79+Y79 -> 250 | ... AV79: =P79+AF79 -> 136
A80: Operating Cash Flow before Investment in Non-Current Assets | B80: =SUM(B77:B79) -> 26666.68 | C80: =SUM(C77:C79) -> 28880.66 | D80: =SUM(D77:D79) -> 21119.8 | E80: =SUM(E77:E79) -> 21348.12 | F80: =SUM(F77:F79) -> 23571.28 | G80: =SUM(G77:G79) -> 23781.18 | H80: =SUM(H77:H79) -> 23860.76 | I80: =SUM(I77:I79) -> 23497.18 | ... P80: =SUM(P77:P79) -> 11550.08 | R80: =SUM(R77:R79) -> 0 | S80: =SUM(S77:S79) -> 20834.25 | T80: =SUM(T77:T79) -> 20052.765 | U80: =SUM(U77:U79) -> 18786.371 | V80: =SUM(V77:V79) -> 20184.724 | W80: =SUM(W77:W79) -> 20249.937 | X80: =SUM(X77:X79) -> 16906.009 | Y80: =SUM(Y77:Y79) -> 14834.92 | ... AF80: =SUM(AF77:AF79) -> 0 | AH80: =B80+R80 -> 26666.68 | AI80: =C80+S80 -> 49714.91 | AJ80: =D80+T80 -> 41172.565 | AK80: =E80+U80 -> 40134.491 | AL80: =F80+V80 -> 43756.004 | AM80: =G80+W80 -> 44031.117 | AN80: =H80+X80 -> 40766.769 | AO80: =I80+Y80 -> 38332.1 | ... AV80: =P80+AF80 -> 11550.08
A82: Interest Received | B82: =VLOOKUP($A82,'Standardized Statements'!$A:$Q,B$4,FALSE) -> 252 | C82: =VLOOKUP($A82,'Standardized Statements'!$A:$Q,C$4,FALSE) -> 376 | D82: =VLOOKUP($A82,'Standardized Statements'!$A:$Q,D$4,FALSE) -> 292 | E82: =VLOOKUP($A82,'Standardized Statements'!$A:$Q,E$4,FALSE) -> 281 | F82: =VLOOKUP($A82,'Standardized Statements'!$A:$Q,F$4,FALSE) -> 224 | G82: =VLOOKUP($A82,'Standardized Statements'!$A:$Q,G$4,FALSE) -> 310 | H82: =VLOOKUP($A82,'Standardized Statements'!$A:$Q,H$4,FALSE) -> 328 | I82: =VLOOKUP($A82,'Standardized Statements'!$A:$Q,I$4,FALSE) -> 367 | ... P82: =VLOOKUP($A82,'Standardized Statements'!$A:$Q,P$4,FALSE) -> 515 | AH82: =B82+R82 -> 252 | AI82: =C82+S82 -> 376 | AJ82: =D82+T82 -> 292 | AK82: =E82+U82 -> 281 | AL82: =F82+V82 -> 224 | AM82: =G82+W82 -> 310 | AN82: =H82+X82 -> 328 | AO82: =I82+Y82 -> 367 | ... AV82: =P82+AF82 -> 515
A83: Dividends received | B83: =VLOOKUP($A83,'Standardized Statements'!$A:$Q,B$4,FALSE) -> 0 | C83: =VLOOKUP($A83,'Standardized Statements'!$A:$Q,C$4,FALSE) -> 0 | D83: =VLOOKUP($A83,'Standardized Statements'!$A:$Q,D$4,FALSE) -> 0 | E83: =VLOOKUP($A83,'Standardized Statements'!$A:$Q,E$4,FALSE) -> 0 | F83: =VLOOKUP($A83,'Standardized Statements'!$A:$Q,F$4,FALSE) -> 0 | G83: =VLOOKUP($A83,'Standardized Statements'!$A:$Q,G$4,FALSE) -> 0 | H83: =VLOOKUP($A83,'Standardized Statements'!$A:$Q,H$4,FALSE) -> 0 | I83: =VLOOKUP($A83,'Standardized Statements'!$A:$Q,I$4,FALSE) -> 0 | ... P83: =VLOOKUP($A83,'Standardized Statements'!$A:$Q,P$4,FALSE) -> 0 | AH83: =B83+R83 -> 0 | AI83: =C83+S83 -> 0 | AJ83: =D83+T83 -> 0 | AK83: =E83+U83 -> 0 | AL83: =F83+V83 -> 0 | AM83: =G83+W83 -> 0 | AN83: =H83+X83 -> 0 | AO83: =I83+Y83 -> 0 | ... AV83: =P83+AF83 -> 0
A84: Net (Investments in) or Liquidation of Non-Current Operating or Investment Assets | B84: =VLOOKUP($A84,'Standardized Statements'!$A:$Q,B$4,FALSE) -> -5244 | C84: =VLOOKUP($A84,'Standardized Statements'!$A:$Q,C$4,FALSE) -> -10528 | D84: =VLOOKUP($A84,'Standardized Statements'!$A:$Q,D$4,FALSE) -> -13152 | E84: =VLOOKUP($A84,'Standardized Statements'!$A:$Q,E$4,FALSE) -> -12496 | F84: =VLOOKUP($A84,'Standardized Statements'!$A:$Q,F$4,FALSE) -> -13498 | G84: =VLOOKUP($A84,'Standardized Statements'!$A:$Q,G$4,FALSE) -> -9610 | H84: =VLOOKUP($A84,'Standardized Statements'!$A:$Q,H$4,FALSE) -> -8708 | I84: =VLOOKUP($A84,'Standardized Statements'!$A:$Q,I$4,FALSE) -> -8369 | ... P84: =VLOOKUP($A84,'Standardized Statements'!$A:$Q,P$4,FALSE) -> -4395 | R84: =-'Lease adjustments'!B24 -> 0 | S84: =-'Lease adjustments'!C24 -> -20379.082 | T84: =-'Lease adjustments'!D24 -> -11534.411 | U84: =-'Lease adjustments'!E24 -> -15057.099 | V84: =-'Lease adjustments'!F24 -> -16110.293 | W84: =-'Lease adjustments'!G24 -> -24500.528 | X84: =-'Lease adjustments'!H24 -> -30251.549 | Y84: =-'Lease adjustments'!I24 -> -21162.138 | ... AF84: =-'Lease adjustments'!P24 -> 0 | AH84: =B84+R84 -> -5244 | AI84: =C84+S84 -> -30907.082 | AJ84: =D84+T84 -> -24686.411 | AK84: =E84+U84 -> -27553.099 | AL84: =F84+V84 -> -29608.293 | AM84: =G84+W84 -> -34110.528 | AN84: =H84+X84 -> -38959.549 | AO84: =I84+Y84 -> -29531.138 | ... AV84: =P84+AF84 -> -4395
A85: Free Cash Flow Available to Debt and Equity | B85: =SUM(B80:B84) -> 21674.68 | C85: =SUM(C80:C84) -> 18728.66 | D85: =SUM(D80:D84) -> 8259.8 | E85: =SUM(E80:E84) -> 9133.12 | F85: =SUM(F80:F84) -> 10297.28 | G85: =SUM(G80:G84) -> 14481.18 | H85: =SUM(H80:H84) -> 15480.76 | I85: =SUM(I80:I84) -> 15495.18 | ... P85: =SUM(P80:P84) -> 7670.08 | R85: =SUM(R80:R84) -> 0 | S85: =SUM(S80:S84) -> 455.16809 | T85: =SUM(T80:T84) -> 8518.3539 | U85: =SUM(U80:U84) -> 3729.2718 | V85: =SUM(V80:V84) -> 4074.431 | W85: =SUM(W80:W84) -> -4250.5907 | X85: =SUM(X80:X84) -> -13345.54 | Y85: =SUM(Y80:Y84) -> -6327.2182 | ... AF85: =SUM(AF80:AF84) -> 0 | AH85: =B85+R85 -> 21674.68 | AI85: =C85+S85 -> 19183.828 | AJ85: =D85+T85 -> 16778.154 | AK85: =E85+U85 -> 12862.392 | AL85: =F85+V85 -> 14371.711 | AM85: =G85+W85 -> 10230.589 | AN85: =H85+X85 -> 2135.2195 | AO85: =I85+Y85 -> 9167.9618 | ... AV85: =P85+AF85 -> 7670.08
A87: Interest Paid | B87: =VLOOKUP($A87,'Standardized Statements'!$A:$Q,B$4,FALSE)*B104 -> -1018.68 | C87: =VLOOKUP($A87,'Standardized Statements'!$A:$Q,C$4,FALSE)*C104 -> -270.66 | D87: =VLOOKUP($A87,'Standardized Statements'!$A:$Q,D$4,FALSE)*D104 -> -124.8 | E87: =VLOOKUP($A87,'Standardized Statements'!$A:$Q,E$4,FALSE)*E104 -> -42.12 | F87: =VLOOKUP($A87,'Standardized Statements'!$A:$Q,F$4,FALSE)*F104 -> -20.28 | G87: =VLOOKUP($A87,'Standardized Statements'!$A:$Q,G$4,FALSE)*G104 -> -24.18 | H87: =VLOOKUP($A87,'Standardized Statements'!$A:$Q,H$4,FALSE)*H104 -> -32.76 | I87: =VLOOKUP($A87,'Standardized Statements'!$A:$Q,I$4,FALSE)*I104 -> -24.18 | ... P87: =VLOOKUP($A87,'Standardized Statements'!$A:$Q,P$4,FALSE)*P104 -> -10.08 | R87: =R12*E104 -> 0 | S87: =S12*C104 -> -1020.2048 | T87: =T12*D104 -> -1135.3792 | U87: =U12*E104 -> -1204.1405 | V87: =V12*F104 -> -1309.2512 | W87: =W12*G104 -> -1078.0423 | X87: =X12*H104 -> -957.24089 | Y87: =Y12*I104 -> -741.28514 | Z87: =Z12*J104 -> -1168.2307 | ... AF87: =AF12*P104 -> 0 | AH87: =B87+R87 -> -1018.68 | AI87: =C87+S87 -> -1290.8648 | AJ87: =D87+T87 -> -1260.1792 | AK87: =E87+U87 -> -1246.2605 | AL87: =F87+V87 -> -1329.5312 | AM87: =G87+W87 -> -1102.2223 | AN87: =H87+X87 -> -990.00089 | AO87: =I87+Y87 -> -765.46514 | ... AV87: =P87+AF87 -> -10.08
A88: Net Debt (Repayment) or Issuance | B88: =VLOOKUP($A88,'Standardized Statements'!$A:$Q,B$4,FALSE) -> -15159 | C88: =VLOOKUP($A88,'Standardized Statements'!$A:$Q,C$4,FALSE) -> -2155 | D88: =VLOOKUP($A88,'Standardized Statements'!$A:$Q,D$4,FALSE) -> 9452 | E88: =VLOOKUP($A88,'Standardized Statements'!$A:$Q,E$4,FALSE) -> 7620 | F88: =VLOOKUP($A88,'Standardized Statements'!$A:$Q,F$4,FALSE) -> 2068 | G88: =VLOOKUP($A88,'Standardized Statements'!$A:$Q,G$4,FALSE) -> 0 | H88: =VLOOKUP($A88,'Standardized Statements'!$A:$Q,H$4,FALSE) -> 0 | I88: =VLOOKUP($A88,'Standardized Statements'!$A:$Q,I$4,FALSE) -> 0 | ... P88: =VLOOKUP($A88,'Standardized Statements'!$A:$Q,P$4,FALSE) -> 0 | R88: =-R76-R84 -> 0 | S88: =-S76-S84 -> 565.03671 | T88: =-T76-T84 -> -7382.9747 | U88: =-U76-U84 -> -2525.1312 | V88: =-V76-V84 -> -2765.1799 | W88: =-W76-W84 -> 5328.633 | X88: =-X76-X84 -> 14302.781 | Y88: =-Y76-Y84 -> 7068.5034 | ... AF88: =-AF76-AF84 -> 0 | AH88: =B88+R88 -> -15159 | AI88: =C88+S88 -> -1589.9633 | AJ88: =D88+T88 -> 2069.0253 | AK88: =E88+U88 -> 5094.8688 | AL88: =F88+V88 -> -697.17988 | AM88: =G88+W88 -> 5328.633 | AN88: =H88+X88 -> 14302.781 | AO88: =I88+Y88 -> 7068.5034 | ... AV88: =P88+AF88 -> 0
A89: Free Cash Flow Available to Equity | B89: =SUM(B85:B88) -> 5497 | C89: =SUM(C85:C88) -> 16303 | D89: =SUM(D85:D88) -> 17587 | E89: =SUM(E85:E88) -> 16711 | F89: =SUM(F85:F88) -> 12345 | G89: =SUM(G85:G88) -> 14457 | H89: =SUM(H85:H88) -> 15448 | I89: =SUM(I85:I88) -> 15471 | ... P89: =SUM(P85:P88) -> 7660 | R89: =SUM(R85:R88) -> 0 | S89: =SUM(S85:S88) -> 0 | T89: =SUM(T85:T88) -> 0 | U89: =SUM(U85:U88) -> 0 | V89: =SUM(V85:V88) -> 0 | W89: =SUM(W85:W88) -> 0 | X89: =SUM(X85:X88) -> 0 | Y89: =SUM(Y85:Y88) -> 0 | ... AF89: =SUM(AF85:AF88) -> 0 | AH89: =B89+R89 -> 5497 | AI89: =C89+S89 -> 16303 | AJ89: =D89+T89 -> 17587 | AK89: =E89+U89 -> 16711 | AL89: =F89+V89 -> 12345 | AM89: =G89+W89 -> 14457 | AN89: =H89+X89 -> 15448 | AO89: =I89+Y89 -> 15471 | ... AV89: =P89+AF89 -> 7660
A91: Dividend (Payments) | B91: =VLOOKUP($A91,'Standardized Statements'!$A:$Q,B$4,FALSE) -> 0 | C91: =VLOOKUP($A91,'Standardized Statements'!$A:$Q,C$4,FALSE) -> -16137 | D91: =VLOOKUP($A91,'Standardized Statements'!$A:$Q,D$4,FALSE) -> -16137 | E91: =VLOOKUP($A91,'Standardized Statements'!$A:$Q,E$4,FALSE) -> -16137 | F91: =VLOOKUP($A91,'Standardized Statements'!$A:$Q,F$4,FALSE) -> -16137 | G91: =VLOOKUP($A91,'Standardized Statements'!$A:$Q,G$4,FALSE) -> -16137 | H91: =VLOOKUP($A91,'Standardized Statements'!$A:$Q,H$4,FALSE) -> -15723 | I91: =VLOOKUP($A91,'Standardized Statements'!$A:$Q,I$4,FALSE) -> -15723 | ... P91: =VLOOKUP($A91,'Standardized Statements'!$A:$Q,P$4,FALSE) -> -7861 | AH91: =B91+R91 -> 0 | AI91: =C91+S91 -> -16137 | AJ91: =D91+T91 -> -16137 | AK91: =E91+U91 -> -16137 | AL91: =F91+V91 -> -16137 | AM91: =G91+W91 -> -16137 | AN91: =H91+X91 -> -15723 | AO91: =I91+Y91 -> -15723 | ... AV91: =P91+AF91 -> -7861
A92: Net share (Repurchase) or Issuance | B92: =VLOOKUP($A92,'Standardized Statements'!$A:$Q,B$4,FALSE) -> 0 | C92: =VLOOKUP($A92,'Standardized Statements'!$A:$Q,C$4,FALSE) -> 0 | D92: =VLOOKUP($A92,'Standardized Statements'!$A:$Q,D$4,FALSE) -> 0 | E92: =VLOOKUP($A92,'Standardized Statements'!$A:$Q,E$4,FALSE) -> 0 | F92: =VLOOKUP($A92,'Standardized Statements'!$A:$Q,F$4,FALSE) -> 0 | G92: =VLOOKUP($A92,'Standardized Statements'!$A:$Q,G$4,FALSE) -> 0 | H92: =VLOOKUP($A92,'Standardized Statements'!$A:$Q,H$4,FALSE) -> 0 | I92: =VLOOKUP($A92,'Standardized Statements'!$A:$Q,I$4,FALSE) -> 0 | ... P92: =VLOOKUP($A92,'Standardized Statements'!$A:$Q,P$4,FALSE) -> 0 | AH92: =B92+R92 -> 0 | AI92: =C92+S92 -> 0 | AJ92: =D92+T92 -> 0 | AK92: =E92+U92 -> 0 | AL92: =F92+V92 -> 0 | AM92: =G92+W92 -> 0 | AN92: =H92+X92 -> 0 | AO92: =I92+Y92 -> 0 | ... AV92: =P92+AF92 -> 0
A93: Net Increase (Decrease) in Cash Balance | B93: =SUM(B89:B92) -> 5497 | C93: =SUM(C89:C92) -> 166 | D93: =SUM(D89:D92) -> 1450 | E93: =SUM(E89:E92) -> 574 | F93: =SUM(F89:F92) -> -3792 | G93: =SUM(G89:G92) -> -1680 | H93: =SUM(H89:H92) -> -275 | I93: =SUM(I89:I92) -> -252 | ... P93: =SUM(P89:P92) -> -201 | R93: =SUM(R89:R92) -> 0 | S93: =SUM(S89:S92) -> 0 | T93: =SUM(T89:T92) -> 0 | U93: =SUM(U89:U92) -> 0 | V93: =SUM(V89:V92) -> 0 | W93: =SUM(W89:W92) -> 0 | X93: =SUM(X89:X92) -> 0 | Y93: =SUM(Y89:Y92) -> 0 | ... AF93: =SUM(AF89:AF92) -> 0 | AH93: =B93+R93 -> 5497 | AI93: =C93+S93 -> 166 | AJ93: =D93+T93 -> 1450 | AK93: =E93+U93 -> 574 | AL93: =F93+V93 -> -3792 | AM93: =G93+W93 -> -1680 | AN93: =H93+X93 -> -275 | AO93: =I93+Y93 -> -252 | ... AV93: =P93+AF93 -> -201
A95: CONDENSED STATEMENTS OF EARNINGS | B95: 2020 | C95: 2019 | D95: 2018 | E95: 2017 | F95: 2016 | G95: 2015 | H95: 2014 | I95: 2013 | J95: 2012 | K95: 2011 | L95: 2010 | M95: 2009 | N95: 2008 | O95: 2007 | P95: 2006 | AH95: 2020 | AI95: 2019 | AJ95: 2018 | AK95: 2017 | AL95: 2016 | AM95: 2015 | AN95: 2014 | AO95: 2013 | AP95: 2012 | AQ95: 2011 | AR95: 2010 | AS95: 2009 | AT95: 2008 | AU95: 2007 | AV95: 2006
A96: Revenue | B96: =B6 -> 187031 | C96: =C6 -> 232755 | D96: =D6 -> 210400 | E96: =E6 -> 200004 | F96: =F6 -> 192267 | G96: =G6 -> 180861 | H96: =H6 -> 151419 | I96: =I6 -> 128562 | ... P96: =P6 -> 68400 | R96: =R6 -> 0 | S96: =S6 -> 0 | T96: =T6 -> 0 | U96: =U6 -> 0 | V96: =V6 -> 0 | W96: =W6 -> 0 | X96: =X6 -> 0 | Y96: =Y6 -> 0 | ... AF96: =AF6 -> 0 | AH96: =AH6 -> 187031 | AI96: =AI6 -> 232755 | AJ96: =AJ6 -> 210400 | AK96: =AK6 -> 200004 | AL96: =AL6 -> 192267 | AM96: =AM6 -> 180861 | AN96: =AN6 -> 151419 | AO96: =AO6 -> 128562 | ... AV96: =AV6 -> 68400
A97: Net operating profit after tax | B97: =B101 -> 2065.12 | C97: =C101 -> 13420.38 | D97: =D101 -> 12549.04 | E97: =E101 -> 16006.94 | F97: =F101 -> 18481.56 | G97: =G101 -> 20680.38 | H97: =H101 -> 19752.92 | I97: =I101 -> 16889.92 | ... P97: =P101 -> 10436.28 | R97: =R101 -> 0 | S97: =S101 -> 1307.9549 | T97: =T101 -> 1455.6144 | U97: =U101 -> 1543.7699 | V97: =V101 -> 1678.5271 | W97: =W101 -> 1382.1055 | X97: =X101 -> 1227.2319 | Y97: =Y101 -> 950.36557 | ... AF97: =AF101 -> 0 | AH97: =AH101 -> 2065.12 | AI97: =AI101 -> 14440.585 | AJ97: =AJ101 -> 13684.419 | AK97: =AK101 -> 17211.081 | AL97: =AL101 -> 19790.811 | AM97: =AM101 -> 21758.422 | AN97: =AN101 -> 20710.161 | AO97: =AO101 -> 17631.205 | ... AV97: =AV101 -> 10436.28
A98: Profit or loss | B98: =B15 -> 1243 | C98: =C15 -> 13443 | D98: =D15 -> 12652 | E98: =E15 -> 16184 | F98: =F15 -> 18636 | G98: =G15 -> 20898 | H98: =H15 -> 19976 | I98: =I15 -> 17152 | ... P98: =P15 -> 10797 | R98: =R15 -> 0 | S98: =S15 -> 0 | T98: =T15 -> 0 | U98: =U15 -> -1.4188117e-12 | V98: =V15 -> 0 | W98: =W15 -> 0 | X98: =X15 -> 0 | Y98: =Y15 -> 0 | ... AF98: =AF15 -> 0 | AH98: =AH15 -> 1243 | AI98: =AI15 -> 13443 | AJ98: =AJ15 -> 12652 | AK98: =AK15 -> 16184 | AL98: =AL15 -> 18636 | AM98: =AM15 -> 20898 | AN98: =AN15 -> 19976 | AO98: =AO15 -> 17152 | ... AV98: =AV15 -> 10797
A99: – Investment profit after tax | B99: =-B106 -> -196.56 | C99: =-C106 -> -293.28 | D99: =-D106 -> -227.76 | E99: =-E106 -> -219.18 | F99: =-F106 -> -174.72 | G99: =-G106 -> -241.8 | H99: =-H106 -> -255.84 | I99: =-I106 -> -286.26 | ... P99: =-P106 -> -370.8 | R99: =-R106 -> 0 | S99: =-S106 -> 0 | T99: =-T106 -> 0 | U99: =-U106 -> 0 | V99: =-V106 -> 0 | W99: =-W106 -> 0 | X99: =-X106 -> 0 | Y99: =-Y106 -> 0 | ... AF99: =-AF106 -> 0 | AH99: =-AH106 -> -196.56 | AI99: =-AI106 -> -293.28 | AJ99: =-AJ106 -> -227.76 | AK99: =-AK106 -> -219.18 | AL99: =-AL106 -> -174.72 | AM99: =-AM106 -> -241.8 | AN99: =-AN106 -> -255.84 | AO99: =-AO106 -> -286.26 | ... AV99: =-AV106 -> -370.8
A100: + Interest expense after tax | B100: =B110 -> 1018.68 | C100: =C110 -> 270.66 | D100: =D110 -> 124.8 | E100: =E110 -> 42.12 | F100: =F110 -> 20.28 | G100: =G110 -> 24.18 | H100: =H110 -> 32.76 | I100: =I110 -> 24.18 | ... P100: =P110 -> 10.08 | R100: =R110 -> 0 | S100: =S110 -> 1307.9549 | T100: =T110 -> 1455.6144 | U100: =U110 -> 1543.7699 | V100: =V110 -> 1678.5271 | W100: =W110 -> 1382.1055 | X100: =X110 -> 1227.2319 | Y100: =Y110 -> 950.36557 | ... AF100: =AF110 -> 0 | AH100: =AH110 -> 1018.68 | AI100: =AI110 -> 1290.8648 | AJ100: =AJ110 -> 1260.1792 | AK100: =AK110 -> 1246.2605 | AL100: =AL110 -> 1329.5312 | AM100: =AM110 -> 1102.2223 | AN100: =AN110 -> 990.00089 | AO100: =AO110 -> 765.46514 | ... AV100: =AV110 -> 10.08
A101: = Net operating profit after tax | B101: =SUM(B98:B100) -> 2065.12 | C101: =SUM(C98:C100) -> 13420.38 | D101: =SUM(D98:D100) -> 12549.04 | E101: =SUM(E98:E100) -> 16006.94 | F101: =SUM(F98:F100) -> 18481.56 | G101: =SUM(G98:G100) -> 20680.38 | H101: =SUM(H98:H100) -> 19752.92 | I101: =SUM(I98:I100) -> 16889.92 | ... P101: =SUM(P98:P100) -> 10436.28 | R101: =SUM(R98:R100) -> 0 | S101: =SUM(S98:S100) -> 1307.9549 | T101: =SUM(T98:T100) -> 1455.6144 | U101: =SUM(U98:U100) -> 1543.7699 | V101: =SUM(V98:V100) -> 1678.5271 | W101: =SUM(W98:W100) -> 1382.1055 | X101: =SUM(X98:X100) -> 1227.2319 | Y101: =SUM(Y98:Y100) -> 950.36557 | ... AF101: =SUM(AF98:AF100) -> 0 | AH101: =SUM(AH98:AH100) -> 2065.12 | AI101: =SUM(AI98:AI100) -> 14440.585 | AJ101: =SUM(AJ98:AJ100) -> 13684.419 | AK101: =SUM(AK98:AK100) -> 17211.081 | AL101: =SUM(AL98:AL100) -> 19790.811 | AM101: =SUM(AM98:AM100) -> 21758.422 | AN101: =SUM(AN98:AN100) -> 20710.161 | AO101: =SUM(AO98:AO100) -> 17631.205 | ... AV101: =SUM(AV98:AV100) -> 10436.28
A102: of which: Net non-recurring expense after tax | B102: =B105 -> 0 | C102: =C105 -> 0 | D102: =D105 -> 0 | E102: =E105 -> 0 | F102: =F105 -> 0 | G102: =G105 -> 0 | H102: =H105 -> 0 | I102: =I105 -> 0 | ... P102: =P105 -> 0 | R102: =R105 -> 0 | S102: =S105 -> 0 | T102: =T105 -> 0 | U102: =U105 -> 0 | V102: =V105 -> 0 | W102: =W105 -> 0 | X102: =X105 -> 0 | Y102: =Y105 -> 0 | ... AF102: =AF105 -> 0 | AH102: =AH105 -> 0 | AI102: =AI105 -> 0 | AJ102: =AJ105 -> 0 | AK102: =AK105 -> 0 | AL102: =AL105 -> 0 | AM102: =AM105 -> 0 | AN102: =AN105 -> 0 | AO102: =AO105 -> 0 | ... AV102: =AV105 -> 0
A103: = Net non-recurring expense (income) | B103: =-B10 -> 0 | C103: =-C10 -> 0 | D103: =-D10 -> 0 | E103: =-E10 -> 0 | F103: =-F10 -> 0 | G103: =-G10 -> 0 | H103: =-H10 -> 0 | I103: =-I10 -> 0 | ... P103: =-P10 -> 0 | R103: =-R10 -> 0 | S103: =-S10 -> 0 | T103: =-T10 -> 0 | U103: =-U10 -> 0 | V103: =-V10 -> 0 | W103: =-W10 -> 0 | X103: =-X10 -> 0 | Y103: =-Y10 -> 0 | ... AF103: =-AF10 -> 0 | AH103: =-AH10 -> 0 | AI103: =-AI10 -> 0 | AJ103: =-AJ10 -> 0 | AK103: =-AK10 -> 0 | AL103: =-AL10 -> 0 | AM103: =-AM10 -> 0 | AN103: =-AN10 -> 0 | AO103: =-AO10 -> 0 | ... AV103: =-AV10 -> 0
A104: x (1 – Tax rate) | B104: =(1-'Lease adjustments'!B8) -> 0.78 | C104: =(1-'Lease adjustments'!C8) -> 0.78 | D104: =(1-'Lease adjustments'!D8) -> 0.78 | E104: =(1-'Lease adjustments'!E8) -> 0.78 | F104: =(1-'Lease adjustments'!F8) -> 0.78 | G104: =(1-'Lease adjustments'!G8) -> 0.78 | H104: =(1-'Lease adjustments'!H8) -> 0.78 | I104: =(1-'Lease adjustments'!I8) -> 0.78 | ... P104: =(1-'Lease adjustments'!P8) -> 0.72 | R104: =(1-'Lease adjustments'!R8) -> 1 | S104: =(1-'Lease adjustments'!S8) -> 1 | T104: =(1-'Lease adjustments'!T8) -> 1 | U104: =(1-'Lease adjustments'!U8) -> 1 | V104: =(1-'Lease adjustments'!V8) -> 1 | W104: =(1-'Lease adjustments'!W8) -> 1 | X104: =(1-'Lease adjustments'!X8) -> 1 | Y104: =(1-'Lease adjustments'!Y8) -> 1 | ... AF104: =(1-'Lease adjustments'!AF8) -> 1 | AH104: =B104 -> 0.78 | AI104: =C104 -> 0.78 | AJ104: =D104 -> 0.78 | AK104: =E104 -> 0.78 | AL104: =F104 -> 0.78 | AM104: =G104 -> 0.78 | AN104: =H104 -> 0.78 | AO104: =I104 -> 0.78 | ... AV104: =P104 -> 0.72
A105: = Net non-recurring expense after tax | B105: =B104*B103 -> 0 | C105: =C104*C103 -> 0 | D105: =D104*D103 -> 0 | E105: =E104*E103 -> 0 | F105: =F104*F103 -> 0 | G105: =G104*G103 -> 0 | H105: =H104*H103 -> 0 | I105: =I104*I103 -> 0 | ... P105: =P104*P103 -> 0 | R105: =R104*R103 -> 0 | S105: =S104*S103 -> 0 | T105: =T104*T103 -> 0 | U105: =U104*U103 -> 0 | V105: =V104*V103 -> 0 | W105: =W104*W103 -> 0 | X105: =X104*X103 -> 0 | Y105: =Y104*Y103 -> 0 | ... AF105: =AF104*AF103 -> 0 | AH105: =AH104*AH103 -> 0 | AI105: =AI104*AI103 -> 0 | AJ105: =AJ104*AJ103 -> 0 | AK105: =AK104*AK103 -> 0 | AL105: =AL104*AL103 -> 0 | AM105: =AM104*AM103 -> 0 | AN105: =AN104*AN103 -> 0 | AO105: =AO104*AO103 -> 0 | ... AV105: =AV104*AV103 -> 0
A106: + Net investment profit after tax | B106: =B109 -> 196.56 | C106: =C109 -> 293.28 | D106: =D109 -> 227.76 | E106: =E109 -> 219.18 | F106: =F109 -> 174.72 | G106: =G109 -> 241.8 | H106: =H109 -> 255.84 | I106: =I109 -> 286.26 | ... P106: =P109 -> 370.8 | R106: =R109 -> 0 | S106: =S109 -> 0 | T106: =T109 -> 0 | U106: =U109 -> 0 | V106: =V109 -> 0 | W106: =W109 -> 0 | X106: =X109 -> 0 | Y106: =Y109 -> 0 | ... AF106: =AF109 -> 0 | AH106: =AH109 -> 196.56 | AI106: =AI109 -> 293.28 | AJ106: =AJ109 -> 227.76 | AK106: =AK109 -> 219.18 | AL106: =AL109 -> 174.72 | AM106: =AM109 -> 241.8 | AN106: =AN109 -> 255.84 | AO106: =AO109 -> 286.26 | ... AV106: =AV109 -> 370.8
A107: = Investment and interest income | B107: =B9+B11 -> 252 | C107: =C9+C11 -> 376 | D107: =D9+D11 -> 292 | E107: =E9+E11 -> 281 | F107: =F9+F11 -> 224 | G107: =G9+G11 -> 310 | H107: =H9+H11 -> 328 | I107: =I9+I11 -> 367 | ... P107: =P9+P11 -> 515 | R107: =R9+R11 -> 0 | S107: =S9+S11 -> 0 | T107: =T9+T11 -> 0 | U107: =U9+U11 -> 0 | V107: =V9+V11 -> 0 | W107: =W9+W11 -> 0 | X107: =X9+X11 -> 0 | Y107: =Y9+Y11 -> 0 | ... AF107: =AF9+AF11 -> 0 | AH107: =AH9+AH11 -> 252 | AI107: =AI9+AI11 -> 376 | AJ107: =AJ9+AJ11 -> 292 | AK107: =AK9+AK11 -> 281 | AL107: =AL9+AL11 -> 224 | AM107: =AM9+AM11 -> 310 | AN107: =AN9+AN11 -> 328 | AO107: =AO9+AO11 -> 367 | ... AV107: =AV9+AV11 -> 515
A108: x (1 – Tax rate) | B108: =(1-'Lease adjustments'!B8) -> 0.78 | C108: =(1-'Lease adjustments'!C8) -> 0.78 | D108: =(1-'Lease adjustments'!D8) -> 0.78 | E108: =(1-'Lease adjustments'!E8) -> 0.78 | F108: =(1-'Lease adjustments'!F8) -> 0.78 | G108: =(1-'Lease adjustments'!G8) -> 0.78 | H108: =(1-'Lease adjustments'!H8) -> 0.78 | I108: =(1-'Lease adjustments'!I8) -> 0.78 | ... P108: =(1-'Lease adjustments'!P8) -> 0.72 | R108: =(1-'Lease adjustments'!R8) -> 1 | S108: =(1-'Lease adjustments'!S8) -> 1 | T108: =(1-'Lease adjustments'!T8) -> 1 | U108: =(1-'Lease adjustments'!U8) -> 1 | V108: =(1-'Lease adjustments'!V8) -> 1 | W108: =(1-'Lease adjustments'!W8) -> 1 | X108: =(1-'Lease adjustments'!X8) -> 1 | Y108: =(1-'Lease adjustments'!Y8) -> 1 | ... AF108: =(1-'Lease adjustments'!AF8) -> 1 | AH108: =B108 -> 0.78 | AI108: =C108 -> 0.78 | AJ108: =D108 -> 0.78 | AK108: =E108 -> 0.78 | AL108: =F108 -> 0.78 | AM108: =G108 -> 0.78 | AN108: =H108 -> 0.78 | AO108: =I108 -> 0.78 | ... AV108: =P108 -> 0.72
A109: = Net investment profit after tax | B109: =B108*B107 -> 196.56 | C109: =C108*C107 -> 293.28 | D109: =D108*D107 -> 227.76 | E109: =E108*E107 -> 219.18 | F109: =F108*F107 -> 174.72 | G109: =G108*G107 -> 241.8 | H109: =H108*H107 -> 255.84 | I109: =I108*I107 -> 286.26 | ... P109: =P108*P107 -> 370.8 | R109: =R108*R107 -> 0 | S109: =S108*S107 -> 0 | T109: =T108*T107 -> 0 | U109: =U108*U107 -> 0 | V109: =V108*V107 -> 0 | W109: =W108*W107 -> 0 | X109: =X108*X107 -> 0 | Y109: =Y108*Y107 -> 0 | ... AF109: =AF108*AF107 -> 0 | AH109: =AH108*AH107 -> 196.56 | AI109: =AI108*AI107 -> 293.28 | AJ109: =AJ108*AJ107 -> 227.76 | AK109: =AK108*AK107 -> 219.18 | AL109: =AL108*AL107 -> 174.72 | AM109: =AM108*AM107 -> 241.8 | AN109: =AN108*AN107 -> 255.84 | AO109: =AO108*AO107 -> 286.26 | ... AV109: =AV108*AV107 -> 370.8
A110: – Interest expense after tax | B110: =B113 -> 1018.68 | C110: =C113 -> 270.66 | D110: =D113 -> 124.8 | E110: =E113 -> 42.12 | F110: =F113 -> 20.28 | G110: =G113 -> 24.18 | H110: =H113 -> 32.76 | I110: =I113 -> 24.18 | ... P110: =P113 -> 10.08 | R110: =R113 -> 0 | S110: =S113 -> 1307.9549 | T110: =T113 -> 1455.6144 | U110: =U113 -> 1543.7699 | V110: =V113 -> 1678.5271 | W110: =W113 -> 1382.1055 | X110: =X113 -> 1227.2319 | Y110: =Y113 -> 950.36557 | ... AF110: =AF113 -> 0 | AH110: =AH113 -> 1018.68 | AI110: =AI113 -> 1290.8648 | AJ110: =AJ113 -> 1260.1792 | AK110: =AK113 -> 1246.2605 | AL110: =AL113 -> 1329.5312 | AM110: =AM113 -> 1102.2223 | AN110: =AN113 -> 990.00089 | AO110: =AO113 -> 765.46514 | ... AV110: =AV113 -> 10.08
A111: = Interest expense | B111: =-(B12) -> 1306 | C111: =-(C12) -> 347 | D111: =-(D12) -> 160 | E111: =-(E12) -> 54 | F111: =-(F12) -> 26 | G111: =-(G12) -> 31 | H111: =-(H12) -> 42 | I111: =-(I12) -> 31 | ... P111: =-(P12) -> 14 | R111: =-(R12) -> 0 | S111: =-(S12) -> 1307.9549 | T111: =-(T12) -> 1455.6144 | U111: =-(U12) -> 1543.7699 | V111: =-(V12) -> 1678.5271 | W111: =-(W12) -> 1382.1055 | X111: =-(X12) -> 1227.2319 | Y111: =-(Y12) -> 950.36557 | ... AF111: =-(AF12) -> 0 | AH111: =-(AH12) -> 1306 | AI111: =-(AI12) -> 1654.9549 | AJ111: =-(AJ12) -> 1615.6144 | AK111: =-(AK12) -> 1597.7699 | AL111: =-(AL12) -> 1704.5271 | AM111: =-(AM12) -> 1413.1055 | AN111: =-(AN12) -> 1269.2319 | AO111: =-(AO12) -> 981.36557 | ... AV111: =-(AV12) -> 14
A112: x (1 – Tax rate) | B112: =(1-'Lease adjustments'!B8) -> 0.78 | C112: =(1-'Lease adjustments'!C8) -> 0.78 | D112: =(1-'Lease adjustments'!D8) -> 0.78 | E112: =(1-'Lease adjustments'!E8) -> 0.78 | F112: =(1-'Lease adjustments'!F8) -> 0.78 | G112: =(1-'Lease adjustments'!G8) -> 0.78 | H112: =(1-'Lease adjustments'!H8) -> 0.78 | I112: =(1-'Lease adjustments'!I8) -> 0.78 | ... P112: =(1-'Lease adjustments'!P8) -> 0.72 | R112: =(1-'Lease adjustments'!R8) -> 1 | S112: =(1-'Lease adjustments'!S8) -> 1 | T112: =(1-'Lease adjustments'!T8) -> 1 | U112: =(1-'Lease adjustments'!U8) -> 1 | V112: =(1-'Lease adjustments'!V8) -> 1 | W112: =(1-'Lease adjustments'!W8) -> 1 | X112: =(1-'Lease adjustments'!X8) -> 1 | Y112: =(1-'Lease adjustments'!Y8) -> 1 | ... AF112: =(1-'Lease adjustments'!AF8) -> 1 | AH112: =B112 -> 0.78 | AI112: =C112 -> 0.78 | AJ112: =D112 -> 0.78 | AK112: =E112 -> 0.78 | AL112: =F112 -> 0.78 | AM112: =G112 -> 0.78 | AN112: =H112 -> 0.78 | AO112: =I112 -> 0.78 | ... AV112: =P112 -> 0.72
A113: = Interest expense after tax | B113: =B112*B111 -> 1018.68 | C113: =C112*C111 -> 270.66 | D113: =D112*D111 -> 124.8 | E113: =E112*E111 -> 42.12 | F113: =F112*F111 -> 20.28 | G113: =G112*G111 -> 24.18 | H113: =H112*H111 -> 32.76 | I113: =I112*I111 -> 24.18 | ... P113: =P112*P111 -> 10.08 | R113: =R112*R111 -> 0 | S113: =S112*S111 -> 1307.9549 | T113: =T112*T111 -> 1455.6144 | U113: =U112*U111 -> 1543.7699 | V113: =V112*V111 -> 1678.5271 | W113: =W112*W111 -> 1382.1055 | X113: =X112*X111 -> 1227.2319 | Y113: =Y112*Y111 -> 950.36557 | ... AF113: =AF112*AF111 -> 0 | AH113: =AH112*AH111 -> 1018.68 | AI113: =AI112*AI111 -> 1290.8648 | AJ113: =AJ112*AJ111 -> 1260.1792 | AK113: =AK112*AK111 -> 1246.2605 | AL113: =AL112*AL111 -> 1329.5312 | AM113: =AM112*AM111 -> 1102.2223 | AN113: =AN112*AN111 -> 990.00089 | AO113: =AO112*AO111 -> 765.46514 | ... AV113: =AV112*AV111 -> 10.08
A114: = Profit or loss | B114: =B101+B106-B110 -> 1243 | C114: =C101+C106-C110 -> 13443 | D114: =D101+D106-D110 -> 12652 | E114: =E101+E106-E110 -> 16184 | F114: =F101+F106-F110 -> 18636 | G114: =G101+G106-G110 -> 20898 | H114: =H101+H106-H110 -> 19976 | I114: =I101+I106-I110 -> 17152 | ... P114: =P101+P106-P110 -> 10797 | R114: =R101+R106-R110 -> 0 | S114: =S101+S106-S110 -> 0 | T114: =T101+T106-T110 -> 0 | U114: =U101+U106-U110 -> 0 | V114: =V101+V106-V110 -> 0 | W114: =W101+W106-W110 -> 0 | X114: =X101+X106-X110 -> 0 | Y114: =Y101+Y106-Y110 -> 0 | ... AF114: =AF101+AF106-AF110 -> 0 | AH114: =AH101+AH106-AH110 -> 1243 | AI114: =AI101+AI106-AI110 -> 13443 | AJ114: =AJ101+AJ106-AJ110 -> 12652 | AK114: =AK101+AK106-AK110 -> 16184 | AL114: =AL101+AL106-AL110 -> 18636 | AM114: =AM101+AM106-AM110 -> 20898 | AN114: =AN101+AN106-AN110 -> 19976 | AO114: =AO101+AO106-AO110 -> 17152 | ... AV114: =AV101+AV106-AV110 -> 10797
A116: CONDENSED BALANCE SHEETS | B116: 2020 | C116: 2019 | D116: 2018 | E116: 2017 | F116: 2016 | G116: 2015 | H116: 2014 | I116: 2013 | J116: 2012 | K116: 2011 | L116: 2010 | M116: 2009 | N116: 2008 | O116: 2007 | P116: 2006 | AH116: 2020 | AI116: 2019 | AJ116: 2018 | AK116: 2017 | AL116: 2016 | AM116: 2015 | AN116: 2014 | AO116: 2013 | AP116: 2012 | AQ116: 2011 | AR116: 2010 | AS116: 2009 | AT116: 2008 | AU116: 2007 | AV116: 2006
A117: Ending operating working capital
A118: Operating cash | B118: =MIN(B2*B6,B43) -> 9351.55 | C118: =MIN(C2*C6,C43) -> 11637.75 | D118: =MIN(D2*D6,D43) -> 10520 | E118: =MIN(E2*E6,E43) -> 9718 | F118: =MIN(F2*F6,F43) -> 9446 | G118: =MIN(G2*G6,G43) -> 9043.05 | H118: =MIN(H2*H6,H43) -> 7570.95 | I118: =MIN(I2*I6,I43) -> 6428.1 | ... P118: =MIN(P2*P6,P43) -> 3420 | AH118: =MIN(AH2*AH6,AH43) -> 9351.55 | AI118: =MIN(AI2*AI6,AI43) -> 11637.75 | AJ118: =MIN(AJ2*AJ6,AJ43) -> 10520 | AK118: =MIN(AK2*AK6,AK43) -> 9718 | AL118: =MIN(AL2*AL6,AL43) -> 9446 | AM118: =MIN(AM2*AM6,AM43) -> 9043.05 | AN118: =MIN(AN2*AN6,AN43) -> 7570.95 | AO118: =MIN(AO2*AO6,AO43) -> 6428.1 | ... AV118: =MIN(AV2*AV6,AV43) -> 3420
A119: + Trade receivables | B119: =B41 -> 3086 | C119: =C41 -> 5879 | D119: =D41 -> 6329 | E119: =E41 -> 5297 | F119: =F41 -> 4881 | G119: =G41 -> 4021 | H119: =H41 -> 3659 | I119: =I41 -> 3107 | ... P119: =P41 -> 865 | AH119: =AH41 -> 3086 | AI119: =AI41 -> 5879 | AJ119: =AJ41 -> 6329 | AK119: =AK41 -> 5297 | AL119: =AL41 -> 4881 | AM119: =AM41 -> 4021 | AN119: =AN41 -> 3659 | AO119: =AO41 -> 3107 | ... AV119: =AV41 -> 865
A120: + Inventories | B120: =B40 -> 38209 | C120: =C40 -> 37823 | D120: =D40 -> 37721 | E120: =E40 -> 33712 | F120: =F40 -> 31732 | G120: =G40 -> 24833 | H120: =H40 -> 19403 | I120: =I40 -> 16695 | ... P120: =P40 -> 7220 | AH120: =AH40 -> 38209 | AI120: =AI40 -> 37823 | AJ120: =AJ40 -> 37721 | AK120: =AK40 -> 33712 | AL120: =AL40 -> 31732 | AM120: =AM40 -> 24833 | AN120: =AN40 -> 19403 | AO120: =AO40 -> 16695 | ... AV120: =AV40 -> 7220
...

Sheet Ratio Analysis
A1: Return on equity
A2: Ratio | B2: 2020 | C2: 2019 | D2: 2018 | E2: 2017 | F2: 2016 | G2: 2015 | H2: 2014 | I2: 2013 | J2: 2012 | K2: 2011 | L2: 2010 | M2: 2009 | N2: 2008 | O2: 2007
A3: Return on equity | B3: ='Adjusted Statements'!AH114/AVERAGE('Adjusted Statements'!AH148,'Adjusted Statements'!AI148) -> 0.022257637 | C3: ='Adjusted Statements'!AI114/AVERAGE('Adjusted Statements'!AI148,'Adjusted Statements'!AJ148) -> 0.23254768 | D3: ='Adjusted Statements'!AJ114/AVERAGE('Adjusted Statements'!AJ148,'Adjusted Statements'!AK148) -> 0.21397103 | E3: ='Adjusted Statements'!AK114/AVERAGE('Adjusted Statements'!AK148,'Adjusted Statements'!AL148) -> 0.26761693 | F3: ='Adjusted Statements'!AL114/AVERAGE('Adjusted Statements'!AL148,'Adjusted Statements'!AM148) -> 0.31246175 | G3: ='Adjusted Statements'!AM114/AVERAGE('Adjusted Statements'!AM148,'Adjusted Statements'!AN148) -> 0.38133297 | H3: ='Adjusted Statements'!AN114/AVERAGE('Adjusted Statements'!AN148,'Adjusted Statements'!AO148) -> 0.41271022 | I3: ='Adjusted Statements'!AO114/AVERAGE('Adjusted Statements'!AO148,'Adjusted Statements'!AP148) -> 0.38507908 | ... O3: ='Adjusted Statements'!AU114/AVERAGE('Adjusted Statements'!AU148,'Adjusted Statements'!AV148) -> 0.45390166
A5: DuPont decomposition of ROE
A6: Ratio | B6: 2020 | C6: 2019 | D6: 2018 | E6: 2017 | F6: 2016 | G6: 2015 | H6: 2014 | I6: 2013 | J6: 2012 | K6: 2011 | L6: 2010 | M6: 2009 | N6: 2008 | O6: 2007
A7: Net profit margin (ROS) | B7: ='Adjusted Statements'!AH114/'Adjusted Statements'!AH96 -> 0.0066459571 | C7: ='Adjusted Statements'!AI114/'Adjusted Statements'!AI96 -> 0.05775601 | D7: ='Adjusted Statements'!AJ114/'Adjusted Statements'!AJ96 -> 0.06013308 | E7: ='Adjusted Statements'!AK114/'Adjusted Statements'!AK96 -> 0.080918382 | F7: ='Adjusted Statements'!AL114/'Adjusted Statements'!AL96 -> 0.09692771 | G7: ='Adjusted Statements'!AM114/'Adjusted Statements'!AM96 -> 0.1155473 | H7: ='Adjusted Statements'!AN114/'Adjusted Statements'!AN96 -> 0.13192532 | I7: ='Adjusted Statements'!AO114/'Adjusted Statements'!AO96 -> 0.13341423 | ... O7: ='Adjusted Statements'!AU114/'Adjusted Statements'!AU96 -> 0.17343578
A8: × Asset turnover | B8: ='Adjusted Statements'!AH96/AVERAGE('Adjusted Statements'!AH48,'Adjusted Statements'!AI48) -> 1.0367032 | C8: ='Adjusted Statements'!AI96/AVERAGE('Adjusted Statements'!AI48,'Adjusted Statements'!AJ48) -> 1.2559778 | D8: ='Adjusted Statements'!AJ96/AVERAGE('Adjusted Statements'!AJ48,'Adjusted Statements'!AK48) -> 1.1575371 | E8: ='Adjusted Statements'!AK96/AVERAGE('Adjusted Statements'!AK48,'Adjusted Statements'!AL48) -> 1.1324371 | F8: ='Adjusted Statements'!AL96/AVERAGE('Adjusted Statements'!AL48,'Adjusted Statements'!AM48) -> 1.138453 | G8: ='Adjusted Statements'!AM96/AVERAGE('Adjusted Statements'!AM48,'Adjusted Statements'!AN48) -> 1.1585357 | H8: ='Adjusted Statements'!AN96/AVERAGE('Adjusted Statements'!AN48,'Adjusted Statements'!AO48) -> 1.1115156 | I8: ='Adjusted Statements'!AO96/AVERAGE('Adjusted Statements'!AO48,'Adjusted Statements'!AP48) -> 1.0910816 | ... O8: ='Adjusted Statements'!AU96/AVERAGE('Adjusted Statements'!AU48,'Adjusted Statements'!AV48) -> 1.128871
A9: = Return on assets (ROA) | B9: =B7*B8 -> 0.0068898853 | C9: =C7*C8 -> 0.072540267 | D9: =D7*D8 -> 0.069606271 | E9: =E7*E8 -> 0.091634977 | F9: =F7*F8 -> 0.11034764 | G9: =G7*G8 -> 0.13386568 | H9: =H7*H8 -> 0.14663705 | I9: =I7*I8 -> 0.14556581 | ... O9: =O7*O8 -> 0.19578663
A10: × Financial leverage | B10: =AVERAGE('Adjusted Statements'!AH48,'Adjusted Statements'!AI48)/AVERAGE('Adjusted Statements'!AH148,'Adjusted Statements'!AI148) -> 3.2304801 | C10: =AVERAGE('Adjusted Statements'!AI48,'Adjusted Statements'!AJ48)/AVERAGE('Adjusted Statements'!AI148,'Adjusted Statements'!AJ148) -> 3.2057737 | D10: =AVERAGE('Adjusted Statements'!AJ48,'Adjusted Statements'!AK48)/AVERAGE('Adjusted Statements'!AJ148,'Adjusted Statements'!AK148) -> 3.0740194 | E10: =AVERAGE('Adjusted Statements'!AK48,'Adjusted Statements'!AL48)/AVERAGE('Adjusted Statements'!AK148,'Adjusted Statements'!AL148) -> 2.920467 | F10: =AVERAGE('Adjusted Statements'!AL48,'Adjusted Statements'!AM48)/AVERAGE('Adjusted Statements'!AL148,'Adjusted Statements'!AM148) -> 2.8316123 | G10: =AVERAGE('Adjusted Statements'!AM48,'Adjusted Statements'!AN48)/AVERAGE('Adjusted Statements'!AM148,'Adjusted Statements'!AN148) -> 2.8486239 | H10: =AVERAGE('Adjusted Statements'!AN48,'Adjusted Statements'!AO48)/AVERAGE('Adjusted Statements'!AN148,'Adjusted Statements'!AO148) -> 2.8145016 | I10: =AVERAGE('Adjusted Statements'!AO48,'Adjusted Statements'!AP48)/AVERAGE('Adjusted Statements'!AO148,'Adjusted Statements'!AP148) -> 2.645395 | ... O10: =AVERAGE('Adjusted Statements'!AU48,'Adjusted Statements'!AV48)/AVERAGE('Adjusted Statements'!AU148,'Adjusted Statements'!AV148) -> 2.3183486
A11: = Return on equity (ROE) | B11: =B9*B10 -> 0.022257637 | C11: =C9*C10 -> 0.23254768 | D11: =D9*D10 -> 0.21397103 | E11: =E9*E10 -> 0.26761693 | F11: =F9*F10 -> 0.31246175 | G11: =G9*G10 -> 0.38133297 | H11: =H9*H10 -> 0.41271022 | I11: =I9*I10 -> 0.38507908 | ... O11: =O9*O10 -> 0.45390166
A13: Decomposing RNOA
A14: Ratio | B14: 2020 | C14: 2019 | D14: 2018 | E14: 2017 | F14: 2016 | G14: 2015 | H14: 2014 | I14: 2013 | J14: 2012 | K14: 2011 | L14: 2010 | M14: 2009 | N14: 2008 | O14: 2007
A15: Net Operating Profit Margin | B15: =('Adjusted Statements'!AH101)/'Adjusted Statements'!AH96 -> 0.011041592 | C15: =('Adjusted Statements'!AI101)/'Adjusted Statements'!AI96 -> 0.062041996 | D15: =('Adjusted Statements'!AJ101)/'Adjusted Statements'!AJ96 -> 0.065040015 | E15: =('Adjusted Statements'!AK101)/'Adjusted Statements'!AK96 -> 0.086053682 | F15: =('Adjusted Statements'!AL101)/'Adjusted Statements'!AL96 -> 0.102934 | G15: =('Adjusted Statements'!AM101)/'Adjusted Statements'!AM96 -> 0.12030467 | H15: =('Adjusted Statements'!AN101)/'Adjusted Statements'!AN96 -> 0.13677386 | I15: =('Adjusted Statements'!AO101)/'Adjusted Statements'!AO96 -> 0.13714165 | ... O15: =('Adjusted Statements'!AU101)/'Adjusted Statements'!AU96 -> 0.17830754
A16: × Net Operating Asset Turnover | B16: ='Adjusted Statements'!AH96/AVERAGE('Adjusted Statements'!AH124+'Adjusted Statements'!AH131,'Adjusted Statements'!AI124+'Adjusted Statements'!AI131) -> 1.4092516 | C16: ='Adjusted Statements'!AI96/AVERAGE('Adjusted Statements'!AI124+'Adjusted Statements'!AI131,'Adjusted Statements'!AJ124+'Adjusted Statements'!AJ131) -> 1.6580869 | D16: ='Adjusted Statements'!AJ96/AVERAGE('Adjusted Statements'!AJ124+'Adjusted Statements'!AJ131,'Adjusted Statements'!AK124+'Adjusted Statements'!AK131) -> 1.4824394 | E16: ='Adjusted Statements'!AK96/AVERAGE('Adjusted Statements'!AK124+'Adjusted Statements'!AK131,'Adjusted Statements'!AL124+'Adjusted Statements'!AL131) -> 1.4259794 | F16: ='Adjusted Statements'!AL96/AVERAGE('Adjusted Statements'!AL124+'Adjusted Statements'!AL131,'Adjusted Statements'!AM124+'Adjusted Statements'!AM131) -> 1.4231725 | G16: ='Adjusted Statements'!AM96/AVERAGE('Adjusted Statements'!AM124+'Adjusted Statements'!AM131,'Adjusted Statements'!AN124+'Adjusted Statements'!AN131) -> 1.4661329 | H16: ='Adjusted Statements'!AN96/AVERAGE('Adjusted Statements'!AN124+'Adjusted Statements'!AN131,'Adjusted Statements'!AO124+'Adjusted Statements'!AO131) -> 1.4597412 | I16: ='Adjusted Statements'!AO96/AVERAGE('Adjusted Statements'!AO124+'Adjusted Statements'!AO131,'Adjusted Statements'!AP124+'Adjusted Statements'!AP131) -> 1.4576705 | ... O16: ='Adjusted Statements'!AU96/AVERAGE('Adjusted Statements'!AU124+'Adjusted Statements'!AU131,'Adjusted Statements'!AV124+'Adjusted Statements'!AV131) -> 1.7475568
A17: = Return on Net Operating Assets | B17: =B15*B16 -> 0.015560382 | C17: =C15*C16 -> 0.10287102 | D17: =D15*D16 -> 0.09641788 | E17: =E15*E16 -> 0.12271078 | F17: =F15*F16 -> 0.14649284 | G17: =G15*G16 -> 0.17638263 | H17: =H15*H16 -> 0.19965444 | I17: =I15*I16 -> 0.19990734 | ... O17: =O15*O16 -> 0.31160255
A19: Common-sized income statement
B20: 2020 | C20: 2019 | D20: 2018 | E20: 2017 | F20: 2016 | G20: 2015 | H20: 2014 | I20: 2013 | J20: 2012 | K20: 2011 | L20: 2010 | M20: 2009 | N20: 2008 | O20: 2007
A21: Line items as a percent of sales
A22: Revenue | B22: ='Adjusted Statements'!AH6/'Adjusted Statements'!$AH$6 -> 1 | C22: ='Adjusted Statements'!AI6/'Adjusted Statements'!$AI$6 -> 1 | D22: ='Adjusted Statements'!AJ6/'Adjusted Statements'!$AJ$6 -> 1 | E22: ='Adjusted Statements'!$AK$6/'Adjusted Statements'!$AK$6 -> 1 | F22: ='Adjusted Statements'!AL6/'Adjusted Statements'!$AL$6 -> 1 | G22: ='Adjusted Statements'!AM6/'Adjusted Statements'!$AM$6 -> 1 | H22: ='Adjusted Statements'!AN6/'Adjusted Statements'!$AN$6 -> 1 | I22: ='Adjusted Statements'!AO6/'Adjusted Statements'!$AO$6 -> 1 | J22: ='Adjusted Statements'!AP6/'Adjusted Statements'!$AP$6 -> 1 | K22: ='Adjusted Statements'!AQ6/'Adjusted Statements'!$AQ$6 -> 1 | L22: ='Adjusted Statements'!AR6/'Adjusted Statements'!$AR$6 -> 1 | M22: ='Adjusted Statements'!AS6/'Adjusted Statements'!$AS$6 -> 1 | N22: ='Adjusted Statements'!AT6/'Adjusted Statements'!$AT$6 -> 1 | O22: ='Adjusted Statements'!AU6/'Adjusted Statements'!$AU$6 -> 1
A23: Net operating expense | B23: ='Adjusted Statements'!AH7/'Adjusted Statements'!AH6 -> -0.98339313 | C23: ='Adjusted Statements'!AI7/'Adjusted Statements'!AI6 -> -0.91978709 | D23: ='Adjusted Statements'!AJ7/'Adjusted Statements'!AJ6 -> -0.91937921 | E23: ='Adjusted Statements'!AK7/'Adjusted Statements'!AK6 -> -0.88937336 | F23: ='Adjusted Statements'!AL7/'Adjusted Statements'!AL6 -> -0.86727037 | G23: ='Adjusted Statements'!AM7/'Adjusted Statements'!AM6 -> -0.84327685 | H23: ='Adjusted Statements'!AN7/'Adjusted Statements'!AN6 -> -0.8227684 | I23: ='Adjusted Statements'!AO7/'Adjusted Statements'!AO6 -> -0.82000618 | ... O23: ='Adjusted Statements'!AU7/'Adjusted Statements'!AU6 -> -0.74854984
A24: Net non-recurring income or expense | B24: ='Adjusted Statements'!AH10/'Adjusted Statements'!AH6 -> 0 | C24: ='Adjusted Statements'!AI10/'Adjusted Statements'!AI6 -> 0 | D24: ='Adjusted Statements'!AJ10/'Adjusted Statements'!AJ6 -> 0 | E24: ='Adjusted Statements'!AK10/'Adjusted Statements'!AK6 -> 0 | F24: ='Adjusted Statements'!AL10/'Adjusted Statements'!AL6 -> 0 | G24: ='Adjusted Statements'!AM10/'Adjusted Statements'!AM6 -> 0 | H24: ='Adjusted Statements'!AN10/'Adjusted Statements'!AN6 -> 0 | I24: ='Adjusted Statements'!AO10/'Adjusted Statements'!AO6 -> 0 | ... O24: ='Adjusted Statements'!AU10/'Adjusted Statements'!AU6 -> 0
A25: Net operating profit before tax | B25: =SUM(B22:B24) -> 0.016606873 | C25: =SUM(C22:C24) -> 0.080212906 | D25: =SUM(D22:D24) -> 0.080620791 | E25: =SUM(E22:E24) -> 0.11062664 | F25: =SUM(F22:F24) -> 0.13272963 | G25: =SUM(G22:G24) -> 0.15672315 | H25: =SUM(H22:H24) -> 0.1772316 | I25: =SUM(I22:I24) -> 0.17999382 | ... O25: =SUM(O22:O24) -> 0.25145016
A26: Non-operating investment income | B26: =('Adjusted Statements'!AH9+'Adjusted Statements'!AH11)/'Adjusted Statements'!AH6 -> 0.0013473702 | C26: =('Adjusted Statements'!AI9+'Adjusted Statements'!AI11)/'Adjusted Statements'!AI6 -> 0.0016154325 | D26: =('Adjusted Statements'!AJ9+'Adjusted Statements'!AJ11)/'Adjusted Statements'!AJ6 -> 0.0013878327 | E26: =('Adjusted Statements'!AK9+'Adjusted Statements'!AK11)/'Adjusted Statements'!AK6 -> 0.0014049719 | F26: =('Adjusted Statements'!AL9+'Adjusted Statements'!AL11)/'Adjusted Statements'!AL6 -> 0.0011650465 | G26: =('Adjusted Statements'!AM9+'Adjusted Statements'!AM11)/'Adjusted Statements'!AM6 -> 0.0017140235 | H26: =('Adjusted Statements'!AN9+'Adjusted Statements'!AN11)/'Adjusted Statements'!AN6 -> 0.0021661747 | I26: =('Adjusted Statements'!AO9+'Adjusted Statements'!AO11)/'Adjusted Statements'!AO6 -> 0.0028546538 | ... O26: =('Adjusted Statements'!AU9+'Adjusted Statements'!AU11)/'Adjusted Statements'!AU6 -> 0.010121768
A27: Interest expense | B27: ='Adjusted Statements'!AH12/'Adjusted Statements'!AH6 -> -0.0069827996 | C27: ='Adjusted Statements'!AI12/'Adjusted Statements'!AI6 -> -0.0071102871 | D27: ='Adjusted Statements'!AJ12/'Adjusted Statements'!AJ6 -> -0.0076787755 | E27: ='Adjusted Statements'!AK12/'Adjusted Statements'!AK6 -> -0.0079886898 | F27: ='Adjusted Statements'!AL12/'Adjusted Statements'!AL6 -> -0.008865417 | G27: ='Adjusted Statements'!AM12/'Adjusted Statements'!AM6 -> -0.0078132131 | H27: ='Adjusted Statements'!AN12/'Adjusted Statements'!AN6 -> -0.00838225 | I27: ='Adjusted Statements'!AO12/'Adjusted Statements'!AO6 -> -0.0076334031 | ... O27: ='Adjusted Statements'!AU12/'Adjusted Statements'!AU6 -> -0.01688809
A28: Tax expense | B28: ='Adjusted Statements'!AH14/'Adjusted Statements'!AH6 -> -0.0043254861 | C28: ='Adjusted Statements'!AI14/'Adjusted Statements'!AI6 -> -0.016962042 | D28: ='Adjusted Statements'!AJ14/'Adjusted Statements'!AJ6 -> -0.014196768 | E28: ='Adjusted Statements'!AK14/'Adjusted Statements'!AK6 -> -0.023124538 | F28: ='Adjusted Statements'!AL14/'Adjusted Statements'!AL6 -> -0.028101546 | G28: ='Adjusted Statements'!AM14/'Adjusted Statements'!AM6 -> -0.035076661 | H28: ='Adjusted Statements'!AN14/'Adjusted Statements'!AN6 -> -0.039090207 | I28: ='Adjusted Statements'!AO14/'Adjusted Statements'!AO6 -> -0.041800843 | ... O28: ='Adjusted Statements'!AU14/'Adjusted Statements'!AU6 -> -0.071248054
A29: Profit or loss | B29: =SUM(B25:B28) -> 0.0066459571 | C29: =SUM(C25:C28) -> 0.05775601 | D29: =SUM(D25:D28) -> 0.06013308 | E29: =SUM(E25:E28) -> 0.080918382 | F29: =SUM(F25:F28) -> 0.09692771 | G29: =SUM(G25:G28) -> 0.1155473 | H29: =SUM(H25:H28) -> 0.13192532 | I29: =SUM(I25:I28) -> 0.13341423 | ... O29: =SUM(O25:O28) -> 0.17343578
A30: Operating expense line items as a percent of sales (by function)
A31: Cost of sales | B31: ='Adjusted Statements'!AH21/'Adjusted Statements'!AH6 -> -0.49984762 | C31: ='Adjusted Statements'!AI21/'Adjusted Statements'!AI6 -> -0.47389745 | D31: ='Adjusted Statements'!AJ21/'Adjusted Statements'!AJ6 -> -0.47297053 | E31: ='Adjusted Statements'!AK21/'Adjusted Statements'!AK6 -> -0.45956081 | F31: ='Adjusted Statements'!AL21/'Adjusted Statements'!AL6 -> -0.44776275 | G31: ='Adjusted Statements'!AM21/'Adjusted Statements'!AM6 -> -0.42957852 | H31: ='Adjusted Statements'!AN21/'Adjusted Statements'!AN6 -> -0.41188358 | I31: ='Adjusted Statements'!AO21/'Adjusted Statements'!AO6 -> -0.40858885 | ... K31: ='Adjusted Statements'!AQ21/'Adjusted Statements'!AQ6 -> -0.39865817 | L31: ='Adjusted Statements'!AR21/'Adjusted Statements'!$AR$6 -> -0.37069403 | M31: ='Adjusted Statements'!AS21/'Adjusted Statements'!$AS$6 -> -0.38384307 | N31: ='Adjusted Statements'!AT21/'Adjusted Statements'!$AT$6 -> -0.38476483 | O31: ='Adjusted Statements'!AU21/'Adjusted Statements'!$AU$6 -> -0.38928599
A32: Selling, general, and administrative expense | B32: ='Adjusted Statements'!AH22/'Adjusted Statements'!AH6 -> -0.48354551 | C32: ='Adjusted Statements'!AI22/'Adjusted Statements'!AI6 -> -0.44588965 | D32: ='Adjusted Statements'!AJ22/'Adjusted Statements'!AJ6 -> -0.44640868 | E32: ='Adjusted Statements'!AK22/'Adjusted Statements'!AK6 -> -0.42981255 | F32: ='Adjusted Statements'!AL22/'Adjusted Statements'!AL6 -> -0.41950763 | G32: ='Adjusted Statements'!AM22/'Adjusted Statements'!AM6 -> -0.41369833 | H32: ='Adjusted Statements'!AN22/'Adjusted Statements'!AN6 -> -0.41088482 | I32: ='Adjusted Statements'!AO22/'Adjusted Statements'!AO6 -> -0.41141733 | ... K32: ='Adjusted Statements'!AQ22/'Adjusted Statements'!AQ6 -> -0.40338096 | L32: ='Adjusted Statements'!AR22/'Adjusted Statements'!$AR$6 -> -0.38840343 | M32: ='Adjusted Statements'!AS22/'Adjusted Statements'!$AS$6 -> -0.38030489 | N32: ='Adjusted Statements'!AT22/'Adjusted Statements'!$AT$6 -> -0.37027835 | O32: ='Adjusted Statements'!AU22/'Adjusted Statements'!$AU$6 -> -0.35926385
A33: Operating expense line items as a percent of sales (by nature)
A34: Personnel expense | B34: ='Adjusted Statements'!AH26/'Adjusted Statements'!AH6 -> -0.19757153 | C34: ='Adjusted Statements'!AI26/'Adjusted Statements'!AI6 -> -0.18210135 | D34: ='Adjusted Statements'!AJ26/'Adjusted Statements'!AJ6 -> -0.18318916 | E34: ='Adjusted Statements'!AK26/'Adjusted Statements'!AK6 -> -0.17816644 | F34: ='Adjusted Statements'!AL26/'Adjusted Statements'!AL6 -> -0.16935304 | G34: ='Adjusted Statements'!AM26/'Adjusted Statements'!AM6 -> -0.16560784 | H34: ='Adjusted Statements'!AN26/'Adjusted Statements'!AN6 -> -0.16542178 | I34: ='Adjusted Statements'!AO26/'Adjusted Statements'!AO6 -> -0.16663555 | ... O34: ='Adjusted Statements'!AU26/'Adjusted Statements'!AU6 -> -0.15531106
A35: Cost of materials | B35: ='Adjusted Statements'!AH25/'Adjusted Statements'!AH6 -> -0.48942689 | C35: ='Adjusted Statements'!AI25/'Adjusted Statements'!AI6 -> -0.47144852 | D35: ='Adjusted Statements'!AJ25/'Adjusted Statements'!AJ6 -> -0.47031844 | E35: ='Adjusted Statements'!AK25/'Adjusted Statements'!AK6 -> -0.45588088 | F35: ='Adjusted Statements'!AL25/'Adjusted Statements'!AL6 -> -0.44335741 | G35: ='Adjusted Statements'!AM25/'Adjusted Statements'!AM6 -> -0.42556991 | H35: ='Adjusted Statements'!AN25/'Adjusted Statements'!AN6 -> -0.4081324 | I35: ='Adjusted Statements'!AO25/'Adjusted Statements'!AO6 -> -0.40493303 | ... O35: ='Adjusted Statements'!AU25/'Adjusted Statements'!AU6 -> -0.38669492
A36: Depreciation and amortization | B36: ='Adjusted Statements'!AH27/'Adjusted Statements'!AH6 -> -0.13876309 | C36: ='Adjusted Statements'!AI27/'Adjusted Statements'!AI6 -> -0.13260744 | D36: ='Adjusted Statements'!AJ27/'Adjusted Statements'!AJ6 -> -0.13587636 | E36: ='Adjusted Statements'!AK27/'Adjusted Statements'!AK6 -> -0.13034854 | F36: ='Adjusted Statements'!AL27/'Adjusted Statements'!AL6 -> -0.1377276 | G36: ='Adjusted Statements'!AM27/'Adjusted Statements'!AM6 -> -0.14138424 | H36: ='Adjusted Statements'!AN27/'Adjusted Statements'!AN6 -> -0.13864685 | I36: ='Adjusted Statements'!AO27/'Adjusted Statements'!AO6 -> -0.14222425 | ... O36: ='Adjusted Statements'!AU27/'Adjusted Statements'!AU6 -> -0.11483529
A37: Other operating income/expense | B37: ='Adjusted Statements'!AH28/'Adjusted Statements'!AH6 -> -0.15763162 | C37: ='Adjusted Statements'!AI28/'Adjusted Statements'!AI6 -> -0.13362978 | D37: ='Adjusted Statements'!AJ28/'Adjusted Statements'!AJ6 -> -0.12999525 | E37: ='Adjusted Statements'!AK28/'Adjusted Statements'!AK6 -> -0.1249775 | F37: ='Adjusted Statements'!AL28/'Adjusted Statements'!AL6 -> -0.11683232 | G37: ='Adjusted Statements'!AM28/'Adjusted Statements'!AM6 -> -0.11071486 | H37: ='Adjusted Statements'!AN28/'Adjusted Statements'!AN6 -> -0.11056737 | I37: ='Adjusted Statements'!AO28/'Adjusted Statements'!AO6 -> -0.10621334 | ... O37: ='Adjusted Statements'!AU28/'Adjusted Statements'!AU6 -> -0.091708575
A39: Other key profitability ratios
A40: Gross profit margin | B40: =1+B31 -> 0.50015238 | C40: =1+C31 -> 0.52610255 | D40: =1+D31 -> 0.52702947 | E40: =1+E31 -> 0.54043919 | F40: =1+F31 -> 0.55223725 | G40: =1+G31 -> 0.57042148 | H40: =1+H31 -> 0.58811642 | I40: =1+I31 -> 0.59141115 | ... O40: =1+O31 -> 0.61071401
A41: EBITDA margin | B41: =SUM(B25:B26)-B36 -> 0.15671734 | C41: =SUM(C25:C26)-C36 -> 0.21443578 | D41: =SUM(D25:D26)-D36 -> 0.21788498 | E41: =SUM(E25:E26)-E36 -> 0.24238015 | F41: =SUM(F25:F26)-F36 -> 0.27162228 | G41: =SUM(G25:G26)-G36 -> 0.29982141 | H41: =SUM(H25:H26)-H36 -> 0.31804463 | I41: =SUM(I25:I26)-I36 -> 0.32507273 | ... O41: =SUM(O25:O26)-O36 -> 0.37640722
A43: Asset management ratios
A44: Ratio | B44: 2020 | C44: 2019 | D44: 2018 | E44: 2017 | F44: 2016 | G44: 2015 | H44: 2014 | I44: 2013 | J44: 2012 | K44: 2011 | L44: 2010 | M44: 2009 | N44: 2008 | O44: 2007
A45: Operating working capital/Revenue | B45: =AVERAGE('Adjusted Statements'!AH124,'Adjusted Statements'!AI124)/'Adjusted Statements'!AH96 -> 0.11641733 | C45: =AVERAGE('Adjusted Statements'!AI124,'Adjusted Statements'!AJ124)/'Adjusted Statements'!AI96 -> 0.098972632 | D45: =AVERAGE('Adjusted Statements'!AJ124,'Adjusted Statements'!AK124)/'Adjusted Statements'!AJ96 -> 0.12058222 | E45: =AVERAGE('Adjusted Statements'!AK124,'Adjusted Statements'!AL124)/'Adjusted Statements'!AK96 -> 0.11677766 | F45: =AVERAGE('Adjusted Statements'!AL124,'Adjusted Statements'!AM124)/'Adjusted Statements'!AL96 -> 0.10324198 | G45: =AVERAGE('Adjusted Statements'!AM124,'Adjusted Statements'!AN124)/'Adjusted Statements'!AM96 -> 0.086845699 | H45: =AVERAGE('Adjusted Statements'!AN124,'Adjusted Statements'!AO124)/'Adjusted Statements'!AN96 -> 0.07998022 | I45: =AVERAGE('Adjusted Statements'!AO124,'Adjusted Statements'!AP124)/'Adjusted Statements'!AO96 -> 0.0905285 | ... O45: =AVERAGE('Adjusted Statements'!AU124,'Adjusted Statements'!AV124)/'Adjusted Statements'!AU96 -> 0.06771437
A46: Net non-current operating assets/Revenue | B46: =AVERAGE('Adjusted Statements'!AH131,'Adjusted Statements'!AI131)/'Adjusted Statements'!AH96 -> 0.59317915 | C46: =AVERAGE('Adjusted Statements'!AI131,'Adjusted Statements'!AJ131)/'Adjusted Statements'!AI96 -> 0.50413208 | D46: =AVERAGE('Adjusted Statements'!AJ131,'Adjusted Statements'!AK131)/'Adjusted Statements'!AJ96 -> 0.55398161 | E46: =AVERAGE('Adjusted Statements'!AK131,'Adjusted Statements'!AL131)/'Adjusted Statements'!AK96 -> 0.58449473 | F46: =AVERAGE('Adjusted Statements'!AL131,'Adjusted Statements'!AM131)/'Adjusted Statements'!AL96 -> 0.59941352 | G46: =AVERAGE('Adjusted Statements'!AM131,'Adjusted Statements'!AN131)/'Adjusted Statements'!AM96 -> 0.59522071 | H46: =AVERAGE('Adjusted Statements'!AN131,'Adjusted Statements'!AO131)/'Adjusted Statements'!AN96 -> 0.60507272 | I46: =AVERAGE('Adjusted Statements'!AO131,'Adjusted Statements'!AP131)/'Adjusted Statements'!AO96 -> 0.59549761 | ... O46: =AVERAGE('Adjusted Statements'!AU131,'Adjusted Statements'!AV131)/'Adjusted Statements'!AU96 -> 0.50451309
A47: PP&E/Revenue | B47: =AVERAGE('Adjusted Statements'!AH126,'Adjusted Statements'!AI126)/'Adjusted Statements'!AH96 -> 0.53101031 | C47: =AVERAGE('Adjusted Statements'!AI126,'Adjusted Statements'!AJ126)/'Adjusted Statements'!AI96 -> 0.46317055 | D47: =AVERAGE('Adjusted Statements'!AJ126,'Adjusted Statements'!AK126)/'Adjusted Statements'!AJ96 -> 0.5264626 | E47: =AVERAGE('Adjusted Statements'!AK126,'Adjusted Statements'!AL126)/'Adjusted Statements'!AK96 -> 0.56953753 | F47: =AVERAGE('Adjusted Statements'!AL126,'Adjusted Statements'!AM126)/'Adjusted Statements'!AL96 -> 0.58856142 | G47: =AVERAGE('Adjusted Statements'!AM126,'Adjusted Statements'!AN126)/'Adjusted Statements'!AM96 -> 0.58578805 | H47: =AVERAGE('Adjusted Statements'!AN126,'Adjusted Statements'!AO126)/'Adjusted Statements'!AN96 -> 0.599053 | I47: =AVERAGE('Adjusted Statements'!AO126,'Adjusted Statements'!AP126)/'Adjusted Statements'!AO96 -> 0.59214903 | ... O47: =AVERAGE('Adjusted Statements'!AU126,'Adjusted Statements'!AV126)/'Adjusted Statements'!AU96 -> 0.50732753
A48: Operating working capital turnover | B48: =1/B45 -> 8.5897863 | C48: =1/C45 -> 10.103803 | D48: =1/D45 -> 8.2930963 | E48: =1/E45 -> 8.5632814 | F48: =1/F45 -> 9.6859828 | G48: =1/G45 -> 11.514675 | H48: =1/H45 -> 12.503091 | I48: =1/I45 -> 11.046245 | ... O48: =1/O45 -> 14.767914
A49: Net non-current asset turnover | B49: =1/B46 -> 1.6858313 | C49: =1/C46 -> 1.9836072 | D49: =1/D46 -> 1.8051141 | E49: =1/E46 -> 1.7108794 | F49: =1/F46 -> 1.6682974 | G49: =1/G46 -> 1.6800491 | H49: =1/H46 -> 1.6526939 | I49: =1/I46 -> 1.6792679 | ... O49: =1/O46 -> 1.9821091
A50: PP&E turnover | B50: =1/B47 -> 1.8832026 | C50: =1/C47 -> 2.1590319 | D50: =1/D47 -> 1.8994702 | E50: =1/E47 -> 1.7558105 | F50: =1/F47 -> 1.699058 | G50: =1/G47 -> 1.7071021 | H50: =1/H47 -> 1.6693014 | I50: =1/I47 -> 1.6887641 | ... O50: =1/O47 -> 1.9711132
A51: Trade receivables turnover | B51: ='Adjusted Statements'!AH96/AVERAGE('Adjusted Statements'!AH119,'Adjusted Statements'!AI119) -> 41.724707 | C51: ='Adjusted Statements'!AI96/AVERAGE('Adjusted Statements'!AI119,'Adjusted Statements'!AJ119) -> 38.131553 | D51: ='Adjusted Statements'!AJ96/AVERAGE('Adjusted Statements'!AJ119,'Adjusted Statements'!AK119) -> 36.194736 | E51: ='Adjusted Statements'!AK96/AVERAGE('Adjusted Statements'!AK119,'Adjusted Statements'!AL119) -> 39.301238 | F51: ='Adjusted Statements'!AL96/AVERAGE('Adjusted Statements'!AL119,'Adjusted Statements'!AM119) -> 43.19636 | G51: ='Adjusted Statements'!AM96/AVERAGE('Adjusted Statements'!AM119,'Adjusted Statements'!AN119) -> 47.099219 | H51: ='Adjusted Statements'!AN96/AVERAGE('Adjusted Statements'!AN119,'Adjusted Statements'!AO119) -> 44.758794 | I51: ='Adjusted Statements'!AO96/AVERAGE('Adjusted Statements'!AO119,'Adjusted Statements'!AP119) -> 48.38615 | ... O51: ='Adjusted Statements'!AU96/AVERAGE('Adjusted Statements'!AU119,'Adjusted Statements'!AV119) -> 78.858581
A52: Days’ receivables | B52: =360*(1/B51) -> 8.6279815 | C52: =360*(1/C51) -> 9.4410002 | D52: =360*(1/D51) -> 9.9461977 | E52: =360*(1/E51) -> 9.1600168 | F52: =360*(1/F51) -> 8.3340355 | G52: =360*(1/G51) -> 7.6434389 | H52: =360*(1/H51) -> 8.0431122 | I52: =360*(1/I51) -> 7.4401456 | ... O52: =360*(1/O51) -> 4.5651341
A53: Inventories turnover | B53: =-'Adjusted Statements'!AH25/AVERAGE('Adjusted Statements'!AH120,'Adjusted Statements'!AI120) -> 2.4078809 | C53: =-'Adjusted Statements'!AI25/AVERAGE('Adjusted Statements'!AI120,'Adjusted Statements'!AJ120) -> 2.9051149 | D53: =-'Adjusted Statements'!AJ25/AVERAGE('Adjusted Statements'!AJ120,'Adjusted Statements'!AK120) -> 2.7705682 | E53: =-'Adjusted Statements'!AK25/AVERAGE('Adjusted Statements'!AK120,'Adjusted Statements'!AL120) -> 2.7864434 | F53: =-'Adjusted Statements'!AL25/AVERAGE('Adjusted Statements'!AL120,'Adjusted Statements'!AM120) -> 3.0139839 | G53: =-'Adjusted Statements'!AM25/AVERAGE('Adjusted Statements'!AM120,'Adjusted Statements'!AN120) -> 3.4799259 | H53: =-'Adjusted Statements'!AN25/AVERAGE('Adjusted Statements'!AN120,'Adjusted Statements'!AO120) -> 3.423957 | I53: =-'Adjusted Statements'!AO25/AVERAGE('Adjusted Statements'!AO120,'Adjusted Statements'!AP120) -> 3.2630688 | ... O53: =-'Adjusted Statements'!AU25/AVERAGE('Adjusted Statements'!AU120,'Adjusted Statements'!AV120) -> 3.9892027
A54: Days’ inventories | B54: =360*(1/B53) -> 149.50906 | C54: =360*(1/C53) -> 123.91937 | D54: =360*(1/D53) -> 129.93724 | E54: =360*(1/E53) -> 129.19696 | F54: =360*(1/F53) -> 119.44324 | G54: =360*(1/G53) -> 103.45048 | H54: =360*(1/H53) -> 105.14151 | I54: =360*(1/I53) -> 110.32559 | ... O54: =360*(1/O53) -> 90.243597
A55: Trade payables turnover | B55: =-'Adjusted Statements'!AH25/AVERAGE('Adjusted Statements'!AH122,'Adjusted Statements'!AI122) -> 10.552539 | C55: =-'Adjusted Statements'!AI25/AVERAGE('Adjusted Statements'!AI122,'Adjusted Statements'!AJ122) -> 14.992759 | D55: =-'Adjusted Statements'!AJ25/AVERAGE('Adjusted Statements'!AJ122,'Adjusted Statements'!AK122) -> 14.121299 | E55: =-'Adjusted Statements'!AK25/AVERAGE('Adjusted Statements'!AK122,'Adjusted Statements'!AL122) -> 12.596256 | F55: =-'Adjusted Statements'!AL25/AVERAGE('Adjusted Statements'!AL122,'Adjusted Statements'!AM122) -> 12.855225 | G55: =-'Adjusted Statements'!AM25/AVERAGE('Adjusted Statements'!AM122,'Adjusted Statements'!AN122) -> 13.362674 | H55: =-'Adjusted Statements'!AN25/AVERAGE('Adjusted Statements'!AN122,'Adjusted Statements'!AO122) -> 11.895861 | I55: =-'Adjusted Statements'!AO25/AVERAGE('Adjusted Statements'!AO122,'Adjusted Statements'!AP122) -> 11.436511 | ... O55: =-'Adjusted Statements'!AU25/AVERAGE('Adjusted Statements'!AU122,'Adjusted Statements'!AV122) -> 13.693107
A56: Days’ payables | B56: =360*(1/B55) -> 34.115012 | C56: =360*(1/C55) -> 24.011592 | D56: =360*(1/D55) -> 25.493406 | E56: =360*(1/E55) -> 28.579921 | F56: =360*(1/F55) -> 28.004176 | G56: =360*(1/G55) -> 26.940716 | H56: =360*(1/H55) -> 30.262626 | I56: =360*(1/I55) -> 31.478131 | ... O56: =360*(1/O55) -> 26.290599
A57: Cash conversion cycle | B57: =B54+B52-B56 -> 124.02203 | C57: =C54+C52-C56 -> 109.34878 | D57: =D54+D52-D56 -> 114.39004 | E57: =E54+E52-E56 -> 109.77705 | F57: =F54+F52-F56 -> 99.773098 | G57: =G54+G52-G56 -> 84.153203 | H57: =H54+H52-H56 -> 82.921994 | I57: =I54+I52-I56 -> 86.287607 | ... O57: =O54+O52-O56 -> 68.518131
A59: Liquidity ratios
A60: Ratio | B60: 2020 | C60: 2019 | D60: 2018 | E60: 2017 | F60: 2016 | G60: 2015 | H60: 2014 | I60: 2013 | J60: 2012 | K60: 2011 | L60: 2010 | M60: 2009 | N60: 2008 | O60: 2007
A61: Current ratio | B61: =AVERAGE('Adjusted Statements'!AH44,'Adjusted Statements'!AI44)/AVERAGE('Adjusted Statements'!AH66,'Adjusted Statements'!AI66) -> 1.0701055 | C61: =AVERAGE('Adjusted Statements'!AI44,'Adjusted Statements'!AJ44)/AVERAGE('Adjusted Statements'!AI66,'Adjusted Statements'!AJ66) -> 1.0135024 | D61: =AVERAGE('Adjusted Statements'!AJ44,'Adjusted Statements'!AK44)/AVERAGE('Adjusted Statements'!AJ66,'Adjusted Statements'!AK66) -> 1.0261041 | E61: =AVERAGE('Adjusted Statements'!AK44,'Adjusted Statements'!AL44)/AVERAGE('Adjusted Statements'!AK66,'Adjusted Statements'!AL66) -> 1.0544718 | F61: =AVERAGE('Adjusted Statements'!AL44,'Adjusted Statements'!AM44)/AVERAGE('Adjusted Statements'!AL66,'Adjusted Statements'!AM66) -> 1.1737233 | G61: =AVERAGE('Adjusted Statements'!AM44,'Adjusted Statements'!AN44)/AVERAGE('Adjusted Statements'!AM66,'Adjusted Statements'!AN66) -> 1.2915478 | H61: =AVERAGE('Adjusted Statements'!AN44,'Adjusted Statements'!AO44)/AVERAGE('Adjusted Statements'!AN66,'Adjusted Statements'!AO66) -> 1.3750607 | I61: =AVERAGE('Adjusted Statements'!AO44,'Adjusted Statements'!AP44)/AVERAGE('Adjusted Statements'!AO66,'Adjusted Statements'!AP66) -> 1.5165033 | ... O61: =AVERAGE('Adjusted Statements'!AU44,'Adjusted Statements'!AV44)/AVERAGE('Adjusted Statements'!AU66,'Adjusted Statements'!AV66) -> 2.2680648
A62: Quick ratio | B62: =AVERAGE('Adjusted Statements'!AH41+'Adjusted Statements'!AH43,'Adjusted Statements'!AI41+'Adjusted Statements'!AI43)/AVERAGE('Adjusted Statements'!AH66,'Adjusted Statements'!AI66) -> 0.32056796 | C62: =AVERAGE('Adjusted Statements'!AI41+'Adjusted Statements'!AI43,'Adjusted Statements'!AJ41+'Adjusted Statements'!AJ43)/AVERAGE('Adjusted Statements'!AI66,'Adjusted Statements'!AJ66) -> 0.29798944 | D62: =AVERAGE('Adjusted Statements'!AJ41+'Adjusted Statements'!AJ43,'Adjusted Statements'!AK41+'Adjusted Statements'!AK43)/AVERAGE('Adjusted Statements'!AJ66,'Adjusted Statements'!AK66) -> 0.29019187 | E62: =AVERAGE('Adjusted Statements'!AK41+'Adjusted Statements'!AK43,'Adjusted Statements'!AL41+'Adjusted Statements'!AL43)/AVERAGE('Adjusted Statements'!AK66,'Adjusted Statements'!AL66) -> 0.29449013 | F62: =AVERAGE('Adjusted Statements'!AL41+'Adjusted Statements'!AL43,'Adjusted Statements'!AM41+'Adjusted Statements'!AM43)/AVERAGE('Adjusted Statements'!AL66,'Adjusted Statements'!AM66) -> 0.38814072 | G62: =AVERAGE('Adjusted Statements'!AM41+'Adjusted Statements'!AM43,'Adjusted Statements'!AN41+'Adjusted Statements'!AN43)/AVERAGE('Adjusted Statements'!AM66,'Adjusted Statements'!AN66) -> 0.55326638 | H62: =AVERAGE('Adjusted Statements'!AN41+'Adjusted Statements'!AN43,'Adjusted Statements'!AO41+'Adjusted Statements'!AO43)/AVERAGE('Adjusted Statements'!AN66,'Adjusted Statements'!AO66) -> 0.68808849 | I62: =AVERAGE('Adjusted Statements'!AO41+'Adjusted Statements'!AO43,'Adjusted Statements'!AP41+'Adjusted Statements'!AP43)/AVERAGE('Adjusted Statements'!AO66,'Adjusted Statements'!AP66) -> 0.79100332 | ... O62: =AVERAGE('Adjusted Statements'!AU41+'Adjusted Statements'!AU43,'Adjusted Statements'!AV41+'Adjusted Statements'!AV43)/AVERAGE('Adjusted Statements'!AU66,'Adjusted Statements'!AV66) -> 1.610264
A63: Cash ratio | B63: =AVERAGE('Adjusted Statements'!AH43,'Adjusted Statements'!AI43)/AVERAGE('Adjusted Statements'!AH66,'Adjusted Statements'!AI66) -> 0.24457326 | C63: =AVERAGE('Adjusted Statements'!AI43,'Adjusted Statements'!AJ43)/AVERAGE('Adjusted Statements'!AI66,'Adjusted Statements'!AJ66) -> 0.19724574 | D63: =AVERAGE('Adjusted Statements'!AJ43,'Adjusted Statements'!AK43)/AVERAGE('Adjusted Statements'!AJ66,'Adjusted Statements'!AK66) -> 0.18775151 | E63: =AVERAGE('Adjusted Statements'!AK43,'Adjusted Statements'!AL43)/AVERAGE('Adjusted Statements'!AK66,'Adjusted Statements'!AL66) -> 0.19233893 | F63: =AVERAGE('Adjusted Statements'!AL43,'Adjusted Statements'!AM43)/AVERAGE('Adjusted Statements'!AL66,'Adjusted Statements'!AM66) -> 0.27774297 | G63: =AVERAGE('Adjusted Statements'!AM43,'Adjusted Statements'!AN43)/AVERAGE('Adjusted Statements'!AM66,'Adjusted Statements'!AN66) -> 0.43942007 | H63: =AVERAGE('Adjusted Statements'!AN43,'Adjusted Statements'!AO43)/AVERAGE('Adjusted Statements'!AN66,'Adjusted Statements'!AO66) -> 0.57365232 | I63: =AVERAGE('Adjusted Statements'!AO43,'Adjusted Statements'!AP43)/AVERAGE('Adjusted Statements'!AO66,'Adjusted Statements'!AP66) -> 0.68507374 | ... O63: =AVERAGE('Adjusted Statements'!AU43,'Adjusted Statements'!AV43)/AVERAGE('Adjusted Statements'!AU66,'Adjusted Statements'!AV66) -> 1.5333063
A64: Operating cash flow ratio | B64: ='Adjusted Statements'!AH80/AVERAGE('Adjusted Statements'!AH66,'Adjusted Statements'!AI66) -> 0.45209738 | C64: ='Adjusted Statements'!AI80/AVERAGE('Adjusted Statements'!AI66,'Adjusted Statements'!AJ66) -> 0.82052165 | D64: ='Adjusted Statements'!AJ80/AVERAGE('Adjusted Statements'!AJ66,'Adjusted Statements'!AK66) -> 0.72556892 | E64: ='Adjusted Statements'!AK80/AVERAGE('Adjusted Statements'!AK66,'Adjusted Statements'!AL66) -> 0.8056173 | F64: ='Adjusted Statements'!AL80/AVERAGE('Adjusted Statements'!AL66,'Adjusted Statements'!AM66) -> 1.0852762 | G64: ='Adjusted Statements'!AM80/AVERAGE('Adjusted Statements'!AM66,'Adjusted Statements'!AN66) -> 1.3054115 | H64: ='Adjusted Statements'!AN80/AVERAGE('Adjusted Statements'!AN66,'Adjusted Statements'!AO66) -> 1.3790106 | I64: ='Adjusted Statements'!AO80/AVERAGE('Adjusted Statements'!AO66,'Adjusted Statements'!AP66) -> 1.5282285 | ... O64: ='Adjusted Statements'!AU80/AVERAGE('Adjusted Statements'!AU66,'Adjusted Statements'!AV66) -> 1.7581784
A66: Solvency ratios
A67: Ratio | B67: 2020 | C67: 2019 | D67: 2018 | E67: 2017 | F67: 2016 | G67: 2015 | H67: 2014 | I67: 2013 | J67: 2012 | K67: 2011 | L67: 2010 | M67: 2009 | N67: 2008 | O67: 2007
A68: Liabilities-to-equity | B68: =AVERAGE('Adjusted Statements'!AH61+'Adjusted Statements'!AH66,'Adjusted Statements'!AI61+'Adjusted Statements'!AI66)/AVERAGE('Adjusted Statements'!AH148,'Adjusted Statements'!AI148) -> 2.2304801 | C68: =AVERAGE('Adjusted Statements'!AI61+'Adjusted Statements'!AI66,'Adjusted Statements'!AJ61+'Adjusted Statements'!AJ66)/AVERAGE('Adjusted Statements'!AI148,'Adjusted Statements'!AJ148) -> 2.2057737 | D68: =AVERAGE('Adjusted Statements'!AJ61+'Adjusted Statements'!AJ66,'Adjusted Statements'!AK61+'Adjusted Statements'!AK66)/AVERAGE('Adjusted Statements'!AJ148,'Adjusted Statements'!AK148) -> 2.0740194 | E68: =AVERAGE('Adjusted Statements'!AK61+'Adjusted Statements'!AK66,'Adjusted Statements'!AL61+'Adjusted Statements'!AL66)/AVERAGE('Adjusted Statements'!AK148,'Adjusted Statements'!AL148) -> 1.920467 | F68: =AVERAGE('Adjusted Statements'!AL61+'Adjusted Statements'!AL66,'Adjusted Statements'!AM61+'Adjusted Statements'!AM66)/AVERAGE('Adjusted Statements'!AL148,'Adjusted Statements'!AM148) -> 1.8316123 | G68: =AVERAGE('Adjusted Statements'!AM61+'Adjusted Statements'!AM66,'Adjusted Statements'!AN61+'Adjusted Statements'!AN66)/AVERAGE('Adjusted Statements'!AM148,'Adjusted Statements'!AN148) -> 1.8486239 | H68: =AVERAGE('Adjusted Statements'!AN61+'Adjusted Statements'!AN66,'Adjusted Statements'!AO61+'Adjusted Statements'!AO66)/AVERAGE('Adjusted Statements'!AN148,'Adjusted Statements'!AO148) -> 1.8145016 | I68: =AVERAGE('Adjusted Statements'!AO61+'Adjusted Statements'!AO66,'Adjusted Statements'!AP61+'Adjusted Statements'!AP66)/AVERAGE('Adjusted Statements'!AO148,'Adjusted Statements'!AP148) -> 1.645395 | ... O68: =AVERAGE('Adjusted Statements'!AU61+'Adjusted Statements'!AU66,'Adjusted Statements'!AV61+'Adjusted Statements'!AV66)/AVERAGE('Adjusted Statements'!AU148,'Adjusted Statements'!AV148) -> 1.3183486
A69: Debt-to-equity | B69: =AVERAGE('Adjusted Statements'!AH143,'Adjusted Statements'!AI143)/AVERAGE('Adjusted Statements'!AH148,'Adjusted Statements'!AI148) -> 1.4759139 | C69: =AVERAGE('Adjusted Statements'!AI143,'Adjusted Statements'!AJ143)/AVERAGE('Adjusted Statements'!AI148,'Adjusted Statements'!AJ148) -> 1.4686202 | D69: =AVERAGE('Adjusted Statements'!AJ143,'Adjusted Statements'!AK143)/AVERAGE('Adjusted Statements'!AJ148,'Adjusted Statements'!AK148) -> 1.4296541 | E69: =AVERAGE('Adjusted Statements'!AK143,'Adjusted Statements'!AL143)/AVERAGE('Adjusted Statements'!AK148,'Adjusted Statements'!AL148) -> 1.3362539 | F69: =AVERAGE('Adjusted Statements'!AL143,'Adjusted Statements'!AM143)/AVERAGE('Adjusted Statements'!AL148,'Adjusted Statements'!AM148) -> 1.3136009 | G69: =AVERAGE('Adjusted Statements'!AM143,'Adjusted Statements'!AN143)/AVERAGE('Adjusted Statements'!AM148,'Adjusted Statements'!AN148) -> 1.3841834 | H69: =AVERAGE('Adjusted Statements'!AN143,'Adjusted Statements'!AO143)/AVERAGE('Adjusted Statements'!AN148,'Adjusted Statements'!AO148) -> 1.362981 | I69: =AVERAGE('Adjusted Statements'!AO143,'Adjusted Statements'!AP143)/AVERAGE('Adjusted Statements'!AO148,'Adjusted Statements'!AP148) -> 1.2403795 | ... O69: =AVERAGE('Adjusted Statements'!AU143,'Adjusted Statements'!AV143)/AVERAGE('Adjusted Statements'!AU148,'Adjusted Statements'!AV148) -> 1.043078
A70: Debt-to-invested capital | B70: =AVERAGE('Adjusted Statements'!AH143,'Adjusted Statements'!AI143)/AVERAGE('Adjusted Statements'!AH149,'Adjusted Statements'!AI149) -> 0.59610874 | C70: =AVERAGE('Adjusted Statements'!AI143,'Adjusted Statements'!AJ143)/AVERAGE('Adjusted Statements'!AI149,'Adjusted Statements'!AJ149) -> 0.59491541 | D70: =AVERAGE('Adjusted Statements'!AJ143,'Adjusted Statements'!AK143)/AVERAGE('Adjusted Statements'!AJ149,'Adjusted Statements'!AK149) -> 0.58841878 | E70: =AVERAGE('Adjusted Statements'!AK143,'Adjusted Statements'!AL143)/AVERAGE('Adjusted Statements'!AK149,'Adjusted Statements'!AL149) -> 0.57196432 | F70: =AVERAGE('Adjusted Statements'!AL143,'Adjusted Statements'!AM143)/AVERAGE('Adjusted Statements'!AL149,'Adjusted Statements'!AM149) -> 0.56777333 | G70: =AVERAGE('Adjusted Statements'!AM143,'Adjusted Statements'!AN143)/AVERAGE('Adjusted Statements'!AM149,'Adjusted Statements'!AN149) -> 0.58056919 | H70: =AVERAGE('Adjusted Statements'!AN143,'Adjusted Statements'!AO143)/AVERAGE('Adjusted Statements'!AN149,'Adjusted Statements'!AO149) -> 0.57680574 | I70: =AVERAGE('Adjusted Statements'!AO143,'Adjusted Statements'!AP143)/AVERAGE('Adjusted Statements'!AO149,'Adjusted Statements'!AP149) -> 0.55364705 | ... O70: =AVERAGE('Adjusted Statements'!AU143,'Adjusted Statements'!AV143)/AVERAGE('Adjusted Statements'!AU149,'Adjusted Statements'!AV149) -> 0.51054242
A71: Interest coverage (earnings based) | B71: =('Adjusted Statements'!AH15-'Adjusted Statements'!AH14-'Adjusted Statements'!AH12)/(-'Adjusted Statements'!AH12) -> 2.5712098 | C71: =('Adjusted Statements'!AI15-'Adjusted Statements'!AI14-'Adjusted Statements'!AI12)/(-'Adjusted Statements'!AI12) -> 11.508444 | D71: =('Adjusted Statements'!AJ15-'Adjusted Statements'!AJ14-'Adjusted Statements'!AJ12)/(-'Adjusted Statements'!AJ12) -> 10.679909 | E71: =('Adjusted Statements'!AK15-'Adjusted Statements'!AK14-'Adjusted Statements'!AK12)/(-'Adjusted Statements'!AK12) -> 14.023778 | F71: =('Adjusted Statements'!AL15-'Adjusted Statements'!AL14-'Adjusted Statements'!AL12)/(-'Adjusted Statements'!AL12) -> 15.103032 | G71: =('Adjusted Statements'!AM15-'Adjusted Statements'!AM14-'Adjusted Statements'!AM12)/(-'Adjusted Statements'!AM12) -> 20.278107 | H71: =('Adjusted Statements'!AN15-'Adjusted Statements'!AN14-'Adjusted Statements'!AN12)/(-'Adjusted Statements'!AN12) -> 21.402103 | I71: =('Adjusted Statements'!AO15-'Adjusted Statements'!AO14-'Adjusted Statements'!AO12)/(-'Adjusted Statements'!AO12) -> 23.95373 | ... O71: =('Adjusted Statements'!AU15-'Adjusted Statements'!AU14-'Adjusted Statements'!AU12)/(-'Adjusted Statements'!AU12) -> 15.488544
A72: Interest coverage (cash flow based) | B72: =('Adjusted Statements'!AH80-B73)/-B74 -> 23.266217 | C72: =('Adjusted Statements'!AI80-C73)/-C74 -> 32.27575 | D72: =('Adjusted Statements'!AJ80-D73)/-D74 -> 27.401691 | E72: =('Adjusted Statements'!AK80-E73)/-E74 -> 28.906221 | F72: =('Adjusted Statements'!AL80-F73)/-F74 -> 28.292893 | G72: =('Adjusted Statements'!AM80-G73)/-G74 -> 36.128311 | H72: =('Adjusted Statements'!AN80-H73)/-H74 -> 36.823664 | I72: =('Adjusted Statements'!AO80-I73)/-I74 -> 42.177045 | ... O72: =('Adjusted Statements'!AU80-O73)/-O74 -> 21.354563
A73: Taxes paid | B73: ='Adjusted Statements'!AH74-(1-'Adjusted Statements'!AH104)*('Adjusted Statements'!AH87/'Adjusted Statements'!AH104) -> -3719 | C73: ='Adjusted Statements'!AI74-(1-'Adjusted Statements'!AI104)*('Adjusted Statements'!AI87/'Adjusted Statements'!AI104) -> -3700 | D73: ='Adjusted Statements'!AJ74-(1-'Adjusted Statements'!AJ104)*('Adjusted Statements'!AJ87/'Adjusted Statements'!AJ104) -> -3098 | E73: ='Adjusted Statements'!AK74-(1-'Adjusted Statements'!AK104)*('Adjusted Statements'!AK87/'Adjusted Statements'!AK104) -> -6051 | F73: ='Adjusted Statements'!AL74-(1-'Adjusted Statements'!AL104)*('Adjusted Statements'!AL87/'Adjusted Statements'!AL104) -> -4470 | G73: ='Adjusted Statements'!AM74-(1-'Adjusted Statements'!AM104)*('Adjusted Statements'!AM87/'Adjusted Statements'!AM104) -> -7022 | H73: ='Adjusted Statements'!AN74-(1-'Adjusted Statements'!AN104)*('Adjusted Statements'!AN87/'Adjusted Statements'!AN104) -> -5971 | I73: ='Adjusted Statements'!AO74-(1-'Adjusted Statements'!AO104)*('Adjusted Statements'!AO87/'Adjusted Statements'!AO104) -> -3059 | ... O73: ='Adjusted Statements'!AU74-(1-'Adjusted Statements'!AU104)*('Adjusted Statements'!AU87/'Adjusted Statements'!AU104) -> -5557
A74: Interest paid | B74: ='Adjusted Statements'!AH87/'Adjusted Statements'!AH104 -> -1306 | C74: ='Adjusted Statements'!AI87/'Adjusted Statements'!AI104 -> -1654.9549 | D74: ='Adjusted Statements'!AJ87/'Adjusted Statements'!AJ104 -> -1615.6144 | E74: ='Adjusted Statements'!AK87/'Adjusted Statements'!AK104 -> -1597.7699 | F74: ='Adjusted Statements'!AL87/'Adjusted Statements'!AL104 -> -1704.5271 | G74: ='Adjusted Statements'!AM87/'Adjusted Statements'!AM104 -> -1413.1055 | H74: ='Adjusted Statements'!AN87/'Adjusted Statements'!AN104 -> -1269.2319 | I74: ='Adjusted Statements'!AO87/'Adjusted Statements'!AO104 -> -981.36557 | ... O74: ='Adjusted Statements'!AU87/'Adjusted Statements'!AU104 -> -1323.1143
A76: Sustainable growth rate
A77: Ratio | B77: 2020 | C77: 2019 | D77: 2018 | E77: 2017 | F77: 2016 | G77: 2015 | H77: 2014 | I77: 2013 | J77: 2012 | K77: 2011 | L77: 2010 | M77: 2009 | N77: 2008 | O77: 2007
A78: ROE | B78: =B3 -> 0.022257637 | C78: =C3 -> 0.23254768 | D78: =D3 -> 0.21397103 | E78: =E3 -> 0.26761693 | F78: =F3 -> 0.31246175 | G78: =G3 -> 0.38133297 | H78: =H3 -> 0.41271022 | I78: =I3 -> 0.38507908 | ... O78: =O3 -> 0.45390166
A79: Dividend payout ratio | B79: =-'Adjusted Statements'!AH91/'Adjusted Statements'!AH114 -> 0 | C79: =-'Adjusted Statements'!AI91/'Adjusted Statements'!AI114 -> 1.2004017 | D79: =-'Adjusted Statements'!AJ91/'Adjusted Statements'!AJ114 -> 1.2754505 | E79: =-'Adjusted Statements'!AK91/'Adjusted Statements'!AK114 -> 0.9970959 | F79: =-'Adjusted Statements'!AL91/'Adjusted Statements'!AL114 -> 0.8659047 | G79: =-'Adjusted Statements'!AM91/'Adjusted Statements'!AM114 -> 0.77217916 | H79: =-'Adjusted Statements'!AN91/'Adjusted Statements'!AN114 -> 0.78709451 | I79: =-'Adjusted Statements'!AO91/'Adjusted Statements'!AO114 -> 0.9166861 | ... O79: =-'Adjusted Statements'!AU91/'Adjusted Statements'!AU114 -> 0.70025022
A80: Sustainable growth rate | B80: =(1-B79)*B78 -> 0.022257637 | C80: =(1-C79)*C78 -> -0.046602949 | D80: =(1-D79)*D78 -> -0.058938432 | E80: =(1-E79)*E78 -> 0.00077718708 | F80: =(1-F79)*F78 -> 0.041899652 | G80: =(1-G79)*G78 -> 0.086875599 | H80: =(1-H79)*H78 -> 0.08786827 | I80: =(1-I79)*I78 -> 0.03208244 | ... O80: =(1-O79)*O78 -> 0.13605692
